Workbook

Sheet 表紙
A1: システム名 | K1: システム種別 | W1: DB定義書 | AP1: 作成者 | AT1: 作成日 | AY1: 更新者 | BC1: 更新日 | BH1: 版数
A2: 現金専用簡易セルフPOS | AP2: きよはら | AT2: 44652 | AY2: =LOOKUP(2,1/(改廃履歴!H11:H30000<>""),改廃履歴!H11:H30000) -> Thanh Nguyên | BC2: =LOOKUP(2,1/(改廃履歴!B11:B30000<>""),改廃履歴!B11:B30000) -> 45285 | BH2: =LOOKUP(2,1/(改廃履歴!O11:O30000<>""),改廃履歴!O11:O30000) -> 0.2
A4: 機能カテゴリ | H4: 共通 | U4: 項目 | AP4: 表紙
L16: 現金専用簡易セルフPOS 基本設計書
L24: =K2&"/"&H4&"/"&Z4 -> /共通/
Q44: 承認日 | AA44: 承認者 | AQ44: 版数

Sheet 改廃履歴
A1: システム名 | K1: システム種別 | W1: =IF(表紙!W1="","",表紙!W1) -> DB定義書 | AP1: 作成者 | AT1: 作成日 | AY1: 更新者 | BC1: 更新日 | BH1: 版数
A2: =IF(表紙!A2="","",表紙!A2) -> 現金専用簡易セルフPOS | K2: =IF(表紙!K2="","",表紙!K2) | AP2: =IF(表紙!AP2="","",表紙!AP2) -> きよはら | AT2: =IF(表紙!AT2="","",表紙!AT2) -> 44652 | AY2: =IF(表紙!AY2="","",表紙!AY2) -> Thanh Nguyên | BC2: =IF(表紙!BC2="","",表紙!BC2) -> 45285 | BH2: =IF(表紙!BH2="","",表紙!BH2) -> 0.2
A4: 機能カテゴリ | H4: =IF(表紙!H4="","",表紙!H4) -> 共通 | U4: 項目 | Z4: =IF(表紙!Z4="","",表紙!Z4) | AP4: 改廃履歴
B8: ■改廃履歴
B10: 更新日付 | H10: 更新者 | O10: 版数 | S10: 変更内容 | AX10: 承認日付 | BD10: 承認者
B11: 44652 | H11: きよはら | O11: 0.1 | S11: 新規作成
B13: 45285 | H13: Thanh Nguyên | O13: 0.2 | S13: プリセットメニューマスタに、プリセットボタンレイアウト名称を追加

Sheet DB一覧
A1: システム名 | K1: システム種別 | W1: =IF(表紙!W1="","",表紙!W1) -> DB定義書 | AP1: 作成者 | AT1: 作成日 | AY1: 更新者 | BC1: 更新日 | BH1: 版数
A2: =IF(表紙!A2="","",表紙!A2) -> 現金専用簡易セルフPOS | K2: =IF(表紙!K2="","",表紙!K2) | AP2: =IF(表紙!AP2="","",表紙!AP2) -> きよはら | AT2: =IF(表紙!AT2="","",表紙!AT2) -> 44652 | AY2: =IF(表紙!AY2="","",表紙!AY2) -> Thanh Nguyên | BC2: =IF(表紙!BC2="","",表紙!BC2) -> 45285 | BH2: =IF(表紙!BH2="","",表紙!BH2) -> 0.2
A4: 機能カテゴリ | H4: =IF(表紙!H4="","",表紙!H4) -> 共通 | U4: 項目 | Z4: =IF(表紙!Z4="","",表紙!Z4) | AP4: Sheet7
B7: ID | D7: 区分 | M7: 論理テーブル名 | AB7: 物理テーブル名 | AW7: 備考
D8: 2_7_設定機能 | M8: 機器接続情報 | AB8: Device_Connection_Information

Sheet ER
A1: システム名 | K1: システム種別 | W1: =IF(表紙!W1="","",表紙!W1) -> DB定義書 | AP1: 作成者 | AT1: 作成日 | AY1: 更新者 | BC1: 更新日 | BH1: 版数
A2: =IF(表紙!A2="","",表紙!A2) -> 現金専用簡易セルフPOS | K2: =IF(表紙!K2="","",表紙!K2) | AP2: =IF(表紙!AP2="","",表紙!AP2) -> きよはら | AT2: =IF(表紙!AT2="","",表紙!AT2) -> 44652 | AY2: =IF(表紙!AY2="","",表紙!AY2) -> Thanh Nguyên | BC2: =IF(表紙!BC2="","",表紙!BC2) -> 45285 | BH2: =IF(表紙!BH2="","",表紙!BH2) -> 0.2
A4: 機能カテゴリ | H4: =IF(表紙!H4="","",表紙!H4) -> 共通 | U4: 項目 | Z4: =IF(表紙!Z4="","",表紙!Z4) | AP4: ER

Sheet POSメニュー
A1: システム名 | K1: システム種別 | W1: =IF(表紙!W1="","",表紙!W1) -> DB定義書 | AP1: 作成者 | AT1: 作成日 | AY1: 更新者 | BC1: 更新日 | BH1: 版数
A2: =IF(表紙!A2="","",表紙!A2) -> 現金専用簡易セルフPOS | K2: =IF(表紙!K2="","",表紙!K2) | AP2: =IF(表紙!AP2="","",表紙!AP2) -> きよはら | AT2: =IF(表紙!AT2="","",表紙!AT2) -> 44652 | AY2: =IF(表紙!AY2="","",表紙!AY2) -> Thanh Nguyên | BC2: =IF(表紙!BC2="","",表紙!BC2) -> 45285 | BH2: =IF(表紙!BH2="","",表紙!BH2) -> 0.2
A4: 機能カテゴリ | H4: =IF(表紙!H4="","",表紙!H4) -> 共通 | U4: 項目 | Z4: =IF(表紙!Z4="","",表紙!Z4) | AP4: テンプレート
B7: ■テーブル情報
B8: スキーマ名 | Y8: RDBMS名
B9: 論理名 | G9: 機器接続情報 | Y9: バージョン
B10: 物理名
B11: 備考
B19: ■カラム情報 | BM19: ="DROP TABLE IF EXISTS `"&$G$8&"`.`"&$G$10&"`;" -> DROP TABLE IF EXISTS ``.``;
B20: No. | D20: 論理名 | R20: 物理名 | AC20: データ型 | AH20: PK | AJ20: Not Null | AM20: デフォルト | AT20: 備考 | BM20: ="CREATE TABLE `"&$G$8&"`.`"&$G$10&"` (" -> CREATE TABLE ``.`` ( | BN20: ="CREATE TABLE `TMP`.`"&G10&"` (" -> CREATE TABLE `TMP`.`` (
B21: 1 | D21: レコードID | R21: RECORD_ID | AC21: BIGINT | AH21: 1 | AJ21: Y | AM21: 自動追加 | BM21: ="`"&R21&"` "&AC21&" "&IF(AJ21="Y","NOT NULL","")&" AUTO_INCREMENT COMMENT '"&D21&IF(AT21="","","/"&AT21)&"'" -> `RECORD_ID` BIGINT NOT NULL AUTO_INCREMENT COMMENT 'レコードID' | BO21: =",A.`"&R21&"` = B.`"&R21&"`" -> ,A.`RECORD_ID` = B.`RECORD_ID` | BP21: =",`"&R21&"`" -> ,`RECORD_ID`
B22: 2 | D22: レコード作成日付 | R22: RECORD_CREATE_DATE | AC22: TIMESTAMP | AJ22: Y | AM22: CURRENT_DATE | BM22: =",`"&R22&"` "&AC22&" "&IF(AJ22="Y","NOT NULL","")&" COMMENT '"&D22&IF(AT22="","","/"&AT22)&"'" -> ,`RECORD_CREATE_DATE` TIMESTAMP NOT NULL COMMENT 'レコード作成日付' | BO22: =",A.`"&R22&"` = B.`"&R22&"`" -> ,A.`RECORD_CREATE_DATE` = B.`RECORD_CREATE_DATE` | BP22: =",`"&R22&"`" -> ,`RECORD_CREATE_DATE`
B23: 3 | D23: レコード作成時間 | R23: RECORD_CREATE_TIME | AC23: BIGINT | AJ23: Y | AM23: CURRENT_TIME | BM23: =",`"&R23&"` "&AC23&" "&IF(AJ23="Y","NOT NULL","")&" COMMENT '"&D23&IF(AT23="","","/"&AT23)&"'" -> ,`RECORD_CREATE_TIME` BIGINT NOT NULL COMMENT 'レコード作成時間' | BO23: =",A.`"&R23&"` = B.`"&R23&"`" -> ,A.`RECORD_CREATE_TIME` = B.`RECORD_CREATE_TIME` | BP23: =",`"&R23&"`" -> ,`RECORD_CREATE_TIME`
B24: 4 | D24: レコード更新日付 | R24: RECORD_UPDATE_DATE | AC24: TIMESTAMP | AJ24: Y | AM24: CURRENT_DATE | AT24: トリガーにより更新 | BM24: =",`"&R24&"` "&AC24&" "&IF(AJ24="Y","NOT NULL","")&" COMMENT '"&D24&IF(AT24="","","/"&AT24)&"'" -> ,`RECORD_UPDATE_DATE` TIMESTAMP NOT NULL COMMENT 'レコード更新日付/トリガーにより更新' | BO24: =",A.`"&R24&"` = B.`"&R24&"`" -> ,A.`RECORD_UPDATE_DATE` = B.`RECORD_UPDATE_DATE` | BP24: =",`"&R24&"`" -> ,`RECORD_UPDATE_DATE`
B25: 5 | D25: レコード更新時間 | R25: RECORD_UPDATE_TIME | AC25: BIGINT | AJ25: Y | AM25: CURRENT_TIME | AT25: トリガーにより更新 | BM25: =",`"&R25&"` "&AC25&" "&IF(AJ25="Y","NOT NULL","")&" COMMENT '"&D25&IF(AT25="","","/"&AT25)&"'" -> ,`RECORD_UPDATE_TIME` BIGINT NOT NULL COMMENT 'レコード更新時間/トリガーにより更新' | BO25: =",A.`"&R25&"` = B.`"&R25&"`" -> ,A.`RECORD_UPDATE_TIME` = B.`RECORD_UPDATE_TIME` | BP25: =",`"&R25&"`" -> ,`RECORD_UPDATE_TIME`
B26: 6 | D26: レコード無効フラグ | R26: RECORD_VOID_FLAG | AC26: BOOL | AJ26: Y | AM26: "" | AT26: true:有効 / false:無効 | BM26: =",`"&R26&"` "&AC26&" "&IF(AJ26="Y","NOT NULL","")&" COMMENT '"&D26&IF(AT26="","","/"&AT26)&"'" -> ,`RECORD_VOID_FLAG` BOOL NOT NULL COMMENT 'レコード無効フラグ/true:有効 / false:無効' | BN26: `CLASS` VARCHAR ( 1 ) NOT NULL COMMENT '処理区分', | BO26: =",A.`"&R26&"` = B.`"&R26&"`" -> ,A.`RECORD_VOID_FLAG` = B.`RECORD_VOID_FLAG` | BP26: =",`"&R26&"`" -> ,`RECORD_VOID_FLAG`
B27: 7 | D27: ボタン番号 | BM27: =",`"&R27&"` "&AC27&" "&IF(AJ27="Y","NOT NULL","")&" COMMENT '"&D27&IF(AT27="","","/"&AT27)&"'" -> ,`` COMMENT 'ボタン番号' | BN27: =",`"&R27&"` "&AC27&" "&IF(AJ27="Y","NOT NULL","")&" COMMENT '"&D27&"'" -> ,`` COMMENT 'ボタン番号' | BO27: =",A.`"&R27&"` = B.`"&R27&"`" -> ,A.`` = B.`` | BP27: =",`"&R27&"`" -> ,``
B28: 8 | D28: ラベル | BM28: =",`"&R28&"` "&AC28&" "&IF(AJ28="Y","NOT NULL","")&" COMMENT '"&D28&IF(AT28="","","/"&AT28)&"'" -> ,`` COMMENT 'ラベル' | BN28: =",`"&R28&"` "&AC28&" "&IF(AJ28="Y","NOT NULL","")&" COMMENT '"&D28&"'" -> ,`` COMMENT 'ラベル' | BO28: =",A.`"&R28&"` = B.`"&R28&"`" -> ,A.`` = B.`` | BP28: =",`"&R28&"`" -> ,``
B29: 9 | D29: 遷移先 | BM29: =",`"&R29&"` "&AC29&" "&IF(AJ29="Y","NOT NULL","")&" COMMENT '"&D29&IF(AT29="","","/"&AT29)&"'" -> ,`` COMMENT '遷移先' | BN29: =",`"&R29&"` "&AC29&" "&IF(AJ29="Y","NOT NULL","")&" COMMENT '"&D29&"'" -> ,`` COMMENT '遷移先' | BO29: =",A.`"&R29&"` = B.`"&R29&"`" -> ,A.`` = B.`` | BP29: =",`"&R29&"`" -> ,``
B30: 10 | D30: 活性化 | AT30: 1：開設時活性 / 2：非開設時活性 /3：常に活性 / 99：常に非活性 | BM30: =",`"&R30&"` "&AC30&" "&IF(AJ30="Y","NOT NULL","")&" COMMENT '"&D30&IF(AT30="","","/"&AT30)&"'" -> ,`` COMMENT '活性化/1：開設時活性 / 2：非開設時活性 /3：常に活性 / 99：常に非活性' | BN30: =",`"&R30&"` "&AC30&" "&IF(AJ30="Y","NOT NULL","")&" COMMENT '"&D30&"'" -> ,`` COMMENT '活性化' | BO30: =",A.`"&R30&"` = B.`"&R30&"`" -> ,A.`` = B.`` | BP30: =",`"&R30&"`" -> ,``
B31: 11 | BM31: =",`"&R31&"` "&AC31&" "&IF(AJ31="Y","NOT NULL","")&" COMMENT '"&D31&IF(AT31="","","/"&AT31)&"'" -> ,`` COMMENT '' | BN31: =",`"&R31&"` "&AC31&" "&IF(AJ31="Y","NOT NULL","")&" COMMENT '"&D31&"'" -> ,`` COMMENT '' | BO31: =",A.`"&R31&"` = B.`"&R31&"`" -> ,A.`` = B.`` | BP31: =",`"&R31&"`" -> ,``
B32: 12 | BM32: =",`"&R32&"` "&AC32&" "&IF(AJ32="Y","NOT NULL","")&" COMMENT '"&D32&IF(AT32="","","/"&AT32)&"'" -> ,`` COMMENT '' | BN32: =",`"&R32&"` "&AC32&" "&IF(AJ32="Y","NOT NULL","")&" COMMENT '"&D32&"'" -> ,`` COMMENT '' | BO32: =",A.`"&R32&"` = B.`"&R32&"`" -> ,A.`` = B.`` | BP32: =",`"&R32&"`" -> ,``
B33: 13 | BM33: =",`"&R33&"` "&AC33&" "&IF(AJ33="Y","NOT NULL","")&" COMMENT '"&D33&IF(AT33="","","/"&AT33)&"'" -> ,`` COMMENT '' | BN33: =",`"&R33&"` "&AC33&" "&IF(AJ33="Y","NOT NULL","")&" COMMENT '"&D33&"'" -> ,`` COMMENT '' | BO33: =",A.`"&R33&"` = B.`"&R33&"`" -> ,A.`` = B.`` | BP33: =",`"&R33&"`" -> ,``
BM34: =",`"&R34&"` "&AC34&" "&IF(AJ34="Y","NOT NULL","")&" COMMENT '"&D34&IF(AT34="","","/"&AT34)&"'" -> ,`` COMMENT '' | BN34: =",`"&R34&"` "&AC34&" "&IF(AJ34="Y","NOT NULL","")&" COMMENT '"&D34&"'" -> ,`` COMMENT '' | BO34: =",A.`"&R34&"` = B.`"&R34&"`" -> ,A.`` = B.`` | BP34: =",`"&R34&"`" -> ,``
BM35: =",`"&R35&"` "&AC35&" "&IF(AJ35="Y","NOT NULL","")&" COMMENT '"&D35&IF(AT35="","","/"&AT35)&"'" -> ,`` COMMENT '' | BN35: =",`"&R35&"` "&AC35&" "&IF(AJ35="Y","NOT NULL","")&" COMMENT '"&D35&"'" -> ,`` COMMENT '' | BO35: =",A.`"&R35&"` = B.`"&R35&"`" -> ,A.`` = B.`` | BP35: =",`"&R35&"`" -> ,``
B36: ■インデックス情報 | BM36: =",`"&R36&"` "&AC36&" "&IF(AJ36="Y","NOT NULL","")&" COMMENT '"&D36&IF(AT36="","","/"&AT36)&"'" -> ,`` COMMENT '' | BN36: =",`"&R36&"` "&AC36&" "&IF(AJ36="Y","NOT NULL","")&" COMMENT '"&D36&"'" -> ,`` COMMENT '' | BO36: =",A.`"&R36&"` = B.`"&R36&"`" -> ,A.`` = B.`` | BP36: =",`"&R36&"`" -> ,``
B37: No. | D37: Index名 | R37: カラム一覧 | AL37: プライマリキー | AP37: ユニーク | AT37: 備考 | BM37: =",`"&R37&"` "&AC37&" "&IF(AJ37="Y","NOT NULL","")&" COMMENT '"&D37&IF(AT37="","","/"&AT37)&"'" -> ,`カラム一覧` COMMENT 'Index名/備考' | BN37: =",`"&R37&"` "&AC37&" "&IF(AJ37="Y","NOT NULL","")&" COMMENT '"&D37&"'" -> ,`カラム一覧` COMMENT 'Index名' | BO37: =",A.`"&R37&"` = B.`"&R37&"`" -> ,A.`カラム一覧` = B.`カラム一覧` | BP37: =",`"&R37&"`" -> ,`カラム一覧`
B38: 1 | D38: PRIMARY | R38: =IF(_xlfn.XLOOKUP(1,AH:AH,R:R,"",0)="","","`"&_xlfn.XLOOKUP(1,AH:AH,R:R,"",0)&"`")&IF(_xlfn.XLOOKUP(2,AH:AH,R:R,"",0)="","",",`"&_xlfn.XLOOKUP(2,AH:AH,R:R,"",0)&"`")&IF(_xlfn.XLOOKUP(3,AH:AH,R:R,"",0)="","",",`"&_xlfn.XLOOKUP(3,AH:AH,R:R,"",0)&"`")&IF(_xlfn.XLOOKUP(4,AH:AH,R:R,"",0)="","",",`"&_xlfn.XLOOKUP(4,AH:AH,R:R,"",0)&"`")&IF(_xlfn.XLOOKUP(5,AH:AH,R:R,"",0)="","",",`"&_xlfn.XLOOKUP(5,AH:AH,R:R,"",0)&"`")&IF(_xlfn.XLOOKUP(6,AH:AH,R:R,"",0)="","",",`"&_xlfn.XLOOKUP(6,AH:AH,R:R,"",0)&"`")&IF(_xlfn.XLOOKUP(7,AH:AH,R:R,"",0)="","",",`"&_xlfn.XLOOKUP(7,AH:AH,R:R,"",0)&"`")&IF(_xlfn.XLOOKUP(8,AH:AH,R:R,"",0)="","",",`"&_xlfn.XLOOKUP(8,AH:AH,R:R,"",0)&"`") -> `RECORD_ID` | AL38: Y | AP38: Y | BM38: =" , PRIMARY KEY ("&IF(_xlfn.XLOOKUP(1,AH:AH,R:R,"",0)="","","`"&_xlfn.XLOOKUP(1,AH:AH,R:R,"",0)&"`")&IF(_xlfn.XLOOKUP(2,AH:AH,R:R,"",0)="","",",`"&_xlfn.XLOOKUP(2,AH:AH,R:R,"",0)&"`")&IF(_xlfn.XLOOKUP(3,AH:AH,R:R,"",0)="","",",`"&_xlfn.XLOOKUP(3,AH:AH,R:R,"",0)&"`")&IF(_xlfn.XLOOKUP(4,AH:AH,R:R,"",0)="","",",`"&_xlfn.XLOOKUP(4,AH:AH,R:R,"",0)&"`")&IF(_xlfn.XLOOKUP(5,AH:AH,R:R,"",0)="","",",`"&_xlfn.XLOOKUP(5,AH:AH,R:R,"",0)&"`")&IF(_xlfn.XLOOKUP(6,AH:AH,R:R,"",0)="","",",`"&_xlfn.XLOOKUP(6,AH:AH,R:R,"",0)&"`")&IF(_xlfn.XLOOKUP(7,AH:AH,R:R,"",0)="","",",`"&_xlfn.XLOOKUP(7,AH:AH,R:R,"",0)&"`")&IF(_xlfn.XLOOKUP(8,AH:AH,R:R,"",0)="","",",`"&_xlfn.XLOOKUP(8,AH:AH,R:R,"",0)&"`")&")," -> , PRIMARY KEY (`RECORD_ID`), | BN38: =BM38 -> , PRIMARY KEY (`RECORD_ID`), | BO38: =",A.`"&R38&"` = B.`"&R38&"`" -> ,A.``RECORD_ID`` = B.``RECORD_ID`` | BP38: =",`"&R38&"`" -> ,``RECORD_ID``
BM39: KEY `RECORD_ID` (`RECORD_ID`) | BO39: =",A.`"&R39&"` = B.`"&R39&"`" -> ,A.`` = B.`` | BP39: =",`"&R39&"`" -> ,``
BM40: =") ENGINE=InnoDB DEFAULT CHARSET=utf8 COMMENT = '"&$G$9&"';" -> ) ENGINE=InnoDB DEFAULT CHARSET=utf8 COMMENT = '機器接続情報'; | BN40: =") ENGINE=InnoDB DEFAULT CHARSET=utf8 COMMENT = '"&$G$9&"_TMP';" -> ) ENGINE=InnoDB DEFAULT CHARSET=utf8 COMMENT = '機器接続情報_TMP'; | BO40: =",A.`"&R40&"` = B.`"&R40&"`" -> ,A.`` = B.`` | BP40: =",`"&R40&"`" -> ,``
B41: トリガー情報 | BO41: =",A.`"&R41&"` = B.`"&R41&"`" -> ,A.`` = B.`` | BP41: =",`"&R41&"`" -> ,``
B42: No. | D42: トリガー名 | R42: イベント | U42: タイミング | Y42: 条件 | BM42: ="CREATE TRIGGER `"&G2&"_CR_Date_Time` BEFORE INSERT ON `"&G2&"` FOR EACH ROW SET NEW.record_create_date = CURRENT_DATE, NEW.record_create_time = CURRENT_TIME, NEW.record_update_date = CURRENT_DATE, NEW.record_update_time = CURRENT_TIME;" -> CREATE TRIGGER `_CR_Date_Time` BEFORE INSERT ON `` FOR EACH ROW SET NEW.record_create_date = CURRENT_DATE, NEW.record_create_time = CURRENT_TIME, NEW.record_update_date = CURRENT_DATE, NEW.record_update_time = CURRENT_TIME; | BO42: =",A.`"&R42&"` = B.`"&R42&"`" -> ,A.`イベント` = B.`イベント` | BP42: =",`"&R42&"`" -> ,`イベント`
B43: 1 | D43: =G10&"_"&R43&"_"&"trg" -> _update_trg | R43: update | U43: Before row | Y43: auto_updated_date | BM43: ="CREATE TRIGGER `"&G2&"_UP_Date_Time` BEFORE UPDATE ON `"&G2&"` FOR EACH ROW SET NEW.record_update_date = CURRENT_DATE, NEW.record_update_time = CURRENT_TIME;" -> CREATE TRIGGER `_UP_Date_Time` BEFORE UPDATE ON `` FOR EACH ROW SET NEW.record_update_date = CURRENT_DATE, NEW.record_update_time = CURRENT_TIME;
BM63: , PRIMARY KEY (`CompanyCode`,`StoreCode`,`ReceiptCouponCode`,`PrintFrom`,`MessagePosition`,`MessageLineNo`), | BN63: =BM63 -> , PRIMARY KEY (`CompanyCode`,`StoreCode`,`ReceiptCouponCode`,`PrintFrom`,`MessagePosition`,`MessageLineNo`), | BO63: =",A.`"&R63&"` = B.`"&R63&"`" -> ,A.`` = B.`` | BP63: =",`"&R63&"`" -> ,``
BM64: KEY `RECORD_ID` (`RECORD_ID`) | BO64: =",A.`"&R64&"` = B.`"&R64&"`" -> ,A.`` = B.`` | BP64: =",`"&R64&"`" -> ,``
BM65: ) ENGINE=InnoDB DEFAULT CHARSET=utf8; | BN65: =BM65 -> ) ENGINE=InnoDB DEFAULT CHARSET=utf8; | BO65: =",A.`"&R65&"` = B.`"&R65&"`" -> ,A.`` = B.`` | BP65: =",`"&R65&"`" -> ,``
BM66: ="CREATE TRIGGER `"&G10&"_CR_Date_Time` BEFORE INSERT ON `"&G10&"` FOR EACH ROW SET NEW.record_create_date = CURRENT_DATE, NEW.record_create_time = CURRENT_TIME, NEW.record_update_date = CURRENT_DATE, NEW.record_update_time = CURRENT_TIME;" -> CREATE TRIGGER `_CR_Date_Time` BEFORE INSERT ON `` FOR EACH ROW SET NEW.record_create_date = CURRENT_DATE, NEW.record_create_time = CURRENT_TIME, NEW.record_update_date = CURRENT_DATE, NEW.record_update_time = CURRENT_TIME;
BM67: ="CREATE TRIGGER `"&G10&"_UP_Date_Time` BEFORE UPDATE ON `"&G10&"` FOR EACH ROW SET NEW.record_update_date = CURRENT_DATE, NEW.record_update_time = CURRENT_TIME;" -> CREATE TRIGGER `_UP_Date_Time` BEFORE UPDATE ON `` FOR EACH ROW SET NEW.record_update_date = CURRENT_DATE, NEW.record_update_time = CURRENT_TIME;

Sheet 売上情報
A1: システム名 | K1: システム種別 | W1: =IF(表紙!W1="","",表紙!W1) -> DB定義書 | AP1: 作成者 | AT1: 作成日 | AY1: 更新者 | BC1: 更新日 | BH1: 版数
A2: =IF(表紙!A2="","",表紙!A2) -> 現金専用簡易セルフPOS | K2: =IF(表紙!K2="","",表紙!K2) | AP2: =IF(表紙!AP2="","",表紙!AP2) -> きよはら | AT2: =IF(表紙!AT2="","",表紙!AT2) -> 44652 | AY2: =IF(表紙!AY2="","",表紙!AY2) -> Thanh Nguyên | BC2: =IF(表紙!BC2="","",表紙!BC2) -> 45285 | BH2: =IF(表紙!BH2="","",表紙!BH2) -> 0.2
A4: 機能カテゴリ | H4: =IF(表紙!H4="","",表紙!H4) -> 共通 | U4: 項目 | Z4: =IF(表紙!Z4="","",表紙!Z4) | AP4: テンプレート
B7: ■テーブル情報
B8: スキーマ名 | Y8: RDBMS名
B9: 論理名 | G9: 売上情報 | Y9: バージョン
B10: 物理名 | G10: sales_details
B11: 備考
B19: ■カラム情報 | BM19: ="DROP TABLE IF EXISTS `"&$G$8&"`.`"&$G$10&"`;" -> DROP TABLE IF EXISTS ``.`sales_details`;
B20: No. | D20: 論理名 | R20: 物理名 | AC20: データ型 | AH20: PK | AJ20: Not Null | AM20: デフォルト | AT20: 備考 | BM20: ="CREATE TABLE `"&$G$8&"`.`"&$G$10&"` (" -> CREATE TABLE ``.`sales_details` ( | BN20: ="CREATE TABLE `TMP`.`"&G10&"` (" -> CREATE TABLE `TMP`.`sales_details` (
B21: 1 | D21: レコードID | R21: RECORD_ID | AC21: BIGINT | AJ21: Y | AM21: 自動追加 | BM21: ="`"&R21&"` "&AC21&" "&IF(AJ21="Y","NOT NULL","")&" AUTO_INCREMENT COMMENT '"&D21&IF(AT21="","","/"&AT21)&"'" -> `RECORD_ID` BIGINT NOT NULL AUTO_INCREMENT COMMENT 'レコードID' | BO21: =",A.`"&R21&"` = B.`"&R21&"`" -> ,A.`RECORD_ID` = B.`RECORD_ID` | BP21: =",`"&R21&"`" -> ,`RECORD_ID`
B22: 2 | D22: レコード作成日付 | R22: RECORD_CREATE_DATE | AC22: TIMESTAMP | AJ22: Y | AM22: CURRENT_DATE | BM22: =",`"&R22&"` "&AC22&" "&IF(AJ22="Y","NOT NULL","")&" COMMENT '"&D22&IF(AT22="","","/"&AT22)&"'" -> ,`RECORD_CREATE_DATE` TIMESTAMP NOT NULL COMMENT 'レコード作成日付' | BO22: =",A.`"&R22&"` = B.`"&R22&"`" -> ,A.`RECORD_CREATE_DATE` = B.`RECORD_CREATE_DATE` | BP22: =",`"&R22&"`" -> ,`RECORD_CREATE_DATE`
B23: 3 | D23: レコード作成時間 | R23: RECORD_CREATE_TIME | AC23: BIGINT | AJ23: Y | AM23: CURRENT_TIME | BM23: =",`"&R23&"` "&AC23&" "&IF(AJ23="Y","NOT NULL","")&" COMMENT '"&D23&IF(AT23="","","/"&AT23)&"'" -> ,`RECORD_CREATE_TIME` BIGINT NOT NULL COMMENT 'レコード作成時間' | BO23: =",A.`"&R23&"` = B.`"&R23&"`" -> ,A.`RECORD_CREATE_TIME` = B.`RECORD_CREATE_TIME` | BP23: =",`"&R23&"`" -> ,`RECORD_CREATE_TIME`
B24: 4 | D24: レコード更新日付 | R24: RECORD_UPDATE_DATE | AC24: TIMESTAMP | AJ24: Y | AM24: CURRENT_DATE | AT24: トリガーにより更新 | BM24: =",`"&R24&"` "&AC24&" "&IF(AJ24="Y","NOT NULL","")&" COMMENT '"&D24&IF(AT24="","","/"&AT24)&"'" -> ,`RECORD_UPDATE_DATE` TIMESTAMP NOT NULL COMMENT 'レコード更新日付/トリガーにより更新' | BO24: =",A.`"&R24&"` = B.`"&R24&"`" -> ,A.`RECORD_UPDATE_DATE` = B.`RECORD_UPDATE_DATE` | BP24: =",`"&R24&"`" -> ,`RECORD_UPDATE_DATE`
B25: 5 | D25: レコード更新時間 | R25: RECORD_UPDATE_TIME | AC25: BIGINT | AJ25: Y | AM25: CURRENT_TIME | AT25: トリガーにより更新 | BM25: =",`"&R25&"` "&AC25&" "&IF(AJ25="Y","NOT NULL","")&" COMMENT '"&D25&IF(AT25="","","/"&AT25)&"'" -> ,`RECORD_UPDATE_TIME` BIGINT NOT NULL COMMENT 'レコード更新時間/トリガーにより更新' | BO25: =",A.`"&R25&"` = B.`"&R25&"`" -> ,A.`RECORD_UPDATE_TIME` = B.`RECORD_UPDATE_TIME` | BP25: =",`"&R25&"`" -> ,`RECORD_UPDATE_TIME`
B26: 6 | D26: レコード無効フラグ | R26: RECORD_VOID_FLAG | AC26: BOOL | AJ26: Y | AM26: "" | AT26: true:有効 / false:無効 | BM26: =",`"&R26&"` "&AC26&" "&IF(AJ26="Y","NOT NULL","")&" COMMENT '"&D26&IF(AT26="","","/"&AT26)&"'" -> ,`RECORD_VOID_FLAG` BOOL NOT NULL COMMENT 'レコード無効フラグ/true:有効 / false:無効' | BN26: `CLASS` VARCHAR ( 1 ) NOT NULL COMMENT '処理区分', | BO26: =",A.`"&R26&"` = B.`"&R26&"`" -> ,A.`RECORD_VOID_FLAG` = B.`RECORD_VOID_FLAG` | BP26: =",`"&R26&"`" -> ,`RECORD_VOID_FLAG`
B27: 7 | D27: 企業コード | R27: company_code | AC27: char(3) | AH27: 1 | BM27: =",`"&R27&"` "&AC27&" "&IF(AJ27="Y","NOT NULL","")&" COMMENT '"&D27&IF(AT27="","","/"&AT27)&"'" -> ,`company_code` char(3) COMMENT '企業コード' | BN27: =",`"&R27&"` "&AC27&" "&IF(AJ27="Y","NOT NULL","")&" COMMENT '"&D27&"'" -> ,`company_code` char(3) COMMENT '企業コード' | BO27: =",A.`"&R27&"` = B.`"&R27&"`" -> ,A.`company_code` = B.`company_code` | BP27: =",`"&R27&"`" -> ,`company_code`
B28: 8 | D28: 店舗コード | R28: store_code | AC28: char(5) | AH28: 2 | BM28: =",`"&R28&"` "&AC28&" "&IF(AJ28="Y","NOT NULL","")&" COMMENT '"&D28&IF(AT28="","","/"&AT28)&"'" -> ,`store_code` char(5) COMMENT '店舗コード' | BN28: =",`"&R28&"` "&AC28&" "&IF(AJ28="Y","NOT NULL","")&" COMMENT '"&D28&"'" -> ,`store_code` char(5) COMMENT '店舗コード' | BO28: =",A.`"&R28&"` = B.`"&R28&"`" -> ,A.`store_code` = B.`store_code` | BP28: =",`"&R28&"`" -> ,`store_code`
B29: 9 | D29: レジ番号 | R29: instore_code | AC29: char(5) | AH29: 3 | BM29: =",`"&R29&"` "&AC29&" "&IF(AJ29="Y","NOT NULL","")&" COMMENT '"&D29&IF(AT29="","","/"&AT29)&"'" -> ,`instore_code` char(5) COMMENT 'レジ番号' | BN29: =",`"&R29&"` "&AC29&" "&IF(AJ29="Y","NOT NULL","")&" COMMENT '"&D29&"'" -> ,`instore_code` char(5) COMMENT 'レジ番号' | BO29: =",A.`"&R29&"` = B.`"&R29&"`" -> ,A.`instore_code` = B.`instore_code` | BP29: =",`"&R29&"`" -> ,`instore_code`
B30: 13 | D30: 取引確定日時<取引確定後> | R30: record_datetime | AC30: char(16) | BM30: =",`"&R30&"` "&AC30&" "&IF(AJ30="Y","NOT NULL","")&" COMMENT '"&D30&IF(AT30="","","/"&AT30)&"'" -> ,`record_datetime` char(16) COMMENT '取引確定日時<取引確定後>' | BN30: =",`"&R30&"` "&AC30&" "&IF(AJ30="Y","NOT NULL","")&" COMMENT '"&D30&"'" -> ,`record_datetime` char(16) COMMENT '取引確定日時<取引確定後>' | BO30: =",A.`"&R30&"` = B.`"&R30&"`" -> ,A.`record_datetime` = B.`record_datetime` | BP30: =",`"&R30&"`" -> ,`record_datetime`
B31: 14 | D31: ジャーナルNO<取引確定後> | R31: journal_no | AC31: char(10) | BM31: =",`"&R31&"` "&AC31&" "&IF(AJ31="Y","NOT NULL","")&" COMMENT '"&D31&IF(AT31="","","/"&AT31)&"'" -> ,`journal_no` char(10) COMMENT 'ジャーナルNO<取引確定後>' | BN31: =",`"&R31&"` "&AC31&" "&IF(AJ31="Y","NOT NULL","")&" COMMENT '"&D31&"'" -> ,`journal_no` char(10) COMMENT 'ジャーナルNO<取引確定後>' | BO31: =",A.`"&R31&"` = B.`"&R31&"`" -> ,A.`journal_no` = B.`journal_no` | BP31: =",`"&R31&"`" -> ,`journal_no`
B32: 15 | D32: レシートNO<取引確定後> | R32: receipt_no | AC32: char(10) | BM32: =",`"&R32&"` "&AC32&" "&IF(AJ32="Y","NOT NULL","")&" COMMENT '"&D32&IF(AT32="","","/"&AT32)&"'" -> ,`receipt_no` char(10) COMMENT 'レシートNO<取引確定後>' | BN32: =",`"&R32&"` "&AC32&" "&IF(AJ32="Y","NOT NULL","")&" COMMENT '"&D32&"'" -> ,`receipt_no` char(10) COMMENT 'レシートNO<取引確定後>' | BO32: =",A.`"&R32&"` = B.`"&R32&"`" -> ,A.`receipt_no` = B.`receipt_no` | BP32: =",`"&R32&"`" -> ,`receipt_no`
B33: 16 | D33: 年齢確認フラグ ( true : 確認済み ) | R33: confirm_age | AC33: bool | AT33: true : 確認済み | BM33: =",`"&R33&"` "&AC33&" "&IF(AJ33="Y","NOT NULL","")&" COMMENT '"&D33&IF(AT33="","","/"&AT33)&"'" -> ,`confirm_age` bool COMMENT '年齢確認フラグ ( true : 確認済み )/true : 確認済み' | BN33: =",`"&R33&"` "&AC33&" "&IF(AJ33="Y","NOT NULL","")&" COMMENT '"&D33&"'" -> ,`confirm_age` bool COMMENT '年齢確認フラグ ( true : 確認済み )' | BO33: =",A.`"&R33&"` = B.`"&R33&"`" -> ,A.`confirm_age` = B.`confirm_age` | BP33: =",`"&R33&"`" -> ,`confirm_age`
B34: 17 | D34: Scan&Go アカウントID | R34: account_id | AC34: string | BM34: =",`"&R34&"` "&AC34&" "&IF(AJ34="Y","NOT NULL","")&" COMMENT '"&D34&IF(AT34="","","/"&AT34)&"'" -> ,`account_id` string COMMENT 'Scan&Go アカウントID' | BN34: =",`"&R34&"` "&AC34&" "&IF(AJ34="Y","NOT NULL","")&" COMMENT '"&D34&"'" -> ,`account_id` string COMMENT 'Scan&Go アカウントID' | BO34: =",A.`"&R34&"` = B.`"&R34&"`" -> ,A.`account_id` = B.`account_id` | BP34: =",`"&R34&"`" -> ,`account_id`
B35: 18 | D35: Scan&Go アカウント名 | R35: account_name | AC35: string | BM35: =",`"&R35&"` "&AC35&" "&IF(AJ35="Y","NOT NULL","")&" COMMENT '"&D35&IF(AT35="","","/"&AT35)&"'" -> ,`account_name` string COMMENT 'Scan&Go アカウント名' | BN35: =",`"&R35&"` "&AC35&" "&IF(AJ35="Y","NOT NULL","")&" COMMENT '"&D35&"'" -> ,`account_name` string COMMENT 'Scan&Go アカウント名' | BO35: =",A.`"&R35&"` = B.`"&R35&"`" -> ,A.`account_name` = B.`account_name` | BP35: =",`"&R35&"`" -> ,`account_name`
B36: 19 | D36: 明細合計金額 | R36: item_total_price_fmt | AC36: string | BM36: =",`"&R36&"` "&AC36&" "&IF(AJ36="Y","NOT NULL","")&" COMMENT '"&D36&IF(AT36="","","/"&AT36)&"'" -> ,`item_total_price_fmt` string COMMENT '明細合計金額' | BN36: =",`"&R36&"` "&AC36&" "&IF(AJ36="Y","NOT NULL","")&" COMMENT '"&D36&"'" -> ,`item_total_price_fmt` string COMMENT '明細合計金額' | BO36: =",A.`"&R36&"` = B.`"&R36&"`" -> ,A.`item_total_price_fmt` = B.`item_total_price_fmt` | BP36: =",`"&R36&"`" -> ,`item_total_price_fmt`
B37: 20 | D37: まとめ値引金額 | R37: mm_discount_price_fmt | AC37: string | BM37: =",`"&R37&"` "&AC37&" "&IF(AJ37="Y","NOT NULL","")&" COMMENT '"&D37&IF(AT37="","","/"&AT37)&"'" -> ,`mm_discount_price_fmt` string COMMENT 'まとめ値引金額' | BN37: =",`"&R37&"` "&AC37&" "&IF(AJ37="Y","NOT NULL","")&" COMMENT '"&D37&"'" -> ,`mm_discount_price_fmt` string COMMENT 'まとめ値引金額' | BO37: =",A.`"&R37&"` = B.`"&R37&"`" -> ,A.`mm_discount_price_fmt` = B.`mm_discount_price_fmt` | BP37: =",`"&R37&"`" -> ,`mm_discount_price_fmt`
B38: 21 | D38: 小計金額 | R38: subtotal_price_fmt | AC38: string | BM38: =",`"&R38&"` "&AC38&" "&IF(AJ38="Y","NOT NULL","")&" COMMENT '"&D38&IF(AT38="","","/"&AT38)&"'" -> ,`subtotal_price_fmt` string COMMENT '小計金額' | BN38: =",`"&R38&"` "&AC38&" "&IF(AJ38="Y","NOT NULL","")&" COMMENT '"&D38&"'" -> ,`subtotal_price_fmt` string COMMENT '小計金額' | BO38: =",A.`"&R38&"` = B.`"&R38&"`" -> ,A.`subtotal_price_fmt` = B.`subtotal_price_fmt` | BP38: =",`"&R38&"`" -> ,`subtotal_price_fmt`
B39: 22 | D39: 小計値引金額 | R39: subtotal_discount_price_fmt | AC39: string | BM39: =",`"&R39&"` "&AC39&" "&IF(AJ39="Y","NOT NULL","")&" COMMENT '"&D39&IF(AT39="","","/"&AT39)&"'" -> ,`subtotal_discount_price_fmt` string COMMENT '小計値引金額' | BN39: =",`"&R39&"` "&AC39&" "&IF(AJ39="Y","NOT NULL","")&" COMMENT '"&D39&"'" -> ,`subtotal_discount_price_fmt` string COMMENT '小計値引金額' | BO39: =",A.`"&R39&"` = B.`"&R39&"`" -> ,A.`subtotal_discount_price_fmt` = B.`subtotal_discount_price_fmt` | BP39: =",`"&R39&"`" -> ,`subtotal_discount_price_fmt`
B40: 23 | D40: 外税合計 | R40: total_tax_excluded_fmt | AC40: string | BM40: =",`"&R40&"` "&AC40&" "&IF(AJ40="Y","NOT NULL","")&" COMMENT '"&D40&IF(AT40="","","/"&AT40)&"'" -> ,`total_tax_excluded_fmt` string COMMENT '外税合計' | BN40: =",`"&R40&"` "&AC40&" "&IF(AJ40="Y","NOT NULL","")&" COMMENT '"&D40&"'" -> ,`total_tax_excluded_fmt` string COMMENT '外税合計' | BO40: =",A.`"&R40&"` = B.`"&R40&"`" -> ,A.`total_tax_excluded_fmt` = B.`total_tax_excluded_fmt` | BP40: =",`"&R40&"`" -> ,`total_tax_excluded_fmt`
B41: 24 | D41: 合計金額 （=小計金額 - 小計値引金額 + 外税合計） | R41: total_price_fmt | AC41: string | BM41: =",`"&R41&"` "&AC41&" "&IF(AJ41="Y","NOT NULL","")&" COMMENT '"&D41&IF(AT41="","","/"&AT41)&"'" -> ,`total_price_fmt` string COMMENT '合計金額 （=小計金額 - 小計値引金額 + 外税合計）' | BN41: =",`"&R41&"` "&AC41&" "&IF(AJ41="Y","NOT NULL","")&" COMMENT '"&D41&"'" -> ,`total_price_fmt` string COMMENT '合計金額 （=小計金額 - 小計値引金額 + 外税合計）' | BO41: =",A.`"&R41&"` = B.`"&R41&"`" -> ,A.`total_price_fmt` = B.`total_price_fmt` | BP41: =",`"&R41&"`" -> ,`total_price_fmt`
B42: 25 | D42: 合計点数 | R42: total_quantity_fmt | AC42: string | BM42: =",`"&R42&"` "&AC42&" "&IF(AJ42="Y","NOT NULL","")&" COMMENT '"&D42&IF(AT42="","","/"&AT42)&"'" -> ,`total_quantity_fmt` string COMMENT '合計点数' | BN42: =",`"&R42&"` "&AC42&" "&IF(AJ42="Y","NOT NULL","")&" COMMENT '"&D42&"'" -> ,`total_quantity_fmt` string COMMENT '合計点数' | BO42: =",A.`"&R42&"` = B.`"&R42&"`" -> ,A.`total_quantity_fmt` = B.`total_quantity_fmt` | BP42: =",`"&R42&"`" -> ,`total_quantity_fmt`
B43: 26
B44: 27
B45: 28
B46: 29
B49: ■インデックス情報
B50: No. | D50: Index名 | R50: カラム一覧 | AL50: プライマリキー | AP50: ユニーク | AT50: 備考
B51: 1 | D51: PRIMARY | R51: =IF(_xlfn.XLOOKUP(1,AH:AH,R:R,"",0)="","","`"&_xlfn.XLOOKUP(1,AH:AH,R:R,"",0)&"`")&IF(_xlfn.XLOOKUP(2,AH:AH,R:R,"",0)="","",",`"&_xlfn.XLOOKUP(2,AH:AH,R:R,"",0)&"`")&IF(_xlfn.XLOOKUP(3,AH:AH,R:R,"",0)="","",",`"&_xlfn.XLOOKUP(3,AH:AH,R:R,"",0)&"`")&IF(_xlfn.XLOOKUP(4,AH:AH,R:R,"",0)="","",",`"&_xlfn.XLOOKUP(4,AH:AH,R:R,"",0)&"`")&IF(_xlfn.XLOOKUP(5,AH:AH,R:R,"",0)="","",",`"&_xlfn.XLOOKUP(5,AH:AH,R:R,"",0)&"`")&IF(_xlfn.XLOOKUP(6,AH:AH,R:R,"",0)="","",",`"&_xlfn.XLOOKUP(6,AH:AH,R:R,"",0)&"`")&IF(_xlfn.XLOOKUP(7,AH:AH,R:R,"",0)="","",",`"&_xlfn.XLOOKUP(7,AH:AH,R:R,"",0)&"`")&IF(_xlfn.XLOOKUP(8,AH:AH,R:R,"",0)="","",",`"&_xlfn.XLOOKUP(8,AH:AH,R:R,"",0)&"`") -> `company_code`,`store_code`,`instore_code` | AL51: Y | AP51: Y | BM51: =" , PRIMARY KEY ("&IF(_xlfn.XLOOKUP(1,AH:AH,R:R,"",0)="","","`"&_xlfn.XLOOKUP(1,AH:AH,R:R,"",0)&"`")&IF(_xlfn.XLOOKUP(2,AH:AH,R:R,"",0)="","",",`"&_xlfn.XLOOKUP(2,AH:AH,R:R,"",0)&"`")&IF(_xlfn.XLOOKUP(3,AH:AH,R:R,"",0)="","",",`"&_xlfn.XLOOKUP(3,AH:AH,R:R,"",0)&"`")&IF(_xlfn.XLOOKUP(4,AH:AH,R:R,"",0)="","",",`"&_xlfn.XLOOKUP(4,AH:AH,R:R,"",0)&"`")&IF(_xlfn.XLOOKUP(5,AH:AH,R:R,"",0)="","",",`"&_xlfn.XLOOKUP(5,AH:AH,R:R,"",0)&"`")&IF(_xlfn.XLOOKUP(6,AH:AH,R:R,"",0)="","",",`"&_xlfn.XLOOKUP(6,AH:AH,R:R,"",0)&"`")&IF(_xlfn.XLOOKUP(7,AH:AH,R:R,"",0)="","",",`"&_xlfn.XLOOKUP(7,AH:AH,R:R,"",0)&"`")&IF(_xlfn.XLOOKUP(8,AH:AH,R:R,"",0)="","",",`"&_xlfn.XLOOKUP(8,AH:AH,R:R,"",0)&"`")&")," -> , PRIMARY KEY (`company_code`,`store_code`,`instore_code`), | BN51: =BM51 -> , PRIMARY KEY (`company_code`,`store_code`,`instore_code`),
BM52: KEY `RECORD_ID` (`RECORD_ID`)
BM53: =") ENGINE=InnoDB DEFAULT CHARSET=utf8 COMMENT = '"&$G$9&"';" -> ) ENGINE=InnoDB DEFAULT CHARSET=utf8 COMMENT = '売上情報'; | BN53: =") ENGINE=InnoDB DEFAULT CHARSET=utf8 COMMENT = '"&$G$9&"_TMP';" -> ) ENGINE=InnoDB DEFAULT CHARSET=utf8 COMMENT = '売上情報_TMP';
B54: トリガー情報
B55: No. | D55: トリガー名 | R55: イベント | U55: タイミング | Y55: 条件 | BM55: ="CREATE TRIGGER `"&G15&"_CR_Date_Time` BEFORE INSERT ON `"&G15&"` FOR EACH ROW SET NEW.record_create_date = CURRENT_DATE, NEW.record_create_time = CURRENT_TIME, NEW.record_update_date = CURRENT_DATE, NEW.record_update_time = CURRENT_TIME;" -> CREATE TRIGGER `_CR_Date_Time` BEFORE INSERT ON `` FOR EACH ROW SET NEW.record_create_date = CURRENT_DATE, NEW.record_create_time = CURRENT_TIME, NEW.record_update_date = CURRENT_DATE, NEW.record_update_time = CURRENT_TIME;
B56: 1 | D56: =G10&"_"&R56&"_"&"trg" -> sales_details_update_trg | R56: update | U56: Before row | Y56: auto_updated_date | BM56: ="CREATE TRIGGER `"&G15&"_UP_Date_Time` BEFORE UPDATE ON `"&G15&"` FOR EACH ROW SET NEW.record_update_date = CURRENT_DATE, NEW.record_update_time = CURRENT_TIME;" -> CREATE TRIGGER `_UP_Date_Time` BEFORE UPDATE ON `` FOR EACH ROW SET NEW.record_update_date = CURRENT_DATE, NEW.record_update_time = CURRENT_TIME;
BM63: , PRIMARY KEY (`CompanyCode`,`StoreCode`,`ReceiptCouponCode`,`PrintFrom`,`MessagePosition`,`MessageLineNo`), | BN63: =BM63 -> , PRIMARY KEY (`CompanyCode`,`StoreCode`,`ReceiptCouponCode`,`PrintFrom`,`MessagePosition`,`MessageLineNo`), | BO63: =",A.`"&R63&"` = B.`"&R63&"`" -> ,A.`` = B.`` | BP63: =",`"&R63&"`" -> ,``
BM64: KEY `RECORD_ID` (`RECORD_ID`) | BO64: =",A.`"&R64&"` = B.`"&R64&"`" -> ,A.`` = B.`` | BP64: =",`"&R64&"`" -> ,``
BM65: ) ENGINE=InnoDB DEFAULT CHARSET=utf8; | BN65: =BM65 -> ) ENGINE=InnoDB DEFAULT CHARSET=utf8; | BO65: =",A.`"&R65&"` = B.`"&R65&"`" -> ,A.`` = B.`` | BP65: =",`"&R65&"`" -> ,``
BM66: ="CREATE TRIGGER `"&G10&"_CR_Date_Time` BEFORE INSERT ON `"&G10&"` FOR EACH ROW SET NEW.record_create_date = CURRENT_DATE, NEW.record_create_time = CURRENT_TIME, NEW.record_update_date = CURRENT_DATE, NEW.record_update_time = CURRENT_TIME;" -> CREATE TRIGGER `sales_details_CR_Date_Time` BEFORE INSERT ON `sales_details` FOR EACH ROW SET NEW.record_create_date = CURRENT_DATE, NEW.record_create_time = CURRENT_TIME, NEW.record_update_date = CURRENT_DATE, NEW.record_update_time = CURRENT_TIME;
BM67: ="CREATE TRIGGER `"&G10&"_UP_Date_Time` BEFORE UPDATE ON `"&G10&"` FOR EACH ROW SET NEW.record_update_date = CURRENT_DATE, NEW.record_update_time = CURRENT_TIME;" -> CREATE TRIGGER `sales_details_UP_Date_Time` BEFORE UPDATE ON `sales_details` FOR EACH ROW SET NEW.record_update_date = CURRENT_DATE, NEW.record_update_time = CURRENT_TIME;

Sheet 売上情報(税)
A1: システム名 | K1: システム種別 | W1: =IF(表紙!W1="","",表紙!W1) -> DB定義書 | AP1: 作成者 | AT1: 作成日 | AY1: 更新者 | BC1: 更新日 | BH1: 版数
A2: =IF(表紙!A2="","",表紙!A2) -> 現金専用簡易セルフPOS | K2: =IF(表紙!K2="","",表紙!K2) | AP2: =IF(表紙!AP2="","",表紙!AP2) -> きよはら | AT2: =IF(表紙!AT2="","",表紙!AT2) -> 44652 | AY2: =IF(表紙!AY2="","",表紙!AY2) -> Thanh Nguyên | BC2: =IF(表紙!BC2="","",表紙!BC2) -> 45285 | BH2: =IF(表紙!BH2="","",表紙!BH2) -> 0.2
A4: 機能カテゴリ | H4: =IF(表紙!H4="","",表紙!H4) -> 共通 | U4: 項目 | Z4: =IF(表紙!Z4="","",表紙!Z4) | AP4: テンプレート
B7: ■テーブル情報
B8: スキーマ名 | Y8: RDBMS名
B9: 論理名 | G9: 売上情報明細 | Y9: バージョン
B10: 物理名 | G10: sales_details
B11: 備考
B19: ■カラム情報 | BM19: ="DROP TABLE IF EXISTS `"&$G$8&"`.`"&$G$10&"`;" -> DROP TABLE IF EXISTS ``.`sales_details`;
B20: No. | D20: 論理名 | R20: 物理名 | AC20: データ型 | AH20: PK | AJ20: Not Null | AM20: デフォルト | AT20: 備考 | BM20: ="CREATE TABLE `"&$G$8&"`.`"&$G$10&"` (" -> CREATE TABLE ``.`sales_details` ( | BN20: ="CREATE TABLE `TMP`.`"&G10&"` (" -> CREATE TABLE `TMP`.`sales_details` (
B21: 1 | D21: レコードID | R21: RECORD_ID | AC21: BIGINT | AJ21: Y | AM21: 自動追加 | BM21: ="`"&R21&"` "&AC21&" "&IF(AJ21="Y","NOT NULL","")&" AUTO_INCREMENT COMMENT '"&D21&IF(AT21="","","/"&AT21)&"'" -> `RECORD_ID` BIGINT NOT NULL AUTO_INCREMENT COMMENT 'レコードID' | BO21: =",A.`"&R21&"` = B.`"&R21&"`" -> ,A.`RECORD_ID` = B.`RECORD_ID` | BP21: =",`"&R21&"`" -> ,`RECORD_ID`
B22: 2 | D22: レコード作成日付 | R22: RECORD_CREATE_DATE | AC22: TIMESTAMP | AJ22: Y | AM22: CURRENT_DATE | BM22: =",`"&R22&"` "&AC22&" "&IF(AJ22="Y","NOT NULL","")&" COMMENT '"&D22&IF(AT22="","","/"&AT22)&"'" -> ,`RECORD_CREATE_DATE` TIMESTAMP NOT NULL COMMENT 'レコード作成日付' | BO22: =",A.`"&R22&"` = B.`"&R22&"`" -> ,A.`RECORD_CREATE_DATE` = B.`RECORD_CREATE_DATE` | BP22: =",`"&R22&"`" -> ,`RECORD_CREATE_DATE`
B23: 3 | D23: レコード作成時間 | R23: RECORD_CREATE_TIME | AC23: BIGINT | AJ23: Y | AM23: CURRENT_TIME | BM23: =",`"&R23&"` "&AC23&" "&IF(AJ23="Y","NOT NULL","")&" COMMENT '"&D23&IF(AT23="","","/"&AT23)&"'" -> ,`RECORD_CREATE_TIME` BIGINT NOT NULL COMMENT 'レコード作成時間' | BO23: =",A.`"&R23&"` = B.`"&R23&"`" -> ,A.`RECORD_CREATE_TIME` = B.`RECORD_CREATE_TIME` | BP23: =",`"&R23&"`" -> ,`RECORD_CREATE_TIME`
B24: 4 | D24: レコード更新日付 | R24: RECORD_UPDATE_DATE | AC24: TIMESTAMP | AJ24: Y | AM24: CURRENT_DATE | AT24: トリガーにより更新 | BM24: =",`"&R24&"` "&AC24&" "&IF(AJ24="Y","NOT NULL","")&" COMMENT '"&D24&IF(AT24="","","/"&AT24)&"'" -> ,`RECORD_UPDATE_DATE` TIMESTAMP NOT NULL COMMENT 'レコード更新日付/トリガーにより更新' | BO24: =",A.`"&R24&"` = B.`"&R24&"`" -> ,A.`RECORD_UPDATE_DATE` = B.`RECORD_UPDATE_DATE` | BP24: =",`"&R24&"`" -> ,`RECORD_UPDATE_DATE`
B25: 5 | D25: レコード更新時間 | R25: RECORD_UPDATE_TIME | AC25: BIGINT | AJ25: Y | AM25: CURRENT_TIME | AT25: トリガーにより更新 | BM25: =",`"&R25&"` "&AC25&" "&IF(AJ25="Y","NOT NULL","")&" COMMENT '"&D25&IF(AT25="","","/"&AT25)&"'" -> ,`RECORD_UPDATE_TIME` BIGINT NOT NULL COMMENT 'レコード更新時間/トリガーにより更新' | BO25: =",A.`"&R25&"` = B.`"&R25&"`" -> ,A.`RECORD_UPDATE_TIME` = B.`RECORD_UPDATE_TIME` | BP25: =",`"&R25&"`" -> ,`RECORD_UPDATE_TIME`
B26: 6 | D26: レコード無効フラグ | R26: RECORD_VOID_FLAG | AC26: BOOL | AJ26: Y | AM26: "" | AT26: true:有効 / false:無効 | BM26: =",`"&R26&"` "&AC26&" "&IF(AJ26="Y","NOT NULL","")&" COMMENT '"&D26&IF(AT26="","","/"&AT26)&"'" -> ,`RECORD_VOID_FLAG` BOOL NOT NULL COMMENT 'レコード無効フラグ/true:有効 / false:無効' | BN26: `CLASS` VARCHAR ( 1 ) NOT NULL COMMENT '処理区分', | BO26: =",A.`"&R26&"` = B.`"&R26&"`" -> ,A.`RECORD_VOID_FLAG` = B.`RECORD_VOID_FLAG` | BP26: =",`"&R26&"`" -> ,`RECORD_VOID_FLAG`
B27: 7 | D27: 企業コード | R27: company_code | AC27: char(3) | AH27: 1 | BM27: =",`"&R27&"` "&AC27&" "&IF(AJ27="Y","NOT NULL","")&" COMMENT '"&D27&IF(AT27="","","/"&AT27)&"'" -> ,`company_code` char(3) COMMENT '企業コード' | BN27: =",`"&R27&"` "&AC27&" "&IF(AJ27="Y","NOT NULL","")&" COMMENT '"&D27&"'" -> ,`company_code` char(3) COMMENT '企業コード' | BO27: =",A.`"&R27&"` = B.`"&R27&"`" -> ,A.`company_code` = B.`company_code` | BP27: =",`"&R27&"`" -> ,`company_code`
B28: 8 | D28: 店舗コード | R28: store_code | AC28: char(5) | AH28: 2 | BM28: =",`"&R28&"` "&AC28&" "&IF(AJ28="Y","NOT NULL","")&" COMMENT '"&D28&IF(AT28="","","/"&AT28)&"'" -> ,`store_code` char(5) COMMENT '店舗コード' | BN28: =",`"&R28&"` "&AC28&" "&IF(AJ28="Y","NOT NULL","")&" COMMENT '"&D28&"'" -> ,`store_code` char(5) COMMENT '店舗コード' | BO28: =",A.`"&R28&"` = B.`"&R28&"`" -> ,A.`store_code` = B.`store_code` | BP28: =",`"&R28&"`" -> ,`store_code`
B29: 9 | D29: レジ番号 | R29: instore_code | AC29: char(5) | AH29: 3 | BM29: =",`"&R29&"` "&AC29&" "&IF(AJ29="Y","NOT NULL","")&" COMMENT '"&D29&IF(AT29="","","/"&AT29)&"'" -> ,`instore_code` char(5) COMMENT 'レジ番号' | BN29: =",`"&R29&"` "&AC29&" "&IF(AJ29="Y","NOT NULL","")&" COMMENT '"&D29&"'" -> ,`instore_code` char(5) COMMENT 'レジ番号' | BO29: =",A.`"&R29&"` = B.`"&R29&"`" -> ,A.`instore_code` = B.`instore_code` | BP29: =",`"&R29&"`" -> ,`instore_code`
B30: 13 | D30: 取引確定日時<取引確定後> | R30: record_datetime | AC30: char(16) | BM30: =",`"&R30&"` "&AC30&" "&IF(AJ30="Y","NOT NULL","")&" COMMENT '"&D30&IF(AT30="","","/"&AT30)&"'" -> ,`record_datetime` char(16) COMMENT '取引確定日時<取引確定後>' | BN30: =",`"&R30&"` "&AC30&" "&IF(AJ30="Y","NOT NULL","")&" COMMENT '"&D30&"'" -> ,`record_datetime` char(16) COMMENT '取引確定日時<取引確定後>' | BO30: =",A.`"&R30&"` = B.`"&R30&"`" -> ,A.`record_datetime` = B.`record_datetime` | BP30: =",`"&R30&"`" -> ,`record_datetime`
B31: 14 | D31: ジャーナルNO<取引確定後> | R31: journal_no | AC31: char(10) | BM31: =",`"&R31&"` "&AC31&" "&IF(AJ31="Y","NOT NULL","")&" COMMENT '"&D31&IF(AT31="","","/"&AT31)&"'" -> ,`journal_no` char(10) COMMENT 'ジャーナルNO<取引確定後>' | BN31: =",`"&R31&"` "&AC31&" "&IF(AJ31="Y","NOT NULL","")&" COMMENT '"&D31&"'" -> ,`journal_no` char(10) COMMENT 'ジャーナルNO<取引確定後>' | BO31: =",A.`"&R31&"` = B.`"&R31&"`" -> ,A.`journal_no` = B.`journal_no` | BP31: =",`"&R31&"`" -> ,`journal_no`
B32: 15 | D32: レシートNO<取引確定後> | R32: receipt_no | AC32: char(10) | AH32: 4 | BM32: =",`"&R32&"` "&AC32&" "&IF(AJ32="Y","NOT NULL","")&" COMMENT '"&D32&IF(AT32="","","/"&AT32)&"'" -> ,`receipt_no` char(10) COMMENT 'レシートNO<取引確定後>' | BN32: =",`"&R32&"` "&AC32&" "&IF(AJ32="Y","NOT NULL","")&" COMMENT '"&D32&"'" -> ,`receipt_no` char(10) COMMENT 'レシートNO<取引確定後>' | BO32: =",A.`"&R32&"` = B.`"&R32&"`" -> ,A.`receipt_no` = B.`receipt_no` | BP32: =",`"&R32&"`" -> ,`receipt_no`
B33: 16 | D33: 明細行番号 | R33: item_no | AC33: string | AH33: 5 | AT33: true : 確認済み | BM33: =",`"&R33&"` "&AC33&" "&IF(AJ33="Y","NOT NULL","")&" COMMENT '"&D33&IF(AT33="","","/"&AT33)&"'" -> ,`item_no` string COMMENT '明細行番号/true : 確認済み' | BN33: =",`"&R33&"` "&AC33&" "&IF(AJ33="Y","NOT NULL","")&" COMMENT '"&D33&"'" -> ,`item_no` string COMMENT '明細行番号' | BO33: =",A.`"&R33&"` = B.`"&R33&"`" -> ,A.`item_no` = B.`item_no` | BP33: =",`"&R33&"`" -> ,`item_no`
B34: 17 | D34: 税種説明 (tax_exclude | tax_include | tax_exempt) | BM34: =",`"&R34&"` "&AC34&" "&IF(AJ34="Y","NOT NULL","")&" COMMENT '"&D34&IF(AT34="","","/"&AT34)&"'" -> ,`` COMMENT '税種説明 (tax_exclude | tax_include | tax_exempt)' | BN34: =",`"&R34&"` "&AC34&" "&IF(AJ34="Y","NOT NULL","")&" COMMENT '"&D34&"'" -> ,`` COMMENT '税種説明 (tax_exclude | tax_include | tax_exempt)' | BO34: =",A.`"&R34&"` = B.`"&R34&"`" -> ,A.`` = B.`` | BP34: =",`"&R34&"`" -> ,``
B35: 18 | D35: 税額 | BM35: =",`"&R35&"` "&AC35&" "&IF(AJ35="Y","NOT NULL","")&" COMMENT '"&D35&IF(AT35="","","/"&AT35)&"'" -> ,`` COMMENT '税額' | BN35: =",`"&R35&"` "&AC35&" "&IF(AJ35="Y","NOT NULL","")&" COMMENT '"&D35&"'" -> ,`` COMMENT '税額' | BO35: =",A.`"&R35&"` = B.`"&R35&"`" -> ,A.`` = B.`` | BP35: =",`"&R35&"`" -> ,``
B36: 19 | D36: 外対象金額 | BM36: =",`"&R36&"` "&AC36&" "&IF(AJ36="Y","NOT NULL","")&" COMMENT '"&D36&IF(AT36="","","/"&AT36)&"'" -> ,`` COMMENT '外対象金額' | BN36: =",`"&R36&"` "&AC36&" "&IF(AJ36="Y","NOT NULL","")&" COMMENT '"&D36&"'" -> ,`` COMMENT '外対象金額' | BO36: =",A.`"&R36&"` = B.`"&R36&"`" -> ,A.`` = B.`` | BP36: =",`"&R36&"`" -> ,``
B37: 20 | BM37: =",`"&R37&"` "&AC37&" "&IF(AJ37="Y","NOT NULL","")&" COMMENT '"&D37&IF(AT37="","","/"&AT37)&"'" -> ,`` COMMENT '' | BN37: =",`"&R37&"` "&AC37&" "&IF(AJ37="Y","NOT NULL","")&" COMMENT '"&D37&"'" -> ,`` COMMENT '' | BO37: =",A.`"&R37&"` = B.`"&R37&"`" -> ,A.`` = B.`` | BP37: =",`"&R37&"`" -> ,``
B38: 21 | BM38: =",`"&R38&"` "&AC38&" "&IF(AJ38="Y","NOT NULL","")&" COMMENT '"&D38&IF(AT38="","","/"&AT38)&"'" -> ,`` COMMENT '' | BN38: =",`"&R38&"` "&AC38&" "&IF(AJ38="Y","NOT NULL","")&" COMMENT '"&D38&"'" -> ,`` COMMENT '' | BO38: =",A.`"&R38&"` = B.`"&R38&"`" -> ,A.`` = B.`` | BP38: =",`"&R38&"`" -> ,``
B39: 22 | BM39: =",`"&R39&"` "&AC39&" "&IF(AJ39="Y","NOT NULL","")&" COMMENT '"&D39&IF(AT39="","","/"&AT39)&"'" -> ,`` COMMENT '' | BN39: =",`"&R39&"` "&AC39&" "&IF(AJ39="Y","NOT NULL","")&" COMMENT '"&D39&"'" -> ,`` COMMENT '' | BO39: =",A.`"&R39&"` = B.`"&R39&"`" -> ,A.`` = B.`` | BP39: =",`"&R39&"`" -> ,``
B40: 23 | BM40: =",`"&R40&"` "&AC40&" "&IF(AJ40="Y","NOT NULL","")&" COMMENT '"&D40&IF(AT40="","","/"&AT40)&"'" -> ,`` COMMENT '' | BN40: =",`"&R40&"` "&AC40&" "&IF(AJ40="Y","NOT NULL","")&" COMMENT '"&D40&"'" -> ,`` COMMENT '' | BO40: =",A.`"&R40&"` = B.`"&R40&"`" -> ,A.`` = B.`` | BP40: =",`"&R40&"`" -> ,``
B41: 24 | BM41: =",`"&R41&"` "&AC41&" "&IF(AJ41="Y","NOT NULL","")&" COMMENT '"&D41&IF(AT41="","","/"&AT41)&"'" -> ,`` COMMENT '' | BN41: =",`"&R41&"` "&AC41&" "&IF(AJ41="Y","NOT NULL","")&" COMMENT '"&D41&"'" -> ,`` COMMENT '' | BO41: =",A.`"&R41&"` = B.`"&R41&"`" -> ,A.`` = B.`` | BP41: =",`"&R41&"`" -> ,``
B42: 25 | BM42: =",`"&R42&"` "&AC42&" "&IF(AJ42="Y","NOT NULL","")&" COMMENT '"&D42&IF(AT42="","","/"&AT42)&"'" -> ,`` COMMENT '' | BN42: =",`"&R42&"` "&AC42&" "&IF(AJ42="Y","NOT NULL","")&" COMMENT '"&D42&"'" -> ,`` COMMENT '' | BO42: =",A.`"&R42&"` = B.`"&R42&"`" -> ,A.`` = B.`` | BP42: =",`"&R42&"`" -> ,``
B43: 26
B44: 27
B45: 28
B46: 29
B49: ■インデックス情報
B50: No. | D50: Index名 | R50: カラム一覧 | AL50: プライマリキー | AP50: ユニーク | AT50: 備考
B51: 1 | D51: PRIMARY | R51: =IF(_xlfn.XLOOKUP(1,AH:AH,R:R,"",0)="","","`"&_xlfn.XLOOKUP(1,AH:AH,R:R,"",0)&"`")&IF(_xlfn.XLOOKUP(2,AH:AH,R:R,"",0)="","",",`"&_xlfn.XLOOKUP(2,AH:AH,R:R,"",0)&"`")&IF(_xlfn.XLOOKUP(3,AH:AH,R:R,"",0)="","",",`"&_xlfn.XLOOKUP(3,AH:AH,R:R,"",0)&"`")&IF(_xlfn.XLOOKUP(4,AH:AH,R:R,"",0)="","",",`"&_xlfn.XLOOKUP(4,AH:AH,R:R,"",0)&"`")&IF(_xlfn.XLOOKUP(5,AH:AH,R:R,"",0)="","",",`"&_xlfn.XLOOKUP(5,AH:AH,R:R,"",0)&"`")&IF(_xlfn.XLOOKUP(6,AH:AH,R:R,"",0)="","",",`"&_xlfn.XLOOKUP(6,AH:AH,R:R,"",0)&"`")&IF(_xlfn.XLOOKUP(7,AH:AH,R:R,"",0)="","",",`"&_xlfn.XLOOKUP(7,AH:AH,R:R,"",0)&"`")&IF(_xlfn.XLOOKUP(8,AH:AH,R:R,"",0)="","",",`"&_xlfn.XLOOKUP(8,AH:AH,R:R,"",0)&"`") -> `company_code`,`store_code`,`instore_code`,`receipt_no`,`item_no` | AL51: Y | AP51: Y | BM51: =" , PRIMARY KEY ("&IF(_xlfn.XLOOKUP(1,AH:AH,R:R,"",0)="","","`"&_xlfn.XLOOKUP(1,AH:AH,R:R,"",0)&"`")&IF(_xlfn.XLOOKUP(2,AH:AH,R:R,"",0)="","",",`"&_xlfn.XLOOKUP(2,AH:AH,R:R,"",0)&"`")&IF(_xlfn.XLOOKUP(3,AH:AH,R:R,"",0)="","",",`"&_xlfn.XLOOKUP(3,AH:AH,R:R,"",0)&"`")&IF(_xlfn.XLOOKUP(4,AH:AH,R:R,"",0)="","",",`"&_xlfn.XLOOKUP(4,AH:AH,R:R,"",0)&"`")&IF(_xlfn.XLOOKUP(5,AH:AH,R:R,"",0)="","",",`"&_xlfn.XLOOKUP(5,AH:AH,R:R,"",0)&"`")&IF(_xlfn.XLOOKUP(6,AH:AH,R:R,"",0)="","",",`"&_xlfn.XLOOKUP(6,AH:AH,R:R,"",0)&"`")&IF(_xlfn.XLOOKUP(7,AH:AH,R:R,"",0)="","",",`"&_xlfn.XLOOKUP(7,AH:AH,R:R,"",0)&"`")&IF(_xlfn.XLOOKUP(8,AH:AH,R:R,"",0)="","",",`"&_xlfn.XLOOKUP(8,AH:AH,R:R,"",0)&"`")&")," -> , PRIMARY KEY (`company_code`,`store_code`,`instore_code`,`receipt_no`,`item_no`), | BN51: =BM51 -> , PRIMARY KEY (`company_code`,`store_code`,`instore_code`,`receipt_no`,`item_no`),
BM52: KEY `RECORD_ID` (`RECORD_ID`)
BM53: =") ENGINE=InnoDB DEFAULT CHARSET=utf8 COMMENT = '"&$G$9&"';" -> ) ENGINE=InnoDB DEFAULT CHARSET=utf8 COMMENT = '売上情報明細'; | BN53: =") ENGINE=InnoDB DEFAULT CHARSET=utf8 COMMENT = '"&$G$9&"_TMP';" -> ) ENGINE=InnoDB DEFAULT CHARSET=utf8 COMMENT = '売上情報明細_TMP';
B54: トリガー情報
B55: No. | D55: トリガー名 | R55: イベント | U55: タイミング | Y55: 条件 | BM55: ="CREATE TRIGGER `"&G15&"_CR_Date_Time` BEFORE INSERT ON `"&G15&"` FOR EACH ROW SET NEW.record_create_date = CURRENT_DATE, NEW.record_create_time = CURRENT_TIME, NEW.record_update_date = CURRENT_DATE, NEW.record_update_time = CURRENT_TIME;" -> CREATE TRIGGER `_CR_Date_Time` BEFORE INSERT ON `` FOR EACH ROW SET NEW.record_create_date = CURRENT_DATE, NEW.record_create_time = CURRENT_TIME, NEW.record_update_date = CURRENT_DATE, NEW.record_update_time = CURRENT_TIME;
B56: 1 | D56: =G10&"_"&R56&"_"&"trg" -> sales_details_update_trg | R56: update | U56: Before row | Y56: auto_updated_date | BM56: ="CREATE TRIGGER `"&G15&"_UP_Date_Time` BEFORE UPDATE ON `"&G15&"` FOR EACH ROW SET NEW.record_update_date = CURRENT_DATE, NEW.record_update_time = CURRENT_TIME;" -> CREATE TRIGGER `_UP_Date_Time` BEFORE UPDATE ON `` FOR EACH ROW SET NEW.record_update_date = CURRENT_DATE, NEW.record_update_time = CURRENT_TIME;
BM63: , PRIMARY KEY (`CompanyCode`,`StoreCode`,`ReceiptCouponCode`,`PrintFrom`,`MessagePosition`,`MessageLineNo`), | BN63: =BM63 -> , PRIMARY KEY (`CompanyCode`,`StoreCode`,`ReceiptCouponCode`,`PrintFrom`,`MessagePosition`,`MessageLineNo`), | BO63: =",A.`"&R63&"` = B.`"&R63&"`" -> ,A.`` = B.`` | BP63: =",`"&R63&"`" -> ,``
BM64: KEY `RECORD_ID` (`RECORD_ID`) | BO64: =",A.`"&R64&"` = B.`"&R64&"`" -> ,A.`` = B.`` | BP64: =",`"&R64&"`" -> ,``
BM65: ) ENGINE=InnoDB DEFAULT CHARSET=utf8; | BN65: =BM65 -> ) ENGINE=InnoDB DEFAULT CHARSET=utf8; | BO65: =",A.`"&R65&"` = B.`"&R65&"`" -> ,A.`` = B.`` | BP65: =",`"&R65&"`" -> ,``
BM66: ="CREATE TRIGGER `"&G10&"_CR_Date_Time` BEFORE INSERT ON `"&G10&"` FOR EACH ROW SET NEW.record_create_date = CURRENT_DATE, NEW.record_create_time = CURRENT_TIME, NEW.record_update_date = CURRENT_DATE, NEW.record_update_time = CURRENT_TIME;" -> CREATE TRIGGER `sales_details_CR_Date_Time` BEFORE INSERT ON `sales_details` FOR EACH ROW SET NEW.record_create_date = CURRENT_DATE, NEW.record_create_time = CURRENT_TIME, NEW.record_update_date = CURRENT_DATE, NEW.record_update_time = CURRENT_TIME;
BM67: ="CREATE TRIGGER `"&G10&"_UP_Date_Time` BEFORE UPDATE ON `"&G10&"` FOR EACH ROW SET NEW.record_update_date = CURRENT_DATE, NEW.record_update_time = CURRENT_TIME;" -> CREATE TRIGGER `sales_details_UP_Date_Time` BEFORE UPDATE ON `sales_details` FOR EACH ROW SET NEW.record_update_date = CURRENT_DATE, NEW.record_update_time = CURRENT_TIME;

Sheet 売上情報(値引)
A1: システム名 | K1: システム種別 | W1: =IF(表紙!W1="","",表紙!W1) -> DB定義書 | AP1: 作成者 | AT1: 作成日 | AY1: 更新者 | BC1: 更新日 | BH1: 版数
A2: =IF(表紙!A2="","",表紙!A2) -> 現金専用簡易セルフPOS | K2: =IF(表紙!K2="","",表紙!K2) | AP2: =IF(表紙!AP2="","",表紙!AP2) -> きよはら | AT2: =IF(表紙!AT2="","",表紙!AT2) -> 44652 | AY2: =IF(表紙!AY2="","",表紙!AY2) -> Thanh Nguyên | BC2: =IF(表紙!BC2="","",表紙!BC2) -> 45285 | BH2: =IF(表紙!BH2="","",表紙!BH2) -> 0.2
A4: 機能カテゴリ | H4: =IF(表紙!H4="","",表紙!H4) -> 共通 | U4: 項目 | Z4: =IF(表紙!Z4="","",表紙!Z4) | AP4: テンプレート
B7: ■テーブル情報
B8: スキーマ名 | Y8: RDBMS名
B9: 論理名 | G9: 売上情報明細 | Y9: バージョン
B10: 物理名 | G10: sales_details
B11: 備考
B19: ■カラム情報 | BM19: ="DROP TABLE IF EXISTS `"&$G$8&"`.`"&$G$10&"`;" -> DROP TABLE IF EXISTS ``.`sales_details`;
B20: No. | D20: 論理名 | R20: 物理名 | AC20: データ型 | AH20: PK | AJ20: Not Null | AM20: デフォルト | AT20: 備考 | BM20: ="CREATE TABLE `"&$G$8&"`.`"&$G$10&"` (" -> CREATE TABLE ``.`sales_details` ( | BN20: ="CREATE TABLE `TMP`.`"&G10&"` (" -> CREATE TABLE `TMP`.`sales_details` (
B21: 1 | D21: レコードID | R21: RECORD_ID | AC21: BIGINT | AH21: Y | AJ21: Y | AM21: 自動追加 | BM21: ="`"&R21&"` "&AC21&" "&IF(AJ21="Y","NOT NULL","")&" AUTO_INCREMENT COMMENT '"&D21&IF(AT21="","","/"&AT21)&"'" -> `RECORD_ID` BIGINT NOT NULL AUTO_INCREMENT COMMENT 'レコードID' | BO21: =",A.`"&R21&"` = B.`"&R21&"`" -> ,A.`RECORD_ID` = B.`RECORD_ID` | BP21: =",`"&R21&"`" -> ,`RECORD_ID`
B22: 2 | D22: レコード作成日付 | R22: RECORD_CREATE_DATE | AC22: TIMESTAMP | AJ22: Y | AM22: CURRENT_DATE | BM22: =",`"&R22&"` "&AC22&" "&IF(AJ22="Y","NOT NULL","")&" COMMENT '"&D22&IF(AT22="","","/"&AT22)&"'" -> ,`RECORD_CREATE_DATE` TIMESTAMP NOT NULL COMMENT 'レコード作成日付' | BO22: =",A.`"&R22&"` = B.`"&R22&"`" -> ,A.`RECORD_CREATE_DATE` = B.`RECORD_CREATE_DATE` | BP22: =",`"&R22&"`" -> ,`RECORD_CREATE_DATE`
B23: 3 | D23: レコード作成時間 | R23: RECORD_CREATE_TIME | AC23: BIGINT | AJ23: Y | AM23: CURRENT_TIME | BM23: =",`"&R23&"` "&AC23&" "&IF(AJ23="Y","NOT NULL","")&" COMMENT '"&D23&IF(AT23="","","/"&AT23)&"'" -> ,`RECORD_CREATE_TIME` BIGINT NOT NULL COMMENT 'レコード作成時間' | BO23: =",A.`"&R23&"` = B.`"&R23&"`" -> ,A.`RECORD_CREATE_TIME` = B.`RECORD_CREATE_TIME` | BP23: =",`"&R23&"`" -> ,`RECORD_CREATE_TIME`
B24: 4 | D24: レコード更新日付 | R24: RECORD_UPDATE_DATE | AC24: TIMESTAMP | AJ24: Y | AM24: CURRENT_DATE | AT24: トリガーにより更新 | BM24: =",`"&R24&"` "&AC24&" "&IF(AJ24="Y","NOT NULL","")&" COMMENT '"&D24&IF(AT24="","","/"&AT24)&"'" -> ,`RECORD_UPDATE_DATE` TIMESTAMP NOT NULL COMMENT 'レコード更新日付/トリガーにより更新' | BO24: =",A.`"&R24&"` = B.`"&R24&"`" -> ,A.`RECORD_UPDATE_DATE` = B.`RECORD_UPDATE_DATE` | BP24: =",`"&R24&"`" -> ,`RECORD_UPDATE_DATE`
B25: 5 | D25: レコード更新時間 | R25: RECORD_UPDATE_TIME | AC25: BIGINT | AJ25: Y | AM25: CURRENT_TIME | AT25: トリガーにより更新 | BM25: =",`"&R25&"` "&AC25&" "&IF(AJ25="Y","NOT NULL","")&" COMMENT '"&D25&IF(AT25="","","/"&AT25)&"'" -> ,`RECORD_UPDATE_TIME` BIGINT NOT NULL COMMENT 'レコード更新時間/トリガーにより更新' | BO25: =",A.`"&R25&"` = B.`"&R25&"`" -> ,A.`RECORD_UPDATE_TIME` = B.`RECORD_UPDATE_TIME` | BP25: =",`"&R25&"`" -> ,`RECORD_UPDATE_TIME`
B26: 6 | D26: レコード無効フラグ | R26: RECORD_VOID_FLAG | AC26: BOOL | AJ26: Y | AM26: "" | AT26: true:有効 / false:無効 | BM26: =",`"&R26&"` "&AC26&" "&IF(AJ26="Y","NOT NULL","")&" COMMENT '"&D26&IF(AT26="","","/"&AT26)&"'" -> ,`RECORD_VOID_FLAG` BOOL NOT NULL COMMENT 'レコード無効フラグ/true:有効 / false:無効' | BN26: `CLASS` VARCHAR ( 1 ) NOT NULL COMMENT '処理区分', | BO26: =",A.`"&R26&"` = B.`"&R26&"`" -> ,A.`RECORD_VOID_FLAG` = B.`RECORD_VOID_FLAG` | BP26: =",`"&R26&"`" -> ,`RECORD_VOID_FLAG`
B27: 7 | D27: 企業コード | R27: company_code | AC27: char(3) | BM27: =",`"&R27&"` "&AC27&" "&IF(AJ27="Y","NOT NULL","")&" COMMENT '"&D27&IF(AT27="","","/"&AT27)&"'" -> ,`company_code` char(3) COMMENT '企業コード' | BN27: =",`"&R27&"` "&AC27&" "&IF(AJ27="Y","NOT NULL","")&" COMMENT '"&D27&"'" -> ,`company_code` char(3) COMMENT '企業コード' | BO27: =",A.`"&R27&"` = B.`"&R27&"`" -> ,A.`company_code` = B.`company_code` | BP27: =",`"&R27&"`" -> ,`company_code`
B28: 8 | D28: 店舗コード | R28: store_code | AC28: char(5) | BM28: =",`"&R28&"` "&AC28&" "&IF(AJ28="Y","NOT NULL","")&" COMMENT '"&D28&IF(AT28="","","/"&AT28)&"'" -> ,`store_code` char(5) COMMENT '店舗コード' | BN28: =",`"&R28&"` "&AC28&" "&IF(AJ28="Y","NOT NULL","")&" COMMENT '"&D28&"'" -> ,`store_code` char(5) COMMENT '店舗コード' | BO28: =",A.`"&R28&"` = B.`"&R28&"`" -> ,A.`store_code` = B.`store_code` | BP28: =",`"&R28&"`" -> ,`store_code`
B29: 9 | D29: レジ番号 | R29: instore_code | AC29: char(5) | BM29: =",`"&R29&"` "&AC29&" "&IF(AJ29="Y","NOT NULL","")&" COMMENT '"&D29&IF(AT29="","","/"&AT29)&"'" -> ,`instore_code` char(5) COMMENT 'レジ番号' | BN29: =",`"&R29&"` "&AC29&" "&IF(AJ29="Y","NOT NULL","")&" COMMENT '"&D29&"'" -> ,`instore_code` char(5) COMMENT 'レジ番号' | BO29: =",A.`"&R29&"` = B.`"&R29&"`" -> ,A.`instore_code` = B.`instore_code` | BP29: =",`"&R29&"`" -> ,`instore_code`
B30: 13 | D30: 取引確定日時<取引確定後> | R30: record_datetime | AC30: char(16) | BM30: =",`"&R30&"` "&AC30&" "&IF(AJ30="Y","NOT NULL","")&" COMMENT '"&D30&IF(AT30="","","/"&AT30)&"'" -> ,`record_datetime` char(16) COMMENT '取引確定日時<取引確定後>' | BN30: =",`"&R30&"` "&AC30&" "&IF(AJ30="Y","NOT NULL","")&" COMMENT '"&D30&"'" -> ,`record_datetime` char(16) COMMENT '取引確定日時<取引確定後>' | BO30: =",A.`"&R30&"` = B.`"&R30&"`" -> ,A.`record_datetime` = B.`record_datetime` | BP30: =",`"&R30&"`" -> ,`record_datetime`
B31: 14 | D31: ジャーナルNO<取引確定後> | R31: journal_no | AC31: char(10) | BM31: =",`"&R31&"` "&AC31&" "&IF(AJ31="Y","NOT NULL","")&" COMMENT '"&D31&IF(AT31="","","/"&AT31)&"'" -> ,`journal_no` char(10) COMMENT 'ジャーナルNO<取引確定後>' | BN31: =",`"&R31&"` "&AC31&" "&IF(AJ31="Y","NOT NULL","")&" COMMENT '"&D31&"'" -> ,`journal_no` char(10) COMMENT 'ジャーナルNO<取引確定後>' | BO31: =",A.`"&R31&"` = B.`"&R31&"`" -> ,A.`journal_no` = B.`journal_no` | BP31: =",`"&R31&"`" -> ,`journal_no`
B32: 15 | D32: レシートNO<取引確定後> | R32: receipt_no | AC32: char(10) | BM32: =",`"&R32&"` "&AC32&" "&IF(AJ32="Y","NOT NULL","")&" COMMENT '"&D32&IF(AT32="","","/"&AT32)&"'" -> ,`receipt_no` char(10) COMMENT 'レシートNO<取引確定後>' | BN32: =",`"&R32&"` "&AC32&" "&IF(AJ32="Y","NOT NULL","")&" COMMENT '"&D32&"'" -> ,`receipt_no` char(10) COMMENT 'レシートNO<取引確定後>' | BO32: =",A.`"&R32&"` = B.`"&R32&"`" -> ,A.`receipt_no` = B.`receipt_no` | BP32: =",`"&R32&"`" -> ,`receipt_no`
B33: 16 | D33: 明細行番号 | R33: item_no | AC33: string | AT33: true : 確認済み | BM33: =",`"&R33&"` "&AC33&" "&IF(AJ33="Y","NOT NULL","")&" COMMENT '"&D33&IF(AT33="","","/"&AT33)&"'" -> ,`item_no` string COMMENT '明細行番号/true : 確認済み' | BN33: =",`"&R33&"` "&AC33&" "&IF(AJ33="Y","NOT NULL","")&" COMMENT '"&D33&"'" -> ,`item_no` string COMMENT '明細行番号' | BO33: =",A.`"&R33&"` = B.`"&R33&"`" -> ,A.`item_no` = B.`item_no` | BP33: =",`"&R33&"`" -> ,`item_no`
B34: 17 | D34: Scan&Go アカウントID | R34: account_id | AC34: string | BM34: =",`"&R34&"` "&AC34&" "&IF(AJ34="Y","NOT NULL","")&" COMMENT '"&D34&IF(AT34="","","/"&AT34)&"'" -> ,`account_id` string COMMENT 'Scan&Go アカウントID' | BN34: =",`"&R34&"` "&AC34&" "&IF(AJ34="Y","NOT NULL","")&" COMMENT '"&D34&"'" -> ,`account_id` string COMMENT 'Scan&Go アカウントID' | BO34: =",A.`"&R34&"` = B.`"&R34&"`" -> ,A.`account_id` = B.`account_id` | BP34: =",`"&R34&"`" -> ,`account_id`
B35: 18 | D35: Scan&Go アカウント名 | R35: account_name | AC35: string | BM35: =",`"&R35&"` "&AC35&" "&IF(AJ35="Y","NOT NULL","")&" COMMENT '"&D35&IF(AT35="","","/"&AT35)&"'" -> ,`account_name` string COMMENT 'Scan&Go アカウント名' | BN35: =",`"&R35&"` "&AC35&" "&IF(AJ35="Y","NOT NULL","")&" COMMENT '"&D35&"'" -> ,`account_name` string COMMENT 'Scan&Go アカウント名' | BO35: =",A.`"&R35&"` = B.`"&R35&"`" -> ,A.`account_name` = B.`account_name` | BP35: =",`"&R35&"`" -> ,`account_name`
B36: 19 | D36: 明細合計金額 | R36: item_total_price_fmt | AC36: string | BM36: =",`"&R36&"` "&AC36&" "&IF(AJ36="Y","NOT NULL","")&" COMMENT '"&D36&IF(AT36="","","/"&AT36)&"'" -> ,`item_total_price_fmt` string COMMENT '明細合計金額' | BN36: =",`"&R36&"` "&AC36&" "&IF(AJ36="Y","NOT NULL","")&" COMMENT '"&D36&"'" -> ,`item_total_price_fmt` string COMMENT '明細合計金額' | BO36: =",A.`"&R36&"` = B.`"&R36&"`" -> ,A.`item_total_price_fmt` = B.`item_total_price_fmt` | BP36: =",`"&R36&"`" -> ,`item_total_price_fmt`
B37: 20 | D37: まとめ値引金額 | R37: mm_discount_price_fmt | AC37: string | BM37: =",`"&R37&"` "&AC37&" "&IF(AJ37="Y","NOT NULL","")&" COMMENT '"&D37&IF(AT37="","","/"&AT37)&"'" -> ,`mm_discount_price_fmt` string COMMENT 'まとめ値引金額' | BN37: =",`"&R37&"` "&AC37&" "&IF(AJ37="Y","NOT NULL","")&" COMMENT '"&D37&"'" -> ,`mm_discount_price_fmt` string COMMENT 'まとめ値引金額' | BO37: =",A.`"&R37&"` = B.`"&R37&"`" -> ,A.`mm_discount_price_fmt` = B.`mm_discount_price_fmt` | BP37: =",`"&R37&"`" -> ,`mm_discount_price_fmt`
B38: 21 | D38: 小計金額 | R38: subtotal_price_fmt | AC38: string | BM38: =",`"&R38&"` "&AC38&" "&IF(AJ38="Y","NOT NULL","")&" COMMENT '"&D38&IF(AT38="","","/"&AT38)&"'" -> ,`subtotal_price_fmt` string COMMENT '小計金額' | BN38: =",`"&R38&"` "&AC38&" "&IF(AJ38="Y","NOT NULL","")&" COMMENT '"&D38&"'" -> ,`subtotal_price_fmt` string COMMENT '小計金額' | BO38: =",A.`"&R38&"` = B.`"&R38&"`" -> ,A.`subtotal_price_fmt` = B.`subtotal_price_fmt` | BP38: =",`"&R38&"`" -> ,`subtotal_price_fmt`
B39: 22 | D39: 小計値引金額 | R39: subtotal_discount_price_fmt | AC39: string | BM39: =",`"&R39&"` "&AC39&" "&IF(AJ39="Y","NOT NULL","")&" COMMENT '"&D39&IF(AT39="","","/"&AT39)&"'" -> ,`subtotal_discount_price_fmt` string COMMENT '小計値引金額' | BN39: =",`"&R39&"` "&AC39&" "&IF(AJ39="Y","NOT NULL","")&" COMMENT '"&D39&"'" -> ,`subtotal_discount_price_fmt` string COMMENT '小計値引金額' | BO39: =",A.`"&R39&"` = B.`"&R39&"`" -> ,A.`subtotal_discount_price_fmt` = B.`subtotal_discount_price_fmt` | BP39: =",`"&R39&"`" -> ,`subtotal_discount_price_fmt`
B40: 23 | D40: 外税合計 | R40: total_tax_excluded_fmt | AC40: string | BM40: =",`"&R40&"` "&AC40&" "&IF(AJ40="Y","NOT NULL","")&" COMMENT '"&D40&IF(AT40="","","/"&AT40)&"'" -> ,`total_tax_excluded_fmt` string COMMENT '外税合計' | BN40: =",`"&R40&"` "&AC40&" "&IF(AJ40="Y","NOT NULL","")&" COMMENT '"&D40&"'" -> ,`total_tax_excluded_fmt` string COMMENT '外税合計' | BO40: =",A.`"&R40&"` = B.`"&R40&"`" -> ,A.`total_tax_excluded_fmt` = B.`total_tax_excluded_fmt` | BP40: =",`"&R40&"`" -> ,`total_tax_excluded_fmt`
B41: 24 | D41: 合計金額 （=小計金額 - 小計値引金額 + 外税合計） | R41: total_price_fmt | AC41: string | BM41: =",`"&R41&"` "&AC41&" "&IF(AJ41="Y","NOT NULL","")&" COMMENT '"&D41&IF(AT41="","","/"&AT41)&"'" -> ,`total_price_fmt` string COMMENT '合計金額 （=小計金額 - 小計値引金額 + 外税合計）' | BN41: =",`"&R41&"` "&AC41&" "&IF(AJ41="Y","NOT NULL","")&" COMMENT '"&D41&"'" -> ,`total_price_fmt` string COMMENT '合計金額 （=小計金額 - 小計値引金額 + 外税合計）' | BO41: =",A.`"&R41&"` = B.`"&R41&"`" -> ,A.`total_price_fmt` = B.`total_price_fmt` | BP41: =",`"&R41&"`" -> ,`total_price_fmt`
B42: 25 | D42: 合計点数 | R42: total_quantity_fmt | AC42: string | BM42: =",`"&R42&"` "&AC42&" "&IF(AJ42="Y","NOT NULL","")&" COMMENT '"&D42&IF(AT42="","","/"&AT42)&"'" -> ,`total_quantity_fmt` string COMMENT '合計点数' | BN42: =",`"&R42&"` "&AC42&" "&IF(AJ42="Y","NOT NULL","")&" COMMENT '"&D42&"'" -> ,`total_quantity_fmt` string COMMENT '合計点数' | BO42: =",A.`"&R42&"` = B.`"&R42&"`" -> ,A.`total_quantity_fmt` = B.`total_quantity_fmt` | BP42: =",`"&R42&"`" -> ,`total_quantity_fmt`
B43: 26
B44: 27
B45: 28
B46: 29
B49: ■インデックス情報
B50: No. | D50: Index名 | R50: カラム一覧 | AL50: プライマリキー | AP50: ユニーク | AT50: 備考
B51: 1 | D51: PRIMARY | R51: =IF(_xlfn.XLOOKUP(1,AH:AH,R:R,"",0)="","","`"&_xlfn.XLOOKUP(1,AH:AH,R:R,"",0)&"`")&IF(_xlfn.XLOOKUP(2,AH:AH,R:R,"",0)="","",",`"&_xlfn.XLOOKUP(2,AH:AH,R:R,"",0)&"`")&IF(_xlfn.XLOOKUP(3,AH:AH,R:R,"",0)="","",",`"&_xlfn.XLOOKUP(3,AH:AH,R:R,"",0)&"`")&IF(_xlfn.XLOOKUP(4,AH:AH,R:R,"",0)="","",",`"&_xlfn.XLOOKUP(4,AH:AH,R:R,"",0)&"`")&IF(_xlfn.XLOOKUP(5,AH:AH,R:R,"",0)="","",",`"&_xlfn.XLOOKUP(5,AH:AH,R:R,"",0)&"`")&IF(_xlfn.XLOOKUP(6,AH:AH,R:R,"",0)="","",",`"&_xlfn.XLOOKUP(6,AH:AH,R:R,"",0)&"`")&IF(_xlfn.XLOOKUP(7,AH:AH,R:R,"",0)="","",",`"&_xlfn.XLOOKUP(7,AH:AH,R:R,"",0)&"`")&IF(_xlfn.XLOOKUP(8,AH:AH,R:R,"",0)="","",",`"&_xlfn.XLOOKUP(8,AH:AH,R:R,"",0)&"`") | AL51: Y | AP51: Y | BM51: =" , PRIMARY KEY ("&IF(_xlfn.XLOOKUP(1,AH:AH,R:R,"",0)="","","`"&_xlfn.XLOOKUP(1,AH:AH,R:R,"",0)&"`")&IF(_xlfn.XLOOKUP(2,AH:AH,R:R,"",0)="","",",`"&_xlfn.XLOOKUP(2,AH:AH,R:R,"",0)&"`")&IF(_xlfn.XLOOKUP(3,AH:AH,R:R,"",0)="","",",`"&_xlfn.XLOOKUP(3,AH:AH,R:R,"",0)&"`")&IF(_xlfn.XLOOKUP(4,AH:AH,R:R,"",0)="","",",`"&_xlfn.XLOOKUP(4,AH:AH,R:R,"",0)&"`")&IF(_xlfn.XLOOKUP(5,AH:AH,R:R,"",0)="","",",`"&_xlfn.XLOOKUP(5,AH:AH,R:R,"",0)&"`")&IF(_xlfn.XLOOKUP(6,AH:AH,R:R,"",0)="","",",`"&_xlfn.XLOOKUP(6,AH:AH,R:R,"",0)&"`")&IF(_xlfn.XLOOKUP(7,AH:AH,R:R,"",0)="","",",`"&_xlfn.XLOOKUP(7,AH:AH,R:R,"",0)&"`")&IF(_xlfn.XLOOKUP(8,AH:AH,R:R,"",0)="","",",`"&_xlfn.XLOOKUP(8,AH:AH,R:R,"",0)&"`")&")," -> , PRIMARY KEY (), | BN51: =BM51 -> , PRIMARY KEY (),
BM52: KEY `RECORD_ID` (`RECORD_ID`)
BM53: =") ENGINE=InnoDB DEFAULT CHARSET=utf8 COMMENT = '"&$G$9&"';" -> ) ENGINE=InnoDB DEFAULT CHARSET=utf8 COMMENT = '売上情報明細'; | BN53: =") ENGINE=InnoDB DEFAULT CHARSET=utf8 COMMENT = '"&$G$9&"_TMP';" -> ) ENGINE=InnoDB DEFAULT CHARSET=utf8 COMMENT = '売上情報明細_TMP';
B54: トリガー情報
B55: No. | D55: トリガー名 | R55: イベント | U55: タイミング | Y55: 条件 | BM55: ="CREATE TRIGGER `"&G15&"_CR_Date_Time` BEFORE INSERT ON `"&G15&"` FOR EACH ROW SET NEW.record_create_date = CURRENT_DATE, NEW.record_create_time = CURRENT_TIME, NEW.record_update_date = CURRENT_DATE, NEW.record_update_time = CURRENT_TIME;" -> CREATE TRIGGER `_CR_Date_Time` BEFORE INSERT ON `` FOR EACH ROW SET NEW.record_create_date = CURRENT_DATE, NEW.record_create_time = CURRENT_TIME, NEW.record_update_date = CURRENT_DATE, NEW.record_update_time = CURRENT_TIME;
B56: 1 | D56: =G10&"_"&R56&"_"&"trg" -> sales_details_update_trg | R56: update | U56: Before row | Y56: auto_updated_date | BM56: ="CREATE TRIGGER `"&G15&"_UP_Date_Time` BEFORE UPDATE ON `"&G15&"` FOR EACH ROW SET NEW.record_update_date = CURRENT_DATE, NEW.record_update_time = CURRENT_TIME;" -> CREATE TRIGGER `_UP_Date_Time` BEFORE UPDATE ON `` FOR EACH ROW SET NEW.record_update_date = CURRENT_DATE, NEW.record_update_time = CURRENT_TIME;
BM63: , PRIMARY KEY (`CompanyCode`,`StoreCode`,`ReceiptCouponCode`,`PrintFrom`,`MessagePosition`,`MessageLineNo`), | BN63: =BM63 -> , PRIMARY KEY (`CompanyCode`,`StoreCode`,`ReceiptCouponCode`,`PrintFrom`,`MessagePosition`,`MessageLineNo`), | BO63: =",A.`"&R63&"` = B.`"&R63&"`" -> ,A.`` = B.`` | BP63: =",`"&R63&"`" -> ,``
BM64: KEY `RECORD_ID` (`RECORD_ID`) | BO64: =",A.`"&R64&"` = B.`"&R64&"`" -> ,A.`` = B.`` | BP64: =",`"&R64&"`" -> ,``
BM65: ) ENGINE=InnoDB DEFAULT CHARSET=utf8; | BN65: =BM65 -> ) ENGINE=InnoDB DEFAULT CHARSET=utf8; | BO65: =",A.`"&R65&"` = B.`"&R65&"`" -> ,A.`` = B.`` | BP65: =",`"&R65&"`" -> ,``
BM66: ="CREATE TRIGGER `"&G10&"_CR_Date_Time` BEFORE INSERT ON `"&G10&"` FOR EACH ROW SET NEW.record_create_date = CURRENT_DATE, NEW.record_create_time = CURRENT_TIME, NEW.record_update_date = CURRENT_DATE, NEW.record_update_time = CURRENT_TIME;" -> CREATE TRIGGER `sales_details_CR_Date_Time` BEFORE INSERT ON `sales_details` FOR EACH ROW SET NEW.record_create_date = CURRENT_DATE, NEW.record_create_time = CURRENT_TIME, NEW.record_update_date = CURRENT_DATE, NEW.record_update_time = CURRENT_TIME;
BM67: ="CREATE TRIGGER `"&G10&"_UP_Date_Time` BEFORE UPDATE ON `"&G10&"` FOR EACH ROW SET NEW.record_update_date = CURRENT_DATE, NEW.record_update_time = CURRENT_TIME;" -> CREATE TRIGGER `sales_details_UP_Date_Time` BEFORE UPDATE ON `sales_details` FOR EACH ROW SET NEW.record_update_date = CURRENT_DATE, NEW.record_update_time = CURRENT_TIME;

Sheet 売上情報(支払)
A1: システム名 | K1: システム種別 | W1: =IF(表紙!W1="","",表紙!W1) -> DB定義書 | AP1: 作成者 | AT1: 作成日 | AY1: 更新者 | BC1: 更新日 | BH1: 版数
A2: =IF(表紙!A2="","",表紙!A2) -> 現金専用簡易セルフPOS | K2: =IF(表紙!K2="","",表紙!K2) | AP2: =IF(表紙!AP2="","",表紙!AP2) -> きよはら | AT2: =IF(表紙!AT2="","",表紙!AT2) -> 44652 | AY2: =IF(表紙!AY2="","",表紙!AY2) -> Thanh Nguyên | BC2: =IF(表紙!BC2="","",表紙!BC2) -> 45285 | BH2: =IF(表紙!BH2="","",表紙!BH2) -> 0.2
A4: 機能カテゴリ | H4: =IF(表紙!H4="","",表紙!H4) -> 共通 | U4: 項目 | Z4: =IF(表紙!Z4="","",表紙!Z4) | AP4: テンプレート
B7: ■テーブル情報
B8: スキーマ名 | Y8: RDBMS名
B9: 論理名 | G9: 売上情報明細 | Y9: バージョン
B10: 物理名 | G10: sales_details
B11: 備考
B19: ■カラム情報 | BM19: ="DROP TABLE IF EXISTS `"&$G$8&"`.`"&$G$10&"`;" -> DROP TABLE IF EXISTS ``.`sales_details`;
B20: No. | D20: 論理名 | R20: 物理名 | AC20: データ型 | AH20: PK | AJ20: Not Null | AM20: デフォルト | AT20: 備考 | BM20: ="CREATE TABLE `"&$G$8&"`.`"&$G$10&"` (" -> CREATE TABLE ``.`sales_details` ( | BN20: ="CREATE TABLE `TMP`.`"&G10&"` (" -> CREATE TABLE `TMP`.`sales_details` (
B21: 1 | D21: レコードID | R21: RECORD_ID | AC21: BIGINT | AH21: Y | AJ21: Y | AM21: 自動追加 | BM21: ="`"&R21&"` "&AC21&" "&IF(AJ21="Y","NOT NULL","")&" AUTO_INCREMENT COMMENT '"&D21&IF(AT21="","","/"&AT21)&"'" -> `RECORD_ID` BIGINT NOT NULL AUTO_INCREMENT COMMENT 'レコードID' | BO21: =",A.`"&R21&"` = B.`"&R21&"`" -> ,A.`RECORD_ID` = B.`RECORD_ID` | BP21: =",`"&R21&"`" -> ,`RECORD_ID`
B22: 2 | D22: レコード作成日付 | R22: RECORD_CREATE_DATE | AC22: TIMESTAMP | AJ22: Y | AM22: CURRENT_DATE | BM22: =",`"&R22&"` "&AC22&" "&IF(AJ22="Y","NOT NULL","")&" COMMENT '"&D22&IF(AT22="","","/"&AT22)&"'" -> ,`RECORD_CREATE_DATE` TIMESTAMP NOT NULL COMMENT 'レコード作成日付' | BO22: =",A.`"&R22&"` = B.`"&R22&"`" -> ,A.`RECORD_CREATE_DATE` = B.`RECORD_CREATE_DATE` | BP22: =",`"&R22&"`" -> ,`RECORD_CREATE_DATE`
B23: 3 | D23: レコード作成時間 | R23: RECORD_CREATE_TIME | AC23: BIGINT | AJ23: Y | AM23: CURRENT_TIME | BM23: =",`"&R23&"` "&AC23&" "&IF(AJ23="Y","NOT NULL","")&" COMMENT '"&D23&IF(AT23="","","/"&AT23)&"'" -> ,`RECORD_CREATE_TIME` BIGINT NOT NULL COMMENT 'レコード作成時間' | BO23: =",A.`"&R23&"` = B.`"&R23&"`" -> ,A.`RECORD_CREATE_TIME` = B.`RECORD_CREATE_TIME` | BP23: =",`"&R23&"`" -> ,`RECORD_CREATE_TIME`
B24: 4 | D24: レコード更新日付 | R24: RECORD_UPDATE_DATE | AC24: TIMESTAMP | AJ24: Y | AM24: CURRENT_DATE | AT24: トリガーにより更新 | BM24: =",`"&R24&"` "&AC24&" "&IF(AJ24="Y","NOT NULL","")&" COMMENT '"&D24&IF(AT24="","","/"&AT24)&"'" -> ,`RECORD_UPDATE_DATE` TIMESTAMP NOT NULL COMMENT 'レコード更新日付/トリガーにより更新' | BO24: =",A.`"&R24&"` = B.`"&R24&"`" -> ,A.`RECORD_UPDATE_DATE` = B.`RECORD_UPDATE_DATE` | BP24: =",`"&R24&"`" -> ,`RECORD_UPDATE_DATE`
B25: 5 | D25: レコード更新時間 | R25: RECORD_UPDATE_TIME | AC25: BIGINT | AJ25: Y | AM25: CURRENT_TIME | AT25: トリガーにより更新 | BM25: =",`"&R25&"` "&AC25&" "&IF(AJ25="Y","NOT NULL","")&" COMMENT '"&D25&IF(AT25="","","/"&AT25)&"'" -> ,`RECORD_UPDATE_TIME` BIGINT NOT NULL COMMENT 'レコード更新時間/トリガーにより更新' | BO25: =",A.`"&R25&"` = B.`"&R25&"`" -> ,A.`RECORD_UPDATE_TIME` = B.`RECORD_UPDATE_TIME` | BP25: =",`"&R25&"`" -> ,`RECORD_UPDATE_TIME`
B26: 6 | D26: レコード無効フラグ | R26: RECORD_VOID_FLAG | AC26: BOOL | AJ26: Y | AM26: "" | AT26: true:有効 / false:無効 | BM26: =",`"&R26&"` "&AC26&" "&IF(AJ26="Y","NOT NULL","")&" COMMENT '"&D26&IF(AT26="","","/"&AT26)&"'" -> ,`RECORD_VOID_FLAG` BOOL NOT NULL COMMENT 'レコード無効フラグ/true:有効 / false:無効' | BN26: `CLASS` VARCHAR ( 1 ) NOT NULL COMMENT '処理区分', | BO26: =",A.`"&R26&"` = B.`"&R26&"`" -> ,A.`RECORD_VOID_FLAG` = B.`RECORD_VOID_FLAG` | BP26: =",`"&R26&"`" -> ,`RECORD_VOID_FLAG`
B27: 7 | D27: 企業コード | R27: company_code | AC27: char(3) | BM27: =",`"&R27&"` "&AC27&" "&IF(AJ27="Y","NOT NULL","")&" COMMENT '"&D27&IF(AT27="","","/"&AT27)&"'" -> ,`company_code` char(3) COMMENT '企業コード' | BN27: =",`"&R27&"` "&AC27&" "&IF(AJ27="Y","NOT NULL","")&" COMMENT '"&D27&"'" -> ,`company_code` char(3) COMMENT '企業コード' | BO27: =",A.`"&R27&"` = B.`"&R27&"`" -> ,A.`company_code` = B.`company_code` | BP27: =",`"&R27&"`" -> ,`company_code`
B28: 8 | D28: 店舗コード | R28: store_code | AC28: char(5) | BM28: =",`"&R28&"` "&AC28&" "&IF(AJ28="Y","NOT NULL","")&" COMMENT '"&D28&IF(AT28="","","/"&AT28)&"'" -> ,`store_code` char(5) COMMENT '店舗コード' | BN28: =",`"&R28&"` "&AC28&" "&IF(AJ28="Y","NOT NULL","")&" COMMENT '"&D28&"'" -> ,`store_code` char(5) COMMENT '店舗コード' | BO28: =",A.`"&R28&"` = B.`"&R28&"`" -> ,A.`store_code` = B.`store_code` | BP28: =",`"&R28&"`" -> ,`store_code`
B29: 9 | D29: レジ番号 | R29: instore_code | AC29: char(5) | BM29: =",`"&R29&"` "&AC29&" "&IF(AJ29="Y","NOT NULL","")&" COMMENT '"&D29&IF(AT29="","","/"&AT29)&"'" -> ,`instore_code` char(5) COMMENT 'レジ番号' | BN29: =",`"&R29&"` "&AC29&" "&IF(AJ29="Y","NOT NULL","")&" COMMENT '"&D29&"'" -> ,`instore_code` char(5) COMMENT 'レジ番号' | BO29: =",A.`"&R29&"` = B.`"&R29&"`" -> ,A.`instore_code` = B.`instore_code` | BP29: =",`"&R29&"`" -> ,`instore_code`
B30: 13 | D30: 取引確定日時<取引確定後> | R30: record_datetime | AC30: char(16) | BM30: =",`"&R30&"` "&AC30&" "&IF(AJ30="Y","NOT NULL","")&" COMMENT '"&D30&IF(AT30="","","/"&AT30)&"'" -> ,`record_datetime` char(16) COMMENT '取引確定日時<取引確定後>' | BN30: =",`"&R30&"` "&AC30&" "&IF(AJ30="Y","NOT NULL","")&" COMMENT '"&D30&"'" -> ,`record_datetime` char(16) COMMENT '取引確定日時<取引確定後>' | BO30: =",A.`"&R30&"` = B.`"&R30&"`" -> ,A.`record_datetime` = B.`record_datetime` | BP30: =",`"&R30&"`" -> ,`record_datetime`
B31: 14 | D31: ジャーナルNO<取引確定後> | R31: journal_no | AC31: char(10) | BM31: =",`"&R31&"` "&AC31&" "&IF(AJ31="Y","NOT NULL","")&" COMMENT '"&D31&IF(AT31="","","/"&AT31)&"'" -> ,`journal_no` char(10) COMMENT 'ジャーナルNO<取引確定後>' | BN31: =",`"&R31&"` "&AC31&" "&IF(AJ31="Y","NOT NULL","")&" COMMENT '"&D31&"'" -> ,`journal_no` char(10) COMMENT 'ジャーナルNO<取引確定後>' | BO31: =",A.`"&R31&"` = B.`"&R31&"`" -> ,A.`journal_no` = B.`journal_no` | BP31: =",`"&R31&"`" -> ,`journal_no`
B32: 15 | D32: レシートNO<取引確定後> | R32: receipt_no | AC32: char(10) | BM32: =",`"&R32&"` "&AC32&" "&IF(AJ32="Y","NOT NULL","")&" COMMENT '"&D32&IF(AT32="","","/"&AT32)&"'" -> ,`receipt_no` char(10) COMMENT 'レシートNO<取引確定後>' | BN32: =",`"&R32&"` "&AC32&" "&IF(AJ32="Y","NOT NULL","")&" COMMENT '"&D32&"'" -> ,`receipt_no` char(10) COMMENT 'レシートNO<取引確定後>' | BO32: =",A.`"&R32&"` = B.`"&R32&"`" -> ,A.`receipt_no` = B.`receipt_no` | BP32: =",`"&R32&"`" -> ,`receipt_no`
B33: 16 | D33: 明細行番号 | R33: item_no | AC33: string | AT33: true : 確認済み | BM33: =",`"&R33&"` "&AC33&" "&IF(AJ33="Y","NOT NULL","")&" COMMENT '"&D33&IF(AT33="","","/"&AT33)&"'" -> ,`item_no` string COMMENT '明細行番号/true : 確認済み' | BN33: =",`"&R33&"` "&AC33&" "&IF(AJ33="Y","NOT NULL","")&" COMMENT '"&D33&"'" -> ,`item_no` string COMMENT '明細行番号' | BO33: =",A.`"&R33&"` = B.`"&R33&"`" -> ,A.`item_no` = B.`item_no` | BP33: =",`"&R33&"`" -> ,`item_no`
B34: 17 | BM34: =",`"&R34&"` "&AC34&" "&IF(AJ34="Y","NOT NULL","")&" COMMENT '"&D34&IF(AT34="","","/"&AT34)&"'" -> ,`` COMMENT '' | BN34: =",`"&R34&"` "&AC34&" "&IF(AJ34="Y","NOT NULL","")&" COMMENT '"&D34&"'" -> ,`` COMMENT '' | BO34: =",A.`"&R34&"` = B.`"&R34&"`" -> ,A.`` = B.`` | BP34: =",`"&R34&"`" -> ,``
B35: 18 | BM35: =",`"&R35&"` "&AC35&" "&IF(AJ35="Y","NOT NULL","")&" COMMENT '"&D35&IF(AT35="","","/"&AT35)&"'" -> ,`` COMMENT '' | BN35: =",`"&R35&"` "&AC35&" "&IF(AJ35="Y","NOT NULL","")&" COMMENT '"&D35&"'" -> ,`` COMMENT '' | BO35: =",A.`"&R35&"` = B.`"&R35&"`" -> ,A.`` = B.`` | BP35: =",`"&R35&"`" -> ,``
B36: 19 | BM36: =",`"&R36&"` "&AC36&" "&IF(AJ36="Y","NOT NULL","")&" COMMENT '"&D36&IF(AT36="","","/"&AT36)&"'" -> ,`` COMMENT '' | BN36: =",`"&R36&"` "&AC36&" "&IF(AJ36="Y","NOT NULL","")&" COMMENT '"&D36&"'" -> ,`` COMMENT '' | BO36: =",A.`"&R36&"` = B.`"&R36&"`" -> ,A.`` = B.`` | BP36: =",`"&R36&"`" -> ,``
B37: 20 | BM37: =",`"&R37&"` "&AC37&" "&IF(AJ37="Y","NOT NULL","")&" COMMENT '"&D37&IF(AT37="","","/"&AT37)&"'" -> ,`` COMMENT '' | BN37: =",`"&R37&"` "&AC37&" "&IF(AJ37="Y","NOT NULL","")&" COMMENT '"&D37&"'" -> ,`` COMMENT '' | BO37: =",A.`"&R37&"` = B.`"&R37&"`" -> ,A.`` = B.`` | BP37: =",`"&R37&"`" -> ,``
B38: 21 | BM38: =",`"&R38&"` "&AC38&" "&IF(AJ38="Y","NOT NULL","")&" COMMENT '"&D38&IF(AT38="","","/"&AT38)&"'" -> ,`` COMMENT '' | BN38: =",`"&R38&"` "&AC38&" "&IF(AJ38="Y","NOT NULL","")&" COMMENT '"&D38&"'" -> ,`` COMMENT '' | BO38: =",A.`"&R38&"` = B.`"&R38&"`" -> ,A.`` = B.`` | BP38: =",`"&R38&"`" -> ,``
B39: 22 | BM39: =",`"&R39&"` "&AC39&" "&IF(AJ39="Y","NOT NULL","")&" COMMENT '"&D39&IF(AT39="","","/"&AT39)&"'" -> ,`` COMMENT '' | BN39: =",`"&R39&"` "&AC39&" "&IF(AJ39="Y","NOT NULL","")&" COMMENT '"&D39&"'" -> ,`` COMMENT '' | BO39: =",A.`"&R39&"` = B.`"&R39&"`" -> ,A.`` = B.`` | BP39: =",`"&R39&"`" -> ,``
B40: 23 | BM40: =",`"&R40&"` "&AC40&" "&IF(AJ40="Y","NOT NULL","")&" COMMENT '"&D40&IF(AT40="","","/"&AT40)&"'" -> ,`` COMMENT '' | BN40: =",`"&R40&"` "&AC40&" "&IF(AJ40="Y","NOT NULL","")&" COMMENT '"&D40&"'" -> ,`` COMMENT '' | BO40: =",A.`"&R40&"` = B.`"&R40&"`" -> ,A.`` = B.`` | BP40: =",`"&R40&"`" -> ,``
B41: 24 | BM41: =",`"&R41&"` "&AC41&" "&IF(AJ41="Y","NOT NULL","")&" COMMENT '"&D41&IF(AT41="","","/"&AT41)&"'" -> ,`` COMMENT '' | BN41: =",`"&R41&"` "&AC41&" "&IF(AJ41="Y","NOT NULL","")&" COMMENT '"&D41&"'" -> ,`` COMMENT '' | BO41: =",A.`"&R41&"` = B.`"&R41&"`" -> ,A.`` = B.`` | BP41: =",`"&R41&"`" -> ,``
B42: 25 | BM42: =",`"&R42&"` "&AC42&" "&IF(AJ42="Y","NOT NULL","")&" COMMENT '"&D42&IF(AT42="","","/"&AT42)&"'" -> ,`` COMMENT '' | BN42: =",`"&R42&"` "&AC42&" "&IF(AJ42="Y","NOT NULL","")&" COMMENT '"&D42&"'" -> ,`` COMMENT '' | BO42: =",A.`"&R42&"` = B.`"&R42&"`" -> ,A.`` = B.`` | BP42: =",`"&R42&"`" -> ,``
B43: 26
B44: 27
B45: 28
B46: 29
B49: ■インデックス情報
B50: No. | D50: Index名 | R50: カラム一覧 | AL50: プライマリキー | AP50: ユニーク | AT50: 備考
B51: 1 | D51: PRIMARY | R51: =IF(_xlfn.XLOOKUP(1,AH:AH,R:R,"",0)="","","`"&_xlfn.XLOOKUP(1,AH:AH,R:R,"",0)&"`")&IF(_xlfn.XLOOKUP(2,AH:AH,R:R,"",0)="","",",`"&_xlfn.XLOOKUP(2,AH:AH,R:R,"",0)&"`")&IF(_xlfn.XLOOKUP(3,AH:AH,R:R,"",0)="","",",`"&_xlfn.XLOOKUP(3,AH:AH,R:R,"",0)&"`")&IF(_xlfn.XLOOKUP(4,AH:AH,R:R,"",0)="","",",`"&_xlfn.XLOOKUP(4,AH:AH,R:R,"",0)&"`")&IF(_xlfn.XLOOKUP(5,AH:AH,R:R,"",0)="","",",`"&_xlfn.XLOOKUP(5,AH:AH,R:R,"",0)&"`")&IF(_xlfn.XLOOKUP(6,AH:AH,R:R,"",0)="","",",`"&_xlfn.XLOOKUP(6,AH:AH,R:R,"",0)&"`")&IF(_xlfn.XLOOKUP(7,AH:AH,R:R,"",0)="","",",`"&_xlfn.XLOOKUP(7,AH:AH,R:R,"",0)&"`")&IF(_xlfn.XLOOKUP(8,AH:AH,R:R,"",0)="","",",`"&_xlfn.XLOOKUP(8,AH:AH,R:R,"",0)&"`") | AL51: Y | AP51: Y | BM51: =" , PRIMARY KEY ("&IF(_xlfn.XLOOKUP(1,AH:AH,R:R,"",0)="","","`"&_xlfn.XLOOKUP(1,AH:AH,R:R,"",0)&"`")&IF(_xlfn.XLOOKUP(2,AH:AH,R:R,"",0)="","",",`"&_xlfn.XLOOKUP(2,AH:AH,R:R,"",0)&"`")&IF(_xlfn.XLOOKUP(3,AH:AH,R:R,"",0)="","",",`"&_xlfn.XLOOKUP(3,AH:AH,R:R,"",0)&"`")&IF(_xlfn.XLOOKUP(4,AH:AH,R:R,"",0)="","",",`"&_xlfn.XLOOKUP(4,AH:AH,R:R,"",0)&"`")&IF(_xlfn.XLOOKUP(5,AH:AH,R:R,"",0)="","",",`"&_xlfn.XLOOKUP(5,AH:AH,R:R,"",0)&"`")&IF(_xlfn.XLOOKUP(6,AH:AH,R:R,"",0)="","",",`"&_xlfn.XLOOKUP(6,AH:AH,R:R,"",0)&"`")&IF(_xlfn.XLOOKUP(7,AH:AH,R:R,"",0)="","",",`"&_xlfn.XLOOKUP(7,AH:AH,R:R,"",0)&"`")&IF(_xlfn.XLOOKUP(8,AH:AH,R:R,"",0)="","",",`"&_xlfn.XLOOKUP(8,AH:AH,R:R,"",0)&"`")&")," -> , PRIMARY KEY (), | BN51: =BM51 -> , PRIMARY KEY (),
BM52: KEY `RECORD_ID` (`RECORD_ID`)
BM53: =") ENGINE=InnoDB DEFAULT CHARSET=utf8 COMMENT = '"&$G$9&"';" -> ) ENGINE=InnoDB DEFAULT CHARSET=utf8 COMMENT = '売上情報明細'; | BN53: =") ENGINE=InnoDB DEFAULT CHARSET=utf8 COMMENT = '"&$G$9&"_TMP';" -> ) ENGINE=InnoDB DEFAULT CHARSET=utf8 COMMENT = '売上情報明細_TMP';
B54: トリガー情報
B55: No. | D55: トリガー名 | R55: イベント | U55: タイミング | Y55: 条件 | BM55: ="CREATE TRIGGER `"&G15&"_CR_Date_Time` BEFORE INSERT ON `"&G15&"` FOR EACH ROW SET NEW.record_create_date = CURRENT_DATE, NEW.record_create_time = CURRENT_TIME, NEW.record_update_date = CURRENT_DATE, NEW.record_update_time = CURRENT_TIME;" -> CREATE TRIGGER `_CR_Date_Time` BEFORE INSERT ON `` FOR EACH ROW SET NEW.record_create_date = CURRENT_DATE, NEW.record_create_time = CURRENT_TIME, NEW.record_update_date = CURRENT_DATE, NEW.record_update_time = CURRENT_TIME;
B56: 1 | D56: =G10&"_"&R56&"_"&"trg" -> sales_details_update_trg | R56: update | U56: Before row | Y56: auto_updated_date | BM56: ="CREATE TRIGGER `"&G15&"_UP_Date_Time` BEFORE UPDATE ON `"&G15&"` FOR EACH ROW SET NEW.record_update_date = CURRENT_DATE, NEW.record_update_time = CURRENT_TIME;" -> CREATE TRIGGER `_UP_Date_Time` BEFORE UPDATE ON `` FOR EACH ROW SET NEW.record_update_date = CURRENT_DATE, NEW.record_update_time = CURRENT_TIME;
BM63: , PRIMARY KEY (`CompanyCode`,`StoreCode`,`ReceiptCouponCode`,`PrintFrom`,`MessagePosition`,`MessageLineNo`), | BN63: =BM63 -> , PRIMARY KEY (`CompanyCode`,`StoreCode`,`ReceiptCouponCode`,`PrintFrom`,`MessagePosition`,`MessageLineNo`), | BO63: =",A.`"&R63&"` = B.`"&R63&"`" -> ,A.`` = B.`` | BP63: =",`"&R63&"`" -> ,``
BM64: KEY `RECORD_ID` (`RECORD_ID`) | BO64: =",A.`"&R64&"` = B.`"&R64&"`" -> ,A.`` = B.`` | BP64: =",`"&R64&"`" -> ,``
BM65: ) ENGINE=InnoDB DEFAULT CHARSET=utf8; | BN65: =BM65 -> ) ENGINE=InnoDB DEFAULT CHARSET=utf8; | BO65: =",A.`"&R65&"` = B.`"&R65&"`" -> ,A.`` = B.`` | BP65: =",`"&R65&"`" -> ,``
BM66: ="CREATE TRIGGER `"&G10&"_CR_Date_Time` BEFORE INSERT ON `"&G10&"` FOR EACH ROW SET NEW.record_create_date = CURRENT_DATE, NEW.record_create_time = CURRENT_TIME, NEW.record_update_date = CURRENT_DATE, NEW.record_update_time = CURRENT_TIME;" -> CREATE TRIGGER `sales_details_CR_Date_Time` BEFORE INSERT ON `sales_details` FOR EACH ROW SET NEW.record_create_date = CURRENT_DATE, NEW.record_create_time = CURRENT_TIME, NEW.record_update_date = CURRENT_DATE, NEW.record_update_time = CURRENT_TIME;
BM67: ="CREATE TRIGGER `"&G10&"_UP_Date_Time` BEFORE UPDATE ON `"&G10&"` FOR EACH ROW SET NEW.record_update_date = CURRENT_DATE, NEW.record_update_time = CURRENT_TIME;" -> CREATE TRIGGER `sales_details_UP_Date_Time` BEFORE UPDATE ON `sales_details` FOR EACH ROW SET NEW.record_update_date = CURRENT_DATE, NEW.record_update_time = CURRENT_TIME;

Sheet 売上情報明細
A1: システム名 | K1: システム種別 | W1: =IF(表紙!W1="","",表紙!W1) -> DB定義書 | AP1: 作成者 | AT1: 作成日 | AY1: 更新者 | BC1: 更新日 | BH1: 版数
A2: =IF(表紙!A2="","",表紙!A2) -> 現金専用簡易セルフPOS | K2: =IF(表紙!K2="","",表紙!K2) | AP2: =IF(表紙!AP2="","",表紙!AP2) -> きよはら | AT2: =IF(表紙!AT2="","",表紙!AT2) -> 44652 | AY2: =IF(表紙!AY2="","",表紙!AY2) -> Thanh Nguyên | BC2: =IF(表紙!BC2="","",表紙!BC2) -> 45285 | BH2: =IF(表紙!BH2="","",表紙!BH2) -> 0.2
A4: 機能カテゴリ | H4: =IF(表紙!H4="","",表紙!H4) -> 共通 | U4: 項目 | Z4: =IF(表紙!Z4="","",表紙!Z4) | AP4: テンプレート
B7: ■テーブル情報
B8: スキーマ名 | Y8: RDBMS名
B9: 論理名 | G9: 売上情報明細 | Y9: バージョン
B10: 物理名 | G10: sales_details
B11: 備考
B19: ■カラム情報 | BM19: ="DROP TABLE IF EXISTS `"&$G$8&"`.`"&$G$10&"`;" -> DROP TABLE IF EXISTS ``.`sales_details`;
B20: No. | D20: 論理名 | R20: 物理名 | AC20: データ型 | AH20: PK | AJ20: Not Null | AM20: デフォルト | AT20: 備考 | BM20: ="CREATE TABLE `"&$G$8&"`.`"&$G$10&"` (" -> CREATE TABLE ``.`sales_details` ( | BN20: ="CREATE TABLE `TMP`.`"&G10&"` (" -> CREATE TABLE `TMP`.`sales_details` (
B21: 1 | D21: レコードID | R21: RECORD_ID | AC21: BIGINT | AH21: Y | AJ21: Y | AM21: 自動追加 | BM21: ="`"&R21&"` "&AC21&" "&IF(AJ21="Y","NOT NULL","")&" AUTO_INCREMENT COMMENT '"&D21&IF(AT21="","","/"&AT21)&"'" -> `RECORD_ID` BIGINT NOT NULL AUTO_INCREMENT COMMENT 'レコードID' | BO21: =",A.`"&R21&"` = B.`"&R21&"`" -> ,A.`RECORD_ID` = B.`RECORD_ID` | BP21: =",`"&R21&"`" -> ,`RECORD_ID`
B22: 2 | D22: レコード作成日付 | R22: RECORD_CREATE_DATE | AC22: TIMESTAMP | AJ22: Y | AM22: CURRENT_DATE | BM22: =",`"&R22&"` "&AC22&" "&IF(AJ22="Y","NOT NULL","")&" COMMENT '"&D22&IF(AT22="","","/"&AT22)&"'" -> ,`RECORD_CREATE_DATE` TIMESTAMP NOT NULL COMMENT 'レコード作成日付' | BO22: =",A.`"&R22&"` = B.`"&R22&"`" -> ,A.`RECORD_CREATE_DATE` = B.`RECORD_CREATE_DATE` | BP22: =",`"&R22&"`" -> ,`RECORD_CREATE_DATE`
B23: 3 | D23: レコード作成時間 | R23: RECORD_CREATE_TIME | AC23: BIGINT | AJ23: Y | AM23: CURRENT_TIME | BM23: =",`"&R23&"` "&AC23&" "&IF(AJ23="Y","NOT NULL","")&" COMMENT '"&D23&IF(AT23="","","/"&AT23)&"'" -> ,`RECORD_CREATE_TIME` BIGINT NOT NULL COMMENT 'レコード作成時間' | BO23: =",A.`"&R23&"` = B.`"&R23&"`" -> ,A.`RECORD_CREATE_TIME` = B.`RECORD_CREATE_TIME` | BP23: =",`"&R23&"`" -> ,`RECORD_CREATE_TIME`
B24: 4 | D24: レコード更新日付 | R24: RECORD_UPDATE_DATE | AC24: TIMESTAMP | AJ24: Y | AM24: CURRENT_DATE | AT24: トリガーにより更新 | BM24: =",`"&R24&"` "&AC24&" "&IF(AJ24="Y","NOT NULL","")&" COMMENT '"&D24&IF(AT24="","","/"&AT24)&"'" -> ,`RECORD_UPDATE_DATE` TIMESTAMP NOT NULL COMMENT 'レコード更新日付/トリガーにより更新' | BO24: =",A.`"&R24&"` = B.`"&R24&"`" -> ,A.`RECORD_UPDATE_DATE` = B.`RECORD_UPDATE_DATE` | BP24: =",`"&R24&"`" -> ,`RECORD_UPDATE_DATE`
B25: 5 | D25: レコード更新時間 | R25: RECORD_UPDATE_TIME | AC25: BIGINT | AJ25: Y | AM25: CURRENT_TIME | AT25: トリガーにより更新 | BM25: =",`"&R25&"` "&AC25&" "&IF(AJ25="Y","NOT NULL","")&" COMMENT '"&D25&IF(AT25="","","/"&AT25)&"'" -> ,`RECORD_UPDATE_TIME` BIGINT NOT NULL COMMENT 'レコード更新時間/トリガーにより更新' | BO25: =",A.`"&R25&"` = B.`"&R25&"`" -> ,A.`RECORD_UPDATE_TIME` = B.`RECORD_UPDATE_TIME` | BP25: =",`"&R25&"`" -> ,`RECORD_UPDATE_TIME`
B26: 6 | D26: レコード無効フラグ | R26: RECORD_VOID_FLAG | AC26: BOOL | AJ26: Y | AM26: "" | AT26: true:有効 / false:無効 | BM26: =",`"&R26&"` "&AC26&" "&IF(AJ26="Y","NOT NULL","")&" COMMENT '"&D26&IF(AT26="","","/"&AT26)&"'" -> ,`RECORD_VOID_FLAG` BOOL NOT NULL COMMENT 'レコード無効フラグ/true:有効 / false:無効' | BN26: `CLASS` VARCHAR ( 1 ) NOT NULL COMMENT '処理区分', | BO26: =",A.`"&R26&"` = B.`"&R26&"`" -> ,A.`RECORD_VOID_FLAG` = B.`RECORD_VOID_FLAG` | BP26: =",`"&R26&"`" -> ,`RECORD_VOID_FLAG`
B27: 7 | D27: 企業コード | R27: company_code | AC27: char(3) | BM27: =",`"&R27&"` "&AC27&" "&IF(AJ27="Y","NOT NULL","")&" COMMENT '"&D27&IF(AT27="","","/"&AT27)&"'" -> ,`company_code` char(3) COMMENT '企業コード' | BN27: =",`"&R27&"` "&AC27&" "&IF(AJ27="Y","NOT NULL","")&" COMMENT '"&D27&"'" -> ,`company_code` char(3) COMMENT '企業コード' | BO27: =",A.`"&R27&"` = B.`"&R27&"`" -> ,A.`company_code` = B.`company_code` | BP27: =",`"&R27&"`" -> ,`company_code`
B28: 8 | D28: 店舗コード | R28: store_code | AC28: char(5) | BM28: =",`"&R28&"` "&AC28&" "&IF(AJ28="Y","NOT NULL","")&" COMMENT '"&D28&IF(AT28="","","/"&AT28)&"'" -> ,`store_code` char(5) COMMENT '店舗コード' | BN28: =",`"&R28&"` "&AC28&" "&IF(AJ28="Y","NOT NULL","")&" COMMENT '"&D28&"'" -> ,`store_code` char(5) COMMENT '店舗コード' | BO28: =",A.`"&R28&"` = B.`"&R28&"`" -> ,A.`store_code` = B.`store_code` | BP28: =",`"&R28&"`" -> ,`store_code`
B29: 9 | D29: レジ番号 | R29: instore_code | AC29: char(5) | BM29: =",`"&R29&"` "&AC29&" "&IF(AJ29="Y","NOT NULL","")&" COMMENT '"&D29&IF(AT29="","","/"&AT29)&"'" -> ,`instore_code` char(5) COMMENT 'レジ番号' | BN29: =",`"&R29&"` "&AC29&" "&IF(AJ29="Y","NOT NULL","")&" COMMENT '"&D29&"'" -> ,`instore_code` char(5) COMMENT 'レジ番号' | BO29: =",A.`"&R29&"` = B.`"&R29&"`" -> ,A.`instore_code` = B.`instore_code` | BP29: =",`"&R29&"`" -> ,`instore_code`
B30: 13 | D30: 取引確定日時<取引確定後> | R30: record_datetime | AC30: char(16) | BM30: =",`"&R30&"` "&AC30&" "&IF(AJ30="Y","NOT NULL","")&" COMMENT '"&D30&IF(AT30="","","/"&AT30)&"'" -> ,`record_datetime` char(16) COMMENT '取引確定日時<取引確定後>' | BN30: =",`"&R30&"` "&AC30&" "&IF(AJ30="Y","NOT NULL","")&" COMMENT '"&D30&"'" -> ,`record_datetime` char(16) COMMENT '取引確定日時<取引確定後>' | BO30: =",A.`"&R30&"` = B.`"&R30&"`" -> ,A.`record_datetime` = B.`record_datetime` | BP30: =",`"&R30&"`" -> ,`record_datetime`
B31: 14 | D31: ジャーナルNO<取引確定後> | R31: journal_no | AC31: char(10) | BM31: =",`"&R31&"` "&AC31&" "&IF(AJ31="Y","NOT NULL","")&" COMMENT '"&D31&IF(AT31="","","/"&AT31)&"'" -> ,`journal_no` char(10) COMMENT 'ジャーナルNO<取引確定後>' | BN31: =",`"&R31&"` "&AC31&" "&IF(AJ31="Y","NOT NULL","")&" COMMENT '"&D31&"'" -> ,`journal_no` char(10) COMMENT 'ジャーナルNO<取引確定後>' | BO31: =",A.`"&R31&"` = B.`"&R31&"`" -> ,A.`journal_no` = B.`journal_no` | BP31: =",`"&R31&"`" -> ,`journal_no`
B32: 15 | D32: レシートNO<取引確定後> | R32: receipt_no | AC32: char(10) | BM32: =",`"&R32&"` "&AC32&" "&IF(AJ32="Y","NOT NULL","")&" COMMENT '"&D32&IF(AT32="","","/"&AT32)&"'" -> ,`receipt_no` char(10) COMMENT 'レシートNO<取引確定後>' | BN32: =",`"&R32&"` "&AC32&" "&IF(AJ32="Y","NOT NULL","")&" COMMENT '"&D32&"'" -> ,`receipt_no` char(10) COMMENT 'レシートNO<取引確定後>' | BO32: =",A.`"&R32&"` = B.`"&R32&"`" -> ,A.`receipt_no` = B.`receipt_no` | BP32: =",`"&R32&"`" -> ,`receipt_no`
B33: 16 | D33: 明細行番号 | R33: item_no | AC33: string | BM33: =",`"&R33&"` "&AC33&" "&IF(AJ33="Y","NOT NULL","")&" COMMENT '"&D33&IF(AT33="","","/"&AT33)&"'" -> ,`item_no` string COMMENT '明細行番号' | BN33: =",`"&R33&"` "&AC33&" "&IF(AJ33="Y","NOT NULL","")&" COMMENT '"&D33&"'" -> ,`item_no` string COMMENT '明細行番号' | BO33: =",A.`"&R33&"` = B.`"&R33&"`" -> ,A.`item_no` = B.`item_no` | BP33: =",`"&R33&"`" -> ,`item_no`
B34: 17 | D34: 明細訂正取消線有無 | R34: item_cancel_line | AC34: bool | BM34: =",`"&R34&"` "&AC34&" "&IF(AJ34="Y","NOT NULL","")&" COMMENT '"&D34&IF(AT34="","","/"&AT34)&"'" -> ,`item_cancel_line` bool COMMENT '明細訂正取消線有無' | BN34: =",`"&R34&"` "&AC34&" "&IF(AJ34="Y","NOT NULL","")&" COMMENT '"&D34&"'" -> ,`item_cancel_line` bool COMMENT '明細訂正取消線有無' | BO34: =",A.`"&R34&"` = B.`"&R34&"`" -> ,A.`item_cancel_line` = B.`item_cancel_line` | BP34: =",`"&R34&"`" -> ,`item_cancel_line`
B35: 18 | D35: スキャンコード | R35: item_scan_code | AC35: string | BM35: =",`"&R35&"` "&AC35&" "&IF(AJ35="Y","NOT NULL","")&" COMMENT '"&D35&IF(AT35="","","/"&AT35)&"'" -> ,`item_scan_code` string COMMENT 'スキャンコード' | BN35: =",`"&R35&"` "&AC35&" "&IF(AJ35="Y","NOT NULL","")&" COMMENT '"&D35&"'" -> ,`item_scan_code` string COMMENT 'スキャンコード' | BO35: =",A.`"&R35&"` = B.`"&R35&"`" -> ,A.`item_scan_code` = B.`item_scan_code` | BP35: =",`"&R35&"`" -> ,`item_scan_code`
B36: 19 | D36: 商品名 | R36: item_name | AC36: string | BM36: =",`"&R36&"` "&AC36&" "&IF(AJ36="Y","NOT NULL","")&" COMMENT '"&D36&IF(AT36="","","/"&AT36)&"'" -> ,`item_name` string COMMENT '商品名' | BN36: =",`"&R36&"` "&AC36&" "&IF(AJ36="Y","NOT NULL","")&" COMMENT '"&D36&"'" -> ,`item_name` string COMMENT '商品名' | BO36: =",A.`"&R36&"` = B.`"&R36&"`" -> ,A.`item_name` = B.`item_name` | BP36: =",`"&R36&"`" -> ,`item_name`
B37: 20 | D37: 採用単価 | R37: item_unit_price | AC37: decimal | BM37: =",`"&R37&"` "&AC37&" "&IF(AJ37="Y","NOT NULL","")&" COMMENT '"&D37&IF(AT37="","","/"&AT37)&"'" -> ,`item_unit_price` decimal COMMENT '採用単価' | BN37: =",`"&R37&"` "&AC37&" "&IF(AJ37="Y","NOT NULL","")&" COMMENT '"&D37&"'" -> ,`item_unit_price` decimal COMMENT '採用単価' | BO37: =",A.`"&R37&"` = B.`"&R37&"`" -> ,A.`item_unit_price` = B.`item_unit_price` | BP37: =",`"&R37&"`" -> ,`item_unit_price`
B38: 21 | D38: 点数 | R38: item_quantity | AC38: string | BM38: =",`"&R38&"` "&AC38&" "&IF(AJ38="Y","NOT NULL","")&" COMMENT '"&D38&IF(AT38="","","/"&AT38)&"'" -> ,`item_quantity` string COMMENT '点数' | BN38: =",`"&R38&"` "&AC38&" "&IF(AJ38="Y","NOT NULL","")&" COMMENT '"&D38&"'" -> ,`item_quantity` string COMMENT '点数' | BO38: =",A.`"&R38&"` = B.`"&R38&"`" -> ,A.`item_quantity` = B.`item_quantity` | BP38: =",`"&R38&"`" -> ,`item_quantity`
... B41: 24 | D41: 税 ("外税 8%") | R41: item_tax_fmt | AC41: string | BM41: =",`"&R41&"` "&AC41&" "&IF(AJ41="Y","NOT NULL","")&" COMMENT '"&D41&IF(AT41="","","/"&AT41)&"'" -> ,`item_tax_fmt` string COMMENT '税 ("外税 8%")' | BN41: =",`"&R41&"` "&AC41&" "&IF(AJ41="Y","NOT NULL","")&" COMMENT '"&D41&"'" -> ,`item_tax_fmt` string COMMENT '税 ("外税 8%")' | BO41: =",A.`"&R41&"` = B.`"&R41&"`" -> ,A.`item_tax_fmt` = B.`item_tax_fmt` | BP41: =",`"&R41&"`" -> ,`item_tax_fmt`
B42: 25 | D42: イートイン対象有無 | R42: item_eatin | AC42: bool | AT42: true : Eat in / false：Take out | BM42: =",`"&R42&"` "&AC42&" "&IF(AJ42="Y","NOT NULL","")&" COMMENT '"&D42&IF(AT42="","","/"&AT42)&"'" -> ,`item_eatin` bool COMMENT 'イートイン対象有無/true : Eat in / false：Take out' | BN42: =",`"&R42&"` "&AC42&" "&IF(AJ42="Y","NOT NULL","")&" COMMENT '"&D42&"'" -> ,`item_eatin` bool COMMENT 'イートイン対象有無' | BO42: =",A.`"&R42&"` = B.`"&R42&"`" -> ,A.`item_eatin` = B.`item_eatin` | BP42: =",`"&R42&"`" -> ,`item_eatin`
B43: 26 | D43: 年齢制限品有無 | R43: item_age_limit | AC43: bool | AT43: true : 年連確認が必要 / false：年連確認が不要
B44: 27
B45: 28
B46: 29
B49: ■インデックス情報
B50: No. | D50: Index名 | R50: カラム一覧 | AL50: プライマリキー | AP50: ユニーク | AT50: 備考
B51: 1 | D51: PRIMARY | R51: =IF(_xlfn.XLOOKUP(1,AH:AH,R:R,"",0)="","","`"&_xlfn.XLOOKUP(1,AH:AH,R:R,"",0)&"`")&IF(_xlfn.XLOOKUP(2,AH:AH,R:R,"",0)="","",",`"&_xlfn.XLOOKUP(2,AH:AH,R:R,"",0)&"`")&IF(_xlfn.XLOOKUP(3,AH:AH,R:R,"",0)="","",",`"&_xlfn.XLOOKUP(3,AH:AH,R:R,"",0)&"`")&IF(_xlfn.XLOOKUP(4,AH:AH,R:R,"",0)="","",",`"&_xlfn.XLOOKUP(4,AH:AH,R:R,"",0)&"`")&IF(_xlfn.XLOOKUP(5,AH:AH,R:R,"",0)="","",",`"&_xlfn.XLOOKUP(5,AH:AH,R:R,"",0)&"`")&IF(_xlfn.XLOOKUP(6,AH:AH,R:R,"",0)="","",",`"&_xlfn.XLOOKUP(6,AH:AH,R:R,"",0)&"`")&IF(_xlfn.XLOOKUP(7,AH:AH,R:R,"",0)="","",",`"&_xlfn.XLOOKUP(7,AH:AH,R:R,"",0)&"`")&IF(_xlfn.XLOOKUP(8,AH:AH,R:R,"",0)="","",",`"&_xlfn.XLOOKUP(8,AH:AH,R:R,"",0)&"`") | AL51: Y | AP51: Y | BM51: =" , PRIMARY KEY ("&IF(_xlfn.XLOOKUP(1,AH:AH,R:R,"",0)="","","`"&_xlfn.XLOOKUP(1,AH:AH,R:R,"",0)&"`")&IF(_xlfn.XLOOKUP(2,AH:AH,R:R,"",0)="","",",`"&_xlfn.XLOOKUP(2,AH:AH,R:R,"",0)&"`")&IF(_xlfn.XLOOKUP(3,AH:AH,R:R,"",0)="","",",`"&_xlfn.XLOOKUP(3,AH:AH,R:R,"",0)&"`")&IF(_xlfn.XLOOKUP(4,AH:AH,R:R,"",0)="","",",`"&_xlfn.XLOOKUP(4,AH:AH,R:R,"",0)&"`")&IF(_xlfn.XLOOKUP(5,AH:AH,R:R,"",0)="","",",`"&_xlfn.XLOOKUP(5,AH:AH,R:R,"",0)&"`")&IF(_xlfn.XLOOKUP(6,AH:AH,R:R,"",0)="","",",`"&_xlfn.XLOOKUP(6,AH:AH,R:R,"",0)&"`")&IF(_xlfn.XLOOKUP(7,AH:AH,R:R,"",0)="","",",`"&_xlfn.XLOOKUP(7,AH:AH,R:R,"",0)&"`")&IF(_xlfn.XLOOKUP(8,AH:AH,R:R,"",0)="","",",`"&_xlfn.XLOOKUP(8,AH:AH,R:R,"",0)&"`")&")," -> , PRIMARY KEY (), | BN51: =BM51 -> , PRIMARY KEY (),
BM52: KEY `RECORD_ID` (`RECORD_ID`)
BM53: =") ENGINE=InnoDB DEFAULT CHARSET=utf8 COMMENT = '"&$G$9&"';" -> ) ENGINE=InnoDB DEFAULT CHARSET=utf8 COMMENT = '売上情報明細'; | BN53: =") ENGINE=InnoDB DEFAULT CHARSET=utf8 COMMENT = '"&$G$9&"_TMP';" -> ) ENGINE=InnoDB DEFAULT CHARSET=utf8 COMMENT = '売上情報明細_TMP';
B54: トリガー情報
B55: No. | D55: トリガー名 | R55: イベント | U55: タイミング | Y55: 条件 | BM55: ="CREATE TRIGGER `"&G15&"_CR_Date_Time` BEFORE INSERT ON `"&G15&"` FOR EACH ROW SET NEW.record_create_date = CURRENT_DATE, NEW.record_create_time = CURRENT_TIME, NEW.record_update_date = CURRENT_DATE, NEW.record_update_time = CURRENT_TIME;" -> CREATE TRIGGER `_CR_Date_Time` BEFORE INSERT ON `` FOR EACH ROW SET NEW.record_create_date = CURRENT_DATE, NEW.record_create_time = CURRENT_TIME, NEW.record_update_date = CURRENT_DATE, NEW.record_update_time = CURRENT_TIME;
B56: 1 | D56: =G10&"_"&R56&"_"&"trg" -> sales_details_update_trg | R56: update | U56: Before row | Y56: auto_updated_date | BM56: ="CREATE TRIGGER `"&G15&"_UP_Date_Time` BEFORE UPDATE ON `"&G15&"` FOR EACH ROW SET NEW.record_update_date = CURRENT_DATE, NEW.record_update_time = CURRENT_TIME;" -> CREATE TRIGGER `_UP_Date_Time` BEFORE UPDATE ON `` FOR EACH ROW SET NEW.record_update_date = CURRENT_DATE, NEW.record_update_time = CURRENT_TIME;
BM63: , PRIMARY KEY (`CompanyCode`,`StoreCode`,`ReceiptCouponCode`,`PrintFrom`,`MessagePosition`,`MessageLineNo`), | BN63: =BM63 -> , PRIMARY KEY (`CompanyCode`,`StoreCode`,`ReceiptCouponCode`,`PrintFrom`,`MessagePosition`,`MessageLineNo`), | BO63: =",A.`"&R63&"` = B.`"&R63&"`" -> ,A.`` = B.`` | BP63: =",`"&R63&"`" -> ,``
BM64: KEY `RECORD_ID` (`RECORD_ID`) | BO64: =",A.`"&R64&"` = B.`"&R64&"`" -> ,A.`` = B.`` | BP64: =",`"&R64&"`" -> ,``
BM65: ) ENGINE=InnoDB DEFAULT CHARSET=utf8; | BN65: =BM65 -> ) ENGINE=InnoDB DEFAULT CHARSET=utf8; | BO65: =",A.`"&R65&"` = B.`"&R65&"`" -> ,A.`` = B.`` | BP65: =",`"&R65&"`" -> ,``
BM66: ="CREATE TRIGGER `"&G10&"_CR_Date_Time` BEFORE INSERT ON `"&G10&"` FOR EACH ROW SET NEW.record_create_date = CURRENT_DATE, NEW.record_create_time = CURRENT_TIME, NEW.record_update_date = CURRENT_DATE, NEW.record_update_time = CURRENT_TIME;" -> CREATE TRIGGER `sales_details_CR_Date_Time` BEFORE INSERT ON `sales_details` FOR EACH ROW SET NEW.record_create_date = CURRENT_DATE, NEW.record_create_time = CURRENT_TIME, NEW.record_update_date = CURRENT_DATE, NEW.record_update_time = CURRENT_TIME;
BM67: ="CREATE TRIGGER `"&G10&"_UP_Date_Time` BEFORE UPDATE ON `"&G10&"` FOR EACH ROW SET NEW.record_update_date = CURRENT_DATE, NEW.record_update_time = CURRENT_TIME;" -> CREATE TRIGGER `sales_details_UP_Date_Time` BEFORE UPDATE ON `sales_details` FOR EACH ROW SET NEW.record_update_date = CURRENT_DATE, NEW.record_update_time = CURRENT_TIME;

Sheet 【釣銭機】在高情報
A1: システム名 | K1: システム種別 | W1: =IF(表紙!W1="","",表紙!W1) -> DB定義書 | AP1: 作成者 | AT1: 作成日 | AY1: 更新者 | BC1: 更新日 | BH1: 版数
A2: =IF(表紙!A2="","",表紙!A2) -> 現金専用簡易セルフPOS | K2: =IF(表紙!K2="","",表紙!K2) | AP2: =IF(表紙!AP2="","",表紙!AP2) -> きよはら | AT2: =IF(表紙!AT2="","",表紙!AT2) -> 44652 | AY2: =IF(表紙!AY2="","",表紙!AY2) -> Thanh Nguyên | BC2: =IF(表紙!BC2="","",表紙!BC2) -> 45285 | BH2: =IF(表紙!BH2="","",表紙!BH2) -> 0.2
A4: 機能カテゴリ | H4: =IF(表紙!H4="","",表紙!H4) -> 共通 | U4: 項目 | Z4: =IF(表紙!Z4="","",表紙!Z4) | AP4: テンプレート
B7: ■テーブル情報
B8: スキーマ名 | Y8: RDBMS名
B9: 論理名 | G9: 【釣銭機】在高情報 | Y9: バージョン
B10: 物理名
B11: 備考
B19: ■カラム情報 | BM19: ="DROP TABLE IF EXISTS `"&$G$8&"`.`"&$G$10&"`;" -> DROP TABLE IF EXISTS ``.``;
B20: No. | D20: 論理名 | R20: 物理名 | AC20: データ型 | AH20: PK | AJ20: Not Null | AM20: デフォルト | AT20: 備考 | BM20: ="CREATE TABLE `"&$G$8&"`.`"&$G$10&"` (" -> CREATE TABLE ``.`` ( | BN20: ="CREATE TABLE `TMP`.`"&G10&"` (" -> CREATE TABLE `TMP`.`` (
B21: 1 | D21: レコードID | R21: RECORD_ID | AC21: BIGINT | AH21: Y | AJ21: Y | AM21: 自動追加 | BM21: ="`"&R21&"` "&AC21&" "&IF(AJ21="Y","NOT NULL","")&" AUTO_INCREMENT COMMENT '"&D21&IF(AT21="","","/"&AT21)&"'" -> `RECORD_ID` BIGINT NOT NULL AUTO_INCREMENT COMMENT 'レコードID' | BO21: =",A.`"&R21&"` = B.`"&R21&"`" -> ,A.`RECORD_ID` = B.`RECORD_ID` | BP21: =",`"&R21&"`" -> ,`RECORD_ID`
B22: 2 | D22: レコード作成日付 | R22: RECORD_CREATE_DATE | AC22: TIMESTAMP | AJ22: Y | AM22: CURRENT_DATE | BM22: =",`"&R22&"` "&AC22&" "&IF(AJ22="Y","NOT NULL","")&" COMMENT '"&D22&IF(AT22="","","/"&AT22)&"'" -> ,`RECORD_CREATE_DATE` TIMESTAMP NOT NULL COMMENT 'レコード作成日付' | BO22: =",A.`"&R22&"` = B.`"&R22&"`" -> ,A.`RECORD_CREATE_DATE` = B.`RECORD_CREATE_DATE` | BP22: =",`"&R22&"`" -> ,`RECORD_CREATE_DATE`
B23: 3 | D23: レコード作成時間 | R23: RECORD_CREATE_TIME | AC23: BIGINT | AJ23: Y | AM23: CURRENT_TIME | BM23: =",`"&R23&"` "&AC23&" "&IF(AJ23="Y","NOT NULL","")&" COMMENT '"&D23&IF(AT23="","","/"&AT23)&"'" -> ,`RECORD_CREATE_TIME` BIGINT NOT NULL COMMENT 'レコード作成時間' | BO23: =",A.`"&R23&"` = B.`"&R23&"`" -> ,A.`RECORD_CREATE_TIME` = B.`RECORD_CREATE_TIME` | BP23: =",`"&R23&"`" -> ,`RECORD_CREATE_TIME`
B24: 4 | D24: レコード更新日付 | R24: RECORD_UPDATE_DATE | AC24: TIMESTAMP | AJ24: Y | AM24: CURRENT_DATE | AT24: トリガーにより更新 | BM24: =",`"&R24&"` "&AC24&" "&IF(AJ24="Y","NOT NULL","")&" COMMENT '"&D24&IF(AT24="","","/"&AT24)&"'" -> ,`RECORD_UPDATE_DATE` TIMESTAMP NOT NULL COMMENT 'レコード更新日付/トリガーにより更新' | BO24: =",A.`"&R24&"` = B.`"&R24&"`" -> ,A.`RECORD_UPDATE_DATE` = B.`RECORD_UPDATE_DATE` | BP24: =",`"&R24&"`" -> ,`RECORD_UPDATE_DATE`
B25: 5 | D25: レコード更新時間 | R25: RECORD_UPDATE_TIME | AC25: BIGINT | AJ25: Y | AM25: CURRENT_TIME | AT25: トリガーにより更新 | BM25: =",`"&R25&"` "&AC25&" "&IF(AJ25="Y","NOT NULL","")&" COMMENT '"&D25&IF(AT25="","","/"&AT25)&"'" -> ,`RECORD_UPDATE_TIME` BIGINT NOT NULL COMMENT 'レコード更新時間/トリガーにより更新' | BO25: =",A.`"&R25&"` = B.`"&R25&"`" -> ,A.`RECORD_UPDATE_TIME` = B.`RECORD_UPDATE_TIME` | BP25: =",`"&R25&"`" -> ,`RECORD_UPDATE_TIME`
B26: 6 | D26: レコード無効フラグ | R26: RECORD_VOID_FLAG | AC26: BOOL | AJ26: Y | AM26: "" | AT26: true:有効 / false:無効 | BM26: =",`"&R26&"` "&AC26&" "&IF(AJ26="Y","NOT NULL","")&" COMMENT '"&D26&IF(AT26="","","/"&AT26)&"'" -> ,`RECORD_VOID_FLAG` BOOL NOT NULL COMMENT 'レコード無効フラグ/true:有効 / false:無効' | BN26: `CLASS` VARCHAR ( 1 ) NOT NULL COMMENT '処理区分', | BO26: =",A.`"&R26&"` = B.`"&R26&"`" -> ,A.`RECORD_VOID_FLAG` = B.`RECORD_VOID_FLAG` | BP26: =",`"&R26&"`" -> ,`RECORD_VOID_FLAG`
B27: 7 | D27: 区分 | R27: class | AC27: INT | AT27: 1:フル 2:ニアフル 3:ニアエンプティ 4:エンプティ 5:残置 6:釣銭準備金 | BM27: =",`"&R27&"` "&AC27&" "&IF(AJ27="Y","NOT NULL","")&" COMMENT '"&D27&IF(AT27="","","/"&AT27)&"'" -> ,`class` INT COMMENT '区分/1:フル 2:ニアフル 3:ニアエンプティ 4:エンプティ 5:残置 6:釣銭準備金' | BN27: =",`"&R27&"` "&AC27&" "&IF(AJ27="Y","NOT NULL","")&" COMMENT '"&D27&"'" -> ,`class` INT COMMENT '区分' | BO27: =",A.`"&R27&"` = B.`"&R27&"`" -> ,A.`class` = B.`class` | BP27: =",`"&R27&"`" -> ,`class`
B28: 8 | D28: 10000円札 | R28: 10000yen | AC28: INT | BM28: =",`"&R28&"` "&AC28&" "&IF(AJ28="Y","NOT NULL","")&" COMMENT '"&D28&IF(AT28="","","/"&AT28)&"'" -> ,`10000yen` INT COMMENT '10000円札' | BN28: =",`"&R28&"` "&AC28&" "&IF(AJ28="Y","NOT NULL","")&" COMMENT '"&D28&"'" -> ,`10000yen` INT COMMENT '10000円札' | BO28: =",A.`"&R28&"` = B.`"&R28&"`" -> ,A.`10000yen` = B.`10000yen` | BP28: =",`"&R28&"`" -> ,`10000yen`
B29: 9 | D29: 5000円札 | R29: 5000yen | AC29: INT | BM29: =",`"&R29&"` "&AC29&" "&IF(AJ29="Y","NOT NULL","")&" COMMENT '"&D29&IF(AT29="","","/"&AT29)&"'" -> ,`5000yen` INT COMMENT '5000円札' | BN29: =",`"&R29&"` "&AC29&" "&IF(AJ29="Y","NOT NULL","")&" COMMENT '"&D29&"'" -> ,`5000yen` INT COMMENT '5000円札' | BO29: =",A.`"&R29&"` = B.`"&R29&"`" -> ,A.`5000yen` = B.`5000yen` | BP29: =",`"&R29&"`" -> ,`5000yen`
B30: 10 | D30: 2000円札 | R30: 2000yen | AC30: INT | BM30: =",`"&R30&"` "&AC30&" "&IF(AJ30="Y","NOT NULL","")&" COMMENT '"&D30&IF(AT30="","","/"&AT30)&"'" -> ,`2000yen` INT COMMENT '2000円札' | BN30: =",`"&R30&"` "&AC30&" "&IF(AJ30="Y","NOT NULL","")&" COMMENT '"&D30&"'" -> ,`2000yen` INT COMMENT '2000円札' | BO30: =",A.`"&R30&"` = B.`"&R30&"`" -> ,A.`2000yen` = B.`2000yen` | BP30: =",`"&R30&"`" -> ,`2000yen`
B31: 11 | D31: 1000円札 | R31: 1000yen | AC31: INT | BM31: =",`"&R31&"` "&AC31&" "&IF(AJ31="Y","NOT NULL","")&" COMMENT '"&D31&IF(AT31="","","/"&AT31)&"'" -> ,`1000yen` INT COMMENT '1000円札' | BN31: =",`"&R31&"` "&AC31&" "&IF(AJ31="Y","NOT NULL","")&" COMMENT '"&D31&"'" -> ,`1000yen` INT COMMENT '1000円札' | BO31: =",A.`"&R31&"` = B.`"&R31&"`" -> ,A.`1000yen` = B.`1000yen` | BP31: =",`"&R31&"`" -> ,`1000yen`
B32: 12 | D32: 500円玉 | R32: 500yen | AC32: INT | BM32: =",`"&R32&"` "&AC32&" "&IF(AJ32="Y","NOT NULL","")&" COMMENT '"&D32&IF(AT32="","","/"&AT32)&"'" -> ,`500yen` INT COMMENT '500円玉' | BN32: =",`"&R32&"` "&AC32&" "&IF(AJ32="Y","NOT NULL","")&" COMMENT '"&D32&"'" -> ,`500yen` INT COMMENT '500円玉' | BO32: =",A.`"&R32&"` = B.`"&R32&"`" -> ,A.`500yen` = B.`500yen` | BP32: =",`"&R32&"`" -> ,`500yen`
B33: 13 | D33: 100円玉 | R33: 100yen | AC33: INT | BM33: =",`"&R33&"` "&AC33&" "&IF(AJ33="Y","NOT NULL","")&" COMMENT '"&D33&IF(AT33="","","/"&AT33)&"'" -> ,`100yen` INT COMMENT '100円玉' | BN33: =",`"&R33&"` "&AC33&" "&IF(AJ33="Y","NOT NULL","")&" COMMENT '"&D33&"'" -> ,`100yen` INT COMMENT '100円玉' | BO33: =",A.`"&R33&"` = B.`"&R33&"`" -> ,A.`100yen` = B.`100yen` | BP33: =",`"&R33&"`" -> ,`100yen`
B34: 14 | D34: 50円玉 | R34: 50yen | AC34: INT | BM34: =",`"&R34&"` "&AC34&" "&IF(AJ34="Y","NOT NULL","")&" COMMENT '"&D34&IF(AT34="","","/"&AT34)&"'" -> ,`50yen` INT COMMENT '50円玉' | BN34: =",`"&R34&"` "&AC34&" "&IF(AJ34="Y","NOT NULL","")&" COMMENT '"&D34&"'" -> ,`50yen` INT COMMENT '50円玉' | BO34: =",A.`"&R34&"` = B.`"&R34&"`" -> ,A.`50yen` = B.`50yen` | BP34: =",`"&R34&"`" -> ,`50yen`
B35: 15 | D35: 10円玉 | R35: 10yen | AC35: INT | BM35: =",`"&R35&"` "&AC35&" "&IF(AJ35="Y","NOT NULL","")&" COMMENT '"&D35&IF(AT35="","","/"&AT35)&"'" -> ,`10yen` INT COMMENT '10円玉' | BN35: =",`"&R35&"` "&AC35&" "&IF(AJ35="Y","NOT NULL","")&" COMMENT '"&D35&"'" -> ,`10yen` INT COMMENT '10円玉' | BO35: =",A.`"&R35&"` = B.`"&R35&"`" -> ,A.`10yen` = B.`10yen` | BP35: =",`"&R35&"`" -> ,`10yen`
B36: 16 | D36: 5円玉 | R36: 5yen | AC36: INT | BM36: =",`"&R36&"` "&AC36&" "&IF(AJ36="Y","NOT NULL","")&" COMMENT '"&D36&IF(AT36="","","/"&AT36)&"'" -> ,`5yen` INT COMMENT '5円玉' | BN36: =",`"&R36&"` "&AC36&" "&IF(AJ36="Y","NOT NULL","")&" COMMENT '"&D36&"'" -> ,`5yen` INT COMMENT '5円玉' | BO36: =",A.`"&R36&"` = B.`"&R36&"`" -> ,A.`5yen` = B.`5yen` | BP36: =",`"&R36&"`" -> ,`5yen`
B37: 17 | D37: 1円玉 | R37: 1yen | AC37: INT | BM37: =",`"&R37&"` "&AC37&" "&IF(AJ37="Y","NOT NULL","")&" COMMENT '"&D37&IF(AT37="","","/"&AT37)&"'" -> ,`1yen` INT COMMENT '1円玉' | BN37: =",`"&R37&"` "&AC37&" "&IF(AJ37="Y","NOT NULL","")&" COMMENT '"&D37&"'" -> ,`1yen` INT COMMENT '1円玉' | BO37: =",A.`"&R37&"` = B.`"&R37&"`" -> ,A.`1yen` = B.`1yen` | BP37: =",`"&R37&"`" -> ,`1yen`
B38: 18 | D38: カセット | R38: cassette | AC38: INT | BM38: =",`"&R38&"` "&AC38&" "&IF(AJ38="Y","NOT NULL","")&" COMMENT '"&D38&IF(AT38="","","/"&AT38)&"'" -> ,`cassette` INT COMMENT 'カセット' | BN38: =",`"&R38&"` "&AC38&" "&IF(AJ38="Y","NOT NULL","")&" COMMENT '"&D38&"'" -> ,`cassette` INT COMMENT 'カセット' | BO38: =",A.`"&R38&"` = B.`"&R38&"`" -> ,A.`cassette` = B.`cassette` | BP38: =",`"&R38&"`" -> ,`cassette`
B39: 19 | D39: 会社コード | R39: company_code | AC39: char(3) | BM39: =",`"&R39&"` "&AC39&" "&IF(AJ39="Y","NOT NULL","")&" COMMENT '"&D39&IF(AT39="","","/"&AT39)&"'" -> ,`company_code` char(3) COMMENT '会社コード' | BN39: =",`"&R39&"` "&AC39&" "&IF(AJ39="Y","NOT NULL","")&" COMMENT '"&D39&"'" -> ,`company_code` char(3) COMMENT '会社コード' | BO39: =",A.`"&R39&"` = B.`"&R39&"`" -> ,A.`company_code` = B.`company_code` | BP39: =",`"&R39&"`" -> ,`company_code`
... B41: 21 | D41: 端末番号 | R41: instore_code | AC41: char(10) | BM41: =",`"&R41&"` "&AC41&" "&IF(AJ41="Y","NOT NULL","")&" COMMENT '"&D41&IF(AT41="","","/"&AT41)&"'" -> ,`instore_code` char(10) COMMENT '端末番号' | BN41: =",`"&R41&"` "&AC41&" "&IF(AJ41="Y","NOT NULL","")&" COMMENT '"&D41&"'" -> ,`instore_code` char(10) COMMENT '端末番号' | BO41: =",A.`"&R41&"` = B.`"&R41&"`" -> ,A.`instore_code` = B.`instore_code` | BP41: =",`"&R41&"`" -> ,`instore_code`
BM42: =",`"&R42&"` "&AC42&" "&IF(AJ42="Y","NOT NULL","")&" COMMENT '"&D42&IF(AT42="","","/"&AT42)&"'" -> ,`` COMMENT '' | BN42: =",`"&R42&"` "&AC42&" "&IF(AJ42="Y","NOT NULL","")&" COMMENT '"&D42&"'" -> ,`` COMMENT '' | BO42: =",A.`"&R42&"` = B.`"&R42&"`" -> ,A.`` = B.`` | BP42: =",`"&R42&"`" -> ,``
B60: ■インデックス情報
B61: No. | D61: Index名 | R61: カラム一覧 | AL61: プライマリキー | AP61: ユニーク | AT61: 備考
B62: 1 | D62: PRIMARY | R62: =IF(_xlfn.XLOOKUP(1,AH:AH,R:R,"",0)="","","`"&_xlfn.XLOOKUP(1,AH:AH,R:R,"",0)&"`")&IF(_xlfn.XLOOKUP(2,AH:AH,R:R,"",0)="","",",`"&_xlfn.XLOOKUP(2,AH:AH,R:R,"",0)&"`")&IF(_xlfn.XLOOKUP(3,AH:AH,R:R,"",0)="","",",`"&_xlfn.XLOOKUP(3,AH:AH,R:R,"",0)&"`")&IF(_xlfn.XLOOKUP(4,AH:AH,R:R,"",0)="","",",`"&_xlfn.XLOOKUP(4,AH:AH,R:R,"",0)&"`")&IF(_xlfn.XLOOKUP(5,AH:AH,R:R,"",0)="","",",`"&_xlfn.XLOOKUP(5,AH:AH,R:R,"",0)&"`")&IF(_xlfn.XLOOKUP(6,AH:AH,R:R,"",0)="","",",`"&_xlfn.XLOOKUP(6,AH:AH,R:R,"",0)&"`")&IF(_xlfn.XLOOKUP(7,AH:AH,R:R,"",0)="","",",`"&_xlfn.XLOOKUP(7,AH:AH,R:R,"",0)&"`")&IF(_xlfn.XLOOKUP(8,AH:AH,R:R,"",0)="","",",`"&_xlfn.XLOOKUP(8,AH:AH,R:R,"",0)&"`") | AL62: Y | AP62: Y | BM62: =" , PRIMARY KEY ("&IF(_xlfn.XLOOKUP(1,AH:AH,R:R,"",0)="","","`"&_xlfn.XLOOKUP(1,AH:AH,R:R,"",0)&"`")&IF(_xlfn.XLOOKUP(2,AH:AH,R:R,"",0)="","",",`"&_xlfn.XLOOKUP(2,AH:AH,R:R,"",0)&"`")&IF(_xlfn.XLOOKUP(3,AH:AH,R:R,"",0)="","",",`"&_xlfn.XLOOKUP(3,AH:AH,R:R,"",0)&"`")&IF(_xlfn.XLOOKUP(4,AH:AH,R:R,"",0)="","",",`"&_xlfn.XLOOKUP(4,AH:AH,R:R,"",0)&"`")&IF(_xlfn.XLOOKUP(5,AH:AH,R:R,"",0)="","",",`"&_xlfn.XLOOKUP(5,AH:AH,R:R,"",0)&"`")&IF(_xlfn.XLOOKUP(6,AH:AH,R:R,"",0)="","",",`"&_xlfn.XLOOKUP(6,AH:AH,R:R,"",0)&"`")&IF(_xlfn.XLOOKUP(7,AH:AH,R:R,"",0)="","",",`"&_xlfn.XLOOKUP(7,AH:AH,R:R,"",0)&"`")&IF(_xlfn.XLOOKUP(8,AH:AH,R:R,"",0)="","",",`"&_xlfn.XLOOKUP(8,AH:AH,R:R,"",0)&"`")&")," -> , PRIMARY KEY (), | BN62: =BM62 -> , PRIMARY KEY (),
BM63: KEY `RECORD_ID` (`RECORD_ID`) | BO63: =",A.`"&R63&"` = B.`"&R63&"`" -> ,A.`` = B.`` | BP63: =",`"&R63&"`" -> ,``
BM64: =") ENGINE=InnoDB DEFAULT CHARSET=utf8 COMMENT = '"&$G$9&"';" -> ) ENGINE=InnoDB DEFAULT CHARSET=utf8 COMMENT = '【釣銭機】在高情報'; | BN64: =") ENGINE=InnoDB DEFAULT CHARSET=utf8 COMMENT = '"&$G$9&"_TMP';" -> ) ENGINE=InnoDB DEFAULT CHARSET=utf8 COMMENT = '【釣銭機】在高情報_TMP'; | BO64: =",A.`"&R64&"` = B.`"&R64&"`" -> ,A.`` = B.`` | BP64: =",`"&R64&"`" -> ,``
B65: トリガー情報 | BO65: =",A.`"&R65&"` = B.`"&R65&"`" -> ,A.`` = B.`` | BP65: =",`"&R65&"`" -> ,``
B66: No. | D66: トリガー名 | R66: イベント | U66: タイミング | Y66: 条件 | BM66: ="CREATE TRIGGER `"&G26&"_CR_Date_Time` BEFORE INSERT ON `"&G26&"` FOR EACH ROW SET NEW.record_create_date = CURRENT_DATE, NEW.record_create_time = CURRENT_TIME, NEW.record_update_date = CURRENT_DATE, NEW.record_update_time = CURRENT_TIME;" -> CREATE TRIGGER `_CR_Date_Time` BEFORE INSERT ON `` FOR EACH ROW SET NEW.record_create_date = CURRENT_DATE, NEW.record_create_time = CURRENT_TIME, NEW.record_update_date = CURRENT_DATE, NEW.record_update_time = CURRENT_TIME;
B67: 1 | D67: =G10&"_"&R67&"_"&"trg" -> _update_trg | R67: update | U67: Before row | Y67: auto_updated_date | BM67: ="CREATE TRIGGER `"&G26&"_UP_Date_Time` BEFORE UPDATE ON `"&G26&"` FOR EACH ROW SET NEW.record_update_date = CURRENT_DATE, NEW.record_update_time = CURRENT_TIME;" -> CREATE TRIGGER `_UP_Date_Time` BEFORE UPDATE ON `` FOR EACH ROW SET NEW.record_update_date = CURRENT_DATE, NEW.record_update_time = CURRENT_TIME;

Sheet 商品マスタ
A1: システム名 | K1: システム種別 | W1: =IF(表紙!W1="","",表紙!W1) -> DB定義書 | AP1: 作成者 | AT1: 作成日 | AY1: 更新者 | BC1: 更新日 | BH1: 版数
A2: =IF(表紙!A2="","",表紙!A2) -> 現金専用簡易セルフPOS | K2: =IF(表紙!K2="","",表紙!K2) | AP2: =IF(表紙!AP2="","",表紙!AP2) -> きよはら | AT2: =IF(表紙!AT2="","",表紙!AT2) -> 44652 | AY2: =IF(表紙!AY2="","",表紙!AY2) -> Thanh Nguyên | BC2: =IF(表紙!BC2="","",表紙!BC2) -> 45285 | BH2: =IF(表紙!BH2="","",表紙!BH2) -> 0.2
A4: 機能カテゴリ | H4: =IF(表紙!H4="","",表紙!H4) -> 共通 | U4: 項目 | Z4: =IF(表紙!Z4="","",表紙!Z4) | AP4: テンプレート
B7: ■テーブル情報
B8: スキーマ名 | G8: POS_MASTER | Y8: RDBMS名
B9: 論理名 | G9: 商品マスタ | Y9: バージョン
B10: 物理名 | G10: ItemMaster
B11: 備考
BT16: ="if(nullif( @"&B27-5&",'') > '', @"&B27-5&", null )" -> if(nullif( @2,'') > '', @2, null )
BT17: ="if(@"&B27-5&" > '0000-00-00 00:00:00', @"&B27-5&", null)" -> if(@2 > '0000-00-00 00:00:00', @2, null)
BT18: =IF(LEFT(AC27,4)="DATA", "if(@"&B27-5&" > '0000-00-00 00:00:00', @"&B27-5&", null)","if(nullif( @"&B27-5&",'') > '', @"&B27-5&", null )") -> if(nullif( @2,'') > '', @2, null )
B19: ■カラム情報 | BP19: ="DROP TABLE IF EXISTS `"&$G$8&"`.`"&$G$10&"`;" -> DROP TABLE IF EXISTS `POS_MASTER`.`ItemMaster`;
B20: No. | D20: 論理名 | R20: 物理名 | AC20: データ型 | AH20: PK | AJ20: Not Null | AM20: デフォルト | AT20: 備考 | BP20: ="CREATE TABLE `"&$G$8&"`.`"&$G$10&"` (" -> CREATE TABLE `POS_MASTER`.`ItemMaster` (
B21: 1 | D21: レコードID | R21: RECORD_ID | AC21: bigint | AJ21: Y | AM21: 自動追加 | BP21: `RECORD_ID` bigint NOT NULL AUTO_INCREMENT COMMENT 'レコードID'
B22: =B21+1 -> 2 | D22: レコード作成日付 | R22: RECORD_CREATE_DATE | AC22: date | AJ22: Y | AM22: CURRENT_DATE | BP22: ,`RECORD_CREATE_DATE` date NOT NULL COMMENT 'レコード作成日付'
B23: =B22+1 -> 3 | D23: レコード作成時間 | R23: RECORD_CREATE_TIME | AC23: time | AJ23: Y | AM23: CURRENT_TIME | BP23: ,`RECORD_CREATE_TIME` time NOT NULL COMMENT 'レコード作成時間'
B24: =B23+1 -> 4 | D24: レコード更新日付 | R24: RECORD_UPDATE_DATE | AC24: date | AJ24: Y | AM24: CURRENT_DATE | AT24: トリガーにより更新 | BP24: ,`RECORD_UPDATE_DATE` date NOT NULL COMMENT 'レコード更新日付/トリガーにより更新' | BV24: ="UPDATE `POS_MASTER`.`"&$G$10&"` A,`TMP`.`"&$G$10&"` B" -> UPDATE `POS_MASTER`.`ItemMaster` A,`TMP`.`ItemMaster` B
B25: =B24+1 -> 5 | D25: レコード更新時間 | R25: RECORD_UPDATE_TIME | AC25: time | AJ25: Y | AM25: CURRENT_TIME | AT25: トリガーにより更新 | BP25: ,`RECORD_UPDATE_TIME` time NOT NULL COMMENT 'レコード更新時間/トリガーにより更新' | BR25: ="DROP TABLE IF EXISTS `TMP`.`"&$G$10&"`;" -> DROP TABLE IF EXISTS `TMP`.`ItemMaster`; | BT25: ="LOAD DATA INFILE 'C:/04_DATAFILE/"&$G$10&"/TMP/"&$G$10&".CSV' " -> LOAD DATA INFILE 'C:/04_DATAFILE/ItemMaster/TMP/ItemMaster.CSV' | BV25: SET
A26: @1 | B26: =B25+1 -> 6 | D26: レコード無効フラグ | R26: RECORD_VOID_FLAG | AC26: char(1) | AJ26: Y | AM26: "" | AT26: 0: 有効フラグ、 1:無効フラグ | BP26: ,`RECORD_VOID_FLAG` char(1) NOT NULL DEFAULT '' COMMENT 'レコード無効フラグ '''': 有効フラグ、 1:無効フラグ' | BR26: ="CREATE TABLE `TMP`.`"&G10&"` (" -> CREATE TABLE `TMP`.`ItemMaster` ( | BT26: ="REPLACE INTO TABLE TMP.`"&$G$10&"` FIELDS TERMINATED BY ',' ENCLOSED BY '\""' LINES TERMINATED BY '\r\n' (" -> REPLACE INTO TABLE TMP.`ItemMaster` FIELDS TERMINATED BY ',' ENCLOSED BY '\"' LINES TERMINATED BY '\r\n' ( | BX26: ="INSERT INTO `POS_MASTER`.`"&$G$10&"` (" -> INSERT INTO `POS_MASTER`.`ItemMaster` ( | BZ26: ) SELECT
A27: @2 | B27: =B26+1 -> 7 | D27: 企業コード | R27: CompanyCode | AC27: {=_xlfn.SWITCH(BM27,"nvarchar","varchar("&BN27&")","smallint","smallint","date","date","money","decimal(19,4)","numeric","numeric("&BN27&")","int","int","bit","char(1)","datetime2","datetime","time","time")} -> varchar(10) | AH27: 1 | AT27: 会社コード | BM27: nvarchar | BN27: 10 | BP27: =",`"&R27&"` "&AC27&" "&IF(AJ27="Y","NOT NULL","")&" COMMENT '"&D27&"'" -> ,`CompanyCode` varchar(10) COMMENT '企業コード' | BR27: ="`"&R27&"` "&AC27&" "&IF(AJ27="Y","NOT NULL","") -> `CompanyCode` varchar(10) | BT27: ="`"&R27&"`" -> `CompanyCode` | BV27: ="A.`"&R27&"` = B.`"&R27&"`" -> A.`CompanyCode` = B.`CompanyCode` | BX27: ="`"&R27&"`" -> `CompanyCode` | BZ27: ="`"&R27&"`" -> `CompanyCode`
A28: @3 | B28: =B27+1 -> 8 | D28: 店舗コード | R28: StoreCode | AC28: {=_xlfn.SWITCH(BM28,"nvarchar","varchar("&BN28&")","smallint","smallint","date","date","money","decimal(19,4)","numeric","numeric("&BN28&")","int","int","bit","char(1)","datetime2","datetime","time","time")} -> varchar(10) | AH28: 2 | AT28: 店舗コード | BM28: nvarchar | BN28: 10 | BP28: =",`"&R28&"` "&AC28&" "&IF(AJ28="Y","NOT NULL","")&" COMMENT '"&D28&"'" -> ,`StoreCode` varchar(10) COMMENT '店舗コード' | BR28: =",`"&R28&"` "&AC28&" "&IF(AJ28="Y","NOT NULL","") -> ,`StoreCode` varchar(10) | BT28: =",`"&R28&"`" -> ,`StoreCode` | BV28: =",A.`"&R28&"` = B.`"&R28&"`" -> ,A.`StoreCode` = B.`StoreCode` | BX28: =",`"&R28&"`" -> ,`StoreCode` | BZ28: =",`"&R28&"`" -> ,`StoreCode`
A29: @4 | B29: =B28+1 -> 9 | D29: 単品コード | R29: ItemCode | AC29: {=_xlfn.SWITCH(BM29,"nvarchar","varchar("&BN29&")","smallint","smallint","date","date","money","decimal(19,4)","numeric","numeric("&BN29&")","int","int","bit","char(1)","datetime2","datetime","time","time")} -> varchar(26) | AH29: 3 | AT29: 商品コード 商品登録時の検索、画面/レシートへの表示に使用 | BM29: nvarchar | BN29: 26 | BP29: =",`"&R29&"` "&AC29&" "&IF(AJ29="Y","NOT NULL","")&" COMMENT '"&D29&"'" -> ,`ItemCode` varchar(26) COMMENT '単品コード' | BR29: =",`"&R29&"` "&AC29&" "&IF(AJ29="Y","NOT NULL","") -> ,`ItemCode` varchar(26) | BT29: =",`"&R29&"`" -> ,`ItemCode` | BV29: =",A.`"&R29&"` = B.`"&R29&"`" -> ,A.`ItemCode` = B.`ItemCode` | BX29: =",`"&R29&"`" -> ,`ItemCode` | BZ29: =",`"&R29&"`" -> ,`ItemCode`
A30: @5 | B30: =B29+1 -> 10 | D30: 適用日 | R30: ApplyDate | AC30: {=_xlfn.SWITCH(BM30,"nvarchar","varchar("&BN30&")","smallint","smallint","date","date","money","decimal(19,4)","numeric","numeric("&BN30&")","int","int","bit","char(1)","datetime2","datetime","time","time")} -> date | AH30: 4 | AT30: 商品情報が適用される営業日を設定する | BM30: date | BP30: =",`"&R30&"` "&AC30&" "&IF(AJ30="Y","NOT NULL","")&" COMMENT '"&D30&"'" -> ,`ApplyDate` date COMMENT '適用日' | BR30: =",`"&R30&"` "&AC30&" "&IF(AJ30="Y","NOT NULL","") -> ,`ApplyDate` date | BT30: =",`"&R30&"`" -> ,`ApplyDate` | BV30: =",A.`"&R30&"` = B.`"&R30&"`" -> ,A.`ApplyDate` = B.`ApplyDate` | BX30: =",`"&R30&"`" -> ,`ApplyDate` | BZ30: =",`"&R30&"`" -> ,`ApplyDate`
A31: @6 | B31: =B30+1 -> 11 | D31: 親分類コード | R31: ParentCode | AC31: {=_xlfn.SWITCH(BM31,"nvarchar","varchar("&BN31&")","smallint","smallint","date","date","money","decimal(19,4)","numeric","numeric("&BN31&")","int","int","bit","char(1)","datetime2","datetime","time","time")} -> varchar(10) | AT31: 商品の分類コードを設定する | BM31: nvarchar | BN31: 10 | BP31: =",`"&R31&"` "&AC31&" "&IF(AJ31="Y","NOT NULL","")&" COMMENT '"&D31&"'" -> ,`ParentCode` varchar(10) COMMENT '親分類コード' | BR31: =",`"&R31&"` "&AC31&" "&IF(AJ31="Y","NOT NULL","") -> ,`ParentCode` varchar(10) | BT31: =",`"&R31&"`" -> ,`ParentCode` | BV31: =",A.`"&R31&"` = B.`"&R31&"`" -> ,A.`ParentCode` = B.`ParentCode` | BX31: =",`"&R31&"`" -> ,`ParentCode` | BZ31: =",`"&R31&"`" -> ,`ParentCode`
A32: @7 | B32: =B31+1 -> 12 | D32: 商品コード | R32: MyCompanyCode | AC32: {=_xlfn.SWITCH(BM32,"nvarchar","varchar("&BN32&")","smallint","smallint","date","date","money","decimal(19,4)","numeric","numeric("&BN32&")","int","int","bit","char(1)","datetime2","datetime","time","time")} -> varchar(26) | AT32: 自社コード カスミ様の商品管理コードを設定する | BM32: nvarchar | BN32: 26 | BP32: =",`"&R32&"` "&AC32&" "&IF(AJ32="Y","NOT NULL","")&" COMMENT '"&D32&"'" -> ,`MyCompanyCode` varchar(26) COMMENT '商品コード' | BR32: =",`"&R32&"` "&AC32&" "&IF(AJ32="Y","NOT NULL","") -> ,`MyCompanyCode` varchar(26) | BT32: =",`"&R32&"`" -> ,`MyCompanyCode` | BV32: =",A.`"&R32&"` = B.`"&R32&"`" -> ,A.`MyCompanyCode` = B.`MyCompanyCode` | BX32: =",`"&R32&"`" -> ,`MyCompanyCode` | BZ32: =",`"&R32&"`" -> ,`MyCompanyCode`
A33: @8 | B33: =B32+1 -> 13 | D33: 親JANコード | R33: ParentItemCode | AC33: {=_xlfn.SWITCH(BM33,"nvarchar","varchar("&BN33&")","smallint","smallint","date","date","money","decimal(19,4)","numeric","numeric("&BN33&")","int","int","bit","char(1)","datetime2","datetime","time","time")} -> varchar(26) | AT33: 単品コードの親JAN情報 | BM33: nvarchar | BN33: 26 | BP33: =",`"&R33&"` "&AC33&" "&IF(AJ33="Y","NOT NULL","")&" COMMENT '"&D33&"'" -> ,`ParentItemCode` varchar(26) COMMENT '親JANコード' | BR33: =",`"&R33&"` "&AC33&" "&IF(AJ33="Y","NOT NULL","") -> ,`ParentItemCode` varchar(26) | BT33: =",`"&R33&"`" -> ,`ParentItemCode` | BV33: =",A.`"&R33&"` = B.`"&R33&"`" -> ,A.`ParentItemCode` = B.`ParentItemCode` | BX33: =",`"&R33&"`" -> ,`ParentItemCode` | BZ33: =",`"&R33&"`" -> ,`ParentItemCode`
A34: @9 | B34: =B33+1 -> 14 | D34: 説明 （画面、レシート、ラインディスプレイにて使用） | R34: Description | AC34: {=_xlfn.SWITCH(BM34,"nvarchar","varchar("&BN34&")","smallint","smallint","date","date","money","decimal(19,4)","numeric","numeric("&BN34&")","int","int","bit","char(1)","datetime2","datetime","time","time")} -> varchar(50) | AT34: 商品の名称を設定する 画面、レシート、ラインディスプレイにて使用 | BM34: nvarchar | BN34: 50 | BP34: =",`"&R34&"` "&AC34&" "&IF(AJ34="Y","NOT NULL","")&" COMMENT '"&D34&"'" -> ,`Description` varchar(50) COMMENT '説明 （画面、レシート、ラインディスプレイにて使用）' | BR34: =",`"&R34&"` "&AC34&" "&IF(AJ34="Y","NOT NULL","") -> ,`Description` varchar(50) | BT34: =",`"&R34&"`" -> ,`Description` | BV34: =",A.`"&R34&"` = B.`"&R34&"`" -> ,A.`Description` = B.`Description` | BX34: =",`"&R34&"`" -> ,`Description` | BZ34: =",`"&R34&"`" -> ,`Description`
A35: @10 | B35: =B34+1 -> 15 | D35: 簡略説明 （ラインディスプレイ（半角カナ用）にて使用） | R35: DescriptionShort | AC35: {=_xlfn.SWITCH(BM35,"nvarchar","varchar("&BN35&")","smallint","smallint","date","date","money","decimal(19,4)","numeric","numeric("&BN35&")","int","int","bit","char(1)","datetime2","datetime","time","time")} -> varchar(30) | AT35: 商品の名称を設定する ラインディスプレイ（半角カナ用）にて使用 | BM35: nvarchar | BN35: 30 | BP35: =",`"&R35&"` "&AC35&" "&IF(AJ35="Y","NOT NULL","")&" COMMENT '"&D35&"'" -> ,`DescriptionShort` varchar(30) COMMENT '簡略説明 （ラインディスプレイ（半角カナ用）にて使用）' | BR35: =",`"&R35&"` "&AC35&" "&IF(AJ35="Y","NOT NULL","") -> ,`DescriptionShort` varchar(30) | BT35: =",`"&R35&"`" -> ,`DescriptionShort` | BV35: =",A.`"&R35&"` = B.`"&R35&"`" -> ,A.`DescriptionShort` = B.`DescriptionShort` | BX35: =",`"&R35&"`" -> ,`DescriptionShort` | BZ35: =",`"&R35&"`" -> ,`DescriptionShort`
A36: @11 | B36: =B35+1 -> 16 | D36: 詳細説明 （レポートにて使用） | R36: DescriptionLong | AC36: {=_xlfn.SWITCH(BM36,"nvarchar","varchar("&BN36&")","smallint","smallint","date","date","money","decimal(19,4)","numeric","numeric("&BN36&")","int","int","bit","char(1)","datetime2","datetime","time","time")} -> varchar(100) | AT36: 商品の名称を設定する レポートにて使用 | BM36: nvarchar | BN36: 100 | BP36: =",`"&R36&"` "&AC36&" "&IF(AJ36="Y","NOT NULL","")&" COMMENT '"&D36&"'" -> ,`DescriptionLong` varchar(100) COMMENT '詳細説明 （レポートにて使用）' | BR36: =",`"&R36&"` "&AC36&" "&IF(AJ36="Y","NOT NULL","") -> ,`DescriptionLong` varchar(100) | BT36: =",`"&R36&"`" -> ,`DescriptionLong` | BV36: =",A.`"&R36&"` = B.`"&R36&"`" -> ,A.`DescriptionLong` = B.`DescriptionLong` | BX36: =",`"&R36&"`" -> ,`DescriptionLong` | BZ36: =",`"&R36&"`" -> ,`DescriptionLong`
A37: @12 | B37: =B36+1 -> 17 | D37: 補足説明 (規格) | R37: SubDescription | AC37: {=_xlfn.SWITCH(BM37,"nvarchar","varchar("&BN37&")","smallint","smallint","date","date","money","decimal(19,4)","numeric","numeric("&BN37&")","int","int","bit","char(1)","datetime2","datetime","time","time")} -> varchar(5) | BM37: nvarchar | BN37: 5 | BP37: =",`"&R37&"` "&AC37&" "&IF(AJ37="Y","NOT NULL","")&" COMMENT '"&D37&"'" -> ,`SubDescription` varchar(5) COMMENT '補足説明 (規格)' | BR37: =",`"&R37&"` "&AC37&" "&IF(AJ37="Y","NOT NULL","") -> ,`SubDescription` varchar(5) | BT37: =",`"&R37&"`" -> ,`SubDescription` | BV37: =",A.`"&R37&"` = B.`"&R37&"`" -> ,A.`SubDescription` = B.`SubDescription` | BX37: =",`"&R37&"`" -> ,`SubDescription` | BZ37: =",`"&R37&"`" -> ,`SubDescription`
A38: @13 | B38: =B37+1 -> 18 | D38: メーカー | R38: Manufacturer | AC38: {=_xlfn.SWITCH(BM38,"nvarchar","varchar("&BN38&")","smallint","smallint","date","date","money","decimal(19,4)","numeric","numeric("&BN38&")","int","int","bit","char(1)","datetime2","datetime","time","time")} -> varchar(50) | BM38: nvarchar | BN38: 50 | BP38: =",`"&R38&"` "&AC38&" "&IF(AJ38="Y","NOT NULL","")&" COMMENT '"&D38&"'" -> ,`Manufacturer` varchar(50) COMMENT 'メーカー' | BR38: =",`"&R38&"` "&AC38&" "&IF(AJ38="Y","NOT NULL","") -> ,`Manufacturer` varchar(50) | BT38: =",`"&R38&"`" -> ,`Manufacturer` | BV38: =",A.`"&R38&"` = B.`"&R38&"`" -> ,A.`Manufacturer` = B.`Manufacturer` | BX38: =",`"&R38&"`" -> ,`Manufacturer` | BZ38: =",`"&R38&"`" -> ,`Manufacturer`
A39: @14 | B39: =B38+1 -> 19 | D39: 単価 | R39: UnitPrice | AC39: {=_xlfn.SWITCH(BM39,"nvarchar","varchar("&BN39&")","smallint","smallint","date","date","money","decimal(19,4)","numeric","numeric("&BN39&")","int","int","bit","char(1)","datetime2","datetime","time","time")} -> decimal(19,4) | AT39: 商品の販売単価を設定する | BM39: money | BP39: =",`"&R39&"` "&AC39&" "&IF(AJ39="Y","NOT NULL","")&" COMMENT '"&D39&"'" -> ,`UnitPrice` decimal(19,4) COMMENT '単価' | BR39: =",`"&R39&"` "&AC39&" "&IF(AJ39="Y","NOT NULL","") -> ,`UnitPrice` decimal(19,4) | BT39: =",`"&R39&"`" -> ,`UnitPrice` | BV39: =",A.`"&R39&"` = B.`"&R39&"`" -> ,A.`UnitPrice` = B.`UnitPrice` | BX39: =",`"&R39&"`" -> ,`UnitPrice` | BZ39: =",`"&R39&"`" -> ,`UnitPrice`
A40: @15 | B40: =B39+1 -> 20 | D40: 本部指示売価 | R40: HeadquartersIndicationPrice | AC40: {=_xlfn.SWITCH(BM40,"nvarchar","varchar("&BN40&")","smallint","smallint","date","date","money","decimal(19,4)","numeric","numeric("&BN40&")","int","int","bit","char(1)","datetime2","datetime","time","time")} -> decimal(19,4) | BM40: money | BP40: =",`"&R40&"` "&AC40&" "&IF(AJ40="Y","NOT NULL","")&" COMMENT '"&D40&"'" -> ,`HeadquartersIndicationPrice` decimal(19,4) COMMENT '本部指示売価' | BR40: =",`"&R40&"` "&AC40&" "&IF(AJ40="Y","NOT NULL","") -> ,`HeadquartersIndicationPrice` decimal(19,4) | BT40: =",`"&R40&"`" -> ,`HeadquartersIndicationPrice` | BV40: =",A.`"&R40&"` = B.`"&R40&"`" -> ,A.`HeadquartersIndicationPrice` = B.`HeadquartersIndicationPrice` | BX40: =",`"&R40&"`" -> ,`HeadquartersIndicationPrice` | BZ40: =",`"&R40&"`" -> ,`HeadquartersIndicationPrice`
A41: @16 | B41: =B40+1 -> 21 | D41: 原価 | R41: CostPrice | AC41: {=_xlfn.SWITCH(BM41,"nvarchar","varchar("&BN41&")","smallint","smallint","date","date","money","decimal(19,4)","numeric","numeric("&BN41&")","int","int","bit","char(1)","datetime2","datetime","time","time")} -> decimal(19,4) | AT41: 商品の原価を設定する。 原価額ではなく原価率で管理する場合はNULLとする ※原価、値入率が未設定(NULL)の場合、分類マスタの値入率が採用される | BM41: money | BP41: =",`"&R41&"` "&AC41&" "&IF(AJ41="Y","NOT NULL","")&" COMMENT '"&D41&"'" -> ,`CostPrice` decimal(19,4) COMMENT '原価' | BR41: =",`"&R41&"` "&AC41&" "&IF(AJ41="Y","NOT NULL","") -> ,`CostPrice` decimal(19,4) | BT41: =",`"&R41&"`" -> ,`CostPrice` | BV41: =",A.`"&R41&"` = B.`"&R41&"`" -> ,A.`CostPrice` = B.`CostPrice` | BX41: =",`"&R41&"`" -> ,`CostPrice` | BZ41: =",`"&R41&"`" -> ,`CostPrice`
A42: @17 | B42: =B41+1 -> 22 | D42: 値入率 | R42: MarkupRatio | AC42: {=_xlfn.SWITCH(BM42,"nvarchar","varchar("&BN42&")","smallint","smallint","date","date","money","decimal(19,4)","numeric","numeric("&BN42&")","int","int","bit","char(1)","datetime2","datetime","time","time")} -> numeric(5, 2) | AT42: 粗利率を設定する（100-原価率) 原価率ではなく原価額で管理する場合はNULLとする ※原価、値入率が未設定(NULL)の場合、分類マスタの値入率が採用される | BM42: numeric | BN42: 5, 2 | BP42: =",`"&R42&"` "&AC42&" "&IF(AJ42="Y","NOT NULL","")&" COMMENT '"&D42&"'" -> ,`MarkupRatio` numeric(5, 2) COMMENT '値入率' | BR42: =",`"&R42&"` "&AC42&" "&IF(AJ42="Y","NOT NULL","") -> ,`MarkupRatio` numeric(5, 2) | BT42: =",`"&R42&"`" -> ,`MarkupRatio` | BV42: =",A.`"&R42&"` = B.`"&R42&"`" -> ,A.`MarkupRatio` = B.`MarkupRatio` | BX42: =",`"&R42&"`" -> ,`MarkupRatio` | BZ42: =",`"&R42&"`" -> ,`MarkupRatio`
A43: @18 | B43: =B42+1 -> 23 | D43: 税グループコード | R43: TaxGroupCode | AC43: {=_xlfn.SWITCH(BM43,"nvarchar","varchar("&BN43&")","smallint","smallint","date","date","money","decimal(19,4)","numeric","numeric("&BN43&")","int","int","bit","char(1)","datetime2","datetime","time","time")} -> varchar(2) | AT43: 税率セットの定義コードを設定する NULL：上位参照 "01" ：外税8% （2019/10/1以降、軽減税率) "02" ：内税8% （2019/10/1以降、軽減税率) "03" ：非課税 "11" ：外税10% "12" ：内税10% "31" ：外税8%(返品用) "32" ：内税8%(返品用) | BM43: nvarchar | BN43: 2 | BP43: =",`"&R43&"` "&AC43&" "&IF(AJ43="Y","NOT NULL","")&" COMMENT '"&D43&"'" -> ,`TaxGroupCode` varchar(2) COMMENT '税グループコード' | BR43: =",`"&R43&"` "&AC43&" "&IF(AJ43="Y","NOT NULL","") -> ,`TaxGroupCode` varchar(2) | BT43: =",`"&R43&"`" -> ,`TaxGroupCode` | BV43: =",A.`"&R43&"` = B.`"&R43&"`" -> ,A.`TaxGroupCode` = B.`TaxGroupCode` | BX43: =",`"&R43&"`" -> ,`TaxGroupCode` | BZ43: =",`"&R43&"`" -> ,`TaxGroupCode`
A44: @19 | B44: =B43+1 -> 24 | D44: 税変換種別 | R44: TaxConvertType | AC44: {=_xlfn.SWITCH(BM44,"nvarchar","varchar("&BN44&")","smallint","smallint","date","date","money","decimal(19,4)","numeric","numeric("&BN44&")","int","int","bit","char(1)","datetime2","datetime","time","time")} -> int | AT44: 税変換種別を設定する 0：変換なし 1：みなし内税 | BM44: int | BP44: =",`"&R44&"` "&AC44&" "&IF(AJ44="Y","NOT NULL","")&" COMMENT '"&D44&"'" -> ,`TaxConvertType` int COMMENT '税変換種別' | BR44: =",`"&R44&"` "&AC44&" "&IF(AJ44="Y","NOT NULL","") -> ,`TaxConvertType` int | BT44: =",`"&R44&"`" -> ,`TaxConvertType` | BV44: =",A.`"&R44&"` = B.`"&R44&"`" -> ,A.`TaxConvertType` = B.`TaxConvertType` | BX44: =",`"&R44&"`" -> ,`TaxConvertType` | BZ44: =",`"&R44&"`" -> ,`TaxConvertType`
A45: @20 | B45: =B44+1 -> 25 | D45: 容量 | R45: Volume | AC45: {=_xlfn.SWITCH(BM45,"nvarchar","varchar("&BN45&")","smallint","smallint","date","date","money","decimal(19,4)","numeric","numeric("&BN45&")","int","int","bit","char(1)","datetime2","datetime","time","time")} -> numeric(7, 0) | BM45: numeric | BN45: 7, 0 | BP45: =",`"&R45&"` "&AC45&" "&IF(AJ45="Y","NOT NULL","")&" COMMENT '"&D45&"'" -> ,`Volume` numeric(7, 0) COMMENT '容量' | BR45: =",`"&R45&"` "&AC45&" "&IF(AJ45="Y","NOT NULL","") -> ,`Volume` numeric(7, 0) | BT45: =",`"&R45&"`" -> ,`Volume` | BV45: =",A.`"&R45&"` = B.`"&R45&"`" -> ,A.`Volume` = B.`Volume` | BX45: =",`"&R45&"`" -> ,`Volume` | BZ45: =",`"&R45&"`" -> ,`Volume`
A46: @21 | B46: =B45+1 -> 26 | D46: 入数 | R46: NumberOfPiecesPerBox | AC46: {=_xlfn.SWITCH(BM46,"nvarchar","varchar("&BN46&")","smallint","smallint","date","date","money","decimal(19,4)","numeric","numeric("&BN46&")","int","int","bit","char(1)","datetime2","datetime","time","time")} -> numeric(5, 0) | BM46: numeric | BN46: 5, 0 | BP46: =",`"&R46&"` "&AC46&" "&IF(AJ46="Y","NOT NULL","")&" COMMENT '"&D46&"'" -> ,`NumberOfPiecesPerBox` numeric(5, 0) COMMENT '入数' | BR46: =",`"&R46&"` "&AC46&" "&IF(AJ46="Y","NOT NULL","") -> ,`NumberOfPiecesPerBox` numeric(5, 0) | BT46: =",`"&R46&"`" -> ,`NumberOfPiecesPerBox` | BV46: =",A.`"&R46&"` = B.`"&R46&"`" -> ,A.`NumberOfPiecesPerBox` = B.`NumberOfPiecesPerBox` | BX46: =",`"&R46&"`" -> ,`NumberOfPiecesPerBox` | BZ46: =",`"&R46&"`" -> ,`NumberOfPiecesPerBox`
A47: @22 | B47: =B46+1 -> 27 | D47: 現金以外決済不可フラグ | R47: IsCashOnly | AC47: {=_xlfn.SWITCH(BM47,"nvarchar","varchar("&BN47&")","smallint","smallint","date","date","money","decimal(19,4)","numeric","numeric("&BN47&")","int","int","bit","char(1)","datetime2","datetime","time","time")} -> char(1) | AT47: 支払方法を現金に限定するか否かを設定する NULL：上位参照 0：現金以外決済可 1：現金以外決済不可 | BM47: bit | BP47: =",`"&R47&"` "&AC47&" "&IF(AJ47="Y","NOT NULL","")&" COMMENT '"&D47&"'" -> ,`IsCashOnly` char(1) COMMENT '現金以外決済不可フラグ' | BR47: =",`"&R47&"` "&AC47&" "&IF(AJ47="Y","NOT NULL","") -> ,`IsCashOnly` char(1) | BT47: =",`"&R47&"`" -> ,`IsCashOnly` | BV47: =",A.`"&R47&"` = B.`"&R47&"`" -> ,A.`IsCashOnly` = B.`IsCashOnly` | BX47: =",`"&R47&"`" -> ,`IsCashOnly` | BZ47: =",`"&R47&"`" -> ,`IsCashOnly`
A48: @23 | B48: =B47+1 -> 28 | D48: 手動アイテム値引禁止フラグ | R48: IsItemManualDiscountProhibition | AC48: {=_xlfn.SWITCH(BM48,"nvarchar","varchar("&BN48&")","smallint","smallint","date","date","money","decimal(19,4)","numeric","numeric("&BN48&")","int","int","bit","char(1)","datetime2","datetime","time","time")} -> char(1) | AT48: POS操作による値引を許可するか否かを設定する NULL：上位参照 0：手動アイテム値引可 1：手動アイテム値引不可 | BM48: bit | BP48: =",`"&R48&"` "&AC48&" "&IF(AJ48="Y","NOT NULL","")&" COMMENT '"&D48&"'" -> ,`IsItemManualDiscountProhibition` char(1) COMMENT '手動アイテム値引禁止フラグ' | BR48: =",`"&R48&"` "&AC48&" "&IF(AJ48="Y","NOT NULL","") -> ,`IsItemManualDiscountProhibition` char(1) | BT48: =",`"&R48&"`" -> ,`IsItemManualDiscountProhibition` | BV48: =",A.`"&R48&"` = B.`"&R48&"`" -> ,A.`IsItemManualDiscountProhibition` = B.`IsItemManualDiscountProhibition` | BX48: =",`"&R48&"`" -> ,`IsItemManualDiscountProhibition` | BZ48: =",`"&R48&"`" -> ,`IsItemManualDiscountProhibition`
A49: @24 | B49: =B48+1 -> 29 | D49: 小計値引禁止フラグ | R49: IsSubTotalDiscountProhibition | AC49: {=_xlfn.SWITCH(BM49,"nvarchar","varchar("&BN49&")","smallint","smallint","date","date","money","decimal(19,4)","numeric","numeric("&BN49&")","int","int","bit","char(1)","datetime2","datetime","time","time")} -> char(1) | AT49: クーポン等による小計値引の対象とするか否かを設定する NULL：上位参照 0：小計値引可 1：小計値引不可 | BM49: bit | BP49: =",`"&R49&"` "&AC49&" "&IF(AJ49="Y","NOT NULL","")&" COMMENT '"&D49&"'" -> ,`IsSubTotalDiscountProhibition` char(1) COMMENT '小計値引禁止フラグ' | BR49: =",`"&R49&"` "&AC49&" "&IF(AJ49="Y","NOT NULL","") -> ,`IsSubTotalDiscountProhibition` char(1) | BT49: =",`"&R49&"`" -> ,`IsSubTotalDiscountProhibition` | BV49: =",A.`"&R49&"` = B.`"&R49&"`" -> ,A.`IsSubTotalDiscountProhibition` = B.`IsSubTotalDiscountProhibition` | BX49: =",`"&R49&"`" -> ,`IsSubTotalDiscountProhibition` | BZ49: =",`"&R49&"`" -> ,`IsSubTotalDiscountProhibition`
A50: @25 | B50: =B49+1 -> 30 | D50: 売価変更禁止フラグ | R50: IsChangePriceProhibition | AC50: {=_xlfn.SWITCH(BM50,"nvarchar","varchar("&BN50&")","smallint","smallint","date","date","money","decimal(19,4)","numeric","numeric("&BN50&")","int","int","bit","char(1)","datetime2","datetime","time","time")} -> char(1) | AT50: POS操作による売価変更を許可するか否かを設定する NULL：上位参照 0：売価変更可 1：売価変更不可 | BM50: bit | BP50: =",`"&R50&"` "&AC50&" "&IF(AJ50="Y","NOT NULL","")&" COMMENT '"&D50&"'" -> ,`IsChangePriceProhibition` char(1) COMMENT '売価変更禁止フラグ' | BR50: =",`"&R50&"` "&AC50&" "&IF(AJ50="Y","NOT NULL","") -> ,`IsChangePriceProhibition` char(1) | BT50: =",`"&R50&"`" -> ,`IsChangePriceProhibition` | BV50: =",A.`"&R50&"` = B.`"&R50&"`" -> ,A.`IsChangePriceProhibition` = B.`IsChangePriceProhibition` | BX50: =",`"&R50&"`" -> ,`IsChangePriceProhibition` | BZ50: =",`"&R50&"`" -> ,`IsChangePriceProhibition`
A51: @26 | B51: =B50+1 -> 31 | D51: 自動値引き不可フラグ | R51: IsAutoDiscountProhibition | AC51: {=_xlfn.SWITCH(BM51,"nvarchar","varchar("&BN51&")","smallint","smallint","date","date","money","decimal(19,4)","numeric","numeric("&BN51&")","int","int","bit","char(1)","datetime2","datetime","time","time")} -> char(1) | AT51: 分類レベルでの自動値引設定にて値引の対象外とするか否かを設定する 0：自動値引き可 1：自動値引き不可 | BM51: bit | BP51: =",`"&R51&"` "&AC51&" "&IF(AJ51="Y","NOT NULL","")&" COMMENT '"&D51&"'" -> ,`IsAutoDiscountProhibition` char(1) COMMENT '自動値引き不可フラグ' | BR51: =",`"&R51&"` "&AC51&" "&IF(AJ51="Y","NOT NULL","") -> ,`IsAutoDiscountProhibition` char(1) | BT51: =",`"&R51&"`" -> ,`IsAutoDiscountProhibition` | BV51: =",A.`"&R51&"` = B.`"&R51&"`" -> ,A.`IsAutoDiscountProhibition` = B.`IsAutoDiscountProhibition` | BX51: =",`"&R51&"`" -> ,`IsAutoDiscountProhibition` | BZ51: =",`"&R51&"`" -> ,`IsAutoDiscountProhibition`
A52: @27 | B52: =B51+1 -> 32 | D52: 単価強制入力フラグ | R52: IsUnitPriceForced | AC52: {=_xlfn.SWITCH(BM52,"nvarchar","varchar("&BN52&")","smallint","smallint","date","date","money","decimal(19,4)","numeric","numeric("&BN52&")","int","int","bit","char(1)","datetime2","datetime","time","time")} -> char(1) | AT52: 商品登録時、単価入力を求めるか否かを設定する ０：単価強制入力なし １：単価強制入力あり | BM52: bit | BP52: =",`"&R52&"` "&AC52&" "&IF(AJ52="Y","NOT NULL","")&" COMMENT '"&D52&"'" -> ,`IsUnitPriceForced` char(1) COMMENT '単価強制入力フラグ' | BR52: =",`"&R52&"` "&AC52&" "&IF(AJ52="Y","NOT NULL","") -> ,`IsUnitPriceForced` char(1) | BT52: =",`"&R52&"`" -> ,`IsUnitPriceForced` | BV52: =",A.`"&R52&"` = B.`"&R52&"`" -> ,A.`IsUnitPriceForced` = B.`IsUnitPriceForced` | BX52: =",`"&R52&"`" -> ,`IsUnitPriceForced` | BZ52: =",`"&R52&"`" -> ,`IsUnitPriceForced`
A53: @28 | B53: =B52+1 -> 33 | D53: ポイント除外フラグ | R53: IsPointProhibition | AC53: {=_xlfn.SWITCH(BM53,"nvarchar","varchar("&BN53&")","smallint","smallint","date","date","money","decimal(19,4)","numeric","numeric("&BN53&")","int","int","bit","char(1)","datetime2","datetime","time","time")} -> char(1) | AT53: 対象商品販売時、ポイント付与対象から除外するか否かを設定する NULL：上位参照 0：ポイント対象 1：ポイント対象外 | BM53: bit | BP53: =",`"&R53&"` "&AC53&" "&IF(AJ53="Y","NOT NULL","")&" COMMENT '"&D53&"'" -> ,`IsPointProhibition` char(1) COMMENT 'ポイント除外フラグ' | BR53: =",`"&R53&"` "&AC53&" "&IF(AJ53="Y","NOT NULL","") -> ,`IsPointProhibition` char(1) | BT53: =",`"&R53&"`" -> ,`IsPointProhibition` | BV53: =",A.`"&R53&"` = B.`"&R53&"`" -> ,A.`IsPointProhibition` = B.`IsPointProhibition` | BX53: =",`"&R53&"`" -> ,`IsPointProhibition` | BZ53: =",`"&R53&"`" -> ,`IsPointProhibition`
A54: @29 | B54: =B53+1 -> 34 | D54: 販売制限商品区分 | R54: SalesRestrictionItemArea | AC54: {=_xlfn.SWITCH(BM54,"nvarchar","varchar("&BN54&")","smallint","smallint","date","date","money","decimal(19,4)","numeric","numeric("&BN54&")","int","int","bit","char(1)","datetime2","datetime","time","time")} -> varchar(2) | AT54: 設定ありで所属する分類にも販売制限商品区分が設定されている場合：《単品マスタ》の設定を採用 NULL：上位参照 1:分類なし 2:第1分類 3:指定第2分類 4:第2分類 5:第3分類 6:要指導 | BM54: nvarchar | BN54: 2 | BP54: =",`"&R54&"` "&AC54&" "&IF(AJ54="Y","NOT NULL","")&" COMMENT '"&D54&"'" -> ,`SalesRestrictionItemArea` varchar(2) COMMENT '販売制限商品区分' | BR54: =",`"&R54&"` "&AC54&" "&IF(AJ54="Y","NOT NULL","") -> ,`SalesRestrictionItemArea` varchar(2) | BT54: =",`"&R54&"`" -> ,`SalesRestrictionItemArea` | BV54: =",A.`"&R54&"` = B.`"&R54&"`" -> ,A.`SalesRestrictionItemArea` = B.`SalesRestrictionItemArea` | BX54: =",`"&R54&"`" -> ,`SalesRestrictionItemArea` | BZ54: =",`"&R54&"`" -> ,`SalesRestrictionItemArea`
A55: @30 | B55: =B54+1 -> 35 | D55: 販売制限年齢区分 | R55: SalesAlertAge | AC55: {=_xlfn.SWITCH(BM55,"nvarchar","varchar("&BN55&")","smallint","smallint","date","date","money","decimal(19,4)","numeric","numeric("&BN55&")","int","int","bit","char(1)","datetime2","datetime","time","time")} -> numeric(3,0) | AT55: 年齢制限を行う場合のみ制限する年齢 (設定ありで所属する分類にも販売制限年齢が設定されている場合：《単品マスタ》の設定を採用 NULL：上位参照 0の場合：年齢制限なし) | BM55: numeric | BN55: 3,0 | BP55: =",`"&R55&"` "&AC55&" "&IF(AJ55="Y","NOT NULL","")&" COMMENT '"&D55&"'" -> ,`SalesAlertAge` numeric(3,0) COMMENT '販売制限年齢区分' | BR55: =",`"&R55&"` "&AC55&" "&IF(AJ55="Y","NOT NULL","") -> ,`SalesAlertAge` numeric(3,0) | BT55: =",`"&R55&"`" -> ,`SalesAlertAge` | BV55: =",A.`"&R55&"` = B.`"&R55&"`" -> ,A.`SalesAlertAge` = B.`SalesAlertAge` | BX55: =",`"&R55&"`" -> ,`SalesAlertAge` | BZ55: =",`"&R55&"`" -> ,`SalesAlertAge`
A56: @31 | B56: =B55+1 -> 36 | D56: 保証書発行フラグ | R56: IsWarrantyReceiptPrint | AC56: {=_xlfn.SWITCH(BM56,"nvarchar","varchar("&BN56&")","smallint","smallint","date","date","money","decimal(19,4)","numeric","numeric("&BN56&")","int","int","bit","char(1)","datetime2","datetime","time","time")} -> char(1) | AT56: 対象商品販売時、保証書を発行するか否かを設定する 0：発行しない 1：発行する | BM56: bit | BP56: =",`"&R56&"` "&AC56&" "&IF(AJ56="Y","NOT NULL","")&" COMMENT '"&D56&"'" -> ,`IsWarrantyReceiptPrint` char(1) COMMENT '保証書発行フラグ' | BR56: =",`"&R56&"` "&AC56&" "&IF(AJ56="Y","NOT NULL","") -> ,`IsWarrantyReceiptPrint` char(1) | BT56: =",`"&R56&"`" -> ,`IsWarrantyReceiptPrint` | BV56: =",A.`"&R56&"` = B.`"&R56&"`" -> ,A.`IsWarrantyReceiptPrint` = B.`IsWarrantyReceiptPrint` | BX56: =",`"&R56&"`" -> ,`IsWarrantyReceiptPrint` | BZ56: =",`"&R56&"`" -> ,`IsWarrantyReceiptPrint`
A57: @32 | B57: =B56+1 -> 37 | D57: 重点区分 | R57: PriorityType | AC57: {=_xlfn.SWITCH(BM57,"nvarchar","varchar("&BN57&")","smallint","smallint","date","date","money","decimal(19,4)","numeric","numeric("&BN57&")","int","int","bit","char(1)","datetime2","datetime","time","time")} -> smallint | AT57: 重点対象商品か 0：対象外 1：対象 | BM57: smallint | BP57: =",`"&R57&"` "&AC57&" "&IF(AJ57="Y","NOT NULL","")&" COMMENT '"&D57&"'" -> ,`PriorityType` smallint COMMENT '重点区分' | BR57: =",`"&R57&"` "&AC57&" "&IF(AJ57="Y","NOT NULL","") -> ,`PriorityType` smallint | BT57: =",`"&R57&"`" -> ,`PriorityType` | BV57: =",A.`"&R57&"` = B.`"&R57&"`" -> ,A.`PriorityType` = B.`PriorityType` | BX57: =",`"&R57&"`" -> ,`PriorityType` | BZ57: =",`"&R57&"`" -> ,`PriorityType`
A58: @33 | B58: =B57+1 -> 38 | D58: 消費税免税タイプ | R58: TaxFreeType | AC58: {=_xlfn.SWITCH(BM58,"nvarchar","varchar("&BN58&")","smallint","smallint","date","date","money","decimal(19,4)","numeric","numeric("&BN58&")","int","int","bit","char(1)","datetime2","datetime","time","time")} -> int | AT58: 免税販売時、対象商品の免税種別を設定する NULL：上位参照 1：消耗品 2：一般品 | BM58: int | BP58: =",`"&R58&"` "&AC58&" "&IF(AJ58="Y","NOT NULL","")&" COMMENT '"&D58&"'" -> ,`TaxFreeType` int COMMENT '消費税免税タイプ' | BR58: =",`"&R58&"` "&AC58&" "&IF(AJ58="Y","NOT NULL","") -> ,`TaxFreeType` int | BT58: =",`"&R58&"`" -> ,`TaxFreeType` | BV58: =",A.`"&R58&"` = B.`"&R58&"`" -> ,A.`TaxFreeType` = B.`TaxFreeType` | BX58: =",`"&R58&"`" -> ,`TaxFreeType` | BZ58: =",`"&R58&"`" -> ,`TaxFreeType`
A59: @34 | B59: =B58+1 -> 39 | D59: 緊急登録フラグ | R59: EmergencyFlag | AC59: {=_xlfn.SWITCH(BM59,"nvarchar","varchar("&BN59&")","smallint","smallint","date","date","money","decimal(19,4)","numeric","numeric("&BN59&")","int","int","bit","char(1)","datetime2","datetime","time","time")} -> char(1) | AT59: 緊急単品登録された商品か 0：緊急単品登録されていない 1：緊急単品登録された | BM59: bit | BP59: =",`"&R59&"` "&AC59&" "&IF(AJ59="Y","NOT NULL","")&" COMMENT '"&D59&"'" -> ,`EmergencyFlag` char(1) COMMENT '緊急登録フラグ' | BR59: =",`"&R59&"` "&AC59&" "&IF(AJ59="Y","NOT NULL","") -> ,`EmergencyFlag` char(1) | BT59: =",`"&R59&"`" -> ,`EmergencyFlag` | BV59: =",A.`"&R59&"` = B.`"&R59&"`" -> ,A.`EmergencyFlag` = B.`EmergencyFlag` | BX59: =",`"&R59&"`" -> ,`EmergencyFlag` | BZ59: =",`"&R59&"`" -> ,`EmergencyFlag`
A60: @35 | B60: =B59+1 -> 40 | D60: セルフメディケーションフラグ | R60: IsSelfMedication | AC60: {=_xlfn.SWITCH(BM60,"nvarchar","varchar("&BN60&")","smallint","smallint","date","date","money","decimal(19,4)","numeric","numeric("&BN60&")","int","int","bit","char(1)","datetime2","datetime","time","time")} -> char(1) | AT60: セルフメディケーション 0：対象外 1：対象 NULL：対象外 | BM60: bit | BP60: =",`"&R60&"` "&AC60&" "&IF(AJ60="Y","NOT NULL","")&" COMMENT '"&D60&"'" -> ,`IsSelfMedication` char(1) COMMENT 'セルフメディケーションフラグ' | BR60: =",`"&R60&"` "&AC60&" "&IF(AJ60="Y","NOT NULL","") -> ,`IsSelfMedication` char(1) | BT60: =",`"&R60&"`" -> ,`IsSelfMedication` | BV60: =",A.`"&R60&"` = B.`"&R60&"`" -> ,A.`IsSelfMedication` = B.`IsSelfMedication` | BX60: =",`"&R60&"`" -> ,`IsSelfMedication` | BZ60: =",`"&R60&"`" -> ,`IsSelfMedication`
A61: @36 | B61: =B60+1 -> 41 | D61: 売価一括変更フラグ | R61: IsChangePriceBulk | AC61: {=_xlfn.SWITCH(BM61,"nvarchar","varchar("&BN61&")","smallint","smallint","date","date","money","decimal(19,4)","numeric","numeric("&BN61&")","int","int","bit","char(1)","datetime2","datetime","time","time")} -> char(1) | AT61: 0：通常 1：売価一括変更 売価一括変更機能で、1：売価一括変更の商品を対象にメンテナンスする | BM61: bit | BP61: =",`"&R61&"` "&AC61&" "&IF(AJ61="Y","NOT NULL","")&" COMMENT '"&D61&"'" -> ,`IsChangePriceBulk` char(1) COMMENT '売価一括変更フラグ' | BR61: =",`"&R61&"` "&AC61&" "&IF(AJ61="Y","NOT NULL","") -> ,`IsChangePriceBulk` char(1) | BT61: =",`"&R61&"`" -> ,`IsChangePriceBulk` | BV61: =",A.`"&R61&"` = B.`"&R61&"`" -> ,A.`IsChangePriceBulk` = B.`IsChangePriceBulk` | BX61: =",`"&R61&"`" -> ,`IsChangePriceBulk` | BZ61: =",`"&R61&"`" -> ,`IsChangePriceBulk`
A62: @37 | B62: =B61+1 -> 42 | D62: 本部配信データとしての最終更新日時 | R62: HeadquartersLastUpdateDateTime | AC62: {=_xlfn.SWITCH(BM62,"nvarchar","varchar("&BN62&")","smallint","smallint","date","date","money","decimal(19,4)","numeric","numeric("&BN62&")","int","int","bit","char(1)","datetime2","datetime","time","time")} -> datetime | AT62: 本部での登録日時 | BM62: datetime2 | BN62: 7 | BP62: =",`"&R62&"` "&AC62&" "&IF(AJ62="Y","NOT NULL","")&" COMMENT '"&D62&"'" -> ,`HeadquartersLastUpdateDateTime` datetime COMMENT '本部配信データとしての最終更新日時' | BR62: =",`"&R62&"` "&AC62&" "&IF(AJ62="Y","NOT NULL","") -> ,`HeadquartersLastUpdateDateTime` datetime | BT62: =",`"&R62&"`" -> ,`HeadquartersLastUpdateDateTime` | BV62: =",A.`"&R62&"` = B.`"&R62&"`" -> ,A.`HeadquartersLastUpdateDateTime` = B.`HeadquartersLastUpdateDateTime` | BX62: =",`"&R62&"`" -> ,`HeadquartersLastUpdateDateTime` | BZ62: =",`"&R62&"`" -> ,`HeadquartersLastUpdateDateTime`
BP63: =" , PRIMARY KEY ("&IF(_xlfn.XLOOKUP(1,$AH:$AH,$R:$R,"",0)="","","`"&_xlfn.XLOOKUP(1,$AH:$AH,$R:$R,"",0)&"`")&IF(_xlfn.XLOOKUP(2,$AH:$AH,$R:$R,"",0)="","",",`"&_xlfn.XLOOKUP(2,$AH:$AH,$R:$R,"",0)&"`")&IF(_xlfn.XLOOKUP(3,$AH:$AH,$R:$R,"",0)="","",",`"&_xlfn.XLOOKUP(3,$AH:$AH,$R:$R,"",0)&"`")&IF(_xlfn.XLOOKUP(4,$AH:$AH,$R:$R,"",0)="","",",`"&_xlfn.XLOOKUP(4,$AH:$AH,$R:$R,"",0)&"`")&IF(_xlfn.XLOOKUP(5,$AH:$AH,$R:$R,"",0)="","",",`"&_xlfn.XLOOKUP(5,$AH:$AH,$R:$R,"",0)&"`")&IF(_xlfn.XLOOKUP(6,$AH:$AH,$R:$R,"",0)="","",",`"&_xlfn.XLOOKUP(6,$AH:$AH,$R:$R,"",0)&"`")&IF(_xlfn.XLOOKUP(7,$AH:$AH,$R:$R,"",0)="","",",`"&_xlfn.XLOOKUP(7,$AH:$AH,$R:$R,"",0)&"`")&IF(_xlfn.XLOOKUP(8,$AH:$AH,$R:$R,"",0)="","",",`"&_xlfn.XLOOKUP(8,$AH:$AH,$R:$R,"",0)&"`")&")," -> , PRIMARY KEY (`CompanyCode`,`StoreCode`,`ItemCode`,`ApplyDate`), | BR63: =" , PRIMARY KEY ("&IF(_xlfn.XLOOKUP(1,$AH:$AH,$R:$R,"",0)="","","`"&_xlfn.XLOOKUP(1,$AH:$AH,$R:$R,"",0)&"`")&IF(_xlfn.XLOOKUP(2,$AH:$AH,$R:$R,"",0)="","",",`"&_xlfn.XLOOKUP(2,$AH:$AH,$R:$R,"",0)&"`")&IF(_xlfn.XLOOKUP(3,$AH:$AH,$R:$R,"",0)="","",",`"&_xlfn.XLOOKUP(3,$AH:$AH,$R:$R,"",0)&"`")&IF(_xlfn.XLOOKUP(4,$AH:$AH,$R:$R,"",0)="","",",`"&_xlfn.XLOOKUP(4,$AH:$AH,$R:$R,"",0)&"`")&IF(_xlfn.XLOOKUP(5,$AH:$AH,$R:$R,"",0)="","",",`"&_xlfn.XLOOKUP(5,$AH:$AH,$R:$R,"",0)&"`")&IF(_xlfn.XLOOKUP(6,$AH:$AH,$R:$R,"",0)="","",",`"&_xlfn.XLOOKUP(6,$AH:$AH,$R:$R,"",0)&"`")&IF(_xlfn.XLOOKUP(7,$AH:$AH,$R:$R,"",0)="","",",`"&_xlfn.XLOOKUP(7,$AH:$AH,$R:$R,"",0)&"`")&IF(_xlfn.XLOOKUP(8,$AH:$AH,$R:$R,"",0)="","",",`"&_xlfn.XLOOKUP(8,$AH:$AH,$R:$R,"",0)&"`")&")" -> , PRIMARY KEY (`CompanyCode`,`StoreCode`,`ItemCode`,`ApplyDate`) | BT63: ; | BV63: WHERE | BZ63: ="FROM `TMP`.`"&$G$10&"` A" -> FROM `TMP`.`ItemMaster` A
BP64: KEY `RECORD_ID` (`RECORD_ID`) | BR64: =") ENGINE=InnoDB DEFAULT CHARSET=utf8mb4 COLLATE=utf8mb4_0900_ai_ci COMMENT = '"&$G$9&"_TMP';" -> ) ENGINE=InnoDB DEFAULT CHARSET=utf8mb4 COLLATE=utf8mb4_0900_ai_ci COMMENT = '商品マスタ_TMP'; | BV64: =IF(_xlfn.XLOOKUP(1,$AH:$AH,$R:$R,"",0)="","","A.`"&_xlfn.XLOOKUP(1,$AH:$AH,$R:$R,"",0)&"` = B.`"&_xlfn.XLOOKUP(1,$AH:$AH,$R:$R,"",0)&"`") -> A.`CompanyCode` = B.`CompanyCode` | BZ64: WHERE NOT EXISTS ( SELECT RECORD_ID
B65: ■インデックス情報 | BP65: =") ENGINE=InnoDB DEFAULT CHARSET=utf8mb4 COLLATE=utf8mb4_0900_ai_ci COMMENT = '"&$G$9&"';" -> ) ENGINE=InnoDB DEFAULT CHARSET=utf8mb4 COLLATE=utf8mb4_0900_ai_ci COMMENT = '商品マスタ'; | BV65: =IF(_xlfn.XLOOKUP(2,$AH:$AH,$R:$R,"",0)="","","AND A.`"&_xlfn.XLOOKUP(2,$AH:$AH,$R:$R,"",0)&"` = B.`"&_xlfn.XLOOKUP(2,$AH:$AH,$R:$R,"",0)&"`") -> AND A.`StoreCode` = B.`StoreCode` | BZ65: ="FROM `POS_MASTER`.`"&$G$10&"` B" -> FROM `POS_MASTER`.`ItemMaster` B
B66: No. | D66: Index名 | R66: カラム一覧 | AL66: プライマリキー | AP66: ユニーク | AT66: 備考 | BV66: =IF(_xlfn.XLOOKUP(3,$AH:$AH,$R:$R,"",0)="","","AND A.`"&_xlfn.XLOOKUP(3,$AH:$AH,$R:$R,"",0)&"` = B.`"&_xlfn.XLOOKUP(3,$AH:$AH,$R:$R,"",0)&"`") -> AND A.`ItemCode` = B.`ItemCode` | BZ66: WHERE
B67: 1 | D67: PRIMARY | R67: =IF(_xlfn.XLOOKUP(1,$AH:$AH,$R:$R,"",0)="","","`"&_xlfn.XLOOKUP(1,$AH:$AH,$R:$R,"",0)&"`")&IF(_xlfn.XLOOKUP(2,$AH:$AH,$R:$R,"",0)="","",",`"&_xlfn.XLOOKUP(2,$AH:$AH,$R:$R,"",0)&"`")&IF(_xlfn.XLOOKUP(3,$AH:$AH,$R:$R,"",0)="","",",`"&_xlfn.XLOOKUP(3,$AH:$AH,$R:$R,"",0)&"`")&IF(_xlfn.XLOOKUP(4,$AH:$AH,$R:$R,"",0)="","",",`"&_xlfn.XLOOKUP(4,$AH:$AH,$R:$R,"",0)&"`")&IF(_xlfn.XLOOKUP(5,$AH:$AH,$R:$R,"",0)="","",",`"&_xlfn.XLOOKUP(5,$AH:$AH,$R:$R,"",0)&"`")&IF(_xlfn.XLOOKUP(6,$AH:$AH,$R:$R,"",0)="","",",`"&_xlfn.XLOOKUP(6,$AH:$AH,$R:$R,"",0)&"`")&IF(_xlfn.XLOOKUP(7,$AH:$AH,$R:$R,"",0)="","",",`"&_xlfn.XLOOKUP(7,$AH:$AH,$R:$R,"",0)&"`")&IF(_xlfn.XLOOKUP(8,$AH:$AH,$R:$R,"",0)="","",",`"&_xlfn.XLOOKUP(8,$AH:$AH,$R:$R,"",0)&"`") -> `CompanyCode`,`StoreCode`,`ItemCode`,`ApplyDate` | AL67: Y | AP67: Y | BP67: ="CREATE TRIGGER `"&$G$10&"_CR_Date_Time` BEFORE INSERT ON `"&$G$10&"` FOR EACH ROW SET NEW.record_create_date = CURRENT_DATE, NEW.record_create_time = CURRENT_TIME, NEW.record_update_date = CURRENT_DATE, NEW.record_update_time = CURRENT_TIME;" -> CREATE TRIGGER `ItemMaster_CR_Date_Time` BEFORE INSERT ON `ItemMaster` FOR EACH ROW SET NEW.record_create_date = CURRENT_DATE, NEW.record_create_time = CURRENT_TIME, NEW.record_update_date = CURRENT_DATE, NEW.record_update_time = CURRENT_TIME; | BV67: =IF(_xlfn.XLOOKUP(4,$AH:$AH,$R:$R,"",0)="","","AND A.`"&_xlfn.XLOOKUP(4,$AH:$AH,$R:$R,"",0)&"` = B.`"&_xlfn.XLOOKUP(4,$AH:$AH,$R:$R,"",0)&"`") -> AND A.`ApplyDate` = B.`ApplyDate` | BZ67: =IF(_xlfn.XLOOKUP(1,$AH:$AH,$R:$R,"",0)="","","A.`"&_xlfn.XLOOKUP(1,$AH:$AH,$R:$R,"",0)&"` = B.`"&_xlfn.XLOOKUP(1,$AH:$AH,$R:$R,"",0)&"`") -> A.`CompanyCode` = B.`CompanyCode`
BP68: ="CREATE TRIGGER `"&$G$10&"_UP_Date_Time` BEFORE UPDATE ON `"&$G$10&"` FOR EACH ROW SET NEW.record_update_date = CURRENT_DATE, NEW.record_update_time = CURRENT_TIME;" -> CREATE TRIGGER `ItemMaster_UP_Date_Time` BEFORE UPDATE ON `ItemMaster` FOR EACH ROW SET NEW.record_update_date = CURRENT_DATE, NEW.record_update_time = CURRENT_TIME; | BV68: =IF(_xlfn.XLOOKUP(5,$AH:$AH,$R:$R,"",0)="","","AND A.`"&_xlfn.XLOOKUP(5,$AH:$AH,$R:$R,"",0)&"` = B.`"&_xlfn.XLOOKUP(5,$AH:$AH,$R:$R,"",0)&"`") | BZ68: =IF(_xlfn.XLOOKUP(2,$AH:$AH,$R:$R,"",0)="","","AND A.`"&_xlfn.XLOOKUP(2,$AH:$AH,$R:$R,"",0)&"` = B.`"&_xlfn.XLOOKUP(2,$AH:$AH,$R:$R,"",0)&"`") -> AND A.`StoreCode` = B.`StoreCode`
BV69: =IF(_xlfn.XLOOKUP(6,$AH:$AH,$R:$R,"",0)="","","AND A.`"&_xlfn.XLOOKUP(6,$AH:$AH,$R:$R,"",0)&"` = B.`"&_xlfn.XLOOKUP(6,$AH:$AH,$R:$R,"",0)&"`") | BZ69: =IF(_xlfn.XLOOKUP(3,$AH:$AH,$R:$R,"",0)="","","AND A.`"&_xlfn.XLOOKUP(3,$AH:$AH,$R:$R,"",0)&"` = B.`"&_xlfn.XLOOKUP(3,$AH:$AH,$R:$R,"",0)&"`") -> AND A.`ItemCode` = B.`ItemCode`
B70: トリガー情報 | BV70: =IF(_xlfn.XLOOKUP(7,$AH:$AH,$R:$R,"",0)="","","AND A.`"&_xlfn.XLOOKUP(7,$AH:$AH,$R:$R,"",0)&"` = B.`"&_xlfn.XLOOKUP(7,$AH:$AH,$R:$R,"",0)&"`") | BZ70: =IF(_xlfn.XLOOKUP(4,$AH:$AH,$R:$R,"",0)="","","AND A.`"&_xlfn.XLOOKUP(4,$AH:$AH,$R:$R,"",0)&"` = B.`"&_xlfn.XLOOKUP(4,$AH:$AH,$R:$R,"",0)&"`") -> AND A.`ApplyDate` = B.`ApplyDate`
B71: No. | D71: トリガー名 | R71: イベント | U71: タイミング | Y71: 条件 | BV71: =IF(_xlfn.XLOOKUP(8,$AH:$AH,$R:$R,"",0)="","","AND A.`"&_xlfn.XLOOKUP(8,$AH:$AH,$R:$R,"",0)&"` = B.`"&_xlfn.XLOOKUP(8,$AH:$AH,$R:$R,"",0)&"`") | BZ71: =IF(_xlfn.XLOOKUP(5,$AH:$AH,$R:$R,"",0)="","","AND A.`"&_xlfn.XLOOKUP(5,$AH:$AH,$R:$R,"",0)&"` = B.`"&_xlfn.XLOOKUP(5,$AH:$AH,$R:$R,"",0)&"`")
B72: 1 | D72: =G10&"_"&R72&"_"&"trg" -> ItemMaster_update_trg | R72: update | U72: Before row | Y72: auto_updated_date | BV72: ; | BZ72: =IF(_xlfn.XLOOKUP(6,$AH:$AH,$R:$R,"",0)="","","AND A.`"&_xlfn.XLOOKUP(6,$AH:$AH,$R:$R,"",0)&"` = B.`"&_xlfn.XLOOKUP(6,$AH:$AH,$R:$R,"",0)&"`")
BZ73: =IF(_xlfn.XLOOKUP(7,$AH:$AH,$R:$R,"",0)="","","AND A.`"&_xlfn.XLOOKUP(7,$AH:$AH,$R:$R,"",0)&"` = B.`"&_xlfn.XLOOKUP(7,$AH:$AH,$R:$R,"",0)&"`")
BZ74: =IF(_xlfn.XLOOKUP(8,$AH:$AH,$R:$R,"",0)="","","AND A.`"&_xlfn.XLOOKUP(8,$AH:$AH,$R:$R,"",0)&"` = B.`"&_xlfn.XLOOKUP(8,$AH:$AH,$R:$R,"",0)&"`")
BZ75: );
BZ78: ="DROP TABLE IF EXISTS `TMP`.`"&$G$10&"`;" -> DROP TABLE IF EXISTS `TMP`.`ItemMaster`;
BZ79: COMMIT;

Sheet 商品拡張マスタ
A1: システム名 | K1: システム種別 | W1: =IF(表紙!W1="","",表紙!W1) -> DB定義書 | AP1: 作成者 | AT1: 作成日 | AY1: 更新者 | BC1: 更新日 | BH1: 版数
A2: =IF(表紙!A2="","",表紙!A2) -> 現金専用簡易セルフPOS | K2: =IF(表紙!K2="","",表紙!K2) | AP2: =IF(表紙!AP2="","",表紙!AP2) -> きよはら | AT2: =IF(表紙!AT2="","",表紙!AT2) -> 44652 | AY2: =IF(表紙!AY2="","",表紙!AY2) -> Thanh Nguyên | BC2: =IF(表紙!BC2="","",表紙!BC2) -> 45285 | BH2: =IF(表紙!BH2="","",表紙!BH2) -> 0.2
A4: 機能カテゴリ | H4: =IF(表紙!H4="","",表紙!H4) -> 共通 | U4: 項目 | Z4: =IF(表紙!Z4="","",表紙!Z4) | AP4: 商品拡張マスタ
B7: ■テーブル情報
B8: スキーマ名 | G8: POS_MASTER | Y8: RDBMS名
B9: 論理名 | G9: 商品拡張マスタ | Y9: バージョン
B10: 物理名 | G10: ItemExMvkMaster
B11: 備考
B19: ■カラム情報 | BP19: ="DROP TABLE IF EXISTS `"&$G$8&"`.`"&$G$10&"`;" -> DROP TABLE IF EXISTS `POS_MASTER`.`ItemExMvkMaster`;
B20: No. | D20: 論理名 | R20: 物理名 | AC20: データ型 | AH20: PK | AJ20: Not Null | AM20: デフォルト | AT20: 備考 | BP20: ="CREATE TABLE `"&$G$8&"`.`"&$G$10&"` (" -> CREATE TABLE `POS_MASTER`.`ItemExMvkMaster` (
B21: 1 | D21: レコードID | R21: RECORD_ID | AC21: bigint | AJ21: Y | AM21: 自動追加 | BP21: `RECORD_ID` bigint NOT NULL AUTO_INCREMENT COMMENT 'レコードID'
B22: =B21+1 -> 2 | D22: レコード作成日付 | R22: RECORD_CREATE_DATE | AC22: date | AJ22: Y | AM22: CURRENT_DATE | BP22: ,`RECORD_CREATE_DATE` date NOT NULL COMMENT 'レコード作成日付'
B23: =B22+1 -> 3 | D23: レコード作成時間 | R23: RECORD_CREATE_TIME | AC23: time | AJ23: Y | AM23: CURRENT_TIME | BP23: ,`RECORD_CREATE_TIME` time NOT NULL COMMENT 'レコード作成時間'
B24: =B23+1 -> 4 | D24: レコード更新日付 | R24: RECORD_UPDATE_DATE | AC24: date | AJ24: Y | AM24: CURRENT_DATE | AT24: トリガーにより更新 | BP24: ,`RECORD_UPDATE_DATE` date NOT NULL COMMENT 'レコード更新日付/トリガーにより更新' | BT24: ="LOAD DATA INFILE 'C:/04_DATAFILE/"&$G$10&"/TMP/"&$G$10&".CSV' " -> LOAD DATA INFILE 'C:/04_DATAFILE/ItemExMvkMaster/TMP/ItemExMvkMaster.CSV' | BV24: ="UPDATE `POS_MASTER`.`"&$G$10&"` A,`TMP`.`"&$G$10&"` B" -> UPDATE `POS_MASTER`.`ItemExMvkMaster` A,`TMP`.`ItemExMvkMaster` B
B25: =B24+1 -> 5 | D25: レコード更新時間 | R25: RECORD_UPDATE_TIME | AC25: time | AJ25: Y | AM25: CURRENT_TIME | AT25: トリガーにより更新 | BP25: ,`RECORD_UPDATE_TIME` time NOT NULL COMMENT 'レコード更新時間/トリガーにより更新' | BR25: ="DROP TABLE IF EXISTS `TMP`.`"&$G$10&"`;" -> DROP TABLE IF EXISTS `TMP`.`ItemExMvkMaster`; | BT25: ="REPLACE INTO TABLE TMP.`"&$G$10&"` CHARACTER SET 'UTF8'" -> REPLACE INTO TABLE TMP.`ItemExMvkMaster` CHARACTER SET 'UTF8' | BV25: SET
A26: @1 | B26: =B25+1 -> 6 | D26: レコード無効フラグ | R26: RECORD_VOID_FLAG | AC26: char(1) | AJ26: Y | AM26: "" | AT26: 0: 有効フラグ、 1:無効フラグ | BM26: nvarchar | BN26: 1 | BP26: ,`RECORD_VOID_FLAG` char(1) NOT NULL DEFAULT '' COMMENT 'レコード無効フラグ '''': 有効フラグ、 1:無効フラグ' | BR26: ="CREATE TABLE `TMP`.`"&G10&"` (" -> CREATE TABLE `TMP`.`ItemExMvkMaster` ( | BT26: =SUBSTITUTE(SUBSTITUTE("("&A26&","&A27&","&A28&","&A29&","&A30&","&A31&","&A32&","&A33&","&A34&","&A35&","&A36&","&A37&","&A38&","&A39&","&A40&","&A41&","&A42&","&A43&","&A44&","&A45&","&A46&","&A47&","&A48&","&A49&","&A50&","&A51&","&A52&","&A53&","&A54&","&A55&","&A56&","&A57&","&A58&","&A59&","&A60&","&A61&","&A62&")",",,",""),",)",")") -> (@1,@2,@3,@4,@5,@6,@7,@8,@9) | BX26: ="INSERT INTO `POS_MASTER`.`"&$G$10&"` (" -> INSERT INTO `POS_MASTER`.`ItemExMvkMaster` ( | BZ26: ) SELECT
A27: @2 | B27: =B26+1 -> 7 | D27: 企業コード | R27: CompanyCode | AC27: {=_xlfn.SWITCH(BM27,"nvarchar","varchar("&BN27&")","smallint","smallint","date","date","money","decimal(19,4)","numeric","numeric("&BN27&")","int","int","bit","char(1)","datetime2","datetime","time","time")} -> varchar(10) | AH27: 1 | AJ27: Y | AT27: 会社コード | BM27: nvarchar | BN27: 10 | BP27: =",`"&R27&"` "&AC27&" "&IF(AJ27="Y","NOT NULL","")&" COMMENT '"&D27&"'" -> ,`CompanyCode` varchar(10) NOT NULL COMMENT '企業コード' | BR27: ="`"&R27&"` "&AC27&" "&IF(AJ27="Y","NOT NULL","") -> `CompanyCode` varchar(10) NOT NULL | BT27: ="SET `"&R27&"` = "&IF(LEFT(AC27,4)="date", "if(@"&B27-5&" > '0000-00-00 00:00:00', @"&B27-5&", null)","if(nullif( @"&B27-5&",'') > '', @"&B27-5&", null )") -> SET `CompanyCode` = if(nullif( @2,'') > '', @2, null ) | BV27: ="A.`"&R27&"` = B.`"&R27&"`" -> A.`CompanyCode` = B.`CompanyCode` | BX27: ="`"&R27&"`" -> `CompanyCode` | BZ27: ="`"&R27&"`" -> `CompanyCode`
A28: @3 | B28: =B27+1 -> 8 | D28: 店舗コード | R28: StoreCode | AC28: {=_xlfn.SWITCH(BM28,"nvarchar","varchar("&BN28&")","smallint","smallint","date","date","money","decimal(19,4)","numeric","numeric("&BN28&")","int","int","bit","char(1)","datetime2","datetime","time","time")} -> varchar(10) | AH28: 2 | AJ28: Y | AT28: 店舗コード | BM28: nvarchar | BN28: 10 | BP28: =",`"&R28&"` "&AC28&" "&IF(AJ28="Y","NOT NULL","")&" COMMENT '"&D28&"'" -> ,`StoreCode` varchar(10) NOT NULL COMMENT '店舗コード' | BR28: =",`"&R28&"` "&AC28&" "&IF(AJ28="Y","NOT NULL","") -> ,`StoreCode` varchar(10) NOT NULL | BT28: =",`"&R28&"` = "&IF(LEFT(AC28,4)="date", "if(@"&B28-5&" > '0000-00-00 00:00:00', if(@"&B28-5&" > '2999-12-31 23:59:59', '2999-12-31 23:59:59', @"&B28-5&"), null)","if(nullif( @"&B28-5&",'') > '', @"&B28-5&", null )") -> ,`StoreCode` = if(nullif( @3,'') > '', @3, null ) | BV28: =",A.`"&R28&"` = B.`"&R28&"`" -> ,A.`StoreCode` = B.`StoreCode` | BX28: =",`"&R28&"`" -> ,`StoreCode` | BZ28: =",`"&R28&"`" -> ,`StoreCode`
A29: @4 | B29: =B28+1 -> 9 | D29: 単品コード | R29: ItemCode | AC29: {=_xlfn.SWITCH(BM29,"nvarchar","varchar("&BN29&")","smallint","smallint","date","date","money","decimal(19,4)","numeric","numeric("&BN29&")","int","int","bit","char(1)","datetime2","datetime","time","time")} -> varchar(26) | AH29: 3 | AJ29: Y | BM29: nvarchar | BN29: 26 | BP29: =",`"&R29&"` "&AC29&" "&IF(AJ29="Y","NOT NULL","")&" COMMENT '"&D29&"'" -> ,`ItemCode` varchar(26) NOT NULL COMMENT '単品コード' | BR29: =",`"&R29&"` "&AC29&" "&IF(AJ29="Y","NOT NULL","") -> ,`ItemCode` varchar(26) NOT NULL | BT29: =",`"&R29&"` = "&IF(LEFT(AC29,4)="date", "if(@"&B29-5&" > '0000-00-00 00:00:00', if(@"&B29-5&" > '2999-12-31 23:59:59', '2999-12-31 23:59:59', @"&B29-5&"), null)","if(nullif( @"&B29-5&",'') > '', @"&B29-5&", null )") -> ,`ItemCode` = if(nullif( @4,'') > '', @4, null ) | BV29: =",A.`"&R29&"` = B.`"&R29&"`" -> ,A.`ItemCode` = B.`ItemCode` | BX29: =",`"&R29&"`" -> ,`ItemCode` | BZ29: =",`"&R29&"`" -> ,`ItemCode`
A30: @5 | B30: =B29+1 -> 10 | D30: 適用日 | R30: ApplyDate | AC30: {=_xlfn.SWITCH(BM30,"nvarchar","varchar("&BN30&")","smallint","smallint","date","date","money","decimal(19,4)","numeric","numeric("&BN30&")","int","int","bit","char(1)","datetime2","datetime","time","time")} -> date | AH30: 4 | AJ30: Y | BM30: date | BP30: =",`"&R30&"` "&AC30&" "&IF(AJ30="Y","NOT NULL","")&" COMMENT '"&D30&"'" -> ,`ApplyDate` date NOT NULL COMMENT '適用日' | BR30: =",`"&R30&"` "&AC30&" "&IF(AJ30="Y","NOT NULL","") -> ,`ApplyDate` date NOT NULL | BT30: =",`"&R30&"` = "&IF(LEFT(AC30,4)="date", "if(@"&B30-5&" > '0000-00-00 00:00:00', if(@"&B30-5&" > '2999-12-31 23:59:59', '2999-12-31 23:59:59', @"&B30-5&"), null)","if(nullif( @"&B30-5&",'') > '', @"&B30-5&", null )") -> ,`ApplyDate` = if(@5 > '0000-00-00 00:00:00', if(@5 > '2999-12-31 23:59:59', '2999-12-31 23:59:59', @5), null) | BV30: =",A.`"&R30&"` = B.`"&R30&"`" -> ,A.`ApplyDate` = B.`ApplyDate` | BX30: =",`"&R30&"`" -> ,`ApplyDate` | BZ30: =",`"&R30&"`" -> ,`ApplyDate`
A31: @6 | B31: =B30+1 -> 11 | D31: WAONポイント付与数 | R31: WaonPoint | AC31: {=_xlfn.SWITCH(BM31,"nvarchar","varchar("&BN31&")","smallint","smallint","date","date","money","decimal(19,4)","numeric","numeric("&BN31&")","int","int","bit","char(1)","datetime2","datetime","time","time")} -> numeric(5, 0) | AT31: WAONボーナスポイント付与数 | BM31: numeric | BN31: 5, 0 | BP31: =",`"&R31&"` "&AC31&" "&IF(AJ31="Y","NOT NULL","")&" COMMENT '"&D31&"'" -> ,`WaonPoint` numeric(5, 0) COMMENT 'WAONポイント付与数' | BR31: =",`"&R31&"` "&AC31&" "&IF(AJ31="Y","NOT NULL","") -> ,`WaonPoint` numeric(5, 0) | BT31: =",`"&R31&"` = "&IF(LEFT(AC31,4)="date", "if(@"&B31-5&" > '0000-00-00 00:00:00', if(@"&B31-5&" > '2999-12-31 23:59:59', '2999-12-31 23:59:59', @"&B31-5&"), null)","if(nullif( @"&B31-5&",'') > '', @"&B31-5&", null )") -> ,`WaonPoint` = if(nullif( @6,'') > '', @6, null ) | BV31: =",A.`"&R31&"` = B.`"&R31&"`" -> ,A.`WaonPoint` = B.`WaonPoint` | BX31: =",`"&R31&"`" -> ,`WaonPoint` | BZ31: =",`"&R31&"`" -> ,`WaonPoint`
A32: @7 | B32: =B31+1 -> 12 | D32: 取り扱いメディア区分 | R32: WaonPointMediaType | AC32: {=_xlfn.SWITCH(BM32,"nvarchar","varchar("&BN32&")","smallint","smallint","date","date","money","decimal(19,4)","numeric","numeric("&BN32&")","int","int","bit","char(1)","datetime2","datetime","time","time")} -> varchar(1) | AT32: 0:未設定 1:WAONボーナスポイント | BM32: nvarchar | BN32: 1 | BP32: =",`"&R32&"` "&AC32&" "&IF(AJ32="Y","NOT NULL","")&" COMMENT '"&D32&"'" -> ,`WaonPointMediaType` varchar(1) COMMENT '取り扱いメディア区分' | BR32: =",`"&R32&"` "&AC32&" "&IF(AJ32="Y","NOT NULL","") -> ,`WaonPointMediaType` varchar(1) | BT32: =",`"&R32&"` = "&IF(LEFT(AC32,4)="date", "if(@"&B32-5&" > '0000-00-00 00:00:00', if(@"&B32-5&" > '2999-12-31 23:59:59', '2999-12-31 23:59:59', @"&B32-5&"), null)","if(nullif( @"&B32-5&",'') > '', @"&B32-5&", null )") -> ,`WaonPointMediaType` = if(nullif( @7,'') > '', @7, null ) | BV32: =",A.`"&R32&"` = B.`"&R32&"`" -> ,A.`WaonPointMediaType` = B.`WaonPointMediaType` | BX32: =",`"&R32&"`" -> ,`WaonPointMediaType` | BZ32: =",`"&R32&"`" -> ,`WaonPointMediaType`
A33: @8 | B33: =B32+1 -> 13 | D33: TBP値引禁止フラグ | R33: IsTBPDiscountProhibition | AC33: {=_xlfn.SWITCH(BM33,"nvarchar","varchar("&BN33&")","smallint","smallint","date","date","money","decimal(19,4)","numeric","numeric("&BN33&")","int","int","bit","char(1)","datetime2","datetime","time","time")} -> char(1) | AJ33: Y | BM33: bit | BP33: =",`"&R33&"` "&AC33&" "&IF(AJ33="Y","NOT NULL","")&" COMMENT '"&D33&"'" -> ,`IsTBPDiscountProhibition` char(1) NOT NULL COMMENT 'TBP値引禁止フラグ' | BR33: =",`"&R33&"` "&AC33&" "&IF(AJ33="Y","NOT NULL","") -> ,`IsTBPDiscountProhibition` char(1) NOT NULL | BT33: =",`"&R33&"` = "&IF(LEFT(AC33,4)="date", "if(@"&B33-5&" > '0000-00-00 00:00:00', if(@"&B33-5&" > '2999-12-31 23:59:59', '2999-12-31 23:59:59', @"&B33-5&"), null)","if(nullif( @"&B33-5&",'') > '', @"&B33-5&", null )") -> ,`IsTBPDiscountProhibition` = if(nullif( @8,'') > '', @8, null ) | BV33: =",A.`"&R33&"` = B.`"&R33&"`" -> ,A.`IsTBPDiscountProhibition` = B.`IsTBPDiscountProhibition` | BX33: =",`"&R33&"`" -> ,`IsTBPDiscountProhibition` | BZ33: =",`"&R33&"`" -> ,`IsTBPDiscountProhibition`
A34: @9 | B34: =B33+1 -> 14 | D34: 本部配信データとしての最終更新日時 | R34: HeadquartersLastUpdateDateTime | AC34: {=_xlfn.SWITCH(BM34,"nvarchar","varchar("&BN34&")","smallint","smallint","date","date","money","decimal(19,4)","numeric","numeric("&BN34&")","int","int","bit","char(1)","datetime2","datetime","time","time")} -> datetime | BM34: datetime2 | BN34: 7 | BP34: =",`"&R34&"` "&AC34&" "&IF(AJ34="Y","NOT NULL","")&" COMMENT '"&D34&"'" -> ,`HeadquartersLastUpdateDateTime` datetime COMMENT '本部配信データとしての最終更新日時' | BR34: =",`"&R34&"` "&AC34&" "&IF(AJ34="Y","NOT NULL","") -> ,`HeadquartersLastUpdateDateTime` datetime | BT34: =",`"&R34&"` = "&IF(LEFT(AC34,4)="date", "if(@"&B34-5&" > '0000-00-00 00:00:00', if(@"&B34-5&" > '2999-12-31 23:59:59', '2999-12-31 23:59:59', @"&B34-5&"), null)","if(nullif( @"&B34-5&",'') > '', @"&B34-5&", null )") -> ,`HeadquartersLastUpdateDateTime` = if(@9 > '0000-00-00 00:00:00', if(@9 > '2999-12-31 23:59:59', '2999-12-31 23:59:59', @9), null) | BV34: =",A.`"&R34&"` = B.`"&R34&"`" -> ,A.`HeadquartersLastUpdateDateTime` = B.`HeadquartersLastUpdateDateTime` | BX34: =",`"&R34&"`" -> ,`HeadquartersLastUpdateDateTime` | BZ34: =",`"&R34&"`" -> ,`HeadquartersLastUpdateDateTime`
BP35: =" , PRIMARY KEY ("&IF(_xlfn.XLOOKUP(1,$AH:$AH,$R:$R,"",0)="","","`"&_xlfn.XLOOKUP(1,$AH:$AH,$R:$R,"",0)&"`")&IF(_xlfn.XLOOKUP(2,$AH:$AH,$R:$R,"",0)="","",",`"&_xlfn.XLOOKUP(2,$AH:$AH,$R:$R,"",0)&"`")&IF(_xlfn.XLOOKUP(3,$AH:$AH,$R:$R,"",0)="","",",`"&_xlfn.XLOOKUP(3,$AH:$AH,$R:$R,"",0)&"`")&IF(_xlfn.XLOOKUP(4,$AH:$AH,$R:$R,"",0)="","",",`"&_xlfn.XLOOKUP(4,$AH:$AH,$R:$R,"",0)&"`")&IF(_xlfn.XLOOKUP(5,$AH:$AH,$R:$R,"",0)="","",",`"&_xlfn.XLOOKUP(5,$AH:$AH,$R:$R,"",0)&"`")&IF(_xlfn.XLOOKUP(6,$AH:$AH,$R:$R,"",0)="","",",`"&_xlfn.XLOOKUP(6,$AH:$AH,$R:$R,"",0)&"`")&IF(_xlfn.XLOOKUP(7,$AH:$AH,$R:$R,"",0)="","",",`"&_xlfn.XLOOKUP(7,$AH:$AH,$R:$R,"",0)&"`")&IF(_xlfn.XLOOKUP(8,$AH:$AH,$R:$R,"",0)="","",",`"&_xlfn.XLOOKUP(8,$AH:$AH,$R:$R,"",0)&"`")&")," -> , PRIMARY KEY (`CompanyCode`,`StoreCode`,`ItemCode`,`ApplyDate`), | BR35: =" , PRIMARY KEY ("&IF(_xlfn.XLOOKUP(1,$AH:$AH,$R:$R,"",0)="","","`"&_xlfn.XLOOKUP(1,$AH:$AH,$R:$R,"",0)&"`")&IF(_xlfn.XLOOKUP(2,$AH:$AH,$R:$R,"",0)="","",",`"&_xlfn.XLOOKUP(2,$AH:$AH,$R:$R,"",0)&"`")&IF(_xlfn.XLOOKUP(3,$AH:$AH,$R:$R,"",0)="","",",`"&_xlfn.XLOOKUP(3,$AH:$AH,$R:$R,"",0)&"`")&IF(_xlfn.XLOOKUP(4,$AH:$AH,$R:$R,"",0)="","",",`"&_xlfn.XLOOKUP(4,$AH:$AH,$R:$R,"",0)&"`")&IF(_xlfn.XLOOKUP(5,$AH:$AH,$R:$R,"",0)="","",",`"&_xlfn.XLOOKUP(5,$AH:$AH,$R:$R,"",0)&"`")&IF(_xlfn.XLOOKUP(6,$AH:$AH,$R:$R,"",0)="","",",`"&_xlfn.XLOOKUP(6,$AH:$AH,$R:$R,"",0)&"`")&IF(_xlfn.XLOOKUP(7,$AH:$AH,$R:$R,"",0)="","",",`"&_xlfn.XLOOKUP(7,$AH:$AH,$R:$R,"",0)&"`")&IF(_xlfn.XLOOKUP(8,$AH:$AH,$R:$R,"",0)="","",",`"&_xlfn.XLOOKUP(8,$AH:$AH,$R:$R,"",0)&"`")&")" -> , PRIMARY KEY (`CompanyCode`,`StoreCode`,`ItemCode`,`ApplyDate`) | BT35: ; | BV35: WHERE | BZ35: ="FROM `TMP`.`"&$G$10&"` A" -> FROM `TMP`.`ItemExMvkMaster` A
BP36: KEY `RECORD_ID` (`RECORD_ID`) | BR36: =") ENGINE=InnoDB DEFAULT CHARSET=utf8mb4 COLLATE=utf8mb4_0900_ai_ci COMMENT = '"&$G$9&"_TMP';" -> ) ENGINE=InnoDB DEFAULT CHARSET=utf8mb4 COLLATE=utf8mb4_0900_ai_ci COMMENT = '商品拡張マスタ_TMP'; | BV36: =IF(_xlfn.XLOOKUP(1,$AH:$AH,$R:$R,"",0)="","","A.`"&_xlfn.XLOOKUP(1,$AH:$AH,$R:$R,"",0)&"` = B.`"&_xlfn.XLOOKUP(1,$AH:$AH,$R:$R,"",0)&"`") -> A.`CompanyCode` = B.`CompanyCode` | BZ36: WHERE NOT EXISTS ( SELECT RECORD_ID
B37: ■インデックス情報 | BP37: =") ENGINE=InnoDB DEFAULT CHARSET=utf8mb4 COLLATE=utf8mb4_0900_ai_ci COMMENT = '"&$G$9&"';" -> ) ENGINE=InnoDB DEFAULT CHARSET=utf8mb4 COLLATE=utf8mb4_0900_ai_ci COMMENT = '商品拡張マスタ'; | BV37: =IF(_xlfn.XLOOKUP(2,$AH:$AH,$R:$R,"",0)="","","AND A.`"&_xlfn.XLOOKUP(2,$AH:$AH,$R:$R,"",0)&"` = B.`"&_xlfn.XLOOKUP(2,$AH:$AH,$R:$R,"",0)&"`") -> AND A.`StoreCode` = B.`StoreCode` | BZ37: ="FROM `POS_MASTER`.`"&$G$10&"` B" -> FROM `POS_MASTER`.`ItemExMvkMaster` B
B38: No. | D38: Index名 | R38: カラム一覧 | AL38: プライマリキー | AP38: ユニーク | AT38: 備考 | BV38: =IF(_xlfn.XLOOKUP(3,$AH:$AH,$R:$R,"",0)="","","AND A.`"&_xlfn.XLOOKUP(3,$AH:$AH,$R:$R,"",0)&"` = B.`"&_xlfn.XLOOKUP(3,$AH:$AH,$R:$R,"",0)&"`") -> AND A.`ItemCode` = B.`ItemCode` | BZ38: WHERE
B39: 1 | D39: PRIMARY | R39: =IF(_xlfn.XLOOKUP(1,AH:AH,R:R,"",0)="","","`"&_xlfn.XLOOKUP(1,AH:AH,R:R,"",0)&"`")&IF(_xlfn.XLOOKUP(2,AH:AH,R:R,"",0)="","",",`"&_xlfn.XLOOKUP(2,AH:AH,R:R,"",0)&"`")&IF(_xlfn.XLOOKUP(3,AH:AH,R:R,"",0)="","",",`"&_xlfn.XLOOKUP(3,AH:AH,R:R,"",0)&"`")&IF(_xlfn.XLOOKUP(4,AH:AH,R:R,"",0)="","",",`"&_xlfn.XLOOKUP(4,AH:AH,R:R,"",0)&"`")&IF(_xlfn.XLOOKUP(5,AH:AH,R:R,"",0)="","",",`"&_xlfn.XLOOKUP(5,AH:AH,R:R,"",0)&"`")&IF(_xlfn.XLOOKUP(6,AH:AH,R:R,"",0)="","",",`"&_xlfn.XLOOKUP(6,AH:AH,R:R,"",0)&"`")&IF(_xlfn.XLOOKUP(7,AH:AH,R:R,"",0)="","",",`"&_xlfn.XLOOKUP(7,AH:AH,R:R,"",0)&"`")&IF(_xlfn.XLOOKUP(8,AH:AH,R:R,"",0)="","",",`"&_xlfn.XLOOKUP(8,AH:AH,R:R,"",0)&"`") -> `CompanyCode`,`StoreCode`,`ItemCode`,`ApplyDate` | AL39: Y | AP39: Y | BP39: ="CREATE TRIGGER `"&$G$10&"_CR_Date_Time` BEFORE INSERT ON `"&$G$10&"` FOR EACH ROW SET NEW.record_create_date = CURRENT_DATE, NEW.record_create_time = CURRENT_TIME, NEW.record_update_date = CURRENT_DATE, NEW.record_update_time = CURRENT_TIME;" -> CREATE TRIGGER `ItemExMvkMaster_CR_Date_Time` BEFORE INSERT ON `ItemExMvkMaster` FOR EACH ROW SET NEW.record_create_date = CURRENT_DATE, NEW.record_create_time = CURRENT_TIME, NEW.record_update_date = CURRENT_DATE, NEW.record_update_time = CURRENT_TIME; | BV39: =IF(_xlfn.XLOOKUP(4,$AH:$AH,$R:$R,"",0)="","","AND A.`"&_xlfn.XLOOKUP(4,$AH:$AH,$R:$R,"",0)&"` = B.`"&_xlfn.XLOOKUP(4,$AH:$AH,$R:$R,"",0)&"`") -> AND A.`ApplyDate` = B.`ApplyDate` | BZ39: =IF(_xlfn.XLOOKUP(1,$AH:$AH,$R:$R,"",0)="","","A.`"&_xlfn.XLOOKUP(1,$AH:$AH,$R:$R,"",0)&"` = B.`"&_xlfn.XLOOKUP(1,$AH:$AH,$R:$R,"",0)&"`") -> A.`CompanyCode` = B.`CompanyCode`
BP40: ="CREATE TRIGGER `"&$G$10&"_UP_Date_Time` BEFORE UPDATE ON `"&$G$10&"` FOR EACH ROW SET NEW.record_update_date = CURRENT_DATE, NEW.record_update_time = CURRENT_TIME;" -> CREATE TRIGGER `ItemExMvkMaster_UP_Date_Time` BEFORE UPDATE ON `ItemExMvkMaster` FOR EACH ROW SET NEW.record_update_date = CURRENT_DATE, NEW.record_update_time = CURRENT_TIME; | BV40: =IF(_xlfn.XLOOKUP(5,$AH:$AH,$R:$R,"",0)="","","AND A.`"&_xlfn.XLOOKUP(5,$AH:$AH,$R:$R,"",0)&"` = B.`"&_xlfn.XLOOKUP(5,$AH:$AH,$R:$R,"",0)&"`") | BZ40: =IF(_xlfn.XLOOKUP(2,$AH:$AH,$R:$R,"",0)="","","AND A.`"&_xlfn.XLOOKUP(2,$AH:$AH,$R:$R,"",0)&"` = B.`"&_xlfn.XLOOKUP(2,$AH:$AH,$R:$R,"",0)&"`") -> AND A.`StoreCode` = B.`StoreCode`
BV41: =IF(_xlfn.XLOOKUP(6,$AH:$AH,$R:$R,"",0)="","","AND A.`"&_xlfn.XLOOKUP(6,$AH:$AH,$R:$R,"",0)&"` = B.`"&_xlfn.XLOOKUP(6,$AH:$AH,$R:$R,"",0)&"`") | BZ41: =IF(_xlfn.XLOOKUP(3,$AH:$AH,$R:$R,"",0)="","","AND A.`"&_xlfn.XLOOKUP(3,$AH:$AH,$R:$R,"",0)&"` = B.`"&_xlfn.XLOOKUP(3,$AH:$AH,$R:$R,"",0)&"`") -> AND A.`ItemCode` = B.`ItemCode`
B42: トリガー情報 | BV42: =IF(_xlfn.XLOOKUP(7,$AH:$AH,$R:$R,"",0)="","","AND A.`"&_xlfn.XLOOKUP(7,$AH:$AH,$R:$R,"",0)&"` = B.`"&_xlfn.XLOOKUP(7,$AH:$AH,$R:$R,"",0)&"`") | BZ42: =IF(_xlfn.XLOOKUP(4,$AH:$AH,$R:$R,"",0)="","","AND A.`"&_xlfn.XLOOKUP(4,$AH:$AH,$R:$R,"",0)&"` = B.`"&_xlfn.XLOOKUP(4,$AH:$AH,$R:$R,"",0)&"`") -> AND A.`ApplyDate` = B.`ApplyDate`
B43: No. | D43: トリガー名 | R43: イベント | U43: タイミング | Y43: 条件 | BV43: =IF(_xlfn.XLOOKUP(8,$AH:$AH,$R:$R,"",0)="","","AND A.`"&_xlfn.XLOOKUP(8,$AH:$AH,$R:$R,"",0)&"` = B.`"&_xlfn.XLOOKUP(8,$AH:$AH,$R:$R,"",0)&"`") | BZ43: =IF(_xlfn.XLOOKUP(5,$AH:$AH,$R:$R,"",0)="","","AND A.`"&_xlfn.XLOOKUP(5,$AH:$AH,$R:$R,"",0)&"` = B.`"&_xlfn.XLOOKUP(5,$AH:$AH,$R:$R,"",0)&"`")
B44: 1 | D44: =G10&"_"&R44&"_"&"trg" -> ItemExMvkMaster_update_trg | R44: update | U44: Before row | Y44: auto_updated_date | BV44: ; | BZ44: =IF(_xlfn.XLOOKUP(6,$AH:$AH,$R:$R,"",0)="","","AND A.`"&_xlfn.XLOOKUP(6,$AH:$AH,$R:$R,"",0)&"` = B.`"&_xlfn.XLOOKUP(6,$AH:$AH,$R:$R,"",0)&"`")
BZ45: =IF(_xlfn.XLOOKUP(7,$AH:$AH,$R:$R,"",0)="","","AND A.`"&_xlfn.XLOOKUP(7,$AH:$AH,$R:$R,"",0)&"` = B.`"&_xlfn.XLOOKUP(7,$AH:$AH,$R:$R,"",0)&"`")
BZ46: =IF(_xlfn.XLOOKUP(8,$AH:$AH,$R:$R,"",0)="","","AND A.`"&_xlfn.XLOOKUP(8,$AH:$AH,$R:$R,"",0)&"` = B.`"&_xlfn.XLOOKUP(8,$AH:$AH,$R:$R,"",0)&"`")
BZ47: );
BZ50: ="DROP TABLE IF EXISTS `TMP`.`"&$G$10&"`;" -> DROP TABLE IF EXISTS `TMP`.`ItemExMvkMaster`;
BZ51: COMMIT;

Sheet 分類マスタ
A1: システム名 | K1: システム種別 | W1: =IF(表紙!W1="","",表紙!W1) -> DB定義書 | AP1: 作成者 | AT1: 作成日 | AY1: 更新者 | BC1: 更新日 | BH1: 版数
A2: =IF(表紙!A2="","",表紙!A2) -> 現金専用簡易セルフPOS | K2: =IF(表紙!K2="","",表紙!K2) | AP2: =IF(表紙!AP2="","",表紙!AP2) -> きよはら | AT2: =IF(表紙!AT2="","",表紙!AT2) -> 44652 | AY2: =IF(表紙!AY2="","",表紙!AY2) -> Thanh Nguyên | BC2: =IF(表紙!BC2="","",表紙!BC2) -> 45285 | BH2: =IF(表紙!BH2="","",表紙!BH2) -> 0.2
A4: 機能カテゴリ | H4: =IF(表紙!H4="","",表紙!H4) -> 共通 | U4: 項目 | Z4: =IF(表紙!Z4="","",表紙!Z4) | AP4: 商品拡張マスタ
B7: ■テーブル情報
B8: スキーマ名 | G8: POS_MASTER | Y8: RDBMS名
B9: 論理名 | G9: 分類マスタ | Y9: バージョン
B10: 物理名 | G10: MDHierarchyMaster
B11: 備考
B19: ■カラム情報 | BP19: ="DROP TABLE IF EXISTS `"&$G$8&"`.`"&$G$10&"`;" -> DROP TABLE IF EXISTS `POS_MASTER`.`MDHierarchyMaster`;
B20: No. | D20: 論理名 | R20: 物理名 | AC20: データ型 | AH20: PK | AJ20: Not Null | AM20: デフォルト | AT20: 備考 | BP20: ="CREATE TABLE `"&$G$8&"`.`"&$G$10&"` (" -> CREATE TABLE `POS_MASTER`.`MDHierarchyMaster` (
B21: 1 | D21: レコードID | R21: RECORD_ID | AC21: bigint | AJ21: Y | AM21: 自動追加 | BP21: `RECORD_ID` bigint NOT NULL AUTO_INCREMENT COMMENT 'レコードID'
B22: =B21+1 -> 2 | D22: レコード作成日付 | R22: RECORD_CREATE_DATE | AC22: date | AJ22: Y | AM22: CURRENT_DATE | BP22: ,`RECORD_CREATE_DATE` date NOT NULL COMMENT 'レコード作成日付'
B23: =B22+1 -> 3 | D23: レコード作成時間 | R23: RECORD_CREATE_TIME | AC23: time | AJ23: Y | AM23: CURRENT_TIME | BP23: ,`RECORD_CREATE_TIME` time NOT NULL COMMENT 'レコード作成時間'
B24: =B23+1 -> 4 | D24: レコード更新日付 | R24: RECORD_UPDATE_DATE | AC24: date | AJ24: Y | AM24: CURRENT_DATE | AT24: トリガーにより更新 | BP24: ,`RECORD_UPDATE_DATE` date NOT NULL COMMENT 'レコード更新日付/トリガーにより更新' | BT24: ="LOAD DATA INFILE 'C:/04_DATAFILE/"&$G$10&"/TMP/"&$G$10&".CSV' " -> LOAD DATA INFILE 'C:/04_DATAFILE/MDHierarchyMaster/TMP/MDHierarchyMaster.CSV' | BV24: ="UPDATE `POS_MASTER`.`"&$G$10&"` A,`TMP`.`"&$G$10&"` B" -> UPDATE `POS_MASTER`.`MDHierarchyMaster` A,`TMP`.`MDHierarchyMaster` B
B25: =B24+1 -> 5 | D25: レコード更新時間 | R25: RECORD_UPDATE_TIME | AC25: time | AJ25: Y | AM25: CURRENT_TIME | AT25: トリガーにより更新 | BP25: ,`RECORD_UPDATE_TIME` time NOT NULL COMMENT 'レコード更新時間/トリガーにより更新' | BR25: ="DROP TABLE IF EXISTS `TMP`.`"&$G$10&"`;" -> DROP TABLE IF EXISTS `TMP`.`MDHierarchyMaster`; | BT25: ="REPLACE INTO TABLE TMP.`"&$G$10&"` CHARACTER SET 'UTF8'" -> REPLACE INTO TABLE TMP.`MDHierarchyMaster` CHARACTER SET 'UTF8' | BV25: SET
A26: @1 | B26: =B25+1 -> 6 | D26: レコード無効フラグ | R26: RECORD_VOID_FLAG | AC26: char(1) | AJ26: Y | AM26: "" | AT26: 0: 有効フラグ、 1:無効フラグ | BP26: ,`RECORD_VOID_FLAG` char(1) NOT NULL DEFAULT '' COMMENT 'レコード無効フラグ '''': 有効フラグ、 1:無効フラグ' | BR26: ="CREATE TABLE `TMP`.`"&G10&"` (" -> CREATE TABLE `TMP`.`MDHierarchyMaster` ( | BT26: =SUBSTITUTE(SUBSTITUTE("("&A26&","&A27&","&A28&","&A29&","&A30&","&A31&","&A32&","&A33&","&A34&","&A35&","&A36&","&A37&","&A38&","&A39&","&A40&","&A41&","&A42&","&A43&","&A44&","&A45&","&A46&","&A47&","&A48&","&A49&","&A50&","&A51&","&A52&","&A53&","&A54&","&A55&","&A56&","&A57&","&A58&","&A59&","&A60&","&A61&","&A62&")",",,",""),",)",")") -> (@1,@2,@3,@4,@5,@6,@7,@8,@9,@10,@11,@12,@13,@14,@15,@16,@17,@18,@19,@20,@21,@22,@23,@24) | BX26: ="INSERT INTO `POS_MASTER`.`"&$G$10&"` (" -> INSERT INTO `POS_MASTER`.`MDHierarchyMaster` ( | BZ26: ) SELECT
A27: @2 | B27: =B26+1 -> 7 | D27: 企業コード | R27: CompanyCode | AC27: {=_xlfn.SWITCH(BM27,"nvarchar","varchar("&BN27&")","smallint","smallint","date","date","money","decimal(19,4)","numeric","numeric("&BN27&")","int","int","bit","char(1)","datetime2","datetime","time","time")} -> varchar(10) | AH27: 1 | AJ27: Y | AT27: 会社コード | BM27: nvarchar | BN27: 10 | BP27: =",`"&R27&"` "&AC27&" "&IF(AJ27="Y","NOT NULL","")&" COMMENT '"&D27&"'" -> ,`CompanyCode` varchar(10) NOT NULL COMMENT '企業コード' | BR27: ="`"&R27&"` "&AC27&" "&IF(AJ27="Y","NOT NULL","") -> `CompanyCode` varchar(10) NOT NULL | BT27: ="SET `"&R27&"` = "&IF(LEFT(AC27,4)="date", "if(@"&B27-5&" > '0000-00-00 00:00:00', @"&B27-5&", null)","if(nullif( @"&B27-5&",'') > '', @"&B27-5&", null )") -> SET `CompanyCode` = if(nullif( @2,'') > '', @2, null ) | BV27: ="A.`"&R27&"` = B.`"&R27&"`" -> A.`CompanyCode` = B.`CompanyCode` | BX27: ="`"&R27&"`" -> `CompanyCode` | BZ27: ="`"&R27&"`" -> `CompanyCode`
A28: @3 | B28: =B27+1 -> 8 | D28: 店舗コード | R28: StoreCode | AC28: {=_xlfn.SWITCH(BM28,"nvarchar","varchar("&BN28&")","smallint","smallint","date","date","money","decimal(19,4)","numeric","numeric("&BN28&")","int","int","bit","char(1)","datetime2","datetime","time","time")} -> varchar(10) | AH28: 2 | AJ28: Y | AT28: 店舗コード | BM28: nvarchar | BN28: 10 | BP28: =",`"&R28&"` "&AC28&" "&IF(AJ28="Y","NOT NULL","")&" COMMENT '"&D28&"'" -> ,`StoreCode` varchar(10) NOT NULL COMMENT '店舗コード' | BR28: =",`"&R28&"` "&AC28&" "&IF(AJ28="Y","NOT NULL","") -> ,`StoreCode` varchar(10) NOT NULL | BT28: =",`"&R28&"` = "&IF(LEFT(AC28,4)="date", "if(@"&B28-5&" > '0000-00-00 00:00:00', if(@"&B28-5&" > '2999-12-31 23:59:59', '2999-12-31 23:59:59', @"&B28-5&"), null)","if(nullif( @"&B28-5&",'') > '', @"&B28-5&", null )") -> ,`StoreCode` = if(nullif( @3,'') > '', @3, null ) | BV28: =",A.`"&R28&"` = B.`"&R28&"`" -> ,A.`StoreCode` = B.`StoreCode` | BX28: =",`"&R28&"`" -> ,`StoreCode` | BZ28: =",`"&R28&"`" -> ,`StoreCode`
A29: @4 | B29: =B28+1 -> 9 | D29: 分類コード | R29: MDHierarchyCode | AC29: {=_xlfn.SWITCH(BM29,"nvarchar","varchar("&BN29&")","smallint","smallint","date","date","money","decimal(19,4)","numeric","numeric("&BN29&")","int","int","bit","char(1)","datetime2","datetime","time","time")} -> varchar(10) | AH29: 3 | AJ29: Y | AT29: 各分類コードを設定する | BM29: nvarchar | BN29: 10 | BP29: =",`"&R29&"` "&AC29&" "&IF(AJ29="Y","NOT NULL","")&" COMMENT '"&D29&"'" -> ,`MDHierarchyCode` varchar(10) NOT NULL COMMENT '分類コード' | BR29: =",`"&R29&"` "&AC29&" "&IF(AJ29="Y","NOT NULL","") -> ,`MDHierarchyCode` varchar(10) NOT NULL | BT29: =",`"&R29&"` = "&IF(LEFT(AC29,4)="date", "if(@"&B29-5&" > '0000-00-00 00:00:00', if(@"&B29-5&" > '2999-12-31 23:59:59', '2999-12-31 23:59:59', @"&B29-5&"), null)","if(nullif( @"&B29-5&",'') > '', @"&B29-5&", null )") -> ,`MDHierarchyCode` = if(nullif( @4,'') > '', @4, null ) | BV29: =",A.`"&R29&"` = B.`"&R29&"`" -> ,A.`MDHierarchyCode` = B.`MDHierarchyCode` | BX29: =",`"&R29&"`" -> ,`MDHierarchyCode` | BZ29: =",`"&R29&"`" -> ,`MDHierarchyCode`
A30: @5 | B30: =B29+1 -> 10 | D30: 分類レベル | R30: MDHierarchyLevel | AC30: {=_xlfn.SWITCH(BM30,"nvarchar","varchar("&BN30&")","smallint","smallint","date","date","money","decimal(19,4)","numeric","numeric("&BN30&")","int","int","bit","char(1)","datetime2","datetime","time","time")} -> int | AH30: 4 | AJ30: Y | AT30: 各分類のレベルコードを設定する "1"：部門 "2"：品種 "3"：品群 "4"：分類 | BM30: int | BP30: =",`"&R30&"` "&AC30&" "&IF(AJ30="Y","NOT NULL","")&" COMMENT '"&D30&"'" -> ,`MDHierarchyLevel` int NOT NULL COMMENT '分類レベル' | BR30: =",`"&R30&"` "&AC30&" "&IF(AJ30="Y","NOT NULL","") -> ,`MDHierarchyLevel` int NOT NULL | BT30: =",`"&R30&"` = "&IF(LEFT(AC30,4)="date", "if(@"&B30-5&" > '0000-00-00 00:00:00', if(@"&B30-5&" > '2999-12-31 23:59:59', '2999-12-31 23:59:59', @"&B30-5&"), null)","if(nullif( @"&B30-5&",'') > '', @"&B30-5&", null )") -> ,`MDHierarchyLevel` = if(nullif( @5,'') > '', @5, null ) | BV30: =",A.`"&R30&"` = B.`"&R30&"`" -> ,A.`MDHierarchyLevel` = B.`MDHierarchyLevel` | BX30: =",`"&R30&"`" -> ,`MDHierarchyLevel` | BZ30: =",`"&R30&"`" -> ,`MDHierarchyLevel`
A31: @6 | B31: =B30+1 -> 11 | D31: 適用日 | R31: ApplyDate | AC31: {=_xlfn.SWITCH(BM31,"nvarchar","varchar("&BN31&")","smallint","smallint","date","date","money","decimal(19,4)","numeric","numeric("&BN31&")","int","int","bit","char(1)","datetime2","datetime","time","time")} -> date | AH31: 5 | AJ31: Y | AT31: 利用開始日を設定する | BM31: date | BP31: =",`"&R31&"` "&AC31&" "&IF(AJ31="Y","NOT NULL","")&" COMMENT '"&D31&"'" -> ,`ApplyDate` date NOT NULL COMMENT '適用日' | BR31: =",`"&R31&"` "&AC31&" "&IF(AJ31="Y","NOT NULL","") -> ,`ApplyDate` date NOT NULL | BT31: =",`"&R31&"` = "&IF(LEFT(AC31,4)="date", "if(@"&B31-5&" > '0000-00-00 00:00:00', if(@"&B31-5&" > '2999-12-31 23:59:59', '2999-12-31 23:59:59', @"&B31-5&"), null)","if(nullif( @"&B31-5&",'') > '', @"&B31-5&", null )") -> ,`ApplyDate` = if(@6 > '0000-00-00 00:00:00', if(@6 > '2999-12-31 23:59:59', '2999-12-31 23:59:59', @6), null) | BV31: =",A.`"&R31&"` = B.`"&R31&"`" -> ,A.`ApplyDate` = B.`ApplyDate` | BX31: =",`"&R31&"`" -> ,`ApplyDate` | BZ31: =",`"&R31&"`" -> ,`ApplyDate`
A32: @7 | B32: =B31+1 -> 12 | D32: 親分類コード | R32: ParentCode | AC32: {=_xlfn.SWITCH(BM32,"nvarchar","varchar("&BN32&")","smallint","smallint","date","date","money","decimal(19,4)","numeric","numeric("&BN32&")","int","int","bit","char(1)","datetime2","datetime","time","time")} -> varchar(10) | AT32: 各分類コードが属する上位の分類コード ※分類レベルが「"1"：部門」である場合、NULL固定 | BM32: nvarchar | BN32: 10 | BP32: =",`"&R32&"` "&AC32&" "&IF(AJ32="Y","NOT NULL","")&" COMMENT '"&D32&"'" -> ,`ParentCode` varchar(10) COMMENT '親分類コード' | BR32: =",`"&R32&"` "&AC32&" "&IF(AJ32="Y","NOT NULL","") -> ,`ParentCode` varchar(10) | BT32: =",`"&R32&"` = "&IF(LEFT(AC32,4)="date", "if(@"&B32-5&" > '0000-00-00 00:00:00', if(@"&B32-5&" > '2999-12-31 23:59:59', '2999-12-31 23:59:59', @"&B32-5&"), null)","if(nullif( @"&B32-5&",'') > '', @"&B32-5&", null )") -> ,`ParentCode` = if(nullif( @7,'') > '', @7, null ) | BV32: =",A.`"&R32&"` = B.`"&R32&"`" -> ,A.`ParentCode` = B.`ParentCode` | BX32: =",`"&R32&"`" -> ,`ParentCode` | BZ32: =",`"&R32&"`" -> ,`ParentCode`
A33: @8 | B33: =B32+1 -> 13 | D33: 親分類レベルコード | R33: ParentHierarchyLevel | AC33: {=_xlfn.SWITCH(BM33,"nvarchar","varchar("&BN33&")","smallint","smallint","date","date","money","decimal(19,4)","numeric","numeric("&BN33&")","int","int","bit","char(1)","datetime2","datetime","time","time")} -> int | AT33: 各分類コードが属する上位の分類のレベルコードを設定する ※MD階層レベルが「"1"：部門」である場合、NULL固定 | BM33: int | BP33: =",`"&R33&"` "&AC33&" "&IF(AJ33="Y","NOT NULL","")&" COMMENT '"&D33&"'" -> ,`ParentHierarchyLevel` int COMMENT '親分類レベルコード' | BR33: =",`"&R33&"` "&AC33&" "&IF(AJ33="Y","NOT NULL","") -> ,`ParentHierarchyLevel` int | BT33: =",`"&R33&"` = "&IF(LEFT(AC33,4)="date", "if(@"&B33-5&" > '0000-00-00 00:00:00', if(@"&B33-5&" > '2999-12-31 23:59:59', '2999-12-31 23:59:59', @"&B33-5&"), null)","if(nullif( @"&B33-5&",'') > '', @"&B33-5&", null )") -> ,`ParentHierarchyLevel` = if(nullif( @8,'') > '', @8, null ) | BV33: =",A.`"&R33&"` = B.`"&R33&"`" -> ,A.`ParentHierarchyLevel` = B.`ParentHierarchyLevel` | BX33: =",`"&R33&"`" -> ,`ParentHierarchyLevel` | BZ33: =",`"&R33&"`" -> ,`ParentHierarchyLevel`
A34: @9 | B34: =B33+1 -> 14 | D34: 説明 （画面、レシート、ラインディスプレイにて使用） | R34: Description | AC34: {=_xlfn.SWITCH(BM34,"nvarchar","varchar("&BN34&")","smallint","smallint","date","date","money","decimal(19,4)","numeric","numeric("&BN34&")","int","int","bit","char(1)","datetime2","datetime","time","time")} -> varchar(50) | AT34: 画面、レシート、ラインディスプレイにて使用 | BM34: nvarchar | BN34: 50 | BP34: =",`"&R34&"` "&AC34&" "&IF(AJ34="Y","NOT NULL","")&" COMMENT '"&D34&"'" -> ,`Description` varchar(50) COMMENT '説明 （画面、レシート、ラインディスプレイにて使用）' | BR34: =",`"&R34&"` "&AC34&" "&IF(AJ34="Y","NOT NULL","") -> ,`Description` varchar(50) | BT34: =",`"&R34&"` = "&IF(LEFT(AC34,4)="date", "if(@"&B34-5&" > '0000-00-00 00:00:00', if(@"&B34-5&" > '2999-12-31 23:59:59', '2999-12-31 23:59:59', @"&B34-5&"), null)","if(nullif( @"&B34-5&",'') > '', @"&B34-5&", null )") -> ,`Description` = if(nullif( @9,'') > '', @9, null ) | BV34: =",A.`"&R34&"` = B.`"&R34&"`" -> ,A.`Description` = B.`Description` | BX34: =",`"&R34&"`" -> ,`Description` | BZ34: =",`"&R34&"`" -> ,`Description`
A35: @10 | B35: =B34+1 -> 15 | D35: 簡略説明 （ラインディスプレイ（半角カナ用）にて使用） | R35: DescriptionShort | AC35: {=_xlfn.SWITCH(BM35,"nvarchar","varchar("&BN35&")","smallint","smallint","date","date","money","decimal(19,4)","numeric","numeric("&BN35&")","int","int","bit","char(1)","datetime2","datetime","time","time")} -> varchar(25) | AT35: ラインディスプレイ（半角カナ用）にて使用 | BM35: nvarchar | BN35: 25 | BP35: =",`"&R35&"` "&AC35&" "&IF(AJ35="Y","NOT NULL","")&" COMMENT '"&D35&"'" -> ,`DescriptionShort` varchar(25) COMMENT '簡略説明 （ラインディスプレイ（半角カナ用）にて使用）' | BR35: =",`"&R35&"` "&AC35&" "&IF(AJ35="Y","NOT NULL","") -> ,`DescriptionShort` varchar(25) | BT35: =",`"&R35&"` = "&IF(LEFT(AC35,4)="date", "if(@"&B35-5&" > '0000-00-00 00:00:00', if(@"&B35-5&" > '2999-12-31 23:59:59', '2999-12-31 23:59:59', @"&B35-5&"), null)","if(nullif( @"&B35-5&",'') > '', @"&B35-5&", null )") -> ,`DescriptionShort` = if(nullif( @10,'') > '', @10, null ) | BV35: =",A.`"&R35&"` = B.`"&R35&"`" -> ,A.`DescriptionShort` = B.`DescriptionShort` | BX35: =",`"&R35&"`" -> ,`DescriptionShort` | BZ35: =",`"&R35&"`" -> ,`DescriptionShort`
A36: @11 | B36: =B35+1 -> 16 | D36: 税グループコード | R36: TaxGroupCode | AC36: {=_xlfn.SWITCH(BM36,"nvarchar","varchar("&BN36&")","smallint","smallint","date","date","money","decimal(19,4)","numeric","numeric("&BN36&")","int","int","bit","char(1)","datetime2","datetime","time","time")} -> varchar(2) | AT36: 税率セットの定義コードを設定する NULL：上位参照 "01" ：外税8% （2019/10/1以降、軽減税率) "02" ：内税8% （2019/10/1以降、軽減税率) "03" ：非課税 "11" ：外税10% "12" ：内税10% "31" ：外税8%(返品用) "32" ：内税8%(返品用) | BM36: nvarchar | BN36: 2 | BP36: =",`"&R36&"` "&AC36&" "&IF(AJ36="Y","NOT NULL","")&" COMMENT '"&D36&"'" -> ,`TaxGroupCode` varchar(2) COMMENT '税グループコード' | BR36: =",`"&R36&"` "&AC36&" "&IF(AJ36="Y","NOT NULL","") -> ,`TaxGroupCode` varchar(2) | BT36: =",`"&R36&"` = "&IF(LEFT(AC36,4)="date", "if(@"&B36-5&" > '0000-00-00 00:00:00', if(@"&B36-5&" > '2999-12-31 23:59:59', '2999-12-31 23:59:59', @"&B36-5&"), null)","if(nullif( @"&B36-5&",'') > '', @"&B36-5&", null )") -> ,`TaxGroupCode` = if(nullif( @11,'') > '', @11, null ) | BV36: =",A.`"&R36&"` = B.`"&R36&"`" -> ,A.`TaxGroupCode` = B.`TaxGroupCode` | BX36: =",`"&R36&"`" -> ,`TaxGroupCode` | BZ36: =",`"&R36&"`" -> ,`TaxGroupCode`
A37: @12 | B37: =B36+1 -> 17 | D37: 値入率 | R37: MarkupRatio | AC37: {=_xlfn.SWITCH(BM37,"nvarchar","varchar("&BN37&")","smallint","smallint","date","date","money","decimal(19,4)","numeric","numeric("&BN37&")","int","int","bit","char(1)","datetime2","datetime","time","time")} -> numeric(5, 2) | BM37: numeric | BN37: 5, 2 | BP37: =",`"&R37&"` "&AC37&" "&IF(AJ37="Y","NOT NULL","")&" COMMENT '"&D37&"'" -> ,`MarkupRatio` numeric(5, 2) COMMENT '値入率' | BR37: =",`"&R37&"` "&AC37&" "&IF(AJ37="Y","NOT NULL","") -> ,`MarkupRatio` numeric(5, 2) | BT37: =",`"&R37&"` = "&IF(LEFT(AC37,4)="date", "if(@"&B37-5&" > '0000-00-00 00:00:00', if(@"&B37-5&" > '2999-12-31 23:59:59', '2999-12-31 23:59:59', @"&B37-5&"), null)","if(nullif( @"&B37-5&",'') > '', @"&B37-5&", null )") -> ,`MarkupRatio` = if(nullif( @12,'') > '', @12, null ) | BV37: =",A.`"&R37&"` = B.`"&R37&"`" -> ,A.`MarkupRatio` = B.`MarkupRatio` | BX37: =",`"&R37&"`" -> ,`MarkupRatio` | BZ37: =",`"&R37&"`" -> ,`MarkupRatio`
A38: @13 | B38: =B37+1 -> 18 | D38: 部門区分コード | R38: DepartmentTypeCode | AC38: {=_xlfn.SWITCH(BM38,"nvarchar","varchar("&BN38&")","smallint","smallint","date","date","money","decimal(19,4)","numeric","numeric("&BN38&")","int","int","bit","char(1)","datetime2","datetime","time","time")} -> varchar(2) | AT38: 売上部門を設定する 「通常商品、売上外商品」を別けて集計します。 "00"：通常 "01"：売上外 | BM38: nvarchar | BN38: 2 | BP38: =",`"&R38&"` "&AC38&" "&IF(AJ38="Y","NOT NULL","")&" COMMENT '"&D38&"'" -> ,`DepartmentTypeCode` varchar(2) COMMENT '部門区分コード' | BR38: =",`"&R38&"` "&AC38&" "&IF(AJ38="Y","NOT NULL","") -> ,`DepartmentTypeCode` varchar(2) | BT38: =",`"&R38&"` = "&IF(LEFT(AC38,4)="date", "if(@"&B38-5&" > '0000-00-00 00:00:00', if(@"&B38-5&" > '2999-12-31 23:59:59', '2999-12-31 23:59:59', @"&B38-5&"), null)","if(nullif( @"&B38-5&",'') > '', @"&B38-5&", null )") -> ,`DepartmentTypeCode` = if(nullif( @13,'') > '', @13, null ) | BV38: =",A.`"&R38&"` = B.`"&R38&"`" -> ,A.`DepartmentTypeCode` = B.`DepartmentTypeCode` | BX38: =",`"&R38&"`" -> ,`DepartmentTypeCode` | BZ38: =",`"&R38&"`" -> ,`DepartmentTypeCode`
A39: @14 | B39: =B38+1 -> 19 | D39: 現金以外決済不可フラグ | R39: IsCashOnly | AC39: {=_xlfn.SWITCH(BM39,"nvarchar","varchar("&BN39&")","smallint","smallint","date","date","money","decimal(19,4)","numeric","numeric("&BN39&")","int","int","bit","char(1)","datetime2","datetime","time","time")} -> char(1) | AT39: 支払方法を現金に限定するか否かを設定する NULL：上位参照 0：現金以外決済可 1：現金以外決済不可 | BM39: bit | BP39: =",`"&R39&"` "&AC39&" "&IF(AJ39="Y","NOT NULL","")&" COMMENT '"&D39&"'" -> ,`IsCashOnly` char(1) COMMENT '現金以外決済不可フラグ' | BR39: =",`"&R39&"` "&AC39&" "&IF(AJ39="Y","NOT NULL","") -> ,`IsCashOnly` char(1) | BT39: =",`"&R39&"` = "&IF(LEFT(AC39,4)="date", "if(@"&B39-5&" > '0000-00-00 00:00:00', if(@"&B39-5&" > '2999-12-31 23:59:59', '2999-12-31 23:59:59', @"&B39-5&"), null)","if(nullif( @"&B39-5&",'') > '', @"&B39-5&", null )") -> ,`IsCashOnly` = if(nullif( @14,'') > '', @14, null ) | BV39: =",A.`"&R39&"` = B.`"&R39&"`" -> ,A.`IsCashOnly` = B.`IsCashOnly` | BX39: =",`"&R39&"`" -> ,`IsCashOnly` | BZ39: =",`"&R39&"`" -> ,`IsCashOnly`
A40: @15 | B40: =B39+1 -> 20 | D40: 手動アイテム値引禁止フラグ | R40: IsItemManualDiscountProhibition | AC40: {=_xlfn.SWITCH(BM40,"nvarchar","varchar("&BN40&")","smallint","smallint","date","date","money","decimal(19,4)","numeric","numeric("&BN40&")","int","int","bit","char(1)","datetime2","datetime","time","time")} -> char(1) | AT40: POS操作による値引を許可するか否かを設定する NULL：上位参照 0：手動アイテム値引可 1：手動アイテム値引不可 | BM40: bit | BP40: =",`"&R40&"` "&AC40&" "&IF(AJ40="Y","NOT NULL","")&" COMMENT '"&D40&"'" -> ,`IsItemManualDiscountProhibition` char(1) COMMENT '手動アイテム値引禁止フラグ' | BR40: =",`"&R40&"` "&AC40&" "&IF(AJ40="Y","NOT NULL","") -> ,`IsItemManualDiscountProhibition` char(1) | BT40: =",`"&R40&"` = "&IF(LEFT(AC40,4)="date", "if(@"&B40-5&" > '0000-00-00 00:00:00', if(@"&B40-5&" > '2999-12-31 23:59:59', '2999-12-31 23:59:59', @"&B40-5&"), null)","if(nullif( @"&B40-5&",'') > '', @"&B40-5&", null )") -> ,`IsItemManualDiscountProhibition` = if(nullif( @15,'') > '', @15, null ) | BV40: =",A.`"&R40&"` = B.`"&R40&"`" -> ,A.`IsItemManualDiscountProhibition` = B.`IsItemManualDiscountProhibition` | BX40: =",`"&R40&"`" -> ,`IsItemManualDiscountProhibition` | BZ40: =",`"&R40&"`" -> ,`IsItemManualDiscountProhibition`
A41: @16 | B41: =B40+1 -> 21 | D41: 小計値引禁止フラグ | R41: IsSubTotalDiscountProhibition | AC41: {=_xlfn.SWITCH(BM41,"nvarchar","varchar("&BN41&")","smallint","smallint","date","date","money","decimal(19,4)","numeric","numeric("&BN41&")","int","int","bit","char(1)","datetime2","datetime","time","time")} -> char(1) | AT41: クーポン等による小計値引の対象とするか否かを設定する NULL：上位参照 0：小計値引対象 1：小計値引対象外 | BM41: bit | BP41: =",`"&R41&"` "&AC41&" "&IF(AJ41="Y","NOT NULL","")&" COMMENT '"&D41&"'" -> ,`IsSubTotalDiscountProhibition` char(1) COMMENT '小計値引禁止フラグ' | BR41: =",`"&R41&"` "&AC41&" "&IF(AJ41="Y","NOT NULL","") -> ,`IsSubTotalDiscountProhibition` char(1) | BT41: =",`"&R41&"` = "&IF(LEFT(AC41,4)="date", "if(@"&B41-5&" > '0000-00-00 00:00:00', if(@"&B41-5&" > '2999-12-31 23:59:59', '2999-12-31 23:59:59', @"&B41-5&"), null)","if(nullif( @"&B41-5&",'') > '', @"&B41-5&", null )") -> ,`IsSubTotalDiscountProhibition` = if(nullif( @16,'') > '', @16, null ) | BV41: =",A.`"&R41&"` = B.`"&R41&"`" -> ,A.`IsSubTotalDiscountProhibition` = B.`IsSubTotalDiscountProhibition` | BX41: =",`"&R41&"`" -> ,`IsSubTotalDiscountProhibition` | BZ41: =",`"&R41&"`" -> ,`IsSubTotalDiscountProhibition`
A42: @17 | B42: =B41+1 -> 22 | D42: 売価変更禁止フラグ | R42: IsChangePriceProhibition | AC42: {=_xlfn.SWITCH(BM42,"nvarchar","varchar("&BN42&")","smallint","smallint","date","date","money","decimal(19,4)","numeric","numeric("&BN42&")","int","int","bit","char(1)","datetime2","datetime","time","time")} -> char(1) | AT42: POS操作による売価変更を許可するか否かを設定する NULL：上位参照 0：売価変更可 1：売価変更不可 | BM42: bit | BP42: =",`"&R42&"` "&AC42&" "&IF(AJ42="Y","NOT NULL","")&" COMMENT '"&D42&"'" -> ,`IsChangePriceProhibition` char(1) COMMENT '売価変更禁止フラグ' | BR42: =",`"&R42&"` "&AC42&" "&IF(AJ42="Y","NOT NULL","") -> ,`IsChangePriceProhibition` char(1) | BT42: =",`"&R42&"` = "&IF(LEFT(AC42,4)="date", "if(@"&B42-5&" > '0000-00-00 00:00:00', if(@"&B42-5&" > '2999-12-31 23:59:59', '2999-12-31 23:59:59', @"&B42-5&"), null)","if(nullif( @"&B42-5&",'') > '', @"&B42-5&", null )") -> ,`IsChangePriceProhibition` = if(nullif( @17,'') > '', @17, null ) | BV42: =",A.`"&R42&"` = B.`"&R42&"`" -> ,A.`IsChangePriceProhibition` = B.`IsChangePriceProhibition` | BX42: =",`"&R42&"`" -> ,`IsChangePriceProhibition` | BZ42: =",`"&R42&"`" -> ,`IsChangePriceProhibition`
A43: @18 | B43: =B42+1 -> 23 | D43: 販売制限商品区分 | R43: SalesRestrictionItemArea | AC43: {=_xlfn.SWITCH(BM43,"nvarchar","varchar("&BN43&")","smallint","smallint","date","date","money","decimal(19,4)","numeric","numeric("&BN43&")","int","int","bit","char(1)","datetime2","datetime","time","time")} -> varchar(2) | AT43: (設定ありで所属する分類にも販売制限商品区分が設定されている場合：《単品マスタ》の設定を採用 NULL：上位参照) 1:分類なし 2:第1分類 3:指定第2分類 4:第2分類 5:第3分類 6:要指導 | BM43: nvarchar | BN43: 2 | BP43: =",`"&R43&"` "&AC43&" "&IF(AJ43="Y","NOT NULL","")&" COMMENT '"&D43&"'" -> ,`SalesRestrictionItemArea` varchar(2) COMMENT '販売制限商品区分' | BR43: =",`"&R43&"` "&AC43&" "&IF(AJ43="Y","NOT NULL","") -> ,`SalesRestrictionItemArea` varchar(2) | BT43: =",`"&R43&"` = "&IF(LEFT(AC43,4)="date", "if(@"&B43-5&" > '0000-00-00 00:00:00', if(@"&B43-5&" > '2999-12-31 23:59:59', '2999-12-31 23:59:59', @"&B43-5&"), null)","if(nullif( @"&B43-5&",'') > '', @"&B43-5&", null )") -> ,`SalesRestrictionItemArea` = if(nullif( @18,'') > '', @18, null ) | BV43: =",A.`"&R43&"` = B.`"&R43&"`" -> ,A.`SalesRestrictionItemArea` = B.`SalesRestrictionItemArea` | BX43: =",`"&R43&"`" -> ,`SalesRestrictionItemArea` | BZ43: =",`"&R43&"`" -> ,`SalesRestrictionItemArea`
A44: @19 | B44: =B43+1 -> 24 | D44: 販売制限年齢 | R44: SalesAlertAge | AC44: {=_xlfn.SWITCH(BM44,"nvarchar","varchar("&BN44&")","smallint","smallint","date","date","money","decimal(19,4)","numeric","numeric("&BN44&")","int","int","bit","char(1)","datetime2","datetime","time","time")} -> int | AT44: 年齢制限を行う場合のみ制限する年齢 (設定ありで所属する分類にも販売制限年齢が設定されている場合：《単品マスタ》の設定を採用 NULL：上位参照 0の場合：年齢制限なし) | BM44: int | BP44: =",`"&R44&"` "&AC44&" "&IF(AJ44="Y","NOT NULL","")&" COMMENT '"&D44&"'" -> ,`SalesAlertAge` int COMMENT '販売制限年齢' | BR44: =",`"&R44&"` "&AC44&" "&IF(AJ44="Y","NOT NULL","") -> ,`SalesAlertAge` int | BT44: =",`"&R44&"` = "&IF(LEFT(AC44,4)="date", "if(@"&B44-5&" > '0000-00-00 00:00:00', if(@"&B44-5&" > '2999-12-31 23:59:59', '2999-12-31 23:59:59', @"&B44-5&"), null)","if(nullif( @"&B44-5&",'') > '', @"&B44-5&", null )") -> ,`SalesAlertAge` = if(nullif( @19,'') > '', @19, null ) | BV44: =",A.`"&R44&"` = B.`"&R44&"`" -> ,A.`SalesAlertAge` = B.`SalesAlertAge` | BX44: =",`"&R44&"`" -> ,`SalesAlertAge` | BZ44: =",`"&R44&"`" -> ,`SalesAlertAge`
A45: @20 | B45: =B44+1 -> 25 | D45: 保証書発行フラグ | R45: IsWarrantyReceiptPrint | AC45: {=_xlfn.SWITCH(BM45,"nvarchar","varchar("&BN45&")","smallint","smallint","date","date","money","decimal(19,4)","numeric","numeric("&BN45&")","int","int","bit","char(1)","datetime2","datetime","time","time")} -> char(1) | AT45: 対象商品販売時、保証書を発行するか否かを設定する （単品指定のみ） 0：発行しない 1：発行する | BM45: bit | BP45: =",`"&R45&"` "&AC45&" "&IF(AJ45="Y","NOT NULL","")&" COMMENT '"&D45&"'" -> ,`IsWarrantyReceiptPrint` char(1) COMMENT '保証書発行フラグ' | BR45: =",`"&R45&"` "&AC45&" "&IF(AJ45="Y","NOT NULL","") -> ,`IsWarrantyReceiptPrint` char(1) | BT45: =",`"&R45&"` = "&IF(LEFT(AC45,4)="date", "if(@"&B45-5&" > '0000-00-00 00:00:00', if(@"&B45-5&" > '2999-12-31 23:59:59', '2999-12-31 23:59:59', @"&B45-5&"), null)","if(nullif( @"&B45-5&",'') > '', @"&B45-5&", null )") -> ,`IsWarrantyReceiptPrint` = if(nullif( @20,'') > '', @20, null ) | BV45: =",A.`"&R45&"` = B.`"&R45&"`" -> ,A.`IsWarrantyReceiptPrint` = B.`IsWarrantyReceiptPrint` | BX45: =",`"&R45&"`" -> ,`IsWarrantyReceiptPrint` | BZ45: =",`"&R45&"`" -> ,`IsWarrantyReceiptPrint`
A46: @21 | B46: =B45+1 -> 26 | D46: ポイント除外フラグ | R46: IsPointProhibition | AC46: {=_xlfn.SWITCH(BM46,"nvarchar","varchar("&BN46&")","smallint","smallint","date","date","money","decimal(19,4)","numeric","numeric("&BN46&")","int","int","bit","char(1)","datetime2","datetime","time","time")} -> char(1) | AT46: 対象商品販売時、ポイント付与対象から除外するか否かを設定する NULL：上位参照 0：ポイント対象 1：ポイント対象外 ※但し、WAONポイント除外対象は当項目の値を利用せずに実現している | BM46: bit | BP46: =",`"&R46&"` "&AC46&" "&IF(AJ46="Y","NOT NULL","")&" COMMENT '"&D46&"'" -> ,`IsPointProhibition` char(1) COMMENT 'ポイント除外フラグ' | BR46: =",`"&R46&"` "&AC46&" "&IF(AJ46="Y","NOT NULL","") -> ,`IsPointProhibition` char(1) | BT46: =",`"&R46&"` = "&IF(LEFT(AC46,4)="date", "if(@"&B46-5&" > '0000-00-00 00:00:00', if(@"&B46-5&" > '2999-12-31 23:59:59', '2999-12-31 23:59:59', @"&B46-5&"), null)","if(nullif( @"&B46-5&",'') > '', @"&B46-5&", null )") -> ,`IsPointProhibition` = if(nullif( @21,'') > '', @21, null ) | BV46: =",A.`"&R46&"` = B.`"&R46&"`" -> ,A.`IsPointProhibition` = B.`IsPointProhibition` | BX46: =",`"&R46&"`" -> ,`IsPointProhibition` | BZ46: =",`"&R46&"`" -> ,`IsPointProhibition`
A47: @22 | B47: =B46+1 -> 27 | D47: ポイント率 | R47: PointRate | AC47: {=_xlfn.SWITCH(BM47,"nvarchar","varchar("&BN47&")","smallint","smallint","date","date","money","decimal(19,4)","numeric","numeric("&BN47&")","int","int","bit","char(1)","datetime2","datetime","time","time")} -> numeric(5, 2) | AJ47: Y | AT47: ポイント率 | BM47: numeric | BN47: 5, 2 | BP47: =",`"&R47&"` "&AC47&" "&IF(AJ47="Y","NOT NULL","")&" COMMENT '"&D47&"'" -> ,`PointRate` numeric(5, 2) NOT NULL COMMENT 'ポイント率' | BR47: =",`"&R47&"` "&AC47&" "&IF(AJ47="Y","NOT NULL","") -> ,`PointRate` numeric(5, 2) NOT NULL | BT47: =",`"&R47&"` = "&IF(LEFT(AC47,4)="date", "if(@"&B47-5&" > '0000-00-00 00:00:00', if(@"&B47-5&" > '2999-12-31 23:59:59', '2999-12-31 23:59:59', @"&B47-5&"), null)","if(nullif( @"&B47-5&",'') > '', @"&B47-5&", null )") -> ,`PointRate` = if(nullif( @22,'') > '', @22, null ) | BV47: =",A.`"&R47&"` = B.`"&R47&"`" -> ,A.`PointRate` = B.`PointRate` | BX47: =",`"&R47&"`" -> ,`PointRate` | BZ47: =",`"&R47&"`" -> ,`PointRate`
A48: @23 | B48: =B47+1 -> 28 | D48: 原価率 | R48: CostRate | AC48: {=_xlfn.SWITCH(BM48,"nvarchar","varchar("&BN48&")","smallint","smallint","date","date","money","decimal(19,4)","numeric","numeric("&BN48&")","int","int","bit","char(1)","datetime2","datetime","time","time")} -> numeric(5, 2) | AJ48: Y | AT48: 原価率 | BM48: numeric | BN48: 5, 2 | BP48: =",`"&R48&"` "&AC48&" "&IF(AJ48="Y","NOT NULL","")&" COMMENT '"&D48&"'" -> ,`CostRate` numeric(5, 2) NOT NULL COMMENT '原価率' | BR48: =",`"&R48&"` "&AC48&" "&IF(AJ48="Y","NOT NULL","") -> ,`CostRate` numeric(5, 2) NOT NULL | BT48: =",`"&R48&"` = "&IF(LEFT(AC48,4)="date", "if(@"&B48-5&" > '0000-00-00 00:00:00', if(@"&B48-5&" > '2999-12-31 23:59:59', '2999-12-31 23:59:59', @"&B48-5&"), null)","if(nullif( @"&B48-5&",'') > '', @"&B48-5&", null )") -> ,`CostRate` = if(nullif( @23,'') > '', @23, null ) | BV48: =",A.`"&R48&"` = B.`"&R48&"`" -> ,A.`CostRate` = B.`CostRate` | BX48: =",`"&R48&"`" -> ,`CostRate` | BZ48: =",`"&R48&"`" -> ,`CostRate`
A49: @24 | B49: =B48+1 -> 29 | D49: 消費税免税タイプ | R49: TaxFreeType | AC49: {=_xlfn.SWITCH(BM49,"nvarchar","varchar("&BN49&")","smallint","smallint","date","date","money","decimal(19,4)","numeric","numeric("&BN49&")","int","int","bit","char(1)","datetime2","datetime","time","time")} -> int | AT49: 免税販売時、対象商品の免税種別を設定する NULL：上位参照 1：消耗品 2：一般品 | BM49: int | BP49: =",`"&R49&"` "&AC49&" "&IF(AJ49="Y","NOT NULL","")&" COMMENT '"&D49&"'" -> ,`TaxFreeType` int COMMENT '消費税免税タイプ' | BR49: =",`"&R49&"` "&AC49&" "&IF(AJ49="Y","NOT NULL","") -> ,`TaxFreeType` int | BT49: =",`"&R49&"` = "&IF(LEFT(AC49,4)="date", "if(@"&B49-5&" > '0000-00-00 00:00:00', if(@"&B49-5&" > '2999-12-31 23:59:59', '2999-12-31 23:59:59', @"&B49-5&"), null)","if(nullif( @"&B49-5&",'') > '', @"&B49-5&", null )") -> ,`TaxFreeType` = if(nullif( @24,'') > '', @24, null ) | BV49: =",A.`"&R49&"` = B.`"&R49&"`" -> ,A.`TaxFreeType` = B.`TaxFreeType` | BX49: =",`"&R49&"`" -> ,`TaxFreeType` | BZ49: =",`"&R49&"`" -> ,`TaxFreeType`
BP50: =" , PRIMARY KEY ("&IF(_xlfn.XLOOKUP(1,$AH:$AH,$R:$R,"",0)="","","`"&_xlfn.XLOOKUP(1,$AH:$AH,$R:$R,"",0)&"`")&IF(_xlfn.XLOOKUP(2,$AH:$AH,$R:$R,"",0)="","",",`"&_xlfn.XLOOKUP(2,$AH:$AH,$R:$R,"",0)&"`")&IF(_xlfn.XLOOKUP(3,$AH:$AH,$R:$R,"",0)="","",",`"&_xlfn.XLOOKUP(3,$AH:$AH,$R:$R,"",0)&"`")&IF(_xlfn.XLOOKUP(4,$AH:$AH,$R:$R,"",0)="","",",`"&_xlfn.XLOOKUP(4,$AH:$AH,$R:$R,"",0)&"`")&IF(_xlfn.XLOOKUP(5,$AH:$AH,$R:$R,"",0)="","",",`"&_xlfn.XLOOKUP(5,$AH:$AH,$R:$R,"",0)&"`")&IF(_xlfn.XLOOKUP(6,$AH:$AH,$R:$R,"",0)="","",",`"&_xlfn.XLOOKUP(6,$AH:$AH,$R:$R,"",0)&"`")&IF(_xlfn.XLOOKUP(7,$AH:$AH,$R:$R,"",0)="","",",`"&_xlfn.XLOOKUP(7,$AH:$AH,$R:$R,"",0)&"`")&IF(_xlfn.XLOOKUP(8,$AH:$AH,$R:$R,"",0)="","",",`"&_xlfn.XLOOKUP(8,$AH:$AH,$R:$R,"",0)&"`")&")," -> , PRIMARY KEY (`CompanyCode`,`StoreCode`,`MDHierarchyCode`,`MDHierarchyLevel`,`ApplyDate`), | BR50: =" , PRIMARY KEY ("&IF(_xlfn.XLOOKUP(1,$AH:$AH,$R:$R,"",0)="","","`"&_xlfn.XLOOKUP(1,$AH:$AH,$R:$R,"",0)&"`")&IF(_xlfn.XLOOKUP(2,$AH:$AH,$R:$R,"",0)="","",",`"&_xlfn.XLOOKUP(2,$AH:$AH,$R:$R,"",0)&"`")&IF(_xlfn.XLOOKUP(3,$AH:$AH,$R:$R,"",0)="","",",`"&_xlfn.XLOOKUP(3,$AH:$AH,$R:$R,"",0)&"`")&IF(_xlfn.XLOOKUP(4,$AH:$AH,$R:$R,"",0)="","",",`"&_xlfn.XLOOKUP(4,$AH:$AH,$R:$R,"",0)&"`")&IF(_xlfn.XLOOKUP(5,$AH:$AH,$R:$R,"",0)="","",",`"&_xlfn.XLOOKUP(5,$AH:$AH,$R:$R,"",0)&"`")&IF(_xlfn.XLOOKUP(6,$AH:$AH,$R:$R,"",0)="","",",`"&_xlfn.XLOOKUP(6,$AH:$AH,$R:$R,"",0)&"`")&IF(_xlfn.XLOOKUP(7,$AH:$AH,$R:$R,"",0)="","",",`"&_xlfn.XLOOKUP(7,$AH:$AH,$R:$R,"",0)&"`")&IF(_xlfn.XLOOKUP(8,$AH:$AH,$R:$R,"",0)="","",",`"&_xlfn.XLOOKUP(8,$AH:$AH,$R:$R,"",0)&"`")&")" -> , PRIMARY KEY (`CompanyCode`,`StoreCode`,`MDHierarchyCode`,`MDHierarchyLevel`,`ApplyDate`) | BT50: ; | BV50: WHERE | BZ50: ="FROM `TMP`.`"&$G$10&"` A" -> FROM `TMP`.`MDHierarchyMaster` A
BP51: KEY `RECORD_ID` (`RECORD_ID`) | BR51: =") ENGINE=InnoDB DEFAULT CHARSET=utf8mb4 COLLATE=utf8mb4_0900_ai_ci COMMENT = '"&$G$9&"_TMP';" -> ) ENGINE=InnoDB DEFAULT CHARSET=utf8mb4 COLLATE=utf8mb4_0900_ai_ci COMMENT = '分類マスタ_TMP'; | BV51: =IF(_xlfn.XLOOKUP(1,$AH:$AH,$R:$R,"",0)="","","A.`"&_xlfn.XLOOKUP(1,$AH:$AH,$R:$R,"",0)&"` = B.`"&_xlfn.XLOOKUP(1,$AH:$AH,$R:$R,"",0)&"`") -> A.`CompanyCode` = B.`CompanyCode` | BZ51: WHERE NOT EXISTS ( SELECT RECORD_ID
B52: ■インデックス情報 | BP52: =") ENGINE=InnoDB DEFAULT CHARSET=utf8mb4 COLLATE=utf8mb4_0900_ai_ci COMMENT = '"&$G$9&"';" -> ) ENGINE=InnoDB DEFAULT CHARSET=utf8mb4 COLLATE=utf8mb4_0900_ai_ci COMMENT = '分類マスタ'; | BV52: =IF(_xlfn.XLOOKUP(2,$AH:$AH,$R:$R,"",0)="","","AND A.`"&_xlfn.XLOOKUP(2,$AH:$AH,$R:$R,"",0)&"` = B.`"&_xlfn.XLOOKUP(2,$AH:$AH,$R:$R,"",0)&"`") -> AND A.`StoreCode` = B.`StoreCode` | BZ52: ="FROM `POS_MASTER`.`"&$G$10&"` B" -> FROM `POS_MASTER`.`MDHierarchyMaster` B
B53: No. | D53: Index名 | R53: カラム一覧 | AL53: プライマリキー | AP53: ユニーク | AT53: 備考 | BV53: =IF(_xlfn.XLOOKUP(3,$AH:$AH,$R:$R,"",0)="","","AND A.`"&_xlfn.XLOOKUP(3,$AH:$AH,$R:$R,"",0)&"` = B.`"&_xlfn.XLOOKUP(3,$AH:$AH,$R:$R,"",0)&"`") -> AND A.`MDHierarchyCode` = B.`MDHierarchyCode` | BZ53: WHERE
B54: 1 | D54: PRIMARY | R54: =IF(_xlfn.XLOOKUP(1,AH:AH,R:R,"",0)="","","`"&_xlfn.XLOOKUP(1,AH:AH,R:R,"",0)&"`")&IF(_xlfn.XLOOKUP(2,AH:AH,R:R,"",0)="","",",`"&_xlfn.XLOOKUP(2,AH:AH,R:R,"",0)&"`")&IF(_xlfn.XLOOKUP(3,AH:AH,R:R,"",0)="","",",`"&_xlfn.XLOOKUP(3,AH:AH,R:R,"",0)&"`")&IF(_xlfn.XLOOKUP(4,AH:AH,R:R,"",0)="","",",`"&_xlfn.XLOOKUP(4,AH:AH,R:R,"",0)&"`")&IF(_xlfn.XLOOKUP(5,AH:AH,R:R,"",0)="","",",`"&_xlfn.XLOOKUP(5,AH:AH,R:R,"",0)&"`")&IF(_xlfn.XLOOKUP(6,AH:AH,R:R,"",0)="","",",`"&_xlfn.XLOOKUP(6,AH:AH,R:R,"",0)&"`")&IF(_xlfn.XLOOKUP(7,AH:AH,R:R,"",0)="","",",`"&_xlfn.XLOOKUP(7,AH:AH,R:R,"",0)&"`")&IF(_xlfn.XLOOKUP(8,AH:AH,R:R,"",0)="","",",`"&_xlfn.XLOOKUP(8,AH:AH,R:R,"",0)&"`") -> `CompanyCode`,`StoreCode`,`MDHierarchyCode`,`MDHierarchyLevel`,`ApplyDate` | AL54: Y | AP54: Y | BP54: ="CREATE TRIGGER `"&$G$10&"_CR_Date_Time` BEFORE INSERT ON `"&$G$10&"` FOR EACH ROW SET NEW.record_create_date = CURRENT_DATE, NEW.record_create_time = CURRENT_TIME, NEW.record_update_date = CURRENT_DATE, NEW.record_update_time = CURRENT_TIME;" -> CREATE TRIGGER `MDHierarchyMaster_CR_Date_Time` BEFORE INSERT ON `MDHierarchyMaster` FOR EACH ROW SET NEW.record_create_date = CURRENT_DATE, NEW.record_create_time = CURRENT_TIME, NEW.record_update_date = CURRENT_DATE, NEW.record_update_time = CURRENT_TIME; | BV54: =IF(_xlfn.XLOOKUP(4,$AH:$AH,$R:$R,"",0)="","","AND A.`"&_xlfn.XLOOKUP(4,$AH:$AH,$R:$R,"",0)&"` = B.`"&_xlfn.XLOOKUP(4,$AH:$AH,$R:$R,"",0)&"`") -> AND A.`MDHierarchyLevel` = B.`MDHierarchyLevel` | BZ54: =IF(_xlfn.XLOOKUP(1,$AH:$AH,$R:$R,"",0)="","","A.`"&_xlfn.XLOOKUP(1,$AH:$AH,$R:$R,"",0)&"` = B.`"&_xlfn.XLOOKUP(1,$AH:$AH,$R:$R,"",0)&"`") -> A.`CompanyCode` = B.`CompanyCode`
BP55: ="CREATE TRIGGER `"&$G$10&"_UP_Date_Time` BEFORE UPDATE ON `"&$G$10&"` FOR EACH ROW SET NEW.record_update_date = CURRENT_DATE, NEW.record_update_time = CURRENT_TIME;" -> CREATE TRIGGER `MDHierarchyMaster_UP_Date_Time` BEFORE UPDATE ON `MDHierarchyMaster` FOR EACH ROW SET NEW.record_update_date = CURRENT_DATE, NEW.record_update_time = CURRENT_TIME; | BV55: =IF(_xlfn.XLOOKUP(5,$AH:$AH,$R:$R,"",0)="","","AND A.`"&_xlfn.XLOOKUP(5,$AH:$AH,$R:$R,"",0)&"` = B.`"&_xlfn.XLOOKUP(5,$AH:$AH,$R:$R,"",0)&"`") -> AND A.`ApplyDate` = B.`ApplyDate` | BZ55: =IF(_xlfn.XLOOKUP(2,$AH:$AH,$R:$R,"",0)="","","AND A.`"&_xlfn.XLOOKUP(2,$AH:$AH,$R:$R,"",0)&"` = B.`"&_xlfn.XLOOKUP(2,$AH:$AH,$R:$R,"",0)&"`") -> AND A.`StoreCode` = B.`StoreCode`
BV56: =IF(_xlfn.XLOOKUP(6,$AH:$AH,$R:$R,"",0)="","","AND A.`"&_xlfn.XLOOKUP(6,$AH:$AH,$R:$R,"",0)&"` = B.`"&_xlfn.XLOOKUP(6,$AH:$AH,$R:$R,"",0)&"`") | BZ56: =IF(_xlfn.XLOOKUP(3,$AH:$AH,$R:$R,"",0)="","","AND A.`"&_xlfn.XLOOKUP(3,$AH:$AH,$R:$R,"",0)&"` = B.`"&_xlfn.XLOOKUP(3,$AH:$AH,$R:$R,"",0)&"`") -> AND A.`MDHierarchyCode` = B.`MDHierarchyCode`
B57: トリガー情報 | BV57: =IF(_xlfn.XLOOKUP(7,$AH:$AH,$R:$R,"",0)="","","AND A.`"&_xlfn.XLOOKUP(7,$AH:$AH,$R:$R,"",0)&"` = B.`"&_xlfn.XLOOKUP(7,$AH:$AH,$R:$R,"",0)&"`") | BZ57: =IF(_xlfn.XLOOKUP(4,$AH:$AH,$R:$R,"",0)="","","AND A.`"&_xlfn.XLOOKUP(4,$AH:$AH,$R:$R,"",0)&"` = B.`"&_xlfn.XLOOKUP(4,$AH:$AH,$R:$R,"",0)&"`") -> AND A.`MDHierarchyLevel` = B.`MDHierarchyLevel`
B58: No. | D58: トリガー名 | R58: イベント | U58: タイミング | Y58: 条件 | BV58: =IF(_xlfn.XLOOKUP(8,$AH:$AH,$R:$R,"",0)="","","AND A.`"&_xlfn.XLOOKUP(8,$AH:$AH,$R:$R,"",0)&"` = B.`"&_xlfn.XLOOKUP(8,$AH:$AH,$R:$R,"",0)&"`") | BZ58: =IF(_xlfn.XLOOKUP(5,$AH:$AH,$R:$R,"",0)="","","AND A.`"&_xlfn.XLOOKUP(5,$AH:$AH,$R:$R,"",0)&"` = B.`"&_xlfn.XLOOKUP(5,$AH:$AH,$R:$R,"",0)&"`") -> AND A.`ApplyDate` = B.`ApplyDate`
B59: 1 | D59: =G10&"_"&R59&"_"&"trg" -> MDHierarchyMaster_update_trg | R59: update | U59: Before row | Y59: auto_updated_date | BV59: ; | BZ59: =IF(_xlfn.XLOOKUP(6,$AH:$AH,$R:$R,"",0)="","","AND A.`"&_xlfn.XLOOKUP(6,$AH:$AH,$R:$R,"",0)&"` = B.`"&_xlfn.XLOOKUP(6,$AH:$AH,$R:$R,"",0)&"`")
BZ60: =IF(_xlfn.XLOOKUP(7,$AH:$AH,$R:$R,"",0)="","","AND A.`"&_xlfn.XLOOKUP(7,$AH:$AH,$R:$R,"",0)&"` = B.`"&_xlfn.XLOOKUP(7,$AH:$AH,$R:$R,"",0)&"`")
BZ61: =IF(_xlfn.XLOOKUP(8,$AH:$AH,$R:$R,"",0)="","","AND A.`"&_xlfn.XLOOKUP(8,$AH:$AH,$R:$R,"",0)&"` = B.`"&_xlfn.XLOOKUP(8,$AH:$AH,$R:$R,"",0)&"`")
BZ62: );
BZ65: ="DROP TABLE IF EXISTS `TMP`.`"&$G$10&"`;" -> DROP TABLE IF EXISTS `TMP`.`MDHierarchyMaster`;
BZ66: COMMIT;

Sheet 分類拡張マスタ
A1: システム名 | K1: システム種別 | W1: =IF(表紙!W1="","",表紙!W1) -> DB定義書 | AP1: 作成者 | AT1: 作成日 | AY1: 更新者 | BC1: 更新日 | BH1: 版数
A2: =IF(表紙!A2="","",表紙!A2) -> 現金専用簡易セルフPOS | K2: =IF(表紙!K2="","",表紙!K2) | AP2: =IF(表紙!AP2="","",表紙!AP2) -> きよはら | AT2: =IF(表紙!AT2="","",表紙!AT2) -> 44652 | AY2: =IF(表紙!AY2="","",表紙!AY2) -> Thanh Nguyên | BC2: =IF(表紙!BC2="","",表紙!BC2) -> 45285 | BH2: =IF(表紙!BH2="","",表紙!BH2) -> 0.2
A4: 機能カテゴリ | H4: =IF(表紙!H4="","",表紙!H4) -> 共通 | U4: 項目 | Z4: =IF(表紙!Z4="","",表紙!Z4) | AP4: 商品拡張マスタ
B7: ■テーブル情報
B8: スキーマ名 | G8: POS_MASTER | Y8: RDBMS名
B9: 論理名 | G9: 分類拡張マスタ | Y9: バージョン
B10: 物理名 | G10: MDHierarchyExMvkMaster
B11: 備考
B19: ■カラム情報 | BP19: ="DROP TABLE IF EXISTS `"&$G$8&"`.`"&$G$10&"`;" -> DROP TABLE IF EXISTS `POS_MASTER`.`MDHierarchyExMvkMaster`;
B20: No. | D20: 論理名 | R20: 物理名 | AC20: データ型 | AH20: PK | AJ20: Not Null | AM20: デフォルト | AT20: 備考 | BP20: ="CREATE TABLE `"&$G$8&"`.`"&$G$10&"` (" -> CREATE TABLE `POS_MASTER`.`MDHierarchyExMvkMaster` (
B21: 1 | D21: レコードID | R21: RECORD_ID | AC21: bigint | AJ21: Y | AM21: 自動追加 | BP21: `RECORD_ID` bigint NOT NULL AUTO_INCREMENT COMMENT 'レコードID'
B22: =B21+1 -> 2 | D22: レコード作成日付 | R22: RECORD_CREATE_DATE | AC22: date | AJ22: Y | AM22: CURRENT_DATE | BP22: ,`RECORD_CREATE_DATE` date NOT NULL COMMENT 'レコード作成日付'
B23: =B22+1 -> 3 | D23: レコード作成時間 | R23: RECORD_CREATE_TIME | AC23: time | AJ23: Y | AM23: CURRENT_TIME | BP23: ,`RECORD_CREATE_TIME` time NOT NULL COMMENT 'レコード作成時間'
B24: =B23+1 -> 4 | D24: レコード更新日付 | R24: RECORD_UPDATE_DATE | AC24: date | AJ24: Y | AM24: CURRENT_DATE | AT24: トリガーにより更新 | BP24: ,`RECORD_UPDATE_DATE` date NOT NULL COMMENT 'レコード更新日付/トリガーにより更新' | BT24: ="LOAD DATA INFILE 'C:/04_DATAFILE/"&$G$10&"/TMP/"&$G$10&".CSV' " -> LOAD DATA INFILE 'C:/04_DATAFILE/MDHierarchyExMvkMaster/TMP/MDHierarchyExMvkMaster.CSV' | BV24: ="UPDATE `POS_MASTER`.`"&$G$10&"` A,`TMP`.`"&$G$10&"` B" -> UPDATE `POS_MASTER`.`MDHierarchyExMvkMaster` A,`TMP`.`MDHierarchyExMvkMaster` B
B25: =B24+1 -> 5 | D25: レコード更新時間 | R25: RECORD_UPDATE_TIME | AC25: time | AJ25: Y | AM25: CURRENT_TIME | AT25: トリガーにより更新 | BP25: ,`RECORD_UPDATE_TIME` time NOT NULL COMMENT 'レコード更新時間/トリガーにより更新' | BR25: ="DROP TABLE IF EXISTS `TMP`.`"&$G$10&"`;" -> DROP TABLE IF EXISTS `TMP`.`MDHierarchyExMvkMaster`; | BT25: ="REPLACE INTO TABLE TMP.`"&$G$10&"` CHARACTER SET 'UTF8'" -> REPLACE INTO TABLE TMP.`MDHierarchyExMvkMaster` CHARACTER SET 'UTF8' | BV25: SET
A26: @1 | B26: =B25+1 -> 6 | D26: レコード無効フラグ | R26: RECORD_VOID_FLAG | AC26: char(1) | AJ26: Y | AM26: "" | AT26: 0: 有効フラグ、 1:無効フラグ | BM26: nvarchar | BN26: 1 | BP26: ,`RECORD_VOID_FLAG` char(1) NOT NULL DEFAULT '' COMMENT 'レコード無効フラグ '''': 有効フラグ、 1:無効フラグ' | BR26: ="CREATE TABLE `TMP`.`"&G10&"` (" -> CREATE TABLE `TMP`.`MDHierarchyExMvkMaster` ( | BT26: =SUBSTITUTE(SUBSTITUTE("("&A26&","&A27&","&A28&","&A29&","&A30&","&A31&","&A32&","&A33&","&A34&","&A35&","&A36&","&A37&","&A38&","&A39&","&A40&","&A41&","&A42&","&A43&","&A44&","&A45&","&A46&","&A47&","&A48&","&A49&","&A50&","&A51&","&A52&","&A53&","&A54&","&A55&","&A56&","&A57&","&A58&","&A59&","&A60&","&A61&","&A62&")",",,",""),",)",")") -> (@1,@2,@3,@4,@5,@6,@7,@8,@9) | BX26: ="INSERT INTO `POS_MASTER`.`"&$G$10&"` (" -> INSERT INTO `POS_MASTER`.`MDHierarchyExMvkMaster` ( | BZ26: ) SELECT
A27: @2 | B27: =B26+1 -> 7 | D27: 企業コード | R27: CompanyCode | AC27: {=_xlfn.SWITCH(BM27,"nvarchar","varchar("&BN27&")","smallint","smallint","date","date","money","decimal(19,4)","numeric","numeric("&BN27&")","int","int","bit","char(1)","datetime2","datetime","time","time")} -> varchar(10) | AH27: 1 | AJ27: Y | AT27: 会社コード | BM27: nvarchar | BN27: 10 | BP27: =",`"&R27&"` "&AC27&" "&IF(AJ27="Y","NOT NULL","")&" COMMENT '"&D27&"'" -> ,`CompanyCode` varchar(10) NOT NULL COMMENT '企業コード' | BR27: ="`"&R27&"` "&AC27&" "&IF(AJ27="Y","NOT NULL","") -> `CompanyCode` varchar(10) NOT NULL | BT27: ="SET `"&R27&"` = "&IF(LEFT(AC27,4)="date", "if(@"&B27-5&" > '0000-00-00 00:00:00', @"&B27-5&", null)","if(nullif( @"&B27-5&",'') > '', @"&B27-5&", null )") -> SET `CompanyCode` = if(nullif( @2,'') > '', @2, null ) | BV27: ="A.`"&R27&"` = B.`"&R27&"`" -> A.`CompanyCode` = B.`CompanyCode` | BX27: ="`"&R27&"`" -> `CompanyCode` | BZ27: ="`"&R27&"`" -> `CompanyCode`
A28: @3 | B28: =B27+1 -> 8 | D28: 店舗コード | R28: StoreCode | AC28: {=_xlfn.SWITCH(BM28,"nvarchar","varchar("&BN28&")","smallint","smallint","date","date","money","decimal(19,4)","numeric","numeric("&BN28&")","int","int","bit","char(1)","datetime2","datetime","time","time")} -> varchar(10) | AH28: 2 | AJ28: Y | AT28: 店舗コード | BM28: nvarchar | BN28: 10 | BP28: =",`"&R28&"` "&AC28&" "&IF(AJ28="Y","NOT NULL","")&" COMMENT '"&D28&"'" -> ,`StoreCode` varchar(10) NOT NULL COMMENT '店舗コード' | BR28: =",`"&R28&"` "&AC28&" "&IF(AJ28="Y","NOT NULL","") -> ,`StoreCode` varchar(10) NOT NULL | BT28: =",`"&R28&"` = "&IF(LEFT(AC28,4)="date", "if(@"&B28-5&" > '0000-00-00 00:00:00', if(@"&B28-5&" > '2999-12-31 23:59:59', '2999-12-31 23:59:59', @"&B28-5&"), null)","if(nullif( @"&B28-5&",'') > '', @"&B28-5&", null )") -> ,`StoreCode` = if(nullif( @3,'') > '', @3, null ) | BV28: =",A.`"&R28&"` = B.`"&R28&"`" -> ,A.`StoreCode` = B.`StoreCode` | BX28: =",`"&R28&"`" -> ,`StoreCode` | BZ28: =",`"&R28&"`" -> ,`StoreCode`
A29: @4 | B29: =B28+1 -> 9 | D29: MD階層コード | R29: MDHierarchyCode | AC29: {=_xlfn.SWITCH(BM29,"nvarchar","varchar("&BN29&")","smallint","smallint","date","date","money","decimal(19,4)","numeric","numeric("&BN29&")","int","int","bit","char(1)","datetime2","datetime","time","time")} -> varchar(10) | AH29: 3 | AJ29: Y | BM29: nvarchar | BN29: 10 | BP29: =",`"&R29&"` "&AC29&" "&IF(AJ29="Y","NOT NULL","")&" COMMENT '"&D29&"'" -> ,`MDHierarchyCode` varchar(10) NOT NULL COMMENT 'MD階層コード' | BR29: =",`"&R29&"` "&AC29&" "&IF(AJ29="Y","NOT NULL","") -> ,`MDHierarchyCode` varchar(10) NOT NULL | BT29: =",`"&R29&"` = "&IF(LEFT(AC29,4)="date", "if(@"&B29-5&" > '0000-00-00 00:00:00', if(@"&B29-5&" > '2999-12-31 23:59:59', '2999-12-31 23:59:59', @"&B29-5&"), null)","if(nullif( @"&B29-5&",'') > '', @"&B29-5&", null )") -> ,`MDHierarchyCode` = if(nullif( @4,'') > '', @4, null ) | BV29: =",A.`"&R29&"` = B.`"&R29&"`" -> ,A.`MDHierarchyCode` = B.`MDHierarchyCode` | BX29: =",`"&R29&"`" -> ,`MDHierarchyCode` | BZ29: =",`"&R29&"`" -> ,`MDHierarchyCode`
