Workbook

Sheet 表紙
A1: システム名 | K1: システム種別 | W1: DB定義書 | AP1: 作成者 | AT1: 作成日 | AY1: 更新者 | BC1: 更新日 | BH1: 版数
A2: 現金専用簡易セルフPOS | AP2: きよはら | AT2: 44652 | AY2: =LOOKUP(2,1/(改廃履歴!H11:H30000<>""),改廃履歴!H11:H30000) -> Thanh Nguyên | BC2: =LOOKUP(2,1/(改廃履歴!B11:B30000<>""),改廃履歴!B11:B30000) -> 45285 | BH2: =LOOKUP(2,1/(改廃履歴!O11:O30000<>""),改廃履歴!O11:O30000) -> 0.2
A4: 機能カテゴリ | H4: 共通 | U4: 項目 | AP4: 表紙
L16: 現金専用簡易セルフPOS 基本設計書
L24: =K2&"/"&H4&"/"&Z4 -> /共通/
Q44: 承認日 | AA44: 承認者 | AQ44: 版数

Sheet 改廃履歴
A1: システム名 | K1: システム種別 | W1: =IF(表紙!W1="","",表紙!W1) -> DB定義書 | AP1: 作成者 | AT1: 作成日 | AY1: 更新者 | BC1: 更新日 | BH1: 版数
A2: =IF(表紙!A2="","",表紙!A2) -> 現金専用簡易セルフPOS | K2: =IF(表紙!K2="","",表紙!K2) | AP2: =IF(表紙!AP2="","",表紙!AP2) -> きよはら | AT2: =IF(表紙!AT2="","",表紙!AT2) -> 44652 | AY2: =IF(表紙!AY2="","",表紙!AY2) -> Thanh Nguyên | BC2: =IF(表紙!BC2="","",表紙!BC2) -> 45285 | BH2: =IF(表紙!BH2="","",表紙!BH2) -> 0.2
A4: 機能カテゴリ | H4: =IF(表紙!H4="","",表紙!H4) -> 共通 | U4: 項目 | Z4: =IF(表紙!Z4="","",表紙!Z4) | AP4: 改廃履歴
B8: ■改廃履歴
B10: 更新日付 | H10: 更新者 | O10: 版数 | S10: 変更内容 | AX10: 承認日付 | BD10: 承認者
B11: 44652 | H11: きよはら | O11: 0.1 | S11: 新規作成
B13: 45285 | H13: Thanh Nguyên | O13: 0.2 | S13: プリセットメニューマスタに、プリセットボタンレイアウト名称を追加

Sheet DB一覧
A1: システム名 | K1: システム種別 | W1: =IF(表紙!W1="","",表紙!W1) -> DB定義書 | AP1: 作成者 | AT1: 作成日 | AY1: 更新者 | BC1: 更新日 | BH1: 版数
A2: =IF(表紙!A2="","",表紙!A2) -> 現金専用簡易セルフPOS | K2: =IF(表紙!K2="","",表紙!K2) | AP2: =IF(表紙!AP2="","",表紙!AP2) -> きよはら | AT2: =IF(表紙!AT2="","",表紙!AT2) -> 44652 | AY2: =IF(表紙!AY2="","",表紙!AY2) -> Thanh Nguyên | BC2: =IF(表紙!BC2="","",表紙!BC2) -> 45285 | BH2: =IF(表紙!BH2="","",表紙!BH2) -> 0.2
A4: 機能カテゴリ | H4: =IF(表紙!H4="","",表紙!H4) -> 共通 | U4: 項目 | Z4: =IF(表紙!Z4="","",表紙!Z4) | AP4: Sheet7
B7: ID | D7: 区分 | M7: 論理テーブル名 | AB7: 物理テーブル名 | AW7: 備考
D8: マスタ連携 | M8: PLUメンテ | AB8: GHPLUM.CSV
D9: マスタ連携 | M9: 特売マスタ | AB9: GHDISCOUNTM.CSV
D10: マスタ連携 | M10: MMマスタ | AB10: GHBUNDLEM.CSV
D11: マスタ連携 | M11: 企画マスタ | AB11: GHEVENTM.CSV
AB12: GHPLUPOINT.CSV
D13: マスタ連携 | M13: P001(POP商品情報送付データ) | AB13: Ｐ001_yyyymmdd.csv
D14: マスタ連携 | M14: Ｐ003(POP棚番情報送付データ) | AB14: Ｐ003_yyyymmdd.csv

Sheet テスト
A1: システム名 | K1: システム種別 | W1: =IF(表紙!W1="","",表紙!W1) -> DB定義書 | AP1: 作成者 | AT1: 作成日 | AY1: 更新者 | BC1: 更新日 | BH1: 版数
A2: =IF(表紙!A2="","",表紙!A2) -> 現金専用簡易セルフPOS | K2: =IF(表紙!K2="","",表紙!K2) | AP2: =IF(表紙!AP2="","",表紙!AP2) -> きよはら | AT2: =IF(表紙!AT2="","",表紙!AT2) -> 44652 | AY2: =IF(表紙!AY2="","",表紙!AY2) -> Thanh Nguyên | BC2: =IF(表紙!BC2="","",表紙!BC2) -> 45285 | BH2: =IF(表紙!BH2="","",表紙!BH2) -> 0.2
A4: 機能カテゴリ | H4: =IF(表紙!H4="","",表紙!H4) -> 共通 | U4: 項目 | Z4: =IF(表紙!Z4="","",表紙!Z4) | AP4: Sheet7
B7: ID | D7: 論理テーブル名 | M7: テストデータ | Y7: CSV | AC7: レプリカ | AG7: レプリカ
Y8: ﾚｺｰﾄﾞ数 | AC8: ｲﾝﾎﾟｰﾄ数 | AG8: 所要時間
B9: 01 | D9: PLUメンテ | M9: 20240110223036GHPLUM.CSV | Y9: 87383 | AC9: 87383 | AG9: 0.00076388889
B10: 02 | D10: 特売マスタ | M10: 20240110223046GHDISCOUNTM.CSV | Y10: 36176 | AC10: 36176 | AG10: 0.00017361111
B11: 03 | D11: MMマスタ | M11: 20240110223101GHBUNDLEM.CSV | Y11: 17201 | AC11: 17201 | AG11: 0.00015046296
B12: 04 | D12: 企画マスタ | M12: 20240108223019GHEVENTM.CSV | Y12: 469 | AC12: 469 | AG12: 2.3148148e-05
D13: ????????? | M13: 20240110200005GHPLUPOINT.CSV | Y13: 0 | AC13: 0
D14: 階層マスタ
B15: 06 | D15: P001(POP商品情報送付データ) | M15: Ｐ001_yyyymmdd.csv | Y15: 201250 | AC15: 200810 | AG15: 0.0035416667
D16: P001(ヘッダー) | Y16: - | AC16: 220
D17: P001(エンドレコード) | Y17: - | AC17: 220
B18: 07 | D18: P003(POP棚番情報送付データ) | M18: Ｐ003_yyyymmdd.csv | Y18: 2770268 | AC18: 2717635 | AG18: 0.014074074
AF19: 合計 | AG19: =SUM(AG9:AJ18) -> 0.018726852

Sheet ER
A1: システム名 | K1: システム種別 | W1: =IF(表紙!W1="","",表紙!W1) -> DB定義書 | AP1: 作成者 | AT1: 作成日 | AY1: 更新者 | BC1: 更新日 | BH1: 版数
A2: =IF(表紙!A2="","",表紙!A2) -> 現金専用簡易セルフPOS | K2: =IF(表紙!K2="","",表紙!K2) | AP2: =IF(表紙!AP2="","",表紙!AP2) -> きよはら | AT2: =IF(表紙!AT2="","",表紙!AT2) -> 44652 | AY2: =IF(表紙!AY2="","",表紙!AY2) -> Thanh Nguyên | BC2: =IF(表紙!BC2="","",表紙!BC2) -> 45285 | BH2: =IF(表紙!BH2="","",表紙!BH2) -> 0.2
A4: 機能カテゴリ | H4: =IF(表紙!H4="","",表紙!H4) -> 共通 | U4: 項目 | Z4: =IF(表紙!Z4="","",表紙!Z4) | AP4: ER

Sheet PLUメンテ
A1: システム名 | K1: システム種別 | W1: =IF(表紙!W1="","",表紙!W1) -> DB定義書 | AP1: 作成者 | AT1: 作成日 | AY1: 更新者 | BC1: 更新日 | BH1: 版数
A2: =IF(表紙!A2="","",表紙!A2) -> 現金専用簡易セルフPOS | K2: =IF(表紙!K2="","",表紙!K2) | AP2: =IF(表紙!AP2="","",表紙!AP2) -> きよはら | AT2: =IF(表紙!AT2="","",表紙!AT2) -> 44652 | AY2: =IF(表紙!AY2="","",表紙!AY2) -> Thanh Nguyên | BC2: =IF(表紙!BC2="","",表紙!BC2) -> 45285 | BH2: =IF(表紙!BH2="","",表紙!BH2) -> 0.2
A4: 機能カテゴリ | H4: =IF(表紙!H4="","",表紙!H4) -> 共通 | U4: 項目 | Z4: =IF(表紙!Z4="","",表紙!Z4) | AP4: テンプレート
B7: ■テーブル情報
B8: スキーマ名 | G8: Replica_Kasumi | Y8: RDBMS名
B9: 論理名 | G9: ＰＬＵメンテ | Y9: バージョン
B10: 物理名 | G10: GHPLUM
B11: 備考
B19: ■カラム情報 | BP19: ="DROP TABLE IF EXISTS `"&$G$8&"`.`"&$G$10&"`;" -> DROP TABLE IF EXISTS `Replica_Kasumi`.`GHPLUM`;
B20: No. | D20: 論理名 | R20: 物理名 | AC20: データ型 | AH20: PK | AJ20: Not Null | AM20: デフォルト | AT20: 備考 | BP20: ="CREATE TABLE `"&$G$8&"`.`"&$G$10&"` (" -> CREATE TABLE `Replica_Kasumi`.`GHPLUM` (
B21: 1 | D21: レコードID | R21: RECORD_ID | AC21: bigint | AJ21: Y | AM21: 自動追加 | BL21: =REPT("a"&CHAR(10)&"b",INT(LENB(SUBSTITUTE(AT21,CHAR(10),""))/70)+1) -> a b | BP21: `RECORD_ID` bigint NOT NULL AUTO_INCREMENT COMMENT 'レコードID'
B22: =B21+1 -> 2 | D22: レコード作成日付 | R22: RECORD_CREATE_DATE | AC22: date | AJ22: Y | AM22: CURRENT_DATE | BL22: =REPT("a"&CHAR(10)&"b",INT(LENB(SUBSTITUTE(AT22,CHAR(10),""))/70)+1) -> a b | BP22: ,`RECORD_CREATE_DATE` date NOT NULL COMMENT 'レコード作成日付'
B23: =B22+1 -> 3 | D23: レコード作成時間 | R23: RECORD_CREATE_TIME | AC23: time | AJ23: Y | AM23: CURRENT_TIME | BL23: =REPT("a"&CHAR(10)&"b",INT(LENB(SUBSTITUTE(AT23,CHAR(10),""))/70)+1) -> a b | BP23: ,`RECORD_CREATE_TIME` time NOT NULL COMMENT 'レコード作成時間' | BV23: SET CHARACTER_SET_DATABASE = UTF8;
B24: =B23+1 -> 4 | D24: レコード更新日付 | R24: RECORD_UPDATE_DATE | AC24: date | AJ24: Y | AM24: CURRENT_DATE | AT24: トリガーにより更新 | BL24: =REPT("a"&CHAR(10)&"b",INT(LENB(SUBSTITUTE(AT24,CHAR(10),""))/70)+1) -> a b | BP24: ,`RECORD_UPDATE_DATE` date NOT NULL COMMENT 'レコード更新日付/トリガーにより更新' | BV24: ="UPDATE `REPLICA_KASUMI`.`"&$G$10&"` A,`TMP`.`"&$G$10&"` B" -> UPDATE `REPLICA_KASUMI`.`GHPLUM` A,`TMP`.`GHPLUM` B
B25: =B24+1 -> 5 | D25: レコード更新時間 | R25: RECORD_UPDATE_TIME | AC25: time | AJ25: Y | AM25: CURRENT_TIME | AT25: トリガーにより更新 | BL25: =REPT("a"&CHAR(10)&"b",INT(LENB(SUBSTITUTE(AT25,CHAR(10),""))/70)+1) -> a b | BP25: ,`RECORD_UPDATE_TIME` time NOT NULL COMMENT 'レコード更新時間/トリガーにより更新' | BR25: ="DROP TABLE IF EXISTS `TMP`.`"&$G$10&"`;" -> DROP TABLE IF EXISTS `TMP`.`GHPLUM`; | BT25: ="LOAD DATA INFILE 'C:/04_DATAFILE/"&$G$10&"/TMP/"&$G$10&".CSV' " -> LOAD DATA INFILE 'C:/04_DATAFILE/GHPLUM/TMP/GHPLUM.CSV' | BV25: SET
A26: @1 | B26: =B25+1 -> 6 | D26: レコード無効フラグ | R26: RECORD_VOID_FLAG | AC26: char(1) | AJ26: Y | AM26: "" | AT26: 0: 有効フラグ、 1:無効フラグ | BL26: =REPT("a"&CHAR(10)&"b",INT(LENB(SUBSTITUTE(AT26,CHAR(10),""))/70)+1) -> a b | BP26: ,`RECORD_VOID_FLAG` char(1) NOT NULL DEFAULT '' COMMENT 'レコード無効フラグ '''': 有効フラグ、 1:無効フラグ' | BR26: ="CREATE TABLE `TMP`.`"&G10&"` (" -> CREATE TABLE `TMP`.`GHPLUM` ( | BT26: ="REPLACE INTO TABLE TMP.`"&$G$10&"` FIELDS TERMINATED BY ',' ENCLOSED BY '\""' LINES TERMINATED BY '\r\n' (" -> REPLACE INTO TABLE TMP.`GHPLUM` FIELDS TERMINATED BY ',' ENCLOSED BY '\"' LINES TERMINATED BY '\r\n' ( | BX26: ="INSERT INTO `REPLICA_KASUMI`.`"&$G$10&"` (" -> INSERT INTO `REPLICA_KASUMI`.`GHPLUM` ( | BZ26: ) SELECT
A27: @2 | B27: 7 | D27: 処理区分 | R27: PRCS_TYP | AC27: {=_xlfn.SWITCH(BM27,"String","varchar("&BN27&")","Long","int","Integer","smallint","Double","decimal(9,2)","Currency","int")} -> varchar(1) | AT27: Ａ：登録 Ｕ：更新 Ｄ：削除 | BL27: =REPT("a"&CHAR(10)&"b",INT(LENB(SUBSTITUTE(AT27,CHAR(10),""))/70)+1) -> a b | BM27: String | BN27: 1 | BP27: =",`"&R27&"` "&AC27&" "&IF(AJ27="Y","NOT NULL","")&" COMMENT '"&D27&"'" -> ,`PRCS_TYP` varchar(1) COMMENT '処理区分' | BR27: ="`"&R27&"` "&AC27&" "&IF(AJ27="Y","NOT NULL","") -> `PRCS_TYP` varchar(1) | BT27: ="`"&R27&"`" -> `PRCS_TYP` | BV27: ="A.`"&R27&"` = B.`"&R27&"`" -> A.`PRCS_TYP` = B.`PRCS_TYP` | BX27: ="`"&R27&"`" -> `PRCS_TYP` | BZ27: ="`"&R27&"`" -> `PRCS_TYP`
A28: @3 | B28: 8 | D28: 商品コード | R28: PLUID | AC28: {=_xlfn.SWITCH(BM28,"String","varchar("&BN28&")","Long","int","Integer","smallint","Double","decimal(9,2)","Currency","int")} -> varchar(24) | AH28: 1 | AT28: 左づめ 数字で最大19桁（5桁分はシステムで使用する） 特にＰＬＵコードを使用しない場合はｽｷｬﾝｺｰﾄﾞと同じ値を入れておくこと | BL28: =REPT("a"&CHAR(10)&"b",INT(LENB(SUBSTITUTE(AT28,CHAR(10),""))/70)+1) -> a ba b | BM28: String | BN28: 24 | BP28: =",`"&R28&"` "&AC28&" "&IF(AJ28="Y","NOT NULL","")&" COMMENT '"&D28&"'" -> ,`PLUID` varchar(24) COMMENT '商品コード' | BR28: =",`"&R28&"` "&AC28&" "&IF(AJ28="Y","NOT NULL","") -> ,`PLUID` varchar(24) | BT28: =",`"&R28&"`" -> ,`PLUID` | BV28: =",A.`"&R28&"` = B.`"&R28&"`" -> ,A.`PLUID` = B.`PLUID` | BX28: =",`"&R28&"`" -> ,`PLUID` | BZ28: =",`"&R28&"`" -> ,`PLUID`
A29: @4 | B29: 9 | D29: 店舗コード | R29: STR_ID | AC29: {=_xlfn.SWITCH(BM29,"String","varchar("&BN29&")","Long","int","Integer","smallint","Double","decimal(9,2)","Currency","int")} -> int | AH29: 2 | AT29: ０は不可 | BL29: =REPT("a"&CHAR(10)&"b",INT(LENB(SUBSTITUTE(AT29,CHAR(10),""))/70)+1) -> a b | BM29: Long | BP29: =",`"&R29&"` "&AC29&" "&IF(AJ29="Y","NOT NULL","")&" COMMENT '"&D29&"'" -> ,`STR_ID` int COMMENT '店舗コード' | BR29: =",`"&R29&"` "&AC29&" "&IF(AJ29="Y","NOT NULL","") -> ,`STR_ID` int | BT29: =",`"&R29&"`" -> ,`STR_ID` | BV29: =",A.`"&R29&"` = B.`"&R29&"`" -> ,A.`STR_ID` = B.`STR_ID` | BX29: =",`"&R29&"`" -> ,`STR_ID` | BZ29: =",`"&R29&"`" -> ,`STR_ID`
A30: @5 | B30: 9 | D30: 税種別コード | R30: TAXBLTY_CD | AC30: {=_xlfn.SWITCH(BM30,"String","varchar("&BN30&")","Long","int","Integer","smallint","Double","decimal(9,2)","Currency","int")} -> smallint | AT30: 例 １：外税 ２：内税 ３：非課税 （ＧＳの税設定で指定したものと同じものを入れる） | BL30: =REPT("a"&CHAR(10)&"b",INT(LENB(SUBSTITUTE(AT30,CHAR(10),""))/70)+1) -> a ba b | BM30: Integer | BP30: =",`"&R30&"` "&AC30&" "&IF(AJ30="Y","NOT NULL","")&" COMMENT '"&D30&"'" -> ,`TAXBLTY_CD` smallint COMMENT '税種別コード' | BR30: =",`"&R30&"` "&AC30&" "&IF(AJ30="Y","NOT NULL","") -> ,`TAXBLTY_CD` smallint | BT30: =",`"&R30&"`" -> ,`TAXBLTY_CD` | BV30: =",A.`"&R30&"` = B.`"&R30&"`" -> ,A.`TAXBLTY_CD` = B.`TAXBLTY_CD` | BX30: =",`"&R30&"`" -> ,`TAXBLTY_CD` | BZ30: =",`"&R30&"`" -> ,`TAXBLTY_CD`
A31: @6 | B31: 9 | D31: 単品名称 | R31: DSPL_DESCR | AC31: {=_xlfn.SWITCH(BM31,"String","varchar("&BN31&")","Long","int","Integer","smallint","Double","decimal(9,2)","Currency","int")} -> varchar(20) | AT31: 日本語２０文字以内 | BL31: =REPT("a"&CHAR(10)&"b",INT(LENB(SUBSTITUTE(AT31,CHAR(10),""))/70)+1) -> a b | BM31: String | BN31: 20 | BP31: =",`"&R31&"` "&AC31&" "&IF(AJ31="Y","NOT NULL","")&" COMMENT '"&D31&"'" -> ,`DSPL_DESCR` varchar(20) COMMENT '単品名称' | BR31: =",`"&R31&"` "&AC31&" "&IF(AJ31="Y","NOT NULL","") -> ,`DSPL_DESCR` varchar(20) | BT31: =",`"&R31&"`" -> ,`DSPL_DESCR` | BV31: =",A.`"&R31&"` = B.`"&R31&"`" -> ,A.`DSPL_DESCR` = B.`DSPL_DESCR` | BX31: =",`"&R31&"`" -> ,`DSPL_DESCR` | BZ31: =",`"&R31&"`" -> ,`DSPL_DESCR`
A32: @7 | B32: 9 | D32: レシート記述名 | R32: DCPT_DESCR | AC32: {=_xlfn.SWITCH(BM32,"String","varchar("&BN32&")","Long","int","Integer","smallint","Double","decimal(9,2)","Currency","int")} -> varchar(10) | AT32: レシートに印字される名称 日本語１0文字以内 | BL32: =REPT("a"&CHAR(10)&"b",INT(LENB(SUBSTITUTE(AT32,CHAR(10),""))/70)+1) -> a b | BM32: String | BN32: 10 | BP32: =",`"&R32&"` "&AC32&" "&IF(AJ32="Y","NOT NULL","")&" COMMENT '"&D32&"'" -> ,`DCPT_DESCR` varchar(10) COMMENT 'レシート記述名' | BR32: =",`"&R32&"` "&AC32&" "&IF(AJ32="Y","NOT NULL","") -> ,`DCPT_DESCR` varchar(10) | BT32: =",`"&R32&"`" -> ,`DCPT_DESCR` | BV32: =",A.`"&R32&"` = B.`"&R32&"`" -> ,A.`DCPT_DESCR` = B.`DCPT_DESCR` | BX32: =",`"&R32&"`" -> ,`DCPT_DESCR` | BZ32: =",`"&R32&"`" -> ,`DCPT_DESCR`
A33: @8 | B33: 9 | D33: 店舗階層コード | R33: STR_HIER_ID | AC33: {=_xlfn.SWITCH(BM33,"String","varchar("&BN33&")","Long","int","Integer","smallint","Double","decimal(9,2)","Currency","int")} -> int | AT33: 現在未使用 ０固定 | BL33: =REPT("a"&CHAR(10)&"b",INT(LENB(SUBSTITUTE(AT33,CHAR(10),""))/70)+1) -> a b | BM33: Long | BP33: =",`"&R33&"` "&AC33&" "&IF(AJ33="Y","NOT NULL","")&" COMMENT '"&D33&"'" -> ,`STR_HIER_ID` int COMMENT '店舗階層コード' | BR33: =",`"&R33&"` "&AC33&" "&IF(AJ33="Y","NOT NULL","") -> ,`STR_HIER_ID` int | BT33: =",`"&R33&"`" -> ,`STR_HIER_ID` | BV33: =",A.`"&R33&"` = B.`"&R33&"`" -> ,A.`STR_HIER_ID` = B.`STR_HIER_ID` | BX33: =",`"&R33&"`" -> ,`STR_HIER_ID` | BZ33: =",`"&R33&"`" -> ,`STR_HIER_ID`
A34: @9 | B34: 9 | D34: 商品／非商品識別コード | R34: LN_ITM_CD | AC34: {=_xlfn.SWITCH(BM34,"String","varchar("&BN34&")","Long","int","Integer","smallint","Double","decimal(9,2)","Currency","int")} -> int | AT34: 現在０固定 ０：通常商品 １：売上除外商品 ２：非商品 ３：非商品＆売上除外商品 | BL34: =REPT("a"&CHAR(10)&"b",INT(LENB(SUBSTITUTE(AT34,CHAR(10),""))/70)+1) -> a ba b | BM34: Long | BP34: =",`"&R34&"` "&AC34&" "&IF(AJ34="Y","NOT NULL","")&" COMMENT '"&D34&"'" -> ,`LN_ITM_CD` int COMMENT '商品／非商品識別コード' | BR34: =",`"&R34&"` "&AC34&" "&IF(AJ34="Y","NOT NULL","") -> ,`LN_ITM_CD` int | BT34: =",`"&R34&"`" -> ,`LN_ITM_CD` | BV34: =",A.`"&R34&"` = B.`"&R34&"`" -> ,A.`LN_ITM_CD` = B.`LN_ITM_CD` | BX34: =",`"&R34&"`" -> ,`LN_ITM_CD` | BZ34: =",`"&R34&"`" -> ,`LN_ITM_CD`
A35: @10 | B35: 9 | D35: 限定商品グループ | R35: SLS_RSTRCT_GRP | AC35: {=_xlfn.SWITCH(BM35,"String","varchar("&BN35&")","Long","int","Integer","smallint","Double","decimal(9,2)","Currency","int")} -> int | AT35: 現在未使用 ０固定 | BL35: =REPT("a"&CHAR(10)&"b",INT(LENB(SUBSTITUTE(AT35,CHAR(10),""))/70)+1) -> a b | BM35: Long | BP35: =",`"&R35&"` "&AC35&" "&IF(AJ35="Y","NOT NULL","")&" COMMENT '"&D35&"'" -> ,`SLS_RSTRCT_GRP` int COMMENT '限定商品グループ' | BR35: =",`"&R35&"` "&AC35&" "&IF(AJ35="Y","NOT NULL","") -> ,`SLS_RSTRCT_GRP` int | BT35: =",`"&R35&"`" -> ,`SLS_RSTRCT_GRP` | BV35: =",A.`"&R35&"` = B.`"&R35&"`" -> ,A.`SLS_RSTRCT_GRP` = B.`SLS_RSTRCT_GRP` | BX35: =",`"&R35&"`" -> ,`SLS_RSTRCT_GRP` | BZ35: =",`"&R35&"`" -> ,`SLS_RSTRCT_GRP`
A36: @11 | B36: 9 | D36: 商品返品場所 | R36: DFLT_RTN_LOC_ID | AC36: {=_xlfn.SWITCH(BM36,"String","varchar("&BN36&")","Long","int","Integer","smallint","Double","decimal(9,2)","Currency","int")} -> varchar(10) | AT36: 現在未使用 Ｎｕｌｌ固定 | BL36: =REPT("a"&CHAR(10)&"b",INT(LENB(SUBSTITUTE(AT36,CHAR(10),""))/70)+1) -> a b | BM36: String | BN36: 10 | BP36: =",`"&R36&"` "&AC36&" "&IF(AJ36="Y","NOT NULL","")&" COMMENT '"&D36&"'" -> ,`DFLT_RTN_LOC_ID` varchar(10) COMMENT '商品返品場所' | BR36: =",`"&R36&"` "&AC36&" "&IF(AJ36="Y","NOT NULL","") -> ,`DFLT_RTN_LOC_ID` varchar(10) | BT36: =",`"&R36&"`" -> ,`DFLT_RTN_LOC_ID` | BV36: =",A.`"&R36&"` = B.`"&R36&"`" -> ,A.`DFLT_RTN_LOC_ID` = B.`DFLT_RTN_LOC_ID` | BX36: =",`"&R36&"`" -> ,`DFLT_RTN_LOC_ID` | BZ36: =",`"&R36&"`" -> ,`DFLT_RTN_LOC_ID`
A37: @12 | B37: 9 | D37: 単品販売単位 | R37: UOM | AC37: {=_xlfn.SWITCH(BM37,"String","varchar("&BN37&")","Long","int","Integer","smallint","Double","decimal(9,2)","Currency","int")} -> varchar(10) | AT37: 現在未使用 Ｎｕｌｌ固定 | BL37: =REPT("a"&CHAR(10)&"b",INT(LENB(SUBSTITUTE(AT37,CHAR(10),""))/70)+1) -> a b | BM37: String | BN37: 10 | BP37: =",`"&R37&"` "&AC37&" "&IF(AJ37="Y","NOT NULL","")&" COMMENT '"&D37&"'" -> ,`UOM` varchar(10) COMMENT '単品販売単位' | BR37: =",`"&R37&"` "&AC37&" "&IF(AJ37="Y","NOT NULL","") -> ,`UOM` varchar(10) | BT37: =",`"&R37&"`" -> ,`UOM` | BV37: =",A.`"&R37&"` = B.`"&R37&"`" -> ,A.`UOM` = B.`UOM` | BX37: =",`"&R37&"`" -> ,`UOM` | BZ37: =",`"&R37&"`" -> ,`UOM`
A38: @13 | B38: 9 | D38: 最小販売単位 | R38: UNT_QTY | AC38: {=_xlfn.SWITCH(BM38,"String","varchar("&BN38&")","Long","int","Integer","smallint","Double","decimal(9,2)","Currency","int")} -> decimal(9,2) | AT38: 現在未使用 ０固定 | BL38: =REPT("a"&CHAR(10)&"b",INT(LENB(SUBSTITUTE(AT38,CHAR(10),""))/70)+1) -> a b | BM38: Double | BP38: =",`"&R38&"` "&AC38&" "&IF(AJ38="Y","NOT NULL","")&" COMMENT '"&D38&"'" -> ,`UNT_QTY` decimal(9,2) COMMENT '最小販売単位' | BR38: =",`"&R38&"` "&AC38&" "&IF(AJ38="Y","NOT NULL","") -> ,`UNT_QTY` decimal(9,2) | BT38: =",`"&R38&"`" -> ,`UNT_QTY` | BV38: =",A.`"&R38&"` = B.`"&R38&"`" -> ,A.`UNT_QTY` = B.`UNT_QTY` | BX38: =",`"&R38&"`" -> ,`UNT_QTY` | BZ38: =",`"&R38&"`" -> ,`UNT_QTY`
A39: @14 | B39: 9 | D39: 値引識別フラグ | R39: MD_FG | AC39: {=_xlfn.SWITCH(BM39,"String","varchar("&BN39&")","Long","int","Integer","smallint","Double","decimal(9,2)","Currency","int")} -> smallint | AT39: 現在未使用 ０固定 | BL39: =REPT("a"&CHAR(10)&"b",INT(LENB(SUBSTITUTE(AT39,CHAR(10),""))/70)+1) -> a b | BM39: Integer | BP39: =",`"&R39&"` "&AC39&" "&IF(AJ39="Y","NOT NULL","")&" COMMENT '"&D39&"'" -> ,`MD_FG` smallint COMMENT '値引識別フラグ' | BR39: =",`"&R39&"` "&AC39&" "&IF(AJ39="Y","NOT NULL","") -> ,`MD_FG` smallint | BT39: =",`"&R39&"`" -> ,`MD_FG` | BV39: =",A.`"&R39&"` = B.`"&R39&"`" -> ,A.`MD_FG` = B.`MD_FG` | BX39: =",`"&R39&"`" -> ,`MD_FG` | BZ39: =",`"&R39&"`" -> ,`MD_FG`
A40: @15 | B40: 9 | D40: 数量登録必須フラグ | R40: QTY_RQED_FG | AC40: {=_xlfn.SWITCH(BM40,"String","varchar("&BN40&")","Long","int","Integer","smallint","Double","decimal(9,2)","Currency","int")} -> smallint | AT40: 現在未使用 ０固定 | BL40: =REPT("a"&CHAR(10)&"b",INT(LENB(SUBSTITUTE(AT40,CHAR(10),""))/70)+1) -> a b | BM40: Integer | BP40: =",`"&R40&"` "&AC40&" "&IF(AJ40="Y","NOT NULL","")&" COMMENT '"&D40&"'" -> ,`QTY_RQED_FG` smallint COMMENT '数量登録必須フラグ' | BR40: =",`"&R40&"` "&AC40&" "&IF(AJ40="Y","NOT NULL","") -> ,`QTY_RQED_FG` smallint | BT40: =",`"&R40&"`" -> ,`QTY_RQED_FG` | BV40: =",A.`"&R40&"` = B.`"&R40&"`" -> ,A.`QTY_RQED_FG` = B.`QTY_RQED_FG` | BX40: =",`"&R40&"`" -> ,`QTY_RQED_FG` | BZ40: =",`"&R40&"`" -> ,`QTY_RQED_FG`
A41: @16 | B41: 9 | D41: 数量登録可否フラグ | R41: QTY_ALLOWD | AC41: {=_xlfn.SWITCH(BM41,"String","varchar("&BN41&")","Long","int","Integer","smallint","Double","decimal(9,2)","Currency","int")} -> smallint | AT41: 現在未使用 ０固定 | BL41: =REPT("a"&CHAR(10)&"b",INT(LENB(SUBSTITUTE(AT41,CHAR(10),""))/70)+1) -> a b | BM41: Integer | BP41: =",`"&R41&"` "&AC41&" "&IF(AJ41="Y","NOT NULL","")&" COMMENT '"&D41&"'" -> ,`QTY_ALLOWD` smallint COMMENT '数量登録可否フラグ' | BR41: =",`"&R41&"` "&AC41&" "&IF(AJ41="Y","NOT NULL","") -> ,`QTY_ALLOWD` smallint | BT41: =",`"&R41&"`" -> ,`QTY_ALLOWD` | BV41: =",A.`"&R41&"` = B.`"&R41&"`" -> ,A.`QTY_ALLOWD` = B.`QTY_ALLOWD` | BX41: =",`"&R41&"`" -> ,`QTY_ALLOWD` | BZ41: =",`"&R41&"`" -> ,`QTY_ALLOWD`
A42: @17 | B42: 9 | D42: 販売時の承認フラグ | R42: SLS_AURH_FG | AC42: {=_xlfn.SWITCH(BM42,"String","varchar("&BN42&")","Long","int","Integer","smallint","Double","decimal(9,2)","Currency","int")} -> smallint | AT42: 現在未使用 ０固定 | BL42: =REPT("a"&CHAR(10)&"b",INT(LENB(SUBSTITUTE(AT42,CHAR(10),""))/70)+1) -> a b | BM42: Integer | BP42: =",`"&R42&"` "&AC42&" "&IF(AJ42="Y","NOT NULL","")&" COMMENT '"&D42&"'" -> ,`SLS_AURH_FG` smallint COMMENT '販売時の承認フラグ' | BR42: =",`"&R42&"` "&AC42&" "&IF(AJ42="Y","NOT NULL","") -> ,`SLS_AURH_FG` smallint | BT42: =",`"&R42&"`" -> ,`SLS_AURH_FG` | BV42: =",A.`"&R42&"` = B.`"&R42&"`" -> ,A.`SLS_AURH_FG` = B.`SLS_AURH_FG` | BX42: =",`"&R42&"`" -> ,`SLS_AURH_FG` | BZ42: =",`"&R42&"`" -> ,`SLS_AURH_FG`
A43: @18 | B43: 9 | D43: 手入力価格変更フラグ | R43: MNL_PRC_LVL | AC43: {=_xlfn.SWITCH(BM43,"String","varchar("&BN43&")","Long","int","Integer","smallint","Double","decimal(9,2)","Currency","int")} -> smallint | AT43: 現在未使用 ０固定 | BL43: =REPT("a"&CHAR(10)&"b",INT(LENB(SUBSTITUTE(AT43,CHAR(10),""))/70)+1) -> a b | BM43: Integer | BP43: =",`"&R43&"` "&AC43&" "&IF(AJ43="Y","NOT NULL","")&" COMMENT '"&D43&"'" -> ,`MNL_PRC_LVL` smallint COMMENT '手入力価格変更フラグ' | BR43: =",`"&R43&"` "&AC43&" "&IF(AJ43="Y","NOT NULL","") -> ,`MNL_PRC_LVL` smallint | BT43: =",`"&R43&"`" -> ,`MNL_PRC_LVL` | BV43: =",A.`"&R43&"` = B.`"&R43&"`" -> ,A.`MNL_PRC_LVL` = B.`MNL_PRC_LVL` | BX43: =",`"&R43&"`" -> ,`MNL_PRC_LVL` | BZ43: =",`"&R43&"`" -> ,`MNL_PRC_LVL`
A44: @19 | B44: 9 | D44: 商品特定フラグ | R44: SRLZD_MDSE_FG | AC44: {=_xlfn.SWITCH(BM44,"String","varchar("&BN44&")","Long","int","Integer","smallint","Double","decimal(9,2)","Currency","int")} -> smallint | AT44: 現在未使用 ０固定 | BL44: =REPT("a"&CHAR(10)&"b",INT(LENB(SUBSTITUTE(AT44,CHAR(10),""))/70)+1) -> a b | BM44: Integer | BP44: =",`"&R44&"` "&AC44&" "&IF(AJ44="Y","NOT NULL","")&" COMMENT '"&D44&"'" -> ,`SRLZD_MDSE_FG` smallint COMMENT '商品特定フラグ' | BR44: =",`"&R44&"` "&AC44&" "&IF(AJ44="Y","NOT NULL","") -> ,`SRLZD_MDSE_FG` smallint | BT44: =",`"&R44&"`" -> ,`SRLZD_MDSE_FG` | BV44: =",A.`"&R44&"` = B.`"&R44&"`" -> ,A.`SRLZD_MDSE_FG` = B.`SRLZD_MDSE_FG` | BX44: =",`"&R44&"`" -> ,`SRLZD_MDSE_FG` | BZ44: =",`"&R44&"`" -> ,`SRLZD_MDSE_FG`
A45: @20 | B45: 9 | D45: フードスタンプ対象 | R45: FD_STMP_FG | AC45: {=_xlfn.SWITCH(BM45,"String","varchar("&BN45&")","Long","int","Integer","smallint","Double","decimal(9,2)","Currency","int")} -> smallint | AT45: 現在未使用 ０固定 | BL45: =REPT("a"&CHAR(10)&"b",INT(LENB(SUBSTITUTE(AT45,CHAR(10),""))/70)+1) -> a b | BM45: Integer | BP45: =",`"&R45&"` "&AC45&" "&IF(AJ45="Y","NOT NULL","")&" COMMENT '"&D45&"'" -> ,`FD_STMP_FG` smallint COMMENT 'フードスタンプ対象' | BR45: =",`"&R45&"` "&AC45&" "&IF(AJ45="Y","NOT NULL","") -> ,`FD_STMP_FG` smallint | BT45: =",`"&R45&"`" -> ,`FD_STMP_FG` | BV45: =",A.`"&R45&"` = B.`"&R45&"`" -> ,A.`FD_STMP_FG` = B.`FD_STMP_FG` | BX45: =",`"&R45&"`" -> ,`FD_STMP_FG` | BZ45: =",`"&R45&"`" -> ,`FD_STMP_FG`
A46: @21 | B46: 9 | D46: ＷＩＣ有効商品フラグ | R46: WIC_FG | AC46: {=_xlfn.SWITCH(BM46,"String","varchar("&BN46&")","Long","int","Integer","smallint","Double","decimal(9,2)","Currency","int")} -> smallint | AT46: 現在未使用 ０固定 | BL46: =REPT("a"&CHAR(10)&"b",INT(LENB(SUBSTITUTE(AT46,CHAR(10),""))/70)+1) -> a b | BM46: Integer | BP46: =",`"&R46&"` "&AC46&" "&IF(AJ46="Y","NOT NULL","")&" COMMENT '"&D46&"'" -> ,`WIC_FG` smallint COMMENT 'ＷＩＣ有効商品フラグ' | BR46: =",`"&R46&"` "&AC46&" "&IF(AJ46="Y","NOT NULL","") -> ,`WIC_FG` smallint | BT46: =",`"&R46&"`" -> ,`WIC_FG` | BV46: =",A.`"&R46&"` = B.`"&R46&"`" -> ,A.`WIC_FG` = B.`WIC_FG` | BX46: =",`"&R46&"`" -> ,`WIC_FG` | BZ46: =",`"&R46&"`" -> ,`WIC_FG`
A47: @22 | B47: 9 | D47: 在庫コード | R47: PERPET_INV_CD | AC47: {=_xlfn.SWITCH(BM47,"String","varchar("&BN47&")","Long","int","Integer","smallint","Double","decimal(9,2)","Currency","int")} -> smallint | AT47: 現在未使用 ０固定 | BL47: =REPT("a"&CHAR(10)&"b",INT(LENB(SUBSTITUTE(AT47,CHAR(10),""))/70)+1) -> a b | BM47: Integer | BP47: =",`"&R47&"` "&AC47&" "&IF(AJ47="Y","NOT NULL","")&" COMMENT '"&D47&"'" -> ,`PERPET_INV_CD` smallint COMMENT '在庫コード' | BR47: =",`"&R47&"` "&AC47&" "&IF(AJ47="Y","NOT NULL","") -> ,`PERPET_INV_CD` smallint | BT47: =",`"&R47&"`" -> ,`PERPET_INV_CD` | BV47: =",A.`"&R47&"` = B.`"&R47&"`" -> ,A.`PERPET_INV_CD` = B.`PERPET_INV_CD` | BX47: =",`"&R47&"`" -> ,`PERPET_INV_CD` | BZ47: =",`"&R47&"`" -> ,`PERPET_INV_CD`
A48: @23 | B48: 9 | D48: 売価 | R48: RTL_PRC NV_CD | AC48: {=_xlfn.SWITCH(BM48,"String","varchar("&BN48&")","Long","int","Integer","smallint","Double","decimal(9,2)","Currency","int")} -> int | BL48: =REPT("a"&CHAR(10)&"b",INT(LENB(SUBSTITUTE(AT48,CHAR(10),""))/70)+1) -> a b | BM48: Currency | BP48: =",`"&R48&"` "&AC48&" "&IF(AJ48="Y","NOT NULL","")&" COMMENT '"&D48&"'" -> ,`RTL_PRC NV_CD` int COMMENT '売価' | BR48: =",`"&R48&"` "&AC48&" "&IF(AJ48="Y","NOT NULL","") -> ,`RTL_PRC NV_CD` int | BT48: =",`"&R48&"`" -> ,`RTL_PRC NV_CD` | BV48: =",A.`"&R48&"` = B.`"&R48&"`" -> ,A.`RTL_PRC NV_CD` = B.`RTL_PRC NV_CD` | BX48: =",`"&R48&"`" -> ,`RTL_PRC NV_CD` | BZ48: =",`"&R48&"`" -> ,`RTL_PRC NV_CD`
A49: @24 | B49: 9 | D49: 単位原価 | R49: UNT_CST | AC49: {=_xlfn.SWITCH(BM49,"String","varchar("&BN49&")","Long","int","Integer","smallint","Double","decimal(9,2)","Currency","int")} -> decimal(9,2) | AT49: 商品の原価を設定する。少数第２位まで可 | BL49: =REPT("a"&CHAR(10)&"b",INT(LENB(SUBSTITUTE(AT49,CHAR(10),""))/70)+1) -> a b | BM49: Double | BP49: =",`"&R49&"` "&AC49&" "&IF(AJ49="Y","NOT NULL","")&" COMMENT '"&D49&"'" -> ,`UNT_CST` decimal(9,2) COMMENT '単位原価' | BR49: =",`"&R49&"` "&AC49&" "&IF(AJ49="Y","NOT NULL","") -> ,`UNT_CST` decimal(9,2) | BT49: =",`"&R49&"`" -> ,`UNT_CST` | BV49: =",A.`"&R49&"` = B.`"&R49&"`" -> ,A.`UNT_CST` = B.`UNT_CST` | BX49: =",`"&R49&"`" -> ,`UNT_CST` | BZ49: =",`"&R49&"`" -> ,`UNT_CST`
A50: @25 | B50: 9 | D50: 最低取引額 | R50: MIN_MDSE_AMT | AC50: {=_xlfn.SWITCH(BM50,"String","varchar("&BN50&")","Long","int","Integer","smallint","Double","decimal(9,2)","Currency","int")} -> int | AT50: 現在未使用 ０固定 | BL50: =REPT("a"&CHAR(10)&"b",INT(LENB(SUBSTITUTE(AT50,CHAR(10),""))/70)+1) -> a b | BM50: Currency | BP50: =",`"&R50&"` "&AC50&" "&IF(AJ50="Y","NOT NULL","")&" COMMENT '"&D50&"'" -> ,`MIN_MDSE_AMT` int COMMENT '最低取引額' | BR50: =",`"&R50&"` "&AC50&" "&IF(AJ50="Y","NOT NULL","") -> ,`MIN_MDSE_AMT` int | BT50: =",`"&R50&"`" -> ,`MIN_MDSE_AMT` | BV50: =",A.`"&R50&"` = B.`"&R50&"`" -> ,A.`MIN_MDSE_AMT` = B.`MIN_MDSE_AMT` | BX50: =",`"&R50&"`" -> ,`MIN_MDSE_AMT` | BZ50: =",`"&R50&"`" -> ,`MIN_MDSE_AMT`
A51: @26 | B51: 9 | D51: 最高取引額 | R51: MAX_MDSE_AMT | AC51: {=_xlfn.SWITCH(BM51,"String","varchar("&BN51&")","Long","int","Integer","smallint","Double","decimal(9,2)","Currency","int")} -> int | AT51: 現在未使用 ０固定 | BL51: =REPT("a"&CHAR(10)&"b",INT(LENB(SUBSTITUTE(AT51,CHAR(10),""))/70)+1) -> a b | BM51: Currency | BP51: =",`"&R51&"` "&AC51&" "&IF(AJ51="Y","NOT NULL","")&" COMMENT '"&D51&"'" -> ,`MAX_MDSE_AMT` int COMMENT '最高取引額' | BR51: =",`"&R51&"` "&AC51&" "&IF(AJ51="Y","NOT NULL","") -> ,`MAX_MDSE_AMT` int | BT51: =",`"&R51&"`" -> ,`MAX_MDSE_AMT` | BV51: =",A.`"&R51&"` = B.`"&R51&"`" -> ,A.`MAX_MDSE_AMT` = B.`MAX_MDSE_AMT` | BX51: =",`"&R51&"`" -> ,`MAX_MDSE_AMT` | BZ51: =",`"&R51&"`" -> ,`MAX_MDSE_AMT`
A52: @27 | B52: 9 | D52: 商品の売上場所 | R52: DFLT_SLS_LOC_ID | AC52: {=_xlfn.SWITCH(BM52,"String","varchar("&BN52&")","Long","int","Integer","smallint","Double","decimal(9,2)","Currency","int")} -> varchar(10) | AT52: 現在未使用 Ｎｕｌｌ固定 | BL52: =REPT("a"&CHAR(10)&"b",INT(LENB(SUBSTITUTE(AT52,CHAR(10),""))/70)+1) -> a b | BM52: String | BN52: 10 | BP52: =",`"&R52&"` "&AC52&" "&IF(AJ52="Y","NOT NULL","")&" COMMENT '"&D52&"'" -> ,`DFLT_SLS_LOC_ID` varchar(10) COMMENT '商品の売上場所' | BR52: =",`"&R52&"` "&AC52&" "&IF(AJ52="Y","NOT NULL","") -> ,`DFLT_SLS_LOC_ID` varchar(10) | BT52: =",`"&R52&"`" -> ,`DFLT_SLS_LOC_ID` | BV52: =",A.`"&R52&"` = B.`"&R52&"`" -> ,A.`DFLT_SLS_LOC_ID` = B.`DFLT_SLS_LOC_ID` | BX52: =",`"&R52&"`" -> ,`DFLT_SLS_LOC_ID` | BZ52: =",`"&R52&"`" -> ,`DFLT_SLS_LOC_ID`
A53: @28 | B53: 9 | D53: 商品移動 | R53: ITM_MVMNT_FG | AC53: {=_xlfn.SWITCH(BM53,"String","varchar("&BN53&")","Long","int","Integer","smallint","Double","decimal(9,2)","Currency","int")} -> smallint | AT53: 現在未使用 ０固定 | BL53: =REPT("a"&CHAR(10)&"b",INT(LENB(SUBSTITUTE(AT53,CHAR(10),""))/70)+1) -> a b | BM53: Integer | BP53: =",`"&R53&"` "&AC53&" "&IF(AJ53="Y","NOT NULL","")&" COMMENT '"&D53&"'" -> ,`ITM_MVMNT_FG` smallint COMMENT '商品移動' | BR53: =",`"&R53&"` "&AC53&" "&IF(AJ53="Y","NOT NULL","") -> ,`ITM_MVMNT_FG` smallint | BT53: =",`"&R53&"`" -> ,`ITM_MVMNT_FG` | BV53: =",A.`"&R53&"` = B.`"&R53&"`" -> ,A.`ITM_MVMNT_FG` = B.`ITM_MVMNT_FG` | BX53: =",`"&R53&"`" -> ,`ITM_MVMNT_FG` | BZ53: =",`"&R53&"`" -> ,`ITM_MVMNT_FG`
A54: @29 | B54: 9 | D54: ＶＦＤ表示名称 | R54: RCPT_DESCR_1 | AC54: {=_xlfn.SWITCH(BM54,"String","varchar("&BN54&")","Long","int","Integer","smallint","Double","decimal(9,2)","Currency","int")} -> varchar(20) | AT54: ＶＦＤに表示される文字 半角２０文字 または 日本語10文字以内 | BL54: =REPT("a"&CHAR(10)&"b",INT(LENB(SUBSTITUTE(AT54,CHAR(10),""))/70)+1) -> a b | BM54: String | BN54: 20 | BP54: =",`"&R54&"` "&AC54&" "&IF(AJ54="Y","NOT NULL","")&" COMMENT '"&D54&"'" -> ,`RCPT_DESCR_1` varchar(20) COMMENT 'ＶＦＤ表示名称' | BR54: =",`"&R54&"` "&AC54&" "&IF(AJ54="Y","NOT NULL","") -> ,`RCPT_DESCR_1` varchar(20) | BT54: =",`"&R54&"`" -> ,`RCPT_DESCR_1` | BV54: =",A.`"&R54&"` = B.`"&R54&"`" -> ,A.`RCPT_DESCR_1` = B.`RCPT_DESCR_1` | BX54: =",`"&R54&"`" -> ,`RCPT_DESCR_1` | BZ54: =",`"&R54&"`" -> ,`RCPT_DESCR_1`
A55: @30 | B55: 9 | D55: レシート記述名称２ | R55: RCPT_DESCR_2 | AC55: {=_xlfn.SWITCH(BM55,"String","varchar("&BN55&")","Long","int","Integer","smallint","Double","decimal(9,2)","Currency","int")} -> varchar(20) | AT55: 現在未使用 Ｎｕｌｌ固定 | BL55: =REPT("a"&CHAR(10)&"b",INT(LENB(SUBSTITUTE(AT55,CHAR(10),""))/70)+1) -> a b | BM55: String | BN55: 20 | BP55: =",`"&R55&"` "&AC55&" "&IF(AJ55="Y","NOT NULL","")&" COMMENT '"&D55&"'" -> ,`RCPT_DESCR_2` varchar(20) COMMENT 'レシート記述名称２' | BR55: =",`"&R55&"` "&AC55&" "&IF(AJ55="Y","NOT NULL","") -> ,`RCPT_DESCR_2` varchar(20) | BT55: =",`"&R55&"`" -> ,`RCPT_DESCR_2` | BV55: =",A.`"&R55&"` = B.`"&R55&"`" -> ,A.`RCPT_DESCR_2` = B.`RCPT_DESCR_2` | BX55: =",`"&R55&"`" -> ,`RCPT_DESCR_2` | BZ55: =",`"&R55&"`" -> ,`RCPT_DESCR_2`
A56: @31 | B56: 9 | D56: レシート記述名称３ | R56: RCPT_DESCR_3 | AC56: {=_xlfn.SWITCH(BM56,"String","varchar("&BN56&")","Long","int","Integer","smallint","Double","decimal(9,2)","Currency","int")} -> varchar(20) | AT56: 現在未使用 Ｎｕｌｌ固定 | BL56: =REPT("a"&CHAR(10)&"b",INT(LENB(SUBSTITUTE(AT56,CHAR(10),""))/70)+1) -> a b | BM56: String | BN56: 20 | BP56: =",`"&R56&"` "&AC56&" "&IF(AJ56="Y","NOT NULL","")&" COMMENT '"&D56&"'" -> ,`RCPT_DESCR_3` varchar(20) COMMENT 'レシート記述名称３' | BR56: =",`"&R56&"` "&AC56&" "&IF(AJ56="Y","NOT NULL","") -> ,`RCPT_DESCR_3` varchar(20) | BT56: =",`"&R56&"`" -> ,`RCPT_DESCR_3` | BV56: =",A.`"&R56&"` = B.`"&R56&"`" -> ,A.`RCPT_DESCR_3` = B.`RCPT_DESCR_3` | BX56: =",`"&R56&"`" -> ,`RCPT_DESCR_3` | BZ56: =",`"&R56&"`" -> ,`RCPT_DESCR_3`
A57: @32 | B57: 9 | D57: レシート記述名称４ | R57: RCPT_DESCR_4 | AC57: {=_xlfn.SWITCH(BM57,"String","varchar("&BN57&")","Long","int","Integer","smallint","Double","decimal(9,2)","Currency","int")} -> varchar(20) | AT57: 現在未使用 Ｎｕｌｌ固定 | BL57: =REPT("a"&CHAR(10)&"b",INT(LENB(SUBSTITUTE(AT57,CHAR(10),""))/70)+1) -> a b | BM57: String | BN57: 20 | BP57: =",`"&R57&"` "&AC57&" "&IF(AJ57="Y","NOT NULL","")&" COMMENT '"&D57&"'" -> ,`RCPT_DESCR_4` varchar(20) COMMENT 'レシート記述名称４' | BR57: =",`"&R57&"` "&AC57&" "&IF(AJ57="Y","NOT NULL","") -> ,`RCPT_DESCR_4` varchar(20) | BT57: =",`"&R57&"`" -> ,`RCPT_DESCR_4` | BV57: =",A.`"&R57&"` = B.`"&R57&"`" -> ,A.`RCPT_DESCR_4` = B.`RCPT_DESCR_4` | BX57: =",`"&R57&"`" -> ,`RCPT_DESCR_4` | BZ57: =",`"&R57&"`" -> ,`RCPT_DESCR_4`
A58: @33 | B58: 9 | D58: 価格算出方法 | R58: PRC_MTHD | AC58: {=_xlfn.SWITCH(BM58,"String","varchar("&BN58&")","Long","int","Integer","smallint","Double","decimal(9,2)","Currency","int")} -> smallint | AT58: 現在未使用 ０固定 | BL58: =REPT("a"&CHAR(10)&"b",INT(LENB(SUBSTITUTE(AT58,CHAR(10),""))/70)+1) -> a b | BM58: Integer | BP58: =",`"&R58&"` "&AC58&" "&IF(AJ58="Y","NOT NULL","")&" COMMENT '"&D58&"'" -> ,`PRC_MTHD` smallint COMMENT '価格算出方法' | BR58: =",`"&R58&"` "&AC58&" "&IF(AJ58="Y","NOT NULL","") -> ,`PRC_MTHD` smallint | BT58: =",`"&R58&"`" -> ,`PRC_MTHD` | BV58: =",A.`"&R58&"` = B.`"&R58&"`" -> ,A.`PRC_MTHD` = B.`PRC_MTHD` | BX58: =",`"&R58&"`" -> ,`PRC_MTHD` | BZ58: =",`"&R58&"`" -> ,`PRC_MTHD`
A59: @34 | B59: 9 | D59: 組合せ成立数量 | R59: DEAL_QTY | AC59: {=_xlfn.SWITCH(BM59,"String","varchar("&BN59&")","Long","int","Integer","smallint","Double","decimal(9,2)","Currency","int")} -> decimal(9,2) | AT59: 現在未使用 ０固定 | BL59: =REPT("a"&CHAR(10)&"b",INT(LENB(SUBSTITUTE(AT59,CHAR(10),""))/70)+1) -> a b | BM59: Double | BP59: =",`"&R59&"` "&AC59&" "&IF(AJ59="Y","NOT NULL","")&" COMMENT '"&D59&"'" -> ,`DEAL_QTY` decimal(9,2) COMMENT '組合せ成立数量' | BR59: =",`"&R59&"` "&AC59&" "&IF(AJ59="Y","NOT NULL","") -> ,`DEAL_QTY` decimal(9,2) | BT59: =",`"&R59&"`" -> ,`DEAL_QTY` | BV59: =",A.`"&R59&"` = B.`"&R59&"`" -> ,A.`DEAL_QTY` = B.`DEAL_QTY` | BX59: =",`"&R59&"`" -> ,`DEAL_QTY` | BZ59: =",`"&R59&"`" -> ,`DEAL_QTY`
A60: @35 | B60: 9 | D60: 組合せ成立金額 | R60: DEAL_PRC | AC60: {=_xlfn.SWITCH(BM60,"String","varchar("&BN60&")","Long","int","Integer","smallint","Double","decimal(9,2)","Currency","int")} -> int | AT60: 現在未使用 ０固定 | BL60: =REPT("a"&CHAR(10)&"b",INT(LENB(SUBSTITUTE(AT60,CHAR(10),""))/70)+1) -> a b | BM60: Currency | BP60: =",`"&R60&"` "&AC60&" "&IF(AJ60="Y","NOT NULL","")&" COMMENT '"&D60&"'" -> ,`DEAL_PRC` int COMMENT '組合せ成立金額' | BR60: =",`"&R60&"` "&AC60&" "&IF(AJ60="Y","NOT NULL","") -> ,`DEAL_PRC` int | BT60: =",`"&R60&"`" -> ,`DEAL_PRC` | BV60: =",A.`"&R60&"` = B.`"&R60&"`" -> ,A.`DEAL_PRC` = B.`DEAL_PRC` | BX60: =",`"&R60&"`" -> ,`DEAL_PRC` | BZ60: =",`"&R60&"`" -> ,`DEAL_PRC`
A61: @36 | B61: 9 | D61: オペレータによる金額入力 | R61: PRC_RQRD_FG | AC61: {=_xlfn.SWITCH(BM61,"String","varchar("&BN61&")","Long","int","Integer","smallint","Double","decimal(9,2)","Currency","int")} -> smallint | AT61: 現在０固定 ０：なし １：あり | BL61: =REPT("a"&CHAR(10)&"b",INT(LENB(SUBSTITUTE(AT61,CHAR(10),""))/70)+1) -> a b | BM61: Integer | BP61: =",`"&R61&"` "&AC61&" "&IF(AJ61="Y","NOT NULL","")&" COMMENT '"&D61&"'" -> ,`PRC_RQRD_FG` smallint COMMENT 'オペレータによる金額入力' | BR61: =",`"&R61&"` "&AC61&" "&IF(AJ61="Y","NOT NULL","") -> ,`PRC_RQRD_FG` smallint | BT61: =",`"&R61&"`" -> ,`PRC_RQRD_FG` | BV61: =",A.`"&R61&"` = B.`"&R61&"`" -> ,A.`PRC_RQRD_FG` = B.`PRC_RQRD_FG` | BX61: =",`"&R61&"`" -> ,`PRC_RQRD_FG` | BZ61: =",`"&R61&"`" -> ,`PRC_RQRD_FG`
A62: @37 | B62: 9 | D62: 販売単位価格 | R62: UNT_PRC | AC62: {=_xlfn.SWITCH(BM62,"String","varchar("&BN62&")","Long","int","Integer","smallint","Double","decimal(9,2)","Currency","int")} -> int | AT62: 売価と同じ | BL62: =REPT("a"&CHAR(10)&"b",INT(LENB(SUBSTITUTE(AT62,CHAR(10),""))/70)+1) -> a b | BM62: Currency | BP62: =",`"&R62&"` "&AC62&" "&IF(AJ62="Y","NOT NULL","")&" COMMENT '"&D62&"'" -> ,`UNT_PRC` int COMMENT '販売単位価格' | BR62: =",`"&R62&"` "&AC62&" "&IF(AJ62="Y","NOT NULL","") -> ,`UNT_PRC` int | BT62: =",`"&R62&"`" -> ,`UNT_PRC` | BV62: =",A.`"&R62&"` = B.`"&R62&"`" -> ,A.`UNT_PRC` = B.`UNT_PRC` | BX62: =",`"&R62&"`" -> ,`UNT_PRC` | BZ62: =",`"&R62&"`" -> ,`UNT_PRC`
A63: @38 | B63: 9 | D63: 返品価格 | R63: RTN_PRC | AC63: {=_xlfn.SWITCH(BM63,"String","varchar("&BN63&")","Long","int","Integer","smallint","Double","decimal(9,2)","Currency","int")} -> int | AT63: 売価と同じ | BL63: =REPT("a"&CHAR(10)&"b",INT(LENB(SUBSTITUTE(AT63,CHAR(10),""))/70)+1) -> a b | BM63: Currency | BP63: =",`"&R63&"` "&AC63&" "&IF(AJ63="Y","NOT NULL","")&" COMMENT '"&D63&"'" -> ,`RTN_PRC` int COMMENT '返品価格' | BR63: =",`"&R63&"` "&AC63&" "&IF(AJ63="Y","NOT NULL","") -> ,`RTN_PRC` int | BT63: =",`"&R63&"`" -> ,`RTN_PRC` | BV63: =",A.`"&R63&"` = B.`"&R63&"`" -> ,A.`RTN_PRC` = B.`RTN_PRC` | BX63: =",`"&R63&"`" -> ,`RTN_PRC` | BZ63: =",`"&R63&"`" -> ,`RTN_PRC`
A64: @39 | B64: 9 | D64: 価格グループ | R64: PRC_GRP_ID | AC64: {=_xlfn.SWITCH(BM64,"String","varchar("&BN64&")","Long","int","Integer","smallint","Double","decimal(9,2)","Currency","int")} -> smallint | AT64: 現在未使用 ０固定 | BL64: =REPT("a"&CHAR(10)&"b",INT(LENB(SUBSTITUTE(AT64,CHAR(10),""))/70)+1) -> a b | BM64: Integer | BP64: =",`"&R64&"` "&AC64&" "&IF(AJ64="Y","NOT NULL","")&" COMMENT '"&D64&"'" -> ,`PRC_GRP_ID` smallint COMMENT '価格グループ' | BR64: =",`"&R64&"` "&AC64&" "&IF(AJ64="Y","NOT NULL","") -> ,`PRC_GRP_ID` smallint | BT64: =",`"&R64&"`" -> ,`PRC_GRP_ID` | BV64: =",A.`"&R64&"` = B.`"&R64&"`" -> ,A.`PRC_GRP_ID` = B.`PRC_GRP_ID` | BX64: =",`"&R64&"`" -> ,`PRC_GRP_ID` | BZ64: =",`"&R64&"`" -> ,`PRC_GRP_ID`
A65: @40 | B65: 9 | D65: 企画番号 | R65: EVENT_ID | AC65: {=_xlfn.SWITCH(BM65,"String","varchar("&BN65&")","Long","int","Integer","smallint","Double","decimal(9,2)","Currency","int")} -> varchar(12) | AT65: 現在未使用 Ｎｕｌｌ固定 | BL65: =REPT("a"&CHAR(10)&"b",INT(LENB(SUBSTITUTE(AT65,CHAR(10),""))/70)+1) -> a b | BM65: String | BN65: 12 | BP65: =",`"&R65&"` "&AC65&" "&IF(AJ65="Y","NOT NULL","")&" COMMENT '"&D65&"'" -> ,`EVENT_ID` varchar(12) COMMENT '企画番号' | BR65: =",`"&R65&"` "&AC65&" "&IF(AJ65="Y","NOT NULL","") -> ,`EVENT_ID` varchar(12) | BT65: =",`"&R65&"`" -> ,`EVENT_ID` | BV65: =",A.`"&R65&"` = B.`"&R65&"`" -> ,A.`EVENT_ID` = B.`EVENT_ID` | BX65: =",`"&R65&"`" -> ,`EVENT_ID` | BZ65: =",`"&R65&"`" -> ,`EVENT_ID`
A66: @41 | B66: 9 | D66: 業態 | R66: MDSE_STRC_NBR1 | AC66: {=_xlfn.SWITCH(BM66,"String","varchar("&BN66&")","Long","int","Integer","smallint","Double","decimal(9,2)","Currency","int")} -> varchar(12) | AT66: 右詰めにし先頭に０を詰める | BL66: =REPT("a"&CHAR(10)&"b",INT(LENB(SUBSTITUTE(AT66,CHAR(10),""))/70)+1) -> a b | BM66: String | BN66: 12 | BP66: =",`"&R66&"` "&AC66&" "&IF(AJ66="Y","NOT NULL","")&" COMMENT '"&D66&"'" -> ,`MDSE_STRC_NBR1` varchar(12) COMMENT '業態' | BR66: =",`"&R66&"` "&AC66&" "&IF(AJ66="Y","NOT NULL","") -> ,`MDSE_STRC_NBR1` varchar(12) | BT66: =",`"&R66&"`" -> ,`MDSE_STRC_NBR1` | BV66: =",A.`"&R66&"` = B.`"&R66&"`" -> ,A.`MDSE_STRC_NBR1` = B.`MDSE_STRC_NBR1` | BX66: =",`"&R66&"`" -> ,`MDSE_STRC_NBR1` | BZ66: =",`"&R66&"`" -> ,`MDSE_STRC_NBR1`
A67: @42 | B67: 9 | D67: グループ | R67: MDSE_STRC_NBR2 | AC67: {=_xlfn.SWITCH(BM67,"String","varchar("&BN67&")","Long","int","Integer","smallint","Double","decimal(9,2)","Currency","int")} -> varchar(12) | AT67: 右詰めにし先頭に０を詰める | BL67: =REPT("a"&CHAR(10)&"b",INT(LENB(SUBSTITUTE(AT67,CHAR(10),""))/70)+1) -> a b | BM67: String | BN67: 12 | BP67: =",`"&R67&"` "&AC67&" "&IF(AJ67="Y","NOT NULL","")&" COMMENT '"&D67&"'" -> ,`MDSE_STRC_NBR2` varchar(12) COMMENT 'グループ' | BR67: =",`"&R67&"` "&AC67&" "&IF(AJ67="Y","NOT NULL","") -> ,`MDSE_STRC_NBR2` varchar(12) | BT67: =",`"&R67&"`" -> ,`MDSE_STRC_NBR2` | BV67: =",A.`"&R67&"` = B.`"&R67&"`" -> ,A.`MDSE_STRC_NBR2` = B.`MDSE_STRC_NBR2` | BX67: =",`"&R67&"`" -> ,`MDSE_STRC_NBR2` | BZ67: =",`"&R67&"`" -> ,`MDSE_STRC_NBR2`
A68: @43 | B68: 9 | D68: 部門 | R68: MDSE_STRC_NBR3 | AC68: {=_xlfn.SWITCH(BM68,"String","varchar("&BN68&")","Long","int","Integer","smallint","Double","decimal(9,2)","Currency","int")} -> varchar(12) | AT68: 右詰めにし先頭に０を詰める | BL68: =REPT("a"&CHAR(10)&"b",INT(LENB(SUBSTITUTE(AT68,CHAR(10),""))/70)+1) -> a b | BM68: String | BN68: 12 | BP68: =",`"&R68&"` "&AC68&" "&IF(AJ68="Y","NOT NULL","")&" COMMENT '"&D68&"'" -> ,`MDSE_STRC_NBR3` varchar(12) COMMENT '部門' | BR68: =",`"&R68&"` "&AC68&" "&IF(AJ68="Y","NOT NULL","") -> ,`MDSE_STRC_NBR3` varchar(12) | BT68: =",`"&R68&"`" -> ,`MDSE_STRC_NBR3` | BV68: =",A.`"&R68&"` = B.`"&R68&"`" -> ,A.`MDSE_STRC_NBR3` = B.`MDSE_STRC_NBR3` | BX68: =",`"&R68&"`" -> ,`MDSE_STRC_NBR3` | BZ68: =",`"&R68&"`" -> ,`MDSE_STRC_NBR3`
A69: @44 | B69: 9 | D69: クラス | R69: MDSE_STRC_NBR4 | AC69: {=_xlfn.SWITCH(BM69,"String","varchar("&BN69&")","Long","int","Integer","smallint","Double","decimal(9,2)","Currency","int")} -> varchar(12) | AT69: 右詰めにし先頭に０を詰める | BL69: =REPT("a"&CHAR(10)&"b",INT(LENB(SUBSTITUTE(AT69,CHAR(10),""))/70)+1) -> a b | BM69: String | BN69: 12 | BP69: =",`"&R69&"` "&AC69&" "&IF(AJ69="Y","NOT NULL","")&" COMMENT '"&D69&"'" -> ,`MDSE_STRC_NBR4` varchar(12) COMMENT 'クラス' | BR69: =",`"&R69&"` "&AC69&" "&IF(AJ69="Y","NOT NULL","") -> ,`MDSE_STRC_NBR4` varchar(12) | BT69: =",`"&R69&"`" -> ,`MDSE_STRC_NBR4` | BV69: =",A.`"&R69&"` = B.`"&R69&"`" -> ,A.`MDSE_STRC_NBR4` = B.`MDSE_STRC_NBR4` | BX69: =",`"&R69&"`" -> ,`MDSE_STRC_NBR4` | BZ69: =",`"&R69&"`" -> ,`MDSE_STRC_NBR4`
A70: @45 | B70: 9 | D70: 品群 | R70: MDSE_STRC_NBR5 | AC70: {=_xlfn.SWITCH(BM70,"String","varchar("&BN70&")","Long","int","Integer","smallint","Double","decimal(9,2)","Currency","int")} -> varchar(12) | AT70: 右詰めにし先頭に０を詰める | BL70: =REPT("a"&CHAR(10)&"b",INT(LENB(SUBSTITUTE(AT70,CHAR(10),""))/70)+1) -> a b | BM70: String | BN70: 12 | BP70: =",`"&R70&"` "&AC70&" "&IF(AJ70="Y","NOT NULL","")&" COMMENT '"&D70&"'" -> ,`MDSE_STRC_NBR5` varchar(12) COMMENT '品群' | BR70: =",`"&R70&"` "&AC70&" "&IF(AJ70="Y","NOT NULL","") -> ,`MDSE_STRC_NBR5` varchar(12) | BT70: =",`"&R70&"`" -> ,`MDSE_STRC_NBR5` | BV70: =",A.`"&R70&"` = B.`"&R70&"`" -> ,A.`MDSE_STRC_NBR5` = B.`MDSE_STRC_NBR5` | BX70: =",`"&R70&"`" -> ,`MDSE_STRC_NBR5` | BZ70: =",`"&R70&"`" -> ,`MDSE_STRC_NBR5`
A71: @46 | B71: 9 | D71: 品種 | R71: MDSE_STRC_NBR6 | AC71: {=_xlfn.SWITCH(BM71,"String","varchar("&BN71&")","Long","int","Integer","smallint","Double","decimal(9,2)","Currency","int")} -> varchar(12) | AT71: 右詰めにし先頭に０を詰める | BL71: =REPT("a"&CHAR(10)&"b",INT(LENB(SUBSTITUTE(AT71,CHAR(10),""))/70)+1) -> a b | BM71: String | BN71: 12 | BP71: =",`"&R71&"` "&AC71&" "&IF(AJ71="Y","NOT NULL","")&" COMMENT '"&D71&"'" -> ,`MDSE_STRC_NBR6` varchar(12) COMMENT '品種' | BR71: =",`"&R71&"` "&AC71&" "&IF(AJ71="Y","NOT NULL","") -> ,`MDSE_STRC_NBR6` varchar(12) | BT71: =",`"&R71&"`" -> ,`MDSE_STRC_NBR6` | BV71: =",A.`"&R71&"` = B.`"&R71&"`" -> ,A.`MDSE_STRC_NBR6` = B.`MDSE_STRC_NBR6` | BX71: =",`"&R71&"`" -> ,`MDSE_STRC_NBR6` | BZ71: =",`"&R71&"`" -> ,`MDSE_STRC_NBR6`
A72: @47 | B72: 9 | D72: 分類 | R72: MDSE_STRC_NBR7 | AC72: {=_xlfn.SWITCH(BM72,"String","varchar("&BN72&")","Long","int","Integer","smallint","Double","decimal(9,2)","Currency","int")} -> varchar(12) | AT72: 右詰めにし先頭に０を詰める | BL72: =REPT("a"&CHAR(10)&"b",INT(LENB(SUBSTITUTE(AT72,CHAR(10),""))/70)+1) -> a b | BM72: String | BN72: 12 | BP72: =",`"&R72&"` "&AC72&" "&IF(AJ72="Y","NOT NULL","")&" COMMENT '"&D72&"'" -> ,`MDSE_STRC_NBR7` varchar(12) COMMENT '分類' | BR72: =",`"&R72&"` "&AC72&" "&IF(AJ72="Y","NOT NULL","") -> ,`MDSE_STRC_NBR7` varchar(12) | BT72: =",`"&R72&"`" -> ,`MDSE_STRC_NBR7` | BV72: =",A.`"&R72&"` = B.`"&R72&"`" -> ,A.`MDSE_STRC_NBR7` = B.`MDSE_STRC_NBR7` | BX72: =",`"&R72&"`" -> ,`MDSE_STRC_NBR7` | BZ72: =",`"&R72&"`" -> ,`MDSE_STRC_NBR7`
A73: @48 | B73: 9 | D73: 商品階層８ | R73: MDSE_STRC_NBR8 | AC73: {=_xlfn.SWITCH(BM73,"String","varchar("&BN73&")","Long","int","Integer","smallint","Double","decimal(9,2)","Currency","int")} -> varchar(12) | AT73: 未使用 | BL73: =REPT("a"&CHAR(10)&"b",INT(LENB(SUBSTITUTE(AT73,CHAR(10),""))/70)+1) -> a b | BM73: String | BN73: 12 | BP73: =",`"&R73&"` "&AC73&" "&IF(AJ73="Y","NOT NULL","")&" COMMENT '"&D73&"'" -> ,`MDSE_STRC_NBR8` varchar(12) COMMENT '商品階層８' | BR73: =",`"&R73&"` "&AC73&" "&IF(AJ73="Y","NOT NULL","") -> ,`MDSE_STRC_NBR8` varchar(12) | BT73: =",`"&R73&"`" -> ,`MDSE_STRC_NBR8` | BV73: =",A.`"&R73&"` = B.`"&R73&"`" -> ,A.`MDSE_STRC_NBR8` = B.`MDSE_STRC_NBR8` | BX73: =",`"&R73&"`" -> ,`MDSE_STRC_NBR8` | BZ73: =",`"&R73&"`" -> ,`MDSE_STRC_NBR8`
A74: @49 | B74: 9 | D74: 商品階層９ | R74: MDSE_STRC_NBR9 | AC74: {=_xlfn.SWITCH(BM74,"String","varchar("&BN74&")","Long","int","Integer","smallint","Double","decimal(9,2)","Currency","int")} -> varchar(12) | AT74: 未使用 | BL74: =REPT("a"&CHAR(10)&"b",INT(LENB(SUBSTITUTE(AT74,CHAR(10),""))/70)+1) -> a b | BM74: String | BN74: 12 | BP74: =",`"&R74&"` "&AC74&" "&IF(AJ74="Y","NOT NULL","")&" COMMENT '"&D74&"'" -> ,`MDSE_STRC_NBR9` varchar(12) COMMENT '商品階層９' | BR74: =",`"&R74&"` "&AC74&" "&IF(AJ74="Y","NOT NULL","") -> ,`MDSE_STRC_NBR9` varchar(12) | BT74: =",`"&R74&"`" -> ,`MDSE_STRC_NBR9` | BV74: =",A.`"&R74&"` = B.`"&R74&"`" -> ,A.`MDSE_STRC_NBR9` = B.`MDSE_STRC_NBR9` | BX74: =",`"&R74&"`" -> ,`MDSE_STRC_NBR9` | BZ74: =",`"&R74&"`" -> ,`MDSE_STRC_NBR9`
A75: @50 | B75: 9 | D75: プロモーション開始時間 | R75: PROMO_BGN_TS | AC75: {=_xlfn.SWITCH(BM75,"String","varchar("&BN75&")","Long","int","Integer","smallint","Double","decimal(9,2)","Currency","int")} -> varchar(20) | AT75: 現在未使用 Ｎｕｌｌ固定 | BL75: =REPT("a"&CHAR(10)&"b",INT(LENB(SUBSTITUTE(AT75,CHAR(10),""))/70)+1) -> a b | BM75: String | BN75: 20 | BP75: =",`"&R75&"` "&AC75&" "&IF(AJ75="Y","NOT NULL","")&" COMMENT '"&D75&"'" -> ,`PROMO_BGN_TS` varchar(20) COMMENT 'プロモーション開始時間' | BR75: =",`"&R75&"` "&AC75&" "&IF(AJ75="Y","NOT NULL","") -> ,`PROMO_BGN_TS` varchar(20) | BT75: =",`"&R75&"`" -> ,`PROMO_BGN_TS` | BV75: =",A.`"&R75&"` = B.`"&R75&"`" -> ,A.`PROMO_BGN_TS` = B.`PROMO_BGN_TS` | BX75: =",`"&R75&"`" -> ,`PROMO_BGN_TS` | BZ75: =",`"&R75&"`" -> ,`PROMO_BGN_TS`
A76: @51 | B76: 9 | D76: プロモーション終了時間 | R76: PROMO_END_TS | AC76: {=_xlfn.SWITCH(BM76,"String","varchar("&BN76&")","Long","int","Integer","smallint","Double","decimal(9,2)","Currency","int")} -> varchar(20) | AT76: 現在未使用 Ｎｕｌｌ固定 | BL76: =REPT("a"&CHAR(10)&"b",INT(LENB(SUBSTITUTE(AT76,CHAR(10),""))/70)+1) -> a b | BM76: String | BN76: 20 | BP76: =",`"&R76&"` "&AC76&" "&IF(AJ76="Y","NOT NULL","")&" COMMENT '"&D76&"'" -> ,`PROMO_END_TS` varchar(20) COMMENT 'プロモーション終了時間' | BR76: =",`"&R76&"` "&AC76&" "&IF(AJ76="Y","NOT NULL","") -> ,`PROMO_END_TS` varchar(20) | BT76: =",`"&R76&"`" -> ,`PROMO_END_TS` | BV76: =",A.`"&R76&"` = B.`"&R76&"`" -> ,A.`PROMO_END_TS` = B.`PROMO_END_TS` | BX76: =",`"&R76&"`" -> ,`PROMO_END_TS` | BZ76: =",`"&R76&"`" -> ,`PROMO_END_TS`
A77: @52 | B77: 9 | D77: プロモーション中の価格計算 | R77: PROMO_PRC_MTHD_ | AC77: {=_xlfn.SWITCH(BM77,"String","varchar("&BN77&")","Long","int","Integer","smallint","Double","decimal(9,2)","Currency","int")} -> smallint | AT77: 現在未使用 ０固定 | BL77: =REPT("a"&CHAR(10)&"b",INT(LENB(SUBSTITUTE(AT77,CHAR(10),""))/70)+1) -> a b | BM77: Integer | BP77: =",`"&R77&"` "&AC77&" "&IF(AJ77="Y","NOT NULL","")&" COMMENT '"&D77&"'" -> ,`PROMO_PRC_MTHD_` smallint COMMENT 'プロモーション中の価格計算' | BR77: =",`"&R77&"` "&AC77&" "&IF(AJ77="Y","NOT NULL","") -> ,`PROMO_PRC_MTHD_` smallint | BT77: =",`"&R77&"`" -> ,`PROMO_PRC_MTHD_` | BV77: =",A.`"&R77&"` = B.`"&R77&"`" -> ,A.`PROMO_PRC_MTHD_` = B.`PROMO_PRC_MTHD_` | BX77: =",`"&R77&"`" -> ,`PROMO_PRC_MTHD_` | BZ77: =",`"&R77&"`" -> ,`PROMO_PRC_MTHD_`
A78: @53 | B78: 9 | D78: プロモーション契約数 | R78: PROMO_DEAL_QTY | AC78: {=_xlfn.SWITCH(BM78,"String","varchar("&BN78&")","Long","int","Integer","smallint","Double","decimal(9,2)","Currency","int")} -> decimal(9,2) | AT78: 現在未使用 ０固定 | BL78: =REPT("a"&CHAR(10)&"b",INT(LENB(SUBSTITUTE(AT78,CHAR(10),""))/70)+1) -> a b | BM78: Double | BP78: =",`"&R78&"` "&AC78&" "&IF(AJ78="Y","NOT NULL","")&" COMMENT '"&D78&"'" -> ,`PROMO_DEAL_QTY` decimal(9,2) COMMENT 'プロモーション契約数' | BR78: =",`"&R78&"` "&AC78&" "&IF(AJ78="Y","NOT NULL","") -> ,`PROMO_DEAL_QTY` decimal(9,2) | BT78: =",`"&R78&"`" -> ,`PROMO_DEAL_QTY` | BV78: =",A.`"&R78&"` = B.`"&R78&"`" -> ,A.`PROMO_DEAL_QTY` = B.`PROMO_DEAL_QTY` | BX78: =",`"&R78&"`" -> ,`PROMO_DEAL_QTY` | BZ78: =",`"&R78&"`" -> ,`PROMO_DEAL_QTY`
A79: @54 | B79: 9 | D79: プロモーション契約価格 | R79: PROMO_DEAL_PRC | AC79: {=_xlfn.SWITCH(BM79,"String","varchar("&BN79&")","Long","int","Integer","smallint","Double","decimal(9,2)","Currency","int")} -> int | AT79: 現在未使用 ０固定 | BL79: =REPT("a"&CHAR(10)&"b",INT(LENB(SUBSTITUTE(AT79,CHAR(10),""))/70)+1) -> a b | BM79: Currency | BP79: =",`"&R79&"` "&AC79&" "&IF(AJ79="Y","NOT NULL","")&" COMMENT '"&D79&"'" -> ,`PROMO_DEAL_PRC` int COMMENT 'プロモーション契約価格' | BR79: =",`"&R79&"` "&AC79&" "&IF(AJ79="Y","NOT NULL","") -> ,`PROMO_DEAL_PRC` int | BT79: =",`"&R79&"`" -> ,`PROMO_DEAL_PRC` | BV79: =",A.`"&R79&"` = B.`"&R79&"`" -> ,A.`PROMO_DEAL_PRC` = B.`PROMO_DEAL_PRC` | BX79: =",`"&R79&"`" -> ,`PROMO_DEAL_PRC` | BZ79: =",`"&R79&"`" -> ,`PROMO_DEAL_PRC`
A80: @55 | B80: 9 | D80: プロモーション単価 | R80: PROMO_UNT_PRC | AC80: {=_xlfn.SWITCH(BM80,"String","varchar("&BN80&")","Long","int","Integer","smallint","Double","decimal(9,2)","Currency","int")} -> int | AT80: 現在未使用 ０固定 | BL80: =REPT("a"&CHAR(10)&"b",INT(LENB(SUBSTITUTE(AT80,CHAR(10),""))/70)+1) -> a b | BM80: Currency | BP80: =",`"&R80&"` "&AC80&" "&IF(AJ80="Y","NOT NULL","")&" COMMENT '"&D80&"'" -> ,`PROMO_UNT_PRC` int COMMENT 'プロモーション単価' | BR80: =",`"&R80&"` "&AC80&" "&IF(AJ80="Y","NOT NULL","") -> ,`PROMO_UNT_PRC` int | BT80: =",`"&R80&"`" -> ,`PROMO_UNT_PRC` | BV80: =",A.`"&R80&"` = B.`"&R80&"`" -> ,A.`PROMO_UNT_PRC` = B.`PROMO_UNT_PRC` | BX80: =",`"&R80&"`" -> ,`PROMO_UNT_PRC` | BZ80: =",`"&R80&"`" -> ,`PROMO_UNT_PRC`
A81: @56 | B81: 9 | D81: プロモーション申込 | R81: PROMO_EXCL_OFFER | AC81: {=_xlfn.SWITCH(BM81,"String","varchar("&BN81&")","Long","int","Integer","smallint","Double","decimal(9,2)","Currency","int")} -> smallint | AT81: 現在未使用 ０固定 | BL81: =REPT("a"&CHAR(10)&"b",INT(LENB(SUBSTITUTE(AT81,CHAR(10),""))/70)+1) -> a b | BM81: Integer | BP81: =",`"&R81&"` "&AC81&" "&IF(AJ81="Y","NOT NULL","")&" COMMENT '"&D81&"'" -> ,`PROMO_EXCL_OFFER` smallint COMMENT 'プロモーション申込' | BR81: =",`"&R81&"` "&AC81&" "&IF(AJ81="Y","NOT NULL","") -> ,`PROMO_EXCL_OFFER` smallint | BT81: =",`"&R81&"`" -> ,`PROMO_EXCL_OFFER` | BV81: =",A.`"&R81&"` = B.`"&R81&"`" -> ,A.`PROMO_EXCL_OFFER` = B.`PROMO_EXCL_OFFER` | BX81: =",`"&R81&"`" -> ,`PROMO_EXCL_OFFER` | BZ81: =",`"&R81&"`" -> ,`PROMO_EXCL_OFFER`
A82: @57 | B82: 9 | D82: プロモーション費用 | R82: PROMO_EXPN_FG | AC82: {=_xlfn.SWITCH(BM82,"String","varchar("&BN82&")","Long","int","Integer","smallint","Double","decimal(9,2)","Currency","int")} -> smallint | AT82: 現在未使用 ０固定 | BL82: =REPT("a"&CHAR(10)&"b",INT(LENB(SUBSTITUTE(AT82,CHAR(10),""))/70)+1) -> a b | BM82: Integer | BP82: =",`"&R82&"` "&AC82&" "&IF(AJ82="Y","NOT NULL","")&" COMMENT '"&D82&"'" -> ,`PROMO_EXPN_FG` smallint COMMENT 'プロモーション費用' | BR82: =",`"&R82&"` "&AC82&" "&IF(AJ82="Y","NOT NULL","") -> ,`PROMO_EXPN_FG` smallint | BT82: =",`"&R82&"`" -> ,`PROMO_EXPN_FG` | BV82: =",A.`"&R82&"` = B.`"&R82&"`" -> ,A.`PROMO_EXPN_FG` = B.`PROMO_EXPN_FG` | BX82: =",`"&R82&"`" -> ,`PROMO_EXPN_FG` | BZ82: =",`"&R82&"`" -> ,`PROMO_EXPN_FG`
A83: @58 | B83: 9 | D83: プロモーション貯金 | R83: PROMO_GL_ACCT | AC83: {=_xlfn.SWITCH(BM83,"String","varchar("&BN83&")","Long","int","Integer","smallint","Double","decimal(9,2)","Currency","int")} -> varchar(20) | AT83: 現在未使用 Ｎｕｌｌ固定 | BL83: =REPT("a"&CHAR(10)&"b",INT(LENB(SUBSTITUTE(AT83,CHAR(10),""))/70)+1) -> a b | BM83: String | BN83: 20 | BP83: =",`"&R83&"` "&AC83&" "&IF(AJ83="Y","NOT NULL","")&" COMMENT '"&D83&"'" -> ,`PROMO_GL_ACCT` varchar(20) COMMENT 'プロモーション貯金' | BR83: =",`"&R83&"` "&AC83&" "&IF(AJ83="Y","NOT NULL","") -> ,`PROMO_GL_ACCT` varchar(20) | BT83: =",`"&R83&"`" -> ,`PROMO_GL_ACCT` | BV83: =",A.`"&R83&"` = B.`"&R83&"`" -> ,A.`PROMO_GL_ACCT` = B.`PROMO_GL_ACCT` | BX83: =",`"&R83&"`" -> ,`PROMO_GL_ACCT` | BZ83: =",`"&R83&"`" -> ,`PROMO_GL_ACCT`
A84: @59 | B84: 9 | D84: ＶＡＴコード | R84: VAT_CD | AC84: {=_xlfn.SWITCH(BM84,"String","varchar("&BN84&")","Long","int","Integer","smallint","Double","decimal(9,2)","Currency","int")} -> varchar(20) | AT84: 現在未使用 Ｎｕｌｌ固定 | BL84: =REPT("a"&CHAR(10)&"b",INT(LENB(SUBSTITUTE(AT84,CHAR(10),""))/70)+1) -> a b | BM84: String | BN84: 20 | BP84: =",`"&R84&"` "&AC84&" "&IF(AJ84="Y","NOT NULL","")&" COMMENT '"&D84&"'" -> ,`VAT_CD` varchar(20) COMMENT 'ＶＡＴコード' | BR84: =",`"&R84&"` "&AC84&" "&IF(AJ84="Y","NOT NULL","") -> ,`VAT_CD` varchar(20) | BT84: =",`"&R84&"`" -> ,`VAT_CD` | BV84: =",A.`"&R84&"` = B.`"&R84&"`" -> ,A.`VAT_CD` = B.`VAT_CD` | BX84: =",`"&R84&"`" -> ,`VAT_CD` | BZ84: =",`"&R84&"`" -> ,`VAT_CD`
A85: @60 | B85: 9 | D85: Ｇ／Ｌ口座ナンバー | R85: GL_ACCT_ID | AC85: {=_xlfn.SWITCH(BM85,"String","varchar("&BN85&")","Long","int","Integer","smallint","Double","decimal(9,2)","Currency","int")} -> varchar(20) | AT85: 現在未使用 Ｎｕｌｌ固定 | BL85: =REPT("a"&CHAR(10)&"b",INT(LENB(SUBSTITUTE(AT85,CHAR(10),""))/70)+1) -> a b | BM85: String | BN85: 20 | BP85: =",`"&R85&"` "&AC85&" "&IF(AJ85="Y","NOT NULL","")&" COMMENT '"&D85&"'" -> ,`GL_ACCT_ID` varchar(20) COMMENT 'Ｇ／Ｌ口座ナンバー' | BR85: =",`"&R85&"` "&AC85&" "&IF(AJ85="Y","NOT NULL","") -> ,`GL_ACCT_ID` varchar(20) | BT85: =",`"&R85&"`" -> ,`GL_ACCT_ID` | BV85: =",A.`"&R85&"` = B.`"&R85&"`" -> ,A.`GL_ACCT_ID` = B.`GL_ACCT_ID` | BX85: =",`"&R85&"`" -> ,`GL_ACCT_ID` | BZ85: =",`"&R85&"`" -> ,`GL_ACCT_ID`
A86: @61 | B86: 9 | D86: 商品グループコード | R86: ITM_GRP_CD | AC86: {=_xlfn.SWITCH(BM86,"String","varchar("&BN86&")","Long","int","Integer","smallint","Double","decimal(9,2)","Currency","int")} -> smallint | AT86: 現在未使用 ０固定 | BL86: =REPT("a"&CHAR(10)&"b",INT(LENB(SUBSTITUTE(AT86,CHAR(10),""))/70)+1) -> a b | BM86: Integer | BP86: =",`"&R86&"` "&AC86&" "&IF(AJ86="Y","NOT NULL","")&" COMMENT '"&D86&"'" -> ,`ITM_GRP_CD` smallint COMMENT '商品グループコード' | BR86: =",`"&R86&"` "&AC86&" "&IF(AJ86="Y","NOT NULL","") -> ,`ITM_GRP_CD` smallint | BT86: =",`"&R86&"`" -> ,`ITM_GRP_CD` | BV86: =",A.`"&R86&"` = B.`"&R86&"`" -> ,A.`ITM_GRP_CD` = B.`ITM_GRP_CD` | BX86: =",`"&R86&"`" -> ,`ITM_GRP_CD` | BZ86: =",`"&R86&"`" -> ,`ITM_GRP_CD`
A87: @62 | B87: 9 | D87: 非商品フラグ | R87: NON_MDSE_FG | AC87: {=_xlfn.SWITCH(BM87,"String","varchar("&BN87&")","Long","int","Integer","smallint","Double","decimal(9,2)","Currency","int")} -> smallint | AT87: 現在０固定 ０：商品 １：非商品 | BL87: =REPT("a"&CHAR(10)&"b",INT(LENB(SUBSTITUTE(AT87,CHAR(10),""))/70)+1) -> a b | BM87: Integer | BP87: =",`"&R87&"` "&AC87&" "&IF(AJ87="Y","NOT NULL","")&" COMMENT '"&D87&"'" -> ,`NON_MDSE_FG` smallint COMMENT '非商品フラグ' | BR87: =",`"&R87&"` "&AC87&" "&IF(AJ87="Y","NOT NULL","") -> ,`NON_MDSE_FG` smallint | BT87: =",`"&R87&"`" -> ,`NON_MDSE_FG` | BV87: =",A.`"&R87&"` = B.`"&R87&"`" -> ,A.`NON_MDSE_FG` = B.`NON_MDSE_FG` | BX87: =",`"&R87&"`" -> ,`NON_MDSE_FG` | BZ87: =",`"&R87&"`" -> ,`NON_MDSE_FG`
A88: @63 | B88: 9 | D88: プロモーション割引 | R88: PROMO_EXCL_DISC | AC88: {=_xlfn.SWITCH(BM88,"String","varchar("&BN88&")","Long","int","Integer","smallint","Double","decimal(9,2)","Currency","int")} -> smallint | AT88: 現在未使用 ０固定 | BL88: =REPT("a"&CHAR(10)&"b",INT(LENB(SUBSTITUTE(AT88,CHAR(10),""))/70)+1) -> a b | BM88: Integer | BP88: =",`"&R88&"` "&AC88&" "&IF(AJ88="Y","NOT NULL","")&" COMMENT '"&D88&"'" -> ,`PROMO_EXCL_DISC` smallint COMMENT 'プロモーション割引' | BR88: =",`"&R88&"` "&AC88&" "&IF(AJ88="Y","NOT NULL","") -> ,`PROMO_EXCL_DISC` smallint | BT88: =",`"&R88&"`" -> ,`PROMO_EXCL_DISC` | BV88: =",A.`"&R88&"` = B.`"&R88&"`" -> ,A.`PROMO_EXCL_DISC` = B.`PROMO_EXCL_DISC` | BX88: =",`"&R88&"`" -> ,`PROMO_EXCL_DISC` | BZ88: =",`"&R88&"`" -> ,`PROMO_EXCL_DISC`
A89: @64 | B89: 9 | D89: 契約申込 | R89: DEAL_EXCL_OFFER | AC89: {=_xlfn.SWITCH(BM89,"String","varchar("&BN89&")","Long","int","Integer","smallint","Double","decimal(9,2)","Currency","int")} -> smallint | AT89: 現在未使用 ０固定 | BL89: =REPT("a"&CHAR(10)&"b",INT(LENB(SUBSTITUTE(AT89,CHAR(10),""))/70)+1) -> a b | BM89: Integer | BP89: =",`"&R89&"` "&AC89&" "&IF(AJ89="Y","NOT NULL","")&" COMMENT '"&D89&"'" -> ,`DEAL_EXCL_OFFER` smallint COMMENT '契約申込' | BR89: =",`"&R89&"` "&AC89&" "&IF(AJ89="Y","NOT NULL","") -> ,`DEAL_EXCL_OFFER` smallint | BT89: =",`"&R89&"`" -> ,`DEAL_EXCL_OFFER` | BV89: =",A.`"&R89&"` = B.`"&R89&"`" -> ,A.`DEAL_EXCL_OFFER` = B.`DEAL_EXCL_OFFER` | BX89: =",`"&R89&"`" -> ,`DEAL_EXCL_OFFER` | BZ89: =",`"&R89&"`" -> ,`DEAL_EXCL_OFFER`
A90: @65 | B90: 9 | D90: 契約値引 | R90: DEAL_EXCL_DISC | AC90: {=_xlfn.SWITCH(BM90,"String","varchar("&BN90&")","Long","int","Integer","smallint","Double","decimal(9,2)","Currency","int")} -> smallint | AT90: 現在未使用 ０固定 | BL90: =REPT("a"&CHAR(10)&"b",INT(LENB(SUBSTITUTE(AT90,CHAR(10),""))/70)+1) -> a b | BM90: Integer | BP90: =",`"&R90&"` "&AC90&" "&IF(AJ90="Y","NOT NULL","")&" COMMENT '"&D90&"'" -> ,`DEAL_EXCL_DISC` smallint COMMENT '契約値引' | BR90: =",`"&R90&"` "&AC90&" "&IF(AJ90="Y","NOT NULL","") -> ,`DEAL_EXCL_DISC` smallint | BT90: =",`"&R90&"`" -> ,`DEAL_EXCL_DISC` | BV90: =",A.`"&R90&"` = B.`"&R90&"`" -> ,A.`DEAL_EXCL_DISC` = B.`DEAL_EXCL_DISC` | BX90: =",`"&R90&"`" -> ,`DEAL_EXCL_DISC` | BZ90: =",`"&R90&"`" -> ,`DEAL_EXCL_DISC`
A91: @66 | B91: 9 | D91: 契約最高数量 | R91: DEAL_MAX_QTY | AC91: {=_xlfn.SWITCH(BM91,"String","varchar("&BN91&")","Long","int","Integer","smallint","Double","decimal(9,2)","Currency","int")} -> decimal(9,2) | AT91: 現在未使用 ０固定 | BL91: =REPT("a"&CHAR(10)&"b",INT(LENB(SUBSTITUTE(AT91,CHAR(10),""))/70)+1) -> a b | BM91: Double | BP91: =",`"&R91&"` "&AC91&" "&IF(AJ91="Y","NOT NULL","")&" COMMENT '"&D91&"'" -> ,`DEAL_MAX_QTY` decimal(9,2) COMMENT '契約最高数量' | BR91: =",`"&R91&"` "&AC91&" "&IF(AJ91="Y","NOT NULL","") -> ,`DEAL_MAX_QTY` decimal(9,2) | BT91: =",`"&R91&"`" -> ,`DEAL_MAX_QTY` | BV91: =",A.`"&R91&"` = B.`"&R91&"`" -> ,A.`DEAL_MAX_QTY` = B.`DEAL_MAX_QTY` | BX91: =",`"&R91&"`" -> ,`DEAL_MAX_QTY` | BZ91: =",`"&R91&"`" -> ,`DEAL_MAX_QTY`
A92: @67 | B92: 9 | D92: プロモーション最高価格 | R92: PROMO_DEAL_MAX_QTY | AC92: {=_xlfn.SWITCH(BM92,"String","varchar("&BN92&")","Long","int","Integer","smallint","Double","decimal(9,2)","Currency","int")} -> decimal(9,2) | AT92: 現在未使用 ０固定 | BL92: =REPT("a"&CHAR(10)&"b",INT(LENB(SUBSTITUTE(AT92,CHAR(10),""))/70)+1) -> a b | BM92: Double | BP92: =",`"&R92&"` "&AC92&" "&IF(AJ92="Y","NOT NULL","")&" COMMENT '"&D92&"'" -> ,`PROMO_DEAL_MAX_QTY` decimal(9,2) COMMENT 'プロモーション最高価格' | BR92: =",`"&R92&"` "&AC92&" "&IF(AJ92="Y","NOT NULL","") -> ,`PROMO_DEAL_MAX_QTY` decimal(9,2) | BT92: =",`"&R92&"`" -> ,`PROMO_DEAL_MAX_QTY` | BV92: =",A.`"&R92&"` = B.`"&R92&"`" -> ,A.`PROMO_DEAL_MAX_QTY` = B.`PROMO_DEAL_MAX_QTY` | BX92: =",`"&R92&"`" -> ,`PROMO_DEAL_MAX_QTY` | BZ92: =",`"&R92&"`" -> ,`PROMO_DEAL_MAX_QTY`
A93: @68 | B93: 9 | D93: 値引商品 | R93: LINK_ITM_FG | AC93: {=_xlfn.SWITCH(BM93,"String","varchar("&BN93&")","Long","int","Integer","smallint","Double","decimal(9,2)","Currency","int")} -> smallint | AT93: 現在未使用 ０固定 | BL93: =REPT("a"&CHAR(10)&"b",INT(LENB(SUBSTITUTE(AT93,CHAR(10),""))/70)+1) -> a b | BM93: Integer | BP93: =",`"&R93&"` "&AC93&" "&IF(AJ93="Y","NOT NULL","")&" COMMENT '"&D93&"'" -> ,`LINK_ITM_FG` smallint COMMENT '値引商品' | BR93: =",`"&R93&"` "&AC93&" "&IF(AJ93="Y","NOT NULL","") -> ,`LINK_ITM_FG` smallint | BT93: =",`"&R93&"`" -> ,`LINK_ITM_FG` | BV93: =",A.`"&R93&"` = B.`"&R93&"`" -> ,A.`LINK_ITM_FG` = B.`LINK_ITM_FG` | BX93: =",`"&R93&"`" -> ,`LINK_ITM_FG` | BZ93: =",`"&R93&"`" -> ,`LINK_ITM_FG`
A94: @69 | B94: 9 | D94: 購買制限グループ | R94: PRCH_RSTRCT_GRP_ID | AC94: {=_xlfn.SWITCH(BM94,"String","varchar("&BN94&")","Long","int","Integer","smallint","Double","decimal(9,2)","Currency","int")} -> int | AT94: 現在未使用 ０固定 | BL94: =REPT("a"&CHAR(10)&"b",INT(LENB(SUBSTITUTE(AT94,CHAR(10),""))/70)+1) -> a b | BM94: Long | BP94: =",`"&R94&"` "&AC94&" "&IF(AJ94="Y","NOT NULL","")&" COMMENT '"&D94&"'" -> ,`PRCH_RSTRCT_GRP_ID` int COMMENT '購買制限グループ' | BR94: =",`"&R94&"` "&AC94&" "&IF(AJ94="Y","NOT NULL","") -> ,`PRCH_RSTRCT_GRP_ID` int | BT94: =",`"&R94&"`" -> ,`PRCH_RSTRCT_GRP_ID` | BV94: =",A.`"&R94&"` = B.`"&R94&"`" -> ,A.`PRCH_RSTRCT_GRP_ID` = B.`PRCH_RSTRCT_GRP_ID` | BX94: =",`"&R94&"`" -> ,`PRCH_RSTRCT_GRP_ID` | BZ94: =",`"&R94&"`" -> ,`PRCH_RSTRCT_GRP_ID`
A95: @70 | B95: 9 | D95: テナントフラグ | R95: STR_FG | AC95: {=_xlfn.SWITCH(BM95,"String","varchar("&BN95&")","Long","int","Integer","smallint","Double","decimal(9,2)","Currency","int")} -> smallint | AT95: 現在０固定 ０：テナントなし １：テナントあり | BL95: =REPT("a"&CHAR(10)&"b",INT(LENB(SUBSTITUTE(AT95,CHAR(10),""))/70)+1) -> a b | BM95: Integer | BP95: =",`"&R95&"` "&AC95&" "&IF(AJ95="Y","NOT NULL","")&" COMMENT '"&D95&"'" -> ,`STR_FG` smallint COMMENT 'テナントフラグ' | BR95: =",`"&R95&"` "&AC95&" "&IF(AJ95="Y","NOT NULL","") -> ,`STR_FG` smallint | BT95: =",`"&R95&"`" -> ,`STR_FG` | BV95: =",A.`"&R95&"` = B.`"&R95&"`" -> ,A.`STR_FG` = B.`STR_FG` | BX95: =",`"&R95&"`" -> ,`STR_FG` | BZ95: =",`"&R95&"`" -> ,`STR_FG`
A96: @71 | B96: 9 | D96: ＰＬＵ属性の有無 | R96: PLU_QUAL_CD | AC96: {=_xlfn.SWITCH(BM96,"String","varchar("&BN96&")","Long","int","Integer","smallint","Double","decimal(9,2)","Currency","int")} -> smallint | AT96: 現在０固定 ０：ＰＬＵ属性なし １：ＰＬＵ属性あり | BL96: =REPT("a"&CHAR(10)&"b",INT(LENB(SUBSTITUTE(AT96,CHAR(10),""))/70)+1) -> a b | BM96: Integer | BP96: =",`"&R96&"` "&AC96&" "&IF(AJ96="Y","NOT NULL","")&" COMMENT '"&D96&"'" -> ,`PLU_QUAL_CD` smallint COMMENT 'ＰＬＵ属性の有無' | BR96: =",`"&R96&"` "&AC96&" "&IF(AJ96="Y","NOT NULL","") -> ,`PLU_QUAL_CD` smallint | BT96: =",`"&R96&"`" -> ,`PLU_QUAL_CD` | BV96: =",A.`"&R96&"` = B.`"&R96&"`" -> ,A.`PLU_QUAL_CD` = B.`PLU_QUAL_CD` | BX96: =",`"&R96&"`" -> ,`PLU_QUAL_CD` | BZ96: =",`"&R96&"`" -> ,`PLU_QUAL_CD`
A97: @72 | B97: 9 | D97: 取引遅延のロケーションコード | R97: DFLT_DP_LOC_ID | AC97: {=_xlfn.SWITCH(BM97,"String","varchar("&BN97&")","Long","int","Integer","smallint","Double","decimal(9,2)","Currency","int")} -> varchar(20) | AT97: 現在未使用 Ｎull固定 | BL97: =REPT("a"&CHAR(10)&"b",INT(LENB(SUBSTITUTE(AT97,CHAR(10),""))/70)+1) -> a b | BM97: String | BN97: 20 | BP97: =",`"&R97&"` "&AC97&" "&IF(AJ97="Y","NOT NULL","")&" COMMENT '"&D97&"'" -> ,`DFLT_DP_LOC_ID` varchar(20) COMMENT '取引遅延のロケーションコード' | BR97: =",`"&R97&"` "&AC97&" "&IF(AJ97="Y","NOT NULL","") -> ,`DFLT_DP_LOC_ID` varchar(20) | BT97: =",`"&R97&"`" -> ,`DFLT_DP_LOC_ID` | BV97: =",A.`"&R97&"` = B.`"&R97&"`" -> ,A.`DFLT_DP_LOC_ID` = B.`DFLT_DP_LOC_ID` | BX97: =",`"&R97&"`" -> ,`DFLT_DP_LOC_ID` | BZ97: =",`"&R97&"`" -> ,`DFLT_DP_LOC_ID`
A98: @73 | B98: 9 | D98: 支払制限フラグ | R98: TND_RSTRCT_FG | AC98: {=_xlfn.SWITCH(BM98,"String","varchar("&BN98&")","Long","int","Integer","smallint","Double","decimal(9,2)","Currency","int")} -> smallint | AT98: 現在未使用 ０固定 | BL98: =REPT("a"&CHAR(10)&"b",INT(LENB(SUBSTITUTE(AT98,CHAR(10),""))/70)+1) -> a b | BM98: Integer | BP98: =",`"&R98&"` "&AC98&" "&IF(AJ98="Y","NOT NULL","")&" COMMENT '"&D98&"'" -> ,`TND_RSTRCT_FG` smallint COMMENT '支払制限フラグ' | BR98: =",`"&R98&"` "&AC98&" "&IF(AJ98="Y","NOT NULL","") -> ,`TND_RSTRCT_FG` smallint | BT98: =",`"&R98&"`" -> ,`TND_RSTRCT_FG` | BV98: =",A.`"&R98&"` = B.`"&R98&"`" -> ,A.`TND_RSTRCT_FG` = B.`TND_RSTRCT_FG` | BX98: =",`"&R98&"`" -> ,`TND_RSTRCT_FG` | BZ98: =",`"&R98&"`" -> ,`TND_RSTRCT_FG`
A99: @74 | B99: 9 | D99: 割引コード | R99: DISC_CD | AC99: {=_xlfn.SWITCH(BM99,"String","varchar("&BN99&")","Long","int","Integer","smallint","Double","decimal(9,2)","Currency","int")} -> smallint | AT99: 現在未使用 ０固定 | BL99: =REPT("a"&CHAR(10)&"b",INT(LENB(SUBSTITUTE(AT99,CHAR(10),""))/70)+1) -> a b | BM99: Integer | BP99: =",`"&R99&"` "&AC99&" "&IF(AJ99="Y","NOT NULL","")&" COMMENT '"&D99&"'" -> ,`DISC_CD` smallint COMMENT '割引コード' | BR99: =",`"&R99&"` "&AC99&" "&IF(AJ99="Y","NOT NULL","") -> ,`DISC_CD` smallint | BT99: =",`"&R99&"`" -> ,`DISC_CD` | BV99: =",A.`"&R99&"` = B.`"&R99&"`" -> ,A.`DISC_CD` = B.`DISC_CD` | BX99: =",`"&R99&"`" -> ,`DISC_CD` | BZ99: =",`"&R99&"`" -> ,`DISC_CD`
A100: @75 | B100: 9 | D100: 会員価格 | R100: GSFD_MBR_PRC | AC100: {=_xlfn.SWITCH(BM100,"String","varchar("&BN100&")","Long","int","Integer","smallint","Double","decimal(9,2)","Currency","int")} -> int | AT100: 会員価格は未使用時は０とする | BL100: =REPT("a"&CHAR(10)&"b",INT(LENB(SUBSTITUTE(AT100,CHAR(10),""))/70)+1) -> a b | BM100: Currency | BP100: =",`"&R100&"` "&AC100&" "&IF(AJ100="Y","NOT NULL","")&" COMMENT '"&D100&"'" -> ,`GSFD_MBR_PRC` int COMMENT '会員価格' | BR100: =",`"&R100&"` "&AC100&" "&IF(AJ100="Y","NOT NULL","") -> ,`GSFD_MBR_PRC` int | BT100: =",`"&R100&"`" -> ,`GSFD_MBR_PRC` | BV100: =",A.`"&R100&"` = B.`"&R100&"`" -> ,A.`GSFD_MBR_PRC` = B.`GSFD_MBR_PRC` | BX100: =",`"&R100&"`" -> ,`GSFD_MBR_PRC` | BZ100: =",`"&R100&"`" -> ,`GSFD_MBR_PRC`
A101: @76 | B101: 9 | D101: 単品値引除外 | R101: GSFD_MINL_DISC_ITEM_EXCL_FG | AC101: {=_xlfn.SWITCH(BM101,"String","varchar("&BN101&")","Long","int","Integer","smallint","Double","decimal(9,2)","Currency","int")} -> smallint | AT101: ０：ﾏﾆｭｱﾙ値引除外しない＋自動値引除外しない１：ﾏﾆｭｱﾙ値引除外（一般対象）＋自動値引除外しない ３：ﾏﾆｭｱﾙ値引除外（一般＆会員対象）＋自動値引除外しない ４：ﾏﾆｭｱﾙ値引除外しない＋自動値引除外 ５：ﾏﾆｭｱﾙ値引（一般）＋自動値引除外 ６：ﾏﾆｭｱﾙ値引除外（一般＆会員）＋自動値引除外 | BL101: =REPT("a"&CHAR(10)&"b",INT(LENB(SUBSTITUTE(AT101,CHAR(10),""))/70)+1) -> a ba ba ba b | BM101: Integer | BP101: =",`"&R101&"` "&AC101&" "&IF(AJ101="Y","NOT NULL","")&" COMMENT '"&D101&"'" -> ,`GSFD_MINL_DISC_ITEM_EXCL_FG` smallint COMMENT '単品値引除外' | BR101: =",`"&R101&"` "&AC101&" "&IF(AJ101="Y","NOT NULL","") -> ,`GSFD_MINL_DISC_ITEM_EXCL_FG` smallint | BT101: =",`"&R101&"`" -> ,`GSFD_MINL_DISC_ITEM_EXCL_FG` | BV101: =",A.`"&R101&"` = B.`"&R101&"`" -> ,A.`GSFD_MINL_DISC_ITEM_EXCL_FG` = B.`GSFD_MINL_DISC_ITEM_EXCL_FG` | BX101: =",`"&R101&"`" -> ,`GSFD_MINL_DISC_ITEM_EXCL_FG` | BZ101: =",`"&R101&"`" -> ,`GSFD_MINL_DISC_ITEM_EXCL_FG`
A102: @77 | B102: 9 | D102: 小計マニュアル値引除外 | R102: GSFD_MINL_DISC_TRAN_EXCL_FG | AC102: {=_xlfn.SWITCH(BM102,"String","varchar("&BN102&")","Long","int","Integer","smallint","Double","decimal(9,2)","Currency","int")} -> smallint | AT102: ０：対象外 １：一般対象 ３：一般＆会員対象 | BL102: =REPT("a"&CHAR(10)&"b",INT(LENB(SUBSTITUTE(AT102,CHAR(10),""))/70)+1) -> a b | BM102: Integer | BP102: =",`"&R102&"` "&AC102&" "&IF(AJ102="Y","NOT NULL","")&" COMMENT '"&D102&"'" -> ,`GSFD_MINL_DISC_TRAN_EXCL_FG` smallint COMMENT '小計マニュアル値引除外' | BR102: =",`"&R102&"` "&AC102&" "&IF(AJ102="Y","NOT NULL","") -> ,`GSFD_MINL_DISC_TRAN_EXCL_FG` smallint | BT102: =",`"&R102&"`" -> ,`GSFD_MINL_DISC_TRAN_EXCL_FG` | BV102: =",A.`"&R102&"` = B.`"&R102&"`" -> ,A.`GSFD_MINL_DISC_TRAN_EXCL_FG` = B.`GSFD_MINL_DISC_TRAN_EXCL_FG` | BX102: =",`"&R102&"`" -> ,`GSFD_MINL_DISC_TRAN_EXCL_FG` | BZ102: =",`"&R102&"`" -> ,`GSFD_MINL_DISC_TRAN_EXCL_FG`
A103: @78 | B103: 9 | D103: 会員価格方式 | R103: MBR_MTHD | AC103: {=_xlfn.SWITCH(BM103,"String","varchar("&BN103&")","Long","int","Integer","smallint","Double","decimal(9,2)","Currency","int")} -> smallint | AT103: 現在６固定 １：値引額 ２：％値引 ６：新売価 | BL103: =REPT("a"&CHAR(10)&"b",INT(LENB(SUBSTITUTE(AT103,CHAR(10),""))/70)+1) -> a b | BM103: Integer | BP103: =",`"&R103&"` "&AC103&" "&IF(AJ103="Y","NOT NULL","")&" COMMENT '"&D103&"'" -> ,`MBR_MTHD` smallint COMMENT '会員価格方式' | BR103: =",`"&R103&"` "&AC103&" "&IF(AJ103="Y","NOT NULL","") -> ,`MBR_MTHD` smallint | BT103: =",`"&R103&"`" -> ,`MBR_MTHD` | BV103: =",A.`"&R103&"` = B.`"&R103&"`" -> ,A.`MBR_MTHD` = B.`MBR_MTHD` | BX103: =",`"&R103&"`" -> ,`MBR_MTHD` | BZ103: =",`"&R103&"`" -> ,`MBR_MTHD`
A104: @79 | B104: 9 | D104: 仕入数 | R104: RCVD_QTY | AC104: {=_xlfn.SWITCH(BM104,"String","varchar("&BN104&")","Long","int","Integer","smallint","Double","decimal(9,2)","Currency","int")} -> int | BL104: =REPT("a"&CHAR(10)&"b",INT(LENB(SUBSTITUTE(AT104,CHAR(10),""))/70)+1) -> a b | BM104: Long | BP104: =",`"&R104&"` "&AC104&" "&IF(AJ104="Y","NOT NULL","")&" COMMENT '"&D104&"'" -> ,`RCVD_QTY` int COMMENT '仕入数' | BR104: =",`"&R104&"` "&AC104&" "&IF(AJ104="Y","NOT NULL","") -> ,`RCVD_QTY` int | BT104: =",`"&R104&"`" -> ,`RCVD_QTY` | BV104: =",A.`"&R104&"` = B.`"&R104&"`" -> ,A.`RCVD_QTY` = B.`RCVD_QTY` | BX104: =",`"&R104&"`" -> ,`RCVD_QTY` | BZ104: =",`"&R104&"`" -> ,`RCVD_QTY`
A105: @80 | B105: 9 | D105: 在庫数 | R105: INV_QTY | AC105: {=_xlfn.SWITCH(BM105,"String","varchar("&BN105&")","Long","int","Integer","smallint","Double","decimal(9,2)","Currency","int")} -> int | BL105: =REPT("a"&CHAR(10)&"b",INT(LENB(SUBSTITUTE(AT105,CHAR(10),""))/70)+1) -> a b | BM105: Long | BP105: =",`"&R105&"` "&AC105&" "&IF(AJ105="Y","NOT NULL","")&" COMMENT '"&D105&"'" -> ,`INV_QTY` int COMMENT '在庫数' | BR105: =",`"&R105&"` "&AC105&" "&IF(AJ105="Y","NOT NULL","") -> ,`INV_QTY` int | BT105: =",`"&R105&"`" -> ,`INV_QTY` | BV105: =",A.`"&R105&"` = B.`"&R105&"`" -> ,A.`INV_QTY` = B.`INV_QTY` | BX105: =",`"&R105&"`" -> ,`INV_QTY` | BZ105: =",`"&R105&"`" -> ,`INV_QTY`
A106: @81 | B106: 9 | D106: 登録日 | R106: ENTRY_DY | AC106: {=_xlfn.SWITCH(BM106,"String","varchar("&BN106&")","Long","int","Integer","smallint","Double","decimal(9,2)","Currency","int")} -> varchar(8) | AT106: 現在未使用 Ｎｕｌｌ固定 | BL106: =REPT("a"&CHAR(10)&"b",INT(LENB(SUBSTITUTE(AT106,CHAR(10),""))/70)+1) -> a b | BM106: String | BN106: 8 | BP106: =",`"&R106&"` "&AC106&" "&IF(AJ106="Y","NOT NULL","")&" COMMENT '"&D106&"'" -> ,`ENTRY_DY` varchar(8) COMMENT '登録日' | BR106: =",`"&R106&"` "&AC106&" "&IF(AJ106="Y","NOT NULL","") -> ,`ENTRY_DY` varchar(8) | BT106: =",`"&R106&"`" -> ,`ENTRY_DY` | BV106: =",A.`"&R106&"` = B.`"&R106&"`" -> ,A.`ENTRY_DY` = B.`ENTRY_DY` | BX106: =",`"&R106&"`" -> ,`ENTRY_DY` | BZ106: =",`"&R106&"`" -> ,`ENTRY_DY`
A107: @82 | B107: 9 | D107: 最終売上日 | R107: LST_SLS_DY | AC107: {=_xlfn.SWITCH(BM107,"String","varchar("&BN107&")","Long","int","Integer","smallint","Double","decimal(9,2)","Currency","int")} -> varchar(8) | AT107: 現在未使用 Ｎｕｌｌ固定 | BL107: =REPT("a"&CHAR(10)&"b",INT(LENB(SUBSTITUTE(AT107,CHAR(10),""))/70)+1) -> a b | BM107: String | BN107: 8 | BP107: =",`"&R107&"` "&AC107&" "&IF(AJ107="Y","NOT NULL","")&" COMMENT '"&D107&"'" -> ,`LST_SLS_DY` varchar(8) COMMENT '最終売上日' | BR107: =",`"&R107&"` "&AC107&" "&IF(AJ107="Y","NOT NULL","") -> ,`LST_SLS_DY` varchar(8) | BT107: =",`"&R107&"`" -> ,`LST_SLS_DY` | BV107: =",A.`"&R107&"` = B.`"&R107&"`" -> ,A.`LST_SLS_DY` = B.`LST_SLS_DY` | BX107: =",`"&R107&"`" -> ,`LST_SLS_DY` | BZ107: =",`"&R107&"`" -> ,`LST_SLS_DY`
A108: @83 | B108: 9 | D108: 定価 | R108: REG_PRC | AC108: {=_xlfn.SWITCH(BM108,"String","varchar("&BN108&")","Long","int","Integer","smallint","Double","decimal(9,2)","Currency","int")} -> int | AT108: 希望小売価格 | BL108: =REPT("a"&CHAR(10)&"b",INT(LENB(SUBSTITUTE(AT108,CHAR(10),""))/70)+1) -> a b | BM108: Currency | BP108: =",`"&R108&"` "&AC108&" "&IF(AJ108="Y","NOT NULL","")&" COMMENT '"&D108&"'" -> ,`REG_PRC` int COMMENT '定価' | BR108: =",`"&R108&"` "&AC108&" "&IF(AJ108="Y","NOT NULL","") -> ,`REG_PRC` int | BT108: =",`"&R108&"`" -> ,`REG_PRC` | BV108: =",A.`"&R108&"` = B.`"&R108&"`" -> ,A.`REG_PRC` = B.`REG_PRC` | BX108: =",`"&R108&"`" -> ,`REG_PRC` | BZ108: =",`"&R108&"`" -> ,`REG_PRC`
A109: @84 | B109: 9 | D109: スキャンコード | R109: SCAN_ID | AC109: {=_xlfn.SWITCH(BM109,"String","varchar("&BN109&")","Long","int","Integer","smallint","Double","decimal(9,2)","Currency","int")} -> varchar(24) | AT109: 左詰 | BL109: =REPT("a"&CHAR(10)&"b",INT(LENB(SUBSTITUTE(AT109,CHAR(10),""))/70)+1) -> a b | BM109: String | BN109: 24 | BP109: =",`"&R109&"` "&AC109&" "&IF(AJ109="Y","NOT NULL","")&" COMMENT '"&D109&"'" -> ,`SCAN_ID` varchar(24) COMMENT 'スキャンコード' | BR109: =",`"&R109&"` "&AC109&" "&IF(AJ109="Y","NOT NULL","") -> ,`SCAN_ID` varchar(24) | BT109: =",`"&R109&"`" -> ,`SCAN_ID` | BV109: =",A.`"&R109&"` = B.`"&R109&"`" -> ,A.`SCAN_ID` = B.`SCAN_ID` | BX109: =",`"&R109&"`" -> ,`SCAN_ID` | BZ109: =",`"&R109&"`" -> ,`SCAN_ID`
A110: @85 | B110: 9 | D110: ＰＬＵタイプ | R110: SCAN_TYP | AC110: {=_xlfn.SWITCH(BM110,"String","varchar("&BN110&")","Long","int","Integer","smallint","Double","decimal(9,2)","Currency","int")} -> smallint | AT110: 現在未使用 ０固定 | BL110: =REPT("a"&CHAR(10)&"b",INT(LENB(SUBSTITUTE(AT110,CHAR(10),""))/70)+1) -> a b | BM110: Integer | BP110: =",`"&R110&"` "&AC110&" "&IF(AJ110="Y","NOT NULL","")&" COMMENT '"&D110&"'" -> ,`SCAN_TYP` smallint COMMENT 'ＰＬＵタイプ' | BR110: =",`"&R110&"` "&AC110&" "&IF(AJ110="Y","NOT NULL","") -> ,`SCAN_TYP` smallint | BT110: =",`"&R110&"`" -> ,`SCAN_TYP` | BV110: =",A.`"&R110&"` = B.`"&R110&"`" -> ,A.`SCAN_TYP` = B.`SCAN_TYP` | BX110: =",`"&R110&"`" -> ,`SCAN_TYP` | BZ110: =",`"&R110&"`" -> ,`SCAN_TYP`
...

Sheet 特売メンテ
A1: システム名 | K1: システム種別 | W1: =IF(表紙!W1="","",表紙!W1) -> DB定義書 | AP1: 作成者 | AT1: 作成日 | AY1: 更新者 | BC1: 更新日 | BH1: 版数
A2: =IF(表紙!A2="","",表紙!A2) -> 現金専用簡易セルフPOS | K2: =IF(表紙!K2="","",表紙!K2) | AP2: =IF(表紙!AP2="","",表紙!AP2) -> きよはら | AT2: =IF(表紙!AT2="","",表紙!AT2) -> 44652 | AY2: =IF(表紙!AY2="","",表紙!AY2) -> Thanh Nguyên | BC2: =IF(表紙!BC2="","",表紙!BC2) -> 45285 | BH2: =IF(表紙!BH2="","",表紙!BH2) -> 0.2
A4: 機能カテゴリ | H4: =IF(表紙!H4="","",表紙!H4) -> 共通 | U4: 項目 | Z4: =IF(表紙!Z4="","",表紙!Z4) | AP4: テンプレート
B7: ■テーブル情報
B8: スキーマ名 | G8: Replica_Kasumi | Y8: RDBMS名
B9: 論理名 | G9: 特売メンテ | Y9: バージョン
B10: 物理名 | G10: GHDISCOUNTM
B11: 備考
B19: ■カラム情報 | BP19: ="DROP TABLE IF EXISTS `"&$G$8&"`.`"&$G$10&"`;" -> DROP TABLE IF EXISTS `Replica_Kasumi`.`GHDISCOUNTM`; | BQ19: DROP TABLE IF EXISTS `Replica_Kasumi`.`GHDISCOUNTM`;
B20: No. | D20: 論理名 | R20: 物理名 | AC20: データ型 | AH20: PK | AJ20: Not Null | AM20: デフォルト | AT20: 備考 | BP20: ="CREATE TABLE `"&$G$8&"`.`"&$G$10&"` (" -> CREATE TABLE `Replica_Kasumi`.`GHDISCOUNTM` ( | BQ20: CREATE TABLE `Replica_Kasumi`.`ghdiscountm` (
B21: 1 | D21: レコードID | R21: RECORD_ID | AC21: bigint | AJ21: Y | AM21: 自動追加 | BP21: `RECORD_ID` bigint NOT NULL AUTO_INCREMENT COMMENT 'レコードID' | BQ21: `RECORD_ID` bigint NOT NULL AUTO_INCREMENT COMMENT 'レコードID',
B22: =B21+1 -> 2 | D22: レコード作成日付 | R22: RECORD_CREATE_DATE | AC22: date | AJ22: Y | AM22: CURRENT_DATE | BP22: ,`RECORD_CREATE_DATE` date NOT NULL COMMENT 'レコード作成日付' | BQ22: `RECORD_CREATE_DATE` date NOT NULL COMMENT 'レコード作成日付',
B23: =B22+1 -> 3 | D23: レコード作成時間 | R23: RECORD_CREATE_TIME | AC23: time | AJ23: Y | AM23: CURRENT_TIME | BP23: ,`RECORD_CREATE_TIME` time NOT NULL COMMENT 'レコード作成時間' | BQ23: `RECORD_CREATE_TIME` time NOT NULL COMMENT 'レコード作成時間', | BV23: SET CHARACTER_SET_DATABASE = UTF8;
B24: =B23+1 -> 4 | D24: レコード更新日付 | R24: RECORD_UPDATE_DATE | AC24: date | AJ24: Y | AM24: CURRENT_DATE | AT24: トリガーにより更新 | BP24: ,`RECORD_UPDATE_DATE` date NOT NULL COMMENT 'レコード更新日付/トリガーにより更新' | BQ24: `RECORD_UPDATE_DATE` date NOT NULL COMMENT 'レコード更新日付/トリガーにより更新', | BV24: ="UPDATE `REPLICA_KASUMI`.`"&$G$10&"` A,`TMP`.`"&$G$10&"` B" -> UPDATE `REPLICA_KASUMI`.`GHDISCOUNTM` A,`TMP`.`GHDISCOUNTM` B
B25: =B24+1 -> 5 | D25: レコード更新時間 | R25: RECORD_UPDATE_TIME | AC25: time | AJ25: Y | AM25: CURRENT_TIME | AT25: トリガーにより更新 | BP25: ,`RECORD_UPDATE_TIME` time NOT NULL COMMENT 'レコード更新時間/トリガーにより更新' | BQ25: `RECORD_UPDATE_TIME` time NOT NULL COMMENT 'レコード更新時間/トリガーにより更新', | BR25: ="DROP TABLE IF EXISTS `TMP`.`"&$G$10&"`;" -> DROP TABLE IF EXISTS `TMP`.`GHDISCOUNTM`; | BT25: ="LOAD DATA INFILE 'C:/04_DATAFILE/"&$G$10&"/TMP/"&$G$10&".CSV' " -> LOAD DATA INFILE 'C:/04_DATAFILE/GHDISCOUNTM/TMP/GHDISCOUNTM.CSV' | BV25: SET
A26: @1 | B26: =B25+1 -> 6 | D26: レコード無効フラグ | R26: RECORD_VOID_FLAG | AC26: char(1) | AJ26: Y | AM26: "" | AT26: 0: 有効フラグ、 1:無効フラグ | BP26: ,`RECORD_VOID_FLAG` char(1) NOT NULL DEFAULT '' COMMENT 'レコード無効フラグ '''': 有効フラグ、 1:無効フラグ' | BQ26: `RECORD_VOID_FLAG` char(1) NOT NULL DEFAULT '' COMMENT 'レコード無効フラグ '''': 有効フラグ、 1:無効フラグ', | BR26: ="CREATE TABLE `TMP`.`"&G10&"` (" -> CREATE TABLE `TMP`.`GHDISCOUNTM` ( | BT26: ="REPLACE INTO TABLE TMP.`"&$G$10&"` FIELDS TERMINATED BY ',' ENCLOSED BY '\""' LINES TERMINATED BY '\r\n' (" -> REPLACE INTO TABLE TMP.`GHDISCOUNTM` FIELDS TERMINATED BY ',' ENCLOSED BY '\"' LINES TERMINATED BY '\r\n' ( | BX26: ="INSERT INTO `REPLICA_KASUMI`.`"&$G$10&"` (" -> INSERT INTO `REPLICA_KASUMI`.`GHDISCOUNTM` ( | BZ26: ) SELECT
A27: @2 | B27: 7 | D27: 処理区分 | R27: PRCS_TYP | AC27: {=_xlfn.SWITCH(BM27,"String","varchar("&BN27&")","Long","int","Integer","smallint","Double","decimal(9,2)","Currency","int")} -> varchar(1) | AT27: Ａ：登録 Ｕ：更新 Ｄ：削除 | BM27: String | BN27: 1 | BP27: =",`"&R27&"` "&AC27&" "&IF(AJ27="Y","NOT NULL","")&" COMMENT '"&D27&" "&AT27&"'" -> ,`PRCS_TYP` varchar(1) COMMENT '処理区分 Ａ：登録 Ｕ：更新 Ｄ：削除' | BQ27: `PRCS_TYP` varchar(1) DEFAULT NULL COMMENT '処理区分 Ａ：登録 Ｕ：更新 Ｄ：削除', | BR27: ="`"&R27&"` "&AC27&" "&IF(AJ27="Y","NOT NULL","") -> `PRCS_TYP` varchar(1) | BT27: ="`"&R27&"`" -> `PRCS_TYP` | BV27: ="A.`"&R27&"` = B.`"&R27&"`" -> A.`PRCS_TYP` = B.`PRCS_TYP` | BX27: ="`"&R27&"`" -> `PRCS_TYP` | BZ27: ="`"&R27&"`" -> `PRCS_TYP`
A28: @3 | B28: 8 | D28: 店舗コード | R28: STR_ID | AC28: {=_xlfn.SWITCH(BM28,"String","varchar("&BN28&")","Long","int","Integer","smallint","Double","decimal(9,2)","Currency","int")} -> int | AH28: 1 | AT28: ０は不可 | BM28: Long | BP28: =",`"&R28&"` "&AC28&" "&IF(AJ28="Y","NOT NULL","")&" COMMENT '"&D28&" "&AT28&"'" -> ,`STR_ID` int COMMENT '店舗コード ０は不可' | BQ28: `STR_ID` int NOT NULL COMMENT '店舗コード ０は不可', | BR28: =",`"&R28&"` "&AC28&" "&IF(AJ28="Y","NOT NULL","") -> ,`STR_ID` int | BT28: =",`"&R28&"`" -> ,`STR_ID` | BV28: =",A.`"&R28&"` = B.`"&R28&"`" -> ,A.`STR_ID` = B.`STR_ID` | BX28: =",`"&R28&"`" -> ,`STR_ID` | BZ28: =",`"&R28&"`" -> ,`STR_ID`
A29: @4 | B29: 9 | D29: 企画Ｎo． | R29: EVNT_NBR | AC29: {=_xlfn.SWITCH(BM29,"String","varchar("&BN29&")","Long","int","Integer","smallint","Double","decimal(9,2)","Currency","int")} -> varchar(7) | AH29: 2 | AT29: 左詰 企画マスタに存在すること | BM29: String | BN29: 7 | BP29: =",`"&R29&"` "&AC29&" "&IF(AJ29="Y","NOT NULL","")&" COMMENT '"&D29&" "&AT29&"'" -> ,`EVNT_NBR` varchar(7) COMMENT '企画Ｎo． 左詰 企画マスタに存在すること' | BQ29: `EVNT_NBR` varchar(7) CHARACTER SET utf8mb4 COLLATE utf8mb4_0900_ai_ci NOT NULL COMMENT '企画Ｎo． 左詰 企画マスタに存在すること', | BR29: =",`"&R29&"` "&AC29&" "&IF(AJ29="Y","NOT NULL","") -> ,`EVNT_NBR` varchar(7) | BT29: =",`"&R29&"`" -> ,`EVNT_NBR` | BV29: =",A.`"&R29&"` = B.`"&R29&"`" -> ,A.`EVNT_NBR` = B.`EVNT_NBR` | BX29: =",`"&R29&"`" -> ,`EVNT_NBR` | BZ29: =",`"&R29&"`" -> ,`EVNT_NBR`
A30: @5 | B30: 9 | D30: 会員フラグ | R30: MBR_FG | AC30: {=_xlfn.SWITCH(BM30,"String","varchar("&BN30&")","Long","int","Integer","smallint","Double","decimal(9,2)","Currency","int")} -> smallint | AH30: 6 | AT30: ０：一般特売 １：会員特売 | BM30: Integer | BP30: =",`"&R30&"` "&AC30&" "&IF(AJ30="Y","NOT NULL","")&" COMMENT '"&D30&" "&AT30&"'" -> ,`MBR_FG` smallint COMMENT '会員フラグ ０：一般特売 １：会員特売' | BQ30: `MBR_FG` smallint NOT NULL COMMENT '会員フラグ ０：一般特売 １：会員特売', | BR30: =",`"&R30&"` "&AC30&" "&IF(AJ30="Y","NOT NULL","") -> ,`MBR_FG` smallint | BT30: =",`"&R30&"`" -> ,`MBR_FG` | BV30: =",A.`"&R30&"` = B.`"&R30&"`" -> ,A.`MBR_FG` = B.`MBR_FG` | BX30: =",`"&R30&"`" -> ,`MBR_FG` | BZ30: =",`"&R30&"`" -> ,`MBR_FG`
A31: @6 | B31: 9 | D31: 商品コード | R31: PLU_ID | AC31: {=_xlfn.SWITCH(BM31,"String","varchar("&BN31&")","Long","int","Integer","smallint","Double","decimal(9,2)","Currency","int")} -> varchar(24) | AH31: 5 | AT31: 左詰 数字で最大19桁。 特にＰＬＵコードを使用しない場合はスキャンコードと同じ値を入れておくこと | BM31: String | BN31: 24 | BP31: =",`"&R31&"` "&AC31&" "&IF(AJ31="Y","NOT NULL","")&" COMMENT '"&D31&" "&AT31&"'" -> ,`PLU_ID` varchar(24) COMMENT '商品コード 左詰 数字で最大19桁。 特にＰＬＵコードを使用しない場合はスキャンコードと同じ値を入れておくこと' | BQ31: `PLU_ID` varchar(24) CHARACTER SET utf8mb4 COLLATE utf8mb4_0900_ai_ci NOT NULL COMMENT '商品コード 左詰 数字で最大19桁。 特にＰＬＵコードを使用しない場合はスキャンコードと同じ値を入れておくこと', | BR31: =",`"&R31&"` "&AC31&" "&IF(AJ31="Y","NOT NULL","") -> ,`PLU_ID` varchar(24) | BT31: =",`"&R31&"`" -> ,`PLU_ID` | BV31: =",A.`"&R31&"` = B.`"&R31&"`" -> ,A.`PLU_ID` = B.`PLU_ID` | BX31: =",`"&R31&"`" -> ,`PLU_ID` | BZ31: =",`"&R31&"`" -> ,`PLU_ID`
A32: @7 | B32: 9 | D32: 特売開始日 | R32: EVNT_BGN_TM | AC32: {=_xlfn.SWITCH(BM32,"String","varchar("&BN32&")","Long","int","Integer","smallint","Double","decimal(9,2)","Currency","int")} -> varchar(8) | AH32: 3 | AT32: ＹＹＹＹＭＭＤＤ形式で８桁フルに設定すること | BM32: String | BN32: 8 | BP32: =",`"&R32&"` "&AC32&" "&IF(AJ32="Y","NOT NULL","")&" COMMENT '"&D32&" "&AT32&"'" -> ,`EVNT_BGN_TM` varchar(8) COMMENT '特売開始日 ＹＹＹＹＭＭＤＤ形式で８桁フルに設定すること' | BQ32: `EVNT_BGN_TM` varchar(8) CHARACTER SET utf8mb4 COLLATE utf8mb4_0900_ai_ci NOT NULL COMMENT '特売開始日 ＹＹＹＹＭＭＤＤ形式で８桁フルに設定すること', | BR32: =",`"&R32&"` "&AC32&" "&IF(AJ32="Y","NOT NULL","") -> ,`EVNT_BGN_TM` varchar(8) | BT32: =",`"&R32&"`" -> ,`EVNT_BGN_TM` | BV32: =",A.`"&R32&"` = B.`"&R32&"`" -> ,A.`EVNT_BGN_TM` = B.`EVNT_BGN_TM` | BX32: =",`"&R32&"`" -> ,`EVNT_BGN_TM` | BZ32: =",`"&R32&"`" -> ,`EVNT_BGN_TM`
A33: @8 | B33: 9 | D33: 特売終了日 | R33: EVNT_END_TM | AC33: {=_xlfn.SWITCH(BM33,"String","varchar("&BN33&")","Long","int","Integer","smallint","Double","decimal(9,2)","Currency","int")} -> varchar(8) | AH33: 4 | AT33: ＹＹＹＹＭＭＤＤ形式で８桁フルに設定すること | BM33: String | BN33: 8 | BP33: =",`"&R33&"` "&AC33&" "&IF(AJ33="Y","NOT NULL","")&" COMMENT '"&D33&" "&AT33&"'" -> ,`EVNT_END_TM` varchar(8) COMMENT '特売終了日 ＹＹＹＹＭＭＤＤ形式で８桁フルに設定すること' | BQ33: `EVNT_END_TM` varchar(8) CHARACTER SET utf8mb4 COLLATE utf8mb4_0900_ai_ci NOT NULL COMMENT '特売終了日 ＹＹＹＹＭＭＤＤ形式で８桁フルに設定すること', | BR33: =",`"&R33&"` "&AC33&" "&IF(AJ33="Y","NOT NULL","") -> ,`EVNT_END_TM` varchar(8) | BT33: =",`"&R33&"`" -> ,`EVNT_END_TM` | BV33: =",A.`"&R33&"` = B.`"&R33&"`" -> ,A.`EVNT_END_TM` = B.`EVNT_END_TM` | BX33: =",`"&R33&"`" -> ,`EVNT_END_TM` | BZ33: =",`"&R33&"`" -> ,`EVNT_END_TM`
A34: @9 | B34: 9 | D34: 特売削除日数 | R34: EVNT_HLDL_DY | AC34: {=_xlfn.SWITCH(BM34,"String","varchar("&BN34&")","Long","int","Integer","smallint","Double","decimal(9,2)","Currency","int")} -> varchar(3) | AT34: 期間終了後の削除猶予期間 ００２－０９９ 未使用時はＮＵＬＬ | BM34: String | BN34: 3 | BP34: =",`"&R34&"` "&AC34&" "&IF(AJ34="Y","NOT NULL","")&" COMMENT '"&D34&" "&AT34&"'" -> ,`EVNT_HLDL_DY` varchar(3) COMMENT '特売削除日数 期間終了後の削除猶予期間 ００２－０９９ 未使用時はＮＵＬＬ' | BQ34: `EVNT_HLDL_DY` varchar(3) DEFAULT NULL COMMENT '特売削除日数 期間終了後の削除猶予期間 ００２－０９９ 未使用時はＮＵＬＬ', | BR34: =",`"&R34&"` "&AC34&" "&IF(AJ34="Y","NOT NULL","") -> ,`EVNT_HLDL_DY` varchar(3) | BT34: =",`"&R34&"`" -> ,`EVNT_HLDL_DY` | BV34: =",A.`"&R34&"` = B.`"&R34&"`" -> ,A.`EVNT_HLDL_DY` = B.`EVNT_HLDL_DY` | BX34: =",`"&R34&"`" -> ,`EVNT_HLDL_DY` | BZ34: =",`"&R34&"`" -> ,`EVNT_HLDL_DY`
A35: @10 | B35: 9 | D35: 特売優先区分 | R35: EVNT_SRC | AC35: {=_xlfn.SWITCH(BM35,"String","varchar("&BN35&")","Long","int","Integer","smallint","Double","decimal(9,2)","Currency","int")} -> smallint | AT35: 現在１固定 ０：店舗優先 １：本部優先 | BM35: Integer | BP35: =",`"&R35&"` "&AC35&" "&IF(AJ35="Y","NOT NULL","")&" COMMENT '"&D35&" "&AT35&"'" -> ,`EVNT_SRC` smallint COMMENT '特売優先区分 現在１固定 ０：店舗優先 １：本部優先' | BQ35: `EVNT_SRC` smallint DEFAULT NULL COMMENT '特売優先区分 現在１固定 ０：店舗優先 １：本部優先', | BR35: =",`"&R35&"` "&AC35&" "&IF(AJ35="Y","NOT NULL","") -> ,`EVNT_SRC` smallint | BT35: =",`"&R35&"`" -> ,`EVNT_SRC` | BV35: =",A.`"&R35&"` = B.`"&R35&"`" -> ,A.`EVNT_SRC` = B.`EVNT_SRC` | BX35: =",`"&R35&"`" -> ,`EVNT_SRC` | BZ35: =",`"&R35&"`" -> ,`EVNT_SRC`
A36: @11 | B36: 9 | D36: 特売保留フラグ | R36: EVNT_EXCL_FG | AC36: {=_xlfn.SWITCH(BM36,"String","varchar("&BN36&")","Long","int","Integer","smallint","Double","decimal(9,2)","Currency","int")} -> smallint | AT36: ０：保留しない １：保留する | BM36: Integer | BP36: =",`"&R36&"` "&AC36&" "&IF(AJ36="Y","NOT NULL","")&" COMMENT '"&D36&" "&AT36&"'" -> ,`EVNT_EXCL_FG` smallint COMMENT '特売保留フラグ ０：保留しない １：保留する' | BQ36: `EVNT_EXCL_FG` smallint DEFAULT NULL COMMENT '特売保留フラグ ０：保留しない １：保留する', | BR36: =",`"&R36&"` "&AC36&" "&IF(AJ36="Y","NOT NULL","") -> ,`EVNT_EXCL_FG` smallint | BT36: =",`"&R36&"`" -> ,`EVNT_EXCL_FG` | BV36: =",A.`"&R36&"` = B.`"&R36&"`" -> ,A.`EVNT_EXCL_FG` = B.`EVNT_EXCL_FG` | BX36: =",`"&R36&"`" -> ,`EVNT_EXCL_FG` | BZ36: =",`"&R36&"`" -> ,`EVNT_EXCL_FG`
A37: @12 | B37: 9 | D37: タイムサービスフラグ | R37: TIME_SERVICE_FG | AC37: {=_xlfn.SWITCH(BM37,"String","varchar("&BN37&")","Long","int","Integer","smallint","Double","decimal(9,2)","Currency","int")} -> smallint | AT37: ０：期間 １：期間＆曜日 ２：期間＆時間 ３：期間＆時間＆曜日 | BM37: Integer | BP37: =",`"&R37&"` "&AC37&" "&IF(AJ37="Y","NOT NULL","")&" COMMENT '"&D37&" "&AT37&"'" -> ,`TIME_SERVICE_FG` smallint COMMENT 'タイムサービスフラグ ０：期間 １：期間＆曜日 ２：期間＆時間 ３：期間＆時間＆曜日' | BQ37: `TIME_SERVICE_FG` smallint DEFAULT NULL COMMENT 'タイムサービスフラグ ０：期間 １：期間＆曜日 ２：期間＆時間 ３：期間＆時間＆曜日', | BR37: =",`"&R37&"` "&AC37&" "&IF(AJ37="Y","NOT NULL","") -> ,`TIME_SERVICE_FG` smallint | BT37: =",`"&R37&"`" -> ,`TIME_SERVICE_FG` | BV37: =",A.`"&R37&"` = B.`"&R37&"`" -> ,A.`TIME_SERVICE_FG` = B.`TIME_SERVICE_FG` | BX37: =",`"&R37&"`" -> ,`TIME_SERVICE_FG` | BZ37: =",`"&R37&"`" -> ,`TIME_SERVICE_FG`
A38: @13 | B38: 9 | D38: 月曜日除外フラグ | R38: MON_EXCL_FG | AC38: {=_xlfn.SWITCH(BM38,"String","varchar("&BN38&")","Long","int","Integer","smallint","Double","decimal(9,2)","Currency","int")} -> smallint | AT38: ０：除外しない １：除外する | BM38: Integer | BP38: =",`"&R38&"` "&AC38&" "&IF(AJ38="Y","NOT NULL","")&" COMMENT '"&D38&" "&AT38&"'" -> ,`MON_EXCL_FG` smallint COMMENT '月曜日除外フラグ ０：除外しない １：除外する' | BQ38: `MON_EXCL_FG` smallint DEFAULT NULL COMMENT '月曜日除外フラグ ０：除外しない １：除外する', | BR38: =",`"&R38&"` "&AC38&" "&IF(AJ38="Y","NOT NULL","") -> ,`MON_EXCL_FG` smallint | BT38: =",`"&R38&"`" -> ,`MON_EXCL_FG` | BV38: =",A.`"&R38&"` = B.`"&R38&"`" -> ,A.`MON_EXCL_FG` = B.`MON_EXCL_FG` | BX38: =",`"&R38&"`" -> ,`MON_EXCL_FG` | BZ38: =",`"&R38&"`" -> ,`MON_EXCL_FG`
A39: @14 | B39: 9 | D39: 火曜日除外フラグ | R39: TUES_EXCL_FG | AC39: {=_xlfn.SWITCH(BM39,"String","varchar("&BN39&")","Long","int","Integer","smallint","Double","decimal(9,2)","Currency","int")} -> smallint | AT39: ０：除外しない １：除外する | BM39: Integer | BP39: =",`"&R39&"` "&AC39&" "&IF(AJ39="Y","NOT NULL","")&" COMMENT '"&D39&" "&AT39&"'" -> ,`TUES_EXCL_FG` smallint COMMENT '火曜日除外フラグ ０：除外しない １：除外する' | BQ39: `TUES_EXCL_FG` smallint DEFAULT NULL COMMENT '火曜日除外フラグ ０：除外しない １：除外する', | BR39: =",`"&R39&"` "&AC39&" "&IF(AJ39="Y","NOT NULL","") -> ,`TUES_EXCL_FG` smallint | BT39: =",`"&R39&"`" -> ,`TUES_EXCL_FG` | BV39: =",A.`"&R39&"` = B.`"&R39&"`" -> ,A.`TUES_EXCL_FG` = B.`TUES_EXCL_FG` | BX39: =",`"&R39&"`" -> ,`TUES_EXCL_FG` | BZ39: =",`"&R39&"`" -> ,`TUES_EXCL_FG`
A40: @15 | B40: 9 | D40: 水曜日除外フラグ | R40: WED_EXCL_FG | AC40: {=_xlfn.SWITCH(BM40,"String","varchar("&BN40&")","Long","int","Integer","smallint","Double","decimal(9,2)","Currency","int")} -> smallint | AT40: ０：除外しない １：除外する | BM40: Integer | BP40: =",`"&R40&"` "&AC40&" "&IF(AJ40="Y","NOT NULL","")&" COMMENT '"&D40&" "&AT40&"'" -> ,`WED_EXCL_FG` smallint COMMENT '水曜日除外フラグ ０：除外しない １：除外する' | BQ40: `WED_EXCL_FG` smallint DEFAULT NULL COMMENT '水曜日除外フラグ ０：除外しない １：除外する', | BR40: =",`"&R40&"` "&AC40&" "&IF(AJ40="Y","NOT NULL","") -> ,`WED_EXCL_FG` smallint | BT40: =",`"&R40&"`" -> ,`WED_EXCL_FG` | BV40: =",A.`"&R40&"` = B.`"&R40&"`" -> ,A.`WED_EXCL_FG` = B.`WED_EXCL_FG` | BX40: =",`"&R40&"`" -> ,`WED_EXCL_FG` | BZ40: =",`"&R40&"`" -> ,`WED_EXCL_FG`
A41: @16 | B41: 9 | D41: 木曜日除外フラグ | R41: THUS_EXCL_FG | AC41: {=_xlfn.SWITCH(BM41,"String","varchar("&BN41&")","Long","int","Integer","smallint","Double","decimal(9,2)","Currency","int")} -> smallint | AT41: ０：除外しない １：除外する | BM41: Integer | BP41: =",`"&R41&"` "&AC41&" "&IF(AJ41="Y","NOT NULL","")&" COMMENT '"&D41&" "&AT41&"'" -> ,`THUS_EXCL_FG` smallint COMMENT '木曜日除外フラグ ０：除外しない １：除外する' | BQ41: `THUS_EXCL_FG` smallint DEFAULT NULL COMMENT '木曜日除外フラグ ０：除外しない １：除外する', | BR41: =",`"&R41&"` "&AC41&" "&IF(AJ41="Y","NOT NULL","") -> ,`THUS_EXCL_FG` smallint | BT41: =",`"&R41&"`" -> ,`THUS_EXCL_FG` | BV41: =",A.`"&R41&"` = B.`"&R41&"`" -> ,A.`THUS_EXCL_FG` = B.`THUS_EXCL_FG` | BX41: =",`"&R41&"`" -> ,`THUS_EXCL_FG` | BZ41: =",`"&R41&"`" -> ,`THUS_EXCL_FG`
A42: @17 | B42: 9 | D42: 金曜日除外フラグ | R42: FRI_EXCL_FG | AC42: {=_xlfn.SWITCH(BM42,"String","varchar("&BN42&")","Long","int","Integer","smallint","Double","decimal(9,2)","Currency","int")} -> smallint | AT42: ０：除外しない １：除外する | BM42: Integer | BP42: =",`"&R42&"` "&AC42&" "&IF(AJ42="Y","NOT NULL","")&" COMMENT '"&D42&" "&AT42&"'" -> ,`FRI_EXCL_FG` smallint COMMENT '金曜日除外フラグ ０：除外しない １：除外する' | BQ42: `FRI_EXCL_FG` smallint DEFAULT NULL COMMENT '金曜日除外フラグ ０：除外しない １：除外する', | BR42: =",`"&R42&"` "&AC42&" "&IF(AJ42="Y","NOT NULL","") -> ,`FRI_EXCL_FG` smallint | BT42: =",`"&R42&"`" -> ,`FRI_EXCL_FG` | BV42: =",A.`"&R42&"` = B.`"&R42&"`" -> ,A.`FRI_EXCL_FG` = B.`FRI_EXCL_FG` | BX42: =",`"&R42&"`" -> ,`FRI_EXCL_FG` | BZ42: =",`"&R42&"`" -> ,`FRI_EXCL_FG`
A43: @18 | B43: 9 | D43: 土曜日除外フラグ | R43: SAT_EXCL_FG | AC43: {=_xlfn.SWITCH(BM43,"String","varchar("&BN43&")","Long","int","Integer","smallint","Double","decimal(9,2)","Currency","int")} -> smallint | AT43: ０：除外しない １：除外する | BM43: Integer | BP43: =",`"&R43&"` "&AC43&" "&IF(AJ43="Y","NOT NULL","")&" COMMENT '"&D43&" "&AT43&"'" -> ,`SAT_EXCL_FG` smallint COMMENT '土曜日除外フラグ ０：除外しない １：除外する' | BQ43: `SAT_EXCL_FG` smallint DEFAULT NULL COMMENT '土曜日除外フラグ ０：除外しない １：除外する', | BR43: =",`"&R43&"` "&AC43&" "&IF(AJ43="Y","NOT NULL","") -> ,`SAT_EXCL_FG` smallint | BT43: =",`"&R43&"`" -> ,`SAT_EXCL_FG` | BV43: =",A.`"&R43&"` = B.`"&R43&"`" -> ,A.`SAT_EXCL_FG` = B.`SAT_EXCL_FG` | BX43: =",`"&R43&"`" -> ,`SAT_EXCL_FG` | BZ43: =",`"&R43&"`" -> ,`SAT_EXCL_FG`
A44: @19 | B44: 9 | D44: 日曜日除外フラグ | R44: SUN_EXCL_FG | AC44: {=_xlfn.SWITCH(BM44,"String","varchar("&BN44&")","Long","int","Integer","smallint","Double","decimal(9,2)","Currency","int")} -> smallint | AT44: ０：除外しない ２：除外する | BM44: Integer | BP44: =",`"&R44&"` "&AC44&" "&IF(AJ44="Y","NOT NULL","")&" COMMENT '"&D44&" "&AT44&"'" -> ,`SUN_EXCL_FG` smallint COMMENT '日曜日除外フラグ ０：除外しない ２：除外する' | BQ44: `SUN_EXCL_FG` smallint DEFAULT NULL COMMENT '日曜日除外フラグ ０：除外しない ２：除外する', | BR44: =",`"&R44&"` "&AC44&" "&IF(AJ44="Y","NOT NULL","") -> ,`SUN_EXCL_FG` smallint | BT44: =",`"&R44&"`" -> ,`SUN_EXCL_FG` | BV44: =",A.`"&R44&"` = B.`"&R44&"`" -> ,A.`SUN_EXCL_FG` = B.`SUN_EXCL_FG` | BX44: =",`"&R44&"`" -> ,`SUN_EXCL_FG` | BZ44: =",`"&R44&"`" -> ,`SUN_EXCL_FG`
A45: @20 | B45: 9 | D45: 特売原価 | R45: PROMO_COST | AC45: {=_xlfn.SWITCH(BM45,"String","varchar("&BN45&")","Long","int","Integer","smallint","Double","decimal(9,2)","Currency","int")} -> int | AT45: ０以上 | BM45: Currency | BP45: =",`"&R45&"` "&AC45&" "&IF(AJ45="Y","NOT NULL","")&" COMMENT '"&D45&" "&AT45&"'" -> ,`PROMO_COST` int COMMENT '特売原価 ０以上' | BQ45: `PROMO_COST` int DEFAULT NULL COMMENT '特売原価 ０以上', | BR45: =",`"&R45&"` "&AC45&" "&IF(AJ45="Y","NOT NULL","") -> ,`PROMO_COST` int | BT45: =",`"&R45&"`" -> ,`PROMO_COST` | BV45: =",A.`"&R45&"` = B.`"&R45&"`" -> ,A.`PROMO_COST` = B.`PROMO_COST` | BX45: =",`"&R45&"`" -> ,`PROMO_COST` | BZ45: =",`"&R45&"`" -> ,`PROMO_COST`
A46: @21 | B46: 9 | D46: 割引タイプ | R46: DISC_MTHD | AC46: {=_xlfn.SWITCH(BM46,"String","varchar("&BN46&")","Long","int","Integer","smallint","Double","decimal(9,2)","Currency","int")} -> smallint | AT46: 現在６固定 １：差額 ２：％（率） ６：金額 | BM46: Integer | BP46: =",`"&R46&"` "&AC46&" "&IF(AJ46="Y","NOT NULL","")&" COMMENT '"&D46&" "&AT46&"'" -> ,`DISC_MTHD` smallint COMMENT '割引タイプ 現在６固定 １：差額 ２：％（率） ６：金額' | BQ46: `DISC_MTHD` smallint DEFAULT NULL COMMENT '割引タイプ 現在６固定 １：差額 ２：％（率） ６：金額', | BR46: =",`"&R46&"` "&AC46&" "&IF(AJ46="Y","NOT NULL","") -> ,`DISC_MTHD` smallint | BT46: =",`"&R46&"`" -> ,`DISC_MTHD` | BV46: =",A.`"&R46&"` = B.`"&R46&"`" -> ,A.`DISC_MTHD` = B.`DISC_MTHD` | BX46: =",`"&R46&"`" -> ,`DISC_MTHD` | BZ46: =",`"&R46&"`" -> ,`DISC_MTHD`
A47: @22 | B47: 9 | D47: 特売価格 | R47: DISC_VALUE | AC47: {=_xlfn.SWITCH(BM47,"String","varchar("&BN47&")","Long","int","Integer","smallint","Double","decimal(9,2)","Currency","int")} -> decimal(9,2) | BM47: Double | BP47: =",`"&R47&"` "&AC47&" "&IF(AJ47="Y","NOT NULL","")&" COMMENT '"&D47&" "&AT47&"'" -> ,`DISC_VALUE` decimal(9,2) COMMENT '特売価格 ' | BQ47: `DISC_VALUE` decimal(9,2) DEFAULT NULL COMMENT '特売価格 ', | BR47: =",`"&R47&"` "&AC47&" "&IF(AJ47="Y","NOT NULL","") -> ,`DISC_VALUE` decimal(9,2) | BT47: =",`"&R47&"`" -> ,`DISC_VALUE` | BV47: =",A.`"&R47&"` = B.`"&R47&"`" -> ,A.`DISC_VALUE` = B.`DISC_VALUE` | BX47: =",`"&R47&"`" -> ,`DISC_VALUE` | BZ47: =",`"&R47&"`" -> ,`DISC_VALUE`
A48: @23 | B48: 9 | D48: 個数制限 | R48: DISC_ITM_LMT | AC48: {=_xlfn.SWITCH(BM48,"String","varchar("&BN48&")","Long","int","Integer","smallint","Double","decimal(9,2)","Currency","int")} -> decimal(9,2) | AT48: 現在未使用 ０固定 | BM48: Double | BP48: =",`"&R48&"` "&AC48&" "&IF(AJ48="Y","NOT NULL","")&" COMMENT '"&D48&" "&AT48&"'" -> ,`DISC_ITM_LMT` decimal(9,2) COMMENT '個数制限 現在未使用 ０固定' | BQ48: `DISC_ITM_LMT` decimal(9,2) DEFAULT NULL COMMENT '個数制限 現在未使用 ０固定', | BR48: =",`"&R48&"` "&AC48&" "&IF(AJ48="Y","NOT NULL","") -> ,`DISC_ITM_LMT` decimal(9,2) | BT48: =",`"&R48&"`" -> ,`DISC_ITM_LMT` | BV48: =",A.`"&R48&"` = B.`"&R48&"`" -> ,A.`DISC_ITM_LMT` = B.`DISC_ITM_LMT` | BX48: =",`"&R48&"`" -> ,`DISC_ITM_LMT` | BZ48: =",`"&R48&"`" -> ,`DISC_ITM_LMT`
A49: @24 | B49: 9 | D49: 特売開始時間 | R49: PROMO_BGN_TM | AC49: {=_xlfn.SWITCH(BM49,"String","varchar("&BN49&")","Long","int","Integer","smallint","Double","decimal(9,2)","Currency","int")} -> varchar(4) | AT49: ＨＨＭＭ形式で４桁フルに設定すること（２４時間制） | BM49: String | BN49: 4 | BP49: =",`"&R49&"` "&AC49&" "&IF(AJ49="Y","NOT NULL","")&" COMMENT '"&D49&" "&AT49&"'" -> ,`PROMO_BGN_TM` varchar(4) COMMENT '特売開始時間 ＨＨＭＭ形式で４桁フルに設定すること（２４時間制）' | BQ49: `PROMO_BGN_TM` varchar(4) DEFAULT NULL COMMENT '特売開始時間 ＨＨＭＭ形式で４桁フルに設定すること（２４時間制）', | BR49: =",`"&R49&"` "&AC49&" "&IF(AJ49="Y","NOT NULL","") -> ,`PROMO_BGN_TM` varchar(4) | BT49: =",`"&R49&"`" -> ,`PROMO_BGN_TM` | BV49: =",A.`"&R49&"` = B.`"&R49&"`" -> ,A.`PROMO_BGN_TM` = B.`PROMO_BGN_TM` | BX49: =",`"&R49&"`" -> ,`PROMO_BGN_TM` | BZ49: =",`"&R49&"`" -> ,`PROMO_BGN_TM`
A50: @25 | B50: 9 | D50: 特売終了時間 | R50: PROMO_END_TM | AC50: {=_xlfn.SWITCH(BM50,"String","varchar("&BN50&")","Long","int","Integer","smallint","Double","decimal(9,2)","Currency","int")} -> varchar(4) | AT50: ＨＨＭＭ形式で４桁フルに設定すること（２４時間制） | BM50: String | BN50: 4 | BP50: =",`"&R50&"` "&AC50&" "&IF(AJ50="Y","NOT NULL","")&" COMMENT '"&D50&" "&AT50&"'" -> ,`PROMO_END_TM` varchar(4) COMMENT '特売終了時間 ＨＨＭＭ形式で４桁フルに設定すること（２４時間制）' | BQ50: `PROMO_END_TM` varchar(4) DEFAULT NULL COMMENT '特売終了時間 ＨＨＭＭ形式で４桁フルに設定すること（２４時間制）', | BR50: =",`"&R50&"` "&AC50&" "&IF(AJ50="Y","NOT NULL","") -> ,`PROMO_END_TM` varchar(4) | BT50: =",`"&R50&"`" -> ,`PROMO_END_TM` | BV50: =",A.`"&R50&"` = B.`"&R50&"`" -> ,A.`PROMO_END_TM` = B.`PROMO_END_TM` | BX50: =",`"&R50&"`" -> ,`PROMO_END_TM` | BZ50: =",`"&R50&"`" -> ,`PROMO_END_TM`
A51: @26 | B51: 9 | D51: 事前特売開始日 | R51: BFR_EVNT_BGN_TM | AC51: {=_xlfn.SWITCH(BM51,"String","varchar("&BN51&")","Long","int","Integer","smallint","Double","decimal(9,2)","Currency","int")} -> varchar(8) | AT51: 現在未使用 Ｎull固定 | BM51: String | BN51: 8 | BP51: =",`"&R51&"` "&AC51&" "&IF(AJ51="Y","NOT NULL","")&" COMMENT '"&D51&" "&AT51&"'" -> ,`BFR_EVNT_BGN_TM` varchar(8) COMMENT '事前特売開始日 現在未使用 Ｎull固定' | BQ51: `BFR_EVNT_BGN_TM` varchar(8) DEFAULT NULL COMMENT '事前特売開始日 現在未使用 Ｎull固定', | BR51: =",`"&R51&"` "&AC51&" "&IF(AJ51="Y","NOT NULL","") -> ,`BFR_EVNT_BGN_TM` varchar(8) | BT51: =",`"&R51&"`" -> ,`BFR_EVNT_BGN_TM` | BV51: =",A.`"&R51&"` = B.`"&R51&"`" -> ,A.`BFR_EVNT_BGN_TM` = B.`BFR_EVNT_BGN_TM` | BX51: =",`"&R51&"`" -> ,`BFR_EVNT_BGN_TM` | BZ51: =",`"&R51&"`" -> ,`BFR_EVNT_BGN_TM`
A52: @27 | B52: 9 | D52: 事前割引タイプ | R52: BFR_DISC_MTHD | AC52: {=_xlfn.SWITCH(BM52,"String","varchar("&BN52&")","Long","int","Integer","smallint","Double","decimal(9,2)","Currency","int")} -> smallint | AT52: 現在未使用 ０固定 | BM52: Integer | BP52: =",`"&R52&"` "&AC52&" "&IF(AJ52="Y","NOT NULL","")&" COMMENT '"&D52&" "&AT52&"'" -> ,`BFR_DISC_MTHD` smallint COMMENT '事前割引タイプ 現在未使用 ０固定' | BQ52: `BFR_DISC_MTHD` smallint DEFAULT NULL COMMENT '事前割引タイプ 現在未使用 ０固定', | BR52: =",`"&R52&"` "&AC52&" "&IF(AJ52="Y","NOT NULL","") -> ,`BFR_DISC_MTHD` smallint | BT52: =",`"&R52&"`" -> ,`BFR_DISC_MTHD` | BV52: =",A.`"&R52&"` = B.`"&R52&"`" -> ,A.`BFR_DISC_MTHD` = B.`BFR_DISC_MTHD` | BX52: =",`"&R52&"`" -> ,`BFR_DISC_MTHD` | BZ52: =",`"&R52&"`" -> ,`BFR_DISC_MTHD`
A53: @28 | B53: 9 | D53: 事前特売価格 | R53: BFR_DISC_VALUE | AC53: {=_xlfn.SWITCH(BM53,"String","varchar("&BN53&")","Long","int","Integer","smallint","Double","decimal(9,2)","Currency","int")} -> decimal(9,2) | AT53: 現在未使用 ０固定 | BM53: Double | BP53: =",`"&R53&"` "&AC53&" "&IF(AJ53="Y","NOT NULL","")&" COMMENT '"&D53&" "&AT53&"'" -> ,`BFR_DISC_VALUE` decimal(9,2) COMMENT '事前特売価格 現在未使用 ０固定' | BQ53: `BFR_DISC_VALUE` decimal(9,2) DEFAULT NULL COMMENT '事前特売価格 現在未使用 ０固定', | BR53: =",`"&R53&"` "&AC53&" "&IF(AJ53="Y","NOT NULL","") -> ,`BFR_DISC_VALUE` decimal(9,2) | BT53: =",`"&R53&"`" -> ,`BFR_DISC_VALUE` | BV53: =",A.`"&R53&"` = B.`"&R53&"`" -> ,A.`BFR_DISC_VALUE` = B.`BFR_DISC_VALUE` | BX53: =",`"&R53&"`" -> ,`BFR_DISC_VALUE` | BZ53: =",`"&R53&"`" -> ,`BFR_DISC_VALUE`
A54: @29 | B54: 9 | D54: 継続特売終了日 | R54: AFT_DISC_END_TM | AC54: {=_xlfn.SWITCH(BM54,"String","varchar("&BN54&")","Long","int","Integer","smallint","Double","decimal(9,2)","Currency","int")} -> varchar(8) | AT54: 現在未使用 Ｎull固定 | BM54: String | BN54: 8 | BP54: =",`"&R54&"` "&AC54&" "&IF(AJ54="Y","NOT NULL","")&" COMMENT '"&D54&" "&AT54&"'" -> ,`AFT_DISC_END_TM` varchar(8) COMMENT '継続特売終了日 現在未使用 Ｎull固定' | BQ54: `AFT_DISC_END_TM` varchar(8) DEFAULT NULL COMMENT '継続特売終了日 現在未使用 Ｎull固定', | BR54: =",`"&R54&"` "&AC54&" "&IF(AJ54="Y","NOT NULL","") -> ,`AFT_DISC_END_TM` varchar(8) | BT54: =",`"&R54&"`" -> ,`AFT_DISC_END_TM` | BV54: =",A.`"&R54&"` = B.`"&R54&"`" -> ,A.`AFT_DISC_END_TM` = B.`AFT_DISC_END_TM` | BX54: =",`"&R54&"`" -> ,`AFT_DISC_END_TM` | BZ54: =",`"&R54&"`" -> ,`AFT_DISC_END_TM`
A55: @30 | B55: 9 | D55: 継続割引タイプ | R55: AFT_DISC_MTHD | AC55: {=_xlfn.SWITCH(BM55,"String","varchar("&BN55&")","Long","int","Integer","smallint","Double","decimal(9,2)","Currency","int")} -> smallint | AT55: 現在未使用 ０固定 | BM55: Integer | BP55: =",`"&R55&"` "&AC55&" "&IF(AJ55="Y","NOT NULL","")&" COMMENT '"&D55&" "&AT55&"'" -> ,`AFT_DISC_MTHD` smallint COMMENT '継続割引タイプ 現在未使用 ０固定' | BQ55: `AFT_DISC_MTHD` smallint DEFAULT NULL COMMENT '継続割引タイプ 現在未使用 ０固定', | BR55: =",`"&R55&"` "&AC55&" "&IF(AJ55="Y","NOT NULL","") -> ,`AFT_DISC_MTHD` smallint | BT55: =",`"&R55&"`" -> ,`AFT_DISC_MTHD` | BV55: =",A.`"&R55&"` = B.`"&R55&"`" -> ,A.`AFT_DISC_MTHD` = B.`AFT_DISC_MTHD` | BX55: =",`"&R55&"`" -> ,`AFT_DISC_MTHD` | BZ55: =",`"&R55&"`" -> ,`AFT_DISC_MTHD`
A56: @31 | B56: 9 | D56: 継続特売価格 | R56: AFT_DISC_VALUE | AC56: {=_xlfn.SWITCH(BM56,"String","varchar("&BN56&")","Long","int","Integer","smallint","Double","decimal(9,2)","Currency","int")} -> decimal(9,2) | AT56: 現在未使用 ０固定 | BM56: Double | BP56: =",`"&R56&"` "&AC56&" "&IF(AJ56="Y","NOT NULL","")&" COMMENT '"&D56&" "&AT56&"'" -> ,`AFT_DISC_VALUE` decimal(9,2) COMMENT '継続特売価格 現在未使用 ０固定' | BQ56: `AFT_DISC_VALUE` decimal(9,2) DEFAULT NULL COMMENT '継続特売価格 現在未使用 ０固定', | BR56: =",`"&R56&"` "&AC56&" "&IF(AJ56="Y","NOT NULL","") -> ,`AFT_DISC_VALUE` decimal(9,2) | BT56: =",`"&R56&"`" -> ,`AFT_DISC_VALUE` | BV56: =",A.`"&R56&"` = B.`"&R56&"`" -> ,A.`AFT_DISC_VALUE` = B.`AFT_DISC_VALUE` | BX56: =",`"&R56&"`" -> ,`AFT_DISC_VALUE` | BZ56: =",`"&R56&"`" -> ,`AFT_DISC_VALUE`
A57: @32 | B57: 9 | D57: 価格グループＩＤ | R57: PRC_GRP_ID | AC57: {=_xlfn.SWITCH(BM57,"String","varchar("&BN57&")","Long","int","Integer","smallint","Double","decimal(9,2)","Currency","int")} -> smallint | AT57: 現在未使用 ０固定 | BM57: Integer | BP57: =",`"&R57&"` "&AC57&" "&IF(AJ57="Y","NOT NULL","")&" COMMENT '"&D57&" "&AT57&"'" -> ,`PRC_GRP_ID` smallint COMMENT '価格グループＩＤ 現在未使用 ０固定' | BQ57: `PRC_GRP_ID` smallint DEFAULT NULL COMMENT '価格グループＩＤ 現在未使用 ０固定', | BR57: =",`"&R57&"` "&AC57&" "&IF(AJ57="Y","NOT NULL","") -> ,`PRC_GRP_ID` smallint | BT57: =",`"&R57&"`" -> ,`PRC_GRP_ID` | BV57: =",A.`"&R57&"` = B.`"&R57&"`" -> ,A.`PRC_GRP_ID` = B.`PRC_GRP_ID` | BX57: =",`"&R57&"`" -> ,`PRC_GRP_ID` | BZ57: =",`"&R57&"`" -> ,`PRC_GRP_ID`
A58: @33 | B58: 9 | D58: 商品階層コード | R58: MDSE_XREF_NO | AC58: {=_xlfn.SWITCH(BM58,"String","varchar("&BN58&")","Long","int","Integer","smallint","Double","decimal(9,2)","Currency","int")} -> int | AT58: 現在未使用 ０固定 | BM58: Long | BP58: =",`"&R58&"` "&AC58&" "&IF(AJ58="Y","NOT NULL","")&" COMMENT '"&D58&" "&AT58&"'" -> ,`MDSE_XREF_NO` int COMMENT '商品階層コード 現在未使用 ０固定' | BQ58: `MDSE_XREF_NO` int DEFAULT NULL COMMENT '商品階層コード 現在未使用 ０固定', | BR58: =",`"&R58&"` "&AC58&" "&IF(AJ58="Y","NOT NULL","") -> ,`MDSE_XREF_NO` int | BT58: =",`"&R58&"`" -> ,`MDSE_XREF_NO` | BV58: =",A.`"&R58&"` = B.`"&R58&"`" -> ,A.`MDSE_XREF_NO` = B.`MDSE_XREF_NO` | BX58: =",`"&R58&"`" -> ,`MDSE_XREF_NO` | BZ58: =",`"&R58&"`" -> ,`MDSE_XREF_NO`
A59: @34 | B59: 9 | D59: PLU属性 | R59: PLU_QUAL_TYP | AC59: {=_xlfn.SWITCH(BM59,"String","varchar("&BN59&")","Long","int","Integer","smallint","Double","decimal(9,2)","Currency","int")} -> int | AT59: 現在未使用 ０固定 | BM59: Long | BP59: =",`"&R59&"` "&AC59&" "&IF(AJ59="Y","NOT NULL","")&" COMMENT '"&D59&" "&AT59&"'" -> ,`PLU_QUAL_TYP` int COMMENT 'PLU属性 現在未使用 ０固定' | BQ59: `PLU_QUAL_TYP` int DEFAULT NULL COMMENT 'ＰＬＵ属性 現在未使用 ０固定', | BR59: =",`"&R59&"` "&AC59&" "&IF(AJ59="Y","NOT NULL","") -> ,`PLU_QUAL_TYP` int | BT59: =",`"&R59&"`" -> ,`PLU_QUAL_TYP` | BV59: =",A.`"&R59&"` = B.`"&R59&"`" -> ,A.`PLU_QUAL_TYP` = B.`PLU_QUAL_TYP` | BX59: =",`"&R59&"`" -> ,`PLU_QUAL_TYP` | BZ59: =",`"&R59&"`" -> ,`PLU_QUAL_TYP`
A60: @35 | B60: 9 | D60: ALTコード | R60: ALT_NO | AC60: {=_xlfn.SWITCH(BM60,"String","varchar("&BN60&")","Long","int","Integer","smallint","Double","decimal(9,2)","Currency","int")} -> smallint | AT60: 現在未使用 ０固定 | BM60: Integer | BP60: =",`"&R60&"` "&AC60&" "&IF(AJ60="Y","NOT NULL","")&" COMMENT '"&D60&" "&AT60&"'" -> ,`ALT_NO` smallint COMMENT 'ALTコード 現在未使用 ０固定' | BQ60: `ALT_NO` smallint DEFAULT NULL COMMENT 'ＡＬＴコード 現在未使用 ０固定', | BR60: =",`"&R60&"` "&AC60&" "&IF(AJ60="Y","NOT NULL","") -> ,`ALT_NO` smallint | BT60: =",`"&R60&"`" -> ,`ALT_NO` | BV60: =",A.`"&R60&"` = B.`"&R60&"`" -> ,A.`ALT_NO` = B.`ALT_NO` | BX60: =",`"&R60&"`" -> ,`ALT_NO` | BZ60: =",`"&R60&"`" -> ,`ALT_NO`
A61: @36 | B61: 9 | D61: サブＩＤ | R61: SUB_ID | AC61: {=_xlfn.SWITCH(BM61,"String","varchar("&BN61&")","Long","int","Integer","smallint","Double","decimal(9,2)","Currency","int")} -> varchar(20) | AT61: 現在未使用 Ｎull固定 | BM61: String | BN61: 20 | BP61: =",`"&R61&"` "&AC61&" "&IF(AJ61="Y","NOT NULL","")&" COMMENT '"&D61&" "&AT61&"'" -> ,`SUB_ID` varchar(20) COMMENT 'サブＩＤ 現在未使用 Ｎull固定' | BQ61: `SUB_ID` varchar(20) DEFAULT NULL COMMENT 'サブＩＤ 現在未使用 Ｎull固定', | BR61: =",`"&R61&"` "&AC61&" "&IF(AJ61="Y","NOT NULL","") -> ,`SUB_ID` varchar(20) | BT61: =",`"&R61&"`" -> ,`SUB_ID` | BV61: =",A.`"&R61&"` = B.`"&R61&"`" -> ,A.`SUB_ID` = B.`SUB_ID` | BX61: =",`"&R61&"`" -> ,`SUB_ID` | BZ61: =",`"&R61&"`" -> ,`SUB_ID`
A62: @37 | B62: 9 | D62: 割引グループＩＤ | R62: DG_ID | AC62: {=_xlfn.SWITCH(BM62,"String","varchar("&BN62&")","Long","int","Integer","smallint","Double","decimal(9,2)","Currency","int")} -> varchar(20) | AT62: 現在未使用 Ｎull固定 | BM62: String | BN62: 20 | BP62: =",`"&R62&"` "&AC62&" "&IF(AJ62="Y","NOT NULL","")&" COMMENT '"&D62&" "&AT62&"'" -> ,`DG_ID` varchar(20) COMMENT '割引グループＩＤ 現在未使用 Ｎull固定' | BQ62: `DG_ID` varchar(20) DEFAULT NULL COMMENT '割引グループＩＤ 現在未使用 Ｎull固定', | BR62: =",`"&R62&"` "&AC62&" "&IF(AJ62="Y","NOT NULL","") -> ,`DG_ID` varchar(20) | BT62: =",`"&R62&"`" -> ,`DG_ID` | BV62: =",A.`"&R62&"` = B.`"&R62&"`" -> ,A.`DG_ID` = B.`DG_ID` | BX62: =",`"&R62&"`" -> ,`DG_ID` | BZ62: =",`"&R62&"`" -> ,`DG_ID`
A63: @38 | B63: 9 | D63: ＡＵＸコード | R63: AUX_CD | AC63: {=_xlfn.SWITCH(BM63,"String","varchar("&BN63&")","Long","int","Integer","smallint","Double","decimal(9,2)","Currency","int")} -> smallint | AT63: ０：一般 １：会員 | BM63: Integer | BP63: =",`"&R63&"` "&AC63&" "&IF(AJ63="Y","NOT NULL","")&" COMMENT '"&D63&" "&AT63&"'" -> ,`AUX_CD` smallint COMMENT 'ＡＵＸコード ０：一般 １：会員' | BQ63: `AUX_CD` smallint DEFAULT NULL COMMENT 'ＡＵＸコード ０：一般 １：会員', | BR63: =",`"&R63&"` "&AC63&" "&IF(AJ63="Y","NOT NULL","") -> ,`AUX_CD` smallint | BT63: =",`"&R63&"`" -> ,`AUX_CD` | BV63: =",A.`"&R63&"` = B.`"&R63&"`" -> ,A.`AUX_CD` = B.`AUX_CD` | BX63: =",`"&R63&"`" -> ,`AUX_CD` | BZ63: =",`"&R63&"`" -> ,`AUX_CD`
A64: @39 | B64: 9 | D64: 割引アカウント | R64: DISC_ACCT | AC64: {=_xlfn.SWITCH(BM64,"String","varchar("&BN64&")","Long","int","Integer","smallint","Double","decimal(9,2)","Currency","int")} -> varchar(20) | AT64: 現在未使用 Ｎull固定 | BM64: String | BN64: 20 | BP64: =",`"&R64&"` "&AC64&" "&IF(AJ64="Y","NOT NULL","")&" COMMENT '"&D64&" "&AT64&"'" -> ,`DISC_ACCT` varchar(20) COMMENT '割引アカウント 現在未使用 Ｎull固定' | BQ64: `DISC_ACCT` varchar(20) DEFAULT NULL COMMENT '割引アカウント 現在未使用 Ｎull固定', | BR64: =",`"&R64&"` "&AC64&" "&IF(AJ64="Y","NOT NULL","") -> ,`DISC_ACCT` varchar(20) | BT64: =",`"&R64&"`" -> ,`DISC_ACCT` | BV64: =",A.`"&R64&"` = B.`"&R64&"`" -> ,A.`DISC_ACCT` = B.`DISC_ACCT` | BX64: =",`"&R64&"`" -> ,`DISC_ACCT` | BZ64: =",`"&R64&"`" -> ,`DISC_ACCT`
A65: @40 | B65: 9 | D65: 割引クラスＩＤ | R65: DISC_CLASS_ID | AC65: {=_xlfn.SWITCH(BM65,"String","varchar("&BN65&")","Long","int","Integer","smallint","Double","decimal(9,2)","Currency","int")} -> int | AT65: 現在未使用 ０固定 | BM65: Long | BP65: =",`"&R65&"` "&AC65&" "&IF(AJ65="Y","NOT NULL","")&" COMMENT '"&D65&" "&AT65&"'" -> ,`DISC_CLASS_ID` int COMMENT '割引クラスＩＤ 現在未使用 ０固定' | BQ65: `DISC_CLASS_ID` int DEFAULT NULL COMMENT '割引クラスＩＤ 現在未使用 ０固定', | BR65: =",`"&R65&"` "&AC65&" "&IF(AJ65="Y","NOT NULL","") -> ,`DISC_CLASS_ID` int | BT65: =",`"&R65&"`" -> ,`DISC_CLASS_ID` | BV65: =",A.`"&R65&"` = B.`"&R65&"`" -> ,A.`DISC_CLASS_ID` = B.`DISC_CLASS_ID` | BX65: =",`"&R65&"`" -> ,`DISC_CLASS_ID` | BZ65: =",`"&R65&"`" -> ,`DISC_CLASS_ID`
A66: @41 | B66: 9 | D66: 特売最大値引額 | R66: MAX_DISC_AMT | AC66: {=_xlfn.SWITCH(BM66,"String","varchar("&BN66&")","Long","int","Integer","smallint","Double","decimal(9,2)","Currency","int")} -> int | AT66: 現在未使用 ０固定 | BM66: Currency | BP66: =",`"&R66&"` "&AC66&" "&IF(AJ66="Y","NOT NULL","")&" COMMENT '"&D66&" "&AT66&"'" -> ,`MAX_DISC_AMT` int COMMENT '特売最大値引額 現在未使用 ０固定' | BQ66: `MAX_DISC_AMT` int DEFAULT NULL COMMENT '特売最大値引額 現在未使用 ０固定', | BR66: =",`"&R66&"` "&AC66&" "&IF(AJ66="Y","NOT NULL","") -> ,`MAX_DISC_AMT` int | BT66: =",`"&R66&"`" -> ,`MAX_DISC_AMT` | BV66: =",A.`"&R66&"` = B.`"&R66&"`" -> ,A.`MAX_DISC_AMT` = B.`MAX_DISC_AMT` | BX66: =",`"&R66&"`" -> ,`MAX_DISC_AMT` | BZ66: =",`"&R66&"`" -> ,`MAX_DISC_AMT`
A67: @42 | B67: 9 | D67: 割引トラン数 | R67: DISC_TRAN_CNT | AC67: {=_xlfn.SWITCH(BM67,"String","varchar("&BN67&")","Long","int","Integer","smallint","Double","decimal(9,2)","Currency","int")} -> smallint | AT67: 現在未使用 ０固定 | BM67: Integer | BP67: =",`"&R67&"` "&AC67&" "&IF(AJ67="Y","NOT NULL","")&" COMMENT '"&D67&" "&AT67&"'" -> ,`DISC_TRAN_CNT` smallint COMMENT '割引トラン数 現在未使用 ０固定' | BQ67: `DISC_TRAN_CNT` smallint DEFAULT NULL COMMENT '割引トラン数 現在未使用 ０固定', | BR67: =",`"&R67&"` "&AC67&" "&IF(AJ67="Y","NOT NULL","") -> ,`DISC_TRAN_CNT` smallint | BT67: =",`"&R67&"`" -> ,`DISC_TRAN_CNT` | BV67: =",A.`"&R67&"` = B.`"&R67&"`" -> ,A.`DISC_TRAN_CNT` = B.`DISC_TRAN_CNT` | BX67: =",`"&R67&"`" -> ,`DISC_TRAN_CNT` | BZ67: =",`"&R67&"`" -> ,`DISC_TRAN_CNT`
A68: @43 | B68: 9 | D68: バッチＮｏ． | R68: BATCH_NBR | AC68: {=_xlfn.SWITCH(BM68,"String","varchar("&BN68&")","Long","int","Integer","smallint","Double","decimal(9,2)","Currency","int")} -> int | AT68: 現在未使用 ０固定 | BM68: Long | BP68: =",`"&R68&"` "&AC68&" "&IF(AJ68="Y","NOT NULL","")&" COMMENT '"&D68&" "&AT68&"'" -> ,`BATCH_NBR` int COMMENT 'バッチＮｏ． 現在未使用 ０固定' | BQ68: `BATCH_NBR` int DEFAULT NULL COMMENT 'バッチＮｏ． 現在未使用 ０固定', | BR68: =",`"&R68&"` "&AC68&" "&IF(AJ68="Y","NOT NULL","") -> ,`BATCH_NBR` int | BT68: =",`"&R68&"`" -> ,`BATCH_NBR` | BV68: =",A.`"&R68&"` = B.`"&R68&"`" -> ,A.`BATCH_NBR` = B.`BATCH_NBR` | BX68: =",`"&R68&"`" -> ,`BATCH_NBR` | BZ68: =",`"&R68&"`" -> ,`BATCH_NBR`
A69: @44 | B69: 9 | D69: シーケンス番号 | R69: SEQ_ID | AC69: {=_xlfn.SWITCH(BM69,"String","varchar("&BN69&")","Long","int","Integer","smallint","Double","decimal(9,2)","Currency","int")} -> smallint | AT69: 現在未使用 ０固定 | BM69: Integer | BP69: =",`"&R69&"` "&AC69&" "&IF(AJ69="Y","NOT NULL","")&" COMMENT '"&D69&" "&AT69&"'" -> ,`SEQ_ID` smallint COMMENT 'シーケンス番号 現在未使用 ０固定' | BQ69: `SEQ_ID` smallint DEFAULT NULL COMMENT 'シーケンス番号 現在未使用 ０固定', | BR69: =",`"&R69&"` "&AC69&" "&IF(AJ69="Y","NOT NULL","") -> ,`SEQ_ID` smallint | BT69: =",`"&R69&"`" -> ,`SEQ_ID` | BV69: =",A.`"&R69&"` = B.`"&R69&"`" -> ,A.`SEQ_ID` = B.`SEQ_ID` | BX69: =",`"&R69&"`" -> ,`SEQ_ID` | BZ69: =",`"&R69&"`" -> ,`SEQ_ID`
A70: @45 | B70: 9 | D70: 成立数量 | R70: MIN_QTY | AC70: {=_xlfn.SWITCH(BM70,"String","varchar("&BN70&")","Long","int","Integer","smallint","Double","decimal(9,2)","Currency","int")} -> decimal(9,2) | AT70: 現在未使用 ０固定 | BM70: Double | BP70: =",`"&R70&"` "&AC70&" "&IF(AJ70="Y","NOT NULL","")&" COMMENT '"&D70&" "&AT70&"'" -> ,`MIN_QTY` decimal(9,2) COMMENT '成立数量 現在未使用 ０固定' | BQ70: `MIN_QTY` decimal(9,2) DEFAULT NULL COMMENT '成立数量 現在未使用 ０固定', | BR70: =",`"&R70&"` "&AC70&" "&IF(AJ70="Y","NOT NULL","") -> ,`MIN_QTY` decimal(9,2) | BT70: =",`"&R70&"`" -> ,`MIN_QTY` | BV70: =",A.`"&R70&"` = B.`"&R70&"`" -> ,A.`MIN_QTY` = B.`MIN_QTY` | BX70: =",`"&R70&"`" -> ,`MIN_QTY` | BZ70: =",`"&R70&"`" -> ,`MIN_QTY`
A71: @46 | B71: 9 | D71: 成立価格 | R71: MIN_AMT | AC71: {=_xlfn.SWITCH(BM71,"String","varchar("&BN71&")","Long","int","Integer","smallint","Double","decimal(9,2)","Currency","int")} -> int | AT71: 現在未使用 ０固定 | BM71: Currency | BP71: =",`"&R71&"` "&AC71&" "&IF(AJ71="Y","NOT NULL","")&" COMMENT '"&D71&" "&AT71&"'" -> ,`MIN_AMT` int COMMENT '成立価格 現在未使用 ０固定' | BQ71: `MIN_AMT` int DEFAULT NULL COMMENT '成立価格 現在未使用 ０固定', | BR71: =",`"&R71&"` "&AC71&" "&IF(AJ71="Y","NOT NULL","") -> ,`MIN_AMT` int | BT71: =",`"&R71&"`" -> ,`MIN_AMT` | BV71: =",A.`"&R71&"` = B.`"&R71&"`" -> ,A.`MIN_AMT` = B.`MIN_AMT` | BX71: =",`"&R71&"`" -> ,`MIN_AMT` | BZ71: =",`"&R71&"`" -> ,`MIN_AMT`
A72: @47 | B72: 9 | D72: ＡＵＸコード２ | R72: AUX_CD2 | AC72: {=_xlfn.SWITCH(BM72,"String","varchar("&BN72&")","Long","int","Integer","smallint","Double","decimal(9,2)","Currency","int")} -> smallint | AT72: 現在未使用 ０固定 | BM72: Integer | BP72: =",`"&R72&"` "&AC72&" "&IF(AJ72="Y","NOT NULL","")&" COMMENT '"&D72&" "&AT72&"'" -> ,`AUX_CD2` smallint COMMENT 'ＡＵＸコード２ 現在未使用 ０固定' | BQ72: `AUX_CD2` smallint DEFAULT NULL COMMENT 'ＡＵＸコード２ 現在未使用 ０固定', | BR72: =",`"&R72&"` "&AC72&" "&IF(AJ72="Y","NOT NULL","") -> ,`AUX_CD2` smallint | BT72: =",`"&R72&"`" -> ,`AUX_CD2` | BV72: =",A.`"&R72&"` = B.`"&R72&"`" -> ,A.`AUX_CD2` = B.`AUX_CD2` | BX72: =",`"&R72&"`" -> ,`AUX_CD2` | BZ72: =",`"&R72&"`" -> ,`AUX_CD2`
A73: @48 | B73: 9 | D73: テナントコード | R73: TNT_ID | AC73: {=_xlfn.SWITCH(BM73,"String","varchar("&BN73&")","Long","int","Integer","smallint","Double","decimal(9,2)","Currency","int")} -> int | AT73: 現在未使用 ０固定 | BM73: Long | BP73: =",`"&R73&"` "&AC73&" "&IF(AJ73="Y","NOT NULL","")&" COMMENT '"&D73&" "&AT73&"'" -> ,`TNT_ID` int COMMENT 'テナントコード 現在未使用 ０固定' | BQ73: `TNT_ID` int DEFAULT NULL COMMENT 'テナントコード 現在未使用 ０固定', | BR73: =",`"&R73&"` "&AC73&" "&IF(AJ73="Y","NOT NULL","") -> ,`TNT_ID` int | BT73: =",`"&R73&"`" -> ,`TNT_ID` | BV73: =",A.`"&R73&"` = B.`"&R73&"`" -> ,A.`TNT_ID` = B.`TNT_ID` | BX73: =",`"&R73&"`" -> ,`TNT_ID` | BZ73: =",`"&R73&"`" -> ,`TNT_ID`
A74: @49 | B74: 9 | D74: ＰＬＵ属性２ | R74: PLU_QUAL_TYP2 | AC74: {=_xlfn.SWITCH(BM74,"String","varchar("&BN74&")","Long","int","Integer","smallint","Double","decimal(9,2)","Currency","int")} -> int | AT74: 現在未使用 ０固定 | BM74: Long | BP74: =",`"&R74&"` "&AC74&" "&IF(AJ74="Y","NOT NULL","")&" COMMENT '"&D74&" "&AT74&"'" -> ,`PLU_QUAL_TYP2` int COMMENT 'ＰＬＵ属性２ 現在未使用 ０固定' | BQ74: `PLU_QUAL_TYP2` int DEFAULT NULL COMMENT 'ＰＬＵ属性２ 現在未使用 ０固定', | BR74: =",`"&R74&"` "&AC74&" "&IF(AJ74="Y","NOT NULL","") -> ,`PLU_QUAL_TYP2` int | BT74: =",`"&R74&"`" -> ,`PLU_QUAL_TYP2` | BV74: =",A.`"&R74&"` = B.`"&R74&"`" -> ,A.`PLU_QUAL_TYP2` = B.`PLU_QUAL_TYP2` | BX74: =",`"&R74&"`" -> ,`PLU_QUAL_TYP2` | BZ74: =",`"&R74&"`" -> ,`PLU_QUAL_TYP2`
A75: @50 | B75: 9 | D75: 作成日 | R75: CRT_DT | AC75: {=_xlfn.SWITCH(BM75,"String","varchar("&BN75&")","Long","int","Integer","smallint","Double","decimal(9,2)","Currency","int")} -> varchar(8) | AT75: ＹＹＹＹＭＭＤＤ形式で8桁フルに設定すること | BM75: String | BN75: 8 | BP75: =",`"&R75&"` "&AC75&" "&IF(AJ75="Y","NOT NULL","")&" COMMENT '"&D75&" "&AT75&"'" -> ,`CRT_DT` varchar(8) COMMENT '作成日 ＹＹＹＹＭＭＤＤ形式で8桁フルに設定すること' | BQ75: `CRT_DT` varchar(8) DEFAULT NULL COMMENT '作成日 ＹＹＹＹＭＭＤＤ形式で8桁フルに設定すること', | BR75: =",`"&R75&"` "&AC75&" "&IF(AJ75="Y","NOT NULL","") -> ,`CRT_DT` varchar(8) | BT75: =",`"&R75&"`" -> ,`CRT_DT` | BV75: =",A.`"&R75&"` = B.`"&R75&"`" -> ,A.`CRT_DT` = B.`CRT_DT` | BX75: =",`"&R75&"`" -> ,`CRT_DT` | BZ75: =",`"&R75&"`" -> ,`CRT_DT`
A76: @51 | B76: 9 | D76: 処理日 | R76: PRCS_DT | AC76: {=_xlfn.SWITCH(BM76,"String","varchar("&BN76&")","Long","int","Integer","smallint","Double","decimal(9,2)","Currency","int")} -> varchar(8) | AT76: ＹＹＹＹＭＭＤＤ形式で8桁フルに設定すること | BM76: String | BN76: 8 | BP76: =",`"&R76&"` "&AC76&" "&IF(AJ76="Y","NOT NULL","")&" COMMENT '"&D76&" "&AT76&"'" -> ,`PRCS_DT` varchar(8) COMMENT '処理日 ＹＹＹＹＭＭＤＤ形式で8桁フルに設定すること' | BQ76: `PRCS_DT` varchar(8) DEFAULT NULL COMMENT '処理日 ＹＹＹＹＭＭＤＤ形式で8桁フルに設定すること', | BR76: =",`"&R76&"` "&AC76&" "&IF(AJ76="Y","NOT NULL","") -> ,`PRCS_DT` varchar(8) | BT76: =",`"&R76&"`" -> ,`PRCS_DT` | BV76: =",A.`"&R76&"` = B.`"&R76&"`" -> ,A.`PRCS_DT` = B.`PRCS_DT` | BX76: =",`"&R76&"`" -> ,`PRCS_DT` | BZ76: =",`"&R76&"`" -> ,`PRCS_DT`
A77: @52 | B77: 9 | D77: 受信日 | R77: RCV_DT | AC77: {=_xlfn.SWITCH(BM77,"String","varchar("&BN77&")","Long","int","Integer","smallint","Double","decimal(9,2)","Currency","int")} -> varchar(8) | AT77: Ｎｕｌｌ固定 システム内で使用 | BM77: String | BN77: 8 | BP77: =",`"&R77&"` "&AC77&" "&IF(AJ77="Y","NOT NULL","")&" COMMENT '"&D77&" "&AT77&"'" -> ,`RCV_DT` varchar(8) COMMENT '受信日 Ｎｕｌｌ固定 システム内で使用' | BQ77: `RCV_DT` varchar(8) DEFAULT NULL COMMENT '受信日 Ｎｕｌｌ固定 システム内で使用', | BR77: =",`"&R77&"` "&AC77&" "&IF(AJ77="Y","NOT NULL","") -> ,`RCV_DT` varchar(8) | BT77: =",`"&R77&"`" -> ,`RCV_DT` | BV77: =",A.`"&R77&"` = B.`"&R77&"`" -> ,A.`RCV_DT` = B.`RCV_DT` | BX77: =",`"&R77&"`" -> ,`RCV_DT` | BZ77: =",`"&R77&"`" -> ,`RCV_DT`
A78: @53 | B78: 9 | D78: 処理フラグ | R78: PRCS_FG | AC78: {=_xlfn.SWITCH(BM78,"String","varchar("&BN78&")","Long","int","Integer","smallint","Double","decimal(9,2)","Currency","int")} -> varchar(1) | AT78: ＊固定 システム内で使用（＊：未処理 １：処理済） | BM78: String | BN78: 1 | BP78: =",`"&R78&"` "&AC78&" "&IF(AJ78="Y","NOT NULL","")&" COMMENT '"&D78&" "&AT78&"'" -> ,`PRCS_FG` varchar(1) COMMENT '処理フラグ ＊固定 システム内で使用（＊：未処理 １：処理済）' | BQ78: `PRCS_FG` varchar(1) DEFAULT NULL COMMENT '処理フラグ ＊固定 システム内で使用（＊：未処理 １：処理済）', | BR78: =",`"&R78&"` "&AC78&" "&IF(AJ78="Y","NOT NULL","") -> ,`PRCS_FG` varchar(1) | BT78: =",`"&R78&"`" -> ,`PRCS_FG` | BV78: =",A.`"&R78&"` = B.`"&R78&"`" -> ,A.`PRCS_FG` = B.`PRCS_FG` | BX78: =",`"&R78&"`" -> ,`PRCS_FG` | BZ78: =",`"&R78&"`" -> ,`PRCS_FG`
BP79: =" , PRIMARY KEY ("&IF(_xlfn.XLOOKUP(1,$AH:$AH,$R:$R,"",0)="","","`"&_xlfn.XLOOKUP(1,$AH:$AH,$R:$R,"",0)&"`")&IF(_xlfn.XLOOKUP(2,$AH:$AH,$R:$R,"",0)="","",",`"&_xlfn.XLOOKUP(2,$AH:$AH,$R:$R,"",0)&"`")&IF(_xlfn.XLOOKUP(3,$AH:$AH,$R:$R,"",0)="","",",`"&_xlfn.XLOOKUP(3,$AH:$AH,$R:$R,"",0)&"`")&IF(_xlfn.XLOOKUP(4,$AH:$AH,$R:$R,"",0)="","",",`"&_xlfn.XLOOKUP(4,$AH:$AH,$R:$R,"",0)&"`")&IF(_xlfn.XLOOKUP(5,$AH:$AH,$R:$R,"",0)="","",",`"&_xlfn.XLOOKUP(5,$AH:$AH,$R:$R,"",0)&"`")&IF(_xlfn.XLOOKUP(6,$AH:$AH,$R:$R,"",0)="","",",`"&_xlfn.XLOOKUP(6,$AH:$AH,$R:$R,"",0)&"`")&IF(_xlfn.XLOOKUP(7,$AH:$AH,$R:$R,"",0)="","",",`"&_xlfn.XLOOKUP(7,$AH:$AH,$R:$R,"",0)&"`")&IF(_xlfn.XLOOKUP(8,$AH:$AH,$R:$R,"",0)="","",",`"&_xlfn.XLOOKUP(8,$AH:$AH,$R:$R,"",0)&"`")&")," -> , PRIMARY KEY (`STR_ID`,`EVNT_NBR`,`EVNT_BGN_TM`,`EVNT_END_TM`,`PLU_ID`,`MBR_FG`), | BQ79: PRIMARY KEY (`STR_ID`,`EVNT_NBR`,`EVNT_BGN_TM`,`EVNT_END_TM`,`PLU_ID`,`MBR_FG`) USING BTREE, | BR79: =" , PRIMARY KEY ("&IF(_xlfn.XLOOKUP(1,$AH:$AH,$R:$R,"",0)="","","`"&_xlfn.XLOOKUP(1,$AH:$AH,$R:$R,"",0)&"`")&IF(_xlfn.XLOOKUP(2,$AH:$AH,$R:$R,"",0)="","",",`"&_xlfn.XLOOKUP(2,$AH:$AH,$R:$R,"",0)&"`")&IF(_xlfn.XLOOKUP(3,$AH:$AH,$R:$R,"",0)="","",",`"&_xlfn.XLOOKUP(3,$AH:$AH,$R:$R,"",0)&"`")&IF(_xlfn.XLOOKUP(4,$AH:$AH,$R:$R,"",0)="","",",`"&_xlfn.XLOOKUP(4,$AH:$AH,$R:$R,"",0)&"`")&IF(_xlfn.XLOOKUP(5,$AH:$AH,$R:$R,"",0)="","",",`"&_xlfn.XLOOKUP(5,$AH:$AH,$R:$R,"",0)&"`")&IF(_xlfn.XLOOKUP(6,$AH:$AH,$R:$R,"",0)="","",",`"&_xlfn.XLOOKUP(6,$AH:$AH,$R:$R,"",0)&"`")&IF(_xlfn.XLOOKUP(7,$AH:$AH,$R:$R,"",0)="","",",`"&_xlfn.XLOOKUP(7,$AH:$AH,$R:$R,"",0)&"`")&IF(_xlfn.XLOOKUP(8,$AH:$AH,$R:$R,"",0)="","",",`"&_xlfn.XLOOKUP(8,$AH:$AH,$R:$R,"",0)&"`")&")" -> , PRIMARY KEY (`STR_ID`,`EVNT_NBR`,`EVNT_BGN_TM`,`EVNT_END_TM`,`PLU_ID`,`MBR_FG`) | BT79: ); | BV79: WHERE | BZ79: ="FROM `TMP`.`"&$G$10&"` A" -> FROM `TMP`.`GHDISCOUNTM` A
BP80: KEY `RECORD_ID` (`RECORD_ID`) | BQ80: KEY `RECORD_ID` (`RECORD_ID`) | BR80: =") ENGINE=InnoDB DEFAULT CHARSET=utf8mb4 COLLATE=utf8mb4_0900_ai_ci COMMENT = '"&$G$9&"_TMP';" -> ) ENGINE=InnoDB DEFAULT CHARSET=utf8mb4 COLLATE=utf8mb4_0900_ai_ci COMMENT = '特売メンテ_TMP'; | BV80: =IF(_xlfn.XLOOKUP(1,$AH:$AH,$R:$R,"",0)="","","A.`"&_xlfn.XLOOKUP(1,$AH:$AH,$R:$R,"",0)&"` = B.`"&_xlfn.XLOOKUP(1,$AH:$AH,$R:$R,"",0)&"`") -> A.`STR_ID` = B.`STR_ID` | BZ80: WHERE NOT EXISTS ( SELECT RECORD_ID
B81: ■インデックス情報 | BP81: =") ENGINE=InnoDB DEFAULT CHARSET=utf8mb4 COLLATE=utf8mb4_0900_ai_ci COMMENT = '"&$G$9&"';" -> ) ENGINE=InnoDB DEFAULT CHARSET=utf8mb4 COLLATE=utf8mb4_0900_ai_ci COMMENT = '特売メンテ'; | BQ81: ) ENGINE=InnoDB DEFAULT CHARSET=utf8mb4 COLLATE=utf8mb4_0900_ai_ci COMMENT='特売メンテ'; | BV81: =IF(_xlfn.XLOOKUP(2,$AH:$AH,$R:$R,"",0)="","","AND A.`"&_xlfn.XLOOKUP(2,$AH:$AH,$R:$R,"",0)&"` = B.`"&_xlfn.XLOOKUP(2,$AH:$AH,$R:$R,"",0)&"`") -> AND A.`EVNT_NBR` = B.`EVNT_NBR` | BZ81: ="FROM `REPLICA_KASUMI`.`"&$G$10&"` B" -> FROM `REPLICA_KASUMI`.`GHDISCOUNTM` B
B82: No. | D82: Index名 | R82: カラム一覧 | AL82: プライマリキー | AP82: ユニーク | AT82: 備考 | BV82: =IF(_xlfn.XLOOKUP(3,$AH:$AH,$R:$R,"",0)="","","AND A.`"&_xlfn.XLOOKUP(3,$AH:$AH,$R:$R,"",0)&"` = B.`"&_xlfn.XLOOKUP(3,$AH:$AH,$R:$R,"",0)&"`") -> AND A.`EVNT_BGN_TM` = B.`EVNT_BGN_TM` | BZ82: WHERE
B83: 1 | D83: PRIMARY | R83: =IF(_xlfn.XLOOKUP(1,AH:AH,R:R,"",0)="","","`"&_xlfn.XLOOKUP(1,AH:AH,R:R,"",0)&"`")&IF(_xlfn.XLOOKUP(2,AH:AH,R:R,"",0)="","",",`"&_xlfn.XLOOKUP(2,AH:AH,R:R,"",0)&"`")&IF(_xlfn.XLOOKUP(3,AH:AH,R:R,"",0)="","",",`"&_xlfn.XLOOKUP(3,AH:AH,R:R,"",0)&"`")&IF(_xlfn.XLOOKUP(4,AH:AH,R:R,"",0)="","",",`"&_xlfn.XLOOKUP(4,AH:AH,R:R,"",0)&"`")&IF(_xlfn.XLOOKUP(5,AH:AH,R:R,"",0)="","",",`"&_xlfn.XLOOKUP(5,AH:AH,R:R,"",0)&"`")&IF(_xlfn.XLOOKUP(6,AH:AH,R:R,"",0)="","",",`"&_xlfn.XLOOKUP(6,AH:AH,R:R,"",0)&"`")&IF(_xlfn.XLOOKUP(7,AH:AH,R:R,"",0)="","",",`"&_xlfn.XLOOKUP(7,AH:AH,R:R,"",0)&"`")&IF(_xlfn.XLOOKUP(8,AH:AH,R:R,"",0)="","",",`"&_xlfn.XLOOKUP(8,AH:AH,R:R,"",0)&"`") -> `STR_ID`,`EVNT_NBR`,`EVNT_BGN_TM`,`EVNT_END_TM`,`PLU_ID`,`MBR_FG` | AL83: Y | AP83: Y | BP83: ="CREATE TRIGGER `"&$G$10&"_CR_Date_Time` BEFORE INSERT ON `"&$G$10&"` FOR EACH ROW SET NEW.record_create_date = CURRENT_DATE, NEW.record_create_time = CURRENT_TIME, NEW.record_update_date = CURRENT_DATE, NEW.record_update_time = CURRENT_TIME;" -> CREATE TRIGGER `GHDISCOUNTM_CR_Date_Time` BEFORE INSERT ON `GHDISCOUNTM` FOR EACH ROW SET NEW.record_create_date = CURRENT_DATE, NEW.record_create_time = CURRENT_TIME, NEW.record_update_date = CURRENT_DATE, NEW.record_update_time = CURRENT_TIME; | BQ83: CREATE DEFINER=`posuser`@`%` TRIGGER `GHDISCOUNTM_CR_Date_Time` BEFORE INSERT ON `ghdiscountm` FOR EACH ROW SET NEW.record_create_date = CURRENT_DATE, NEW.record_create_time = CURRENT_TIME, NEW.record_update_date = CURRENT_DATE, NEW.record_update_time = CURRENT_TIME; | BV83: =IF(_xlfn.XLOOKUP(4,$AH:$AH,$R:$R,"",0)="","","AND A.`"&_xlfn.XLOOKUP(4,$AH:$AH,$R:$R,"",0)&"` = B.`"&_xlfn.XLOOKUP(4,$AH:$AH,$R:$R,"",0)&"`") -> AND A.`EVNT_END_TM` = B.`EVNT_END_TM` | BZ83: =IF(_xlfn.XLOOKUP(1,$AH:$AH,$R:$R,"",0)="","","A.`"&_xlfn.XLOOKUP(1,$AH:$AH,$R:$R,"",0)&"` = B.`"&_xlfn.XLOOKUP(1,$AH:$AH,$R:$R,"",0)&"`") -> A.`STR_ID` = B.`STR_ID`
BP84: ="CREATE TRIGGER `"&$G$10&"_UP_Date_Time` BEFORE UPDATE ON `"&$G$10&"` FOR EACH ROW SET NEW.record_update_date = CURRENT_DATE, NEW.record_update_time = CURRENT_TIME;" -> CREATE TRIGGER `GHDISCOUNTM_UP_Date_Time` BEFORE UPDATE ON `GHDISCOUNTM` FOR EACH ROW SET NEW.record_update_date = CURRENT_DATE, NEW.record_update_time = CURRENT_TIME; | BV84: =IF(_xlfn.XLOOKUP(5,$AH:$AH,$R:$R,"",0)="","","AND A.`"&_xlfn.XLOOKUP(5,$AH:$AH,$R:$R,"",0)&"` = B.`"&_xlfn.XLOOKUP(5,$AH:$AH,$R:$R,"",0)&"`") -> AND A.`PLU_ID` = B.`PLU_ID` | BZ84: =IF(_xlfn.XLOOKUP(2,$AH:$AH,$R:$R,"",0)="","","AND A.`"&_xlfn.XLOOKUP(2,$AH:$AH,$R:$R,"",0)&"` = B.`"&_xlfn.XLOOKUP(2,$AH:$AH,$R:$R,"",0)&"`") -> AND A.`EVNT_NBR` = B.`EVNT_NBR`
BQ85: CREATE DEFINER=`posuser`@`%` TRIGGER `GHDISCOUNTM_UP_Date_Time` BEFORE UPDATE ON `ghdiscountm` FOR EACH ROW SET NEW.record_update_date = CURRENT_DATE, NEW.record_update_time = CURRENT_TIME; | BV85: =IF(_xlfn.XLOOKUP(6,$AH:$AH,$R:$R,"",0)="","","AND A.`"&_xlfn.XLOOKUP(6,$AH:$AH,$R:$R,"",0)&"` = B.`"&_xlfn.XLOOKUP(6,$AH:$AH,$R:$R,"",0)&"`") -> AND A.`MBR_FG` = B.`MBR_FG` | BZ85: =IF(_xlfn.XLOOKUP(3,$AH:$AH,$R:$R,"",0)="","","AND A.`"&_xlfn.XLOOKUP(3,$AH:$AH,$R:$R,"",0)&"` = B.`"&_xlfn.XLOOKUP(3,$AH:$AH,$R:$R,"",0)&"`") -> AND A.`EVNT_BGN_TM` = B.`EVNT_BGN_TM`
B86: トリガー情報 | BV86: =IF(_xlfn.XLOOKUP(7,$AH:$AH,$R:$R,"",0)="","","AND A.`"&_xlfn.XLOOKUP(7,$AH:$AH,$R:$R,"",0)&"` = B.`"&_xlfn.XLOOKUP(7,$AH:$AH,$R:$R,"",0)&"`") | BZ86: =IF(_xlfn.XLOOKUP(4,$AH:$AH,$R:$R,"",0)="","","AND A.`"&_xlfn.XLOOKUP(4,$AH:$AH,$R:$R,"",0)&"` = B.`"&_xlfn.XLOOKUP(4,$AH:$AH,$R:$R,"",0)&"`") -> AND A.`EVNT_END_TM` = B.`EVNT_END_TM`
B87: No. | D87: トリガー名 | R87: イベント | U87: タイミング | Y87: 条件 | BV87: =IF(_xlfn.XLOOKUP(8,$AH:$AH,$R:$R,"",0)="","","AND A.`"&_xlfn.XLOOKUP(8,$AH:$AH,$R:$R,"",0)&"` = B.`"&_xlfn.XLOOKUP(8,$AH:$AH,$R:$R,"",0)&"`") | BZ87: =IF(_xlfn.XLOOKUP(5,$AH:$AH,$R:$R,"",0)="","","AND A.`"&_xlfn.XLOOKUP(5,$AH:$AH,$R:$R,"",0)&"` = B.`"&_xlfn.XLOOKUP(5,$AH:$AH,$R:$R,"",0)&"`") -> AND A.`PLU_ID` = B.`PLU_ID`
B88: 1 | D88: =G10&"_"&R88&"_"&"trg" -> GHDISCOUNTM_update_trg | R88: update | U88: Before row | Y88: auto_updated_date | BV88: ; | BZ88: =IF(_xlfn.XLOOKUP(6,$AH:$AH,$R:$R,"",0)="","","AND A.`"&_xlfn.XLOOKUP(6,$AH:$AH,$R:$R,"",0)&"` = B.`"&_xlfn.XLOOKUP(6,$AH:$AH,$R:$R,"",0)&"`") -> AND A.`MBR_FG` = B.`MBR_FG`
BZ89: =IF(_xlfn.XLOOKUP(7,$AH:$AH,$R:$R,"",0)="","","AND A.`"&_xlfn.XLOOKUP(7,$AH:$AH,$R:$R,"",0)&"` = B.`"&_xlfn.XLOOKUP(7,$AH:$AH,$R:$R,"",0)&"`")
BZ90: =IF(_xlfn.XLOOKUP(8,$AH:$AH,$R:$R,"",0)="","","AND A.`"&_xlfn.XLOOKUP(8,$AH:$AH,$R:$R,"",0)&"` = B.`"&_xlfn.XLOOKUP(8,$AH:$AH,$R:$R,"",0)&"`")
BZ91: );
BZ94: ="DROP TABLE IF EXISTS `TMP`.`"&$G$10&"`;" -> DROP TABLE IF EXISTS `TMP`.`GHDISCOUNTM`;
BZ95: COMMIT;
BV100: =",A.`"&R100&"` = B.`"&R100&"`" -> ,A.`` = B.`` | BX100: =",`"&R100&"`" -> ,`` | BZ100: =",`"&R100&"`" -> ,``
BV101: =",A.`"&R101&"` = B.`"&R101&"`" -> ,A.`` = B.`` | BX101: =",`"&R101&"`" -> ,`` | BZ101: =",`"&R101&"`" -> ,``
BV102: =",A.`"&R102&"` = B.`"&R102&"`" -> ,A.`` = B.`` | BX102: =",`"&R102&"`" -> ,`` | BZ102: =",`"&R102&"`" -> ,``
BV103: =",A.`"&R103&"` = B.`"&R103&"`" -> ,A.`` = B.`` | BX103: =",`"&R103&"`" -> ,`` | BZ103: =",`"&R103&"`" -> ,``
BV104: =",A.`"&R104&"` = B.`"&R104&"`" -> ,A.`` = B.`` | BX104: =",`"&R104&"`" -> ,`` | BZ104: =",`"&R104&"`" -> ,``
BV105: =",A.`"&R105&"` = B.`"&R105&"`" -> ,A.`` = B.`` | BX105: =",`"&R105&"`" -> ,`` | BZ105: =",`"&R105&"`" -> ,``
BV106: =",A.`"&R106&"` = B.`"&R106&"`" -> ,A.`` = B.`` | BX106: =",`"&R106&"`" -> ,`` | BZ106: =",`"&R106&"`" -> ,``
BV107: =",A.`"&R107&"` = B.`"&R107&"`" -> ,A.`` = B.`` | BX107: =",`"&R107&"`" -> ,`` | BZ107: =",`"&R107&"`" -> ,``
BV108: WHERE | BZ108: ="FROM `TMP`.`"&$G$10&"` A" -> FROM `TMP`.`GHDISCOUNTM` A
BV109: =IF(_xlfn.XLOOKUP(1,$AH:$AH,$R:$R,"",0)="","","A.`"&_xlfn.XLOOKUP(1,$AH:$AH,$R:$R,"",0)&"` = B.`"&_xlfn.XLOOKUP(1,$AH:$AH,$R:$R,"",0)&"`") -> A.`STR_ID` = B.`STR_ID` | BZ109: WHERE NOT EXISTS ( SELECT RECORD_ID
BV110: =IF(_xlfn.XLOOKUP(2,$AH:$AH,$R:$R,"",0)="","","AND A.`"&_xlfn.XLOOKUP(2,$AH:$AH,$R:$R,"",0)&"` = B.`"&_xlfn.XLOOKUP(2,$AH:$AH,$R:$R,"",0)&"`") -> AND A.`EVNT_NBR` = B.`EVNT_NBR` | BZ110: ="FROM `REPLICA_KASUMI`.`"&$G$10&"` B" -> FROM `REPLICA_KASUMI`.`GHDISCOUNTM` B
BV111: =IF(_xlfn.XLOOKUP(3,$AH:$AH,$R:$R,"",0)="","","AND A.`"&_xlfn.XLOOKUP(3,$AH:$AH,$R:$R,"",0)&"` = B.`"&_xlfn.XLOOKUP(3,$AH:$AH,$R:$R,"",0)&"`") -> AND A.`EVNT_BGN_TM` = B.`EVNT_BGN_TM` | BZ111: WHERE
BV112: =IF(_xlfn.XLOOKUP(4,$AH:$AH,$R:$R,"",0)="","","AND A.`"&_xlfn.XLOOKUP(4,$AH:$AH,$R:$R,"",0)&"` = B.`"&_xlfn.XLOOKUP(4,$AH:$AH,$R:$R,"",0)&"`") -> AND A.`EVNT_END_TM` = B.`EVNT_END_TM` | BZ112: =IF(_xlfn.XLOOKUP(1,$AH:$AH,$R:$R,"",0)="","","A.`"&_xlfn.XLOOKUP(1,$AH:$AH,$R:$R,"",0)&"` = B.`"&_xlfn.XLOOKUP(1,$AH:$AH,$R:$R,"",0)&"`") -> A.`STR_ID` = B.`STR_ID`
BV113: =IF(_xlfn.XLOOKUP(5,$AH:$AH,$R:$R,"",0)="","","AND A.`"&_xlfn.XLOOKUP(5,$AH:$AH,$R:$R,"",0)&"` = B.`"&_xlfn.XLOOKUP(5,$AH:$AH,$R:$R,"",0)&"`") -> AND A.`PLU_ID` = B.`PLU_ID` | BZ113: =IF(_xlfn.XLOOKUP(2,$AH:$AH,$R:$R,"",0)="","","AND A.`"&_xlfn.XLOOKUP(2,$AH:$AH,$R:$R,"",0)&"` = B.`"&_xlfn.XLOOKUP(2,$AH:$AH,$R:$R,"",0)&"`") -> AND A.`EVNT_NBR` = B.`EVNT_NBR`
BV114: =IF(_xlfn.XLOOKUP(6,$AH:$AH,$R:$R,"",0)="","","AND A.`"&_xlfn.XLOOKUP(6,$AH:$AH,$R:$R,"",0)&"` = B.`"&_xlfn.XLOOKUP(6,$AH:$AH,$R:$R,"",0)&"`") -> AND A.`MBR_FG` = B.`MBR_FG` | BZ114: =IF(_xlfn.XLOOKUP(3,$AH:$AH,$R:$R,"",0)="","","AND A.`"&_xlfn.XLOOKUP(3,$AH:$AH,$R:$R,"",0)&"` = B.`"&_xlfn.XLOOKUP(3,$AH:$AH,$R:$R,"",0)&"`") -> AND A.`EVNT_BGN_TM` = B.`EVNT_BGN_TM`
BV115: =IF(_xlfn.XLOOKUP(7,$AH:$AH,$R:$R,"",0)="","","AND A.`"&_xlfn.XLOOKUP(7,$AH:$AH,$R:$R,"",0)&"` = B.`"&_xlfn.XLOOKUP(7,$AH:$AH,$R:$R,"",0)&"`") | BZ115: =IF(_xlfn.XLOOKUP(4,$AH:$AH,$R:$R,"",0)="","","AND A.`"&_xlfn.XLOOKUP(4,$AH:$AH,$R:$R,"",0)&"` = B.`"&_xlfn.XLOOKUP(4,$AH:$AH,$R:$R,"",0)&"`") -> AND A.`EVNT_END_TM` = B.`EVNT_END_TM`
BV116: =IF(_xlfn.XLOOKUP(8,$AH:$AH,$R:$R,"",0)="","","AND A.`"&_xlfn.XLOOKUP(8,$AH:$AH,$R:$R,"",0)&"` = B.`"&_xlfn.XLOOKUP(8,$AH:$AH,$R:$R,"",0)&"`") | BZ116: =IF(_xlfn.XLOOKUP(5,$AH:$AH,$R:$R,"",0)="","","AND A.`"&_xlfn.XLOOKUP(5,$AH:$AH,$R:$R,"",0)&"` = B.`"&_xlfn.XLOOKUP(5,$AH:$AH,$R:$R,"",0)&"`") -> AND A.`PLU_ID` = B.`PLU_ID`
...

Sheet MMマスタ
A1: システム名 | K1: システム種別 | W1: =IF(表紙!W1="","",表紙!W1) -> DB定義書 | AP1: 作成者 | AT1: 作成日 | AY1: 更新者 | BC1: 更新日 | BH1: 版数
A2: =IF(表紙!A2="","",表紙!A2) -> 現金専用簡易セルフPOS | K2: =IF(表紙!K2="","",表紙!K2) | AP2: =IF(表紙!AP2="","",表紙!AP2) -> きよはら | AT2: =IF(表紙!AT2="","",表紙!AT2) -> 44652 | AY2: =IF(表紙!AY2="","",表紙!AY2) -> Thanh Nguyên | BC2: =IF(表紙!BC2="","",表紙!BC2) -> 45285 | BH2: =IF(表紙!BH2="","",表紙!BH2) -> 0.2
A4: 機能カテゴリ | H4: =IF(表紙!H4="","",表紙!H4) -> 共通 | U4: 項目 | Z4: =IF(表紙!Z4="","",表紙!Z4) | AP4: テンプレート
B7: ■テーブル情報
B8: スキーマ名 | G8: Replica_Kasumi | Y8: RDBMS名
B9: 論理名 | G9: MMマスタ | Y9: バージョン
B10: 物理名 | G10: GHBUNDLEM
B11: 備考
B19: ■カラム情報 | BP19: ="DROP TABLE IF EXISTS `"&$G$8&"`.`"&$G$10&"`;" -> DROP TABLE IF EXISTS `Replica_Kasumi`.`GHBUNDLEM`;
B20: No. | D20: 論理名 | R20: 物理名 | AC20: データ型 | AH20: PK | AJ20: Not Null | AM20: デフォルト | AT20: 備考 | BP20: ="CREATE TABLE `"&$G$8&"`.`"&$G$10&"` (" -> CREATE TABLE `Replica_Kasumi`.`GHBUNDLEM` (
B21: 1 | D21: レコードID | R21: RECORD_ID | AC21: bigint | AJ21: Y | AM21: 自動追加 | BP21: `RECORD_ID` bigint NOT NULL AUTO_INCREMENT COMMENT 'レコードID'
B22: =B21+1 -> 2 | D22: レコード作成日付 | R22: RECORD_CREATE_DATE | AC22: date | AJ22: Y | AM22: CURRENT_DATE | BP22: ,`RECORD_CREATE_DATE` date NOT NULL COMMENT 'レコード作成日付'
B23: =B22+1 -> 3 | D23: レコード作成時間 | R23: RECORD_CREATE_TIME | AC23: time | AJ23: Y | AM23: CURRENT_TIME | BP23: ,`RECORD_CREATE_TIME` time NOT NULL COMMENT 'レコード作成時間' | BV23: SET CHARACTER_SET_DATABASE = UTF8;
B24: =B23+1 -> 4 | D24: レコード更新日付 | R24: RECORD_UPDATE_DATE | AC24: date | AJ24: Y | AM24: CURRENT_DATE | AT24: トリガーにより更新 | BP24: ,`RECORD_UPDATE_DATE` date NOT NULL COMMENT 'レコード更新日付/トリガーにより更新' | BV24: ="UPDATE `REPLICA_KASUMI`.`"&$G$10&"` A,`TMP`.`"&$G$10&"` B" -> UPDATE `REPLICA_KASUMI`.`GHBUNDLEM` A,`TMP`.`GHBUNDLEM` B
B25: =B24+1 -> 5 | D25: レコード更新時間 | R25: RECORD_UPDATE_TIME | AC25: time | AJ25: Y | AM25: CURRENT_TIME | AT25: トリガーにより更新 | BP25: ,`RECORD_UPDATE_TIME` time NOT NULL COMMENT 'レコード更新時間/トリガーにより更新' | BR25: ="DROP TABLE IF EXISTS `TMP`.`"&$G$10&"`;" -> DROP TABLE IF EXISTS `TMP`.`GHBUNDLEM`; | BT25: ="LOAD DATA INFILE 'C:/04_DATAFILE/"&$G$10&"/TMP/"&$G$10&".CSV' " -> LOAD DATA INFILE 'C:/04_DATAFILE/GHBUNDLEM/TMP/GHBUNDLEM.CSV' | BV25: SET
A26: @1 | B26: =B25+1 -> 6 | D26: レコード無効フラグ | R26: RECORD_VOID_FLAG | AC26: char(1) | AJ26: Y | AM26: "" | AT26: 0: 有効フラグ、 1:無効フラグ | BP26: ,`RECORD_VOID_FLAG` char(1) NOT NULL DEFAULT '' COMMENT 'レコード無効フラグ '''': 有効フラグ、 1:無効フラグ' | BR26: ="CREATE TABLE `TMP`.`"&G10&"` (" -> CREATE TABLE `TMP`.`GHBUNDLEM` ( | BT26: ="REPLACE INTO TABLE TMP.`"&$G$10&"` FIELDS TERMINATED BY ',' ENCLOSED BY '\""' LINES TERMINATED BY '\r\n' (" -> REPLACE INTO TABLE TMP.`GHBUNDLEM` FIELDS TERMINATED BY ',' ENCLOSED BY '\"' LINES TERMINATED BY '\r\n' ( | BX26: ="INSERT INTO `REPLICA_KASUMI`.`"&$G$10&"` (" -> INSERT INTO `REPLICA_KASUMI`.`GHBUNDLEM` ( | BZ26: ) SELECT
A27: @2 | B27: 7 | D27: 処理区分 | R27: PRCS_TYP | AC27: {=_xlfn.SWITCH(BM27,"String","varchar("&BN27&")","Long","int","Integer","smallint","Double","decimal(9,2)","Currency","int")} -> varchar(1) | AT27: Ａ：登録 Ｕ：更新 Ｄ：削除 | AZ27: 更新区分によりセット（ＡまたはＵまたはＤ） | BM27: String | BN27: 1 | BP27: =",`"&R27&"` "&AC27&" "&IF(AJ27="Y","NOT NULL","")&" COMMENT '"&D27&"'" -> ,`PRCS_TYP` varchar(1) COMMENT '処理区分' | BR27: ="`"&R27&"` "&AC27&" "&IF(AJ27="Y","NOT NULL","") -> `PRCS_TYP` varchar(1) | BT27: ="`"&R27&"`" -> `PRCS_TYP` | BV27: ="A.`"&R27&"` = B.`"&R27&"`" -> A.`PRCS_TYP` = B.`PRCS_TYP` | BX27: ="`"&R27&"`" -> `PRCS_TYP` | BZ27: ="`"&R27&"`" -> `PRCS_TYP`
A28: @3 | B28: 8 | D28: 店舗コード | R28: STR_ID | AC28: {=_xlfn.SWITCH(BM28,"String","varchar("&BN28&")","Long","int","Integer","smallint","Double","decimal(9,2)","Currency","int")} -> int | AH28: 1 | AT28: ０は不可 | AZ28: 店舗コードをセット | BM28: Long | BP28: =",`"&R28&"` "&AC28&" "&IF(AJ28="Y","NOT NULL","")&" COMMENT '"&D28&"'" -> ,`STR_ID` int COMMENT '店舗コード' | BR28: =",`"&R28&"` "&AC28&" "&IF(AJ28="Y","NOT NULL","") -> ,`STR_ID` int | BT28: =",`"&R28&"`" -> ,`STR_ID` | BV28: =",A.`"&R28&"` = B.`"&R28&"`" -> ,A.`STR_ID` = B.`STR_ID` | BX28: =",`"&R28&"`" -> ,`STR_ID` | BZ28: =",`"&R28&"`" -> ,`STR_ID`
A29: @4 | B29: 9 | D29: 関連企画Ｎo. | R29: PARNT_ENVT_ID | AC29: {=_xlfn.SWITCH(BM29,"String","varchar("&BN29&")","Long","int","Integer","smallint","Double","decimal(9,2)","Currency","int")} -> varchar(7) | AT29: 現在未使用 Ｎull固定 | BM29: String | BN29: 7 | BP29: =",`"&R29&"` "&AC29&" "&IF(AJ29="Y","NOT NULL","")&" COMMENT '"&D29&"'" -> ,`PARNT_ENVT_ID` varchar(7) COMMENT '関連企画Ｎo.' | BR29: =",`"&R29&"` "&AC29&" "&IF(AJ29="Y","NOT NULL","") -> ,`PARNT_ENVT_ID` varchar(7) | BT29: =",`"&R29&"`" -> ,`PARNT_ENVT_ID` | BV29: =",A.`"&R29&"` = B.`"&R29&"`" -> ,A.`PARNT_ENVT_ID` = B.`PARNT_ENVT_ID` | BX29: =",`"&R29&"`" -> ,`PARNT_ENVT_ID` | BZ29: =",`"&R29&"`" -> ,`PARNT_ENVT_ID`
A30: @5 | B30: 9 | D30: 企画Ｎo. | R30: EVNT_NBR | AC30: {=_xlfn.SWITCH(BM30,"String","varchar("&BN30&")","Long","int","Integer","smallint","Double","decimal(9,2)","Currency","int")} -> varchar(7) | AH30: 3 | AT30: 左詰 企画マスタに存在すること | AZ30: プロモーションＮＯをセット | BM30: String | BN30: 7 | BP30: =",`"&R30&"` "&AC30&" "&IF(AJ30="Y","NOT NULL","")&" COMMENT '"&D30&"'" -> ,`EVNT_NBR` varchar(7) COMMENT '企画Ｎo.' | BR30: =",`"&R30&"` "&AC30&" "&IF(AJ30="Y","NOT NULL","") -> ,`EVNT_NBR` varchar(7) | BT30: =",`"&R30&"`" -> ,`EVNT_NBR` | BV30: =",A.`"&R30&"` = B.`"&R30&"`" -> ,A.`EVNT_NBR` = B.`EVNT_NBR` | BX30: =",`"&R30&"`" -> ,`EVNT_NBR` | BZ30: =",`"&R30&"`" -> ,`EVNT_NBR`
A31: @6 | B31: 9 | D31: Ｍ＆Ｍ ＮＯ | R31: DESCR | AC31: {=_xlfn.SWITCH(BM31,"String","varchar("&BN31&")","Long","int","Integer","smallint","Double","decimal(9,2)","Currency","int")} -> varchar(24) | AH31: 5 | AT31: 数字２桁 左詰め | AZ31: Ｍ＆ＭＮＯをセット | BM31: String | BN31: 24 | BP31: =",`"&R31&"` "&AC31&" "&IF(AJ31="Y","NOT NULL","")&" COMMENT '"&D31&"'" -> ,`DESCR` varchar(24) COMMENT 'Ｍ＆Ｍ ＮＯ' | BR31: =",`"&R31&"` "&AC31&" "&IF(AJ31="Y","NOT NULL","") -> ,`DESCR` varchar(24) | BT31: =",`"&R31&"`" -> ,`DESCR` | BV31: =",A.`"&R31&"` = B.`"&R31&"`" -> ,A.`DESCR` = B.`DESCR` | BX31: =",`"&R31&"`" -> ,`DESCR` | BZ31: =",`"&R31&"`" -> ,`DESCR`
A32: @7 | B32: 9 | D32: 会員フラグ | R32: MBR_FG | AC32: {=_xlfn.SWITCH(BM32,"String","varchar("&BN32&")","Long","int","Integer","smallint","Double","decimal(9,2)","Currency","int")} -> smallint | AH32: 4 | AT32: ０：一般組合せ １：会員組合せ | AZ32: ０をセット | BM32: Integer | BP32: =",`"&R32&"` "&AC32&" "&IF(AJ32="Y","NOT NULL","")&" COMMENT '"&D32&"'" -> ,`MBR_FG` smallint COMMENT '会員フラグ' | BR32: =",`"&R32&"` "&AC32&" "&IF(AJ32="Y","NOT NULL","") -> ,`MBR_FG` smallint | BT32: =",`"&R32&"`" -> ,`MBR_FG` | BV32: =",A.`"&R32&"` = B.`"&R32&"`" -> ,A.`MBR_FG` = B.`MBR_FG` | BX32: =",`"&R32&"`" -> ,`MBR_FG` | BZ32: =",`"&R32&"`" -> ,`MBR_FG`
A33: @8 | B33: 9 | D33: 商品コード | R33: PLU_ID | AC33: {=_xlfn.SWITCH(BM33,"String","varchar("&BN33&")","Long","int","Integer","smallint","Double","decimal(9,2)","Currency","int")} -> varchar(24) | AT33: 左詰 数字で最大19桁。特にＰＬUコードを使用しない場合はｽｷｬﾝｺｰﾄﾞと同じ値を入れておくこと | AZ33: 部門＋商品コードをセット | BM33: String | BN33: 24 | BP33: =",`"&R33&"` "&AC33&" "&IF(AJ33="Y","NOT NULL","")&" COMMENT '"&D33&"'" -> ,`PLU_ID` varchar(24) COMMENT '商品コード' | BR33: =",`"&R33&"` "&AC33&" "&IF(AJ33="Y","NOT NULL","") -> ,`PLU_ID` varchar(24) | BT33: =",`"&R33&"`" -> ,`PLU_ID` | BV33: =",A.`"&R33&"` = B.`"&R33&"`" -> ,A.`PLU_ID` = B.`PLU_ID` | BX33: =",`"&R33&"`" -> ,`PLU_ID` | BZ33: =",`"&R33&"`" -> ,`PLU_ID`
A34: @9 | B34: 9 | D34: 組合せ開始日 | R34: EVNT_BGN_TM | AC34: {=_xlfn.SWITCH(BM34,"String","varchar("&BN34&")","Long","int","Integer","smallint","Double","decimal(9,2)","Currency","int")} -> varchar(8) | AT34: ＹＹＹＹＭＭＤＤ形式で8桁フルに設定すること | AZ34: 販売開始日をセット | BM34: String | BN34: 8 | BP34: =",`"&R34&"` "&AC34&" "&IF(AJ34="Y","NOT NULL","")&" COMMENT '"&D34&"'" -> ,`EVNT_BGN_TM` varchar(8) COMMENT '組合せ開始日' | BR34: =",`"&R34&"` "&AC34&" "&IF(AJ34="Y","NOT NULL","") -> ,`EVNT_BGN_TM` varchar(8) | BT34: =",`"&R34&"`" -> ,`EVNT_BGN_TM` | BV34: =",A.`"&R34&"` = B.`"&R34&"`" -> ,A.`EVNT_BGN_TM` = B.`EVNT_BGN_TM` | BX34: =",`"&R34&"`" -> ,`EVNT_BGN_TM` | BZ34: =",`"&R34&"`" -> ,`EVNT_BGN_TM`
A35: @10 | B35: 9 | D35: 組合せ終了日 | R35: EVNT_END_TM | AC35: {=_xlfn.SWITCH(BM35,"String","varchar("&BN35&")","Long","int","Integer","smallint","Double","decimal(9,2)","Currency","int")} -> varchar(8) | AT35: ＹＹＹＹＭＭＤＤ形式で8桁フルに設定すること | AZ35: 販売終了日をセット | BM35: String | BN35: 8 | BP35: =",`"&R35&"` "&AC35&" "&IF(AJ35="Y","NOT NULL","")&" COMMENT '"&D35&"'" -> ,`EVNT_END_TM` varchar(8) COMMENT '組合せ終了日' | BR35: =",`"&R35&"` "&AC35&" "&IF(AJ35="Y","NOT NULL","") -> ,`EVNT_END_TM` varchar(8) | BT35: =",`"&R35&"`" -> ,`EVNT_END_TM` | BV35: =",A.`"&R35&"` = B.`"&R35&"`" -> ,A.`EVNT_END_TM` = B.`EVNT_END_TM` | BX35: =",`"&R35&"`" -> ,`EVNT_END_TM` | BZ35: =",`"&R35&"`" -> ,`EVNT_END_TM`
A36: @11 | B36: 9 | D36: 企画区分 | R36: EVNT_TYP | AC36: {=_xlfn.SWITCH(BM36,"String","varchar("&BN36&")","Long","int","Integer","smallint","Double","decimal(9,2)","Currency","int")} -> smallint | AH36: 2 | AT36: ２：バンドルミックス ６：ペア | AZ36: ２をセット | BM36: Integer | BP36: =",`"&R36&"` "&AC36&" "&IF(AJ36="Y","NOT NULL","")&" COMMENT '"&D36&"'" -> ,`EVNT_TYP` smallint COMMENT '企画区分' | BR36: =",`"&R36&"` "&AC36&" "&IF(AJ36="Y","NOT NULL","") -> ,`EVNT_TYP` smallint | BT36: =",`"&R36&"`" -> ,`EVNT_TYP` | BV36: =",A.`"&R36&"` = B.`"&R36&"`" -> ,A.`EVNT_TYP` = B.`EVNT_TYP` | BX36: =",`"&R36&"`" -> ,`EVNT_TYP` | BZ36: =",`"&R36&"`" -> ,`EVNT_TYP`
A37: @12 | B37: 9 | D37: 企画予算 | R37: EVNT_BDGT | AC37: {=_xlfn.SWITCH(BM37,"String","varchar("&BN37&")","Long","int","Integer","smallint","Double","decimal(9,2)","Currency","int")} -> int | AT37: 現在未使用 ０固定 | AZ37: ０をセット | BM37: Currency | BP37: =",`"&R37&"` "&AC37&" "&IF(AJ37="Y","NOT NULL","")&" COMMENT '"&D37&"'" -> ,`EVNT_BDGT` int COMMENT '企画予算' | BR37: =",`"&R37&"` "&AC37&" "&IF(AJ37="Y","NOT NULL","") -> ,`EVNT_BDGT` int | BT37: =",`"&R37&"`" -> ,`EVNT_BDGT` | BV37: =",A.`"&R37&"` = B.`"&R37&"`" -> ,A.`EVNT_BDGT` = B.`EVNT_BDGT` | BX37: =",`"&R37&"`" -> ,`EVNT_BDGT` | BZ37: =",`"&R37&"`" -> ,`EVNT_BDGT`
A38: @13 | B38: 9 | D38: 組合せ自動削除日数 | R38: EVNT_DEL_DY | AC38: {=_xlfn.SWITCH(BM38,"String","varchar("&BN38&")","Long","int","Integer","smallint","Double","decimal(9,2)","Currency","int")} -> varchar(8) | AT38: 期間終了後の削除猶予期間 ００２－０９９ 未使用時はＮＵＬＬ | AZ38: ００７をセット | BM38: String | BN38: 8 | BP38: =",`"&R38&"` "&AC38&" "&IF(AJ38="Y","NOT NULL","")&" COMMENT '"&D38&"'" -> ,`EVNT_DEL_DY` varchar(8) COMMENT '組合せ自動削除日数' | BR38: =",`"&R38&"` "&AC38&" "&IF(AJ38="Y","NOT NULL","") -> ,`EVNT_DEL_DY` varchar(8) | BT38: =",`"&R38&"`" -> ,`EVNT_DEL_DY` | BV38: =",A.`"&R38&"` = B.`"&R38&"`" -> ,A.`EVNT_DEL_DY` = B.`EVNT_DEL_DY` | BX38: =",`"&R38&"`" -> ,`EVNT_DEL_DY` | BZ38: =",`"&R38&"`" -> ,`EVNT_DEL_DY`
A39: @14 | B39: 9 | D39: 組合せ優先区分 | R39: EVNT_SRC | AC39: {=_xlfn.SWITCH(BM39,"String","varchar("&BN39&")","Long","int","Integer","smallint","Double","decimal(9,2)","Currency","int")} -> smallint | AT39: 現在1固定 ０：店舗優先 １：本部優先 | AZ39: １をセット | BM39: Integer | BP39: =",`"&R39&"` "&AC39&" "&IF(AJ39="Y","NOT NULL","")&" COMMENT '"&D39&"'" -> ,`EVNT_SRC` smallint COMMENT '組合せ優先区分' | BR39: =",`"&R39&"` "&AC39&" "&IF(AJ39="Y","NOT NULL","") -> ,`EVNT_SRC` smallint | BT39: =",`"&R39&"`" -> ,`EVNT_SRC` | BV39: =",A.`"&R39&"` = B.`"&R39&"`" -> ,A.`EVNT_SRC` = B.`EVNT_SRC` | BX39: =",`"&R39&"`" -> ,`EVNT_SRC` | BZ39: =",`"&R39&"`" -> ,`EVNT_SRC`
A40: @15 | B40: 9 | D40: 組合せ保留フラグ | R40: EVNT_EXCL_FG | AC40: {=_xlfn.SWITCH(BM40,"String","varchar("&BN40&")","Long","int","Integer","smallint","Double","decimal(9,2)","Currency","int")} -> smallint | AT40: ０：保留しない １：保留する | AZ40: ０をセット | BM40: Integer | BP40: =",`"&R40&"` "&AC40&" "&IF(AJ40="Y","NOT NULL","")&" COMMENT '"&D40&"'" -> ,`EVNT_EXCL_FG` smallint COMMENT '組合せ保留フラグ' | BR40: =",`"&R40&"` "&AC40&" "&IF(AJ40="Y","NOT NULL","") -> ,`EVNT_EXCL_FG` smallint | BT40: =",`"&R40&"`" -> ,`EVNT_EXCL_FG` | BV40: =",A.`"&R40&"` = B.`"&R40&"`" -> ,A.`EVNT_EXCL_FG` = B.`EVNT_EXCL_FG` | BX40: =",`"&R40&"`" -> ,`EVNT_EXCL_FG` | BZ40: =",`"&R40&"`" -> ,`EVNT_EXCL_FG`
A41: @16 | B41: 9 | D41: タイムサービスフラグ | R41: TIME_SERVICE_FG | AC41: {=_xlfn.SWITCH(BM41,"String","varchar("&BN41&")","Long","int","Integer","smallint","Double","decimal(9,2)","Currency","int")} -> smallint | AT41: ０：期間 １：期間＆曜日 ２：期間&時間 ３：期間&時間&曜日 | AZ41: ０をセット | BM41: Integer | BP41: =",`"&R41&"` "&AC41&" "&IF(AJ41="Y","NOT NULL","")&" COMMENT '"&D41&"'" -> ,`TIME_SERVICE_FG` smallint COMMENT 'タイムサービスフラグ' | BR41: =",`"&R41&"` "&AC41&" "&IF(AJ41="Y","NOT NULL","") -> ,`TIME_SERVICE_FG` smallint | BT41: =",`"&R41&"`" -> ,`TIME_SERVICE_FG` | BV41: =",A.`"&R41&"` = B.`"&R41&"`" -> ,A.`TIME_SERVICE_FG` = B.`TIME_SERVICE_FG` | BX41: =",`"&R41&"`" -> ,`TIME_SERVICE_FG` | BZ41: =",`"&R41&"`" -> ,`TIME_SERVICE_FG`
A42: @17 | B42: 9 | D42: 月曜日除外フラグ | R42: MON_EXCL_FG | AC42: {=_xlfn.SWITCH(BM42,"String","varchar("&BN42&")","Long","int","Integer","smallint","Double","decimal(9,2)","Currency","int")} -> smallint | AT42: ０：除外しない １：除外する | AZ42: ０をセット | BM42: Integer | BP42: =",`"&R42&"` "&AC42&" "&IF(AJ42="Y","NOT NULL","")&" COMMENT '"&D42&"'" -> ,`MON_EXCL_FG` smallint COMMENT '月曜日除外フラグ' | BR42: =",`"&R42&"` "&AC42&" "&IF(AJ42="Y","NOT NULL","") -> ,`MON_EXCL_FG` smallint | BT42: =",`"&R42&"`" -> ,`MON_EXCL_FG` | BV42: =",A.`"&R42&"` = B.`"&R42&"`" -> ,A.`MON_EXCL_FG` = B.`MON_EXCL_FG` | BX42: =",`"&R42&"`" -> ,`MON_EXCL_FG` | BZ42: =",`"&R42&"`" -> ,`MON_EXCL_FG`
A43: @6 | B43: 9 | D43: 火曜日除外フラグ | R43: TUES_EXCL_FG | AC43: {=_xlfn.SWITCH(BM43,"String","varchar("&BN43&")","Long","int","Integer","smallint","Double","decimal(9,2)","Currency","int")} -> smallint | AT43: ０：除外しない １：除外する | AZ43: ０をセット | BM43: Integer | BP43: =",`"&R43&"` "&AC43&" "&IF(AJ43="Y","NOT NULL","")&" COMMENT '"&D43&"'" -> ,`TUES_EXCL_FG` smallint COMMENT '火曜日除外フラグ' | BR43: =",`"&R43&"` "&AC43&" "&IF(AJ43="Y","NOT NULL","") -> ,`TUES_EXCL_FG` smallint | BT43: =",`"&R43&"`" -> ,`TUES_EXCL_FG` | BV43: =",A.`"&R43&"` = B.`"&R43&"`" -> ,A.`TUES_EXCL_FG` = B.`TUES_EXCL_FG` | BX43: =",`"&R43&"`" -> ,`TUES_EXCL_FG` | BZ43: =",`"&R43&"`" -> ,`TUES_EXCL_FG`
A44: @7 | B44: 9 | D44: 水曜日除外フラグ | R44: WED_EXCL_FG | AC44: {=_xlfn.SWITCH(BM44,"String","varchar("&BN44&")","Long","int","Integer","smallint","Double","decimal(9,2)","Currency","int")} -> smallint | AT44: ０：除外しない １：除外する | AZ44: ０をセット | BM44: Integer | BP44: =",`"&R44&"` "&AC44&" "&IF(AJ44="Y","NOT NULL","")&" COMMENT '"&D44&"'" -> ,`WED_EXCL_FG` smallint COMMENT '水曜日除外フラグ' | BR44: =",`"&R44&"` "&AC44&" "&IF(AJ44="Y","NOT NULL","") -> ,`WED_EXCL_FG` smallint | BT44: =",`"&R44&"`" -> ,`WED_EXCL_FG` | BV44: =",A.`"&R44&"` = B.`"&R44&"`" -> ,A.`WED_EXCL_FG` = B.`WED_EXCL_FG` | BX44: =",`"&R44&"`" -> ,`WED_EXCL_FG` | BZ44: =",`"&R44&"`" -> ,`WED_EXCL_FG`
A45: @8 | B45: 9 | D45: 木曜日除外フラグ | R45: THUS_EXCL_FG | AC45: {=_xlfn.SWITCH(BM45,"String","varchar("&BN45&")","Long","int","Integer","smallint","Double","decimal(9,2)","Currency","int")} -> smallint | AT45: ０：除外しない １：除外する | AZ45: ０をセット | BM45: Integer | BP45: =",`"&R45&"` "&AC45&" "&IF(AJ45="Y","NOT NULL","")&" COMMENT '"&D45&"'" -> ,`THUS_EXCL_FG` smallint COMMENT '木曜日除外フラグ' | BR45: =",`"&R45&"` "&AC45&" "&IF(AJ45="Y","NOT NULL","") -> ,`THUS_EXCL_FG` smallint | BT45: =",`"&R45&"`" -> ,`THUS_EXCL_FG` | BV45: =",A.`"&R45&"` = B.`"&R45&"`" -> ,A.`THUS_EXCL_FG` = B.`THUS_EXCL_FG` | BX45: =",`"&R45&"`" -> ,`THUS_EXCL_FG` | BZ45: =",`"&R45&"`" -> ,`THUS_EXCL_FG`
A46: @9 | B46: 9 | D46: 金曜日除外フラグ | R46: FRI_EXCL_FG | AC46: {=_xlfn.SWITCH(BM46,"String","varchar("&BN46&")","Long","int","Integer","smallint","Double","decimal(9,2)","Currency","int")} -> smallint | AT46: ０：除外しない １：除外する | AZ46: ０をセット | BM46: Integer | BP46: =",`"&R46&"` "&AC46&" "&IF(AJ46="Y","NOT NULL","")&" COMMENT '"&D46&"'" -> ,`FRI_EXCL_FG` smallint COMMENT '金曜日除外フラグ' | BR46: =",`"&R46&"` "&AC46&" "&IF(AJ46="Y","NOT NULL","") -> ,`FRI_EXCL_FG` smallint | BT46: =",`"&R46&"`" -> ,`FRI_EXCL_FG` | BV46: =",A.`"&R46&"` = B.`"&R46&"`" -> ,A.`FRI_EXCL_FG` = B.`FRI_EXCL_FG` | BX46: =",`"&R46&"`" -> ,`FRI_EXCL_FG` | BZ46: =",`"&R46&"`" -> ,`FRI_EXCL_FG`
A47: @10 | B47: 9 | D47: 土曜日除外フラグ | R47: SAT_EXCL_FG | AC47: {=_xlfn.SWITCH(BM47,"String","varchar("&BN47&")","Long","int","Integer","smallint","Double","decimal(9,2)","Currency","int")} -> smallint | AT47: ０：除外しない １：除外する | AZ47: ０をセット | BM47: Integer | BP47: =",`"&R47&"` "&AC47&" "&IF(AJ47="Y","NOT NULL","")&" COMMENT '"&D47&"'" -> ,`SAT_EXCL_FG` smallint COMMENT '土曜日除外フラグ' | BR47: =",`"&R47&"` "&AC47&" "&IF(AJ47="Y","NOT NULL","") -> ,`SAT_EXCL_FG` smallint | BT47: =",`"&R47&"`" -> ,`SAT_EXCL_FG` | BV47: =",A.`"&R47&"` = B.`"&R47&"`" -> ,A.`SAT_EXCL_FG` = B.`SAT_EXCL_FG` | BX47: =",`"&R47&"`" -> ,`SAT_EXCL_FG` | BZ47: =",`"&R47&"`" -> ,`SAT_EXCL_FG`
A48: @11 | B48: 9 | D48: 日曜日除外フラグ | R48: SUN_EXCL_FG | AC48: {=_xlfn.SWITCH(BM48,"String","varchar("&BN48&")","Long","int","Integer","smallint","Double","decimal(9,2)","Currency","int")} -> smallint | AT48: ０：除外しない １：除外する | AZ48: ０をセット | BM48: Integer | BP48: =",`"&R48&"` "&AC48&" "&IF(AJ48="Y","NOT NULL","")&" COMMENT '"&D48&"'" -> ,`SUN_EXCL_FG` smallint COMMENT '日曜日除外フラグ' | BR48: =",`"&R48&"` "&AC48&" "&IF(AJ48="Y","NOT NULL","") -> ,`SUN_EXCL_FG` smallint | BT48: =",`"&R48&"`" -> ,`SUN_EXCL_FG` | BV48: =",A.`"&R48&"` = B.`"&R48&"`" -> ,A.`SUN_EXCL_FG` = B.`SUN_EXCL_FG` | BX48: =",`"&R48&"`" -> ,`SUN_EXCL_FG` | BZ48: =",`"&R48&"`" -> ,`SUN_EXCL_FG`
A49: @12 | B49: 9 | D49: ？？？？？？？？ | R49: YOBI1 | AC49: smallint | BP49: =",`"&R49&"` "&AC49&" "&IF(AJ49="Y","NOT NULL","")&" COMMENT '"&D49&"'" -> ,`YOBI1` smallint COMMENT '？？？？？？？？' | BR49: =",`"&R49&"` "&AC49&" "&IF(AJ49="Y","NOT NULL","") -> ,`YOBI1` smallint | BT49: =",`"&R49&"`" -> ,`YOBI1` | BV49: =",A.`"&R49&"` = B.`"&R49&"`" -> ,A.`YOBI1` = B.`YOBI1` | BX49: =",`"&R49&"`" -> ,`YOBI1` | BZ49: =",`"&R49&"`" -> ,`YOBI1`
A50: @13 | B50: 9 | D50: 特売開始時間 | R50: PROMO_BGN_TM | AC50: {=_xlfn.SWITCH(BM50,"String","varchar("&BN50&")","Long","int","Integer","smallint","Double","decimal(9,2)","Currency","int")} -> varchar(4) | AT50: ＨＨＭＭ形式で4桁フルに設定すること（24時間制） | BM50: String | BN50: 4 | BP50: =",`"&R50&"` "&AC50&" "&IF(AJ50="Y","NOT NULL","")&" COMMENT '"&D50&"'" -> ,`PROMO_BGN_TM` varchar(4) COMMENT '特売開始時間' | BR50: =",`"&R50&"` "&AC50&" "&IF(AJ50="Y","NOT NULL","") -> ,`PROMO_BGN_TM` varchar(4) | BT50: =",`"&R50&"`" -> ,`PROMO_BGN_TM` | BV50: =",A.`"&R50&"` = B.`"&R50&"`" -> ,A.`PROMO_BGN_TM` = B.`PROMO_BGN_TM` | BX50: =",`"&R50&"`" -> ,`PROMO_BGN_TM` | BZ50: =",`"&R50&"`" -> ,`PROMO_BGN_TM`
A51: @14 | B51: 9 | D51: 特売終了時間 | R51: PROMO_END_TM | AC51: {=_xlfn.SWITCH(BM51,"String","varchar("&BN51&")","Long","int","Integer","smallint","Double","decimal(9,2)","Currency","int")} -> varchar(4) | AT51: ＨＨＭＭ形式で4桁フルに設定すること（24時間制） | BM51: String | BN51: 4 | BP51: =",`"&R51&"` "&AC51&" "&IF(AJ51="Y","NOT NULL","")&" COMMENT '"&D51&"'" -> ,`PROMO_END_TM` varchar(4) COMMENT '特売終了時間' | BR51: =",`"&R51&"` "&AC51&" "&IF(AJ51="Y","NOT NULL","") -> ,`PROMO_END_TM` varchar(4) | BT51: =",`"&R51&"`" -> ,`PROMO_END_TM` | BV51: =",A.`"&R51&"` = B.`"&R51&"`" -> ,A.`PROMO_END_TM` = B.`PROMO_END_TM` | BX51: =",`"&R51&"`" -> ,`PROMO_END_TM` | BZ51: =",`"&R51&"`" -> ,`PROMO_END_TM`
A52: @15 | B52: 9 | D52: 割引タイプ１ | R52: DISC_MTHD1 | AC52: {=_xlfn.SWITCH(BM52,"String","varchar("&BN52&")","Long","int","Integer","smallint","Double","decimal(9,2)","Currency","int")} -> smallint | AT52: 企画区分が ２のとき１１ ６のとき１８ | AZ52: １１をセット | BM52: Integer | BP52: =",`"&R52&"` "&AC52&" "&IF(AJ52="Y","NOT NULL","")&" COMMENT '"&D52&"'" -> ,`DISC_MTHD1` smallint COMMENT '割引タイプ１' | BR52: =",`"&R52&"` "&AC52&" "&IF(AJ52="Y","NOT NULL","") -> ,`DISC_MTHD1` smallint | BT52: =",`"&R52&"`" -> ,`DISC_MTHD1` | BV52: =",A.`"&R52&"` = B.`"&R52&"`" -> ,A.`DISC_MTHD1` = B.`DISC_MTHD1` | BX52: =",`"&R52&"`" -> ,`DISC_MTHD1` | BZ52: =",`"&R52&"`" -> ,`DISC_MTHD1`
A53: @16 | B53: 9 | D53: 特売価格１ | R53: DISC_VALUE1 | AC53: {=_xlfn.SWITCH(BM53,"String","varchar("&BN53&")","Long","int","Integer","smallint","Double","decimal(9,2)","Currency","int")} -> decimal(9,2) | AT53: 現在未使用 ０固定 | AZ53: ０をセット | BM53: Double | BP53: =",`"&R53&"` "&AC53&" "&IF(AJ53="Y","NOT NULL","")&" COMMENT '"&D53&"'" -> ,`DISC_VALUE1` decimal(9,2) COMMENT '特売価格１' | BR53: =",`"&R53&"` "&AC53&" "&IF(AJ53="Y","NOT NULL","") -> ,`DISC_VALUE1` decimal(9,2) | BT53: =",`"&R53&"`" -> ,`DISC_VALUE1` | BV53: =",A.`"&R53&"` = B.`"&R53&"`" -> ,A.`DISC_VALUE1` = B.`DISC_VALUE1` | BX53: =",`"&R53&"`" -> ,`DISC_VALUE1` | BZ53: =",`"&R53&"`" -> ,`DISC_VALUE1`
A54: @17 | B54: 9 | D54: Ｍ＆Ｍ数 | R54: MIN_QTY1 | AC54: {=_xlfn.SWITCH(BM54,"String","varchar("&BN54&")","Long","int","Integer","smallint","Double","decimal(9,2)","Currency","int")} -> decimal(9,2) | AT54: 成立個数を設定する（２以上） 必要がない場合は０とする。 | AZ54: Ｍ＆Ｍ数をセット | BM54: Double | BP54: =",`"&R54&"` "&AC54&" "&IF(AJ54="Y","NOT NULL","")&" COMMENT '"&D54&"'" -> ,`MIN_QTY1` decimal(9,2) COMMENT 'Ｍ＆Ｍ数' | BR54: =",`"&R54&"` "&AC54&" "&IF(AJ54="Y","NOT NULL","") -> ,`MIN_QTY1` decimal(9,2) | BT54: =",`"&R54&"`" -> ,`MIN_QTY1` | BV54: =",A.`"&R54&"` = B.`"&R54&"`" -> ,A.`MIN_QTY1` = B.`MIN_QTY1` | BX54: =",`"&R54&"`" -> ,`MIN_QTY1` | BZ54: =",`"&R54&"`" -> ,`MIN_QTY1`
A55: @18 | B55: 9 | D55: Ｍ＆Ｍ売価 | R55: MIN_AMT1 | AC55: {=_xlfn.SWITCH(BM55,"String","varchar("&BN55&")","Long","int","Integer","smallint","Double","decimal(9,2)","Currency","int")} -> int | AT55: 成立価格を設定する。 | AZ55: Ｍ＆Ｍ売価をセット | BM55: Currency | BP55: =",`"&R55&"` "&AC55&" "&IF(AJ55="Y","NOT NULL","")&" COMMENT '"&D55&"'" -> ,`MIN_AMT1` int COMMENT 'Ｍ＆Ｍ売価' | BR55: =",`"&R55&"` "&AC55&" "&IF(AJ55="Y","NOT NULL","") -> ,`MIN_AMT1` int | BT55: =",`"&R55&"`" -> ,`MIN_AMT1` | BV55: =",A.`"&R55&"` = B.`"&R55&"`" -> ,A.`MIN_AMT1` = B.`MIN_AMT1` | BX55: =",`"&R55&"`" -> ,`MIN_AMT1` | BZ55: =",`"&R55&"`" -> ,`MIN_AMT1`
A56: @19 | B56: 9 | D56: 割引タイプ２ | R56: DISC_MTHD2 | AC56: {=_xlfn.SWITCH(BM56,"String","varchar("&BN56&")","Long","int","Integer","smallint","Double","decimal(9,2)","Currency","int")} -> smallint | AT56: 割引タイプ２～１０は多段階バンドルを行いたい場合のみ設定すること。 | AZ56: 必要に応じてセット | BM56: Integer | BP56: =",`"&R56&"` "&AC56&" "&IF(AJ56="Y","NOT NULL","")&" COMMENT '"&D56&"'" -> ,`DISC_MTHD2` smallint COMMENT '割引タイプ２' | BR56: =",`"&R56&"` "&AC56&" "&IF(AJ56="Y","NOT NULL","") -> ,`DISC_MTHD2` smallint | BT56: =",`"&R56&"`" -> ,`DISC_MTHD2` | BV56: =",A.`"&R56&"` = B.`"&R56&"`" -> ,A.`DISC_MTHD2` = B.`DISC_MTHD2` | BX56: =",`"&R56&"`" -> ,`DISC_MTHD2` | BZ56: =",`"&R56&"`" -> ,`DISC_MTHD2`
A57: @20 | B57: 9 | D57: 特売価格２ | R57: DISC_VALUE2 | AC57: {=_xlfn.SWITCH(BM57,"String","varchar("&BN57&")","Long","int","Integer","smallint","Double","decimal(9,2)","Currency","int")} -> decimal(9,2) | AT57: 必要がない場合は０とする。 現在未使用 ０固定 | AZ57: ０をセット | BM57: Double | BP57: =",`"&R57&"` "&AC57&" "&IF(AJ57="Y","NOT NULL","")&" COMMENT '"&D57&"'" -> ,`DISC_VALUE2` decimal(9,2) COMMENT '特売価格２' | BR57: =",`"&R57&"` "&AC57&" "&IF(AJ57="Y","NOT NULL","") -> ,`DISC_VALUE2` decimal(9,2) | BT57: =",`"&R57&"`" -> ,`DISC_VALUE2` | BV57: =",A.`"&R57&"` = B.`"&R57&"`" -> ,A.`DISC_VALUE2` = B.`DISC_VALUE2` | BX57: =",`"&R57&"`" -> ,`DISC_VALUE2` | BZ57: =",`"&R57&"`" -> ,`DISC_VALUE2`
A58: @21 | B58: 9 | D58: Ｍ＆Ｍ数２ | R58: MIN_QTY2 | AC58: {=_xlfn.SWITCH(BM58,"String","varchar("&BN58&")","Long","int","Integer","smallint","Double","decimal(9,2)","Currency","int")} -> decimal(9,2) | AT58: 成立個数を設定する（成立数量１より大きい値を設定すること）必要ない場合は０を設定 | AZ58: ０またはＭ＆Ｍ数をセット | BM58: Double | BP58: =",`"&R58&"` "&AC58&" "&IF(AJ58="Y","NOT NULL","")&" COMMENT '"&D58&"'" -> ,`MIN_QTY2` decimal(9,2) COMMENT 'Ｍ＆Ｍ数２' | BR58: =",`"&R58&"` "&AC58&" "&IF(AJ58="Y","NOT NULL","") -> ,`MIN_QTY2` decimal(9,2) | BT58: =",`"&R58&"`" -> ,`MIN_QTY2` | BV58: =",A.`"&R58&"` = B.`"&R58&"`" -> ,A.`MIN_QTY2` = B.`MIN_QTY2` | BX58: =",`"&R58&"`" -> ,`MIN_QTY2` | BZ58: =",`"&R58&"`" -> ,`MIN_QTY2`
A59: @22 | B59: 9 | D59: Ｍ＆Ｍ売価２ | R59: MIN_AMT2 | AC59: {=_xlfn.SWITCH(BM59,"String","varchar("&BN59&")","Long","int","Integer","smallint","Double","decimal(9,2)","Currency","int")} -> int | AT59: 成立価格を設定する（成立価格１より大きい値を設定すること）必要ない場合は０を設定 | BM59: Currency | BP59: =",`"&R59&"` "&AC59&" "&IF(AJ59="Y","NOT NULL","")&" COMMENT '"&D59&"'" -> ,`MIN_AMT2` int COMMENT 'Ｍ＆Ｍ売価２' | BR59: =",`"&R59&"` "&AC59&" "&IF(AJ59="Y","NOT NULL","") -> ,`MIN_AMT2` int | BT59: =",`"&R59&"`" -> ,`MIN_AMT2` | BV59: =",A.`"&R59&"` = B.`"&R59&"`" -> ,A.`MIN_AMT2` = B.`MIN_AMT2` | BX59: =",`"&R59&"`" -> ,`MIN_AMT2` | BZ59: =",`"&R59&"`" -> ,`MIN_AMT2`
A60: @23 | B60: 9 | D60: 割引タイプ３ | R60: DISC_MTHD3 | AC60: {=_xlfn.SWITCH(BM60,"String","varchar("&BN60&")","Long","int","Integer","smallint","Double","decimal(9,2)","Currency","int")} -> smallint | AT60: 必要ない場合はＮullとする。 | BM60: Integer | BP60: =",`"&R60&"` "&AC60&" "&IF(AJ60="Y","NOT NULL","")&" COMMENT '"&D60&"'" -> ,`DISC_MTHD3` smallint COMMENT '割引タイプ３' | BR60: =",`"&R60&"` "&AC60&" "&IF(AJ60="Y","NOT NULL","") -> ,`DISC_MTHD3` smallint | BT60: =",`"&R60&"`" -> ,`DISC_MTHD3` | BV60: =",A.`"&R60&"` = B.`"&R60&"`" -> ,A.`DISC_MTHD3` = B.`DISC_MTHD3` | BX60: =",`"&R60&"`" -> ,`DISC_MTHD3` | BZ60: =",`"&R60&"`" -> ,`DISC_MTHD3`
A61: @24 | B61: 9 | D61: 特売価格３ | R61: DISC_VALUE3 | AC61: {=_xlfn.SWITCH(BM61,"String","varchar("&BN61&")","Long","int","Integer","smallint","Double","decimal(9,2)","Currency","int")} -> decimal(9,2) | AT61: 現在未使用 ０固定 | BM61: Double | BP61: =",`"&R61&"` "&AC61&" "&IF(AJ61="Y","NOT NULL","")&" COMMENT '"&D61&"'" -> ,`DISC_VALUE3` decimal(9,2) COMMENT '特売価格３' | BR61: =",`"&R61&"` "&AC61&" "&IF(AJ61="Y","NOT NULL","") -> ,`DISC_VALUE3` decimal(9,2) | BT61: =",`"&R61&"`" -> ,`DISC_VALUE3` | BV61: =",A.`"&R61&"` = B.`"&R61&"`" -> ,A.`DISC_VALUE3` = B.`DISC_VALUE3` | BX61: =",`"&R61&"`" -> ,`DISC_VALUE3` | BZ61: =",`"&R61&"`" -> ,`DISC_VALUE3`
A62: @25 | B62: 9 | D62: Ｍ＆Ｍ数３ | R62: MIN_QTY3 | AC62: {=_xlfn.SWITCH(BM62,"String","varchar("&BN62&")","Long","int","Integer","smallint","Double","decimal(9,2)","Currency","int")} -> decimal(9,2) | AT62: 必要ない場合は０を設定 | BM62: Double | BP62: =",`"&R62&"` "&AC62&" "&IF(AJ62="Y","NOT NULL","")&" COMMENT '"&D62&"'" -> ,`MIN_QTY3` decimal(9,2) COMMENT 'Ｍ＆Ｍ数３' | BR62: =",`"&R62&"` "&AC62&" "&IF(AJ62="Y","NOT NULL","") -> ,`MIN_QTY3` decimal(9,2) | BT62: =",`"&R62&"`" -> ,`MIN_QTY3` | BV62: =",A.`"&R62&"` = B.`"&R62&"`" -> ,A.`MIN_QTY3` = B.`MIN_QTY3` | BX62: =",`"&R62&"`" -> ,`MIN_QTY3` | BZ62: =",`"&R62&"`" -> ,`MIN_QTY3`
A63: @26 | B63: 9 | D63: Ｍ＆Ｍ売価３ | R63: MIN_AMT3 | AC63: {=_xlfn.SWITCH(BM63,"String","varchar("&BN63&")","Long","int","Integer","smallint","Double","decimal(9,2)","Currency","int")} -> int | AT63: 必要ない場合は０を設定 | BM63: Currency | BP63: =",`"&R63&"` "&AC63&" "&IF(AJ63="Y","NOT NULL","")&" COMMENT '"&D63&"'" -> ,`MIN_AMT3` int COMMENT 'Ｍ＆Ｍ売価３' | BR63: =",`"&R63&"` "&AC63&" "&IF(AJ63="Y","NOT NULL","") -> ,`MIN_AMT3` int | BT63: =",`"&R63&"`" -> ,`MIN_AMT3` | BV63: =",A.`"&R63&"` = B.`"&R63&"`" -> ,A.`MIN_AMT3` = B.`MIN_AMT3` | BX63: =",`"&R63&"`" -> ,`MIN_AMT3` | BZ63: =",`"&R63&"`" -> ,`MIN_AMT3`
A64: @27 | B64: 9 | D64: 割引タイプ４ | R64: DISC_MTHD4 | AC64: {=_xlfn.SWITCH(BM64,"String","varchar("&BN64&")","Long","int","Integer","smallint","Double","decimal(9,2)","Currency","int")} -> smallint | AT64: 現在未使用 ０固定 | BM64: Integer | BP64: =",`"&R64&"` "&AC64&" "&IF(AJ64="Y","NOT NULL","")&" COMMENT '"&D64&"'" -> ,`DISC_MTHD4` smallint COMMENT '割引タイプ４' | BR64: =",`"&R64&"` "&AC64&" "&IF(AJ64="Y","NOT NULL","") -> ,`DISC_MTHD4` smallint | BT64: =",`"&R64&"`" -> ,`DISC_MTHD4` | BV64: =",A.`"&R64&"` = B.`"&R64&"`" -> ,A.`DISC_MTHD4` = B.`DISC_MTHD4` | BX64: =",`"&R64&"`" -> ,`DISC_MTHD4` | BZ64: =",`"&R64&"`" -> ,`DISC_MTHD4`
A65: @28 | B65: 9 | D65: 特売価格４ | R65: DISC_VALUE4 | AC65: {=_xlfn.SWITCH(BM65,"String","varchar("&BN65&")","Long","int","Integer","smallint","Double","decimal(9,2)","Currency","int")} -> decimal(9,2) | AT65: 現在未使用 ０固定 | BM65: Double | BP65: =",`"&R65&"` "&AC65&" "&IF(AJ65="Y","NOT NULL","")&" COMMENT '"&D65&"'" -> ,`DISC_VALUE4` decimal(9,2) COMMENT '特売価格４' | BR65: =",`"&R65&"` "&AC65&" "&IF(AJ65="Y","NOT NULL","") -> ,`DISC_VALUE4` decimal(9,2) | BT65: =",`"&R65&"`" -> ,`DISC_VALUE4` | BV65: =",A.`"&R65&"` = B.`"&R65&"`" -> ,A.`DISC_VALUE4` = B.`DISC_VALUE4` | BX65: =",`"&R65&"`" -> ,`DISC_VALUE4` | BZ65: =",`"&R65&"`" -> ,`DISC_VALUE4`
A66: @29 | B66: 9 | D66: 成立数量４ | R66: MIN_QTY4 | AC66: {=_xlfn.SWITCH(BM66,"String","varchar("&BN66&")","Long","int","Integer","smallint","Double","decimal(9,2)","Currency","int")} -> decimal(9,2) | AT66: 現在未使用 ０固定 | BM66: Double | BP66: =",`"&R66&"` "&AC66&" "&IF(AJ66="Y","NOT NULL","")&" COMMENT '"&D66&"'" -> ,`MIN_QTY4` decimal(9,2) COMMENT '成立数量４' | BR66: =",`"&R66&"` "&AC66&" "&IF(AJ66="Y","NOT NULL","") -> ,`MIN_QTY4` decimal(9,2) | BT66: =",`"&R66&"`" -> ,`MIN_QTY4` | BV66: =",A.`"&R66&"` = B.`"&R66&"`" -> ,A.`MIN_QTY4` = B.`MIN_QTY4` | BX66: =",`"&R66&"`" -> ,`MIN_QTY4` | BZ66: =",`"&R66&"`" -> ,`MIN_QTY4`
A67: @11 | B67: 9 | D67: 成立価格４ | R67: MIN_AMT4 | AC67: {=_xlfn.SWITCH(BM67,"String","varchar("&BN67&")","Long","int","Integer","smallint","Double","decimal(9,2)","Currency","int")} -> int | AT67: 現在未使用 ０固定 | BM67: Currency | BP67: =",`"&R67&"` "&AC67&" "&IF(AJ67="Y","NOT NULL","")&" COMMENT '"&D67&"'" -> ,`MIN_AMT4` int COMMENT '成立価格４' | BR67: =",`"&R67&"` "&AC67&" "&IF(AJ67="Y","NOT NULL","") -> ,`MIN_AMT4` int | BT67: =",`"&R67&"`" -> ,`MIN_AMT4` | BV67: =",A.`"&R67&"` = B.`"&R67&"`" -> ,A.`MIN_AMT4` = B.`MIN_AMT4` | BX67: =",`"&R67&"`" -> ,`MIN_AMT4` | BZ67: =",`"&R67&"`" -> ,`MIN_AMT4`
A68: @12 | B68: 9 | D68: 割引タイプ５ | R68: DISC_MTHD5 | AC68: {=_xlfn.SWITCH(BM68,"String","varchar("&BN68&")","Long","int","Integer","smallint","Double","decimal(9,2)","Currency","int")} -> smallint | AT68: 現在未使用 ０固定 | BM68: Integer | BP68: =",`"&R68&"` "&AC68&" "&IF(AJ68="Y","NOT NULL","")&" COMMENT '"&D68&"'" -> ,`DISC_MTHD5` smallint COMMENT '割引タイプ５' | BR68: =",`"&R68&"` "&AC68&" "&IF(AJ68="Y","NOT NULL","") -> ,`DISC_MTHD5` smallint | BT68: =",`"&R68&"`" -> ,`DISC_MTHD5` | BV68: =",A.`"&R68&"` = B.`"&R68&"`" -> ,A.`DISC_MTHD5` = B.`DISC_MTHD5` | BX68: =",`"&R68&"`" -> ,`DISC_MTHD5` | BZ68: =",`"&R68&"`" -> ,`DISC_MTHD5`
A69: @13 | B69: 9 | D69: 特売価格５ | R69: DISC_VALUE5 | AC69: {=_xlfn.SWITCH(BM69,"String","varchar("&BN69&")","Long","int","Integer","smallint","Double","decimal(9,2)","Currency","int")} -> decimal(9,2) | AT69: 現在未使用 ０固定 | BM69: Double | BP69: =",`"&R69&"` "&AC69&" "&IF(AJ69="Y","NOT NULL","")&" COMMENT '"&D69&"'" -> ,`DISC_VALUE5` decimal(9,2) COMMENT '特売価格５' | BR69: =",`"&R69&"` "&AC69&" "&IF(AJ69="Y","NOT NULL","") -> ,`DISC_VALUE5` decimal(9,2) | BT69: =",`"&R69&"`" -> ,`DISC_VALUE5` | BV69: =",A.`"&R69&"` = B.`"&R69&"`" -> ,A.`DISC_VALUE5` = B.`DISC_VALUE5` | BX69: =",`"&R69&"`" -> ,`DISC_VALUE5` | BZ69: =",`"&R69&"`" -> ,`DISC_VALUE5`
A70: @14 | B70: 9 | D70: 成立数量５ | R70: MIN_QTY5 | AC70: {=_xlfn.SWITCH(BM70,"String","varchar("&BN70&")","Long","int","Integer","smallint","Double","decimal(9,2)","Currency","int")} -> decimal(9,2) | AT70: 現在未使用 ０固定 | BM70: Double | BP70: =",`"&R70&"` "&AC70&" "&IF(AJ70="Y","NOT NULL","")&" COMMENT '"&D70&"'" -> ,`MIN_QTY5` decimal(9,2) COMMENT '成立数量５' | BR70: =",`"&R70&"` "&AC70&" "&IF(AJ70="Y","NOT NULL","") -> ,`MIN_QTY5` decimal(9,2) | BT70: =",`"&R70&"`" -> ,`MIN_QTY5` | BV70: =",A.`"&R70&"` = B.`"&R70&"`" -> ,A.`MIN_QTY5` = B.`MIN_QTY5` | BX70: =",`"&R70&"`" -> ,`MIN_QTY5` | BZ70: =",`"&R70&"`" -> ,`MIN_QTY5`
... A91: @35 | B91: 9 | D91: 成立価格１０ | R91: MIN_AMT10 | AC91: {=_xlfn.SWITCH(BM91,"String","varchar("&BN91&")","Long","int","Integer","smallint","Double","decimal(9,2)","Currency","int")} -> int | AT91: 現在未使用 ０固定 | BM91: Currency | BP91: =",`"&R91&"` "&AC91&" "&IF(AJ91="Y","NOT NULL","")&" COMMENT '"&D91&"'" -> ,`MIN_AMT10` int COMMENT '成立価格１０' | BR91: =",`"&R91&"` "&AC91&" "&IF(AJ91="Y","NOT NULL","") -> ,`MIN_AMT10` int | BT91: =",`"&R91&"`" -> ,`MIN_AMT10` | BV91: =",A.`"&R91&"` = B.`"&R91&"`" -> ,A.`MIN_AMT10` = B.`MIN_AMT10` | BX91: =",`"&R91&"`" -> ,`MIN_AMT10` | BZ91: =",`"&R91&"`" -> ,`MIN_AMT10`
A92: @36 | B92: 9 | D92: 事前組合せ開始日 | R92: BFR_PRACTICE_BGN_TM | AC92: {=_xlfn.SWITCH(BM92,"String","varchar("&BN92&")","Long","int","Integer","smallint","Double","decimal(9,2)","Currency","int")} -> varchar(8) | AT92: 現在未使用 ０固定 | BM92: String | BN92: 8 | BP92: =",`"&R92&"` "&AC92&" "&IF(AJ92="Y","NOT NULL","")&" COMMENT '"&D92&"'" -> ,`BFR_PRACTICE_BGN_TM` varchar(8) COMMENT '事前組合せ開始日' | BR92: =",`"&R92&"` "&AC92&" "&IF(AJ92="Y","NOT NULL","") -> ,`BFR_PRACTICE_BGN_TM` varchar(8) | BT92: =",`"&R92&"`" -> ,`BFR_PRACTICE_BGN_TM` | BV92: =",A.`"&R92&"` = B.`"&R92&"`" -> ,A.`BFR_PRACTICE_BGN_TM` = B.`BFR_PRACTICE_BGN_TM` | BX92: =",`"&R92&"`" -> ,`BFR_PRACTICE_BGN_TM` | BZ92: =",`"&R92&"`" -> ,`BFR_PRACTICE_BGN_TM`
A93: @37 | B93: 9 | D93: 事前割引タイプ１ | R93: EVNT_DISC_MTHD1 | AC93: {=_xlfn.SWITCH(BM93,"String","varchar("&BN93&")","Long","int","Integer","smallint","Double","decimal(9,2)","Currency","int")} -> smallint | AT93: 現在未使用 ０固定 | BM93: Integer | BP93: =",`"&R93&"` "&AC93&" "&IF(AJ93="Y","NOT NULL","")&" COMMENT '"&D93&"'" -> ,`EVNT_DISC_MTHD1` smallint COMMENT '事前割引タイプ１' | BR93: =",`"&R93&"` "&AC93&" "&IF(AJ93="Y","NOT NULL","") -> ,`EVNT_DISC_MTHD1` smallint | BT93: =",`"&R93&"`" -> ,`EVNT_DISC_MTHD1` | BV93: =",A.`"&R93&"` = B.`"&R93&"`" -> ,A.`EVNT_DISC_MTHD1` = B.`EVNT_DISC_MTHD1` | BX93: =",`"&R93&"`" -> ,`EVNT_DISC_MTHD1` | BZ93: =",`"&R93&"`" -> ,`EVNT_DISC_MTHD1`
A94: @38 | B94: 9 | D94: 事前特売価格１ | R94: EVNT_DISC_VALUE1 | AC94: {=_xlfn.SWITCH(BM94,"String","varchar("&BN94&")","Long","int","Integer","smallint","Double","decimal(9,2)","Currency","int")} -> decimal(9,2) | AT94: 現在未使用 ０固定 | BM94: Double | BP94: =",`"&R94&"` "&AC94&" "&IF(AJ94="Y","NOT NULL","")&" COMMENT '"&D94&"'" -> ,`EVNT_DISC_VALUE1` decimal(9,2) COMMENT '事前特売価格１' | BR94: =",`"&R94&"` "&AC94&" "&IF(AJ94="Y","NOT NULL","") -> ,`EVNT_DISC_VALUE1` decimal(9,2) | BT94: =",`"&R94&"`" -> ,`EVNT_DISC_VALUE1` | BV94: =",A.`"&R94&"` = B.`"&R94&"`" -> ,A.`EVNT_DISC_VALUE1` = B.`EVNT_DISC_VALUE1` | BX94: =",`"&R94&"`" -> ,`EVNT_DISC_VALUE1` | BZ94: =",`"&R94&"`" -> ,`EVNT_DISC_VALUE1`
A95: @39 | B95: 9 | D95: 事前成立数量１ | R95: EVNT_MIN_QTY1 | AC95: {=_xlfn.SWITCH(BM95,"String","varchar("&BN95&")","Long","int","Integer","smallint","Double","decimal(9,2)","Currency","int")} -> decimal(9,2) | AT95: 現在未使用 ０固定 | BM95: Double | BP95: =",`"&R95&"` "&AC95&" "&IF(AJ95="Y","NOT NULL","")&" COMMENT '"&D95&"'" -> ,`EVNT_MIN_QTY1` decimal(9,2) COMMENT '事前成立数量１' | BR95: =",`"&R95&"` "&AC95&" "&IF(AJ95="Y","NOT NULL","") -> ,`EVNT_MIN_QTY1` decimal(9,2) | BT95: =",`"&R95&"`" -> ,`EVNT_MIN_QTY1` | BV95: =",A.`"&R95&"` = B.`"&R95&"`" -> ,A.`EVNT_MIN_QTY1` = B.`EVNT_MIN_QTY1` | BX95: =",`"&R95&"`" -> ,`EVNT_MIN_QTY1` | BZ95: =",`"&R95&"`" -> ,`EVNT_MIN_QTY1`
A96: @40 | B96: 9 | D96: 事前成立価格１ | R96: EVNT_MIN_AMT1 | AC96: {=_xlfn.SWITCH(BM96,"String","varchar("&BN96&")","Long","int","Integer","smallint","Double","decimal(9,2)","Currency","int")} -> int | AT96: 現在未使用 ０固定 | BM96: Currency | BP96: =",`"&R96&"` "&AC96&" "&IF(AJ96="Y","NOT NULL","")&" COMMENT '"&D96&"'" -> ,`EVNT_MIN_AMT1` int COMMENT '事前成立価格１' | BR96: =",`"&R96&"` "&AC96&" "&IF(AJ96="Y","NOT NULL","") -> ,`EVNT_MIN_AMT1` int | BT96: =",`"&R96&"`" -> ,`EVNT_MIN_AMT1` | BV96: =",A.`"&R96&"` = B.`"&R96&"`" -> ,A.`EVNT_MIN_AMT1` = B.`EVNT_MIN_AMT1` | BX96: =",`"&R96&"`" -> ,`EVNT_MIN_AMT1` | BZ96: =",`"&R96&"`" -> ,`EVNT_MIN_AMT1`
A97: @41 | B97: 9 | D97: 事前割引タイプ２ | R97: EVNT_DISC_MTHD2 | AC97: {=_xlfn.SWITCH(BM97,"String","varchar("&BN97&")","Long","int","Integer","smallint","Double","decimal(9,2)","Currency","int")} -> smallint | AT97: 現在未使用 ０固定 | BM97: Integer | BP97: =",`"&R97&"` "&AC97&" "&IF(AJ97="Y","NOT NULL","")&" COMMENT '"&D97&"'" -> ,`EVNT_DISC_MTHD2` smallint COMMENT '事前割引タイプ２' | BR97: =",`"&R97&"` "&AC97&" "&IF(AJ97="Y","NOT NULL","") -> ,`EVNT_DISC_MTHD2` smallint | BT97: =",`"&R97&"`" -> ,`EVNT_DISC_MTHD2` | BV97: =",A.`"&R97&"` = B.`"&R97&"`" -> ,A.`EVNT_DISC_MTHD2` = B.`EVNT_DISC_MTHD2` | BX97: =",`"&R97&"`" -> ,`EVNT_DISC_MTHD2` | BZ97: =",`"&R97&"`" -> ,`EVNT_DISC_MTHD2`
A98: @42 | B98: 9 | D98: 事前特売価格２ | R98: EVNT_DISC_VALUE2 | AC98: {=_xlfn.SWITCH(BM98,"String","varchar("&BN98&")","Long","int","Integer","smallint","Double","decimal(9,2)","Currency","int")} -> decimal(9,2) | AT98: 現在未使用 ０固定 | BM98: Double | BP98: =",`"&R98&"` "&AC98&" "&IF(AJ98="Y","NOT NULL","")&" COMMENT '"&D98&"'" -> ,`EVNT_DISC_VALUE2` decimal(9,2) COMMENT '事前特売価格２' | BR98: =",`"&R98&"` "&AC98&" "&IF(AJ98="Y","NOT NULL","") -> ,`EVNT_DISC_VALUE2` decimal(9,2) | BT98: =",`"&R98&"`" -> ,`EVNT_DISC_VALUE2` | BV98: =",A.`"&R98&"` = B.`"&R98&"`" -> ,A.`EVNT_DISC_VALUE2` = B.`EVNT_DISC_VALUE2` | BX98: =",`"&R98&"`" -> ,`EVNT_DISC_VALUE2` | BZ98: =",`"&R98&"`" -> ,`EVNT_DISC_VALUE2`
A99: @43 | B99: 9 | D99: 事前成立数量２ | R99: EVNT_MIN_QTY2 | AC99: {=_xlfn.SWITCH(BM99,"String","varchar("&BN99&")","Long","int","Integer","smallint","Double","decimal(9,2)","Currency","int")} -> decimal(9,2) | AT99: 現在未使用 ０固定 | BM99: Double | BP99: =",`"&R99&"` "&AC99&" "&IF(AJ99="Y","NOT NULL","")&" COMMENT '"&D99&"'" -> ,`EVNT_MIN_QTY2` decimal(9,2) COMMENT '事前成立数量２' | BR99: =",`"&R99&"` "&AC99&" "&IF(AJ99="Y","NOT NULL","") -> ,`EVNT_MIN_QTY2` decimal(9,2) | BT99: =",`"&R99&"`" -> ,`EVNT_MIN_QTY2` | BV99: =",A.`"&R99&"` = B.`"&R99&"`" -> ,A.`EVNT_MIN_QTY2` = B.`EVNT_MIN_QTY2` | BX99: =",`"&R99&"`" -> ,`EVNT_MIN_QTY2` | BZ99: =",`"&R99&"`" -> ,`EVNT_MIN_QTY2`
A100: @44 | B100: 9 | D100: 事前成立価格２ | R100: EVNT_MIN_AMT2 | AC100: {=_xlfn.SWITCH(BM100,"String","varchar("&BN100&")","Long","int","Integer","smallint","Double","decimal(9,2)","Currency","int")} -> int | AT100: 現在未使用 ０固定 | BM100: Currency | BP100: =",`"&R100&"` "&AC100&" "&IF(AJ100="Y","NOT NULL","")&" COMMENT '"&D100&"'" -> ,`EVNT_MIN_AMT2` int COMMENT '事前成立価格２' | BR100: =",`"&R100&"` "&AC100&" "&IF(AJ100="Y","NOT NULL","") -> ,`EVNT_MIN_AMT2` int | BT100: =",`"&R100&"`" -> ,`EVNT_MIN_AMT2` | BV100: =",A.`"&R100&"` = B.`"&R100&"`" -> ,A.`EVNT_MIN_AMT2` = B.`EVNT_MIN_AMT2` | BX100: =",`"&R100&"`" -> ,`EVNT_MIN_AMT2` | BZ100: =",`"&R100&"`" -> ,`EVNT_MIN_AMT2`
A101: @45 | B101: 9 | D101: 事前割引タイプ3 | R101: EVNT_DISC_MTHD3 | AC101: {=_xlfn.SWITCH(BM101,"String","varchar("&BN101&")","Long","int","Integer","smallint","Double","decimal(9,2)","Currency","int")} -> smallint | AT101: 現在未使用 ０固定 | BM101: Integer | BP101: =",`"&R101&"` "&AC101&" "&IF(AJ101="Y","NOT NULL","")&" COMMENT '"&D101&"'" -> ,`EVNT_DISC_MTHD3` smallint COMMENT '事前割引タイプ3' | BR101: =",`"&R101&"` "&AC101&" "&IF(AJ101="Y","NOT NULL","") -> ,`EVNT_DISC_MTHD3` smallint | BT101: =",`"&R101&"`" -> ,`EVNT_DISC_MTHD3` | BV101: =",A.`"&R101&"` = B.`"&R101&"`" -> ,A.`EVNT_DISC_MTHD3` = B.`EVNT_DISC_MTHD3` | BX101: =",`"&R101&"`" -> ,`EVNT_DISC_MTHD3` | BZ101: =",`"&R101&"`" -> ,`EVNT_DISC_MTHD3`
A102: @46 | B102: 9 | D102: 事前特売価格３ | R102: EVNT_DISC_VALUE3 | AC102: {=_xlfn.SWITCH(BM102,"String","varchar("&BN102&")","Long","int","Integer","smallint","Double","decimal(9,2)","Currency","int")} -> decimal(9,2) | AT102: 現在未使用 ０固定 | BM102: Double | BP102: =",`"&R102&"` "&AC102&" "&IF(AJ102="Y","NOT NULL","")&" COMMENT '"&D102&"'" -> ,`EVNT_DISC_VALUE3` decimal(9,2) COMMENT '事前特売価格３' | BR102: =",`"&R102&"` "&AC102&" "&IF(AJ102="Y","NOT NULL","") -> ,`EVNT_DISC_VALUE3` decimal(9,2) | BT102: =",`"&R102&"`" -> ,`EVNT_DISC_VALUE3` | BV102: =",A.`"&R102&"` = B.`"&R102&"`" -> ,A.`EVNT_DISC_VALUE3` = B.`EVNT_DISC_VALUE3` | BX102: =",`"&R102&"`" -> ,`EVNT_DISC_VALUE3` | BZ102: =",`"&R102&"`" -> ,`EVNT_DISC_VALUE3`
A103: @47 | B103: 9 | D103: 事前成立数量３ | R103: EVNT_MIN_QTY3 | AC103: {=_xlfn.SWITCH(BM103,"String","varchar("&BN103&")","Long","int","Integer","smallint","Double","decimal(9,2)","Currency","int")} -> decimal(9,2) | AT103: 現在未使用 ０固定 | BM103: Double | BP103: =",`"&R103&"` "&AC103&" "&IF(AJ103="Y","NOT NULL","")&" COMMENT '"&D103&"'" -> ,`EVNT_MIN_QTY3` decimal(9,2) COMMENT '事前成立数量３' | BR103: =",`"&R103&"` "&AC103&" "&IF(AJ103="Y","NOT NULL","") -> ,`EVNT_MIN_QTY3` decimal(9,2) | BT103: =",`"&R103&"`" -> ,`EVNT_MIN_QTY3` | BV103: =",A.`"&R103&"` = B.`"&R103&"`" -> ,A.`EVNT_MIN_QTY3` = B.`EVNT_MIN_QTY3` | BX103: =",`"&R103&"`" -> ,`EVNT_MIN_QTY3` | BZ103: =",`"&R103&"`" -> ,`EVNT_MIN_QTY3`
A104: @48 | B104: 9 | D104: 事前成立価格３ | R104: EVNT_MIN_AMT3 | AC104: {=_xlfn.SWITCH(BM104,"String","varchar("&BN104&")","Long","int","Integer","smallint","Double","decimal(9,2)","Currency","int")} -> int | AT104: 現在未使用 ０固定 | BM104: Currency | BP104: =",`"&R104&"` "&AC104&" "&IF(AJ104="Y","NOT NULL","")&" COMMENT '"&D104&"'" -> ,`EVNT_MIN_AMT3` int COMMENT '事前成立価格３' | BR104: =",`"&R104&"` "&AC104&" "&IF(AJ104="Y","NOT NULL","") -> ,`EVNT_MIN_AMT3` int | BT104: =",`"&R104&"`" -> ,`EVNT_MIN_AMT3` | BV104: =",A.`"&R104&"` = B.`"&R104&"`" -> ,A.`EVNT_MIN_AMT3` = B.`EVNT_MIN_AMT3` | BX104: =",`"&R104&"`" -> ,`EVNT_MIN_AMT3` | BZ104: =",`"&R104&"`" -> ,`EVNT_MIN_AMT3`
... A132: @76 | B132: 9 | D132: 事前成立価格１０ | R132: BFR_MIN_AMT10 | AC132: {=_xlfn.SWITCH(BM132,"String","varchar("&BN132&")","Long","int","Integer","smallint","Double","decimal(9,2)","Currency","int")} -> int | AT132: 現在未使用 ０固定 | BM132: Currency | BP132: =",`"&R132&"` "&AC132&" "&IF(AJ132="Y","NOT NULL","")&" COMMENT '"&D132&"'" -> ,`BFR_MIN_AMT10` int COMMENT '事前成立価格１０' | BR132: =",`"&R132&"` "&AC132&" "&IF(AJ132="Y","NOT NULL","") -> ,`BFR_MIN_AMT10` int | BT132: =",`"&R132&"`" -> ,`BFR_MIN_AMT10` | BV132: =",A.`"&R132&"` = B.`"&R132&"`" -> ,A.`BFR_MIN_AMT10` = B.`BFR_MIN_AMT10` | BX132: =",`"&R132&"`" -> ,`BFR_MIN_AMT10` | BZ132: =",`"&R132&"`" -> ,`BFR_MIN_AMT10`
A133: @77 | B133: 9 | D133: 継続組合せ終了日 | R133: AFT_PRCTICE_END_TM | AC133: {=_xlfn.SWITCH(BM133,"String","varchar("&BN133&")","Long","int","Integer","smallint","Double","decimal(9,2)","Currency","int")} -> varchar(8) | AT133: 現在未使用 Ｎull固定 | BM133: String | BN133: 8 | BP133: =",`"&R133&"` "&AC133&" "&IF(AJ133="Y","NOT NULL","")&" COMMENT '"&D133&"'" -> ,`AFT_PRCTICE_END_TM` varchar(8) COMMENT '継続組合せ終了日' | BR133: =",`"&R133&"` "&AC133&" "&IF(AJ133="Y","NOT NULL","") -> ,`AFT_PRCTICE_END_TM` varchar(8) | BT133: =",`"&R133&"`" -> ,`AFT_PRCTICE_END_TM` | BV133: =",A.`"&R133&"` = B.`"&R133&"`" -> ,A.`AFT_PRCTICE_END_TM` = B.`AFT_PRCTICE_END_TM` | BX133: =",`"&R133&"`" -> ,`AFT_PRCTICE_END_TM` | BZ133: =",`"&R133&"`" -> ,`AFT_PRCTICE_END_TM`
A134: @78 | B134: 9 | D134: 継続割引タイプ１ | R134: AFT_DISC_MTHD1 | AC134: {=_xlfn.SWITCH(BM134,"String","varchar("&BN134&")","Long","int","Integer","smallint","Double","decimal(9,2)","Currency","int")} -> smallint | AT134: 現在未使用 ０固定 | BM134: Integer | BP134: =",`"&R134&"` "&AC134&" "&IF(AJ134="Y","NOT NULL","")&" COMMENT '"&D134&"'" -> ,`AFT_DISC_MTHD1` smallint COMMENT '継続割引タイプ１' | BR134: =",`"&R134&"` "&AC134&" "&IF(AJ134="Y","NOT NULL","") -> ,`AFT_DISC_MTHD1` smallint | BT134: =",`"&R134&"`" -> ,`AFT_DISC_MTHD1` | BV134: =",A.`"&R134&"` = B.`"&R134&"`" -> ,A.`AFT_DISC_MTHD1` = B.`AFT_DISC_MTHD1` | BX134: =",`"&R134&"`" -> ,`AFT_DISC_MTHD1` | BZ134: =",`"&R134&"`" -> ,`AFT_DISC_MTHD1`
A135: @79 | B135: 9 | D135: 継続特売価格１ | R135: AFT_DISC_VALUE1 | AC135: {=_xlfn.SWITCH(BM135,"String","varchar("&BN135&")","Long","int","Integer","smallint","Double","decimal(9,2)","Currency","int")} -> decimal(9,2) | AT135: 現在未使用 ０固定 | BM135: Double | BP135: =",`"&R135&"` "&AC135&" "&IF(AJ135="Y","NOT NULL","")&" COMMENT '"&D135&"'" -> ,`AFT_DISC_VALUE1` decimal(9,2) COMMENT '継続特売価格１' | BR135: =",`"&R135&"` "&AC135&" "&IF(AJ135="Y","NOT NULL","") -> ,`AFT_DISC_VALUE1` decimal(9,2) | BT135: =",`"&R135&"`" -> ,`AFT_DISC_VALUE1` | BV135: =",A.`"&R135&"` = B.`"&R135&"`" -> ,A.`AFT_DISC_VALUE1` = B.`AFT_DISC_VALUE1` | BX135: =",`"&R135&"`" -> ,`AFT_DISC_VALUE1` | BZ135: =",`"&R135&"`" -> ,`AFT_DISC_VALUE1`
A136: @80 | B136: 9 | D136: 継続成立数量１ | R136: AFT_MIN_QTY1 | AC136: {=_xlfn.SWITCH(BM136,"String","varchar("&BN136&")","Long","int","Integer","smallint","Double","decimal(9,2)","Currency","int")} -> decimal(9,2) | AT136: 現在未使用 ０固定 | BM136: Double | BP136: =",`"&R136&"` "&AC136&" "&IF(AJ136="Y","NOT NULL","")&" COMMENT '"&D136&"'" -> ,`AFT_MIN_QTY1` decimal(9,2) COMMENT '継続成立数量１' | BR136: =",`"&R136&"` "&AC136&" "&IF(AJ136="Y","NOT NULL","") -> ,`AFT_MIN_QTY1` decimal(9,2) | BT136: =",`"&R136&"`" -> ,`AFT_MIN_QTY1` | BV136: =",A.`"&R136&"` = B.`"&R136&"`" -> ,A.`AFT_MIN_QTY1` = B.`AFT_MIN_QTY1` | BX136: =",`"&R136&"`" -> ,`AFT_MIN_QTY1` | BZ136: =",`"&R136&"`" -> ,`AFT_MIN_QTY1`
A137: @81 | B137: 9 | D137: 継続成立価格１ | R137: AFT_MIN_AMT1 | AC137: {=_xlfn.SWITCH(BM137,"String","varchar("&BN137&")","Long","int","Integer","smallint","Double","decimal(9,2)","Currency","int")} -> int | AT137: 現在未使用 ０固定 | BM137: Currency | BP137: =",`"&R137&"` "&AC137&" "&IF(AJ137="Y","NOT NULL","")&" COMMENT '"&D137&"'" -> ,`AFT_MIN_AMT1` int COMMENT '継続成立価格１' | BR137: =",`"&R137&"` "&AC137&" "&IF(AJ137="Y","NOT NULL","") -> ,`AFT_MIN_AMT1` int | BT137: =",`"&R137&"`" -> ,`AFT_MIN_AMT1` | BV137: =",A.`"&R137&"` = B.`"&R137&"`" -> ,A.`AFT_MIN_AMT1` = B.`AFT_MIN_AMT1` | BX137: =",`"&R137&"`" -> ,`AFT_MIN_AMT1` | BZ137: =",`"&R137&"`" -> ,`AFT_MIN_AMT1`
A138: @82 | B138: 9 | D138: 継続割引タイプ２ | R138: AFT_DISC_MTHD2 | AC138: {=_xlfn.SWITCH(BM138,"String","varchar("&BN138&")","Long","int","Integer","smallint","Double","decimal(9,2)","Currency","int")} -> smallint | AT138: 現在未使用 ０固定 | BM138: Integer | BP138: =",`"&R138&"` "&AC138&" "&IF(AJ138="Y","NOT NULL","")&" COMMENT '"&D138&"'" -> ,`AFT_DISC_MTHD2` smallint COMMENT '継続割引タイプ２' | BR138: =",`"&R138&"` "&AC138&" "&IF(AJ138="Y","NOT NULL","") -> ,`AFT_DISC_MTHD2` smallint | BT138: =",`"&R138&"`" -> ,`AFT_DISC_MTHD2` | BV138: =",A.`"&R138&"` = B.`"&R138&"`" -> ,A.`AFT_DISC_MTHD2` = B.`AFT_DISC_MTHD2` | BX138: =",`"&R138&"`" -> ,`AFT_DISC_MTHD2` | BZ138: =",`"&R138&"`" -> ,`AFT_DISC_MTHD2`
A139: @83 | B139: 9 | D139: 継続特売価格２ | R139: AFT_DISC_VALUE2 | AC139: {=_xlfn.SWITCH(BM139,"String","varchar("&BN139&")","Long","int","Integer","smallint","Double","decimal(9,2)","Currency","int")} -> decimal(9,2) | AT139: 現在未使用 ０固定 | BM139: Double | BP139: =",`"&R139&"` "&AC139&" "&IF(AJ139="Y","NOT NULL","")&" COMMENT '"&D139&"'" -> ,`AFT_DISC_VALUE2` decimal(9,2) COMMENT '継続特売価格２' | BR139: =",`"&R139&"` "&AC139&" "&IF(AJ139="Y","NOT NULL","") -> ,`AFT_DISC_VALUE2` decimal(9,2) | BT139: =",`"&R139&"`" -> ,`AFT_DISC_VALUE2` | BV139: =",A.`"&R139&"` = B.`"&R139&"`" -> ,A.`AFT_DISC_VALUE2` = B.`AFT_DISC_VALUE2` | BX139: =",`"&R139&"`" -> ,`AFT_DISC_VALUE2` | BZ139: =",`"&R139&"`" -> ,`AFT_DISC_VALUE2`
A140: @84 | B140: 9 | D140: 継続成立数量２ | R140: AFT_MIN_QTY2 | AC140: {=_xlfn.SWITCH(BM140,"String","varchar("&BN140&")","Long","int","Integer","smallint","Double","decimal(9,2)","Currency","int")} -> decimal(9,2) | AT140: 現在未使用 ０固定 | BM140: Double | BP140: =",`"&R140&"` "&AC140&" "&IF(AJ140="Y","NOT NULL","")&" COMMENT '"&D140&"'" -> ,`AFT_MIN_QTY2` decimal(9,2) COMMENT '継続成立数量２' | BR140: =",`"&R140&"` "&AC140&" "&IF(AJ140="Y","NOT NULL","") -> ,`AFT_MIN_QTY2` decimal(9,2) | BT140: =",`"&R140&"`" -> ,`AFT_MIN_QTY2` | BV140: =",A.`"&R140&"` = B.`"&R140&"`" -> ,A.`AFT_MIN_QTY2` = B.`AFT_MIN_QTY2` | BX140: =",`"&R140&"`" -> ,`AFT_MIN_QTY2` | BZ140: =",`"&R140&"`" -> ,`AFT_MIN_QTY2`
A141: @85 | B141: 9 | D141: 継続成立価格2 | R141: AFT_MIN_AMT2 | AC141: {=_xlfn.SWITCH(BM141,"String","varchar("&BN141&")","Long","int","Integer","smallint","Double","decimal(9,2)","Currency","int")} -> int | AT141: 現在未使用 ０固定 | BM141: Currency | BP141: =",`"&R141&"` "&AC141&" "&IF(AJ141="Y","NOT NULL","")&" COMMENT '"&D141&"'" -> ,`AFT_MIN_AMT2` int COMMENT '継続成立価格2' | BR141: =",`"&R141&"` "&AC141&" "&IF(AJ141="Y","NOT NULL","") -> ,`AFT_MIN_AMT2` int | BT141: =",`"&R141&"`" -> ,`AFT_MIN_AMT2` | BV141: =",A.`"&R141&"` = B.`"&R141&"`" -> ,A.`AFT_MIN_AMT2` = B.`AFT_MIN_AMT2` | BX141: =",`"&R141&"`" -> ,`AFT_MIN_AMT2` | BZ141: =",`"&R141&"`" -> ,`AFT_MIN_AMT2`
A142: @86 | B142: 9 | D142: 継続割引タイプ３ | R142: AFT_DISC_MTHD3 | AC142: {=_xlfn.SWITCH(BM142,"String","varchar("&BN142&")","Long","int","Integer","smallint","Double","decimal(9,2)","Currency","int")} -> smallint | AT142: 現在未使用 ０固定 | BM142: Integer | BP142: =",`"&R142&"` "&AC142&" "&IF(AJ142="Y","NOT NULL","")&" COMMENT '"&D142&"'" -> ,`AFT_DISC_MTHD3` smallint COMMENT '継続割引タイプ３' | BR142: =",`"&R142&"` "&AC142&" "&IF(AJ142="Y","NOT NULL","") -> ,`AFT_DISC_MTHD3` smallint | BT142: =",`"&R142&"`" -> ,`AFT_DISC_MTHD3` | BV142: =",A.`"&R142&"` = B.`"&R142&"`" -> ,A.`AFT_DISC_MTHD3` = B.`AFT_DISC_MTHD3` | BX142: =",`"&R142&"`" -> ,`AFT_DISC_MTHD3` | BZ142: =",`"&R142&"`" -> ,`AFT_DISC_MTHD3`
A143: @87 | B143: 9 | D143: 継続特売価格３ | R143: AFT_DISC_VALUE3 | AC143: {=_xlfn.SWITCH(BM143,"String","varchar("&BN143&")","Long","int","Integer","smallint","Double","decimal(9,2)","Currency","int")} -> decimal(9,2) | AT143: 現在未使用 ０固定 | BM143: Double | BP143: =",`"&R143&"` "&AC143&" "&IF(AJ143="Y","NOT NULL","")&" COMMENT '"&D143&"'" -> ,`AFT_DISC_VALUE3` decimal(9,2) COMMENT '継続特売価格３' | BR143: =",`"&R143&"` "&AC143&" "&IF(AJ143="Y","NOT NULL","") -> ,`AFT_DISC_VALUE3` decimal(9,2) | BT143: =",`"&R143&"`" -> ,`AFT_DISC_VALUE3` | BV143: =",A.`"&R143&"` = B.`"&R143&"`" -> ,A.`AFT_DISC_VALUE3` = B.`AFT_DISC_VALUE3` | BX143: =",`"&R143&"`" -> ,`AFT_DISC_VALUE3` | BZ143: =",`"&R143&"`" -> ,`AFT_DISC_VALUE3`
A144: @88 | B144: 9 | D144: 継続成立数量3 | R144: AFT_MIN_QTY3 | AC144: {=_xlfn.SWITCH(BM144,"String","varchar("&BN144&")","Long","int","Integer","smallint","Double","decimal(9,2)","Currency","int")} -> decimal(9,2) | AT144: 現在未使用 ０固定 | BM144: Double | BP144: =",`"&R144&"` "&AC144&" "&IF(AJ144="Y","NOT NULL","")&" COMMENT '"&D144&"'" -> ,`AFT_MIN_QTY3` decimal(9,2) COMMENT '継続成立数量3' | BR144: =",`"&R144&"` "&AC144&" "&IF(AJ144="Y","NOT NULL","") -> ,`AFT_MIN_QTY3` decimal(9,2) | BT144: =",`"&R144&"`" -> ,`AFT_MIN_QTY3` | BV144: =",A.`"&R144&"` = B.`"&R144&"`" -> ,A.`AFT_MIN_QTY3` = B.`AFT_MIN_QTY3` | BX144: =",`"&R144&"`" -> ,`AFT_MIN_QTY3` | BZ144: =",`"&R144&"`" -> ,`AFT_MIN_QTY3`
A145: @89 | B145: 9 | D145: 継続成立価格3 | R145: AFT_MIN_AMT3 | AC145: {=_xlfn.SWITCH(BM145,"String","varchar("&BN145&")","Long","int","Integer","smallint","Double","decimal(9,2)","Currency","int")} -> int | AT145: 現在未使用 ０固定 | BM145: Currency | BP145: =",`"&R145&"` "&AC145&" "&IF(AJ145="Y","NOT NULL","")&" COMMENT '"&D145&"'" -> ,`AFT_MIN_AMT3` int COMMENT '継続成立価格3' | BR145: =",`"&R145&"` "&AC145&" "&IF(AJ145="Y","NOT NULL","") -> ,`AFT_MIN_AMT3` int | BT145: =",`"&R145&"`" -> ,`AFT_MIN_AMT3` | BV145: =",A.`"&R145&"` = B.`"&R145&"`" -> ,A.`AFT_MIN_AMT3` = B.`AFT_MIN_AMT3` | BX145: =",`"&R145&"`" -> ,`AFT_MIN_AMT3` | BZ145: =",`"&R145&"`" -> ,`AFT_MIN_AMT3`
... A176: @71 | B176: 9 | D176: ALTコード | R176: ALT_CD | AC176: {=_xlfn.SWITCH(BM176,"String","varchar("&BN176&")","Long","int","Integer","smallint","Double","decimal(9,2)","Currency","int")} -> smallint | AT176: 現在未使用 ０固定 | BM176: Integer | BP176: =",`"&R176&"` "&AC176&" "&IF(AJ176="Y","NOT NULL","")&" COMMENT '"&D176&"'" -> ,`ALT_CD` smallint COMMENT 'ALTコード' | BR176: =",`"&R176&"` "&AC176&" "&IF(AJ176="Y","NOT NULL","") -> ,`ALT_CD` smallint | BT176: =",`"&R176&"`" -> ,`ALT_CD` | BV176: =",A.`"&R176&"` = B.`"&R176&"`" -> ,A.`ALT_CD` = B.`ALT_CD` | BX176: =",`"&R176&"`" -> ,`ALT_CD` | BZ176: =",`"&R176&"`" -> ,`ALT_CD`
A177: @72 | B177: 9 | D177: 割引グループID | R177: DG_ID | AC177: {=_xlfn.SWITCH(BM177,"String","varchar("&BN177&")","Long","int","Integer","smallint","Double","decimal(9,2)","Currency","int")} -> varchar(20) | AT177: 現在未使用 Ｎull固定 | BM177: String | BN177: 20 | BP177: =",`"&R177&"` "&AC177&" "&IF(AJ177="Y","NOT NULL","")&" COMMENT '"&D177&"'" -> ,`DG_ID` varchar(20) COMMENT '割引グループID' | BR177: =",`"&R177&"` "&AC177&" "&IF(AJ177="Y","NOT NULL","") -> ,`DG_ID` varchar(20) | BT177: =",`"&R177&"`" -> ,`DG_ID` | BV177: =",A.`"&R177&"` = B.`"&R177&"`" -> ,A.`DG_ID` = B.`DG_ID` | BX177: =",`"&R177&"`" -> ,`DG_ID` | BZ177: =",`"&R177&"`" -> ,`DG_ID`
A178: @73 | B178: 9 | D178: AUXコード | R178: AUX_CD | AC178: {=_xlfn.SWITCH(BM178,"String","varchar("&BN178&")","Long","int","Integer","smallint","Double","decimal(9,2)","Currency","int")} -> smallint | AT178: 企画区分と会員フラグより2，3，10，11のいずれかを設定する。 ２：ﾊﾞﾝﾄﾞﾙﾐｯｸｽ一般 ３：ﾊﾞﾝﾄﾞﾙﾐｯｸｽ会員 | BM178: Integer | BP178: =",`"&R178&"` "&AC178&" "&IF(AJ178="Y","NOT NULL","")&" COMMENT '"&D178&"'" -> ,`AUX_CD` smallint COMMENT 'AUXコード' | BR178: =",`"&R178&"` "&AC178&" "&IF(AJ178="Y","NOT NULL","") -> ,`AUX_CD` smallint | BT178: =",`"&R178&"`" -> ,`AUX_CD` | BV178: =",A.`"&R178&"` = B.`"&R178&"`" -> ,A.`AUX_CD` = B.`AUX_CD` | BX178: =",`"&R178&"`" -> ,`AUX_CD` | BZ178: =",`"&R178&"`" -> ,`AUX_CD`
A179: @74 | B179: 9 | D179: 割引タイプ | R179: DISC_MTHD | AC179: {=_xlfn.SWITCH(BM179,"String","varchar("&BN179&")","Long","int","Integer","smallint","Double","decimal(9,2)","Currency","int")} -> smallint | AT179: 10：ペア一般 11：ペア会員 ５：固定 | BM179: Integer | BP179: =",`"&R179&"` "&AC179&" "&IF(AJ179="Y","NOT NULL","")&" COMMENT '"&D179&"'" -> ,`DISC_MTHD` smallint COMMENT '割引タイプ' | BR179: =",`"&R179&"` "&AC179&" "&IF(AJ179="Y","NOT NULL","") -> ,`DISC_MTHD` smallint | BT179: =",`"&R179&"`" -> ,`DISC_MTHD` | BV179: =",A.`"&R179&"` = B.`"&R179&"`" -> ,A.`DISC_MTHD` = B.`DISC_MTHD` | BX179: =",`"&R179&"`" -> ,`DISC_MTHD` | BZ179: =",`"&R179&"`" -> ,`DISC_MTHD`
A180: @75 | B180: 9 | D180: 割引アカウント | R180: DISC_ACCT | AC180: {=_xlfn.SWITCH(BM180,"String","varchar("&BN180&")","Long","int","Integer","smallint","Double","decimal(9,2)","Currency","int")} -> varchar(20) | AT180: 現在未使用 ０固定 | BM180: String | BN180: 20 | BP180: =",`"&R180&"` "&AC180&" "&IF(AJ180="Y","NOT NULL","")&" COMMENT '"&D180&"'" -> ,`DISC_ACCT` varchar(20) COMMENT '割引アカウント' | BR180: =",`"&R180&"` "&AC180&" "&IF(AJ180="Y","NOT NULL","") -> ,`DISC_ACCT` varchar(20) | BT180: =",`"&R180&"`" -> ,`DISC_ACCT` | BV180: =",A.`"&R180&"` = B.`"&R180&"`" -> ,A.`DISC_ACCT` = B.`DISC_ACCT` | BX180: =",`"&R180&"`" -> ,`DISC_ACCT` | BZ180: =",`"&R180&"`" -> ,`DISC_ACCT`
A181: @76 | B181: 9 | D181: 割引クラスID | R181: DISC_CLSS_ID | AC181: {=_xlfn.SWITCH(BM181,"String","varchar("&BN181&")","Long","int","Integer","smallint","Double","decimal(9,2)","Currency","int")} -> int | AT181: 企画区分を会員フラグより（91315：ﾊﾞﾝﾄﾞﾙﾐｯｸｽ会員 91316：ﾊﾞﾝﾄﾞﾙﾐｯｸｽ一般 91317：ﾍﾟｱ会員 91318：ﾍﾟｱ一般）のいずれかを設定する。 | BM181: Long | BP181: =",`"&R181&"` "&AC181&" "&IF(AJ181="Y","NOT NULL","")&" COMMENT '"&D181&"'" -> ,`DISC_CLSS_ID` int COMMENT '割引クラスID' | BR181: =",`"&R181&"` "&AC181&" "&IF(AJ181="Y","NOT NULL","") -> ,`DISC_CLSS_ID` int | BT181: =",`"&R181&"`" -> ,`DISC_CLSS_ID` | BV181: =",A.`"&R181&"` = B.`"&R181&"`" -> ,A.`DISC_CLSS_ID` = B.`DISC_CLSS_ID` | BX181: =",`"&R181&"`" -> ,`DISC_CLSS_ID` | BZ181: =",`"&R181&"`" -> ,`DISC_CLSS_ID`
A182: @77 | B182: 9 | D182: 個数制限 | R182: DISC_ITM_LMT | AC182: {=_xlfn.SWITCH(BM182,"String","varchar("&BN182&")","Long","int","Integer","smallint","Double","decimal(9,2)","Currency","int")} -> decimal(9,2) | AT182: 現在未使用 ０固定 | BM182: Double | BP182: =",`"&R182&"` "&AC182&" "&IF(AJ182="Y","NOT NULL","")&" COMMENT '"&D182&"'" -> ,`DISC_ITM_LMT` decimal(9,2) COMMENT '個数制限' | BR182: =",`"&R182&"` "&AC182&" "&IF(AJ182="Y","NOT NULL","") -> ,`DISC_ITM_LMT` decimal(9,2) | BT182: =",`"&R182&"`" -> ,`DISC_ITM_LMT` | BV182: =",A.`"&R182&"` = B.`"&R182&"`" -> ,A.`DISC_ITM_LMT` = B.`DISC_ITM_LMT` | BX182: =",`"&R182&"`" -> ,`DISC_ITM_LMT` | BZ182: =",`"&R182&"`" -> ,`DISC_ITM_LMT`
A183: @78 | B183: 9 | D183: 特売最大値引き額 | R183: MAX_DISC_AMT | AC183: {=_xlfn.SWITCH(BM183,"String","varchar("&BN183&")","Long","int","Integer","smallint","Double","decimal(9,2)","Currency","int")} -> smallint | AT183: 現在未使用 ０固定 | BM183: Integer | BP183: =",`"&R183&"` "&AC183&" "&IF(AJ183="Y","NOT NULL","")&" COMMENT '"&D183&"'" -> ,`MAX_DISC_AMT` smallint COMMENT '特売最大値引き額' | BR183: =",`"&R183&"` "&AC183&" "&IF(AJ183="Y","NOT NULL","") -> ,`MAX_DISC_AMT` smallint | BT183: =",`"&R183&"`" -> ,`MAX_DISC_AMT` | BV183: =",A.`"&R183&"` = B.`"&R183&"`" -> ,A.`MAX_DISC_AMT` = B.`MAX_DISC_AMT` | BX183: =",`"&R183&"`" -> ,`MAX_DISC_AMT` | BZ183: =",`"&R183&"`" -> ,`MAX_DISC_AMT`
A184: @79 | B184: 9 | D184: 割引トラン数 | R184: DISC_TRAN_CNT | AC184: {=_xlfn.SWITCH(BM184,"String","varchar("&BN184&")","Long","int","Integer","smallint","Double","decimal(9,2)","Currency","int")} -> smallint | AT184: 現在未使用 ０固定 | BM184: Integer | BP184: =",`"&R184&"` "&AC184&" "&IF(AJ184="Y","NOT NULL","")&" COMMENT '"&D184&"'" -> ,`DISC_TRAN_CNT` smallint COMMENT '割引トラン数' | BR184: =",`"&R184&"` "&AC184&" "&IF(AJ184="Y","NOT NULL","") -> ,`DISC_TRAN_CNT` smallint | BT184: =",`"&R184&"`" -> ,`DISC_TRAN_CNT` | BV184: =",A.`"&R184&"` = B.`"&R184&"`" -> ,A.`DISC_TRAN_CNT` = B.`DISC_TRAN_CNT` | BX184: =",`"&R184&"`" -> ,`DISC_TRAN_CNT` | BZ184: =",`"&R184&"`" -> ,`DISC_TRAN_CNT`
A185: @80 | B185: 9 | D185: バッチＮo. | R185: BATCH_NBR | AC185: {=_xlfn.SWITCH(BM185,"String","varchar("&BN185&")","Long","int","Integer","smallint","Double","decimal(9,2)","Currency","int")} -> int | AT185: 現在未使用 ０固定 | BM185: Long | BP185: =",`"&R185&"` "&AC185&" "&IF(AJ185="Y","NOT NULL","")&" COMMENT '"&D185&"'" -> ,`BATCH_NBR` int COMMENT 'バッチＮo.' | BR185: =",`"&R185&"` "&AC185&" "&IF(AJ185="Y","NOT NULL","") -> ,`BATCH_NBR` int | BT185: =",`"&R185&"`" -> ,`BATCH_NBR` | BV185: =",A.`"&R185&"` = B.`"&R185&"`" -> ,A.`BATCH_NBR` = B.`BATCH_NBR` | BX185: =",`"&R185&"`" -> ,`BATCH_NBR` | BZ185: =",`"&R185&"`" -> ,`BATCH_NBR`
A186: @81 | B186: 9 | D186: シーケンス番号 | R186: SEQ_ID | AC186: {=_xlfn.SWITCH(BM186,"String","varchar("&BN186&")","Long","int","Integer","smallint","Double","decimal(9,2)","Currency","int")} -> smallint | AT186: 現在未使用 ０固定 | BM186: Integer | BP186: =",`"&R186&"` "&AC186&" "&IF(AJ186="Y","NOT NULL","")&" COMMENT '"&D186&"'" -> ,`SEQ_ID` smallint COMMENT 'シーケンス番号' | BR186: =",`"&R186&"` "&AC186&" "&IF(AJ186="Y","NOT NULL","") -> ,`SEQ_ID` smallint | BT186: =",`"&R186&"`" -> ,`SEQ_ID` | BV186: =",A.`"&R186&"` = B.`"&R186&"`" -> ,A.`SEQ_ID` = B.`SEQ_ID` | BX186: =",`"&R186&"`" -> ,`SEQ_ID` | BZ186: =",`"&R186&"`" -> ,`SEQ_ID`
A187: @82 | B187: 9 | D187: 数量 | R187: QTY | AC187: {=_xlfn.SWITCH(BM187,"String","varchar("&BN187&")","Long","int","Integer","smallint","Double","decimal(9,2)","Currency","int")} -> decimal(9,2) | AT187: １固定 | BM187: Double | BP187: =",`"&R187&"` "&AC187&" "&IF(AJ187="Y","NOT NULL","")&" COMMENT '"&D187&"'" -> ,`QTY` decimal(9,2) COMMENT '数量' | BR187: =",`"&R187&"` "&AC187&" "&IF(AJ187="Y","NOT NULL","") -> ,`QTY` decimal(9,2) | BT187: =",`"&R187&"`" -> ,`QTY` | BV187: =",A.`"&R187&"` = B.`"&R187&"`" -> ,A.`QTY` = B.`QTY` | BX187: =",`"&R187&"`" -> ,`QTY` | BZ187: =",`"&R187&"`" -> ,`QTY`
...

Sheet 企画マスタ
A1: システム名 | K1: システム種別 | W1: =IF(表紙!W1="","",表紙!W1) -> DB定義書 | AP1: 作成者 | AT1: 作成日 | AY1: 更新者 | BC1: 更新日 | BH1: 版数
A2: =IF(表紙!A2="","",表紙!A2) -> 現金専用簡易セルフPOS | K2: =IF(表紙!K2="","",表紙!K2) | AP2: =IF(表紙!AP2="","",表紙!AP2) -> きよはら | AT2: =IF(表紙!AT2="","",表紙!AT2) -> 44652 | AY2: =IF(表紙!AY2="","",表紙!AY2) -> Thanh Nguyên | BC2: =IF(表紙!BC2="","",表紙!BC2) -> 45285 | BH2: =IF(表紙!BH2="","",表紙!BH2) -> 0.2
A4: 機能カテゴリ | H4: =IF(表紙!H4="","",表紙!H4) -> 共通 | U4: 項目 | Z4: =IF(表紙!Z4="","",表紙!Z4) | AP4: テンプレート
B7: ■テーブル情報
B8: スキーマ名 | G8: Replica_Kasumi | Y8: RDBMS名
B9: 論理名 | G9: 企画マスタ | Y9: バージョン
B10: 物理名 | G10: GHEVENTM
B11: 備考
B19: ■カラム情報 | BP19: ="DROP TABLE IF EXISTS `"&$G$8&"`.`"&$G$10&"`;" -> DROP TABLE IF EXISTS `Replica_Kasumi`.`GHEVENTM`;
B20: No. | D20: 論理名 | R20: 物理名 | AC20: データ型 | AH20: PK | AJ20: Not Null | AM20: デフォルト | AT20: 備考 | BP20: ="CREATE TABLE `"&$G$8&"`.`"&$G$10&"` (" -> CREATE TABLE `Replica_Kasumi`.`GHEVENTM` (
B21: 1 | D21: レコードID | R21: RECORD_ID | AC21: bigint | AJ21: Y | AM21: 自動追加 | BP21: `RECORD_ID` bigint NOT NULL AUTO_INCREMENT COMMENT 'レコードID'
B22: =B21+1 -> 2 | D22: レコード作成日付 | R22: RECORD_CREATE_DATE | AC22: date | AJ22: Y | AM22: CURRENT_DATE | BP22: ,`RECORD_CREATE_DATE` date NOT NULL COMMENT 'レコード作成日付'
B23: =B22+1 -> 3 | D23: レコード作成時間 | R23: RECORD_CREATE_TIME | AC23: time | AJ23: Y | AM23: CURRENT_TIME | BP23: ,`RECORD_CREATE_TIME` time NOT NULL COMMENT 'レコード作成時間' | BV23: SET CHARACTER_SET_DATABASE = UTF8;
B24: =B23+1 -> 4 | D24: レコード更新日付 | R24: RECORD_UPDATE_DATE | AC24: date | AJ24: Y | AM24: CURRENT_DATE | AT24: トリガーにより更新 | BP24: ,`RECORD_UPDATE_DATE` date NOT NULL COMMENT 'レコード更新日付/トリガーにより更新' | BV24: ="UPDATE `REPLICA_KASUMI`.`"&$G$10&"` A,`TMP`.`"&$G$10&"` B" -> UPDATE `REPLICA_KASUMI`.`GHEVENTM` A,`TMP`.`GHEVENTM` B
B25: =B24+1 -> 5 | D25: レコード更新時間 | R25: RECORD_UPDATE_TIME | AC25: time | AJ25: Y | AM25: CURRENT_TIME | AT25: トリガーにより更新 | BP25: ,`RECORD_UPDATE_TIME` time NOT NULL COMMENT 'レコード更新時間/トリガーにより更新' | BR25: ="DROP TABLE IF EXISTS `TMP`.`"&$G$10&"`;" -> DROP TABLE IF EXISTS `TMP`.`GHEVENTM`; | BT25: ="LOAD DATA INFILE 'C:/04_DATAFILE/"&$G$10&"/TMP/"&$G$10&".CSV' " -> LOAD DATA INFILE 'C:/04_DATAFILE/GHEVENTM/TMP/GHEVENTM.CSV' | BV25: SET
A26: @1 | B26: =B25+1 -> 6 | D26: レコード無効フラグ | R26: RECORD_VOID_FLAG | AC26: char(1) | AJ26: Y | AM26: "" | AT26: 0: 有効フラグ、 1:無効フラグ | BP26: ,`RECORD_VOID_FLAG` char(1) NOT NULL DEFAULT '' COMMENT 'レコード無効フラグ '''': 有効フラグ、 1:無効フラグ' | BR26: ="CREATE TABLE `TMP`.`"&G10&"` (" -> CREATE TABLE `TMP`.`GHEVENTM` ( | BT26: ="REPLACE INTO TABLE TMP.`"&$G$10&"` FIELDS TERMINATED BY ',' ENCLOSED BY '\""' LINES TERMINATED BY '\r\n' (" -> REPLACE INTO TABLE TMP.`GHEVENTM` FIELDS TERMINATED BY ',' ENCLOSED BY '\"' LINES TERMINATED BY '\r\n' ( | BX26: ="INSERT INTO `REPLICA_KASUMI`.`"&$G$10&"` (" -> INSERT INTO `REPLICA_KASUMI`.`GHEVENTM` ( | BZ26: ) SELECT
A27: @2 | B27: 7 | D27: 処理区分 | R27: PRCS_TYP | AC27: {=_xlfn.SWITCH(BM27,"String","varchar("&BN27&")","Long","int","Integer","smallint","Double","decimal(9,2)","Currency","int")} -> varchar(1) | AT27: Ａ：登録 Ｕ：更新 Ｄ：削除 | AZ27: 更新区分によりセット（ＡまたはＵまたはＤ） | BM27: String | BN27: 1 | BP27: =",`"&R27&"` "&AC27&" "&IF(AJ27="Y","NOT NULL","")&" COMMENT '"&D27&"'" -> ,`PRCS_TYP` varchar(1) COMMENT '処理区分' | BR27: ="`"&R27&"` "&AC27&" "&IF(AJ27="Y","NOT NULL","") -> `PRCS_TYP` varchar(1) | BT27: ="`"&R27&"`" -> `PRCS_TYP` | BV27: ="A.`"&R27&"` = B.`"&R27&"`" -> A.`PRCS_TYP` = B.`PRCS_TYP` | BX27: ="`"&R27&"`" -> `PRCS_TYP` | BZ27: ="`"&R27&"`" -> `PRCS_TYP`
A28: @3 | B28: 8 | D28: 店舗コード | R28: STR_ID | AC28: {=_xlfn.SWITCH(BM28,"String","varchar("&BN28&")","Long","int","Integer","smallint","Double","decimal(9,2)","Currency","int")} -> int | AH28: 1 | AT28: ０は不可 | AZ28: 店舗コードをセット | BM28: Long | BP28: =",`"&R28&"` "&AC28&" "&IF(AJ28="Y","NOT NULL","")&" COMMENT '"&D28&"'" -> ,`STR_ID` int COMMENT '店舗コード' | BR28: =",`"&R28&"` "&AC28&" "&IF(AJ28="Y","NOT NULL","") -> ,`STR_ID` int | BT28: =",`"&R28&"`" -> ,`STR_ID` | BV28: =",A.`"&R28&"` = B.`"&R28&"`" -> ,A.`STR_ID` = B.`STR_ID` | BX28: =",`"&R28&"`" -> ,`STR_ID` | BZ28: =",`"&R28&"`" -> ,`STR_ID`
A29: @4 | B29: 9 | D29: 企画Ｎｏ． | R29: EVNT_NBR | AC29: {=_xlfn.SWITCH(BM29,"String","varchar("&BN29&")","Long","int","Integer","smallint","Double","decimal(9,2)","Currency","int")} -> varchar(7) | AH29: 2 | AT29: 左詰７桁以内 | BM29: String | BN29: 7 | BP29: =",`"&R29&"` "&AC29&" "&IF(AJ29="Y","NOT NULL","")&" COMMENT '"&D29&"'" -> ,`EVNT_NBR` varchar(7) COMMENT '企画Ｎｏ．' | BR29: =",`"&R29&"` "&AC29&" "&IF(AJ29="Y","NOT NULL","") -> ,`EVNT_NBR` varchar(7) | BT29: =",`"&R29&"`" -> ,`EVNT_NBR` | BV29: =",A.`"&R29&"` = B.`"&R29&"`" -> ,A.`EVNT_NBR` = B.`EVNT_NBR` | BX29: =",`"&R29&"`" -> ,`EVNT_NBR` | BZ29: =",`"&R29&"`" -> ,`EVNT_NBR`
A30: @5 | B30: 9 | D30: 関連企画Ｎo． | R30: PARNT_EVNT_NBR | AC30: {=_xlfn.SWITCH(BM30,"String","varchar("&BN30&")","Long","int","Integer","smallint","Double","decimal(9,2)","Currency","int")} -> varchar(20) | AT30: 現在未使用 ０固定 | AZ30: プロモーションＮＯをセット | BM30: String | BN30: 20 | BP30: =",`"&R30&"` "&AC30&" "&IF(AJ30="Y","NOT NULL","")&" COMMENT '"&D30&"'" -> ,`PARNT_EVNT_NBR` varchar(20) COMMENT '関連企画Ｎo．' | BR30: =",`"&R30&"` "&AC30&" "&IF(AJ30="Y","NOT NULL","") -> ,`PARNT_EVNT_NBR` varchar(20) | BT30: =",`"&R30&"`" -> ,`PARNT_EVNT_NBR` | BV30: =",A.`"&R30&"` = B.`"&R30&"`" -> ,A.`PARNT_EVNT_NBR` = B.`PARNT_EVNT_NBR` | BX30: =",`"&R30&"`" -> ,`PARNT_EVNT_NBR` | BZ30: =",`"&R30&"`" -> ,`PARNT_EVNT_NBR`
A31: @6 | B31: 9 | D31: タイトル | R31: DESCR | AC31: {=_xlfn.SWITCH(BM31,"String","varchar("&BN31&")","Long","int","Integer","smallint","Double","decimal(9,2)","Currency","int")} -> varchar(24) | AT31: 日本語１２文字以内 | AZ31: Ｍ＆ＭＮＯをセット | BM31: String | BN31: 24 | BP31: =",`"&R31&"` "&AC31&" "&IF(AJ31="Y","NOT NULL","")&" COMMENT '"&D31&"'" -> ,`DESCR` varchar(24) COMMENT 'タイトル' | BR31: =",`"&R31&"` "&AC31&" "&IF(AJ31="Y","NOT NULL","") -> ,`DESCR` varchar(24) | BT31: =",`"&R31&"`" -> ,`DESCR` | BV31: =",A.`"&R31&"` = B.`"&R31&"`" -> ,A.`DESCR` = B.`DESCR` | BX31: =",`"&R31&"`" -> ,`DESCR` | BZ31: =",`"&R31&"`" -> ,`DESCR`
A32: @7 | B32: 9 | D32: 企画開始日 | R32: EVNT_BGN_TM | AC32: {=_xlfn.SWITCH(BM32,"String","varchar("&BN32&")","Long","int","Integer","smallint","Double","decimal(9,2)","Currency","int")} -> varchar(8) | AT32: ＹＹＹＹＭＭＤＤ形式で8桁フルに設定すること | AZ32: ０をセット | BM32: String | BN32: 8 | BP32: =",`"&R32&"` "&AC32&" "&IF(AJ32="Y","NOT NULL","")&" COMMENT '"&D32&"'" -> ,`EVNT_BGN_TM` varchar(8) COMMENT '企画開始日' | BR32: =",`"&R32&"` "&AC32&" "&IF(AJ32="Y","NOT NULL","") -> ,`EVNT_BGN_TM` varchar(8) | BT32: =",`"&R32&"`" -> ,`EVNT_BGN_TM` | BV32: =",A.`"&R32&"` = B.`"&R32&"`" -> ,A.`EVNT_BGN_TM` = B.`EVNT_BGN_TM` | BX32: =",`"&R32&"`" -> ,`EVNT_BGN_TM` | BZ32: =",`"&R32&"`" -> ,`EVNT_BGN_TM`
A33: @8 | B33: 9 | D33: 企画終了日 | R33: EVNT_END_TM | AC33: {=_xlfn.SWITCH(BM33,"String","varchar("&BN33&")","Long","int","Integer","smallint","Double","decimal(9,2)","Currency","int")} -> varchar(8) | AT33: ＹＹＹＹＭＭＤＤ形式で8桁フルに設定すること | AZ33: 部門＋商品コードをセット | BM33: String | BN33: 8 | BP33: =",`"&R33&"` "&AC33&" "&IF(AJ33="Y","NOT NULL","")&" COMMENT '"&D33&"'" -> ,`EVNT_END_TM` varchar(8) COMMENT '企画終了日' | BR33: =",`"&R33&"` "&AC33&" "&IF(AJ33="Y","NOT NULL","") -> ,`EVNT_END_TM` varchar(8) | BT33: =",`"&R33&"`" -> ,`EVNT_END_TM` | BV33: =",A.`"&R33&"` = B.`"&R33&"`" -> ,A.`EVNT_END_TM` = B.`EVNT_END_TM` | BX33: =",`"&R33&"`" -> ,`EVNT_END_TM` | BZ33: =",`"&R33&"`" -> ,`EVNT_END_TM`
A34: @9 | B34: 9 | D34: 企画予算 | R34: EVNT_BDGT | AC34: {=_xlfn.SWITCH(BM34,"String","varchar("&BN34&")","Long","int","Integer","smallint","Double","decimal(9,2)","Currency","int")} -> int | AZ34: 販売開始日をセット | BM34: Currency | BP34: =",`"&R34&"` "&AC34&" "&IF(AJ34="Y","NOT NULL","")&" COMMENT '"&D34&"'" -> ,`EVNT_BDGT` int COMMENT '企画予算' | BR34: =",`"&R34&"` "&AC34&" "&IF(AJ34="Y","NOT NULL","") -> ,`EVNT_BDGT` int | BT34: =",`"&R34&"`" -> ,`EVNT_BDGT` | BV34: =",A.`"&R34&"` = B.`"&R34&"`" -> ,A.`EVNT_BDGT` = B.`EVNT_BDGT` | BX34: =",`"&R34&"`" -> ,`EVNT_BDGT` | BZ34: =",`"&R34&"`" -> ,`EVNT_BDGT`
A35: @10 | B35: 9 | D35: 企画削除日数 | R35: EVNT_HLDL_DY | AC35: {=_xlfn.SWITCH(BM35,"String","varchar("&BN35&")","Long","int","Integer","smallint","Double","decimal(9,2)","Currency","int")} -> varchar(3) | AT35: 期間終了後の削除猶予期間 ００２－０９９ 未使用時はＮＵＬＬ | AZ35: 販売終了日をセット | BM35: String | BN35: 3 | BP35: =",`"&R35&"` "&AC35&" "&IF(AJ35="Y","NOT NULL","")&" COMMENT '"&D35&"'" -> ,`EVNT_HLDL_DY` varchar(3) COMMENT '企画削除日数' | BR35: =",`"&R35&"` "&AC35&" "&IF(AJ35="Y","NOT NULL","") -> ,`EVNT_HLDL_DY` varchar(3) | BT35: =",`"&R35&"`" -> ,`EVNT_HLDL_DY` | BV35: =",A.`"&R35&"` = B.`"&R35&"`" -> ,A.`EVNT_HLDL_DY` = B.`EVNT_HLDL_DY` | BX35: =",`"&R35&"`" -> ,`EVNT_HLDL_DY` | BZ35: =",`"&R35&"`" -> ,`EVNT_HLDL_DY`
A36: @11 | B36: 9 | D36: 企画優先区分 | R36: EVNT_SRC | AC36: {=_xlfn.SWITCH(BM36,"String","varchar("&BN36&")","Long","int","Integer","smallint","Double","decimal(9,2)","Currency","int")} -> smallint | AT36: 現在1固定 ０：店舗優先 １：本部優先 | AZ36: ２をセット | BM36: Integer | BP36: =",`"&R36&"` "&AC36&" "&IF(AJ36="Y","NOT NULL","")&" COMMENT '"&D36&"'" -> ,`EVNT_SRC` smallint COMMENT '企画優先区分' | BR36: =",`"&R36&"` "&AC36&" "&IF(AJ36="Y","NOT NULL","") -> ,`EVNT_SRC` smallint | BT36: =",`"&R36&"`" -> ,`EVNT_SRC` | BV36: =",A.`"&R36&"` = B.`"&R36&"`" -> ,A.`EVNT_SRC` = B.`EVNT_SRC` | BX36: =",`"&R36&"`" -> ,`EVNT_SRC` | BZ36: =",`"&R36&"`" -> ,`EVNT_SRC`
A37: @12 | B37: 9 | D37: タイムサービスフラグ | R37: TIME_SERVICE_FG | AC37: {=_xlfn.SWITCH(BM37,"String","varchar("&BN37&")","Long","int","Integer","smallint","Double","decimal(9,2)","Currency","int")} -> smallint | AT37: ０：期間 １：期間＆曜日 | AZ37: ０をセット | BM37: Integer | BP37: =",`"&R37&"` "&AC37&" "&IF(AJ37="Y","NOT NULL","")&" COMMENT '"&D37&"'" -> ,`TIME_SERVICE_FG` smallint COMMENT 'タイムサービスフラグ' | BR37: =",`"&R37&"` "&AC37&" "&IF(AJ37="Y","NOT NULL","") -> ,`TIME_SERVICE_FG` smallint | BT37: =",`"&R37&"`" -> ,`TIME_SERVICE_FG` | BV37: =",A.`"&R37&"` = B.`"&R37&"`" -> ,A.`TIME_SERVICE_FG` = B.`TIME_SERVICE_FG` | BX37: =",`"&R37&"`" -> ,`TIME_SERVICE_FG` | BZ37: =",`"&R37&"`" -> ,`TIME_SERVICE_FG`
A38: @13 | B38: 9 | D38: 月曜日除外フラグ | R38: MON_EXCL_FG | AC38: {=_xlfn.SWITCH(BM38,"String","varchar("&BN38&")","Long","int","Integer","smallint","Double","decimal(9,2)","Currency","int")} -> smallint | AT38: ０：除外しない １：除外する | AZ38: ００７をセット | BM38: Integer | BP38: =",`"&R38&"` "&AC38&" "&IF(AJ38="Y","NOT NULL","")&" COMMENT '"&D38&"'" -> ,`MON_EXCL_FG` smallint COMMENT '月曜日除外フラグ' | BR38: =",`"&R38&"` "&AC38&" "&IF(AJ38="Y","NOT NULL","") -> ,`MON_EXCL_FG` smallint | BT38: =",`"&R38&"`" -> ,`MON_EXCL_FG` | BV38: =",A.`"&R38&"` = B.`"&R38&"`" -> ,A.`MON_EXCL_FG` = B.`MON_EXCL_FG` | BX38: =",`"&R38&"`" -> ,`MON_EXCL_FG` | BZ38: =",`"&R38&"`" -> ,`MON_EXCL_FG`
A39: @14 | B39: 9 | D39: 火曜日除外フラグ | R39: TUES_EXCL_FG | AC39: {=_xlfn.SWITCH(BM39,"String","varchar("&BN39&")","Long","int","Integer","smallint","Double","decimal(9,2)","Currency","int")} -> smallint | AT39: ０：除外しない １：除外する | AZ39: １をセット | BM39: Integer | BP39: =",`"&R39&"` "&AC39&" "&IF(AJ39="Y","NOT NULL","")&" COMMENT '"&D39&"'" -> ,`TUES_EXCL_FG` smallint COMMENT '火曜日除外フラグ' | BR39: =",`"&R39&"` "&AC39&" "&IF(AJ39="Y","NOT NULL","") -> ,`TUES_EXCL_FG` smallint | BT39: =",`"&R39&"`" -> ,`TUES_EXCL_FG` | BV39: =",A.`"&R39&"` = B.`"&R39&"`" -> ,A.`TUES_EXCL_FG` = B.`TUES_EXCL_FG` | BX39: =",`"&R39&"`" -> ,`TUES_EXCL_FG` | BZ39: =",`"&R39&"`" -> ,`TUES_EXCL_FG`
A40: @15 | B40: 9 | D40: 水曜日除外フラグ | R40: WED_EXCL_FG | AC40: {=_xlfn.SWITCH(BM40,"String","varchar("&BN40&")","Long","int","Integer","smallint","Double","decimal(9,2)","Currency","int")} -> smallint | AT40: ０：除外しない １：除外する | AZ40: ０をセット | BM40: Integer | BP40: =",`"&R40&"` "&AC40&" "&IF(AJ40="Y","NOT NULL","")&" COMMENT '"&D40&"'" -> ,`WED_EXCL_FG` smallint COMMENT '水曜日除外フラグ' | BR40: =",`"&R40&"` "&AC40&" "&IF(AJ40="Y","NOT NULL","") -> ,`WED_EXCL_FG` smallint | BT40: =",`"&R40&"`" -> ,`WED_EXCL_FG` | BV40: =",A.`"&R40&"` = B.`"&R40&"`" -> ,A.`WED_EXCL_FG` = B.`WED_EXCL_FG` | BX40: =",`"&R40&"`" -> ,`WED_EXCL_FG` | BZ40: =",`"&R40&"`" -> ,`WED_EXCL_FG`
A41: @16 | B41: 9 | D41: 木曜日除外フラグ | R41: THUS_EXCL_FG | AC41: {=_xlfn.SWITCH(BM41,"String","varchar("&BN41&")","Long","int","Integer","smallint","Double","decimal(9,2)","Currency","int")} -> smallint | AT41: ０：除外しない １：除外する | AZ41: ０をセット | BM41: Integer | BP41: =",`"&R41&"` "&AC41&" "&IF(AJ41="Y","NOT NULL","")&" COMMENT '"&D41&"'" -> ,`THUS_EXCL_FG` smallint COMMENT '木曜日除外フラグ' | BR41: =",`"&R41&"` "&AC41&" "&IF(AJ41="Y","NOT NULL","") -> ,`THUS_EXCL_FG` smallint | BT41: =",`"&R41&"`" -> ,`THUS_EXCL_FG` | BV41: =",A.`"&R41&"` = B.`"&R41&"`" -> ,A.`THUS_EXCL_FG` = B.`THUS_EXCL_FG` | BX41: =",`"&R41&"`" -> ,`THUS_EXCL_FG` | BZ41: =",`"&R41&"`" -> ,`THUS_EXCL_FG`
A42: @17 | B42: 9 | D42: 金曜日除外フラグ | R42: FRI_EXCL_FG | AC42: {=_xlfn.SWITCH(BM42,"String","varchar("&BN42&")","Long","int","Integer","smallint","Double","decimal(9,2)","Currency","int")} -> smallint | AT42: ０：除外しない １：除外する | AZ42: ０をセット | BM42: Integer | BP42: =",`"&R42&"` "&AC42&" "&IF(AJ42="Y","NOT NULL","")&" COMMENT '"&D42&"'" -> ,`FRI_EXCL_FG` smallint COMMENT '金曜日除外フラグ' | BR42: =",`"&R42&"` "&AC42&" "&IF(AJ42="Y","NOT NULL","") -> ,`FRI_EXCL_FG` smallint | BT42: =",`"&R42&"`" -> ,`FRI_EXCL_FG` | BV42: =",A.`"&R42&"` = B.`"&R42&"`" -> ,A.`FRI_EXCL_FG` = B.`FRI_EXCL_FG` | BX42: =",`"&R42&"`" -> ,`FRI_EXCL_FG` | BZ42: =",`"&R42&"`" -> ,`FRI_EXCL_FG`
A43: @6 | B43: 9 | D43: 土曜日除外フラグ | R43: SAT_EXCL_FG | AC43: {=_xlfn.SWITCH(BM43,"String","varchar("&BN43&")","Long","int","Integer","smallint","Double","decimal(9,2)","Currency","int")} -> smallint | AT43: ０：除外しない １：除外する | AZ43: ０をセット | BM43: Integer | BP43: =",`"&R43&"` "&AC43&" "&IF(AJ43="Y","NOT NULL","")&" COMMENT '"&D43&"'" -> ,`SAT_EXCL_FG` smallint COMMENT '土曜日除外フラグ' | BR43: =",`"&R43&"` "&AC43&" "&IF(AJ43="Y","NOT NULL","") -> ,`SAT_EXCL_FG` smallint | BT43: =",`"&R43&"`" -> ,`SAT_EXCL_FG` | BV43: =",A.`"&R43&"` = B.`"&R43&"`" -> ,A.`SAT_EXCL_FG` = B.`SAT_EXCL_FG` | BX43: =",`"&R43&"`" -> ,`SAT_EXCL_FG` | BZ43: =",`"&R43&"`" -> ,`SAT_EXCL_FG`
A44: @7 | B44: 9 | D44: 日曜日除外フラグ | R44: SUN_EXCL_FG | AC44: {=_xlfn.SWITCH(BM44,"String","varchar("&BN44&")","Long","int","Integer","smallint","Double","decimal(9,2)","Currency","int")} -> smallint | AT44: ０：除外しない １：除外する | AZ44: ０をセット | BM44: Integer | BP44: =",`"&R44&"` "&AC44&" "&IF(AJ44="Y","NOT NULL","")&" COMMENT '"&D44&"'" -> ,`SUN_EXCL_FG` smallint COMMENT '日曜日除外フラグ' | BR44: =",`"&R44&"` "&AC44&" "&IF(AJ44="Y","NOT NULL","") -> ,`SUN_EXCL_FG` smallint | BT44: =",`"&R44&"`" -> ,`SUN_EXCL_FG` | BV44: =",A.`"&R44&"` = B.`"&R44&"`" -> ,A.`SUN_EXCL_FG` = B.`SUN_EXCL_FG` | BX44: =",`"&R44&"`" -> ,`SUN_EXCL_FG` | BZ44: =",`"&R44&"`" -> ,`SUN_EXCL_FG`
A45: @8 | B45: 9 | D45: テナントコード | R45: TNT_ ID | AC45: {=_xlfn.SWITCH(BM45,"String","varchar("&BN45&")","Long","int","Integer","smallint","Double","decimal(9,2)","Currency","int")} -> int | AT45: 現在未使用 ０固定 | AZ45: ０をセット | BM45: Long | BP45: =",`"&R45&"` "&AC45&" "&IF(AJ45="Y","NOT NULL","")&" COMMENT '"&D45&"'" -> ,`TNT_ ID` int COMMENT 'テナントコード' | BR45: =",`"&R45&"` "&AC45&" "&IF(AJ45="Y","NOT NULL","") -> ,`TNT_ ID` int | BT45: =",`"&R45&"`" -> ,`TNT_ ID` | BV45: =",A.`"&R45&"` = B.`"&R45&"`" -> ,A.`TNT_ ID` = B.`TNT_ ID` | BX45: =",`"&R45&"`" -> ,`TNT_ ID` | BZ45: =",`"&R45&"`" -> ,`TNT_ ID`
A46: @9 | B46: 9 | D46: 作成日 | R46: CRT_DT | AC46: {=_xlfn.SWITCH(BM46,"String","varchar("&BN46&")","Long","int","Integer","smallint","Double","decimal(9,2)","Currency","int")} -> varchar(8) | AT46: ＹＹＹＹＭＭＤＤ形式で8桁フルに設定すること | AZ46: ０をセット | BM46: String | BN46: 8 | BP46: =",`"&R46&"` "&AC46&" "&IF(AJ46="Y","NOT NULL","")&" COMMENT '"&D46&"'" -> ,`CRT_DT` varchar(8) COMMENT '作成日' | BR46: =",`"&R46&"` "&AC46&" "&IF(AJ46="Y","NOT NULL","") -> ,`CRT_DT` varchar(8) | BT46: =",`"&R46&"`" -> ,`CRT_DT` | BV46: =",A.`"&R46&"` = B.`"&R46&"`" -> ,A.`CRT_DT` = B.`CRT_DT` | BX46: =",`"&R46&"`" -> ,`CRT_DT` | BZ46: =",`"&R46&"`" -> ,`CRT_DT`
A47: @10 | B47: 9 | D47: 処理日 | R47: PRCS_DT | AC47: {=_xlfn.SWITCH(BM47,"String","varchar("&BN47&")","Long","int","Integer","smallint","Double","decimal(9,2)","Currency","int")} -> varchar(8) | AT47: ＹＹＹＹＭＭＤＤ形式で8桁フルに設定すること | AZ47: ０をセット | BM47: String | BN47: 8 | BP47: =",`"&R47&"` "&AC47&" "&IF(AJ47="Y","NOT NULL","")&" COMMENT '"&D47&"'" -> ,`PRCS_DT` varchar(8) COMMENT '処理日' | BR47: =",`"&R47&"` "&AC47&" "&IF(AJ47="Y","NOT NULL","") -> ,`PRCS_DT` varchar(8) | BT47: =",`"&R47&"`" -> ,`PRCS_DT` | BV47: =",A.`"&R47&"` = B.`"&R47&"`" -> ,A.`PRCS_DT` = B.`PRCS_DT` | BX47: =",`"&R47&"`" -> ,`PRCS_DT` | BZ47: =",`"&R47&"`" -> ,`PRCS_DT`
A48: @11 | B48: 9 | D48: 受信日 | R48: RCV_DT | AC48: {=_xlfn.SWITCH(BM48,"String","varchar("&BN48&")","Long","int","Integer","smallint","Double","decimal(9,2)","Currency","int")} -> varchar(8) | AT48: Ｎｕｌｌ固定 システム内で使用 | AZ48: ０をセット | BM48: String | BN48: 8 | BP48: =",`"&R48&"` "&AC48&" "&IF(AJ48="Y","NOT NULL","")&" COMMENT '"&D48&"'" -> ,`RCV_DT` varchar(8) COMMENT '受信日' | BR48: =",`"&R48&"` "&AC48&" "&IF(AJ48="Y","NOT NULL","") -> ,`RCV_DT` varchar(8) | BT48: =",`"&R48&"`" -> ,`RCV_DT` | BV48: =",A.`"&R48&"` = B.`"&R48&"`" -> ,A.`RCV_DT` = B.`RCV_DT` | BX48: =",`"&R48&"`" -> ,`RCV_DT` | BZ48: =",`"&R48&"`" -> ,`RCV_DT`
A49: @12 | B49: 9 | D49: 処理フラグ | R49: PRCS_FG | AC49: smallint | AT49: ＊固定 システム内で使用（＊：未処理 １：処理済） | BM49: String | BN49: 1 | BP49: =",`"&R49&"` "&AC49&" "&IF(AJ49="Y","NOT NULL","")&" COMMENT '"&D49&"'" -> ,`PRCS_FG` smallint COMMENT '処理フラグ' | BR49: =",`"&R49&"` "&AC49&" "&IF(AJ49="Y","NOT NULL","") -> ,`PRCS_FG` smallint | BT49: =",`"&R49&"`" -> ,`PRCS_FG` | BV49: =",A.`"&R49&"` = B.`"&R49&"`" -> ,A.`PRCS_FG` = B.`PRCS_FG` | BX49: =",`"&R49&"`" -> ,`PRCS_FG` | BZ49: =",`"&R49&"`" -> ,`PRCS_FG`
