Workbook
Name ____PFM2: #REF!
Name ____PFM21: #REF!
Name ____pfm3: #REF!
Name ___PFM2: #REF!
Name ___PFM21: #REF!
Name ___pfm3: #REF!
Name __PFM2: #REF!
Name __PFM21: #REF!
Name __pfm3: #REF!
Name _1Excel_BuiltIn__FilterDatabase_1: #REF!
Name _2Excel_BuiltIn__FilterDatabase_1_1: #REF!
Name _3Nagaoka_障害一覧_発生_改修: #REF!
Name _PFM2: #REF!
Name _PFM21: #REF!
Name _pfm3: #REF!
Name a: #REF!
Name aaa: #REF!
Name BASE: #REF!
Name BASE2: #REF!
Name bbb: #REF!
Name DISC_CLASS_LVL: #REF!
Name DISC_EXCEPTION: #REF!
Name DISC_EXCEPTION: #REF!
Name DISC_EXCEPTION: #REF!
Name DISC_STEP: #REF!
Name DISC_STEP: #REF!
Name DISC_STEP: #REF!
Name DISC_TARGET: #REF!
Name DISC_TARGET: #REF!
Name DISC_TARGET: #REF!
Name DS_KEYS: #REF!
Name DS_NM: #REF!
Name Grpリーダ: #REF!
Name HTML_Control_1: {"'表紙'!$A$1:$W$39"}
Name HTML_Control_1: {"'表紙'!$A$1:$W$39"}
Name HTML_Control_1: {"'表紙'!$A$1:$W$39"}
Name ITﾃｽﾄ基準: #REF!
Name ITﾃｽﾄ基準小計1: #REF!
Name ITﾃｽﾄ基準小計2: #REF!
Name ITﾃｽﾄ基準小計2ｺﾋﾟｰ: #REF!
Name ITﾃｽﾄ実績: #REF!
Name ITﾃｽﾄ実績小計1: #REF!
Name ＩＴﾃｽﾄ実績小計1ｺﾋﾟｰ: #REF!
Name ITﾃｽﾄ実績小計2: #REF!
Name IT障害基準: #REF!
Name IT障害基準小計1: #REF!
Name IT障害基準小計2: #REF!
Name IT障害実績: #REF!
Name IT障害実績小計1: #REF!
Name IT障害実績小計2: #REF!
Name KEYS: #REF!
Name NAMES: #REF!
Name NEC_KEYS: #REF!
Name PGﾃｽﾄ基準: #REF!
Name PGﾃｽﾄ基準小計1: #REF!
Name PGﾃｽﾄ基準小計2: #REF!
Name PGﾃｽﾄ実績: #REF!
Name PGﾃｽﾄ実績小計1: #REF!
Name PGﾃｽﾄ実績小計2: #REF!
Name PG障害基準: #REF!

Sheet 表紙
B3: U.S.M.Holdings様／いなげや様
H24: 1.13
G27: =MAX(改版履歴!C10:F226) -> 45709
F31: 富士通株式会社
D36: U.S.M.Holdings様／いなげや様 | J36: 富士通
D37: 承認 | F37: 承認 | H37: 承認 | J37: 承認 | L37: 確認 | N37: リーダー

Sheet 改版履歴
B2: TeamStore/M POSシステム | O2: システム名 | U2: 業務名 | AB2: 改版履歴 | AO2: 履歴 | AQ2: 改訂者 | AT2: 最新更新日 | AX2: 作成者 | BA2: 作成日
B3: UI設計書 | O3: トラン連携対応 | U3: トラン連携対応レイアウト | AO3: 1.12 | AQ3: 富士通 | AT3: =MAX(C10:F226) -> 45709 | AX3: 富士通 | BA3: 45460
C6: 改版履歴
C8: 日付 | G8: 版数 | I8: 章番号 | O8: 修正内容 | AZ8: 担当
C10: 45460 | G10: 0.1 | O10: 新規作成 | AZ10: 富士通
C12: 45462 | G12: 1 | O12: ＜2024/6/17 打合せ内容の反映＞ | AZ12: 富士通
O13: TRANS_HEADER
O14: No.20 取引合計額
O15: ・入金／出金の設定値を修正
O16: No.54 ポイント対象金額
O17: ・設定値を基本ポイント対象額に修正
O18: LN_LINK
O19: No.3 リンク明細番号
O20: ・説明文を修正
O21: LN_DISCOUNT
O22: No.7 ディスカウントＩＤ
O23: ・取得元マスタ項目の「１：小計額値引」を「１３：小計額値引」に修正
O24: No.15 企画No
... O49: (続く)
B52: TeamStore/M POSシステム | O52: システム名 | U52: 業務名 | AB52: 改版履歴 | AO52: 履歴 | AQ52: 改訂者 | AT52: 最新更新日 | AX52: 作成者 | BA52: 作成日
B53: UI設計書 | O53: トラン連携対応 | U53: トラン連携対応レイアウト | AO53: =AO3 -> 1.12 | AQ53: 富士通 | AT53: =AT3 -> 45709 | AX53: 富士通 | BA53: =BA3 -> 45460
C56: 改版履歴
C58: 日付 | G58: 版数 | I58: 章番号 | O58: 修正内容 | AZ58: 担当
C60: 45462 | G60: 1 | O60: (続き) | AZ60: 富士通
O61: LN_LINK
O62: No.4 リンクタイプ
O63: ・説明文を修正
O64: LN_DETAIL
O65: No.15 合計原価
O66: ・合計原価を設定に修正
O67: No.31 特売原価
O68: ・特売原価を設定（1個当たりの原価）を設定に修正
O69: No.32 スキャンコード（単品登録時）
O70: ・説明文に「部門登録の場合は””(空白)を設定する。」を追記
O71: No.40 ポイント倍率
O72: ・グレーアウト（連携なし）に修正
... O75: ・備考欄を「取引の外税対象金額を設定」に修正
C76: 45467 | G76: 1.1 | O76: ＜2024/6/19 打合せ内容の反映＞ | AZ76: 富士通
O77: 取引ログ作成時の注意事項
O78: 「⑥精算回数、精算通番について」を追加
O79: LN_DETAIL
O80: No.32 スキャンコード(単品登録時)
O81: ・「(空白)」ではなく「(空)」に修正
O82: TRANS_HEADER
O83: No.39 精算回数
O84: No.40 精算通番
O85: ・精算回数、精算通番のカウントアップタイミングと取引情報の設定タイミングを記載
O86: No.61 会員コードマスタ未登録フラグ
O87: ・いなげや様は利用が無いため、設定値は0固定に修正
O88: No.82 GSFD顧客STS
... O98: ・備考に追記、「コード決済取引明細ログレイアウト」を追加
B101: TeamStore/M POSシステム | O101: システム名 | U101: 業務名 | AB101: 改版履歴 | AO101: 履歴 | AQ101: 改訂者 | AT101: 最新更新日 | AX101: 作成者 | BA101: 作成日
B102: UI設計書 | O102: トラン連携対応 | U102: トラン連携対応レイアウト | AO102: =AO3 -> 1.12 | AQ102: 富士通 | AT102: =AT3 -> 45709 | AX102: 富士通 | BA102: =BA3 -> 45460
C105: 改版履歴
C107: 日付 | G107: 版数 | I107: 章番号 | O107: 修正内容 | AZ107: 担当
C109: 45490 | G109: 1.2 | O109: ＜内部指摘を反映＞ | AZ109: 富士通
O110: TRANS_HEADER
O111: No.171 GSFD_INP_DEVICE_FLG
O112: ・いなげや様で使用している設定値に修正(0にIC-RW IC読み込み/IC-RW MSR読み込みを追加、3:MSRを削除)
Q113: 0:なし/IC-RW IC読み込み/IC-RW MSR読み込み、1:手入力、2:SCANNER
C114: 45539 | G114: 1.3 | O114: コード決済取引明細ログレイアウト | AZ114: 富士通
O115: 「■データ部:H1アイテムフォーマット」の項番10「有効期限（決済ブランド）」に以下の追記、削除。
P116: ・"+スペース(8桁)"を削除。（消し線）
P117: ・例）を追記
P118: ・備考欄に、各決済ブランドの決済ブランド設定値を追記
C119: 45548 | G119: 1.4 | O119: TRANS_HEADER | AZ119: 富士通
O120: No.128 GSFD_HANDINPUT
O121: ・入金、入金中止取引の設定値を「設定値：入力された手打ち金額を設定」に修正。
O122: TRANSACTION_TENDER
O123: 売上中止の列を追加し、補足説明(現外支払い後に中止した場合にのみ作成)を記載
O124: GIFT_CERT_TENDER
O125: 売上中止の列を追加し、補足説明(現外支払い後に中止した場合にのみ作成)を記載
C126: 45590 | G126: 1.5 | O126: 取引ログ作成時の注意事項 | AZ126: 富士通
O127: ・新規追加した取引ログ作成時の注意事項（税情報/支払情報/値引併用）に合わせて表記方法を変更
O128: ・「(3)現外支払いのリンク例」に、コード決済とクレジット支払のダミーレコードについての注意書きを追記
O129: ・「(6)売価変更 ※マニュアル操作(価格入力)、または、値引バーコード(価格設定)」、「(7)特売(タイムサービス・マークダウンも同様)と売価変更の併用」を追加
O130: 取引ログ作成時の注意事項（税情報）を追加
O131: 取引ログ作成時の注意事項（支払情報）を追加
O132: 取引ログ作成時の注意事項（値引併用）を追加
O133: TRAMS_HEADER
O134: ・「入金 中止」、「出金 中止」、「釣銭準備金 中止」、「中間回収 中止」 取引をignicaPOS側からトラン連携無しに変更
O135: No.89 GSFD_COMPARE_CASH_AMT：「開始過不足額（現金在高合計 - 現金在高）」を「開始過不足額（釣銭機在高 - 現金在高）」に修正
O136: No.90 GSFD_CASH_COLSPY_AMT：「釣銭準備金」、「釣銭補充」の設定値を""(空)に修正
O137: LN_LINK
O138: No.5 LINK_AMT：リンクタイプ毎の設定値を記載
... O149: 「■データ部:H1アイテムフォーマット」の項番7「伝票番号）」の備考欄に、取引内通番の説明追記。
B151: TeamStore/M POSシステム | O151: システム名 | U151: 業務名 | AB151: 改版履歴 | AO151: 履歴 | AQ151: 改訂者 | AT151: 最新更新日 | AX151: 作成者 | BA151: 作成日
B152: UI設計書 | O152: トラン連携対応 | U152: トラン連携対応レイアウト | AO152: =AO3 -> 1.12 | AQ152: 富士通 | AT152: =AT3 -> 45709 | AX152: 富士通 | BA152: =BA3 -> 45460
C155: 改版履歴
C157: 日付 | G157: 版数 | I157: 章番号 | O157: 修正内容 | AZ157: 担当
C159: 45625 | G159: 1.6 | O159: ＜内部指摘を反映＞ | AZ159: 富士通
O160: TRANS_HEADER
O161: No.4 RGST_TRAN_NBR：備考を修正(先頭0埋め不要を記載)
O162: No.90 GSFD_CASH_COLSPY_AMT：下記の場合のみ値を設定するように修正
X163: ・TRAN_CD=15（入金）
X164: 「棒金ドロア追加(入出金コード=582)」、「紙幣・硬貨追加(入出金コード=580)」の場合に値を設定
X165: ・TRAN_CD=16（出金）
X166: 「途中回収(入出金コード=680)」の場合に値を設定
O167: No.90 GSFD_CASH_COLSPY_AMT：「中間回収」の設定値を""(空)に修正
O168: No.95 GSFD_ITEM_COUNTS：入金、出金の設定値を修正
...

Sheet 連携対象取引ログテーブル一覧
B2: TeamStore/M POSシステム | O2: システム名 | U2: 業務名 | AB2: トラン連携対象取引ログテーブル一覧 | AO2: 履歴 | AQ2: 改訂者 | AT2: 最新更新日 | AX2: 作成者 | BA2: 作成日
B3: UI設計書 | O3: トラン連携対応 | U3: トラン連携対応レイアウト | AO3: =改版履歴!AO3 -> 1.12 | AQ3: 富士通 | AT3: =改版履歴!AT3 -> 45709 | AX3: 富士通 | BA3: 45460
C6: トラン連携対象取引ログテーブル一覧
D8: № | E8: テーブル名 | O8: 名称 | Y8: データ作成元 | AE8: ファイル連携 | AI8: 補足説明
D9: 1 | E9: TRANS_HEADER | O9: 取引情報 | Y9: ignicaPOS | AE9: あり
D10: =OFFSET(D10,-1,0,1,1)+1 -> 2 | E10: LN_LINK | O10: 取引明細のリンク情報 | Y10: ignicaPOS | AE10: あり
D11: =OFFSET(D11,-1,0,1,1)+1 -> 3 | E11: LN_DETAIL | O11: 商品明細情報 | Y11: ignicaPOS | AE11: あり
D12: =OFFSET(D12,-1,0,1,1)+1 -> 4 | E12: LN_DISCOUNT | O12: 値引情報 | Y12: ignicaPOS | AE12: あり
D13: =OFFSET(D13,-1,0,1,1)+1 -> 5 | E13: TRANSACTION_TAX | O13: 取引の税情報 | Y13: ignicaPOS | AE13: あり
D14: =OFFSET(D14,-1,0,1,1)+1 -> 6 | E14: TRANSACTION_TENDER | O14: 取引の支払情報 | Y14: ignicaPOS | AE14: あり
D15: =OFFSET(D15,-1,0,1,1)+1 -> 7 | E15: GIFT_CERT_TENDER | O15: 現外支払情報 | Y15: ignicaPOS | AE15: あり
D16: =OFFSET(D16,-1,0,1,1)+1 -> 8 | E16: GSFD_PNT_TRANS_HEADER | O16: ポイント情報 | Y16: ignicaPOS | AE16: あり
D17: =OFFSET(D17,-1,0,1,1)+1 -> 9 | E17: MANUAL_PRICE | O17: 価格変更情報 | Y17: ignicaPOS、TS/M | AE17: あり | AI17: 特売の時はTS/Mで作成
D18: =OFFSET(D18,-1,0,1,1)+1 -> 10 | E18: GL_TRAN | O18: 支払情報 | Y18: ignicaPOS | AE18: あり
D19: =OFFSET(D19,-1,0,1,1)+1 -> 11 | E19: LOAN_PICKUP | O19: 入出金情報 | Y19: ignicaPOS | AE19: あり
D20: =OFFSET(D20,-1,0,1,1)+1 -> 12 | E20: TENDER_ON_HAND | O20: 支払状況 | Y20: TS/M | AE20: 無し
D21: =OFFSET(D21,-1,0,1,1)+1 -> 13 | E21: GSFD_PNT_KICK | O21: ポイント処理起動トリガテーブル | Y21: TS/M | AE21: 無し
D22: =OFFSET(D22,-1,0,1,1)+1 -> 14 | E22: GSFD_RPT_KICK | O22: 集計起動トリガテーブル | Y22: TS/M | AE22: 無し
D23: =OFFSET(D23,-1,0,1,1)+1 -> 15 | E23: TRANS_DG | O23: 顧客情報 | Y23: - | AE23: -
D24: =OFFSET(D24,-1,0,1,1)+1 -> 16 | E24: PLU_NOT_FOUND | O24: 緊急登録情報 | Y24: - | AE24: -
D25: =OFFSET(D25,-1,0,1,1)+1 -> 17 | E25: POST_VOID_TRAN | O25: 取消情報 | Y25: - | AE25: -
D26: =OFFSET(D26,-1,0,1,1)+1 -> 18 | E26: TENDER_COUNT | O26: 金種登録情報 | Y26: - | AE26: -
D27: =OFFSET(D27,-1,0,1,1)+1 -> 19 | E27: TENDER_CNT_DETAIL | O27: 金種登録詳細情報 | Y27: - | AE27: -

Sheet 取引ログテーブル関連図
B2: TeamStore/M POSシステム | E2: システム名 | K2: 業務名 | N2: 取引ログテーブル関連図 | X2: 履歴 | AA2: 改訂者 | AB2: 最新更新日 | AC2: 作成者 | AF2: 作成日
B3: UI設計書 | E3: トラン連携対応 | K3: トラン連携対応レイアウト | X3: =連携対象取引ログテーブル一覧!AO3 -> 1.12 | AA3: 富士通 | AB3: =連携対象取引ログテーブル一覧!AT3 -> 45709 | AC3: 富士通 | AF3: 45460
AB6: ：TRAN_IDのリンク (富士通側でトラン取込み後にリンク付け)
AB7: ：TRAN_LN_NBR (1取引内での通し番号(抜け/重複なし)、順不同)
AB8: ：TRAN_LN_NBRのリンク
C9: ※1取引に1レコードを作成(必須)
C10: TRANS_HEADER/取引情報 | AA10: ※値引数分のレコードを作成
C11: カラム名称 | D11: 日本語名称 | E11: 型 | F11: サイズ | G11: KEY | H11: 設定例 | K11: ※商品明細数分のレコードを作成 | S11: ※商品明細1レコードに対して複数(リンク数分)のレコードを作成 | AA11: LN_DISCOUNT/値引情報
C12: GSFD_ACCOUNT_ID | D12: アカウントID | E12: varchar | F12: 9 | K12: LN_DETAIL/商品明細情報 | S12: LN_LINK/取引明細のリンク情報 | AA12: カラム名称 | AB12: 日本語名称 | AC12: 型 | AD12: サイズ | AE12: KEY | AF12: 設定例
C13: GSFD_JOURNAL_NO | D13: ジャーナルNo. | E13: varchar | F13: 9 | K13: カラム名称 | L13: 日本語名称 | M13: 型 | N13: サイズ | O13: KEY | P13: 設定例 | S13: カラム名称 | T13: 日本語名称 | U13: 型 | V13: サイズ | W13: KEY | X13: 設定例 | AA13: TRAN_LN_NBR | AB13: 取引明細番号 | AC13: smallint | AE13: PK
C14: TRAN_ID | D14: 取引通番 | E14: int | G14: PK | K14: TRAN_ID | L14: 取引通番 | M14: int | O14: PK | S14: TRAN_ID | T14: 取引通番 | U14: int | W14: PK | AA14: TRAN_ID | AB14: 取引通番 | AC14: int | AE14: PK
C15: RGST_TRAN_NBR | D15: レジ内取引通番 | E15: smallint | K15: TRAN_LN_NBR | L15: 取引明細番号 | M15: smallint | O15: PK | S15: TRAN_LN_NBR | T15: 取引明細番号 | U15: smallint | W15: PK | AA15: STR_ID | AB15: 店舗番号 | AC15: int | AE15: PK
C16: TRAN_CD | D16: 取引コード | E16: smallint | H16: 1 | K16: STR_ID | L16: 店舗番号 | M16: int | O16: PK | S16: LINK_LN_NBR | T16: リンク明細番号 | U16: smallint | W16: PK | AA16: DISC_MTHD | AB16: ディスカウント方法 | AC16: smallint
D17: 1:売上 | K17: LOC_ID | L17: 商品在庫位置 | M17: varchar | N17: 12 | S17: LINK_TYPE | T17: リンクタイプ | U17: smallint | W17: PK | X17: 1 | AA17: DISC_AMT | AB17: ディスカウント金額 | AC17: Money
C18: STR_ID | D18: 店舗番号 | E18: int | G18: PK | K18: SCAN_TYP | L18: PLUタイプ | M18: smallint | T18: 1：値引 | AA18: DISC_VALUE | AB18: ディスカウント値 | AC18: float
C19: EMP_ID | D19: 従業員ＩＤ | E19: varchar | F19: 12 | L19: 2：UPC-A | S19: LINK_AMT | T19: リンク明細額 | U19: Money | AA19: DISC_ID | AB19: ディスカウントＩＤ | AC19: int
C20: RGST_ID | D20: レジスタID | E20: int | L20: 3：部門コード | S20: STR_ID | T20: 店舗番号 | U20: int | W20: PK | AA20: VOID_CD | AB20: 取消コード | AC20: smallint
C21: TILL_ID | D21: ティルID | E21: varchar | F21: 12 | L21: 4：EAN8、JAN8(NONPLU8) | S21: LINK_QTY | T21: リンクの数 | U21: float | AA21: DISC_ACCT | AB21: ディスカウント会計科目 | AC21: varchar | AD21: 24
C22: BUS_DT | D22: 営業日 | E22: datetime | L22: 5：EAN13、JAN13(NONPLU13)、新/旧書籍、新/旧雑誌 | AA22: DG_ID | AB22: ディスカウントグループＩＤ | AC22: varchar | AD22: 12
C23: TRAN_START_TS | D23: 取引開始時刻 | E23: datetime | L23: etc. | AA23: EVNT_ID | AB23: イベントコード | AC23: varchar | AD23: 6
C24: TRAN_END_DTTM | D24: 取引終了時刻 | E24: datetime | K24: PLU_ID | L24: 自社商品コード | M24: varchar | N24: 24 | AA24: DISC_CLSS_ID | AB24: ディスカウントクラスＩＤ | AC24: int
C25: OFFLN_FG | D25: オフライン判別 | E25: smallint | K25: SCAN_ID | L25: スキャンコード | M25: varchar | N25: 24 | AB25: ※値引コード一覧を参照
C26: TRNING_MDE_FG | D26: トレーニングモード | E26: smallint | K26: LN_ITM_CD | L26: 商品明細識別 | M26: smallint | AA26: … | AB26: …
C27: RNTRY_MDE_FG | D27: 再入力モード | E27: smallint | K27: MDSE_XREF_NO | L27: 商品分類番号 | M27: int | AA27: GSFD_EVNT_NBR | AB27: 企画コード | AC27: varchar | AD27: 7
C28: VOID_CD | D28: 取消コード | E28: smallint | K28: STR_HIER_ID | L28: 販売部門ID | M28: int | AA28: … | AB28: …
D29: 0：通常取引、1：取引中止 | K29: QTY | L29: 販売数量 | M29: float
C30: CUST_ID | D30: 顧客ID | E30: varchar | F30: 24 | K30: UOM | L30: 販売単位 | M30: varchar | N30: 4
C31: SHPR_ID | D31: 買い物客ID | E31: varchar | F31: 24 | K31: PRC_MTHD | L31: 価格算出方法 | M31: smallint | AA31: ※部門登録、価格手入力(PLU)、売価変更を行った場合にレコードを作成
C32: STAT | D32: ステータス | E32: smallint | K32: EXT_PRC | L32: 合価 | M32: Money | AA32: MANUAL_PRICE/価格変更情報
C33: TOT_AMT | D33: 取引合計額 | E33: money | K33: EXT_CST | L33: 合計原価 | M33: Money | AA33: カラム名称 | AB33: 日本語名称 | AC33: 型 | AD33: サイズ | AE33: KEY | AF33: 設定例
C34: … | D34: … | K34: RTL_PRC | L34: 小売価格 | M34: Money | AA34: TRAN_LN_NBR | AB34: 取引明細番号 | AC34: smallint | AE34: PK
K35: ENTRY_MTHD | L35: 登録方法 | M35: smallint | AA35: ORIG_PRC | AB35: 変更前価格 | AC35: money | AE35: PK
K36: COMM_EMP_ID | L36: 担当従業員ＩＤ | M36: varchar | N36: 12 | AA36: TRAN_ID | AB36: 取引通番 | AC36: int | AE36: PK
C37: ※1取引に1レコードを作成(ポイントカード登録がある場合のみ) | K37: … | L37: … | AA37: STR_ID | AB37: 店舗番号 | AC37: int | AE37: PK
C38: GSFD_PNT_TRANS_HEADER/ポイント情報 | K38: GSFD_SCAN_CODE | L38: スキャンコード（単品登録時） | M38: varchar | N38: 75 | AA38: AUTH_EMP_ID | AB38: 承認従業員ID | AC38: varchar | AD38: 12
C39: カラム名称 | D39: 日本語名称 | E39: 型 | F39: サイズ | G39: KEY | H39: 設定例 | K39: … | L39: … | AA39: OVRD_PRC | AB39: 変更価格 | AC39: money
C40: TRAN_ID | D40: 取引通番 | E40: int | G40: PK | K40: GSFD_TAX_TYPE | L40: 明細の税種別 | M40: smallint | AA40: … | AB40: …
C41: STR_ID | D41: 店舗番号 | E41: int | G41: PK | L41: 1：外税、2：内税、3：非課税
C42: RGST_TRAN_NBR | D42: POS取引通番 | E42: smallint | K42: … | L42: …
C43: RGST_ID | D43: POS番号 | E43: int | K43: GSFD_PLU_TAXBLTY_CD | L43: 明細の税種別コード | M43: smallint | AA43: ※取引に含まれる税種別コード分のレコードを作成
C44: TRAN_STRT_TS | D44: 取引開始日時 | E44: datetime | L44: 1：外税(8%)、2：内税(8%)、3：非課税、4：外税(10%)、5：内税（10％） | S44: カラム名称 | T44: 日本語名称 | U44: 型 | V44: サイズ | W44: KEY | X44: 設定例 | AA44: TRANSACTION_TAX/取引の税情報
C45: CUST_ID | D45: 顧客コード | E45: varchar | F45: 24 | K45: … | L45: … | S45: TRAN_ID | T45: 取引通番 | U45: int | W45: PK | AA45: カラム名称 | AB45: 日本語名称 | AC45: 型 | AD45: サイズ | AE45: KEY | AF45: 設定例
C46: GSTP_DAILY_RATE | D46: スケジュール倍率 | E46: float | S46: TRAN_LN_NBR | T46: 取引明細番号 | U46: smallint | W46: PK | AA46: TRAN_ID | AB46: 取引通番 | AC46: int | AE46: PK
C47: … | D47: … | S47: LINK_LN_NBR | T47: リンク明細番号 | U47: smallint | W47: PK | AA47: TRAN_LN_NBR | AB47: 取引明細番号 | AC47: smallint | AE47: PK
S48: LINK_TYPE | T48: リンクタイプ | U48: smallint | W48: PK | X48: 3 | AA48: STR_ID | AB48: 店舗番号 | AC48: int | AE48: PK
K49: ※支払明細数分のレコードを作成 | T49: 3：税 | AA49: TAX_CD | AB49: 税金コード | AC49: smallint
K50: TRANSACTION_TENDER/取引の支払情報 | S50: LINK_AMT | T50: リンク明細額 | U50: Money | AB50: 1：外税、2：内税込み、3：非課税、99：課税対象外
K51: カラム名称 | L51: 日本語名称 | M51: 型 | N51: サイズ | O51: KEY | P51: 設定例 | S51: STR_ID | T51: 店舗番号 | U51: int | W51: PK | AA51: TAX_MODIF | AB51: 税変更コード | AC51: smallint
K52: TRAN_LN_NBR | L52: 取引明細番号 | M52: smallint | O52: PK | S52: LINK_QTY | T52: リンクの数 | U52: float | AA52: TAX_AMT | AB52: 税金総額 | AC52: Money
K53: TRAN_ID | L53: 取引通番 | M53: int | O53: PK | AA53: VOID_CD | AB53: 取消コード | AC53: smallint
K54: STR_ID | L54: 店舗番号 | M54: int | O54: PK | AA54: VAT_AMT | AB54: 内税総額 | AC54: Money
K55: TND_CD | L55: 支払種別 | M55: smallint | AA55: VATBL_AMT | AB55: 内税金額 | AC55: Money
K56: TND_TS | L56: 支払日時 | M56: datetime | AA56: TAX_BLE_AMT | AB56: 課税対象金額 | AC56: Money
K57: AMT | L57: 合計金額 | M57: Money | AA57: … | AB57: …
K58: ENTRY_MTHD | L58: 登録方法コード | M58: smallint
K59: TND_AMT | L59: 支払総額 | M59: Money
K60: VOID_CD | L60: 取消コード | M60: smallint
K61: … | L61: …
K64: ※現金以外の支払明細数分のレコードを作成
K65: GIFT_CERT_TENDER/現外支払情報
K66: カラム名称 | L66: 日本語名称 | M66: 型 | N66: サイズ | O66: KEY | P66: 設定例
K67: SRC_STR_ID | L67: 発行店舗番号 | M67: int
K68: GFT_CERT_ID | L68: 商品券番号 | M68: varchar | N68: 24
K69: STR_ID | L69: 店舗番号 | M69: int | O69: PK
K70: TRAN_LN_NBR | L70: 取引明細番号 | M70: smallint | O70: PK
K71: TRAN_ID | L71: 取引ID | M71: int | O71: PK
K72: GFT_CERT_AMT | L72: 商品券価格 | M72: money
K73: CHANGE_AMT | L73: 釣銭金額 | M73: money
B77: TeamStore/M POSシステム | E77: システム名 | K77: 業務名 | N77: =N$2 -> 取引ログテーブル関連図 | X77: 履歴 | AA77: 改訂者 | AB77: 最新更新日 | AC77: 作成者 | AF77: 作成日
B78: UI設計書 | E78: トラン連携対応 | K78: トラン連携対応レイアウト | X78: =X$3 -> 1.12 | AA78: =AA$3 -> 富士通 | AB78: =AB$3 -> 45709 | AC78: =AC$3 -> 富士通 | AF78: =AF$3 -> 45460
AB81: ：TRAN_IDのリンク (富士通側でトラン取込み後にリンク付け)
AB82: ：TRAN_LN_NBR (1取引内での通し番号(抜け/重複なし)、順不同)
C84: ※1取引に1レコードを作成(必須)
C85: TRANS_HEADER/取引情報
C86: カラム名称 | D86: 日本語名称 | E86: 型 | F86: サイズ | G86: KEY | H86: 設定例 | K86: ※1レコードを作成
C87: GSFD_ACCOUNT_ID | D87: アカウントID | E87: varchar | F87: 9 | K87: GL_TRAN/支払情報
C88: GSFD_JOURNAL_NO | D88: ジャーナルNo. | E88: varchar | F88: 9 | K88: カラム名称 | L88: 日本語名称 | M88: 型 | N88: サイズ | O88: KEY | P88: 設定例
C89: TRAN_ID | D89: 取引通番 | E89: int | G89: PK | K89: TRAN_ID | L89: 取引通番 | M89: int | O89: PK
C90: RGST_TRAN_NBR | D90: レジ内取引通番 | E90: smallint | K90: TRAN_LN_NBR | L90: 取引明細番号 | M90: smallint | O90: PK
C91: TRAN_CD | D91: 取引コード | E91: smallint | H91: 15 or 16 | K91: GL_TRAN_TS | L91: 取引日時 | M91: datetime
D92: 15:入金、16:出金 | K92: VOID_CD | L92: 取消コード | M92: smallint
C93: STR_ID | D93: 店舗番号 | E93: int | G93: PK | K93: TND_CD | L93: 支払種別 | M93: smallint
C94: EMP_ID | D94: 従業員ＩＤ | E94: varchar | F94: 12 | K94: STAT | L94: ステータス | M94: smallint
C95: RGST_ID | D95: レジスタID | E95: int | K95: GL_ACCT_ID | L95: G/LアカウントID | M95: varchar | N95: 20
C96: TILL_ID | D96: ティルID | E96: varchar | F96: 12 | K96: GL_AMT | L96: 金額 | M96: money
C97: BUS_DT | D97: 営業日 | E97: datetime | K97: REAS_CD | L97: 理由コード | M97: smallint
C98: TRAN_START_TS | D98: 取引開始時刻 | E98: datetime | K98: DESCR | L98: 入出金名称 | M98: varchar | N98: 20
C99: TRAN_END_DTTM | D99: 取引終了時刻 | E99: datetime | K99: STR_ID | L99: 店舗番号 | M99: int | O99: PK
C100: OFFLN_FG | D100: オフライン判別 | E100: smallint
C101: TRNING_MDE_FG | D101: トレーニングモード | E101: smallint | K101: ※1レコードを作成
C102: RNTRY_MDE_FG | D102: 再入力モード | E102: smallint | K102: TRANSACTION_TENDER/取引の支払情報
C103: VOID_CD | D103: 取消コード | E103: smallint | K103: カラム名称 | L103: 日本語名称 | M103: 型 | N103: サイズ | O103: KEY | P103: 設定例
D104: 0：通常取引、1：取引中止 | K104: TRAN_LN_NBR | L104: 取引明細番号 | M104: smallint | O104: PK
C105: CUST_ID | D105: 顧客ID | E105: varchar | F105: 24 | K105: TRAN_ID | L105: 取引通番 | M105: int | O105: PK
C106: SHPR_ID | D106: 買い物客ID | E106: varchar | F106: 24 | K106: STR_ID | L106: 店舗番号 | M106: int | O106: PK
C107: STAT | D107: ステータス | E107: smallint | K107: TND_CD | L107: 支払種別 | M107: smallint
C108: TOT_AMT | D108: 取引合計額 | E108: money | K108: TND_TS | L108: 支払日時 | M108: datetime
C109: … | D109: … | K109: … | L109: …
L116: ※釣銭補充は、TRANS_HEADERのみ
C118: ※1取引に1レコードを作成(必須)
...

Sheet 取引ログテーブル関連図（補足説明）
B2: TeamStore/M POSシステム | E2: システム名 | K2: 業務名 | N2: 取引ログテーブル関連図（補足説明） | X2: 履歴 | AA2: 改訂者 | AB2: 最新更新日 | AC2: 作成者 | AF2: 作成日
B3: UI設計書 | E3: トラン連携対応 | K3: トラン連携対応レイアウト | X3: =連携対象取引ログテーブル一覧!AO3 -> 1.12 | AA3: 富士通 | AB3: =取引ログテーブル関連図!AB3 -> 45709 | AC3: 富士通 | AF3: 45460
AB6: ：TRAN_IDのリンク (富士通側でトラン取込み後にリンク付け)
J7: ※説明対象テーブルのみを抜粋 | AB7: ：TRAN_LN_NBR (1取引内での通し番号(抜け/重複なし)、順不同)
AB8: ：TRAN_LN_NBRのリンク
C10: TRANS_HEADER/取引情報
C11: カラム名称 | D11: 日本語名称 | E11: 型 | F11: サイズ | G11: KEY | H11: 設定例
C12: GSFD_ACCOUNT_ID | D12: アカウントID | E12: varchar | F12: 9 | K12: LN_DETAIL/商品明細情報 | S12: LN_LINK/取引明細のリンク情報
C13: GSFD_JOURNAL_NO | D13: ジャーナルNo. | E13: varchar | F13: 9 | K13: カラム名称 | L13: 日本語名称 | M13: 型 | N13: サイズ | O13: KEY | P13: 設定例 | S13: カラム名称 | T13: 日本語名称 | U13: 型 | V13: サイズ | W13: KEY | X13: 設定例
C14: TRAN_ID | D14: 取引通番 | E14: int | G14: PK | H14: 6079449 | K14: TRAN_ID | L14: 取引通番 | M14: int | O14: PK | P14: 6079449 | S14: TRAN_ID | T14: 取引通番 | U14: int | W14: PK | X14: 6079449
C15: RGST_TRAN_NBR | D15: レジ内取引通番 | E15: smallint | H15: 54 | K15: TRAN_LN_NBR | L15: 取引明細番号 | M15: smallint | O15: PK | P15: 1 | S15: TRAN_LN_NBR | T15: 取引明細番号 | U15: smallint | W15: PK | X15: 1
C16: TRAN_CD | D16: 取引コード | E16: smallint | H16: 1 | K16: STR_ID | L16: 店舗番号 | M16: int | O16: PK | P16: 200000 | S16: LINK_LN_NBR | T16: リンク明細番号 | U16: smallint | W16: PK | X16: 8
D17: 1:売上 | K17: LOC_ID | L17: 商品在庫位置 | M17: varchar | N17: 12 | S17: LINK_TYPE | T17: リンクタイプ | U17: smallint | W17: PK | X17: 1
C18: STR_ID | D18: 店舗番号 | E18: int | G18: PK | H18: 200000 | K18: SCAN_TYP | L18: PLUタイプ | M18: smallint | P18: 5 | S18: LINK_AMT | T18: リンク明細額 | U18: Money | X18: -113
C19: EMP_ID | D19: 従業員ＩＤ | E19: varchar | F19: 12 | H19: 1111111 | K19: PLU_ID | L19: 自社商品コード | M19: varchar | N19: 24 | P19: 0000010000001 | S19: STR_ID | T19: 店舗番号 | U19: int | W19: PK | X19: 200000
C20: RGST_ID | D20: レジスタID | E20: int | H20: 2 | K20: SCAN_ID | L20: スキャンコード | M20: varchar | N20: 24 | P20: 2162000001918 | S20: LINK_QTY | T20: リンクの数 | U20: float | X20: 1
C21: TILL_ID | D21: ティルID | E21: varchar | F21: 12 | K21: … | L21: …
C22: BUS_DT | D22: 営業日 | E22: datetime | H22: 45442 | K22: QTY | L22: 販売数量 | M22: float | P22: 1
C23: TRAN_START_TS | D23: 取引開始時刻 | E23: datetime | H23: 45442.85 | K23: … | L23: …
C24: TRAN_END_DTTM | D24: 取引終了時刻 | E24: datetime | H24: 45442.851 | K24: EXT_PRC | L24: 合価 | M24: Money | P24: 2248
C25: OFFLN_FG | D25: オフライン判別 | E25: smallint | K25: … | L25: …
C26: TRNING_MDE_FG | D26: トレーニングモード | E26: smallint | K26: RTL_PRC | L26: 小売価格 | M26: Money | P26: 2248
C27: RNTRY_MDE_FG | D27: 再入力モード | E27: smallint | K27: … | L27: … | AA27: LN_DISCOUNT/値引情報
C28: VOID_CD | D28: 取消コード | E28: smallint | H28: 0 | AA28: ※単品系：単品に対する値引はLN_DETAILと１：１でレコードを作成（例：マニュアル値引 10%割引)
D29: 0：通常取引、1：取引中止 | AA29: カラム名称 | AB29: 日本語名称 | AC29: 型 | AD29: サイズ | AE29: KEY | AF29: 設定例
C30: CUST_ID | D30: 顧客ID | E30: varchar | F30: 24 | H30: 2603000711365 | K30: カラム名称 | L30: 日本語名称 | M30: 型 | N30: サイズ | O30: KEY | P30: 設定例 | S30: カラム名称 | T30: 日本語名称 | U30: 型 | V30: サイズ | W30: KEY | X30: 設定例 | AA30: TRAN_LN_NBR | AB30: 取引明細番号 | AC30: smallint | AE30: PK | AF30: 4
C31: SHPR_ID | D31: 買い物客ID | E31: varchar | F31: 24 | K31: TRAN_ID | L31: 取引通番 | M31: int | O31: PK | P31: 6079449 | S31: TRAN_ID | T31: 取引通番 | U31: int | W31: PK | X31: 6079449 | AA31: TRAN_ID | AB31: 取引通番 | AC31: int | AE31: PFK | AF31: 6079449
C32: STAT | D32: ステータス | E32: smallint | K32: TRAN_LN_NBR | L32: 取引明細番号 | M32: smallint | O32: PK | P32: 3 | S32: TRAN_LN_NBR | T32: 取引明細番号 | U32: smallint | W32: PK | X32: 3 | AA32: STR_ID | AB32: 店舗番号 | AC32: int | AE32: PFK | AF32: 200000
C33: TOT_AMT | D33: 取引合計額 | E33: money | H33: 12000 | K33: STR_ID | L33: 店舗番号 | M33: int | O33: PK | P33: 200000 | S33: LINK_LN_NBR | T33: リンク明細番号 | U33: smallint | W33: PK | X33: 4 | AA33: DISC_MTHD | AB33: ディスカウント方法 | AC33: smallint | AF33: 2
C34: … | D34: … | K34: LOC_ID | L34: 商品在庫位置 | M34: varchar | N34: 12 | S34: LINK_TYPE | T34: リンクタイプ | U34: smallint | W34: PK | X34: 1 | AB34: 2：％値引
K35: SCAN_TYP | L35: PLUタイプ | M35: smallint | P35: 5 | S35: LINK_AMT | T35: リンク明細額 | U35: Money | X35: -684 | AA35: DISC_AMT | AB35: ディスカウント金額 | AC35: Money | AF35: -684
K36: PLU_ID | L36: 自社商品コード | M36: varchar | N36: 24 | P36: 0000010000002 | S36: STR_ID | T36: 店舗番号 | U36: int | W36: PK | X36: 200000 | AA36: DISC_VALUE | AB36: ディスカウント値 | AC36: float | AF36: 0.1
C37: 【説明例】 | K37: SCAN_ID | L37: スキャンコード | M37: varchar | N37: 24 | P37: 2162000001390 | S37: LINK_QTY | T37: リンクの数 | U37: float | X37: 3 | AA37: DISC_ID | AB37: ディスカウントＩＤ | AC37: int | AF37: 2
K38: … | L38: … | AA38: VOID_CD | AB38: 取消コード | AC38: smallint
K39: QTY | L39: 販売数量 | M39: float | P39: 3 | S39: カラム名称 | T39: 日本語名称 | U39: 型 | V39: サイズ | W39: KEY | X39: 設定例 | AA39: DISC_ACCT | AB39: ディスカウント会計科目 | AC39: varchar | AD39: 24
K40: … | L40: … | S40: TRAN_ID | T40: 取引通番 | U40: int | W40: PK | X40: 6079449 | AA40: DG_ID | AB40: ディスカウントグループＩＤ | AC40: varchar | AD40: 12
K41: EXT_PRC | L41: 合価 | M41: Money | P41: 6813 | S41: TRAN_LN_NBR | T41: 取引明細番号 | U41: smallint | W41: PK | X41: 3 | AA41: EVNT_ID | AB41: イベントコード | AC41: varchar | AD41: 6
K42: … | L42: … | S42: LINK_LN_NBR | T42: リンク明細番号 | U42: smallint | W42: PK | X42: 8 | AA42: DISC_CLSS_ID | AB42: ディスカウントクラスＩＤ | AC42: int | AF42: 91220
K43: RTL_PRC | L43: 小売価格 | M43: Money | P43: 2271 | S43: LINK_TYPE | T43: リンクタイプ | U43: smallint | W43: PK | X43: 1 | AB43: 91220：マニュアル値引
K44: … | L44: … | S44: LINK_AMT | T44: リンク明細額 | U44: Money | X44: -309 | AA44: … | AB44: …
S45: STR_ID | T45: 店舗番号 | U45: int | W45: PK | X45: 200000
S46: LINK_QTY | T46: リンクの数 | U46: float | X46: 3 | AA46: ※複数明細系：複数の商品に対する値引はLN_DETAILとｎ：１でレコードを作成（例：マニュアル小計値引 532円引き)
AA47: カラム名称 | AB47: 日本語名称 | AC47: 型 | AD47: サイズ | AE47: KEY | AF47: 設定例
K48: カラム名称 | L48: 日本語名称 | M48: 型 | N48: サイズ | O48: KEY | P48: 設定例 | S48: カラム名称 | T48: 日本語名称 | U48: 型 | V48: サイズ | W48: KEY | X48: 設定例 | AA48: TRAN_LN_NBR | AB48: 取引明細番号 | AC48: smallint | AE48: PK | AF48: 8
K49: TRAN_ID | L49: 取引通番 | M49: int | O49: PK | P49: 6079449 | S49: TRAN_ID | T49: 取引通番 | U49: int | W49: PK | X49: 6079449 | AA49: TRAN_ID | AB49: 取引通番 | AC49: int | AE49: PFK | AF49: 6079449
K50: TRAN_LN_NBR | L50: 取引明細番号 | M50: smallint | O50: PK | P50: 5 | S50: TRAN_LN_NBR | T50: 取引明細番号 | U50: smallint | W50: PK | X50: 5 | AA50: STR_ID | AB50: 店舗番号 | AC50: int | AE50: PFK | AF50: 200000
K51: STR_ID | L51: 店舗番号 | M51: int | O51: PK | P51: 200000 | S51: LINK_LN_NBR | T51: リンク明細番号 | U51: smallint | W51: PK | X51: 8 | AA51: DISC_MTHD | AB51: ディスカウント方法 | AC51: smallint | AF51: 13
K52: LOC_ID | L52: 商品在庫位置 | M52: varchar | N52: 12 | S52: LINK_TYPE | T52: リンクタイプ | U52: smallint | W52: PK | X52: 1 | AB52: 13：小計額値引
K53: SCAN_TYP | L53: PLUタイプ | M53: smallint | P53: 5 | S53: LINK_AMT | T53: リンク明細額 | U53: Money | X53: -110 | AA53: DISC_AMT | AB53: ディスカウント金額 | AC53: Money | AF53: -532
K54: PLU_ID | L54: 自社商品コード | M54: varchar | N54: 24 | P54: 0000010000003 | S54: STR_ID | T54: 店舗番号 | U54: int | W54: PK | X54: 200000 | AA54: DISC_VALUE | AB54: ディスカウント値 | AC54: float | AF54: 532
K55: SCAN_ID | L55: スキャンコード | M55: varchar | N55: 24 | P55: 4901650291533 | S55: LINK_QTY | T55: リンクの数 | U55: float | X55: 1 | AA55: DISC_ID | AB55: ディスカウントＩＤ | AC55: int | AF55: 14
K56: … | L56: … | AA56: VOID_CD | AB56: 取消コード | AC56: smallint
K57: QTY | L57: 販売数量 | M57: float | P57: 1 | AA57: DISC_ACCT | AB57: ディスカウント会計科目 | AC57: varchar | AD57: 24
K58: … | L58: … | AA58: DG_ID | AB58: ディスカウントグループＩＤ | AC58: varchar | AD58: 12
K59: EXT_PRC | L59: 合価 | M59: Money | P59: 2248 | AA59: EVNT_ID | AB59: イベントコード | AC59: varchar | AD59: 6
K60: … | L60: … | AA60: DISC_CLSS_ID | AB60: ディスカウントクラスＩＤ | AC60: int | AF60: 91400
K61: RTL_PRC | L61: 小売価格 | M61: Money | P61: 2248 | AB61: 91400：マニュアル小計値引
K62: … | L62: … | AA62: … | AB62: …
AA64: 【値引種類】
K65: ※小計値引除外商品 | AA65: 種別 | AB65: DISC_CLSS_ID | AC65: 値引
K66: カラム名称 | L66: 日本語名称 | M66: 型 | N66: サイズ | O66: KEY | P66: 設定例 | AA66: 単品系 | AB66: 91110(会員)/91111(一般) | AC66: マークダウン
K67: TRAN_ID | L67: 取引通番 | M67: int | O67: PK | P67: 6079449 | AB67: 91120(会員)/91121(一般) | AC67: タイムサービス
K68: TRAN_LN_NBR | L68: 取引明細番号 | M68: smallint | O68: PK | P68: 6 | AB68: 91140(会員)/91141(一般) | AC68: 期間特売
K69: STR_ID | L69: 店舗番号 | M69: int | O69: PK | P69: 200000 | AB69: 91220 | AC69: マニュアル値引、バーコード値引
K70: LOC_ID | L70: 商品在庫位置 | M70: varchar | N70: 12 | AA70: 複数明細系 | AB70: 91315(会員)/91316(一般) | AC70: バンドル
K71: SCAN_TYP | L71: PLUタイプ | M71: smallint | P71: 5 | AB71: 91317(会員)/91318(一般) | AC71: ペアマッチ
K72: PLU_ID | L72: 自社商品コード | M72: varchar | N72: 24 | P72: 0000010000004 | AB72: 91323 | AC72: 商品階層自動値引(中分類) 除外
K73: SCAN_ID | L73: スキャンコード | M73: varchar | N73: 24 | P73: 4900000111118 | AB73: 91324 | AC73: 商品階層自動値引(中分類)
K74: … | L74: … | AB74: 91325 | AC74: 商品階層自動値引(大分類) 除外
K75: QTY | L75: 販売数量 | M75: float | P75: 1 | AB75: 91326 | AC75: 商品階層自動値引(大分類)
K76: … | L76: … | AB76: 91329(会員)/91330(一般) | AC76: 小計自動値引
K77: EXT_PRC | L77: 合価 | M77: Money | P77: 1000 | AB77: 91400 | AC77: マニュアル小計値引
K78: … | L78: …
K79: RTL_PRC | L79: 小売価格 | M79: Money | P79: 1000
K80: … | L80: …
B84: TeamStore/M POSシステム | E84: システム名 | K84: 業務名 | N84: =N$2 -> 取引ログテーブル関連図（補足説明） | X84: 履歴 | AA84: 改訂者 | AB84: 最新更新日 | AC84: 作成者 | AF84: 作成日
B85: UI設計書 | E85: トラン連携対応 | K85: トラン連携対応レイアウト | X85: =X$3 -> 1.12 | AA85: =AA$3 -> 富士通 | AB85: =AB$3 -> 45709 | AC85: =AC$3 -> 富士通 | AF85: =AF$3 -> 45460
AB88: ：TRAN_IDのリンク (富士通側でトラン取込み後にリンク付け)
J89: ※説明対象テーブルのみを抜粋 | AB89: ：TRAN_LN_NBR (1取引内での通し番号(抜け/重複なし)、順不同)
AB90: ：TRAN_LN_NBRのリンク
C92: TRANS_HEADER/取引情報
C93: カラム名称 | D93: 日本語名称 | E93: 型 | F93: サイズ | G93: KEY | H93: 設定例
C94: GSFD_ACCOUNT_ID | D94: アカウントID | E94: varchar | F94: 9 | K94: LN_DETAIL/商品明細情報 | S94: LN_LINK/取引明細のリンク情報 | AA94: TRANSACTION_TAX/取引の税情報
C95: GSFD_JOURNAL_NO | D95: ジャーナルNo. | E95: varchar | F95: 9 | K95: カラム名称 | L95: 日本語名称 | M95: 型 | N95: サイズ | O95: KEY | P95: 設定例 | S95: カラム名称 | T95: 日本語名称 | U95: 型 | V95: サイズ | W95: KEY | X95: 設定例 | AA95: カラム名称 | AB95: 日本語名称 | AC95: 型 | AD95: サイズ | AE95: KEY | AF95: 設定例
C96: TRAN_ID | D96: 取引通番 | E96: int | G96: PK | H96: 6079449 | K96: TRAN_ID | L96: 取引通番 | M96: int | O96: PK | P96: 6079449 | S96: TRAN_ID | T96: 取引通番 | U96: int | W96: PK | X96: 6079449 | AA96: TRAN_ID | AB96: 取引通番 | AC96: int | AE96: PK | AF96: 6079449
C97: RGST_TRAN_NBR | D97: レジ内取引通番 | E97: smallint | H97: 54 | K97: TRAN_LN_NBR | L97: 取引明細番号 | M97: smallint | O97: PK | P97: 1 | S97: TRAN_LN_NBR | T97: 取引明細番号 | U97: smallint | W97: PK | X97: 1 | AA97: TRAN_LN_NBR | AB97: 取引明細番号 | AC97: smallint | AE97: PK | AF97: 2
C98: TRAN_CD | D98: 取引コード | E98: smallint | H98: 1 | K98: STR_ID | L98: 店舗番号 | M98: int | O98: PK | P98: 200000 | S98: LINK_LN_NBR | T98: リンク明細番号 | U98: smallint | W98: PK | X98: 2 | AA98: STR_ID | AB98: 店舗番号 | AC98: int | AE98: PK | AF98: 200000
D99: 1:売上 | K99: LOC_ID | L99: 商品在庫位置 | M99: varchar | N99: 12 | S99: LINK_TYPE | T99: リンクタイプ | U99: smallint | W99: PK | X99: 3 | AA99: TAX_CD | AB99: 税金コード | AC99: smallint | AF99: 1
C100: STR_ID | D100: 店舗番号 | E100: int | G100: PK | H100: 200000 | K100: SCAN_TYP | L100: PLUタイプ | M100: smallint | P100: 5 | S100: LINK_AMT | T100: リンク明細額 | U100: Money | X100: 0 | AB100: 1：外税(8%)
C101: EMP_ID | D101: 従業員ＩＤ | E101: varchar | F101: 12 | H101: 1111111 | K101: PLU_ID | L101: 自社商品コード | M101: varchar | N101: 24 | P101: 0000010000001 | S101: STR_ID | T101: 店舗番号 | U101: int | W101: PK | X101: 200000 | AA101: TAX_MODIF | AB101: 税変更コード | AC101: smallint | AF101: 1
C102: RGST_ID | D102: レジスタID | E102: int | H102: 2 | K102: SCAN_ID | L102: スキャンコード | M102: varchar | N102: 24 | P102: 2162000001918 | S102: LINK_QTY | T102: リンクの数 | U102: float | X102: 0 | AA102: TAX_AMT | AB102: 税金総額 | AC102: Money | AF102: 807
C103: TILL_ID | D103: ティルID | E103: varchar | F103: 12 | K103: … | L103: … | AA103: VOID_CD | AB103: 取消コード | AC103: smallint
C104: BUS_DT | D104: 営業日 | E104: datetime | H104: 45442 | K104: QTY | L104: 販売数量 | M104: float | P104: 1 | AA104: VAT_AMT | AB104: 内税総額 | AC104: Money | AF104: 0
C105: TRAN_START_TS | D105: 取引開始時刻 | E105: datetime | H105: 45442.85 | K105: … | L105: … | AA105: VATBL_AMT | AB105: 内税金額 | AC105: Money | AF105: 0
C106: TRAN_END_DTTM | D106: 取引終了時刻 | E106: datetime | H106: 45442.851 | K106: EXT_PRC | L106: 合価 | M106: Money | P106: 2248 | AA106: TAX_BLE_AMT | AB106: 課税対象金額 | AC106: Money | AF106: 10093
C107: OFFLN_FG | D107: オフライン判別 | E107: smallint | K107: … | L107: … | AA107: … | AB107: …
C108: TRNING_MDE_FG | D108: トレーニングモード | E108: smallint | K108: RTL_PRC | L108: 小売価格 | M108: Money | P108: 2248
C109: RNTRY_MDE_FG | D109: 再入力モード | E109: smallint | K109: … | L109: …
C110: VOID_CD | D110: 取消コード | E110: smallint | H110: 0
D111: 0：通常取引、1：取引中止
...

Sheet 取引ログ作成時の注意事項
B2: TeamStore/M POSシステム | O2: システム名 | U2: 業務名 | AB2: 取引ログ作成時の注意事項 | AO2: 履歴 | AQ2: 改訂者 | AT2: 最新更新日 | AX2: 作成者 | BA2: 作成日
B3: UI設計書 | O3: トラン連携対応 | U3: トラン連携対応レイアウト | AO3: ='取引ログテーブル関連図（補足説明）'!X3 -> 1.12 | AQ3: 富士通 | AT3: ='取引ログテーブル関連図（補足説明）'!AB3 -> 45709 | AX3: 富士通 | BA3: 45460
C6: (1) | D6: 内税のリンク例 | BE6: (*1.5)
D8: 商品明細 | G8: 1個 | I8: \200 | J8: 内税10%商品(税抜価格：\182)
D9: 商品明細 | G9: 1個 | I9: \200 | J9: 内税8%商品(税抜価格：\186)
D10: 預金 | I10: \400
D12: 税種別（TAX_CD)
D13: 外税：１、内税：２、非課税：３、内税：９９
D15: 取引情報 | M15: 商品明細情報 | V15: 取引明細のリンク情報 | AE15: 取引の税情報
D16: TRSNS_HEADER | M16: LN_DETAIL | V16: LN_LINK | AE16: TRANSACTION_TAX | AM16: 内税10%のレコード
E17: TRAN_ID | J17: TS/Mで採番 | N17: TRAN_ID | S17: TS/Mで採番 | W17: TRAN_ID | AB17: TS/Mで採番 | AF17: TRAN_ID | AK17: TS/Mで採番
E18: TRAN_CD | J18: 1 | N18: TRAN_LN_NBR | S18: 1 | W18: TRAN_LN_NBR | AB18: 1 | AF18: TRAN_LN_NBR | AK18: 4
E19: TOT_AMT | J19: 400 | W19: LINK_LN_NBR | AB19: 4 | AF19: TAX_CD | AK19: 5(内税10%)
M20: 内税10%商品のレコード | W20: LINK_TYP | AB20: 3 | AF20: VAT_AMT | AK20: 18
V21: 内税のリンク情報 | AF21: VATABL_AMT | AK21: 182
AF22: TAXBLE_AMT | AK22: 200
V23: 取引明細のリンク情報
V24: LN_LINK
W25: TRAN_ID | AB25: TS/Mで採番
W26: TRAN_LN_NBR | AB26: 1 | AS26: 商品明細に紐づく税情報
W27: LINK_LN_NBR | AB27: 4 | AS27: ３つのリンクと1つの税情報を作成する。
W28: LINK_TYP | AB28: 9
V29: 内税額のリンク情報
V31: 取引明細のリンク情報
V32: LN_LINK
W33: TRAN_ID | AB33: TS/Mで採番
W34: TRAN_LN_NBR | AB34: 1
W35: LINK_LN_NBR | AB35: 4
W36: LINK_TYP | AB36: 10
V37: 内税商品額(税抜き)のリンク情報
V43: 取引明細のリンク情報 | AE43: 取引の税情報
V44: LN_LINK | AE44: TRANSACTION_TAX | AM44: 内税合計のレコード
W45: TRAN_ID | AB45: TS/Mで採番 | AF45: TRAN_ID | AK45: TS/Mで採番
W46: TRAN_LN_NBR | AB46: 1 | AF46: TRAN_LN_NBR | AK46: 5
W47: LINK_LN_NBR | AB47: 5 | AF47: TAX_CD | AK47: 99(内税) | AS47: 内税の合計情報
W48: LINK_TYP | AB48: 3 | AF48: VAT_AMT | AK48: 0 | AS48: (内税10%・内税8%の合計)
V49: 内税合計のレコードへのリンク | AF49: VATABL_AMT | AK49: 0
AF50: TAXBLE_AMT | AK50: 400
B56: TeamStore/M POSシステム | O56: システム名 | U56: 業務名 | AB56: 取引ログ作成時の注意事項 | AO56: 履歴 | AQ56: 改訂者 | AT56: 最新更新日 | AX56: 作成者 | BA56: 作成日
B57: UI設計書 | O57: トラン連携対応 | U57: トラン連携対応レイアウト | AO57: =AO$3 -> 1.12 | AQ57: 富士通 | AT57: =AT$3 -> 45709 | AX57: 富士通 | BA57: 45460
BE60: (*1.5)
M61: 商品明細情報 | V61: 取引明細のリンク情報 | AE61: 取引の税情報
M62: LN_DETAIL | V62: LN_LINK | AE62: TRANSACTION_TAX | AM62: 内税8%のレコード
N63: TRAN_ID | S63: TS/Mで採番 | W63: TRAN_ID | AB63: TS/Mで採番 | AF63: TRAN_ID | AK63: TS/Mで採番
N64: TRAN_LN_NBR | S64: 2 | W64: TRAN_LN_NBR | AB64: 2 | AF64: TRAN_LN_NBR | AK64: 6
W65: LINK_LN_NBR | AB65: 6 | AF65: TAX_CD | AK65: 2(内税8%)
M66: 内税8%商品のレコード | W66: LINK_TYP | AB66: 3 | AF66: VAT_AMT | AK66: 14
V67: 内税のリンク情報 | AF67: VATABL_AMT | AK67: 186
AF68: TAXBLE_AMT | AK68: 200
V69: 取引明細のリンク情報
V70: LN_LINK
W71: TRAN_ID | AB71: TS/Mで採番
W72: TRAN_LN_NBR | AB72: 2 | AS72: 商品明細に紐づく税情報
W73: LINK_LN_NBR | AB73: 6 | AS73: ３つのリンクと1つの税情報を作成する。
W74: LINK_TYP | AB74: 9
V75: 内税額のリンク情報
V77: 取引明細のリンク情報
V78: LN_LINK
W79: TRAN_ID | AB79: TS/Mで採番
W80: TRAN_LN_NBR | AB80: 2
W81: LINK_LN_NBR | AB81: 6
W82: LINK_TYP | AB82: 10
V83: 内税商品額(税抜き)のリンク情報
V87: 取引明細のリンク情報
V88: LN_LINK
W89: TRAN_ID | AB89: TS/Mで採番
W90: TRAN_LN_NBR | AB90: 2
W91: LINK_LN_NBR | AB91: 5
W92: LINK_TYP | AB92: 3
V94: 内税合計のレコードへのリンク
M100: 取引の支払情報
M101: TRANSACTION_TENDER | U101: 現金（支払）のレコード
N102: TRAN_ID | S102: TS/Mで採番
N103: TRAN_LN_NBR | S103: 3
N104: AMT | S104: -400
B110: TeamStore/M POSシステム | O110: システム名 | U110: 業務名 | AB110: 取引ログ作成時の注意事項 | AO110: 履歴 | AQ110: 改訂者 | AT110: 最新更新日 | AX110: 作成者 | BA110: 作成日
B111: UI設計書 | O111: トラン連携対応 | U111: トラン連携対応レイアウト | AO111: =AO$3 -> 1.12 | AQ111: 富士通 | AT111: =AT$3 -> 45709 | AX111: 富士通 | BA111: 45460
C114: (2) | D114: お釣り発生時のリンク例 | BE114: (*1.5)
D116: 商品明細 | G116: 1個 | I116: \168 | J116: 外税8%商品（税抜き価格）、税込み \181
D117: 預金 | I117: \200
D118: お釣り | I118: \19
D120: 税種別（TAX_CD)
D121: 外税：１、内税：２、非課税：３、内税：９９
D123: 取引情報 | M123: 商品明細情報 | V123: 取引明細のリンク情報 | AE123: 取引の税情報
D124: TRSNS_HEADER | M124: LN_DETAIL | V124: LN_LINK | AE124: TRANSACTION_TAX | AM124: 外税のレコード
E125: TRAN_ID | J125: TS/Mで採番 | N125: TRAN_ID | S125: TS/Mで採番 | W125: TRAN_ID | AB125: TS/Mで採番 | AF125: TRAN_ID | AK125: TS/Mで採番
E126: TRAN_CD | J126: 1 | N126: TRAN_LN_NBR | S126: 1 | W126: TRAN_LN_NBR | AB126: 1 | AF126: TRAN_LN_NBR | AK126: 2
E127: TOT_AMT | J127: 181 | W127: LINK_LN_NBR | AB127: 2 | AF127: TAX_CD | AK127: 1(外税)
W128: LINK_TYP | AB128: 3 | AF128: TAX＿AMT | AK128: 13
AF129: TAXBLE_AMT | AK129: 168
M130: 取引の支払情報
M131: TRANSACTION_TENDER | U131: 現金（入金）のレコード
N132: TRAN_ID | S132: TS/Mで採番
N133: TRAN_LN_NBR | S133: 3
N134: TND_CD | S134: 1
N135: AMT | S135: -200
M137: 取引の支払情報 | AC137: 現金（入金）と現金（お釣り）の２レコード作成
M138: TRANSACTION_TENDER | U138: 現金（お釣り）のレコード
N139: TRAN_ID | S139: TS/Mで採番
N140: TRAN_LN_NBR | S140: 4
...

Sheet 取引ログ作成時の注意事項(税情報)
B1: TeamStore/M POSシステム | O1: システム名 | U1: 業務名 | AB1: 取引ログ作成時の注意事項（税情報） | AO1: 履歴 | AQ1: 改訂者 | AT1: 最新更新日 | AX1: 作成者 | BA1: 作成日 | BE1: *1.5 本ページ追加
B2: UI設計書 | O2: トラン連携対応 | U2: トラン連携対応レイアウト | AO2: =取引ログ作成時の注意事項!AO3 -> 1.12 | AQ2: 富士通 | AT2: =取引ログ作成時の注意事項!AT3 -> 45709 | AX2: 富士通 | BA2: 45581
C5: (1) | D5: 税情報 (複合パターン)
D7: [売上取引 登録明細]
D8: 明細No. | F8: 商品名 | I8: 個数 | J8: 単価 | K8: 明細内合計 | N8: 税種別 | P8: 税率 | S8: 備考
D9: 1 | F9: 商品Ａ | I9: 2個 | J9: 100 | K9: 200 | N9: 外税 | P9: 0.08
D10: 2 | F10: 商品Ｂ | I10: 2個 | J10: 95 | K10: 190 | N10: 外税 | P10: 0.08
D11: 3 | F11: 商品Ｃ | I11: 2個 | J11: 100 | K11: 200 | N11: 外税 | P11: 0.1
D12: 4 | F12: 商品Ａ | I12: 3個 | J12: 100 | K12: 300 | N12: 外税 | P12: 0.1 | S12: 商品Ａ(明細No.1と同じ商品)を登録して税率変更(8%→10%)
D13: 5 | F13: 商品Ｄ | I13: 2個 | J13: 100 | K13: 200 | N13: 内税 | P13: 0.08
D14: 6 | F14: 商品Ｅ | I14: 2個 | J14: 95 | K14: 190 | N14: 内税 | P14: 0.08
D15: 7 | F15: 商品Ｆ | I15: 2個 | J15: 100 | K15: 200 | N15: 内税 | P15: 0.1
D16: 8 | F16: 商品Ｄ | I16: 3個 | J16: 100 | K16: 300 | N16: 内税 | P16: 0.1 | S16: 商品Ｄ(明細No.5と同じ商品)を登録して税率変更(8%→10%)
D17: 9 | F17: 商品Ｇ | I17: 2個 | J17: 100 | K17: 200 | N17: 非課税 | P17: 0
D18: 10 | F18: 商品Ｈ | I18: 3個 | J18: 95 | K18: 285 | N18: 非課税 | P18: 0
D20: [税種別（TAX_CD)]
D21: 外税（８％）：１、内税（８％）：２、非課税：３、外税（１０％）：４、内税（１０％）：５、内税（合計）：９９
D23: [レコード関連図] ※税情報に関連する情報のみを抜粋
L25: 【商品明細情報(外税)】 | AF25: 【税情報(外税)】
D26: 取引情報 | M26: 商品明細情報：商品Ａ | W26: 取引明細のリンク情報 | AG26: 取引の税情報
D27: TRSNS_HEADER | M27: LN_DETAIL | W27: LN_LINK | AG27: TRANSACTION_TAX | AO27: 外税8%のレコード
E28: TRAN_ID | J28: TS/Mで採番 | N28: TRAN_ID | T28: TS/Mで採番 | X28: TRAN_ID | AC28: TS/Mで採番 | AH28: TRAN_ID | AM28: TS/Mで採番
E29: TRAN_CD | J29: 1 | N29: TRAN_LN_NBR | T29: 1 | X29: TRAN_LN_NBR | AC29: 1 | AH29: TRAN_LN_NBR | AM29: 2
N30: QTY | T30: 2 | X30: LINK_LN_NBR | AC30: 2 | AH30: TAX_CD | AM30: 1 | AN30: (外税8%) | AU30: 同じ税種別(TAX_CD)の商品明細は
N31: EXT_PRC | T31: 200 | X31: LINK_TYP | AC31: 3 | AD31: (税) | AH31: TAX_MODIF | AM31: 1 | AU31: １つの税情報にまとめる
N32: GSFD_TAX_TYPE | T32: 1 | U32: (外税) | X32: LINK_AMT | AC32: 0 | AH32: TAX_AMT | AM32: 31
N33: GSFD_TAX_AMT | T33: 16 | AH33: VAT_AMT | AM33: 0
N34: GSFD_SELLING_PRC | T34: 100 | AH34: VATABL_AMT | AM34: 0
N35: GSFD_PLU_TAXBLTY_CD | T35: 1 | AH35: TAXBLE_AMT | AM35: 390
M37: 商品明細情報：商品Ｂ | W37: 取引明細のリンク情報
M38: LN_DETAIL | W38: LN_LINK
N39: TRAN_ID | T39: TS/Mで採番 | X39: TRAN_ID | AC39: TS/Mで採番
N40: TRAN_LN_NBR | T40: 3 | X40: TRAN_LN_NBR | AC40: 3
N41: QTY | T41: 2 | X41: LINK_LN_NBR | AC41: 2
N42: EXT_PRC | T42: 190 | X42: LINK_TYP | AC42: 3 | AD42: (税)
N43: GSFD_TAX_TYPE | T43: 1 | U43: (外税) | X43: LINK_AMT | AC43: 0
N44: GSFD_TAX_AMT | T44: 15
N45: GSFD_SELLING_PRC | T45: 95
N46: GSFD_PLU_TAXBLTY_CD | T46: 1
M48: 商品明細情報：商品Ｃ | W48: 取引明細のリンク情報 | AG48: 取引の税情報
M49: LN_DETAIL | W49: LN_LINK | AG49: TRANSACTION_TAX | AO49: 外税10%のレコード
N50: TRAN_ID | T50: TS/Mで採番 | X50: TRAN_ID | AC50: TS/Mで採番 | AH50: TRAN_ID | AM50: TS/Mで採番
N51: TRAN_LN_NBR | T51: 4 | X51: TRAN_LN_NBR | AC51: 4 | AH51: TRAN_LN_NBR | AM51: 5 | AU51: 外税の場合、税率変更した商品明細は、
N52: QTY | T52: 2 | X52: LINK_LN_NBR | AC52: 5 | AH52: TAX_CD | AM52: 4 | AN52: (外税10%) | AU52: 税率変更後の税種別(TAX_CD)と同じ
N53: EXT_PRC | T53: 200 | X53: LINK_TYP | AC53: 3 | AD53: (税) | AH53: TAX_MODIF | AM53: 1 | AU53: 税種別の商品明細と同じ税情報に
N54: GSFD_TAX_TYPE | T54: 1 | U54: (外税) | X54: LINK_AMT | AC54: 0 | AH54: TAX_AMT | AM54: 50 | AU54: まとめる
N55: GSFD_TAX_AMT | T55: 20 | AH55: VAT_AMT | AM55: 0
N56: GSFD_SELLING_PRC | T56: 100 | AH56: VATABL_AMT | AM56: 0
N57: GSFD_PLU_TAXBLTY_CD | T57: 4 | AH57: TAXBLE_AMT | AM57: 500
M59: 商品明細情報：商品Ａ | T59: ※税率変更 | W59: 取引明細のリンク情報
M60: LN_DETAIL | W60: LN_LINK
N61: TRAN_ID | T61: TS/Mで採番 | X61: TRAN_ID | AC61: TS/Mで採番
N62: TRAN_LN_NBR | T62: 6 | X62: TRAN_LN_NBR | AC62: 6
N63: QTY | T63: 3 | X63: LINK_LN_NBR | AC63: 5
N64: EXT_PRC | T64: 300 | X64: LINK_TYP | AC64: 3 | AD64: (税)
N65: GSFD_TAX_TYPE | T65: 1 | U65: (外税) | X65: LINK_AMT | AC65: 0
N66: GSFD_TAX_AMT | T66: 30
N67: GSFD_SELLING_PRC | T67: 100
N68: GSFD_PLU_TAXBLTY_CD | T68: 1 | V68: ←税率変更前の税種別
L70: 【商品明細情報(内税)】 | AF70: 【税情報(内税)】
M71: 商品明細情報：商品Ｄ | W71: 取引明細のリンク情報 | AG71: 取引の税情報
M72: LN_DETAIL | W72: LN_LINK | AG72: TRANSACTION_TAX | AO72: 内税8%のレコード
N73: TRAN_ID | T73: TS/Mで採番 | X73: TRAN_ID | AC73: TS/Mで採番 | AH73: TRAN_ID | AM73: TS/Mで採番
N74: TRAN_LN_NBR | T74: 7 | X74: TRAN_LN_NBR | AC74: 7 | AH74: TRAN_LN_NBR | AM74: 8
N75: QTY | T75: 2 | X75: LINK_LN_NBR | AC75: 8 | AH75: TAX_CD | AM75: 2 | AN75: (内税8%)
N76: EXT_PRC | T76: 200 | X76: LINK_TYP | AC76: 3 | AD76: (税) | AH76: TAX_MODIF | AM76: 1
N77: GSFD_TAX_TYPE | T77: 2 | U77: (内税) | X77: LINK_AMT | AC77: 0 | AH77: TAX_AMT | AM77: 0
N78: GSFD_TAX_AMT | T78: 15 | AH78: VAT_AMT | AM78: 29
N79: GSFD_SELLING_PRC | T79: 100 | W79: 取引明細のリンク情報 | AH79: VATABL_AMT | AM79: 361
N80: GSFD_PLU_TAXBLTY_CD | T80: 99 | W80: LN_LINK | AH80: TAXBLE_AMT | AM80: 390
X81: TRAN_ID | AC81: TS/Mで採番
X82: TRAN_LN_NBR | AC82: 7
X83: LINK_LN_NBR | AC83: 8
X84: LINK_TYP | AC84: 9 | AD84: (内税額)
X85: LINK_AMT | AC85: 15
W86: ※内税額へのリンク情報
W88: 取引明細のリンク情報
W89: LN_LINK
X90: TRAN_ID | AC90: TS/Mで採番
X91: TRAN_LN_NBR | AC91: 7
X92: LINK_LN_NBR | AC92: 8
X93: LINK_TYP | AC93: 10 | AD93: (内税商品額(税抜き)
X94: LINK_AMT | AC94: 185
W95: ※内税商品額(税抜き)へのリンク情報
W97: 取引明細のリンク情報 | AI97: 取引の税情報
W98: LN_LINK | AI98: TRANSACTION_TAX | AQ98: 内税のレコード(内税合計)
X99: TRAN_ID | AC99: TS/Mで採番 | AJ99: TRAN_ID | AO99: TS/Mで採番
X100: TRAN_LN_NBR | AC100: 7 | AJ100: TRAN_LN_NBR | AO100: 9
X101: LINK_LN_NBR | AC101: 9 | AJ101: TAX_CD | AO101: 99 | AP101: (内税) | AY101: 内税の場合は、内税合計
X102: LINK_TYP | AC102: 3 | AD102: (税) | AJ102: TAX_MODIF | AO102: 1 | AY102: レコードを作成する
X103: LINK_AMT | AC103: 0 | AJ103: TAX_AMT | AO103: 0
W104: ※内税合計へのリンク情報 | AJ104: VAT_AMT | AO104: 0
AJ105: VATABL_AMT | AO105: 0
M106: 商品明細情報：商品Ｅ | W106: 取引明細のリンク情報 | AJ106: TAXBLE_AMT | AO106: 890
M107: LN_DETAIL | W107: LN_LINK
N108: TRAN_ID | T108: TS/Mで採番 | X108: TRAN_ID | AC108: TS/Mで採番
N109: TRAN_LN_NBR | T109: 10 | X109: TRAN_LN_NBR | AC109: 10
N110: QTY | T110: 2 | X110: LINK_LN_NBR | AC110: 8
N111: EXT_PRC | T111: 190 | X111: LINK_TYP | AC111: 3 | AD111: (税)
N112: GSFD_TAX_TYPE | T112: 2 | U112: (内税) | X112: LINK_AMT | AC112: 0
...

Sheet 取引ログ作成時の注意事項(支払情報)
B1: TeamStore/M POSシステム | O1: システム名 | U1: 業務名 | AB1: 取引ログ作成時の注意事項（支払情報） | AO1: 履歴 | AQ1: 改訂者 | AT1: 最新更新日 | AX1: 作成者 | BA1: 作成日 | BE1: *1.5 本ページ追加
B2: UI設計書 | O2: トラン連携対応 | U2: トラン連携対応レイアウト | AO2: ='取引ログ作成時の注意事項(税情報)'!AO2 -> 1.12 | AQ2: 富士通 | AT2: ='取引ログ作成時の注意事項(税情報)'!AT2 -> 45709 | AX2: 富士通 | BA2: 45581
C5: (1) | D5: 支払情報 (複合パターン)
D7: [売上取引]
D8: ・商品登録
E9: 明細No. | G9: 商品名 | J9: 個数 | K9: 単価 | L9: 明細内合計 | O9: 税種別 | Q9: 税率 | T9: 備考
E10: 1 | G10: 商品Ａ | J10: 30個 | K10: 100 | L10: 3000 | O10: 外税 | Q10: 0.08
D12: ・支払登録
E13: 明細No. | G13: 現外名 | J13: 枚数 | K13: 単価 | L13: 明細内合計 | N13: 現外コード | R13: 現外バーコード | V13: 備考
E14: 1 | G14: ギフト券 | J14: 1枚 | K14: 500 | L14: 500 | O14: 103 | R14: 4901231703028
E15: 2 | G15: ギフト券 | J15: 1枚 | K15: 100 | L15: 100 | O15: 103 | R15: 4991002950102
E16: 3 | G16: ご優待券 | J16: 5枚 | K16: 100 | L16: 500 | O16: 104 | R16: (無し) | V16: 値引扱い現外
E17: 4 | G17: 商品券 | J17: 2枚 | K17: 1000 | L17: 2000 | O17: 101 | R17: (無し) | V17: 支払取消(タッチ訂正) | AS17: ：ダミーレコード
D19: [レコード関連図] ※支払情報に関連する情報のみを抜粋
L21: 【商品明細】 | AF21: 【税情報】
D22: 取引情報 | M22: 商品明細情報：商品Ａ | W22: 取引明細のリンク情報 | AG22: 取引の税情報
D23: TRSNS_HEADER | M23: LN_DETAIL | W23: LN_LINK | AG23: TRANSACTION_TAX | AO23: 外税8%のレコード
E24: TRAN_ID | J24: TS/Mで採番 | N24: TRAN_ID | T24: TS/Mで採番 | X24: TRAN_ID | AC24: TS/Mで採番 | AH24: TRAN_ID | AM24: TS/Mで採番
E25: TRAN_CD | J25: 1 | N25: TRAN_LN_NBR | T25: 1 | X25: TRAN_LN_NBR | AC25: 1 | AH25: TRAN_LN_NBR | AM25: 2
N26: QTY | T26: 30 | X26: LINK_LN_NBR | AC26: 2 | AH26: TAX_CD | AM26: 1 | AN26: (外税8%)
N27: EXT_PRC | T27: 3000 | X27: LINK_TYP | AC27: 3 | AD27: (税) | AH27: TAX_MODIF | AM27: 1
N28: GSFD_TAX_TYPE | T28: 1 | U28: (外税) | X28: LINK_AMT | AC28: 0 | AH28: TAX_AMT | AM28: 240
N29: GSFD_TAX_AMT | T29: 240 | X29: LINK_QTY | AC29: 0 | AH29: VAT_AMT | AM29: 0
N30: GSFD_SELLING_PRC | T30: 100 | AH30: VATABL_AMT | AM30: 0
N31: GSFD_PLU_TAXBLTY_CD | T31: 1 | AH31: TAXBLE_AMT | AM31: 3000
L34: 【No.1 ギフト券】
M35: 取引の支払情報 | AG35: 取引の現外支払情報
M36: TRANSACTION_TENDER | AG36: GIFT_CERT_TENDER
N37: TRAN_LN_NBR | T37: 3 | AH37: TRAN_LN_NBR | AM37: 3
N38: TRAN_ID | T38: TS/Mで採番 | AH38: TRAN_ID | AM38: TS/Mで採番
N39: TND_CD | T39: 103 | W39: 取引明細のリンク情報 | AH39: GFT_CERT_AMT | AM39: -500
N40: AMT | T40: -500 | W40: LN_LINK
N41: TND_AMT | T41: -500 | X41: TRAN_ID | AC41: TS/Mで採番
N42: VOID_CD | T42: 18 | U42: (Dummy Void) | X42: TRAN_LN_NBR | AC42: 3
N43: GSFD_CHG_NON_CASH_AMT | T43: 0 | X43: LINK_LN_NBR | AC43: 4
N44: GSFD_GIFT_CERT_CNT | T44: 0 | X44: LINK_TYP | AC44: 6 | AD44: (訂正済み現外支払)
N45: GSFD_GIFT_BARCODE | T45: "" | X45: LINK_AMT | AC45: 0
X46: LINK_QTY | AC46: 0
AR47: 現外券支払を行った場合、ダミー支払レコードを作成
M48: 取引の支払情報 | AG48: 取引の現外支払情報
M49: TRANSACTION_TENDER | AG49: GIFT_CERT_TENDER
N50: TRAN_LN_NBR | T50: 4 | AH50: TRAN_LN_NBR | AM50: 4
N51: TRAN_ID | T51: TS/Mで採番 | AH51: TRAN_ID | AM51: TS/Mで採番
N52: TND_CD | T52: 103 | W52: 取引明細のリンク情報 | AH52: GFT_CERT_AMT | AM52: 500
N53: AMT | T53: 500 | W53: LN_LINK
N54: TND_AMT | T54: 500 | X54: TRAN_ID | AC54: TS/Mで採番
N55: VOID_CD | T55: 18 | U55: (Dummy Void) | X55: TRAN_LN_NBR | AC55: 4
N56: GSFD_CHG_NON_CASH_AMT | T56: 0 | X56: LINK_LN_NBR | AC56: 3
N57: GSFD_GIFT_CERT_CNT | T57: 0 | X57: LINK_TYP | AC57: 6 | AD57: (訂正済み現外支払)
N58: GSFD_GIFT_BARCODE | T58: "" | X58: LINK_AMT | AC58: 0
X59: LINK_QTY | AC59: 0
M61: 取引の支払情報 | AG61: 取引の現外支払情報
M62: TRANSACTION_TENDER | AG62: GIFT_CERT_TENDER
N63: TRAN_LN_NBR | T63: 5 | AH63: TRAN_LN_NBR | AM63: 5
N64: TRAN_ID | T64: TS/Mで採番 | AH64: TRAN_ID | AM64: TS/Mで採番
N65: TND_CD | T65: 103 | AH65: GFT_CERT_AMT | AM65: -500
N66: AMT | T66: -500
N67: TND_AMT | T67: -500
N68: VOID_CD | T68: 0
N69: GSFD_CHG_NON_CASH_AMT | T69: 0
N70: GSFD_GIFT_CERT_CNT | T70: 1
N71: GSFD_GIFT_BARCODE | T71: 4901231703028
L73: 【No.2 ギフト券】
M74: 取引の支払情報 | AG74: 取引の現外支払情報
M75: TRANSACTION_TENDER | AG75: GIFT_CERT_TENDER
N76: TRAN_LN_NBR | T76: 6 | AH76: TRAN_LN_NBR | AM76: 6
N77: TRAN_ID | T77: TS/Mで採番 | AH77: TRAN_ID | AM77: TS/Mで採番
N78: TND_CD | T78: 103 | W78: 取引明細のリンク情報 | AH78: GFT_CERT_AMT | AM78: -100
N79: AMT | T79: -100 | W79: LN_LINK
N80: TND_AMT | T80: -100 | X80: TRAN_ID | AC80: TS/Mで採番
N81: VOID_CD | T81: 18 | U81: (Dummy Void) | X81: TRAN_LN_NBR | AC81: 6
N82: GSFD_CHG_NON_CASH_AMT | T82: 0 | X82: LINK_LN_NBR | AC82: 7
N83: GSFD_GIFT_CERT_CNT | T83: 0 | X83: LINK_TYP | AC83: 6 | AD83: (訂正済み現外支払)
N84: GSFD_GIFT_BARCODE | T84: "" | X84: LINK_AMT | AC84: 0
X85: LINK_QTY | AC85: 0
AR86: 現外券支払を行った場合、ダミー支払レコードを作成
M87: 取引の支払情報 | AG87: 取引の現外支払情報
M88: TRANSACTION_TENDER | AG88: GIFT_CERT_TENDER
N89: TRAN_LN_NBR | T89: 7 | AH89: TRAN_LN_NBR | AM89: 7
N90: TRAN_ID | T90: TS/Mで採番 | AH90: TRAN_ID | AM90: TS/Mで採番
N91: TND_CD | T91: 103 | W91: 取引明細のリンク情報 | AH91: GFT_CERT_AMT | AM91: 100
N92: AMT | T92: 100 | W92: LN_LINK
N93: TND_AMT | T93: 100 | X93: TRAN_ID | AC93: TS/Mで採番
N94: VOID_CD | T94: 18 | U94: (Dummy Void) | X94: TRAN_LN_NBR | AC94: 7
N95: GSFD_CHG_NON_CASH_AMT | T95: 0 | X95: LINK_LN_NBR | AC95: 6
N96: GSFD_GIFT_CERT_CNT | T96: 0 | X96: LINK_TYP | AC96: 6 | AD96: (訂正済み現外支払)
N97: GSFD_GIFT_BARCODE | T97: "" | X97: LINK_AMT | AC97: 0
X98: LINK_QTY | AC98: 0
M100: 取引の支払情報 | AG100: 取引の現外支払情報
M101: TRANSACTION_TENDER | AG101: GIFT_CERT_TENDER
N102: TRAN_LN_NBR | T102: 8 | AH102: TRAN_LN_NBR | AM102: 8
N103: TRAN_ID | T103: TS/Mで採番 | AH103: TRAN_ID | AM103: TS/Mで採番
N104: TND_CD | T104: 103 | AH104: GFT_CERT_AMT | AM104: -100
N105: AMT | T105: -100 | AR105: 現外バーコードが異なる場合は、取引種別(TND_CD)
N106: TND_AMT | T106: -100 | AR106: が同じでも別レコードを作成
N107: VOID_CD | T107: 0
N108: GSFD_CHG_NON_CASH_AMT | T108: 0
N109: GSFD_GIFT_CERT_CNT | T109: 1
N110: GSFD_GIFT_BARCODE | T110: 4991002950102
L112: 【No.3 ご優待券】※値引扱い現外 ⇒ 取引ログは値引扱いしない現外と同様になる
...

Sheet 取引ログ作成時の注意事項(値引併用)
B1: TeamStore/M POSシステム | O1: システム名 | U1: 業務名 | AB1: 取引ログ作成時の注意事項（値引併用） | AO1: 履歴 | AQ1: 改訂者 | AT1: 最新更新日 | AX1: 作成者 | BA1: 作成日 | BE1: *1.5 本ページ追加
B2: UI設計書 | O2: トラン連携対応 | U2: トラン連携対応レイアウト | AO2: ='取引ログ作成時の注意事項(支払情報)'!AO2 -> 1.12 | AQ2: 富士通 | AT2: ='取引ログ作成時の注意事項(支払情報)'!AT2 -> 45709 | AX2: 富士通 | BA2: 45588
C5: (1) | D5: 値引併用マトリクス
B61: TeamStore/M POSシステム | O61: システム名 | U61: 業務名 | AB61: =AB$1 -> 取引ログ作成時の注意事項（値引併用） | AO61: 履歴 | AQ61: 改訂者 | AT61: 最新更新日 | AX61: 作成者 | BA61: 作成日 | BE61: *1.5 本ページ追加
B62: UI設計書 | O62: トラン連携対応 | U62: トラン連携対応レイアウト | AO62: =AO$2 -> 1.12 | AQ62: =AQ$2 -> 富士通 | AT62: =AT$2 -> 45709 | AX62: 富士通 | BA62: 45588
C65: (2) | D65: ①マークダウンと②タイムサービスと③期間特売の併用
D67: ※価格計算：①マークダウンのみ有効
D69: [売上取引 登録明細]
D70: 明細No. | F70: 大分類 | H70: 中分類 | J70: 商品名 | O70: 標準価格 | R70: 個数 | U70: 備考
D71: 1 | F71: 0102 | H71: 010200 | J71: 商品Ａ | O71: 100 | R71: 1個
J72: 値引 | O72: 設定値 | R72: 値引方法 | U72: 補足情報
J73: ①マークダウン | O73: 99 | R73: 売価
I74: 無効→ | J74: ②タイムサービス | O74: 96 | R74: 売価
I75: 無効→ | J75: ③期間特売 | O75: 95 | R75: 売価 | U75: 当日緊急登録
I76: 無効→ | J76: ③期間特売 | O76: 94 | R76: 売価
D79: [レコード関連図] ※値引情報に関連する情報のみを抜粋
AG80: 【値引情報】
D81: 取引情報 | M81: 商品明細情報：商品Ａ | W81: 取引明細のリンク情報 | AH81: 取引明細の値引情報 (①マークダウン)
D82: TRSNS_HEADER | M82: LN_DETAIL | W82: LN_LINK | AH82: LN_DISCOUNT
E83: TRAN_ID | J83: TS/Mで採番 | N83: TRAN_ID | T83: TS/Mで採番 | X83: TRAN_ID | AC83: TS/Mで採番 | AI83: TRAN_ID | AN83: TS/Mで採番
E84: TRAN_CD | J84: 1 | N84: TRAN_LN_NBR | T84: 1 | X84: TRAN_LN_NBR | AC84: 1 | AI84: TRAN_LN_NBR | AN84: 5
N85: QTY | T85: 1 | X85: LINK_LN_NBR | AC85: 5 | AI85: DISC_MTHD | AN85: 6 | AP85: ６：売価変更値引
N86: EXT_PRC | T86: 99 | X86: LINK_TYP | AC86: 1 | AD86: (値引) | AI86: DISC_AMT | AN86: 0 | AP86: 特売・タイムサービス・マークダウンの場合は\0を設定
N87: RTL_PRC | T87: 100 | X87: LINK_AMT | AC87: 0 | AI87: DISC_VALUE | AN87: 99 | AP87: マークダウン売価
N88: GSFD_SELLING_PRC | T88: 99 | X88: LINK_QTY | AC88: 0 | AI88: DISC_CLSS_ID | AN88: 91111 | AP88: 91111: マークダウン
T89: EXT_PRCは、マークダウン売価×数量 | AI89: DISC_VALUE2 | AN89: 0
T90: GSFD_SELLING_PRCは、マークダウン売価
W92: 取引明細のリンク情報 | AH92: 取引明細の値引情報 (②タイムサービス)
W93: LN_LINK | AH93: LN_DISCOUNT
X94: TRAN_ID | AC94: TS/Mで採番 | AI94: TRAN_ID | AN94: TS/Mで採番
X95: TRAN_LN_NBR | AC95: 1 | AI95: TRAN_LN_NBR | AN95: 4
X96: LINK_LN_NBR | AC96: 4 | AI96: DISC_MTHD | AN96: 6 | AP96: ６：売価変更値引
X97: LINK_TYP | AC97: 1 | AD97: (値引) | AI97: DISC_AMT | AN97: 0 | AP97: 特売・タイムサービス・マークダウンの場合は\0を設定
X98: LINK_AMT | AC98: 0 | AI98: DISC_VALUE | AN98: 96 | AP98: タイムサービス売価
X99: LINK_QTY | AC99: 0 | AI99: DISC_CLSS_ID | AN99: 91121 | AP99: 91121: タイムサービス
AI100: DISC_VALUE2 | AN100: 0
W103: 取引明細のリンク情報 | AH103: 取引明細の値引情報 (③期間特売) | AP103: ※当日緊急登録した期間特売のみ生成
W104: LN_LINK | AH104: LN_DISCOUNT
X105: TRAN_ID | AC105: TS/Mで採番 | AI105: TRAN_ID | AN105: TS/Mで採番
X106: TRAN_LN_NBR | AC106: 1 | AI106: TRAN_LN_NBR | AN106: 3
X107: LINK_LN_NBR | AC107: 3 | AI107: DISC_MTHD | AN107: 6 | AP107: ６：売価変更値引
X108: LINK_TYP | AC108: 1 | AD108: (値引) | AI108: DISC_AMT | AN108: 0 | AP108: 特売・タイムサービス・マークダウンの場合は\0を設定
X109: LINK_AMT | AC109: 0 | AI109: DISC_VALUE | AN109: 95 | AP109: 期間特売売価
X110: LINK_QTY | AC110: 0 | AI110: DISC_CLSS_ID | AN110: 91141 | AP110: 91141: 期間特売
AI111: DISC_VALUE2 | AN111: 0
B121: TeamStore/M POSシステム | O121: システム名 | U121: 業務名 | AB121: =AB$1 -> 取引ログ作成時の注意事項（値引併用） | AO121: 履歴 | AQ121: 改訂者 | AT121: 最新更新日 | AX121: 作成者 | BA121: 作成日 | BE121: *1.5 本ページ追加
B122: UI設計書 | O122: トラン連携対応 | U122: トラン連携対応レイアウト | AO122: =AO$2 -> 1.12 | AQ122: =AQ$2 -> 富士通 | AT122: =AT$2 -> 45709 | AX122: 富士通 | BA122: 45588
C125: (3) | D125: ①マークダウンと④自動値引/割引の併用
D127: ※価格計算：①マークダウンのみ有効
C129: ・ | D129: 同一自動値引/割引対象の明細が他に無い場合
D131: [売上取引 登録明細]
D132: 明細No. | F132: 大分類 | H132: 中分類 | J132: 商品名 | O132: 標準価格 | R132: 個数 | U132: 備考
D133: 1 | F133: 0103 | H133: 010300 | J133: 商品Ｂ | O133: 100 | R133: 1個
J134: 値引 | O134: 設定値 | R134: 値引方法 | U134: 補足情報
J135: ①マークダウン | O135: 93 | R135: 売価
I136: 無効→ | J136: ④自動値引/割引 | O136: 0.15 | R136: 割引 | U136: 商品階層自動値引(大分類：0103)
D139: [レコード関連図] ※値引情報に関連する情報のみを抜粋
AG140: 【値引情報】
D141: 取引情報 | M141: 商品明細情報：商品Ｂ | W141: 取引明細のリンク情報 | AH141: 取引明細の値引情報 (①マークダウン)
D142: TRSNS_HEADER | M142: LN_DETAIL | W142: LN_LINK | AH142: LN_DISCOUNT
E143: TRAN_ID | J143: TS/Mで採番 | N143: TRAN_ID | T143: TS/Mで採番 | X143: TRAN_ID | AC143: TS/Mで採番 | AI143: TRAN_ID | AN143: TS/Mで採番
E144: TRAN_CD | J144: 1 | N144: TRAN_LN_NBR | T144: 1 | X144: TRAN_LN_NBR | AC144: 1 | AI144: TRAN_LN_NBR | AN144: 3
N145: QTY | T145: 1 | X145: LINK_LN_NBR | AC145: 3 | AI145: DISC_MTHD | AN145: 6 | AP145: ６：売価変更値引
N146: EXT_PRC | T146: 93 | X146: LINK_TYP | AC146: 1 | AD146: (値引) | AI146: DISC_AMT | AN146: 0 | AP146: 特売・タイムサービス・マークダウンの場合は\0を設定
N147: RTL_PRC | T147: 100 | X147: LINK_AMT | AC147: 0 | AI147: DISC_VALUE | AN147: 93 | AP147: マークダウン売価
N148: GSFD_SELLING_PRC | T148: 93 | X148: LINK_QTY | AC148: 0 | AI148: DISC_CLSS_ID | AN148: 91111 | AP148: 91111: マークダウン
T149: EXT_PRCは、マークダウン売価×数量 | AI149: DISC_VALUE2 | AN149: 0
T150: GSFD_SELLING_PRCは、マークダウン売価
W152: 取引明細のリンク情報 | AH152: 取引明細の値引情報 (④自動値引/割引)
W153: LN_LINK | AH153: LN_DISCOUNT
X154: TRAN_ID | AC154: TS/Mで採番 | AI154: TRAN_ID | AN154: TS/Mで採番
X155: TRAN_LN_NBR | AC155: 1 | AI155: TRAN_LN_NBR | AN155: 4
X156: LINK_LN_NBR | AC156: 4 | AI156: DISC_MTHD | AN156: 2 | AP156: ２：明細％値引
X157: LINK_TYP | AC157: 1 | AD157: (値引) | AI157: DISC_AMT | AN157: 0 | AP157: 0を設定
X158: LINK_AMT | AC158: 0 | AE158: 0を設定 | AI158: DISC_VALUE | AN158: 0.15 | AP158: 自動値引/割引の割引率
X159: LINK_QTY | AC159: 0 | AE159: 0を設定 | AI159: DISC_CLSS_ID | AN159: 91326 | AP159: 91326: 部門自動
AI160: DISC_VALUE2 | AN160: 0
B181: TeamStore/M POSシステム | O181: システム名 | U181: 業務名 | AB181: =AB$1 -> 取引ログ作成時の注意事項（値引併用） | AO181: 履歴 | AQ181: 改訂者 | AT181: 最新更新日 | AX181: 作成者 | BA181: 作成日 | BE181: *1.5 本ページ追加
B182: UI設計書 | O182: トラン連携対応 | U182: トラン連携対応レイアウト | AO182: =AO$2 -> 1.12 | AQ182: =AQ$2 -> 富士通 | AT182: =AT$2 -> 45709 | AX182: 富士通 | BA182: 45588
C185: ・ | D185: 同一自動値引/割引対象の明細が他に存在する場合
D187: [売上取引 登録明細]
D188: 明細No. | F188: 大分類 | H188: 中分類 | J188: 商品名 | O188: 標準価格 | R188: 個数 | U188: 備考
D189: 1 | F189: 0103 | H189: 010300 | J189: 商品Ｂ | O189: 100 | R189: 1個
J190: 値引 | O190: 設定値 | R190: 値引方法 | U190: 補足情報
J191: ①マークダウン | O191: 93 | R191: 売価
I192: 無効→ | J192: ④自動値引/割引 | O192: 0.15 | R192: 割引 | U192: 商品階層自動値引(大分類：0103)
D193: 2 | F193: 0103 | H193: 010300 | J193: 商品Ｃ | O193: 100 | R193: 1個
J194: 値引 | O194: 設定値 | R194: 値引方法 | U194: 補足情報
J195: ④自動値引/割引 | O195: 0.15 | R195: 割引 | U195: 商品階層自動値引(大分類：0103)
D196: 3 | F196: 0103 | H196: 010300 | J196: 商品Ｄ | O196: 100 | R196: 3個
J197: 値引 | O197: 設定値 | R197: 値引方法 | U197: 補足情報
J198: ④自動値引/割引 | O198: 0.15 | R198: 割引 | U198: 商品階層自動値引(大分類：0103)
D199: 4 | F199: 0103 | H199: 010301 | J199: 商品Ｅ | O199: 100 | R199: 2個
J200: 値引 | O200: 設定値 | R200: 値引方法 | U200: 補足情報
I201: 無効→ | J201: ④自動値引/割引 | O201: 0.15 | R201: 割引 | U201: 商品階層自動値引(大分類：0103)
J202: ・自動値引/割引除外 | O202: - | R202: 除外 | U202: 商品階層自動値引除外(中分類：010301)
D203: 5 | F203: 0103 | H203: 010300 | J203: 商品Ｆ | O203: 100 | R203: 1個
J204: 値引 | O204: 設定値 | R204: 値引方法 | U204: 補足情報
I205: 無効→ | J205: ④自動値引/割引 | O205: 0.15 | R205: 割引 | U205: 商品階層自動値引(大分類：0103)
J206: ・単品自動値引除外 | O206: - | R206: 除外 | U206: 商品マスタで自動値引除外
...

Sheet TRANS_HEADER
A1: トラン連携ファイルレイアウト | C1: 対象テーブル：TRANS_HEADER 形式：TSV | P1: *1.5 「入金 中止」は、ignicaPOS側からトラン連携無し | R1: *1.5 「出金 中止」は、ignicaPOS側からトラン連携無し | T1: *1.5 「釣銭準備金 中止」は、ignicaPOS側からトラン連携無し | W1: *1.5 「中間回収 中止」は、ignicaPOS側からトラン連携無し | Z1: *1.5
A2: NO | B2: 項目 | H2: 説明 | I2: 取得元マスタ項目 | J2: 設定元 | K2: 一次開発 必須項目 | L2: ignicaPOS・Scan&Go設定値 | Y2: 備考
B3: カラム名称 | C3: 日本語名称 | D3: 型 | E3: サイズ | F3: NULL 許可 | G3: KEY | L3: 開局 | M3: 売上 | N3: 売上 中止 | O3: 入金 | P3: 入金 中止 | Q3: 出金 | R3: 出金 中止 | S3: 釣銭準備金 | T3: 釣銭準備金 中止 | U3: 釣銭補充 | V3: 中間回収 | W3: 中間回収 中止 | X3: 精算
A4: 1 | B4: GSFD_ACCOUNT_ID | C4: アカウントID | D4: varchar | E4: 9 | F4: ● | H4: アカウントID 先頭0埋めで9桁固定 | I4: - | J4: ignicaPOS | K4: 〇 | L4: 設定値：アカウントIDを設定 ignicaPOS 設定値：""(空) Scan&Go 設定値：""(空) | M4: 設定値：アカウントIDを設定 ignicaPOS 設定値：""(空) Scan&Go 設定値：アカウントID | N4: 設定値：アカウントIDを設定 ignicaPOS 設定値：""(空) Scan&Go 設定値：アカウントID | O4: 設定値：アカウントIDを設定 ignicaPOS 設定値：""(空) Scan&Go 設定値：""(空) | P4: 設定値：アカウントIDを設定 ignicaPOS 設定値：""(空) Scan&Go 設定値：""(空) | Q4: 設定値：アカウントIDを設定 ignicaPOS 設定値：""(空) Scan&Go 設定値：""(空) | R4: 設定値：アカウントIDを設定 ignicaPOS 設定値：""(空) Scan&Go 設定値：""(空) | S4: 設定値：アカウントIDを設定 ignicaPOS 設定値：""(空) Scan&Go 設定値：""(空) | T4: 設定値：アカウントIDを設定 ignicaPOS 設定値：""(空) Scan&Go 設定値：""(空) | U4: 設定値：アカウントIDを設定 ignicaPOS 設定値：""(空) Scan&Go 設定値：""(空) | V4: 設定値：アカウントIDを設定 ignicaPOS 設定値：""(空) Scan&Go 設定値：""(空) | W4: 設定値：アカウントIDを設定 ignicaPOS 設定値：""(空) Scan&Go 設定値：""(空) | X4: 設定値：アカウントIDを設定 ignicaPOS 設定値：""(空) Scan&Go 設定値：""(空) | Y4: Scan&Goの売上取引/売上中止取引のみ値を設定する
A5: =A4+1 -> 2 | B5: GSFD_JOURNAL_NO | C5: ジャーナルNo. | D5: varchar | E5: 9 | F5: ● | H5: ジャーナルNo. 先頭0埋めで9桁固定 | I5: - | J5: ignicaPOS | K5: 〇 | L5: 設定値：ジャーナルNo. ignicaPOS 設定値：""(空) Scan&Go 設定値：""(空) | M5: 設定値：ジャーナルNo. ignicaPOS 設定値：""(空) Scan&Go 設定値：ジャーナルNo. | N5: 設定値：ジャーナルNo. ignicaPOS 設定値：""(空) Scan&Go 設定値：ジャーナルNo. | O5: 設定値：ジャーナルNo. ignicaPOS 設定値：""(空) Scan&Go 設定値：""(空) | P5: 設定値：ジャーナルNo. ignicaPOS 設定値：""(空) Scan&Go 設定値：""(空) | Q5: 設定値：ジャーナルNo. ignicaPOS 設定値：""(空) Scan&Go 設定値：""(空) | R5: 設定値：ジャーナルNo. ignicaPOS 設定値：""(空) Scan&Go 設定値：""(空) | S5: 設定値：ジャーナルNo. ignicaPOS 設定値：""(空) Scan&Go 設定値：""(空) | T5: 設定値：ジャーナルNo. ignicaPOS 設定値：""(空) Scan&Go 設定値：""(空) | U5: 設定値：ジャーナルNo. ignicaPOS 設定値：""(空) Scan&Go 設定値：""(空) | V5: 設定値：ジャーナルNo. ignicaPOS 設定値：""(空) Scan&Go 設定値：""(空) | W5: 設定値：ジャーナルNo. ignicaPOS 設定値：""(空) Scan&Go 設定値：""(空) | X5: 設定値：ジャーナルNo. ignicaPOS 設定値：""(空) Scan&Go 設定値：""(空) | Y5: Scan&Goの売上取引/売上中止取引のみ値を設定する
A6: =A5+1 -> 3 | B6: TRAN_ID | C6: 取引通番 | D6: int | G6: PK | H6: 取引の識別子 | I6: - | J6: TS/M | K6: ● | L6: TSM側で設定となるため、設定不要（固定値） 設定値：""(空) | M6: TSM側で設定となるため、設定不要（固定値） 設定値：""(空) | N6: TSM側で設定となるため、設定不要（固定値） 設定値：""(空) | O6: TSM側で設定となるため、設定不要（固定値） 設定値：""(空) | P6: TSM側で設定となるため、設定不要（固定値） 設定値：""(空) | Q6: TSM側で設定となるため、設定不要（固定値） 設定値：""(空) | R6: TSM側で設定となるため、設定不要（固定値） 設定値：""(空) | S6: TSM側で設定となるため、設定不要（固定値） 設定値：""(空) | T6: TSM側で設定となるため、設定不要（固定値） 設定値：""(空) | U6: TSM側で設定となるため、設定不要（固定値） 設定値：""(空) | V6: TSM側で設定となるため、設定不要（固定値） 設定値：""(空) | W6: TSM側で設定となるため、設定不要（固定値） 設定値：""(空) | X6: TSM側で設定となるため、設定不要（固定値） 設定値：""(空)
A7: =A6+1 -> 4 | B7: RGST_TRAN_NBR | C7: レジ内取引通番 | D7: smallint | H7: レジスタ単位の取引通番 | I7: - | J7: ignicaPOS | K7: ◎ | L7: 設定値：取引通番を設定 | M7: 設定値：取引通番を設定 | N7: 設定値：取引通番を設定 | O7: 設定値：取引通番を設定 | P7: 設定値：取引通番を設定 | Q7: 設定値：取引通番を設定 | R7: 設定値：取引通番を設定 | S7: 設定値：取引通番を設定 | T7: 設定値：取引通番を設定 | U7: 設定値：取引通番を設定 | V7: 設定値：取引通番を設定 | W7: 設定値：取引通番を設定 | X7: 設定値：取引通番を設定 | Y7: POS番号単位での通し番号 (抜け/重複なし) 最大4桁(0001～9999)で、日またぎでサイクリック (日付が変わってもリセットしない) 本通番を用いて通番抜けチェックを行う ※レシート/ジャーナル印字は4桁固定(先頭0埋め)するが、トラン連携ファイルには数値として設定して先頭0埋めは不要 | Z7: *1.6
A8: =A7+1 -> 5 | B8: TRAN_CD | C8: 取引コード | D8: smallint | F8: ● | H8: 取引の種類を示します。 | I8: - | J8: ignicaPOS | K8: ◎ | L8: 設定値：31,37 開局 31：Terminal open 再開局 37：Terminal open | M8: 設定値：1 1：Item Sales | N8: 設定値：1 1：Item Sales | O8: 設定値：15 15：Payin | P8: 設定値：15 15：Payin | Q8: 設定値：16 16：PayOut | R8: 設定値：16 16：PayOut | S8: 設定値：11 11：Loan | T8: 設定値：11 11：Loan | U8: 設定値：14 14:Money Exchange | V8: 設定値：12 12：Pickup | W8: 設定値：12 12：Pickup | X8: 設定値：33 33：Terminal close
A9: =A8+1 -> 6 | B9: STR_ID | C9: 店舗番号 | D9: int | G9: PK | J9: ignicaPOS | K9: ◎ | L9: 設定値：店舗番号×10000 | M9: 設定値：店舗番号×10000 | N9: 設定値：店舗番号×10000 | O9: 設定値：店舗番号×10000 | P9: 設定値：店舗番号×10000 | Q9: 設定値：店舗番号×10000 | R9: 設定値：店舗番号×10000 | S9: 設定値：店舗番号×10000 | T9: 設定値：店舗番号×10000 | U9: 設定値：店舗番号×10000 | V9: 設定値：店舗番号×10000 | W9: 設定値：店舗番号×10000 | X9: 設定値：店舗番号×10000
A10: =A9+1 -> 7 | B10: EMP_ID | C10: 従業員コード | D10: varchar | E10: 12 | H10: 取引を入力した従業員 | I10: 担当者マスタ連携ファイル No.3 従業員コード | J10: ignicaPOS | K10: ◎ | L10: 設定値：従業員コード ignicaPOS 取引を行った従業員コード Scan&Go 集計対象とする従業員コード | M10: 設定値：従業員コード ignicaPOS ﾌﾙｾﾙﾌモードの場合 売上取引を集計対象とする従業員コード POSモードの場合 取引を行った従業員コード Scan&Go 売上取引を集計対象とする従業員コード | N10: 設定値：従業員コード ignicaPOS ﾌﾙｾﾙﾌモードの場合 売上取引を集計対象とする従業員コード POSモードの場合 取引を行った従業員コード Scan&Go 売上取引を集計対象とする従業員コード | O10: 設定値：従業員コード ignicaPOS 取引を行った従業員コード Scan&Go 集計対象とする従業員コード | P10: 設定値：従業員コード ignicaPOS 取引を行った従業員コード Scan&Go 集計対象とする従業員コード | Q10: 設定値：従業員コード ignicaPOS 取引を行った従業員コード Scan&Go 集計対象とする従業員コード | R10: 設定値：従業員コード ignicaPOS 取引を行った従業員コード Scan&Go 集計対象とする従業員コード | S10: 設定値：従業員コード ignicaPOS 取引を行った従業員コード Scan&Go 集計対象とする従業員コード | T10: 設定値：従業員コード ignicaPOS 取引を行った従業員コード Scan&Go 集計対象とする従業員コード | U10: 設定値：従業員コード ignicaPOS 取引を行った従業員コード Scan&Go 集計対象とする従業員コード | V10: 設定値：従業員コード ignicaPOS 取引を行った従業員コード Scan&Go 集計対象とする従業員コード | W10: 設定値：従業員コード ignicaPOS 取引を行った従業員コード Scan&Go 集計対象とする従業員コード | X10: 設定値：従業員コード ignicaPOS 取引を行った従業員コード Scan&Go 集計対象とする従業員コード | Z10: *1.0
A11: =A10+1 -> 8 | B11: RGST_ID | C11: レジスタID | D11: int | H11: 取引が発生したレジスタ | I11: - | J11: ignicaPOS | K11: ◎ | L11: 設定値：POS番号を設定 | M11: 設定値：POS番号を設定 | N11: 設定値：POS番号を設定 | O11: 設定値：POS番号を設定 | P11: 設定値：POS番号を設定 | Q11: 設定値：POS番号を設定 | R11: 設定値：POS番号を設定 | S11: 設定値：POS番号を設定 | T11: 設定値：POS番号を設定 | U11: 設定値：POS番号を設定 | V11: 設定値：POS番号を設定 | W11: 設定値：POS番号を設定 | X11: 設定値：POS番号を設定
A12: =A11+1 -> 9 | B12: TILL_ID | C12: ティルID | D12: varchar | E12: 12 | H12: 取引に関わるティル | I12: - | J12: TS/M | K12: ● | L12: TSM側で設定となるため、設定不要（固定値） 設定値：""(空) | M12: TSM側で設定となるため、設定不要（固定値） 設定値：""(空) | N12: TSM側で設定となるため、設定不要（固定値） 設定値：""(空) | O12: TSM側で設定となるため、設定不要（固定値） 設定値：""(空) | P12: TSM側で設定となるため、設定不要（固定値） 設定値：""(空) | Q12: TSM側で設定となるため、設定不要（固定値） 設定値：""(空) | R12: TSM側で設定となるため、設定不要（固定値） 設定値：""(空) | S12: TSM側で設定となるため、設定不要（固定値） 設定値：""(空) | T12: TSM側で設定となるため、設定不要（固定値） 設定値：""(空) | U12: TSM側で設定となるため、設定不要（固定値） 設定値：""(空) | V12: TSM側で設定となるため、設定不要（固定値） 設定値：""(空) | W12: TSM側で設定となるため、設定不要（固定値） 設定値：""(空) | X12: TSM側で設定となるため、設定不要（固定値） 設定値：""(空)
A13: =A12+1 -> 10 | B13: BUS_DT | C13: 営業日 | D13: datetime | H13: 取引が発生した営業日 | I13: - | J13: ignicaPOS | K13: ◎ | L13: 設定値：営業日を設定 9999-99-99 00:00:00.000 <例> 2021-02-04 00:00:00.000 | M13: 設定値：営業日を設定 9999-99-99 00:00:00.000 <例> 2021-02-04 00:00:00.000 | N13: 設定値：営業日を設定 9999-99-99 00:00:00.000 <例> 2021-02-04 00:00:00.000 | O13: 設定値：営業日を設定 9999-99-99 00:00:00.000 <例> 2021-02-04 00:00:00.000 | P13: 設定値：営業日を設定 9999-99-99 00:00:00.000 <例> 2021-02-04 00:00:00.000 | Q13: 設定値：営業日を設定 9999-99-99 00:00:00.000 <例> 2021-02-04 00:00:00.000 | R13: 設定値：営業日を設定 9999-99-99 00:00:00.000 <例> 2021-02-04 00:00:00.000 | S13: 設定値：営業日を設定 9999-99-99 00:00:00.000 <例> 2021-02-04 00:00:00.000 | T13: 設定値：営業日を設定 9999-99-99 00:00:00.000 <例> 2021-02-04 00:00:00.000 | U13: 設定値：営業日を設定 9999-99-99 00:00:00.000 <例> 2021-02-04 00:00:00.000 | V13: 設定値：営業日を設定 9999-99-99 00:00:00.000 <例> 2021-02-04 00:00:00.000 | W13: 設定値：営業日を設定 9999-99-99 00:00:00.000 <例> 2021-02-04 00:00:00.000 | X13: 設定値：営業日を設定 9999-99-99 00:00:00.000 <例> 2021-02-04 00:00:00.000 | Y13: 取引が発生した営業日を設定する。
A14: =A13+1 -> 11 | B14: TRAN_STRT_TS | C14: 取引開始時刻 | D14: datetime | I14: - | J14: ignicaPOS | K14: ◎ | L14: 設定値：取引開始時刻を設定 9999-99-99 99:99:99.000 <例> 2021-02-04 10:4:57.000 | M14: 設定値：取引開始時刻を設定 9999-99-99 99:99:99.000 <例> 2021-02-04 10:4:57.000 | N14: 設定値：取引開始時刻を設定 9999-99-99 99:99:99.000 <例> 2021-02-04 10:4:57.000 | O14: 設定値：取引開始時刻を設定 9999-99-99 99:99:99.000 <例> 2021-02-04 10:4:57.000 | P14: 設定値：取引開始時刻を設定 9999-99-99 99:99:99.000 <例> 2021-02-04 10:4:57.000 | Q14: 設定値：取引開始時刻を設定 9999-99-99 99:99:99.000 <例> 2021-02-04 10:4:57.000 | R14: 設定値：取引開始時刻を設定 9999-99-99 99:99:99.000 <例> 2021-02-04 10:4:57.000 | S14: 設定値：取引開始時刻を設定 9999-99-99 99:99:99.000 <例> 2021-02-04 10:4:57.000 | T14: 設定値：取引開始時刻を設定 9999-99-99 99:99:99.000 <例> 2021-02-04 10:4:57.000 | U14: 設定値：取引開始時刻を設定 9999-99-99 99:99:99.000 <例> 2021-02-04 10:4:57.000 | V14: 設定値：取引開始時刻を設定 9999-99-99 99:99:99.000 <例> 2021-02-04 10:4:57.000 | W14: 設定値：取引開始時刻を設定 9999-99-99 99:99:99.000 <例> 2021-02-04 10:4:57.000 | X14: 設定値：取引開始時刻を設定 9999-99-99 99:99:99.000 <例> 2021-02-04 10:4:57.000 | Y14: 取引開始時刻を持っていない場合は取引終了時刻を設定する。
A15: =A14+1 -> 12 | B15: TRAN_END_DTTM | C15: 取引終了時刻 | D15: datetime | F15: ● | I15: - | J15: ignicaPOS | K15: ◎ | L15: 設定値：取引終了時刻を設定 9999-99-99 99:99:99.000 <例> 2021-02-04 10:4:57.000 | M15: 設定値：取引終了時刻を設定 9999-99-99 99:99:99.000 <例> 2021-02-04 10:4:57.000 | N15: 設定値：取引終了時刻を設定 9999-99-99 99:99:99.000 <例> 2021-02-04 10:4:57.000 | O15: 設定値：取引終了時刻を設定 9999-99-99 99:99:99.000 <例> 2021-02-04 10:4:57.000 | P15: 設定値：取引終了時刻を設定 9999-99-99 99:99:99.000 <例> 2021-02-04 10:4:57.000 | Q15: 設定値：取引終了時刻を設定 9999-99-99 99:99:99.000 <例> 2021-02-04 10:4:57.000 | R15: 設定値：取引終了時刻を設定 9999-99-99 99:99:99.000 <例> 2021-02-04 10:4:57.000 | S15: 設定値：取引終了時刻を設定 9999-99-99 99:99:99.000 <例> 2021-02-04 10:4:57.000 | T15: 設定値：取引終了時刻を設定 9999-99-99 99:99:99.000 <例> 2021-02-04 10:4:57.000 | U15: 設定値：取引終了時刻を設定 9999-99-99 99:99:99.000 <例> 2021-02-04 10:4:57.000 | V15: 設定値：取引終了時刻を設定 9999-99-99 99:99:99.000 <例> 2021-02-04 10:4:57.000 | W15: 設定値：取引終了時刻を設定 9999-99-99 99:99:99.000 <例> 2021-02-04 10:4:57.000 | X15: 設定値：取引終了時刻を設定 9999-99-99 99:99:99.000 <例> 2021-02-04 10:4:57.000
A16: =A15+1 -> 13 | B16: OFFLN_FG | C16: オフライン判別 | D16: smallint | H16: オフラインフラグ | I16: - | J16: TS/M | K16: ● | L16: TSM側で設定となるため、設定不要（固定値） 設定値：""(空) | M16: TSM側で設定となるため、設定不要（固定値） 設定値：""(空) | N16: TSM側で設定となるため、設定不要（固定値） 設定値：""(空) | O16: TSM側で設定となるため、設定不要（固定値） 設定値：""(空) | P16: TSM側で設定となるため、設定不要（固定値） 設定値：""(空) | Q16: TSM側で設定となるため、設定不要（固定値） 設定値：""(空) | R16: TSM側で設定となるため、設定不要（固定値） 設定値：""(空) | S16: TSM側で設定となるため、設定不要（固定値） 設定値：""(空) | T16: TSM側で設定となるため、設定不要（固定値） 設定値：""(空) | U16: TSM側で設定となるため、設定不要（固定値） 設定値：""(空) | V16: TSM側で設定となるため、設定不要（固定値） 設定値：""(空) | W16: TSM側で設定となるため、設定不要（固定値） 設定値：""(空) | X16: TSM側で設定となるため、設定不要（固定値） 設定値：""(空)
A17: =A16+1 -> 14 | B17: TRNING_MDE_FG | C17: トレーニングモード | D17: smallint | H17: 練習モードフラグ ０：通常業務モード １：練習モード | I17: - | J17: TS/M | K17: ● | L17: TSM側で設定となるため、設定不要（固定値） 設定値：""(空) | M17: TSM側で設定となるため、設定不要（固定値） 設定値：""(空) | N17: TSM側で設定となるため、設定不要（固定値） 設定値：""(空) | O17: TSM側で設定となるため、設定不要（固定値） 設定値：""(空) | P17: TSM側で設定となるため、設定不要（固定値） 設定値：""(空) | Q17: TSM側で設定となるため、設定不要（固定値） 設定値：""(空) | R17: TSM側で設定となるため、設定不要（固定値） 設定値：""(空) | S17: TSM側で設定となるため、設定不要（固定値） 設定値：""(空) | T17: TSM側で設定となるため、設定不要（固定値） 設定値：""(空) | U17: TSM側で設定となるため、設定不要（固定値） 設定値：""(空) | V17: TSM側で設定となるため、設定不要（固定値） 設定値：""(空) | W17: TSM側で設定となるため、設定不要（固定値） 設定値：""(空) | X17: TSM側で設定となるため、設定不要（固定値） 設定値：""(空) | Y17: 練習モードは連携しない。
A18: =A17+1 -> 15 | B18: RNTRY_MDE_FG | C18: 再入力モード | D18: smallint | H18: TRUEの場合、取引が再エントリモードで記録されたことを示します。 | I18: - | J18: TS/M | K18: ● | L18: TSM側で設定となるため、設定不要（固定値） 設定値：""(空) | M18: TSM側で設定となるため、設定不要（固定値） 設定値：""(空) | N18: TSM側で設定となるため、設定不要（固定値） 設定値：""(空) | O18: TSM側で設定となるため、設定不要（固定値） 設定値：""(空) | P18: TSM側で設定となるため、設定不要（固定値） 設定値：""(空) | Q18: TSM側で設定となるため、設定不要（固定値） 設定値：""(空) | R18: TSM側で設定となるため、設定不要（固定値） 設定値：""(空) | S18: TSM側で設定となるため、設定不要（固定値） 設定値：""(空) | T18: TSM側で設定となるため、設定不要（固定値） 設定値：""(空) | U18: TSM側で設定となるため、設定不要（固定値） 設定値：""(空) | V18: TSM側で設定となるため、設定不要（固定値） 設定値：""(空) | W18: TSM側で設定となるため、設定不要（固定値） 設定値：""(空) | X18: TSM側で設定となるため、設定不要（固定値） 設定値：""(空)
A19: =A18+1 -> 16 | B19: VOID_CD | C19: 取消コード | D19: smallint | H19: 取引中止フラグ ０：通常取引 １：取引中止 | I19: - | J19: ignicaPOS | K19: ◎ | L19: 設定値：0 ０：通常取引 １：取引中止 | M19: 設定値：0 ０：通常取引 １：取引中止 | N19: 設定値：1 ０：通常取引 １：取引中止 | O19: 設定値：0 ０：通常取引 １：取引中止 | P19: 設定値：1 ０：通常取引 １：取引中止 | Q19: 設定値：0 ０：通常取引 １：取引中止 | R19: 設定値：1 ０：通常取引 １：取引中止 | S19: 設定値：0 ０：通常取引 １：取引中止 | T19: 設定値：1 ０：通常取引 １：取引中止 | U19: 設定値：0 ０：通常取引 １：取引中止 | V19: 設定値：0 ０：通常取引 １：取引中止 | W19: 設定値：1 ０：通常取引 １：取引中止 | X19: 設定値：0 ０：通常取引 １：取引中止
A20: =A19+1 -> 17 | B20: CUST_ID | C20: 顧客ID | D20: varchar | E20: 24 | F20: ● | H20: 取引に対応する顧客ＩＤを示します。 | I20: - | J20: ignicaPOS | K20: ◎ | L20: 設定値：""(空) | M20: 設定値：登録した顧客コード。プリンスポイント対象金額が存在する場合はプリンスポイント対象金額を設定 ※プリンスカードは次回開発 ※No.84 GSFD_CARD_ENTRY_TYPE=5の時はプリンスカードとして扱う 上記以外の場合は、""(空) | N20: 設定値：登録した顧客コード。プリンスポイント対象金額が存在する場合はプリンスポイント対象金額を設定 ※プリンスカードは次回開発 ※No.84 GSFD_CARD_ENTRY_TYPE=5の時はプリンスカードとして扱う 上記以外の場合は、""(空) | O20: 設定値：""(空) | P20: 設定値：""(空) | Q20: 設定値：""(空) | R20: 設定値：""(空) | S20: 設定値：""(空) | T20: 設定値：""(空) | U20: 設定値：""(空) | V20: 設定値：""(空) | W20: 設定値：""(空) | X20: 設定値：""(空)
A21: =A20+1 -> 18 | B21: SHPR_ID | C21: 買い物客ID | D21: varchar | E21: 24 | F21: ● | H21: 取引に対応する買い物客IDを示します。 | I21: - | J21: TS/M | K21: ● | L21: 設定不要(固定値) 設定値："" | M21: 設定不要(固定値) 設定値："" | N21: 設定不要(固定値) 設定値："" | O21: 設定不要(固定値) 設定値："" | P21: 設定不要(固定値) 設定値："" | Q21: 設定不要(固定値) 設定値："" | R21: 設定不要(固定値) 設定値："" | S21: 設定不要(固定値) 設定値："" | T21: 設定不要(固定値) 設定値："" | U21: 設定不要(固定値) 設定値："" | V21: 設定不要(固定値) 設定値："" | W21: 設定不要(固定値) 設定値："" | X21: 設定不要(固定値) 設定値："" | Y21: 未使用領域のため
A22: =A21+1 -> 19 | B22: STAT | C22: ステータス | D22: smallint | H22: 取引のステータス １：通常取引 ６：Ｓｕｓｐｅｎｄされた取引（保留取引） ７：ＰｏｓｔＶｏｉｄされた取引（通番打消） | I22: - | J22: TS/M | K22: ● | L22: 設定不要(固定値) 設定値："" | M22: 設定不要(固定値) 設定値："" | N22: 設定不要(固定値) 設定値："" | O22: 設定不要(固定値) 設定値："" | P22: 設定不要(固定値) 設定値："" | Q22: 設定不要(固定値) 設定値："" | R22: 設定不要(固定値) 設定値："" | S22: 設定不要(固定値) 設定値："" | T22: 設定不要(固定値) 設定値："" | U22: 設定不要(固定値) 設定値："" | V22: 設定不要(固定値) 設定値："" | W22: 設定不要(固定値) 設定値："" | X22: 設定不要(固定値) 設定値：""
A23: =A22+1 -> 20 | B23: TOT_AMT | C23: 取引合計額 | D23: money | F23: ● | H23: 取引合計額売上および入出金取引の合計金額。符号表記 （＋：売上、入金、出金打消 －：返品、打消、出金、入金打消 ） | I23: - | J23: ignicaPOS | K23: ◎ | L23: 設定値：0 | M23: 設定値：取引合計額を設定 | N23: 設定値：取引合計額を設定 | O23: 設定値：取引合計額を設定 | P23: 設定値：取引合計額を設定 | Q23: 設定値：取引合計額を設定 | R23: 設定値：取引合計額を設定 | S23: 設定値：0 | T23: 設定値：0 | U23: 設定値：0 | V23: 設定値：0 | W23: 設定値：0 | X23: 設定値：0 | Z23: *1.0
A24: =A23+1 -> 21 | B24: EMP_ID_DISC | C24: 割引購入した従業員ＩＤ | D24: varchar | E24: 12 | F24: ● | H24: 従業員ディスカウントを受ける従業員ＩＤ | I24: - | J24: TS/M | K24: ● | L24: 設定不要(固定値) 設定値：""(空) | M24: 設定不要(固定値) 設定値：""(空) | N24: 設定不要(固定値) 設定値：""(空) | O24: 設定不要(固定値) 設定値：""(空) | P24: 設定不要(固定値) 設定値：""(空) | Q24: 設定不要(固定値) 設定値：""(空) | R24: 設定不要(固定値) 設定値：""(空) | S24: 設定不要(固定値) 設定値：""(空) | T24: 設定不要(固定値) 設定値：""(空) | U24: 設定不要(固定値) 設定値：""(空) | V24: 設定不要(固定値) 設定値：""(空) | W24: 設定不要(固定値) 設定値：""(空) | X24: 設定不要(固定値) 設定値：""(空) | Y24: 未使用領域のため
A25: =A24+1 -> 22 | B25: LTILL_ID | C25: 論理ティルＩＤ | D25: varchar | E25: 12 | H25: 取引に対応する論理ティル | I25: - | J25: TS/M | K25: ● | L25: 設定不要(固定値) 設定値：""(空) | M25: 設定不要(固定値) 設定値：""(空) | N25: 設定不要(固定値) 設定値：""(空) | O25: 設定不要(固定値) 設定値：""(空) | P25: 設定不要(固定値) 設定値：""(空) | Q25: 設定不要(固定値) 設定値：""(空) | R25: 設定不要(固定値) 設定値：""(空) | S25: 設定不要(固定値) 設定値：""(空) | T25: 設定不要(固定値) 設定値：""(空) | U25: 設定不要(固定値) 設定値：""(空) | V25: 設定不要(固定値) 設定値：""(空) | W25: 設定不要(固定値) 設定値：""(空) | X25: 設定不要(固定値) 設定値：""(空)
A26: =A25+1 -> 23 | B26: REAS_CD | C26: 理由コード | D26: smallint | F26: ● | H26: 理由を記録する必要がある取引タイプの場合は、理由を示します。 | I26: - | J26: TS/M | K26: ● | L26: 設定不要(固定値) 設定値：""(空) | M26: 設定不要(固定値) 設定値：""(空) | N26: 設定不要(固定値) 設定値：""(空) | O26: 設定不要(固定値) 設定値：""(空) | P26: 設定不要(固定値) 設定値：""(空) | Q26: 設定不要(固定値) 設定値：""(空) | R26: 設定不要(固定値) 設定値：""(空) | S26: 設定不要(固定値) 設定値：""(空) | T26: 設定不要(固定値) 設定値：""(空) | U26: 設定不要(固定値) 設定値：""(空) | V26: 設定不要(固定値) 設定値：""(空) | W26: 設定不要(固定値) 設定値：""(空) | X26: 設定不要(固定値) 設定値：""(空) | Y26: 未使用領域のため
A27: =A26+1 -> 24 | B27: RAFT_RLSE | C27: RAFTリリース | D27: varchar | E27: 12 | F27: ● | H27: 取引を作成したRAFTのリリースを識別します。 | I27: - | J27: TS/M | K27: ● | L27: 設定不要(固定値) 設定値：""(空) | M27: 設定不要(固定値) 設定値：""(空) | N27: 設定不要(固定値) 設定値：""(空) | O27: 設定不要(固定値) 設定値：""(空) | P27: 設定不要(固定値) 設定値：""(空) | Q27: 設定不要(固定値) 設定値：""(空) | R27: 設定不要(固定値) 設定値：""(空) | S27: 設定不要(固定値) 設定値：""(空) | T27: 設定不要(固定値) 設定値：""(空) | U27: 設定不要(固定値) 設定値：""(空) | V27: 設定不要(固定値) 設定値：""(空) | W27: 設定不要(固定値) 設定値：""(空) | X27: 設定不要(固定値) 設定値：""(空) | Y27: 未使用領域のため
A28: =A27+1 -> 25 | B28: TRAN_GRP_ID | C28: 取引グループＩＤ | D28: int | F28: ● | H28: 取引に対応する取引グループの識別子 | I28: - | J28: TS/M | K28: ● | L28: 設定不要(固定値) 設定値：""(空) | M28: 設定不要(固定値) 設定値：""(空) | N28: 設定不要(固定値) 設定値：""(空) | O28: 設定不要(固定値) 設定値：""(空) | P28: 設定不要(固定値) 設定値：""(空) | Q28: 設定不要(固定値) 設定値：""(空) | R28: 設定不要(固定値) 設定値：""(空) | S28: 設定不要(固定値) 設定値：""(空) | T28: 設定不要(固定値) 設定値：""(空) | U28: 設定不要(固定値) 設定値：""(空) | V28: 設定不要(固定値) 設定値：""(空) | W28: 設定不要(固定値) 設定値：""(空) | X28: 設定不要(固定値) 設定値：""(空) | Y28: 未使用領域のため
A29: =A28+1 -> 26 | B29: POST_VOID_CD | C29: ポスト取消CD | D29: smallint | F29: ● | I29: - | J29: TS/M | K29: ● | L29: 設定不要(固定値) 設定値：""(空) | M29: 設定不要(固定値) 設定値：""(空) | N29: 設定不要(固定値) 設定値：""(空) | O29: 設定不要(固定値) 設定値：""(空) | P29: 設定不要(固定値) 設定値：""(空) | Q29: 設定不要(固定値) 設定値：""(空) | R29: 設定不要(固定値) 設定値：""(空) | S29: 設定不要(固定値) 設定値：""(空) | T29: 設定不要(固定値) 設定値：""(空) | U29: 設定不要(固定値) 設定値：""(空) | V29: 設定不要(固定値) 設定値：""(空) | W29: 設定不要(固定値) 設定値：""(空) | X29: 設定不要(固定値) 設定値：""(空) | Y29: 通番取消時：「1」が設定される ignicaPOS側から通番取消取引を連携しないため、設定不要
A30: =A29+1 -> 27 | B30: POST_VOID_REAS_CD | C30: ポスト取消理由CD | D30: smallint | F30: ● | I30: - | J30: TS/M | K30: ● | L30: 設定不要(固定値) 設定値：""(空) | M30: 設定不要(固定値) 設定値：""(空) | N30: 設定不要(固定値) 設定値：""(空) | O30: 設定不要(固定値) 設定値：""(空) | P30: 設定不要(固定値) 設定値：""(空) | Q30: 設定不要(固定値) 設定値：""(空) | R30: 設定不要(固定値) 設定値：""(空) | S30: 設定不要(固定値) 設定値：""(空) | T30: 設定不要(固定値) 設定値：""(空) | U30: 設定不要(固定値) 設定値：""(空) | V30: 設定不要(固定値) 設定値：""(空) | W30: 設定不要(固定値) 設定値：""(空) | X30: 設定不要(固定値) 設定値：""(空) | Y30: 通番取消時：「」が設定される ignicaPOS側から通番取消取引を連携しないため、設定不要
A31: =A30+1 -> 28 | B31: RGST_GRP_ID | C31: レジスタグループID | D31: smallint | F31: ● | I31: - | J31: TS/M | K31: ● | L31: 設定不要(固定値) 設定値：""(空) | M31: 設定不要(固定値) 設定値：""(空) | N31: 設定不要(固定値) 設定値：""(空) | O31: 設定不要(固定値) 設定値：""(空) | P31: 設定不要(固定値) 設定値：""(空) | Q31: 設定不要(固定値) 設定値：""(空) | R31: 設定不要(固定値) 設定値：""(空) | S31: 設定不要(固定値) 設定値：""(空) | T31: 設定不要(固定値) 設定値：""(空) | U31: 設定不要(固定値) 設定値：""(空) | V31: 設定不要(固定値) 設定値：""(空) | W31: 設定不要(固定値) 設定値：""(空) | X31: 設定不要(固定値) 設定値：""(空) | Y31: 未使用領域のため
A32: =A31+1 -> 29 | B32: LCL_TND_CD | C32: 現地支払CD | D32: smallint | F32: ● | I32: - | J32: TS/M | K32: ● | L32: 設定不要(固定値) 設定値：""(空) | M32: 設定不要(固定値) 設定値：""(空) | N32: 設定不要(固定値) 設定値：""(空) | O32: 設定不要(固定値) 設定値：""(空) | P32: 設定不要(固定値) 設定値：""(空) | Q32: 設定不要(固定値) 設定値：""(空) | R32: 設定不要(固定値) 設定値：""(空) | S32: 設定不要(固定値) 設定値：""(空) | T32: 設定不要(固定値) 設定値：""(空) | U32: 設定不要(固定値) 設定値：""(空) | V32: 設定不要(固定値) 設定値：""(空) | W32: 設定不要(固定値) 設定値：""(空) | X32: 設定不要(固定値) 設定値：""(空) | Y32: 未使用領域のため
A33: =A32+1 -> 30 | B33: GSFD_RCPT_TYPE | C33: 領収証発行種別 | D33: smallint | F33: ● | H33: １：領収証発行 ２：金額指定発行 | I33: - | J33: TS/M | K33: ● | L33: 設定不要(固定値) 設定値：""(空) | M33: 設定不要(固定値) 設定値：""(空) | N33: 設定不要(固定値) 設定値：""(空) | O33: 設定不要(固定値) 設定値：""(空) | P33: 設定不要(固定値) 設定値：""(空) | Q33: 設定不要(固定値) 設定値：""(空) | R33: 設定不要(固定値) 設定値：""(空) | S33: 設定不要(固定値) 設定値：""(空) | T33: 設定不要(固定値) 設定値：""(空) | U33: 設定不要(固定値) 設定値：""(空) | V33: 設定不要(固定値) 設定値：""(空) | W33: 設定不要(固定値) 設定値：""(空) | X33: 設定不要(固定値) 設定値：""(空) | Y33: 領収証取引を連携しないため、設定不要 集計もされない
A34: =A33+1 -> 31 | B34: GSFD_RCPT_INFO_ON_MEM_FG | C34: 領収証印字フラグ | D34: smallint | F34: ● | H34: 1：直前印字 | I34: - | J34: TS/M | K34: ● | L34: 設定不要(固定値) 設定値：""(空) | M34: 設定不要(固定値) 設定値：""(空) | N34: 設定不要(固定値) 設定値：""(空) | O34: 設定不要(固定値) 設定値：""(空) | P34: 設定不要(固定値) 設定値：""(空) | Q34: 設定不要(固定値) 設定値：""(空) | R34: 設定不要(固定値) 設定値：""(空) | S34: 設定不要(固定値) 設定値：""(空) | T34: 設定不要(固定値) 設定値：""(空) | U34: 設定不要(固定値) 設定値：""(空) | V34: 設定不要(固定値) 設定値：""(空) | W34: 設定不要(固定値) 設定値：""(空) | X34: 設定不要(固定値) 設定値：""(空) | Y34: 領収証取引を連携しないため、設定不要 集計もされない
A35: =A34+1 -> 32 | B35: GSFD_RCPT_RGST_TRAN_NBR | C35: 領収証発行対象取引通番 | D35: smallint | F35: ● | H35: 領収証発行対象取引通番 （通番指定時） | I35: - | J35: TS/M | K35: ● | L35: 設定不要(固定値) 設定値：""(空) | M35: 設定不要(固定値) 設定値：""(空) | N35: 設定不要(固定値) 設定値：""(空) | O35: 設定不要(固定値) 設定値：""(空) | P35: 設定不要(固定値) 設定値：""(空) | Q35: 設定不要(固定値) 設定値：""(空) | R35: 設定不要(固定値) 設定値：""(空) | S35: 設定不要(固定値) 設定値：""(空) | T35: 設定不要(固定値) 設定値：""(空) | U35: 設定不要(固定値) 設定値：""(空) | V35: 設定不要(固定値) 設定値：""(空) | W35: 設定不要(固定値) 設定値：""(空) | X35: 設定不要(固定値) 設定値：""(空) | Y35: 領収証取引を連携しないため、設定不要 集計もされない
A36: =A35+1 -> 33 | B36: GSFD_RCPT_RGST_ID | C36: 領収証発行対象ＰＯＳ通番 | D36: int | F36: ● | H36: 領収証発行対象POS番号 （通番指定時） | I36: - | J36: TS/M | K36: ● | L36: 設定不要(固定値) 設定値：""(空) | M36: 設定不要(固定値) 設定値：""(空) | N36: 設定不要(固定値) 設定値：""(空) | O36: 設定不要(固定値) 設定値：""(空) | P36: 設定不要(固定値) 設定値：""(空) | Q36: 設定不要(固定値) 設定値：""(空) | R36: 設定不要(固定値) 設定値：""(空) | S36: 設定不要(固定値) 設定値：""(空) | T36: 設定不要(固定値) 設定値：""(空) | U36: 設定不要(固定値) 設定値：""(空) | V36: 設定不要(固定値) 設定値：""(空) | W36: 設定不要(固定値) 設定値：""(空) | X36: 設定不要(固定値) 設定値：""(空) | Y36: 領収証取引を連携しないため、設定不要 集計もされない
A37: =A36+1 -> 34 | B37: GSFD_OFFCL_RCPT_AMT | C37: 領収証金額 | D37: money | F37: ● | H37: 領収書金額 | I37: - | J37: TS/M | K37: ● | L37: 設定不要(固定値) 設定値：""(空) | M37: 設定不要(固定値) 設定値：""(空) | N37: 設定不要(固定値) 設定値：""(空) | O37: 設定不要(固定値) 設定値：""(空) | P37: 設定不要(固定値) 設定値：""(空) | Q37: 設定不要(固定値) 設定値：""(空) | R37: 設定不要(固定値) 設定値：""(空) | S37: 設定不要(固定値) 設定値：""(空) | T37: 設定不要(固定値) 設定値：""(空) | U37: 設定不要(固定値) 設定値：""(空) | V37: 設定不要(固定値) 設定値：""(空) | W37: 設定不要(固定値) 設定値：""(空) | X37: 設定不要(固定値) 設定値：""(空) | Y37: 領収証取引を連携しないため、設定不要 集計もされない
A38: =A37+1 -> 35 | B38: GSFD_TRAN_TENDER_TS | C38: 小計キー押下日時 | D38: datetime | F38: ● | I38: - | J38: ignicaPOS | K38: ◎ | L38: 設定不要(固定値) 設定値： 1899-12-30 00:00:00.000 | M38: 設定値：取引終了日時を設定 9999-99-99 99:99:99.000 <例> 2021-02-04 10:45:44.000 | N38: 設定不要(固定値) 設定値： 1899-12-30 00:00:00.000 | O38: 設定不要(固定値) 設定値： 1899-12-30 00:00:00.000 | P38: 設定不要(固定値) 設定値： 1899-12-30 00:00:00.000 | Q38: 設定不要(固定値) 設定値： 1899-12-30 00:00:00.000 | R38: 設定不要(固定値) 設定値： 1899-12-30 00:00:00.000 | S38: 設定不要(固定値) 設定値： 1899-12-30 00:00:00.000 | T38: 設定不要(固定値) 設定値： 1899-12-30 00:00:00.000 | U38: 設定不要(固定値) 設定値： 1899-12-30 00:00:00.000 | V38: 設定不要(固定値) 設定値： 1899-12-30 00:00:00.000 | W38: 設定不要(固定値) 設定値： 1899-12-30 00:00:00.000 | X38: 設定不要(固定値) 設定値： 1899-12-30 00:00:00.000 | Y38: 担当者別の支払時間、登録時間の集計に使用 取引終了時刻しか持っていない場合は取引終了時刻を設定する。 | Z38: *1.9
A39: =A38+1 -> 36 | B39: GSFD_BILL_CNT | C39: 万券枚数 | D39: int | F39: ● | I39: - | J39: ignicaPOS | K39: ◎ | L39: 設定値：""(空) | M39: 設定値：取引で発生した万券枚数を設定 | N39: 設定値：取引で発生した万券枚数を設定 | O39: 設定値：取引で発生した万券枚数を設定 | P39: 設定値：取引で発生した万券枚数を設定 | Q39: 設定値：取引で発生した万券枚数を設定 | R39: 設定値：取引で発生した万券枚数を設定 | S39: 設定値：取引で発生した万券枚数を設定 | T39: 設定値：取引で発生した万券枚数を設定 | U39: 設定値：取引で発生した万券枚数を設定 | V39: 設定値：取引で発生した万券枚数を設定 | W39: 設定値：取引で発生した万券枚数を設定 | X39: 設定不要(固定値) 設定値：""(空)
A40: =A39+1 -> 37 | B40: GSFD_OFFCL_RCPT_CNT | C40: 領収証発行枚数 | D40: smallint | F40: ● | I40: - | J40: TS/M | K40: ● | L40: 設定不要(固定値) 設定値：""(空) | M40: 設定不要(固定値) 設定値：""(空) | N40: 設定不要(固定値) 設定値：""(空) | O40: 設定不要(固定値) 設定値：""(空) | P40: 設定不要(固定値) 設定値：""(空) | Q40: 設定不要(固定値) 設定値：""(空) | R40: 設定不要(固定値) 設定値：""(空) | S40: 設定不要(固定値) 設定値：""(空) | T40: 設定不要(固定値) 設定値：""(空) | U40: 設定不要(固定値) 設定値：""(空) | V40: 設定不要(固定値) 設定値：""(空) | W40: 設定不要(固定値) 設定値：""(空) | X40: 設定不要(固定値) 設定値：""(空) | Y40: ignicaPOS側から領収証取引を連携しないため、設定不要 領収証は無し
A41: =A40+1 -> 38 | B41: GSFD_SLIP_CNT | C41: 伝票発行枚数 | D41: smallint | F41: ● | I41: - | J41: TS/M | K41: ● | L41: 設定不要(固定値) 設定値：""(空) | M41: 設定不要(固定値) 設定値：""(空) | N41: 設定不要(固定値) 設定値：""(空) | O41: 設定不要(固定値) 設定値：""(空) | P41: 設定不要(固定値) 設定値：""(空) | Q41: 設定不要(固定値) 設定値：""(空) | R41: 設定不要(固定値) 設定値：""(空) | S41: 設定不要(固定値) 設定値：""(空) | T41: 設定不要(固定値) 設定値：""(空) | U41: 設定不要(固定値) 設定値：""(空) | V41: 設定不要(固定値) 設定値：""(空) | W41: 設定不要(固定値) 設定値：""(空) | X41: 設定不要(固定値) 設定値：""(空) | Y41: ignicaPOS側で掛け支払できないため、設定不要
A42: =A41+1 -> 39 | B42: GSFD_TC_COUNT | C42: 精算回数 | D42: smallint | F42: ● | H42: 「取引ログ作成時の注意事項」シートの⑥に記載 | I42: - | J42: ignicaPOS | K42: ◎ | L42: 設定値：精算回数を設定 | M42: 設定値：""(空) | N42: 設定値：""(空) | O42: 設定値：""(空) | P42: 設定値：""(空) | Q42: 設定値：""(空) | R42: 設定値：""(空) | S42: 設定値：""(空) | T42: 設定値：""(空) | U42: 設定値：""(空) | V42: 設定値：""(空) | W42: 設定値：""(空) | X42: 設定値：精算回数を設定 | Z42: *1.1
A43: =A42+1 -> 40 | B43: GSFD_TC_NUM | C43: 精算通番 | D43: smallint | F43: ● | H43: 「取引ログ作成時の注意事項」シートの⑥に記載 | I43: - | J43: ignicaPOS | K43: ◎ | L43: 設定値：精算通番を設定 | M43: 設定値：""(空) | N43: 設定値：""(空) | O43: 設定値：""(空) | P43: 設定値：""(空) | Q43: 設定値：""(空) | R43: 設定値：""(空) | S43: 設定値：""(空) | T43: 設定値：""(空) | U43: 設定値：""(空) | V43: 設定値：""(空) | W43: 設定値：""(空) | X43: 設定値：精算通番を設定 | Z43: *1.1
A44: =A43+1 -> 41 | B44: GSFD_SLIP_NUM | C44: 伝票通番 | D44: smallint | F44: ● | I44: - | J44: TS/M | K44: ● | L44: 設定不要(固定値) 設定値：""(空) | M44: 設定不要(固定値) 設定値：""(空) | N44: 設定不要(固定値) 設定値：""(空) | O44: 設定不要(固定値) 設定値：""(空) | P44: 設定不要(固定値) 設定値：""(空) | Q44: 設定不要(固定値) 設定値：""(空) | R44: 設定不要(固定値) 設定値：""(空) | S44: 設定不要(固定値) 設定値：""(空) | T44: 設定不要(固定値) 設定値：""(空) | U44: 設定不要(固定値) 設定値：""(空) | V44: 設定不要(固定値) 設定値：""(空) | W44: 設定不要(固定値) 設定値：""(空) | X44: 設定不要(固定値) 設定値：""(空) | Y44: 掛／領収証は連携しないため不要。 集計もされない
A45: =A44+1 -> 42 | B45: GSFD_FR_NUM | C45: 領収証通番 | D45: smallint | F45: ● | I45: - | J45: TS/M | K45: ● | L45: 設定不要(固定値) 設定値：""(空) | M45: 設定不要(固定値) 設定値：""(空) | N45: 設定不要(固定値) 設定値：""(空) | O45: 設定不要(固定値) 設定値：""(空) | P45: 設定不要(固定値) 設定値：""(空) | Q45: 設定不要(固定値) 設定値：""(空) | R45: 設定不要(固定値) 設定値：""(空) | S45: 設定不要(固定値) 設定値：""(空) | T45: 設定不要(固定値) 設定値：""(空) | U45: 設定不要(固定値) 設定値：""(空) | V45: 設定不要(固定値) 設定値：""(空) | W45: 設定不要(固定値) 設定値：""(空) | X45: 設定不要(固定値) 設定値：""(空) | Y45: 掛／領収証は連携しないため不要。 集計もされない
A46: =A45+1 -> 43 | B46: GSFD_CS_NUM | C46: クレジット通番 | D46: smallint | F46: ● | I46: - | J46: ignicaPOS | K46: ◎ | L46: 設定不要(固定値) 設定値：""(空) | M46: 設定値：クレジット支払があった時、クレジット通番を設定 ignicaPOS クレジット通番を設定 Scan&Go 現外券と同等の扱いとなるため、連携不要となる。 ""(空)を設定。 | N46: 設定値：クレジット支払があった時、クレジット通番を設定 ignicaPOS クレジット通番を設定 Scan&Go 現外券と同等の扱いとなるため、連携不要となる。 ""(空)を設定。 | O46: 設定不要(固定値) 設定値：""(空) | P46: 設定不要(固定値) 設定値：""(空) | Q46: 設定不要(固定値) 設定値：""(空) | R46: 設定不要(固定値) 設定値：""(空) | S46: 設定不要(固定値) 設定値：""(空) | T46: 設定不要(固定値) 設定値：""(空) | U46: 設定不要(固定値) 設定値：""(空) | V46: 設定不要(固定値) 設定値：""(空) | W46: 設定不要(固定値) 設定値：""(空) | X46: 設定不要(固定値) 設定値：""(空)
A47: =A46+1 -> 44 | B47: GSFD_REGISTER_MODE | C47: 運用モード | D47: smallint | F47: ● | H47: 0：一人制 1：一人二人制 2：二人二人制 | I47: - | J47: ignicaPOS | K47: ◎ | L47: 設定値：0固定 | M47: 設定値：0固定 | N47: 設定値：0固定 | O47: 設定値：0固定 | P47: 設定値：0固定 | Q47: 設定値：0固定 | R47: 設定値：0固定 | S47: 設定値：0固定 | T47: 設定値：0固定 | U47: 設定値：0固定 | V47: 設定値：0固定 | W47: 設定値：0固定 | X47: 設定値：0固定
A48: =A47+1 -> 45 | B48: GSFD_CHECKER_ID | C48: 二人制時のチェッカーＩＤ | D48: varchar | E48: 12 | F48: ● | I48: - | J48: TS/M | K48: ● | L48: 設定不要(固定値) 設定値：""(空) | M48: 設定不要(固定値) 設定値：""(空) | N48: 設定不要(固定値) 設定値：""(空) | O48: 設定不要(固定値) 設定値：""(空) | P48: 設定不要(固定値) 設定値：""(空) | Q48: 設定不要(固定値) 設定値：""(空) | R48: 設定不要(固定値) 設定値：""(空) | S48: 設定不要(固定値) 設定値：""(空) | T48: 設定不要(固定値) 設定値：""(空) | U48: 設定不要(固定値) 設定値：""(空) | V48: 設定不要(固定値) 設定値：""(空) | W48: 設定不要(固定値) 設定値：""(空) | X48: 設定不要(固定値) 設定値：""(空)
A49: =A48+1 -> 46 | B49: GSFD_CHECKER_STRT_TS | C49: 二人制時のチェッカー取引開始日時 | D49: datetime | F49: ● | I49: - | J49: TS/M | K49: ● | L49: TSM側で設定となるため、設定不要（固定値） 設定値：""(空) ※TS/M側で「11.TRAN_STRT_TS」の値を設定する。 | M49: TSM側で設定となるため、設定不要（固定値） 設定値：""(空) ※TS/M側で「11.TRAN_STRT_TS」の値を設定する。 | N49: TSM側で設定となるため、設定不要（固定値） 設定値：""(空) ※TS/M側で「11.TRAN_STRT_TS」の値を設定する。 | O49: TSM側で設定となるため、設定不要（固定値） 設定値：""(空) ※TS/M側で「11.TRAN_STRT_TS」の値を設定する。 | P49: TSM側で設定となるため、設定不要（固定値） 設定値：""(空) ※TS/M側で「11.TRAN_STRT_TS」の値を設定する。 | Q49: TSM側で設定となるため、設定不要（固定値） 設定値：""(空) ※TS/M側で「11.TRAN_STRT_TS」の値を設定する。 | R49: TSM側で設定となるため、設定不要（固定値） 設定値：""(空) ※TS/M側で「11.TRAN_STRT_TS」の値を設定する。 | S49: TSM側で設定となるため、設定不要（固定値） 設定値：""(空) ※TS/M側で「11.TRAN_STRT_TS」の値を設定する。 | T49: TSM側で設定となるため、設定不要（固定値） 設定値：""(空) ※TS/M側で「11.TRAN_STRT_TS」の値を設定する。 | U49: TSM側で設定となるため、設定不要（固定値） 設定値：""(空) ※TS/M側で「11.TRAN_STRT_TS」の値を設定する。 | V49: TSM側で設定となるため、設定不要（固定値） 設定値：""(空) ※TS/M側で「11.TRAN_STRT_TS」の値を設定する。 | W49: TSM側で設定となるため、設定不要（固定値） 設定値：""(空) ※TS/M側で「11.TRAN_STRT_TS」の値を設定する。 | X49: TSM側で設定となるため、設定不要（固定値） 設定値：""(空) ※TS/M側で「11.TRAN_STRT_TS」の値を設定する。 | Y49: 商品登録開始時に設定 待ち時間、商品登録時間等に集計
A50: =A49+1 -> 47 | B50: GSFD_TRAN_SUSPEND_TS | C50: 二人制時のチェッカー取引終了日時 | D50: datetime | F50: ● | I50: - | J50: TS/M | K50: ● | L50: TSM側で設定となるため、設定不要（固定値） 設定値：""(空) ※TS/M側で「11.TRAN_STRT_TS」の値を設定する。 | M50: TSM側で設定となるため、設定不要（固定値） 設定値：""(空) ※TS/M側で「11.TRAN_STRT_TS」の値を設定する。 | N50: TSM側で設定となるため、設定不要（固定値） 設定値：""(空) ※TS/M側で「11.TRAN_STRT_TS」の値を設定する。 | O50: TSM側で設定となるため、設定不要（固定値） 設定値：""(空) ※TS/M側で「11.TRAN_STRT_TS」の値を設定する。 | P50: TSM側で設定となるため、設定不要（固定値） 設定値：""(空) ※TS/M側で「11.TRAN_STRT_TS」の値を設定する。 | Q50: TSM側で設定となるため、設定不要（固定値） 設定値：""(空) ※TS/M側で「11.TRAN_STRT_TS」の値を設定する。 | R50: TSM側で設定となるため、設定不要（固定値） 設定値：""(空) ※TS/M側で「11.TRAN_STRT_TS」の値を設定する。 | S50: TSM側で設定となるため、設定不要（固定値） 設定値：""(空) ※TS/M側で「11.TRAN_STRT_TS」の値を設定する。 | T50: TSM側で設定となるため、設定不要（固定値） 設定値：""(空) ※TS/M側で「11.TRAN_STRT_TS」の値を設定する。 | U50: TSM側で設定となるため、設定不要（固定値） 設定値：""(空) ※TS/M側で「11.TRAN_STRT_TS」の値を設定する。 | V50: TSM側で設定となるため、設定不要（固定値） 設定値：""(空) ※TS/M側で「11.TRAN_STRT_TS」の値を設定する。 | W50: TSM側で設定となるため、設定不要（固定値） 設定値：""(空) ※TS/M側で「11.TRAN_STRT_TS」の値を設定する。 | X50: TSM側で設定となるため、設定不要（固定値） 設定値：""(空) ※TS/M側で「11.TRAN_STRT_TS」の値を設定する。 | Y50: 商品登録開始時に設定 待ち時間、商品登録時間等に集計
A51: =A50+1 -> 48 | B51: GSFD_TRANS_SOURCE | C51: 取引発生元情報 | D51: smallint | F51: ● | H51: ０：一人制／二人制キャッシャ側 １：二人制チェッカー側 | I51: - | J51: TS/M | K51: ● | L51: 設定不要(固定値) 設定値：""(空) | M51: 設定不要(固定値) 設定値：""(空) | N51: 設定不要(固定値) 設定値：""(空) | O51: 設定不要(固定値) 設定値：""(空) | P51: 設定不要(固定値) 設定値：""(空) | Q51: 設定不要(固定値) 設定値：""(空) | R51: 設定不要(固定値) 設定値：""(空) | S51: 設定不要(固定値) 設定値：""(空) | T51: 設定不要(固定値) 設定値：""(空) | U51: 設定不要(固定値) 設定値：""(空) | V51: 設定不要(固定値) 設定値：""(空) | W51: 設定不要(固定値) 設定値：""(空) | X51: 設定不要(固定値) 設定値：""(空)
A52: =A51+1 -> 49 | B52: GSFD_NONCASH_QTY | C52: GSFDNONCASH数量 | D52: int | F52: ● | I52: - | J52: TS/M | K52: ● | L52: 設定不要(固定値) 設定値：""(空) | M52: 設定不要(固定値) 設定値：""(空) | N52: 設定不要(固定値) 設定値：""(空) | O52: 設定不要(固定値) 設定値：""(空) | P52: 設定不要(固定値) 設定値：""(空) | Q52: 設定不要(固定値) 設定値：""(空) | R52: 設定不要(固定値) 設定値：""(空) | S52: 設定不要(固定値) 設定値：""(空) | T52: 設定不要(固定値) 設定値：""(空) | U52: 設定不要(固定値) 設定値：""(空) | V52: 設定不要(固定値) 設定値：""(空) | W52: 設定不要(固定値) 設定値：""(空) | X52: 設定不要(固定値) 設定値：""(空) | Y52: 未使用領域のため
A53: =A52+1 -> 50 | B53: GSFD_NEW_PNT | C53: 今回ポイント | D53: int | F53: ● | I53: 今回ポイント = 基本ポイント対象ポイント(No.151 GSFD_ING_POINT02) + 特別ポイント対象ポイント(No.150 GSFD_ING_POINT01) + ポイントプラス計(No.78.GSFD_FSP_PNT) + クーポンポイント(No.224 GSFD_CATALINA_POINT) | J53: ignicaPOS | K53: ◎ | L53: 設定値：0固定 | M53: 設定値：今回ポイント | N53: 設定値：""(空) | O53: 設定値：0固定 | P53: 設定値：0固定 | Q53: 設定値：0固定 | R53: 設定値：0固定 | S53: 設定値：0固定 | T53: 設定値：0固定 | U53: 設定値：0固定 | V53: 設定値：0固定 | W53: 設定値：0固定 | X53: 設定値：0固定 | Z53: *1.9
A54: =A53+1 -> 51 | B54: GSFD_LAST_PNT | C54: 旧累計ポイント | D54: int | F54: ● | I54: Satisfaの応答値を使用。 残高ポイント1 | J54: ignicaPOS | K54: ◎ | L54: 設定値：0固定 | M54: 設定値：残高ポイント1 | N54: 設定値：残高ポイント1 | O54: 設定値：0固定 | P54: 設定値：0固定 | Q54: 設定値：0固定 | R54: 設定値：0固定 | S54: 設定値：0固定 | T54: 設定値：0固定 | U54: 設定値：0固定 | V54: 設定値：0固定 | W54: 設定値：0固定 | X54: 設定値：0固定 | Y54: TSM参考 GetCustomerByNumberASY呼び出しで連携。残高ポイント1<POINT_QT1>
A55: =A54+1 -> 52 | B55: GSFD_REDUCT_PNT | C55: 還元ポイント | D55: int | F55: ● | I55: - | J55: TS/M | K55: ● | L55: 設定不要(固定値) 設定値：""(空) | M55: 設定不要(固定値) 設定値：""(空) | N55: 設定不要(固定値) 設定値：""(空) | O55: 設定不要(固定値) 設定値：""(空) | P55: 設定不要(固定値) 設定値：""(空) | Q55: 設定不要(固定値) 設定値：""(空) | R55: 設定不要(固定値) 設定値：""(空) | S55: 設定不要(固定値) 設定値：""(空) | T55: 設定不要(固定値) 設定値：""(空) | U55: 設定不要(固定値) 設定値：""(空) | V55: 設定不要(固定値) 設定値：""(空) | W55: 設定不要(固定値) 設定値：""(空) | X55: 設定不要(固定値) 設定値：""(空)
A56: =A55+1 -> 53 | B56: GSFD_FULLPNT_CNT | C56: 満点回数 | D56: int | F56: ● | I56: - | J56: TS/M | K56: ● | L56: 設定不要(固定値) 設定値：""(空) | M56: 設定不要(固定値) 設定値：""(空) | N56: 設定不要(固定値) 設定値：""(空) | O56: 設定不要(固定値) 設定値：""(空) | P56: 設定不要(固定値) 設定値：""(空) | Q56: 設定不要(固定値) 設定値：""(空) | R56: 設定不要(固定値) 設定値：""(空) | S56: 設定不要(固定値) 設定値：""(空) | T56: 設定不要(固定値) 設定値：""(空) | U56: 設定不要(固定値) 設定値：""(空) | V56: 設定不要(固定値) 設定値：""(空) | W56: 設定不要(固定値) 設定値：""(空) | X56: 設定不要(固定値) 設定値：""(空)
A57: =A56+1 -> 54 | B57: GSFD_PNT_AMT | C57: ポイント対象金額 | D57: money | F57: ● | I57: Satisfaの応答値を使用。 基本ポイント対象金額 | J57: ignicaPOS | K57: ◎ | L57: 設定値：0固定 | M57: 設定値：基本ポイント対象金額 | N57: 設定値：""(空) | O57: 設定値：0固定 | P57: 設定値：0固定 | Q57: 設定値：0固定 | R57: 設定値：0固定 | S57: 設定値：0固定 | T57: 設定値：0固定 | U57: 設定値：0固定 | V57: 設定値：0固定 | W57: 設定値：0固定 | X57: 設定値：0固定 | Y57: TSMでは下記を設定 GetCustomerByNumberASY呼び出しで連携。 通常ポイント対象金額<DEFAULTPT_VAL> | Z57: *1.0,1.9
A58: =A57+1 -> 55 | B58: GSFD_REDUCT_AMT | C58: 還元金額 | D58: money | F58: ● | I58: - | J58: TS/M | K58: ● | L58: 設定不要(固定値) 設定値：""(空) | M58: 設定不要(固定値) 設定値：""(空) | N58: 設定不要(固定値) 設定値：""(空) | O58: 設定不要(固定値) 設定値：""(空) | P58: 設定不要(固定値) 設定値：""(空) | Q58: 設定不要(固定値) 設定値：""(空) | R58: 設定不要(固定値) 設定値：""(空) | S58: 設定不要(固定値) 設定値：""(空) | T58: 設定不要(固定値) 設定値：""(空) | U58: 設定不要(固定値) 設定値：""(空) | V58: 設定不要(固定値) 設定値：""(空) | W58: 設定不要(固定値) 設定値：""(空) | X58: 設定不要(固定値) 設定値：""(空)
A59: =A58+1 -> 56 | B59: GSFD_REDUCT_TYP | C59: ポイント還元種別 | D59: smallint | F59: ● | H59: ポイント還元種別 （ 0：ポイント還元なし／ 1：満点処理／10：割戻（値引き）／20：割戻（支払い）／4：マニュアル割戻／5：ポイント強制修正） | I59: - | J59: TS/M | K59: ● | L59: 設定不要(固定値) 設定値：""(空) | M59: 設定不要(固定値) 設定値：""(空) | N59: 設定不要(固定値) 設定値：""(空) | O59: 設定不要(固定値) 設定値：""(空) | P59: 設定不要(固定値) 設定値：""(空) | Q59: 設定不要(固定値) 設定値：""(空) | R59: 設定不要(固定値) 設定値：""(空) | S59: 設定不要(固定値) 設定値：""(空) | T59: 設定不要(固定値) 設定値：""(空) | U59: 設定不要(固定値) 設定値：""(空) | V59: 設定不要(固定値) 設定値：""(空) | W59: 設定不要(固定値) 設定値：""(空) | X59: 設定不要(固定値) 設定値：""(空)
A60: =A59+1 -> 57 | B60: GSFD_PNT_HT_FG | C60: ポイント修正時ＨＴ集計フラグ | D60: smallint | F60: ● | H60: ポイント修正時ＨＴ集計フラグ （0：行わない／1：行う） | I60: - | J60: TS/M | K60: ● | L60: 設定不要(固定値) 設定値：""(空) | M60: 設定不要(固定値) 設定値：""(空) | N60: 設定不要(固定値) 設定値：""(空) | O60: 設定不要(固定値) 設定値：""(空) | P60: 設定不要(固定値) 設定値：""(空) | Q60: 設定不要(固定値) 設定値：""(空) | R60: 設定不要(固定値) 設定値：""(空) | S60: 設定不要(固定値) 設定値：""(空) | T60: 設定不要(固定値) 設定値：""(空) | U60: 設定不要(固定値) 設定値：""(空) | V60: 設定不要(固定値) 設定値：""(空) | W60: 設定不要(固定値) 設定値：""(空) | X60: 設定不要(固定値) 設定値：""(空)
A61: =A60+1 -> 58 | B61: GSFD_PNT_RCPT_FG | C61: ポイントレシート印字フラグ | D61: smallint | F61: ● | H61: ポイントレシート印字フラグ （0：印字しない／1：印字する） | I61: - | J61: TS/M | K61: ● | L61: 設定不要(固定値) 設定値：""(空) | M61: 設定不要(固定値) 設定値：""(空) | N61: 設定不要(固定値) 設定値：""(空) | O61: 設定不要(固定値) 設定値：""(空) | P61: 設定不要(固定値) 設定値：""(空) | Q61: 設定不要(固定値) 設定値：""(空) | R61: 設定不要(固定値) 設定値：""(空) | S61: 設定不要(固定値) 設定値：""(空) | T61: 設定不要(固定値) 設定値：""(空) | U61: 設定不要(固定値) 設定値：""(空) | V61: 設定不要(固定値) 設定値：""(空) | W61: 設定不要(固定値) 設定値：""(空) | X61: 設定不要(固定値) 設定値：""(空)
A62: =A61+1 -> 59 | B62: GSFD_FULLPNT_RCPT_FG | C62: 満点券印字フラグ | D62: smallint | F62: ● | H62: 満点券印字フラグ （0：印字しない／1：印字する） | I62: - | J62: TS/M | K62: ● | L62: 設定不要(固定値) 設定値：""(空) | M62: 設定不要(固定値) 設定値：""(空) | N62: 設定不要(固定値) 設定値：""(空) | O62: 設定不要(固定値) 設定値：""(空) | P62: 設定不要(固定値) 設定値：""(空) | Q62: 設定不要(固定値) 設定値：""(空) | R62: 設定不要(固定値) 設定値：""(空) | S62: 設定不要(固定値) 設定値：""(空) | T62: 設定不要(固定値) 設定値：""(空) | U62: 設定不要(固定値) 設定値：""(空) | V62: 設定不要(固定値) 設定値：""(空) | W62: 設定不要(固定値) 設定値：""(空) | X62: 設定不要(固定値) 設定値：""(空)
A63: =A62+1 -> 60 | B63: GSFD_BIRTH_MSG_FG | C63: 誕生日メッセージ印字フラグ | D63: smallint | F63: ● | H63: 誕生日メッセージ印字フラグ （0：印字しない／1：印字する） | I63: - | J63: TS/M | K63: ● | L63: 設定不要(固定値) 設定値：""(空) | M63: 設定不要(固定値) 設定値：""(空) | N63: 設定不要(固定値) 設定値：""(空) | O63: 設定不要(固定値) 設定値：""(空) | P63: 設定不要(固定値) 設定値：""(空) | Q63: 設定不要(固定値) 設定値：""(空) | R63: 設定不要(固定値) 設定値：""(空) | S63: 設定不要(固定値) 設定値：""(空) | T63: 設定不要(固定値) 設定値：""(空) | U63: 設定不要(固定値) 設定値：""(空) | V63: 設定不要(固定値) 設定値：""(空) | W63: 設定不要(固定値) 設定値：""(空) | X63: 設定不要(固定値) 設定値：""(空)
A64: =A63+1 -> 61 | B64: GSFD_NO_CUST_FG | C64: 会員コードマスタ未登録フラグ | D64: smallint | F64: ● | H64: 会員コードマスタ未登録フラグ （0：通常、1：他店舗会員、2：マスタ未登録、3：使用不可カード） | I64: - | J64: ignicaPOS | K64: ◎ | L64: 設定値：0固定 | M64: 設定値：0固定 | N64: 設定値：0固定 | O64: 設定値：0固定 | P64: 設定値：0固定 | Q64: 設定値：0固定 | R64: 設定値：0固定 | S64: 設定値：0固定 | T64: 設定値：0固定 | U64: 設定値：0固定 | V64: 設定値：0固定 | W64: 設定値：0固定 | X64: 設定値：0固定 | Z64: *1.1
A65: =A64+1 -> 62 | B65: GSFD_OFFLINE_FG | C65: オフラインフラグ | D65: smallint | F65: ● | H65: オフラインフラグ （0：通常／ 1：オフライン／ 2：リライタ未接続／ 3：カード書込異常） | I65: Satisfa連携でｵﾌﾗｲﾝが発生した時に1を設定。 | J65: ignicaPOS | K65: ◎ | L65: 設定値：0固定 | M65: 設定値：0 or 1 顧客登録あり時 0:オンライン、1:オフライン 顧客登録なし時 0 | N65: 設定値：0 or 1 顧客登録あり時 0:オンライン、1:オフライン 顧客登録なし時 0 | O65: 設定値：0固定 | P65: 設定値：0固定 | Q65: 設定値：0固定 | R65: 設定値：0固定 | S65: 設定値：0固定 | T65: 設定値：0固定 | U65: 設定値：0固定 | V65: 設定値：0固定 | W65: 設定値：0固定 | X65: 設定値：0固定 | Y65: TSM参考 ignicaPOS側でポイントINQオフラインフラグを設定 GetCustomerByNumberASY呼び出しで"4903"または"4904"が返却された時に１を設定。
A66: =A65+1 -> 63 | B66: GSFD_CUST_RANK | C66: 顧客ランク／カード種別 | D66: char | E66: 1 | F66: ● | I66: - | J66: TS/M | K66: ● | L66: 設定不要(固定値) 設定値：""(空) | M66: 設定値：""(空) | N66: 設定値：""(空) | O66: 設定不要(固定値) 設定値：""(空) | P66: 設定不要(固定値) 設定値：""(空) | Q66: 設定不要(固定値) 設定値：""(空) | R66: 設定不要(固定値) 設定値：""(空) | S66: 設定不要(固定値) 設定値：""(空) | T66: 設定不要(固定値) 設定値：""(空) | U66: 設定不要(固定値) 設定値：""(空) | V66: 設定不要(固定値) 設定値：""(空) | W66: 設定不要(固定値) 設定値：""(空) | X66: 設定不要(固定値) 設定値：""(空) | Y66: 顧客ランク未使用のため。
A67: =A66+1 -> 64 | B67: GSFD_CARD_DATA | C67: ポイントカード情報 | D67: char | E67: 69 | F67: ● | H67: ポイントカード情報 PC版でのみ出力する。（書込後の情報） 通常売上 ： 出力あり 返品 ： 出力あり 取消 ： 出力あり 返品取消 ： 出力あり 通番取消 ： 出力なし | I67: - | J67: TS/M | K67: ● | L67: 設定不要(固定値) 設定値：""(空) | M67: 設定不要(固定値) 設定値：""(空) | N67: 設定不要(固定値) 設定値：""(空) | O67: 設定不要(固定値) 設定値：""(空) | P67: 設定不要(固定値) 設定値：""(空) | Q67: 設定不要(固定値) 設定値：""(空) | R67: 設定不要(固定値) 設定値：""(空) | S67: 設定不要(固定値) 設定値：""(空) | T67: 設定不要(固定値) 設定値：""(空) | U67: 設定不要(固定値) 設定値：""(空) | V67: 設定不要(固定値) 設定値：""(空) | W67: 設定不要(固定値) 設定値：""(空) | X67: 設定不要(固定値) 設定値：""(空)
A68: =A67+1 -> 65 | B68: GSFD_DEMOGRAPHIC_CODE | C68: 客層コード | D68: smallint | F68: ● | H68: 客層コード。客層登録なし時は"0"が入る。 | I68: - | J68: TS/M | K68: ● | L68: 設定不要(固定値) 設定値：""(空) | M68: 設定不要(固定値) 設定値：""(空) | N68: 設定不要(固定値) 設定値：""(空) | O68: 設定不要(固定値) 設定値：""(空) | P68: 設定不要(固定値) 設定値：""(空) | Q68: 設定不要(固定値) 設定値：""(空) | R68: 設定不要(固定値) 設定値：""(空) | S68: 設定不要(固定値) 設定値：""(空) | T68: 設定不要(固定値) 設定値：""(空) | U68: 設定不要(固定値) 設定値：""(空) | V68: 設定不要(固定値) 設定値：""(空) | W68: 設定不要(固定値) 設定値：""(空) | X68: 設定不要(固定値) 設定値：""(空) | Y68: 客層コードは釣銭増資時に設定 ignicaPOS側で釣銭増資はしない認識のため、設定不要
A69: =A68+1 -> 66 | B69: GSFD_STAMP_DUTY | C69: 収入印紙税金額 | D69: money | F69: ● | I69: - | J69: ignicaPOS | K69: ◎ | L69: 設定値：0固定 | M69: 設定値：収入印紙税金額を設定 99999 <例>00.0000 | N69: 設定値：0固定 | O69: 設定値：0固定 | P69: 設定値：0固定 | Q69: 設定値：0固定 | R69: 設定値：0固定 | S69: 設定値：0固定 | T69: 設定値：0固定 | U69: 設定値：0固定 | V69: 設定値：0固定 | W69: 設定値：0固定 | X69: 設定値：0固定
A70: =A69+1 -> 67 | B70: GSFD_RCPT_ISSUED | C70: 領収証発行済フラグ | D70: smallint | F70: ● | I70: - | J70: TS/M | K70: ● | L70: 設定不要(固定値) 設定値：""(空) | M70: 設定不要(固定値) 設定値：""(空) | N70: 設定不要(固定値) 設定値：""(空) | O70: 設定不要(固定値) 設定値：""(空) | P70: 設定不要(固定値) 設定値：""(空) | Q70: 設定不要(固定値) 設定値：""(空) | R70: 設定不要(固定値) 設定値：""(空) | S70: 設定不要(固定値) 設定値：""(空) | T70: 設定不要(固定値) 設定値：""(空) | U70: 設定不要(固定値) 設定値：""(空) | V70: 設定不要(固定値) 設定値：""(空) | W70: 設定不要(固定値) 設定値：""(空) | X70: 設定不要(固定値) 設定値：""(空) | Y70: 未使用領域のため。 設定箇所なし
A71: =A70+1 -> 68 | B71: GSFD_DP_DOC_ID | C71: 承り伝票番号 | D71: char | E71: 24 | F71: ● | H71: 承り伝票番号 11桁固定 左詰め余りｽﾍﾟｰｽ | I71: - | J71: TS/M | K71: ● | L71: 設定不要(固定値) 設定値：""(空) | M71: 設定不要(固定値) 設定値：""(空) | N71: 設定不要(固定値) 設定値：""(空) | O71: 設定不要(固定値) 設定値：""(空) | P71: 設定不要(固定値) 設定値：""(空) | Q71: 設定不要(固定値) 設定値：""(空) | R71: 設定不要(固定値) 設定値：""(空) | S71: 設定不要(固定値) 設定値：""(空) | T71: 設定不要(固定値) 設定値：""(空) | U71: 設定不要(固定値) 設定値：""(空) | V71: 設定不要(固定値) 設定値：""(空) | W71: 設定不要(固定値) 設定値：""(空) | X71: 設定不要(固定値) 設定値：""(空) | Y71: 未使用領域のため。 設定箇所なし
A72: =A71+1 -> 69 | B72: GSFD_DFRDUP_TOTAL | C72: GSFDDERDUPトータル | D72: smallint | F72: ● | I72: - | J72: TS/M | K72: ● | L72: 設定不要(固定値) 設定値：""(空) | M72: 設定不要(固定値) 設定値：""(空) | N72: 設定不要(固定値) 設定値：""(空) | O72: 設定不要(固定値) 設定値：""(空) | P72: 設定不要(固定値) 設定値：""(空) | Q72: 設定不要(固定値) 設定値：""(空) | R72: 設定不要(固定値) 設定値：""(空) | S72: 設定不要(固定値) 設定値：""(空) | T72: 設定不要(固定値) 設定値：""(空) | U72: 設定不要(固定値) 設定値：""(空) | V72: 設定不要(固定値) 設定値：""(空) | W72: 設定不要(固定値) 設定値：""(空) | X72: 設定不要(固定値) 設定値：""(空)
A73: =A72+1 -> 70 | B73: GSFD_HAS_TOTAL_FG | C73: GSFDHASトータルフラグ | D73: smallint | F73: ● | I73: - | J73: TS/M | K73: ● | L73: 設定不要(固定値) 設定値：""(空) | M73: 設定不要(固定値) 設定値：""(空) | N73: 設定不要(固定値) 設定値：""(空) | O73: 設定不要(固定値) 設定値：""(空) | P73: 設定不要(固定値) 設定値：""(空) | Q73: 設定不要(固定値) 設定値：""(空) | R73: 設定不要(固定値) 設定値：""(空) | S73: 設定不要(固定値) 設定値：""(空) | T73: 設定不要(固定値) 設定値：""(空) | U73: 設定不要(固定値) 設定値：""(空) | V73: 設定不要(固定値) 設定値：""(空) | W73: 設定不要(固定値) 設定値：""(空) | X73: 設定不要(固定値) 設定値：""(空)
A74: =A73+1 -> 71 | B74: GSFD_PICKUP_FG | C74: GSFDピックアップフラグ | D74: smallint | F74: ● | I74: - | J74: TS/M | K74: ● | L74: 設定不要(固定値) 設定値：""(空) | M74: 設定不要(固定値) 設定値：""(空) | N74: 設定不要(固定値) 設定値：""(空) | O74: 設定不要(固定値) 設定値：""(空) | P74: 設定不要(固定値) 設定値：""(空) | Q74: 設定不要(固定値) 設定値：""(空) | R74: 設定不要(固定値) 設定値：""(空) | S74: 設定不要(固定値) 設定値：""(空) | T74: 設定不要(固定値) 設定値：""(空) | U74: 設定不要(固定値) 設定値：""(空) | V74: 設定不要(固定値) 設定値：""(空) | W74: 設定不要(固定値) 設定値：""(空) | X74: 設定不要(固定値) 設定値：""(空)
A75: =A74+1 -> 72 | B75: GSFD_POSTVOID_FLAG | C75: GSFDPOSTVOIDフラグ | D75: smallint | F75: ● | I75: - | J75: TS/M | K75: ● | L75: 設定不要(固定値) 設定値：""(空) | M75: 設定不要(固定値) 設定値：""(空) | N75: 設定不要(固定値) 設定値：""(空) | O75: 設定不要(固定値) 設定値：""(空) | P75: 設定不要(固定値) 設定値：""(空) | Q75: 設定不要(固定値) 設定値：""(空) | R75: 設定不要(固定値) 設定値：""(空) | S75: 設定不要(固定値) 設定値：""(空) | T75: 設定不要(固定値) 設定値：""(空) | U75: 設定不要(固定値) 設定値：""(空) | V75: 設定不要(固定値) 設定値：""(空) | W75: 設定不要(固定値) 設定値：""(空) | X75: 設定不要(固定値) 設定値：""(空)
A76: =A75+1 -> 73 | B76: GSFD_CARD_LOG_DATA | C76: GSFDカードログデータ | D76: text | F76: ● | H76: クレジット明細データを格納する | I76: - | J76: ignicaPOS | K76: ◎ | L76: 設定値：""(空) | M76: 設定値：クレジット支払があった時、ログデータを設定 ignicaPOS 設定値：「UI-0 トラン連携対応 方式設計 UI設計書」の「9-4.クレジット取引ログインタフェースレイアウト」を参照。 Scan&Go 現外券と同等の扱いとなるため、連携不要となる。 ""(空)を設定。 | N76: 設定値：クレジット支払があった時、クレジット通番を設定 ignicaPOS 設定値：「UI-0 トラン連携対応 方式設計 UI設計書」の「9-4.クレジット取引ログインタフェースレイアウト」を参照。 Scan&Go 現外券と同等の扱いとなるため、連携不要となる。 ""(空)を設定。 | O76: 設定値：""(空) | P76: 設定値：""(空) | Q76: 設定値：""(空) | R76: 設定値：""(空) | S76: 設定値：""(空) | T76: 設定値：""(空) | U76: 設定値：""(空) | V76: 設定値：""(空) | W76: 設定値：""(空) | X76: 設定値：""(空)
A77: =A76+1 -> 74 | B77: GSFD_ADD_PNT | C77: 誕生日ポイント | D77: int | F77: ● | I77: - | J77: TS/M | K77: ● | L77: 設定不要(固定値) 設定値：""(空) | M77: 設定不要(固定値) 設定値：""(空) | N77: 設定不要(固定値) 設定値：""(空) | O77: 設定不要(固定値) 設定値：""(空) | P77: 設定不要(固定値) 設定値：""(空) | Q77: 設定不要(固定値) 設定値：""(空) | R77: 設定不要(固定値) 設定値：""(空) | S77: 設定不要(固定値) 設定値：""(空) | T77: 設定不要(固定値) 設定値：""(空) | U77: 設定不要(固定値) 設定値：""(空) | V77: 設定不要(固定値) 設定値：""(空) | W77: 設定不要(固定値) 設定値：""(空) | X77: 設定不要(固定値) 設定値：""(空)
A78: =A77+1 -> 75 | B78: GSFD_FSP_TCKT_FG | C78: GSFD_FSPチェットフラグ | D78: smallint | F78: ● | I78: - | J78: TS/M | K78: ● | L78: 設定不要(固定値) 設定値：""(空) | M78: 設定不要(固定値) 設定値：""(空) | N78: 設定不要(固定値) 設定値：""(空) | O78: 設定不要(固定値) 設定値：""(空) | P78: 設定不要(固定値) 設定値：""(空) | Q78: 設定不要(固定値) 設定値：""(空) | R78: 設定不要(固定値) 設定値：""(空) | S78: 設定不要(固定値) 設定値：""(空) | T78: 設定不要(固定値) 設定値：""(空) | U78: 設定不要(固定値) 設定値：""(空) | V78: 設定不要(固定値) 設定値：""(空) | W78: 設定不要(固定値) 設定値：""(空) | X78: 設定不要(固定値) 設定値：""(空) | Y78: 未使用領域の認識
A79: =A78+1 -> 76 | B79: GSFD_TRAN_CD_DETAIL | C79: 取引種別の詳細コード | D79: smallint | F79: ● | I79: - | J79: TS/M | K79: ● | L79: 設定不要(固定値) 設定値：""(空) | M79: 設定不要(固定値) 設定値：""(空) | N79: 設定不要(固定値) 設定値：""(空) | O79: 設定不要(固定値) 設定値：""(空) | P79: 設定不要(固定値) 設定値：""(空) | Q79: 設定不要(固定値) 設定値：""(空) | R79: 設定不要(固定値) 設定値：""(空) | S79: 設定不要(固定値) 設定値：""(空) | T79: 設定不要(固定値) 設定値：""(空) | U79: 設定不要(固定値) 設定値：""(空) | V79: 設定不要(固定値) 設定値：""(空) | W79: 設定不要(固定値) 設定値：""(空) | X79: 設定不要(固定値) 設定値：""(空) | Y79: 通番取消取引の時にしか設定していないため、設定不要
A80: =A79+1 -> 77 | B80: GSFD_CUSTOMIZE_DATA | C80: カスタマイズデータ | D80: char | E80: 240 | F80: ● | I80: - | J80: TS/M | K80: ● | L80: 設定不要(固定値) 設定値：""(空) | M80: 設定不要(固定値) 設定値：""(空) | N80: 設定不要(固定値) 設定値：""(空) | O80: 設定不要(固定値) 設定値：""(空) | P80: 設定不要(固定値) 設定値：""(空) | Q80: 設定不要(固定値) 設定値：""(空) | R80: 設定不要(固定値) 設定値：""(空) | S80: 設定不要(固定値) 設定値：""(空) | T80: 設定不要(固定値) 設定値：""(空) | U80: 設定不要(固定値) 設定値：""(空) | V80: 設定不要(固定値) 設定値：""(空) | W80: 設定不要(固定値) 設定値：""(空) | X80: 設定不要(固定値) 設定値：""(空)
A81: =A80+1 -> 78 | B81: GSFD_FSP_PNT | C81: FSP単品付与ポイント合計値 | D81: int | F81: ● | I81: Satisfaの応答値を使用。 合計ポイントプラス数 | J81: ignicaPOS | K81: 〇 | L81: 設定値：0固定 | M81: 設定値：合計ポイントプラス数を設定 | N81: 設定値：""(空) | O81: 設定値：0固定 | P81: 設定値：0固定 | Q81: 設定値：0固定 | R81: 設定値：0固定 | S81: 設定値：0固定 | T81: 設定値：0固定 | U81: 設定値：0固定 | V81: 設定値：0固定 | W81: 設定値：0固定 | X81: 設定値：0固定 | Y81: TSM参考 GetCustomerByNumberASY呼び出しで連携。 合計ポイントプラス数<TOTALPPLUS_QT> | Z81: *1.9
A82: =A81+1 -> 79 | B82: GSFD_OFFER_ID | C82: 計画Ｎｏ | D82: varchar | E82: 255 | F82: ● | I82: - | J82: TS/M | K82: ● | L82: 設定不要(固定値) 設定値：""(空) | M82: 設定不要(固定値) 設定値：""(空) | N82: 設定不要(固定値) 設定値：""(空) | O82: 設定不要(固定値) 設定値：""(空) | P82: 設定不要(固定値) 設定値：""(空) | Q82: 設定不要(固定値) 設定値：""(空) | R82: 設定不要(固定値) 設定値：""(空) | S82: 設定不要(固定値) 設定値：""(空) | T82: 設定不要(固定値) 設定値：""(空) | U82: 設定不要(固定値) 設定値：""(空) | V82: 設定不要(固定値) 設定値：""(空) | W82: 設定不要(固定値) 設定値：""(空) | X82: 設定不要(固定値) 設定値：""(空)
A83: =A82+1 -> 80 | B83: GSFD_ECO_PNT | C83: エコポイント | D83: int | F83: ● | I83: - | J83: TS/M | K83: ● | L83: 設定不要(固定値) 設定値：""(空) | M83: 設定不要(固定値) 設定値：""(空) | N83: 設定不要(固定値) 設定値：""(空) | O83: 設定不要(固定値) 設定値：""(空) | P83: 設定不要(固定値) 設定値：""(空) | Q83: 設定不要(固定値) 設定値：""(空) | R83: 設定不要(固定値) 設定値：""(空) | S83: 設定不要(固定値) 設定値：""(空) | T83: 設定不要(固定値) 設定値：""(空) | U83: 設定不要(固定値) 設定値：""(空) | V83: 設定不要(固定値) 設定値：""(空) | W83: 設定不要(固定値) 設定値：""(空) | X83: 設定不要(固定値) 設定値：""(空)
A84: =A83+1 -> 81 | B84: GSFD_CAP_AMT | C84: GSFDCAP金額 | D84: money | F84: ● | I84: - | J84: TS/M | K84: ● | L84: 設定不要(固定値) 設定値：""(空) | M84: 設定不要(固定値) 設定値：""(空) | N84: 設定不要(固定値) 設定値：""(空) | O84: 設定不要(固定値) 設定値：""(空) | P84: 設定不要(固定値) 設定値：""(空) | Q84: 設定不要(固定値) 設定値：""(空) | R84: 設定不要(固定値) 設定値：""(空) | S84: 設定不要(固定値) 設定値：""(空) | T84: 設定不要(固定値) 設定値：""(空) | U84: 設定不要(固定値) 設定値：""(空) | V84: 設定不要(固定値) 設定値：""(空) | W84: 設定不要(固定値) 設定値：""(空) | X84: 設定不要(固定値) 設定値：""(空) | Y84: 未使用領域の認識
A85: =A84+1 -> 82 | B85: GSFD_CUST_STS | C85: GSFD顧客STS | D85: smallint | F85: ● | I85: - | J85: ignicaPOS | K85: 〇 | L85: 設定値：0（固定） | M85: 設定値：顧客ステータスを設定 0:顧客無し、1:仮会員、2:通常顧客、3:カード忘れ ※取消線はいなげや様は未使用 | N85: 設定値：顧客ステータスを設定 0:顧客無し、1:仮会員、2:通常顧客、3:カード忘れ ※取消線はいなげや様は未使用 | O85: 設定値：0（固定） | P85: 設定値：0（固定） | Q85: 設定値：0（固定） | R85: 設定値：0（固定） | S85: 設定値：0（固定） | T85: 設定値：0（固定） | U85: 設定値：0（固定） | V85: 設定値：0（固定） | W85: 設定値：0（固定） | X85: 設定値：0（固定） | Z85: *1.1
A86: =A85+1 -> 83 | B86: GSFD_CUST_INF | C86: GSFD顧客ＩＮＦ | D86: smallint | F86: ● | I86: - | J86: TS/M | K86: ● | L86: 設定不要(固定値) 設定値：""(空) | M86: 設定不要(固定値) 設定値：""(空) | N86: 設定不要(固定値) 設定値：""(空) | O86: 設定不要(固定値) 設定値：""(空) | P86: 設定不要(固定値) 設定値：""(空) | Q86: 設定不要(固定値) 設定値：""(空) | R86: 設定不要(固定値) 設定値：""(空) | S86: 設定不要(固定値) 設定値：""(空) | T86: 設定不要(固定値) 設定値：""(空) | U86: 設定不要(固定値) 設定値：""(空) | V86: 設定不要(固定値) 設定値：""(空) | W86: 設定不要(固定値) 設定値：""(空) | X86: 設定不要(固定値) 設定値：""(空)
A87: =A86+1 -> 84 | B87: GSFD_CARD_ENTRY_TYPE | C87: GSFDカード登録種別 | D87: smallint | F87: ● | I87: - | J87: ignicaPOS | K87: ◎ | L87: 設定値：0（固定） | M87: 設定値：カード登録種別 0:顧客無し、4:顧客登録あり、5:プリンスカード ※プリンスカードは次回開発 | N87: 設定値：カード登録種別 0:顧客無し、4:顧客登録あり、5:プリンスカード ※プリンスカードは次回開発 | O87: 設定値：0（固定） | P87: 設定値：0（固定） | Q87: 設定値：0（固定） | R87: 設定値：0（固定） | S87: 設定値：0（固定） | T87: 設定値：0（固定） | U87: 設定値：0（固定） | V87: 設定値：0（固定） | W87: 設定値：0（固定） | X87: 設定値：0（固定）
A88: =A87+1 -> 85 | B88: GSFD_PAYMENT_PNT | C88: 利用ポイント数 | D88: int | F88: ● | I88: - | J88: TS/M | K88: ● | L88: 設定不要(固定値) 設定値：""(空) | M88: 設定不要(固定値) 設定値：""(空) | N88: 設定不要(固定値) 設定値：""(空) | O88: 設定不要(固定値) 設定値：""(空) | P88: 設定不要(固定値) 設定値：""(空) | Q88: 設定不要(固定値) 設定値：""(空) | R88: 設定不要(固定値) 設定値：""(空) | S88: 設定不要(固定値) 設定値：""(空) | T88: 設定不要(固定値) 設定値：""(空) | U88: 設定不要(固定値) 設定値：""(空) | V88: 設定不要(固定値) 設定値：""(空) | W88: 設定不要(固定値) 設定値：""(空) | X88: 設定不要(固定値) 設定値：""(空)
A89: =A88+1 -> 86 | B89: GSFD_BONUS_PNT | C89: ボーナスポイント数 | D89: int | F89: ● | I89: - | J89: TS/M | K89: ● | L89: 設定不要(固定値) 設定値：""(空) | M89: 設定不要(固定値) 設定値：""(空) | N89: 設定不要(固定値) 設定値：""(空) | O89: 設定不要(固定値) 設定値：""(空) | P89: 設定不要(固定値) 設定値：""(空) | Q89: 設定不要(固定値) 設定値：""(空) | R89: 設定不要(固定値) 設定値：""(空) | S89: 設定不要(固定値) 設定値：""(空) | T89: 設定不要(固定値) 設定値：""(空) | U89: 設定不要(固定値) 設定値：""(空) | V89: 設定不要(固定値) 設定値：""(空) | W89: 設定不要(固定値) 設定値：""(空) | X89: 設定不要(固定値) 設定値：""(空)
A90: =A89+1 -> 87 | B90: GSFD_BONUS_AMT | C90: ボーナスポイント金額 | D90: money | F90: ● | I90: - | J90: TS/M | K90: ● | L90: 設定不要(固定値) 設定値：""(空) | M90: 設定不要(固定値) 設定値：""(空) | N90: 設定不要(固定値) 設定値：""(空) | O90: 設定不要(固定値) 設定値：""(空) | P90: 設定不要(固定値) 設定値：""(空) | Q90: 設定不要(固定値) 設定値：""(空) | R90: 設定不要(固定値) 設定値：""(空) | S90: 設定不要(固定値) 設定値：""(空) | T90: 設定不要(固定値) 設定値：""(空) | U90: 設定不要(固定値) 設定値：""(空) | V90: 設定不要(固定値) 設定値：""(空) | W90: 設定不要(固定値) 設定値：""(空) | X90: 設定不要(固定値) 設定値：""(空)
A91: =A90+1 -> 88 | B91: GSFD_CASH_COUNTS | C91: 釣銭補充アイテムレコード | D91: varchar | E91: 255 | F91: ● | H91: 釣銭補充アイテムレコード | I91: - | J91: ignicaPOS | K91: ◎ | L91: 設定値：釣銭情報（精査結果の機内在高） 1：1円収納庫枚数，5：5円収納庫枚数，10：10円収納庫枚数，50：50円収納庫枚数，100：100円収納庫枚数，500：500円収納庫枚数；1000：1000円収納庫枚数，2000：2000円収納庫枚数，5000：5000円収納庫枚数，10000：10000円収納庫枚数/1000：1000円回収庫枚数，2000：2000円回収庫枚数，5000：5000円回収庫枚数，10000：10000円回収庫枚数/1：1円棒金庫本数，5：5円棒金庫本数，10：10円棒金庫本数，50：50円棒金庫本数，100：100円棒金庫本数，500：500円棒金庫本数 ＜例1 全金種に数値がある場合＞ 1:999,5:999,10:999,50:999,100:999,500:999;1000:999,2000:999,5000:999,10000:999/1000:999,2000:999,5000:999,10000:999/1:99,5:99,10:99,50:99,100:99,500:99 ＜例2 全金種に数値がない場合＞ 1:0,5:0,10:0,50:0,100:0,500:0;1000:0,2000:0,5000:0,10000:0/1000:0,2000:0,5000:0,10000:0/1:0,5:0,10:0,50:0,100:0,500:0 | M91: 設定値：釣銭情報（精査結果の機内在高） 1：1円収納庫枚数，5：5円収納庫枚数，10：10円収納庫枚数，50：50円収納庫枚数，100：100円収納庫枚数，500：500円収納庫枚数；1000：1000円収納庫枚数，2000：2000円収納庫枚数，5000：5000円収納庫枚数，10000：10000円収納庫枚数/1000：1000円回収庫枚数，2000：2000円回収庫枚数，5000：5000円回収庫枚数，10000：10000円回収庫枚数/1：1円棒金庫本数，5：5円棒金庫本数，10：10円棒金庫本数，50：50円棒金庫本数，100：100円棒金庫本数，500：500円棒金庫本数 ＜例1 全金種に数値がある場合＞ 1:999,5:999,10:999,50:999,100:999,500:999;1000:999,2000:999,5000:999,10000:999/1000:999,2000:999,5000:999,10000:999/1:99,5:99,10:99,50:99,100:99,500:99 ＜例2 全金種に数値がない場合＞ 1:0,5:0,10:0,50:0,100:0,500:0;1000:0,2000:0,5000:0,10000:0/1000:0,2000:0,5000:0,10000:0/1:0,5:0,10:0,50:0,100:0,500:0 | N91: 設定値：釣銭情報（精査結果の機内在高） 1：1円収納庫枚数，5：5円収納庫枚数，10：10円収納庫枚数，50：50円収納庫枚数，100：100円収納庫枚数，500：500円収納庫枚数；1000：1000円収納庫枚数，2000：2000円収納庫枚数，5000：5000円収納庫枚数，10000：10000円収納庫枚数/1000：1000円回収庫枚数，2000：2000円回収庫枚数，5000：5000円回収庫枚数，10000：10000円回収庫枚数/1：1円棒金庫本数，5：5円棒金庫本数，10：10円棒金庫本数，50：50円棒金庫本数，100：100円棒金庫本数，500：500円棒金庫本数 ＜例1 全金種に数値がある場合＞ 1:999,5:999,10:999,50:999,100:999,500:999;1000:999,2000:999,5000:999,10000:999/1000:999,2000:999,5000:999,10000:999/1:99,5:99,10:99,50:99,100:99,500:99 ＜例2 全金種に数値がない場合＞ 1:0,5:0,10:0,50:0,100:0,500:0;1000:0,2000:0,5000:0,10000:0/1000:0,2000:0,5000:0,10000:0/1:0,5:0,10:0,50:0,100:0,500:0 | O91: 設定値：釣銭情報（精査結果の機内在高） 1：1円収納庫枚数，5：5円収納庫枚数，10：10円収納庫枚数，50：50円収納庫枚数，100：100円収納庫枚数，500：500円収納庫枚数；1000：1000円収納庫枚数，2000：2000円収納庫枚数，5000：5000円収納庫枚数，10000：10000円収納庫枚数/1000：1000円回収庫枚数，2000：2000円回収庫枚数，5000：5000円回収庫枚数，10000：10000円回収庫枚数/1：1円棒金庫本数，5：5円棒金庫本数，10：10円棒金庫本数，50：50円棒金庫本数，100：100円棒金庫本数，500：500円棒金庫本数 ＜例1 全金種に数値がある場合＞ 1:999,5:999,10:999,50:999,100:999,500:999;1000:999,2000:999,5000:999,10000:999/1000:999,2000:999,5000:999,10000:999/1:99,5:99,10:99,50:99,100:99,500:99 ＜例2 全金種に数値がない場合＞ 1:0,5:0,10:0,50:0,100:0,500:0;1000:0,2000:0,5000:0,10000:0/1000:0,2000:0,5000:0,10000:0/1:0,5:0,10:0,50:0,100:0,500:0 | P91: 設定値：""(空) | Q91: 設定値：釣銭情報（精査結果の機内在高） 1：1円収納庫枚数，5：5円収納庫枚数，10：10円収納庫枚数，50：50円収納庫枚数，100：100円収納庫枚数，500：500円収納庫枚数；1000：1000円収納庫枚数，2000：2000円収納庫枚数，5000：5000円収納庫枚数，10000：10000円収納庫枚数/1000：1000円回収庫枚数，2000：2000円回収庫枚数，5000：5000円回収庫枚数，10000：10000円回収庫枚数/1：1円棒金庫本数，5：5円棒金庫本数，10：10円棒金庫本数，50：50円棒金庫本数，100：100円棒金庫本数，500：500円棒金庫本数 ＜例1 全金種に数値がある場合＞ 1:999,5:999,10:999,50:999,100:999,500:999;1000:999,2000:999,5000:999,10000:999/1000:999,2000:999,5000:999,10000:999/1:99,5:99,10:99,50:99,100:99,500:99 ＜例2 全金種に数値がない場合＞ 1:0,5:0,10:0,50:0,100:0,500:0;1000:0,2000:0,5000:0,10000:0/1000:0,2000:0,5000:0,10000:0/1:0,5:0,10:0,50:0,100:0,500:0 | R91: 設定値：""(空) | S91: 設定値：釣銭情報（精査結果の機内在高） 1：1円収納庫枚数，5：5円収納庫枚数，10：10円収納庫枚数，50：50円収納庫枚数，100：100円収納庫枚数，500：500円収納庫枚数；1000：1000円収納庫枚数，2000：2000円収納庫枚数，5000：5000円収納庫枚数，10000：10000円収納庫枚数/1000：1000円回収庫枚数，2000：2000円回収庫枚数，5000：5000円回収庫枚数，10000：10000円回収庫枚数/1：1円棒金庫本数，5：5円棒金庫本数，10：10円棒金庫本数，50：50円棒金庫本数，100：100円棒金庫本数，500：500円棒金庫本数 ＜例1 全金種に数値がある場合＞ 1:999,5:999,10:999,50:999,100:999,500:999;1000:999,2000:999,5000:999,10000:999/1000:999,2000:999,5000:999,10000:999/1:99,5:99,10:99,50:99,100:99,500:99 ＜例2 全金種に数値がない場合＞ 1:0,5:0,10:0,50:0,100:0,500:0;1000:0,2000:0,5000:0,10000:0/1000:0,2000:0,5000:0,10000:0/1:0,5:0,10:0,50:0,100:0,500:0 | T91: 設定値：""(空) | U91: 設定値：釣銭情報（精査結果の機内在高） 1：1円収納庫枚数，5：5円収納庫枚数，10：10円収納庫枚数，50：50円収納庫枚数，100：100円収納庫枚数，500：500円収納庫枚数；1000：1000円収納庫枚数，2000：2000円収納庫枚数，5000：5000円収納庫枚数，10000：10000円収納庫枚数/1000：1000円回収庫枚数，2000：2000円回収庫枚数，5000：5000円回収庫枚数，10000：10000円回収庫枚数/1：1円棒金庫本数，5：5円棒金庫本数，10：10円棒金庫本数，50：50円棒金庫本数，100：100円棒金庫本数，500：500円棒金庫本数 ＜例1 全金種に数値がある場合＞ 1:999,5:999,10:999,50:999,100:999,500:999;1000:999,2000:999,5000:999,10000:999/1000:999,2000:999,5000:999,10000:999/1:99,5:99,10:99,50:99,100:99,500:99 ＜例2 全金種に数値がない場合＞ 1:0,5:0,10:0,50:0,100:0,500:0;1000:0,2000:0,5000:0,10000:0/1000:0,2000:0,5000:0,10000:0/1:0,5:0,10:0,50:0,100:0,500:0 | V91: 設定値：釣銭情報（精査結果の機内在高） 1：1円収納庫枚数，5：5円収納庫枚数，10：10円収納庫枚数，50：50円収納庫枚数，100：100円収納庫枚数，500：500円収納庫枚数；1000：1000円収納庫枚数，2000：2000円収納庫枚数，5000：5000円収納庫枚数，10000：10000円収納庫枚数/1000：1000円回収庫枚数，2000：2000円回収庫枚数，5000：5000円回収庫枚数，10000：10000円回収庫枚数/1：1円棒金庫本数，5：5円棒金庫本数，10：10円棒金庫本数，50：50円棒金庫本数，100：100円棒金庫本数，500：500円棒金庫本数 ＜例1 全金種に数値がある場合＞ 1:999,5:999,10:999,50:999,100:999,500:999;1000:999,2000:999,5000:999,10000:999/1000:999,2000:999,5000:999,10000:999/1:99,5:99,10:99,50:99,100:99,500:99 ＜例2 全金種に数値がない場合＞ 1:0,5:0,10:0,50:0,100:0,500:0;1000:0,2000:0,5000:0,10000:0/1000:0,2000:0,5000:0,10000:0/1:0,5:0,10:0,50:0,100:0,500:0 | W91: 設定値：""(空) | X91: 設定値：釣銭情報（精査結果の機内在高） 1：1円収納庫枚数，5：5円収納庫枚数，10：10円収納庫枚数，50：50円収納庫枚数，100：100円収納庫枚数，500：500円収納庫枚数；1000：1000円収納庫枚数，2000：2000円収納庫枚数，5000：5000円収納庫枚数，10000：10000円収納庫枚数/1000：1000円回収庫枚数，2000：2000円回収庫枚数，5000：5000円回収庫枚数，10000：10000円回収庫枚数/1：1円棒金庫本数，5：5円棒金庫本数，10：10円棒金庫本数，50：50円棒金庫本数，100：100円棒金庫本数，500：500円棒金庫本数 ＜例1 全金種に数値がある場合＞ 1:999,5:999,10:999,50:999,100:999,500:999;1000:999,2000:999,5000:999,10000:999/1000:999,2000:999,5000:999,10000:999/1:99,5:99,10:99,50:99,100:99,500:99 ＜例2 全金種に数値がない場合＞ 1:0,5:0,10:0,50:0,100:0,500:0;1000:0,2000:0,5000:0,10000:0/1000:0,2000:0,5000:0,10000:0/1:0,5:0,10:0,50:0,100:0,500:0 | Z91: *1.10
A92: =A91+1 -> 89 | B92: GSFD_COMPARE_CASH_AMT | C92: 釣銭過不足履歴アイテムレコード | D92: varchar | E92: 255 | F92: ● | H92: 釣銭過不足履歴アイテムレコード | I92: - | J92: ignicaPOS | K92: ◎ | L92: 設定値："POS番号, 担当者番号, 開始時刻, 現金在高, 釣銭機在高, 開始過不足額（釣銭機在高 - 現金在高）"を設定 ＜例＞ 0001,0001,2003/11/18 11:15:44,99999999,99999999 | M92: 設定不要(固定値) 設定値：""(空) | N92: 設定不要(固定値) 設定値：""(空) | O92: 設定不要(固定値) 設定値：""(空) | P92: 設定不要(固定値) 設定値：""(空) | Q92: 設定不要(固定値) 設定値：""(空) | R92: 設定不要(固定値) 設定値：""(空) | S92: 設定不要(固定値) 設定値：""(空) | T92: 設定不要(固定値) 設定値：""(空) | U92: 設定不要(固定値) 設定値：""(空) | V92: 設定不要(固定値) 設定値：""(空) | W92: 設定不要(固定値) 設定値：""(空) | X92: 設定値："POS番号, 担当者番号, 開始時刻, 現金在高, 釣銭機在高, 開始過不足額（現金在高合計 - 現金在高）"を設定 ＜例＞ 0001,0001,2003/11/18 11:15:44,99999999,99999999 | Z92: *1.5
A93: =A92+1 -> 90 | B93: GSFD_CASH_COLSPY_AMT | C93: 現金COLSPY金額 | D93: varchar | E93: 255 | F93: ● | H93: 現金COLSPY金額 ※下記の場合のみ設定する ・TRAN_CD=15（入金） 「棒金ドロア追加(入出金コード=582)」、「紙幣・硬貨追加(入出金コード=580)」、「硬貨・紙幣追加(全填)(入出金コード=581)」の場合に値を設定 ・TRAN_CD=16（出金） 「途中回収(入出金コード=680)」、「全回収(入出金コード=681)」と「レジ撤去(入出金コード=682)」の場合に値を設定 | I93: - | J93: ignicaPOS | K93: ◎ | L93: 設定値：""(空) | M93: 設定値：""(空) | N93: 設定値：""(空) | O93: 設定値：釣銭機紙幣・硬貨の回収ｶﾝﾏﾃﾞｰﾀの時 ＜例1＞ ボックス回収の時 1000:999,2000:999,5000:999,10000:999 釣銭補充の時 1:999,5:999,10:999,50:999,100:999,500:999;1000:999,2000:999,5000:999,10000:999 ＜例2＞ ボックス回収の時 1000:0,2000:0,5000:0,10000:0 釣銭補充の時 1:0,5:0,10:0,50:0,100:0,500:0;1000:0,2000:0,5000:0,10000:0 | P93: 設定値：""(空) | Q93: 設定値：釣銭機紙幣・硬貨の回収ｶﾝﾏﾃﾞｰﾀの時 ＜例1＞ ボックス回収の時 1000:999,2000:999,5000:999,10000:999 釣銭補充の時 1:999,5:999,10:999,50:999,100:999,500:999;1000:999,2000:999,5000:999,10000:999 ＜例2＞ ボックス回収の時 1000:0,2000:0,5000:0,10000:0 釣銭補充の時 1:0,5:0,10:0,50:0,100:0,500:0;1000:0,2000:0,5000:0,10000:0 | R93: 設定値：""(空) | S93: 設定値：""(空) | T93: 設定値：""(空) | U93: 設定値：""(空) | V93: 設定値：釣銭機紙幣・硬貨の回収ｶﾝﾏﾃﾞｰﾀの時 ＜例1＞ ボックス回収の時 1000:999,2000:999,5000:999,10000:999 釣銭補充の時 1:999,5:999,10:999,50:999,100:999,500:999;1000:999,2000:999,5000:999,10000:999 ＜例2＞ ボックス回収の時 1000:0,2000:0,5000:0,10000:0 釣銭補充の時 1:0,5:0,10:0,50:0,100:0,500:0;1000:0,2000:0,5000:0,10000:0 | W93: 設定値：""(空) | X93: 設定値：""(空) | Z93: *1.5,1.6,1.11,1.12
A94: =A93+1 -> 91 | B94: GSFD_GIFT_BARCODE | C94: ギフトバーコード | D94: varchar | E94: 30 | F94: ● | I94: - | J94: TS/M | K94: ● | L94: 設定不要(固定値) 設定値：""(空) | M94: 設定不要(固定値) 設定値：""(空) | N94: 設定不要(固定値) 設定値：""(空) | O94: 設定不要(固定値) 設定値：""(空) | P94: 設定不要(固定値) 設定値：""(空) | Q94: 設定不要(固定値) 設定値：""(空) | R94: 設定不要(固定値) 設定値：""(空) | S94: 設定不要(固定値) 設定値：""(空) | T94: 設定不要(固定値) 設定値：""(空) | U94: 設定不要(固定値) 設定値：""(空) | V94: 設定不要(固定値) 設定値：""(空) | W94: 設定不要(固定値) 設定値：""(空) | X94: 設定不要(固定値) 設定値：""(空)
A95: =A94+1 -> 92 | B95: GSFD_UCST_DATA01 | C95: カスタマイズデータ０１ | D95: varchar | E95: 20 | F95: ● | I95: - | J95: TS/M | K95: ● | L95: 設定不要(固定値) 設定値：""(空) | M95: 設定不要(固定値) 設定値：""(空) | N95: 設定不要(固定値) 設定値：""(空) | O95: 設定不要(固定値) 設定値：""(空) | P95: 設定不要(固定値) 設定値：""(空) | Q95: 設定不要(固定値) 設定値：""(空) | R95: 設定不要(固定値) 設定値：""(空) | S95: 設定不要(固定値) 設定値：""(空) | T95: 設定不要(固定値) 設定値：""(空) | U95: 設定不要(固定値) 設定値：""(空) | V95: 設定不要(固定値) 設定値：""(空) | W95: 設定不要(固定値) 設定値：""(空) | X95: 設定不要(固定値) 設定値：""(空) | Y95: 未使用領域のため
A96: =A95+1 -> 93 | B96: GSFD_SUS_CNT | C96: サスペント数 | D96: char | E96: 7 | F96: ● | I96: - | J96: TS/M | K96: ● | L96: 設定不要(固定値) 設定値：""(空) | M96: 設定不要(固定値) 設定値：""(空) | N96: 設定不要(固定値) 設定値：""(空) | O96: 設定不要(固定値) 設定値：""(空) | P96: 設定不要(固定値) 設定値：""(空) | Q96: 設定不要(固定値) 設定値：""(空) | R96: 設定不要(固定値) 設定値：""(空) | S96: 設定不要(固定値) 設定値：""(空) | T96: 設定不要(固定値) 設定値：""(空) | U96: 設定不要(固定値) 設定値：""(空) | V96: 設定不要(固定値) 設定値：""(空) | W96: 設定不要(固定値) 設定値：""(空) | X96: 設定不要(固定値) 設定値：""(空)
A97: =A96+1 -> 94 | B97: GSFD_CNCL_RSN_CD | C97: 通番取消理由コード | D97: smallint | F97: ● | H97: 取引に対しての取消理由コードを設定 | I97: - | J97: TS/M | K97: ● | L97: 設定不要(固定値) 設定値：""(空) | M97: 設定不要(固定値) 設定値：""(空) | N97: 設定不要(固定値) 設定値：""(空) | O97: 設定不要(固定値) 設定値：""(空) | P97: 設定不要(固定値) 設定値：""(空) | Q97: 設定不要(固定値) 設定値：""(空) | R97: 設定不要(固定値) 設定値：""(空) | S97: 設定不要(固定値) 設定値：""(空) | T97: 設定不要(固定値) 設定値：""(空) | U97: 設定不要(固定値) 設定値：""(空) | V97: 設定不要(固定値) 設定値：""(空) | W97: 設定不要(固定値) 設定値：""(空) | X97: 設定不要(固定値) 設定値：""(空) | Y97: 売上、返品では設定されないため設定不要
A98: =A97+1 -> 95 | B98: GSFD_ITEM_COUNTS | C98: 単品カウント | D98: varchar | E98: 20 | F98: ● | I98: - | J98: ignicaPOS | K98: ◎ | L98: 設定値：0,0,0（固定） | M98: 設定値：9,9,9 1カラム：LN_DETAIL数 2カラム：LN_DISCOUNT数 3カラム：TRANSCATION_TENDER数 | N98: 設定値：9,9,9 1カラム：LN_DETAIL数 2カラム：LN_DISCOUNT数 3カラム：TRANSCATION_TENDER数 | O98: 設定値：0,0,1（固定） 1カラム：0 固定 2カラム：0 固定 3カラム：TRANSCATION_TENDER数 | P98: 設定値：0,0,0（固定） | Q98: 設定値：0,0,1（固定） 1カラム：0 固定 2カラム：0 固定 3カラム：TRANSCATION_TENDER数 | R98: 設定値：0,0,0（固定） | S98: 設定値：0,0,0（固定） | T98: 設定値：0,0,0（固定） | U98: 設定値：0,0,0（固定） | V98: 設定値：0,0,0（固定） | W98: 設定値：0,0,0（固定） | X98: 設定値：0,0,0（固定） | Z98: *1.6
A99: =A98+1 -> 96 | B99: GSFD_UCST_RSV01 | C99: カスタマイズ予約１ | D99: varchar | E99: 5 | F99: ● | I99: - | J99: TS/M | K99: ● | L99: 設定不要(固定値) 設定値：""(空) | M99: 設定不要(固定値) 設定値：""(空) | N99: 設定不要(固定値) 設定値：""(空) | O99: 設定不要(固定値) 設定値：""(空) | P99: 設定不要(固定値) 設定値：""(空) | Q99: 設定不要(固定値) 設定値：""(空) | R99: 設定不要(固定値) 設定値：""(空) | S99: 設定不要(固定値) 設定値：""(空) | T99: 設定不要(固定値) 設定値：""(空) | U99: 設定不要(固定値) 設定値：""(空) | V99: 設定不要(固定値) 設定値：""(空) | W99: 設定不要(固定値) 設定値：""(空) | X99: 設定不要(固定値) 設定値：""(空)
A100: =A99+1 -> 97 | B100: GSFD_UCST_RSV02 | C100: カスタマイズ予約２ | D100: varchar | E100: 10 | F100: ● | I100: - | J100: TS/M | K100: ● | L100: 設定不要(固定値) 設定値：""(空) | M100: 設定不要(固定値) 設定値：""(空) | N100: 設定不要(固定値) 設定値：""(空) | O100: 設定不要(固定値) 設定値：""(空) | P100: 設定不要(固定値) 設定値：""(空) | Q100: 設定不要(固定値) 設定値：""(空) | R100: 設定不要(固定値) 設定値：""(空) | S100: 設定不要(固定値) 設定値：""(空) | T100: 設定不要(固定値) 設定値：""(空) | U100: 設定不要(固定値) 設定値：""(空) | V100: 設定不要(固定値) 設定値：""(空) | W100: 設定不要(固定値) 設定値：""(空) | X100: 設定不要(固定値) 設定値：""(空)
...

Sheet LN_LINK
A1: トラン連携ファイルレイアウト | C1: 対象テーブル：LN_LINK 形式：TSV
A2: NO | B2: 項目 | H2: 説明 | I2: 取得元マスタ項目 | J2: 設定元 | K2: 一次開発 必須項目 | L2: ignicaPOS・Scan&Go設定値 | N2: 備考
B3: カラム名称 | C3: 日本語名称 | D3: 型 | E3: サイズ | F3: NULL 許可 | G3: KEY | L3: 売上 | M3: 売上中止
A4: 1 | B4: TRAN_ID | C4: 取引通番 | D4: int | G4: PK | H4: 取引の識別子 | J4: TS/M | K4: ● | L4: TSM側で設定となるため、設定不要（固定値） 設定値：""(空) | M4: TSM側で設定となるため、設定不要（固定値） 設定値：""(空)
A5: 2 | B5: TRAN_LN_NBR | C5: 取引明細番号 | D5: smallint | G5: PK | H5: 取引の明細レベルに割当てられるライン番号 | I5: - | J5: ignicaPOS | K5: ◎ | L5: 設定値： リンク元となるLN_DETAILのTRAN_LN_NBR | M5: 設定値： リンク元となるLN_DETAILのTRAN_LN_NBR
A6: 3 | B6: LINK_LN_NBR | C6: リンク明細番号 | D6: smallint | G6: PK | H6: 取引内通番とリンクする内部管理番号（リンク先のTRAN_LN_NBRとなる） | I6: - | J6: ignicaPOS | K6: ◎ | L6: 設定値： リンク先となる下記テーブルのTRAN_LN_NBR ・LN_DISCOUNT ・TRANSACTION_TAX | M6: 設定値： リンク先となる下記テーブルのTRAN_LN_NBR ・LN_DISCOUNT ・TRANSACTION_TAX | O6: *1.0
A7: 4 | B7: LINK_TYP | C7: リンクタイプ | D7: smallint | G7: PK | H7: リンクのタイプまたは理由(税金、ディスカウントなど) 1：値引、 3：税、5：税(税率変更)、6：訂正済み現外支払、9：内税額、10：内税商品額(税抜き) | I7: - | J7: ignicaPOS | K7: ◎ | L7: 設定値：リンクのタイプまたは理由(税金、ディスカウントなど) | M7: 設定値：リンクのタイプまたは理由(税金、ディスカウントなど) | N7: 他の情報から、リンクテーブルを作成 | O7: *1.0
A8: 5 | B8: LINK_AMT | C8: リンク明細額 | D8: money | F8: ● | H8: このアイテムだけに適用される取引ディスカウントの金額等。 リンク先の金額。通番取消の場合、"0"が入る。値引の場合、値引額×数量の金額が入る。また、取引に対する値引（取引売価変更、小計値引等）が行われた場合は按分価格となる。 リンクタイプ=1：値引 値引額の明細按分額 リンクタイプ=9：内税 内税額の明細按分額 リンクタイプ=10：内税商品額(税抜き) 内税商品額(税抜き)の明細按分額 ※リンクタイプが1:値引の場合でも、特売・タイムサービス・マークダウンの場合は0を設定 | I8: - | J8: ignicaPOS | K8: ◎ | L8: 設定値： リンクタイプ=1：値引 値引額の明細按分額 リンクタイプ=9：内税 内税額の明細按分額 リンクタイプ=10：内税商品額(税抜き) 内税商品額(税抜き)の明細按分額 | M8: 設定値： リンクタイプ=1：値引 値引額の明細按分額 リンクタイプ=9：内税 内税額の明細按分額 リンクタイプ=10：内税商品額(税抜き) 内税商品額(税抜き)の明細按分額 | N8: 他の情報から、リンクテーブルを作成 | O8: *1.5,1.8
A9: 6 | B9: STR_ID | C9: 店舗番号 | D9: int | G9: PK | H9: 店舗番号 | I9: 店舗番号 | J9: ignicaPOS | K9: ◎ | L9: 設定値：店舗番号×10000 | M9: 設定値：店舗番号×10000
A10: 7 | B10: LINK_QTY | C10: リンクの数 | D10: float | F10: ● | H10: LinkTypeが1:値引の場合に数量を設定。 ※LinkTypeが1:値引の場合でも、特売・タイムサービス・マークダウンの場合は0を設定 | I10: - | J10: ignicaPOS | K10: ◎ | L10: 設定値：LinkTypeが1:値引の場合に数量を設定。 | M10: 設定値：LinkTypeが1:値引の場合に数量を設定。 | N10: 他の情報から、リンクテーブルを作成 | O10: *1.8

Sheet LN_DETAIL
A1: トラン連携ファイルレイアウト | C1: 対象テーブル：LN_DETAIL 形式：TSV
A2: NO | B2: 項目 | H2: 説明 | I2: 取得元マスタ項目 | J2: 設定元 | K2: 一次開発 必須項目 | L2: ignicaPOS・Scan&Go設定値 | N2: 備考
B3: カラム名称 | C3: 日本語名称 | D3: 型 | E3: サイズ | F3: NULL 許可 | G3: KEY | L3: 売上 | M3: 売上 中止
A4: 1 | B4: TRAN_ID | C4: 取引通番 | D4: int | G4: PK | H4: 取引の識別子 | I4: - | J4: TS/M | K4: ● | L4: TSM側で設定となるため、設定不要（固定値） 設定値：""(空) | M4: TSM側で設定となるため、設定不要（固定値） 設定値：""(空)
A5: =A4+1 -> 2 | B5: TRAN_LN_NBR | C5: 取引明細番号 | D5: smallint | G5: PK | H5: 取引の明細レベルに割当てられるライン番号 | I5: - | J5: ignicaPOS | K5: ◎ | L5: 設定値： 1取引内の下記テーブルのレコードの同一カラム名に通し番号を振る(番号が重複しなければ順不同で構わない) ・LN_DETAIL ・LN_DISCOUNT ・TRANSACTION_TAX ・TRANSACTION_TENDER | M5: 設定値： 1取引内の下記テーブルのレコードの同一カラム名に通し番号を振る(番号が重複しなければ順不同で構わない) ・LN_DETAIL ・LN_DISCOUNT ・TRANSACTION_TAX ・TRANSACTION_TENDER
A6: =A5+1 -> 3 | B6: STR_ID | C6: 店舗番号 | D6: int | G6: PK | H6: 店舗番号 | I6: 店舗番号 | J6: ignicaPOS | K6: ◎ | L6: 設定値：店舗番号×10000 | M6: 設定値：店舗番号×10000
A7: =A6+1 -> 4 | B7: LOC_ID | C7: 商品在庫位置 | D7: varchar | E7: 12 | F7: ● | H7: 販売／返品によって計算される在庫の位置 注：在庫が他の店舗または配送センター／倉庫にある場合、LOC_IDは他方店舗のロケーションになります。 | I7: - | J7: TS/M | K7: ● | L7: 設定不要(固定値) 設定値："" | M7: 設定不要(固定値) 設定値：""
A8: =A7+1 -> 5 | B8: SCAN_TYP | C8: PLUタイプ | D8: smallint | H8: 1：SKU 2：UPC-A 3：部門コード 4：EAN8、 JAN8 (NONPLU8) 5：EAN13、JAN13(NONPLU13) 新/旧書籍、新/旧雑誌 6：UPCE 7：ISBN100：KeyPLU、ShortCode 100：キーPLU 101：UPC-E | I8: 商品マスタ連携ファイル No.84 ＰＬＵタイプ | J8: ignicaPOS | K8: ◎ | L8: 設定値：商品マスタ連携ファイルから取得して設定 | M8: 設定値：商品マスタ連携ファイルから取得して設定
A9: =A8+1 -> 6 | B9: PLU_ID | C9: 自社商品コード | D9: varchar | E9: 24 | H9: 販売または返品された商品を表すPLU ＩＤ | I9: 商品マスタ連携ファイル No.2 自社商品コード | J9: ignicaPOS | K9: ◎ | L9: 設定値：商品マスタ連携ファイルから取得して設定 | M9: 設定値：商品マスタ連携ファイルから取得して設定
A10: =A9+1 -> 7 | B10: SCAN_ID | C10: スキャンコード | D10: varchar | E10: 24 | F10: ● | H10: 商品に付く数値の識別子で、通常はマシンで読取り可能なバーコードです。 | I10: 商品マスタ連携ファイル No.83 スキャンコード | J10: ignicaPOS | K10: ◎ | L10: 設定値：商品マスタ連携ファイルから取得して設定 | M10: 設定値：商品マスタ連携ファイルから取得して設定
A11: =A10+1 -> 8 | B11: LN_ITM_CD | C11: 商品明細識別 | D11: smallint | H11: 0：売上部門1：売上除外部門2：非商品部門3：非商品売上除外部門 明細種別 各ビットは ’１’で有意とする。 LSB ビット０：売上除外 ビット１：非商品 ビット２：返ビン ビット３：販売制限フラグ （酒類販売など） ビット４：特売（本部指示） ビット５：特売（店舗指示） ビット６：マークダウン ビット７：値引バーコード ビット８：緊急登録 ビット９：FSPクーポン値引バーコード ビット１０：値引除外 ビット１１：販売停止 ビット１２：販売証明書印刷指定 ビット１３：確認メッセージ出力商品 ビット１４：オフラインＰＬＵメンテフラグ（特売未反映フラグ） MSB ビット１５： | I11: 商品マスタ連携ファイルの「No.8 商品／非商品識別コード」に対して、下記のビットを立てる(ORする) ・マークダウン(一般)が採用された場合 ⇒ビット５：特売（店舗指示）＝32 および、ビット６：マークダウン＝64 ※32＋64＝96をORする ・タイムサービス(一般)、または、特売(一般)が採用された場合 ⇒ビット４：特売（本部指示）＝16 または、ビット５：特売（店舗指示）＝32 ※ビット４：特売（本部指示） or ビット５：特売（店舗指示）の判別方法 企画マスタ連携ファイルの「No.10 企画優先区分」を参照 ・企画優先区分=1(本部優先)の場合 ⇒ビット４：特売（本部指示）＝16 ・企画優先区分=0(店舗優先)の場合 ⇒ビット５：特売（店舗指示）＝32 ※ビット１０：値引除外は、POS操作で値引除外した場合に立てるフラグのため、ignica連携ではフラグ立ては不要 | J11: ignicaPOS | K11: ◎ | L11: 設定値：取得元マスタ項目を参照 | M11: 設定値：取得元マスタ項目を参照
A12: =A11+1 -> 9 | B12: MDSE_XREF_NO | C12: 商品分類番号 | D12: int | F12: ● | H12: 商品階層の最下層へのクロスリファレンス | I12: 商品マスタ連携ファイル No.91 内部商品分類番号 | J12: ignicaPOS | K12: ◎ | L12: 設定値：商品マスタ連携ファイルから取得して設定 | M12: 設定値：商品マスタ連携ファイルから取得して設定
A13: =A12+1 -> 10 | B13: STR_HIER_ID | C13: 販売部門ID | D13: int | F13: ● | H13: 商品を販売または返品する、店舗の販売部門 | I13: - | J13: TS/M | K13: ● | L13: 設定不要(固定値) 設定値：""(空) | M13: 設定不要(固定値) 設定値：""(空) | N13: 未使用領域の認識。
A14: =A13+1 -> 11 | B14: QTY | C14: 販売数量 | D14: float | H14: 単一の明細情報内の、販売または返品された商品の合計数量 | I14: - | J14: ignicaPOS | K14: ◎ | L14: 設定値：商品の数量 | M14: 設定値：商品の数量
A15: =A14+1 -> 12 | B15: UOM | C15: 販売単位 | D15: varchar | E15: 4 | F15: ● | H15: 明細の数量を計測する単位 | I15: - | J15: TS/M | K15: ● | L15: 設定不要(固定値) 設定値：""(空) | M15: 設定不要(固定値) 設定値：""(空) | N15: 未使用領域の認識。
A16: =A15+1 -> 13 | B16: PRC_MTHD | C16: 価格算出方法 | D16: smallint | H16: 合価を決定するために使用される値づけ方法 | I16: - | J16: TS/M | K16: ● | L16: 設定不要(固定値) 設定値：""(空) | M16: 設定不要(固定値) 設定値：""(空) | N16: 未使用領域の認識。
A17: =A16+1 -> 14 | B17: EXT_PRC | C17: 合価 | D17: money | H17: 販売価格（特売の場合は特売価格、売価変更時は売価変更後の価格、その他の場合は「商品マスタ連携ファイル No.22 売価」）× 数量の金額を設定する。 | I17: 商品マスタ連携ファイル No.22 売価 × 数量 | J17: ignicaPOS | K17: ◎ | L17: 設定値：明細情報に対して課される合計価格 | M17: 設定値：明細情報に対して課される合計価格
A18: =A17+1 -> 15 | B18: EXT_CST | C18: 合計原価 | D18: money | F18: ● | H18: 合計原価。商品原価×数量の金額が入る。 | I18: 商品マスタ連携ファイル No.23 単位原価 No.26 原価率フラグ | J18: ignicaPOS | K18: ◎ | L18: 設定値：合計原価を設定 | M18: 設定値：合計原価を設定 | O18: *1.0
A19: =A18+1 -> 16 | B19: RTL_PRC | C19: 売価 | D19: money | I19: 商品マスタ連携ファイル No.22 売価 | J19: ignicaPOS | K19: ◎ | L19: 設定値：売価を設定 | M19: 設定値：売価を設定
A20: =A19+1 -> 17 | B20: ENTRY_MTHD | C20: 登録方法 | D20: smallint | H20: POSでの商品識別メソッドを識別するコードで、通常はマニュアル入力かスキャンかを区別します。 １：キーボード入力 ２：スキャナ入力 | I20: - | J20: ignicaPOS | K20: ◎ | L20: 設定値：入力方法に従い設定 １：キーボード入力 ２：スキャナ入力 | M20: 設定値：入力方法に従い設定 １：キーボード入力 ２：スキャナ入力
A21: =A20+1 -> 18 | B21: COMM_EMP_ID | C21: 担当従業員ＩＤ | D21: varchar | E21: 12 | F21: ● | H21: 商品販売に携わった従業員 | I21: - | J21: TS/M | K21: ● | L21: 設定不要(固定値) 設定値：""(空) | M21: 設定不要(固定値) 設定値：""(空) | N21: 未使用領域の認識。
A22: =A21+1 -> 19 | B22: ITM_MVMT_FG | C22: 売上集計加算判別 | D22: smallint | H22: TRUEの場合、アイテムは集計されます。運用中の在庫管理の動きが意味をなさない明細情報については、この属性はFALSEにすることもできます。 | I22: - | J22: TS/M | K22: ● | L22: 設定不要(固定値) 設定値：""(空) | M22: 設定不要(固定値) 設定値：""(空) | N22: 未使用領域の認識。
A23: =A22+1 -> 20 | B23: VOID_CD | C23: 取消コード | D23: smallint | H23: 明細をボイドにする理由を記述する数値コード。値0は、その詳細がボイドになっていないことを示します。 | I23: - | J23: TS/M | K23: ● | L23: 設定不要(固定値) 設定値：""(空) | M23: 設定不要(固定値) 設定値：""(空) | N23: 訂正明細は連携しない。
A24: =A23+1 -> 21 | B24: EVNT_ID | C24: イベントID | D24: varchar | E24: 6 | H24: 売上げ明細が対応するイベントコードを識別します。 | I24: - | J24: TS/M | K24: ● | L24: 設定不要(固定値) 設定値：""(空) | M24: 設定不要(固定値) 設定値：""(空) | N24: 未使用領域の認識。
A25: =A24+1 -> 22 | B25: RTN_REAS_CD | C25: 返品理由コード | D25: smallint | H25: 顧客が示した商品を返品する理由です。 ０：通常明細、返品取消明細 １：返品明細 ２：取消明細 ※返品明細の判定には使用できない。→GSFD_RTN_REAS_CDを参照。 | I25: - | J25: TS/M | K25: ● | L25: 設定不要(固定値) 設定値：""(空) | M25: 設定不要(固定値) 設定値：""(空) | N25: いなげやでは、返品取引がないため０固定 ０：通常明細, １：返品明細
A26: =A25+1 -> 23 | B26: RCPT_PRSNT_FG | C26: レシート有無 | D26: smallint | H26: ブール値。TRUEは、返品がレシートと一緒に受け付けられたことを示します。 | I26: - | J26: TS/M | K26: ● | L26: 設定不要(固定値) 設定値：""(空) | M26: 設定不要(固定値) 設定値：""(空) | N26: 未使用領域の認識。
A27: =A26+1 -> 24 | B27: PKG_OPEN_FG | C27: パッケージの開封 | D27: smallint | H27: ブール値。TRUEは、返品されたアイテムのパッケージングが破られていたことを示します。 | I27: - | J27: TS/M | K27: ● | L27: 設定不要(固定値) 設定値：""(空) | M27: 設定不要(固定値) 設定値：""(空) | N27: 未使用領域の認識。
A28: =A27+1 -> 25 | B28: LN_ITM_TS | C28: 商品明細日時 | D28: datetime | H28: 商品詳細が入力された日付と時間 | I28: - | J28: ignicaPOS | K28: 〇 | L28: 設定値：取引開始時刻を設定 9999-99-99 99:99:99.000 <例> 2021-02-04 10:4:57.000 | M28: 設定値：取引開始時刻を設定 9999-99-99 99:99:99.000 <例> 2021-02-04 10:4:57.000 | N28: 取引開始時刻を持っていない場合は取引終了時刻を設定する。
A29: =A28+1 -> 26 | B29: FOR_QTY | C29: 組合せ販売数量 | D29: smallint | F29: ● | H29: これはスプリットプライスに使用され、ForPriceフィールドに対応する数量を表します。ユニットタイプアイテムにだけ適用でき、デフォルトは1です。 | I29: - | J29: TS/M | K29: ● | L29: TSM側で設定となるため、設定不要（固定値） 設定値：""(空) | M29: TSM側で設定となるため、設定不要（固定値） 設定値：""(空)
A30: =A29+1 -> 27 | B30: PERPET_INV_CD | C30: 永続在庫管理コード | D30: smallint | F30: ● | H30: アイテムの売上げ／返品によって手持ち在庫を更新する必要があるかどうかと、その更新方法を識別します。 | I30: - | J30: TS/M | K30: ● | L30: 設定不要(固定値) 設定値：""(空) | M30: 設定不要(固定値) 設定値：""(空) | N30: 未使用領域の認識。
A31: =A30+1 -> 28 | B31: DMGD_CD | C31: 損傷コード | D31: smallint | F31: ● | H31: 返品されたアイテムが損傷状態にあるかどうか、または最終処分のために特別な処理を必要とするかどうかを識別します。 例：修復不能な損傷状態、在庫から除く。最終処分にマネージャの評価が必要。販売フロアに配置する前にクリーニングおよびプレスが必要。供給者として、損傷の原因を示すRTVを作成。 | I31: - | J31: TS/M | K31: ● | L31: 設定不要(固定値) 設定値：""(空) | M31: 設定不要(固定値) 設定値：""(空) | N31: 未使用領域の認識。
A32: =A31+1 -> 29 | B32: PLU_QUAL_TYP | C32: PLU属性種別 | D32: int | F32: ● | H32: PLU属性種別 | I32: - | J32: TS/M | K32: ● | L32: 設定不要(固定値) 設定値：""(空) | M32: 設定不要(固定値) 設定値：""(空) | N32: 未使用領域の認識。
A33: =A32+1 -> 30 | B33: LOC_STR_ID | C33: 在庫店舗番号 | D33: int | F33: ● | H33: 販売されるべき在庫がある店舗／倉庫を識別します。販売店舗が在庫店舗と別の場合だけ設定します。 | I33: 店舗番号 | J33: ignicaPOS | K33: ◎ | L33: 設定値：店舗番号×10000 | M33: 設定値：店舗番号×10000
A34: =A33+1 -> 31 | B34: GSFD_EXT_PROMO_CST | C34: 特売原価 | D34: money | F34: ● | H34: 特売原価を設定（1個当たりの原価） ※マークダウンの場合は、0を設定 | I34: 特売マスタ連携ファイル No.19 特売原価 No35 原価率フラグ | J34: ignicaPOS | K34: ◎ | L34: 設定値：特売原価を設定 | M34: 設定値：特売原価を設定
A35: =A34+1 -> 32 | B35: GSFD_SCAN_CODE | C35: スキャンコード（単品登録時） | D35: varchar | E35: 75 | F35: ● | H35: スキャンコード(生データ)。スキャン登録を行った場合のみ値が入る。 入力コードをそのまま格納し、セミコロンで区切る。 多段バーコードの場合は各段がセミコロンで区切られる。 例）JAN13の場合“4903080109181;” 例）書籍二段コードの場合“9784095060217;1910582028004;” 部門登録の場合は””(空)を設定する。 | I35: - | J35: ignicaPOS | K35: ◎ | L35: 設定値：スキャンコード+";"(セミコロン) | M35: 設定値：スキャンコード+";"(セミコロン) | O35: *1.0*1.1
A36: =A35+1 -> 33 | B36: GSFD_DIFFERENCE_PRICE | C36: 会員価格と一般価格の差額 | D36: money | F36: ● | H36: 会員価格と一般価格の差額（合価） | I36: - | J36: TS/M | K36: ● | L36: 設定不要(固定値) 設定値：""(空) | M36: 設定不要(固定値) 設定値：""(空) | N36: 会員価格は未使用の認識
A37: =A36+1 -> 34 | B37: GSFD_ENTRY_OPERATOR | C37: 本明細を登録した担当者コード | D37: varchar | E37: 12 | F37: ● | I37: 担当者マスタ連携ファイル No.6 担当者コード | J37: ignicaPOS | K37: ◎ | L37: 設定値：本明細を登録した担当者番号 | M37: 設定値：本明細を登録した担当者番号
A38: =A37+1 -> 35 | B38: GSFD_NONCASH_CD | D38: smallint | F38: ● | H38: 商品券対象数 | I38: - | J38: TS/M | K38: ● | L38: 設定不要(固定値) 設定値：""(空) | M38: 設定不要(固定値) 設定値：""(空) | N38: 未使用領域の認識。
A39: =A38+1 -> 36 | B39: GSFD_SAVE_EXT_PRC | D39: money | F39: ● | H39: 商品券対象額 | I39: - | J39: TS/M | K39: ● | L39: 設定不要(固定値) 設定値：""(空) | M39: 設定不要(固定値) 設定値：""(空) | N39: 未使用領域の認識。
A40: =A39+1 -> 37 | B40: GSFD_HSTR_FG | D40: smallint | F40: ● | H40: 履歴収集フラグ （0:対象としない、1:対象とする） | I40: - | J40: TS/M | K40: ● | L40: 設定不要(固定値) 設定値：""(空) | M40: 設定不要(固定値) 設定値：""(空) | N40: 未使用領域の認識。
A41: =A40+1 -> 38 | B41: GSFD_PNT_FG | C41: ポイント対象フラグ | D41: smallint | F41: ● | H41: ポイント倍率 いなげや様ではポイント倍率を設定する。 | I41: Satisfaの応答値を使用。 適用ポイント倍率. | J41: ignicaPOS | K41: 〇 | L41: 設定値：適用ポイント倍率を設定 | M41: 設定値：適用ポイント倍率を設定 | N41: GetCustomerByNumberASY呼び出しで連携。適用ポイント倍率<PBAI_QT> | O41: *1.1
A42: =A41+1 -> 39 | B42: GSFD_TB_RANK_FG | D42: smallint | F42: ● | H42: 倍率／付与識別区分（1:倍率、2:付与ポイント） | I42: - | J42: TS/M | K42: ● | L42: 設定不要(固定値) 設定値：""(空) | M42: 設定不要(固定値) 設定値：""(空) | N42: 未使用領域の認識。
A43: =A42+1 -> 40 | B43: GSFD_PNT_RATE | C43: ポイント倍率 | D43: float | F43: ● | H43: ポイント倍率 ポイント倍率を設定する。小数点以下第１位まで設定可能（99.9） | I43: - | J43: TS/M | K43: ● | L43: 設定不要(固定値) 設定値：""(空) | M43: 設定不要(固定値) 設定値：""(空) | N43: 未使用領域の認識。 | O43: *1.0
A44: =A43+1 -> 41 | B44: GSFD_TAX_TYPE | C44: 明細の税種別 | D44: smallint | F44: ● | H44: 1：外税2：内税3：非課税 明細の税種別 | I44: - | J44: ignicaPOS | K44: ◎ | L44: 設定値： 1：外税 2：内税 3：非課税 | M44: 設定値： 1：外税 2：内税 3：非課税 | N44: 商品マスタ連携ﾌｧｲﾙの税種別コードとは異なる項目。
A45: =A44+1 -> 42 | B45: GSFD_TAX_AMT | C45: 明細の税金額 | D45: money | F45: ● | H45: 明細の税金額。GSFD_TAX_TYPEの設定値によって以下の値が入る。 GSFD_TAX_TYPE 説明 1 按分した外税額 2 内税額 3 0固定 | I45: - | J45: ignicaPOS | K45: ◎ | L45: 設定値： GSFD_TAX_TYPEに従い下記の通りに設定 GSFD_TAX_TYPE=1：按分した外税額 GSFD_TAX_TYPE=2：内税額 GSFD_TAX_TYPE=3：0固定 | M45: 設定値： GSFD_TAX_TYPEに従い下記の通りに設定 GSFD_TAX_TYPE=1：按分した外税額 GSFD_TAX_TYPE=2：内税額 GSFD_TAX_TYPE=3：0固定
A46: =A45+1 -> 43 | B46: GSFD_RTN_REAS_CD | C46: 返品理由コード | D46: smallint | F46: ● | H46: 0：通常明細1：返品明細 | I46: - | J46: TS/M | K46: ● | L46: 設定不要(固定値) 設定値：""(空) | M46: 設定不要(固定値) 設定値：""(空) | N46: 返品取引なしのため0固定 0：通常明細1：返品明細
A47: =A46+1 -> 44 | B47: GSFD_DECIMAL_POINT | C47: 小数点以下の登録桁数 | D47: smallint | F47: ● | H47: 0：小数点以下なし1：小数点第１位2：小数点第２位 | I47: - | J47: TS/M | K47: ● | L47: 設定不要(固定値) 設定値：""(空) | M47: 設定不要(固定値) 設定値：""(空) | N47: 小数点入力は未使用の認識。
A48: =A47+1 -> 45 | B48: GSFD_SCAN_ID | C48: スキャンコードログ | D48: varchar | E48: 24 | F48: ● | H48: ※ＮＯＮ-ＰＬＵのとき、価格情報をゼロマスクする。 ※OPTION_ID:362000104が”0”（0マスク処理を行う）で、 ＮＯＮ-ＰＬＵのとき、ＣＤをゼロマスクする。 | I48: - | J48: TS/M | K48: ● | L48: 設定不要(固定値) 設定値：""(空) | M48: 設定不要(固定値) 設定値：""(空)
A49: =A48+1 -> 46 | B49: GSFD_FSP_DATA | D49: varchar | E49: 256 | F49: ● | I49: - | J49: TS/M | K49: ● | L49: 設定不要(固定値) 設定値：""(空) | M49: 設定不要(固定値) 設定値：""(空) | N49: FSP連携は無しと判断。
A50: =A49+1 -> 47 | B50: GSFD_SELLING_PRC | C50: 実行売価 | D50: money | F50: ● | H50: 特売系(期間特売、マークダウン、タイムサービス)の値引が存在した場合は特売後価格を設定する。存在しない場合は「No.16 売価」と同じ値を設定する。 | J50: ignicaPOS | K50: ◎ | L50: 設定値：標準価格または特売後価格 | M50: 設定値：標準価格または特売後価格
A51: =A50+1 -> 48 | B51: GSFD_CNCL_RSN_CD | C51: 取消・返品理由コード | D51: smallint | F51: ● | H51: 明細に対しての返品、取消の理由コードを設定 | I51: - | J51: TS/M | K51: ● | L51: 設定不要(固定値) 設定値：""(空) | M51: 設定不要(固定値) 設定値：""(空)
A52: =A51+1 -> 49 | B52: GSFD_PNT_RATE_ID | D52: smallint | F52: ● | I52: - | J52: TS/M | K52: ● | L52: 設定不要(固定値) 設定値：""(空) | M52: 設定不要(固定値) 設定値：""(空)
A53: =A52+1 -> 50 | B53: GSFD_RSTR_ITM_DATA | D53: varchar | E53: 255 | F53: ● | I53: - | J53: TS/M | K53: ● | L53: 設定不要(固定値) 設定値：""(空) | M53: 設定不要(固定値) 設定値：""(空) | N53: 通番修正で利用するデータ。
A54: =A53+1 -> 51 | B54: GSFD_CATALINA_COUPON_UCST_KSM | D54: smallint | F54: ● | I54: - | J54: TS/M | K54: ● | L54: 設定不要(固定値) 設定値：""(空) | M54: 設定不要(固定値) 設定値：""(空)
A55: =A54+1 -> 52 | B55: GSFD_DEPT_CODE | C55: 部門コード | D55: varchar | E55: 20 | F55: ● | I55: - | J55: TS/M | K55: ● | L55: TSM側で設定 設定値：""(空) | M55: TSM側で設定 設定値：""(空)
A56: =A55+1 -> 53 | B56: GSFD_MDSE_STRC_NBR1 | C56: 商品階層番号１ | D56: varchar | E56: 12 | F56: ● | I56: - | J56: TS/M | K56: ● | L56: TSM側で設定 設定値：""(空) | M56: TSM側で設定 設定値：""(空) | N56: 未使用領域の認識。
A57: =A56+1 -> 54 | B57: GSFD_MERCHANDISE_DESCR1 | C57: 商品階層名称１ | D57: varchar | E57: 60 | F57: ● | I57: - | J57: TS/M | K57: ● | L57: TSM側で設定 設定値：""(空) | M57: TSM側で設定 設定値：""(空) | N57: 未使用領域の認識。
A58: =A57+1 -> 55 | B58: GSFD_MDSE_STRC_NBR2 | C58: 商品階層番号２ | D58: varchar | E58: 12 | F58: ● | I58: - | J58: TS/M | K58: ● | L58: TSM側で設定 設定値：""(空) | M58: TSM側で設定 設定値：""(空) | N58: 未使用領域の認識。
A59: =A58+1 -> 56 | B59: GSFD_MERCHANDISE_DESCR2 | C59: 商品階層名称２ | D59: varchar | E59: 60 | F59: ● | I59: - | J59: TS/M | K59: ● | L59: TSM側で設定 設定値：""(空) | M59: TSM側で設定 設定値：""(空) | N59: 未使用領域の認識。
A60: =A59+1 -> 57 | B60: GSFD_MDSE_STRC_NBR3 | C60: 商品階層番号３ | D60: varchar | E60: 12 | F60: ● | I60: - | J60: TS/M | K60: ● | L60: TSM側で設定 設定値：""(空) | M60: TSM側で設定 設定値：""(空) | N60: 未使用領域の認識。
A61: =A60+1 -> 58 | B61: GSFD_MERCHANDISE_DESCR3 | C61: 商品階層名称３ | D61: varchar | E61: 60 | F61: ● | I61: - | J61: TS/M | K61: ● | L61: TSM側で設定 設定値：""(空) | M61: TSM側で設定 設定値：""(空) | N61: 未使用領域の認識。
A62: =A61+1 -> 59 | B62: GSFD_MDSE_STRC_NBR4 | C62: 商品階層番号４ | D62: varchar | E62: 12 | F62: ● | I62: - | J62: TS/M | K62: ● | L62: TSM側で設定 設定値：""(空) | M62: TSM側で設定 設定値：""(空) | N62: 未使用領域の認識。
A63: =A62+1 -> 60 | B63: GSFD_MERCHANDISE_DESCR4 | C63: 商品階層名称４ | D63: varchar | E63: 60 | F63: ● | I63: - | J63: TS/M | K63: ● | L63: TSM側で設定 設定値：""(空) | M63: TSM側で設定 設定値：""(空) | N63: 未使用領域の認識。
A64: =A63+1 -> 61 | B64: GSFD_MDSE_STRC_NBR5 | C64: 商品階層番号５ | D64: varchar | E64: 12 | F64: ● | I64: - | J64: TS/M | K64: ● | L64: TSM側で設定 設定値：""(空) | M64: TSM側で設定 設定値：""(空) | N64: 未使用領域の認識。
A65: =A64+1 -> 62 | B65: GSFD_MERCHANDISE_DESCR5 | C65: 商品階層名称５ | D65: varchar | E65: 60 | F65: ● | I65: - | J65: TS/M | K65: ● | L65: TSM側で設定 設定値：""(空) | M65: TSM側で設定 設定値：""(空) | N65: 未使用領域の認識。
A66: =A65+1 -> 63 | B66: GSFD_MDSE_STRC_NBR6 | C66: 商品階層番号６ | D66: varchar | E66: 12 | F66: ● | I66: - | J66: TS/M | K66: ● | L66: TSM側で設定 設定値：""(空) | M66: TSM側で設定 設定値：""(空) | N66: 未使用領域の認識。
A67: =A66+1 -> 64 | B67: GSFD_MERCHANDISE_DESCR6 | C67: 商品階層名称６ | D67: varchar | E67: 60 | F67: ● | I67: - | J67: TS/M | K67: ● | L67: TSM側で設定 設定値：""(空) | M67: TSM側で設定 設定値：""(空) | N67: 未使用領域の認識。
... A74: =A73+1 -> 71 | B74: GSFD_PLU_DSPL_DESCR | C74: 単品名称 | D74: varchar | E74: 80 | F74: ● | I74: 商品マスタ連携ファイル No.5 単品名称 | J74: ignicaPOS | K74: 〇 | L74: 設定値：商品マスタ連携ファイルから取得して設定 | M74: 設定値：商品マスタ連携ファイルから取得して設定 | N74: 全店速報サーバで使用
A75: =A74+1 -> 72 | B75: GSFD_PLU_TAXBLTY_CD | C75: 明細の税種別コード | D75: smallint | F75: ● | H75: 明細の税種別コード | I75: 商品マスタ連携ファイル No.4 税種別コード 注）但し、内税の場合は、"99"を設定する。 | J75: ignicaPOS | K75: 〇 | L75: 設定値：商品マスタ連携ファイルから取得して設定 | M75: 設定値：商品マスタ連携ファイルから取得して設定 | N75: 全店速報サーバで使用
A76: =A75+1 -> 73 | B76: GSFD_PLU_QUAL_TYP_DESCR | D76: varchar | E76: 60 | F76: ● | I76: - | J76: TS/M | K76: ● | L76: TSM側で設定 設定値：""(空) | M76: TSM側で設定 設定値：""(空) | N76: TSM側で設定 No6.PLUIDを元に設定する。 "PLU属性 " + No6.PLUIDの桁目から4桁を抜き出して設定。
A77: =A76+1 -> 74 | B77: GSFD_ISSUED_OFFCL_RCPT | D77: smallint | F77: ● | I77: - | J77: TS/M | K77: ● | L77: 設定不要(固定値) 設定値：""(空) | M77: 設定不要(固定値) 設定値：""(空)
A78: =A77+1 -> 75 | B78: GSFD_GIFT_START | D78: varchar | E78: 20 | F78: ● | I78: - | J78: TS/M | K78: ● | L78: 設定不要(固定値) 設定値：""(空) | M78: 設定不要(固定値) 設定値：""(空) | N78: 商品券販売明細の連携は不要？
A79: =A78+1 -> 76 | B79: GSFD_GIFT_END | D79: varchar | E79: 20 | F79: ● | I79: - | J79: TS/M | K79: ● | L79: 設定不要(固定値) 設定値：""(空) | M79: 設定不要(固定値) 設定値：""(空) | N79: 商品券販売明細の連携は不要？
A80: =A79+1 -> 77 | B80: GSFD_ADD_PNT | C80: 単品付与ポイント | D80: int | F80: ● | I80: Satisfaの応答値を使用。 ポイントプラス数を設定 | J80: ignicaPOS | K80: 〇 | L80: 設定値：ポイントプラス数を設定 | M80: 設定値：ポイントプラス数を設定 | N80: GetCustomerByNumberASY呼び出しで連携。 ポイントプラス数<PPLUS_QT>
A81: =A80+1 -> 78 | B81: GSFD_GL_ACCT_ID | D81: smallint | F81: ● | I81: - | J81: TS/M | K81: ● | L81: 設定不要(固定値) 設定値：""(空) | M81: 設定不要(固定値) 設定値：""(空) | N81: 掛入金対応は不要
A82: =A81+1 -> 79 | B82: GSFD_FSP_DATA2 | D82: varchar | E82: 128 | F82: ● | I82: - | J82: TS/M | K82: ● | L82: 設定不要(固定値) 設定値：""(空) | M82: 設定不要(固定値) 設定値：""(空) | N82: FSP連携は無しと判断。
A83: =A82+1 -> 80 | B83: GSFD_SUM_EVNT_ID | D83: varchar | E83: 240 | F83: ● | I83: - | J83: TS/M | K83: ● | L83: 設定不要(固定値) 設定値：""(空) | M83: 設定不要(固定値) 設定値：""(空)
A84: =A83+1 -> 81 | B84: GSFD_SUM_EVNT_NO | D84: varchar | E84: 240 | F84: ● | I84: - | J84: TS/M | K84: ● | L84: 設定不要(固定値) 設定値：""(空) | M84: 設定不要(固定値) 設定値：""(空)
A85: =A84+1 -> 82 | B85: GSFD_FSP_ITMPNT_PRINM | D85: varchar | E85: 32 | F85: ● | I85: - | J85: TS/M | K85: ● | L85: 設定不要(固定値) 設定値：""(空) | M85: 設定不要(固定値) 設定値：""(空)
A86: =A85+1 -> 83 | B86: GSFD_VOID_ITM_CNT | D86: float | F86: ● | I86: - | J86: TS/M | K86: ● | L86: 設定不要(固定値) 設定値：""(空) | M86: 設定不要(固定値) 設定値：""(空)
A87: =A86+1 -> 84 | B87: GSFD_VOID_ITM_AMT | D87: money | F87: ● | I87: - | J87: TS/M | K87: ● | L87: 設定不要(固定値) 設定値：""(空) | M87: 設定不要(固定値) 設定値：""(空)
A88: =A87+1 -> 85 | B88: GSFD_OVRD_PRC | D88: money | F88: ● | I88: - | J88: TS/M | K88: ● | L88: 設定不要(固定値) 設定値：""(空) | M88: 設定不要(固定値) 設定値：""(空)
A89: =A88+1 -> 86 | B89: GSFD_UNT_PRC | C89: 販売単位価格 | D89: money | I89: 商品マスタ連携ファイル No.36 販売単位価格（No.22 売価と同じ値）を設定 | J89: ignicaPOS | K89: ◎ | L89: 設定値：販売単位価格を設定 | M89: 設定値：販売単位価格を設定 | N89: 店舗分析用
A90: =A89+1 -> 87 | B90: GSFD_TAX_FR_STAT | D90: smallint | I90: - | J90: TS/M | K90: ● | L90: 設定不要(固定値) 設定値：""(空) | M90: 設定不要(固定値) 設定値：""(空) | N90: 免税は不要と判断
A91: =A90+1 -> 88 | B91: GSFD_TAX_FR_AMT | D91: money | I91: - | J91: TS/M | K91: ● | L91: 設定不要(固定値) 設定値：""(空) | M91: 設定不要(固定値) 設定値：""(空) | N91: 免税は不要と判断
A92: =A91+1 -> 89 | B92: GSFD_REDUCEDTAX_CODE | C92: 税率変更後の税コード | D92: smallint | F92: ● | I92: - | J92: TS/M | K92: ● | L92: 設定不要(固定値) 設定値：""(空) | M92: 設定不要(固定値) 設定値：""(空) | N92: 税率変更は未使用の認識
A93: =A92+1 -> 90 | B93: GSFD_REDUCEDTAX_ORG_CODE | C93: 税率変更前の税コード | D93: smallint | F93: ● | I93: - | J93: TS/M | K93: ● | L93: 設定不要(固定値) 設定値：""(空) | M93: 設定不要(固定値) 設定値：""(空) | N93: 税率変更は未使用の認識
A94: =A93+1 -> 91 | B94: GSFD_DEPT_RATE | C94: 部門別倍率 | D94: float | F94: ● | H94: 部門別ポイント倍率を設定 | I94: - | J94: TS/M | K94: ● | L94: 設定不要(固定値) 設定値：""(空) | M94: 設定不要(固定値) 設定値：""(空)
A95: =A94+1 -> 92 | B95: GSFD_POINT_GRANT_RATE | D95: varcha | E95: 4 | F95: ● | I95: - | J95: TS/M | K95: ● | L95: 設定不要(固定値) 設定値：""(空) | M95: 設定不要(固定値) 設定値：""(空)
A96: =A95+1 -> 93 | B96: GSFD_CHG_MANUAL_PER | D96: float | I96: - | J96: TS/M | K96: ● | L96: 設定不要(固定値) 設定値：""(空) | M96: 設定不要(固定値) 設定値：""(空)
A97: =A96+1 -> 94 | B97: GSFD_TAX_ENTRY_DATE | D97: datetime | F97: ● | I97: - | J97: TS/M | K97: ● | L97: 設定不要(固定値) 設定値：""(空) | M97: 設定不要(固定値) 設定値：""(空)
A98: =A97+1 -> 95 | B98: GSFD_ORG_UNIT_PRICE | D98: money | I98: - | J98: TS/M | K98: ● | L98: 設定不要(固定値) 設定値：""(空) | M98: 設定不要(固定値) 設定値：""(空) | N98: 通番修正で利用するデータ。不要。
A99: =A98+1 -> 96 | B99: GSFD_DIFF_VAT | D99: money | I99: - | J99: TS/M | K99: ● | L99: 設定不要(固定値) 設定値：""(空) | M99: 設定不要(固定値) 設定値：""(空) | N99: 通番修正で利用するデータ。不要。
A100: =A99+1 -> 97 | B100: GSFD_TENDER_PRO_RATE | C100: 内税額の再計算による差額 | D100: varchar | E100: 240 | F100: ● | I100: - | J100: TS/M | K100: ● | L100: 設定不要(固定値) 設定値：""(空) | M100: 設定不要(固定値) 設定値：""(空)
A101: =A100+1 -> 98 | B101: GSFD_GIFT_CERT_CNT | D101: smallint | I101: - | J101: TS/M | K101: ● | L101: 設定不要(固定値) 設定値：""(空) | M101: 設定不要(固定値) 設定値：""(空)

Sheet LN_DISCOUNT
A1: トラン連携ファイルレイアウト | C1: 対象テーブル：LN_DISCOUNT 形式：TSV
A2: NO | B2: 項目 | H2: 説明 | I2: 取得元マスタ項目 | J2: 設定元 | K2: 一次開発 必須項目 | L2: ignicaPOS・Scan&Go設定値 | N2: 備考
B3: カラム名称 | C3: 日本語名称 | D3: 型 | E3: サイズ | F3: NULL 許可 | G3: KEY | L3: 売上 | M3: 売上中止
A4: 1 | B4: TRAN_LN_NBR | C4: 取引明細番号 | D4: smallint | G4: PK | H4: 取引の明細レベルに割当てられるライン番号 | I4: - | J4: ignicaPOS | K4: ◎ | L4: 設定値： 1取引内の下記テーブルのレコードの同一カラム名に通し番号を振る(番号が重複しなければ順不同で構わない) ・LN_DETAIL ・LN_DISCOUNT ・TRANSACTION_TAX ・TRANSACTION_TENDER | M4: 設定値： 1取引内の下記テーブルのレコードの同一カラム名に通し番号を振る(番号が重複しなければ順不同で構わない) ・LN_DETAIL ・LN_DISCOUNT ・TRANSACTION_TAX ・TRANSACTION_TENDER
A5: =A4+1 -> 2 | B5: TRAN_ID | C5: 取引通番 | D5: int | G5: PK | H5: 取引の識別子 | I5: - | J5: TS/M | K5: ● | L5: TSM側で設定となるため、設定不要（固定値） 設定値：""(空) | M5: TSM側で設定となるため、設定不要（固定値） 設定値：""(空)
A6: =A5+1 -> 3 | B6: STR_ID | C6: 店舗番号 | D6: int | G6: PK | I6: 店舗番号 | J6: ignicaPOS | K6: ◎ | L6: 設定値：店舗番号×10000 | M6: 設定値：店舗番号×10000
A7: =A6+1 -> 4 | B7: DISC_MTHD | C7: ディスカウント方法 | D7: smallint | H7: 値引方法 １：額値引 ２：％値引 ５：バンドル・ミックス・ペアマッチ ６：売価変更値引 １１：合計額変更値引 １３：小計額値引、小計％値引 １４：小計％値引 | J7: ignicaPOS | K7: ◎ | L7: 設定値：値引方法を設定 | M7: 設定値：値引方法を設定 | O7: *1.6
A8: =A7+1 -> 5 | B8: DISC_AMT | C8: ディスカウント金額 | D8: money | F8: ● | I8: - | J8: ignicaPOS | K8: ◎ | L8: 設定値：値引金額を設定 ※値引対象の全明細の値引額を設定する。 ※マークダウン（会員）・マークダウン（一般）・タイムサービス（会員）・タイムサービス（一般）・特売（会員）・特売（一般）の場合は、0を設定する。 | M8: 設定値：値引金額を設定 ※値引対象の全明細の値引額を設定する。 ※マークダウン（会員）・マークダウン（一般）・タイムサービス（会員）・タイムサービス（一般）・特売（会員）・特売（一般）の場合は、0を設定する。
A9: =A8+1 -> 6 | B9: DISC_VALUE | C9: ディスカウント値 | D9: float | F9: ● | H9: 値引値 値引方法により格納される値が変わる 額値引：値引額 ％値引：値引率 売価変更：新売価 | I9: ①マークダウン（会員）・マークダウン（一般）・タイムサービス（会員）・タイムサービス（一般）・特売（会員）・特売（一般）の場合、値引値を設定 ②バンドル・ミックス（会員）・バンドル・ミックス（一般）・ペアマッチ（会員）・ペアマッチ（一般）の場合、0を設定 ③中分類自動値引除外・中分類自動値引・大分類自動値引除外・大分類自動値引の場合、値引値を設定 ④その他の値引は値引操作に従い下記を設定 ・値引率の場合は値引率を設定する。 ・値引額の場合は値引額を設定する。 ・売価変更の場合は新売価を設定する。 ※値引バーコードの場合はバーコードから取得した値を設定する。 ※小計値引(%引)・小計自動割引(%引)の場合、値引額を算出して、小計値引(額引)として値引を行うため、DISC_VALUEは算出した小計値引額を設定する。値引率はDISC_VALUE2に設定する。 | J9: ignicaPOS | K9: ◎ | L9: 設定値：値引値 | M9: 設定値：値引値
A10: =A9+1 -> 7 | B10: DISC_ID | C10: ディスカウントＩＤ | D10: int | F10: ● | G10: FK | H10: ディスカウントＩＤ マニュアル値引時は以下の値が格納される。自動値引時はサーバでの自動採番。 １：明細額値引 ２：明細％値引 ６：売価変更値引 １１：合計額変更値引 １３：小計額値引 １４：小計％値引 １５：セット販売 ２０：ポイント割り戻し値引 995:FSP単品値引 996:FSP部門値引 １１６：値引バーコード（値引フラグ１：売価） １１１：値引バーコード（値引フラグ２：値引） １１２：値引バーコード（値引フラグ３：割引） １２６：値引バーコード（値引フラグ４：カット品（売価）） １２１：値引バーコード（値引フラグ５：クーポン値引額） １２２：値引バーコード（値引フラグ６：クーポン値引率） | I10: ①マークダウン（会員）・マークダウン（一般）・タイムサービス（会員）・タイムサービス（一般）・特売（会員）・特売（一般）の場合、「「特売マスタ連携ファイル No.50 内部ディスカウントID」を設定 ②バンドル・ミックス（会員）・バンドル・ミックス（一般）・ペアマッチ（会員）・ペアマッチ（一般）の場合、「組合せマスタ連携ファイル No.167 内部ディスカウントID」を設定 ③中分類自動値引除外・中分類自動値引・大分類自動値引除外・大分類自動値引の場合、「商品階層自動値引きマスタ連携 No.33 内部ディスカウントID」を設定 ④値引バーコードの場合は下記を設定 １１６：値引バーコード（値引フラグ１：売価） １１１：値引バーコード（値引フラグ２：値引） １１２：値引バーコード（値引フラグ３：割引） １２６：値引バーコード（値引フラグ４：カット品（売価）） １２１：値引バーコード（値引フラグ５：クーポン値引額） １２２：値引バーコード（値引フラグ６：クーポン値引率） ⑤その他の値引は値引操作に従い下記を設定 マニュアル値引時は以下の値を格納する。 １：明細額値引 ２：明細％値引 ６：売価変更値引 １１：合計額変更値引 １３：小計額値引 １４：小計％値引 １５：セット販売 ２０：ポイント割り戻し値引 ※小計値引(%引)・小計自動割引(%引)の場合は、まず小計値引額を算出して、小計値引(額引)として値引を行うため、DISC_IDは"１３：小計額値引"を設定する | J10: ignicaPOS | K10: ◎ | L10: 設定値：ディスカウントＩＤを設定 | M10: 設定値：ディスカウントＩＤを設定 | O10: *1.0、*1.5
A11: =A10+1 -> 8 | B11: VOID_CD | C11: 取消コード | D11: smallint | H11: 値引中止コード ０以外で値引が中止されたことを示す | I11: - | J11: TS/M | K11: ● | L11: 設定不要(固定値) 設定値："" | M11: 設定不要(固定値) 設定値："" | N11: 訂正明細は引き継がない。
A12: =A11+1 -> 9 | B12: DISC_ACCT | C12: ディスカウント会計科目 | D12: varchar | E12: 24 | F12: ● | G12: FK | H12: ディスカウント金額が適用されるG/Lアカウント、またはそれを表す識別子 | I12: - | J12: TS/M | K12: ● | L12: 設定不要(固定値) 設定値："" | M12: 設定不要(固定値) 設定値：""
A13: =A12+1 -> 10 | B13: DG_ID | C13: ディスカウントグループＩＤ | D13: varchar | E13: 12 | F13: ● | G13: FK | H13: ディスカウントに対応するDiscountGroupを識別します。 | I13: - | J13: ignicaPOS | K13: ◎ | L13: 設定値：会員なら"MemberShip"、一般なら""を設定。 | M13: 設定値：会員なら"MemberShip"、一般なら""を設定。 | N13: ignicaPOS側で会員／一般の識別を返却してもらい、"MemberShip" Or "" の設定を行う。
A14: =A13+1 -> 11 | B14: EVNT_ID | C14: イベントコード | D14: varchar | E14: 6 | F14: ● | G14: FK | H14: ディスカウントに対応するイベントを識別します。 | I14: ①マークダウン（会員）・マークダウン（一般）・タイムサービス（会員）・タイムサービス（一般）・特売（会員）・特売（一般）の場合、「特売マスタ連携ファイル No.51 内部イベントコード」を設定 ②バンドル・ミックス（会員）・バンドル・ミックス（一般）・ペアマッチ（会員）・ペアマッチ（一般）の場合、「組合せマスタ連携ファイル No.168 内部イベントコード」を設定 ③中分類自動値引除外・中分類自動値引・大分類自動値引除外・大分類自動値引の場合、「商品階層自動値引きマスタ連携 No.35 内部イベントコード」を設定 ④その他の値引は""を設定 | J14: ignicaPOS | K14: ◎ | L14: 設定値：対象の値引の内部イベントコードを設定 | M14: 設定値：対象の値引の内部イベントコードを設定 | O14: *1.10
A15: =A14+1 -> 12 | B15: DISC_CLSS_ID | C15: ディスカウントクラスＩＤ | D15: int | F15: ● | G15: FK | H15: ディスカウントクラスＩＤ 会員 / 一般 91110/91111: マークダウン 91120/91121: タイムサービス 91140/91141: 期間特売 91210 : セット販売 91220 : マニュアル明細値引 91315/91316: バンドル・ミックスマッチ 91317/91318: ペアマッチ 91321/91322: メーカー自動 91323/91324: クラス自動 91325/91326: 部門自動 91327/91328: 全品自動 91329/91330: 小計自動 91400 : マニュアル小計値引/さんにち割引 91402 : マニュアル合計額値引 92101 : FSP単品値引 92102 : FSP部門値引 | I15: ①マークダウン（会員）・マークダウン（一般）・タイムサービス（会員）・タイムサービス（一般）・特売（会員）・特売（一般）の場合、「特売マスタ連携ファイル No.49 内部ディスカウントクラスID」を設定 ②バンドル・ミックス（会員）・バンドル・ミックス（一般）・ペアマッチ（会員）・ペアマッチ（一般）の場合、「組合せマスタ連携ファイル No.166 内部ディスカウントクラスID」を設定 ③中分類自動値引除外・中分類自動値引・大分類自動値引除外・大分類自動値引の場合、「商品階層自動値引きマスタ連携 No.6 内部ディスカウントクラスID」を設定 ④その他の値引は値引操作に従い値引クラスコード（値引分類）を設定 | J15: ignicaPOS | K15: ◎ | L15: 設定値：対象の値引の内部ディスカウントクラスIDを設定 | M15: 設定値：対象の値引の内部ディスカウントクラスIDを設定 | O15: *1.6
A16: =A15+1 -> 13 | B16: EMP_DISC_CD | C16: 従業員ディスカウントコード | D16: smallint | F16: ● | H16: LineDiscountが従業員ディスカウントのためのものかどうかを識別します。 | J16: TS/M | K16: ● | L16: 設定不要(固定値) 設定値："" | M16: 設定不要(固定値) 設定値："" | N16: 未使用領域の認識。
A17: =A16+1 -> 14 | B17: GSFD_DISC_REASON_CODE | C17: 値引理由コード | D17: smallint | F17: ● | H17: 値引き理由コード 値引理由コード登録時に設定される | J17: TS/M | K17: ● | L17: 設定不要(固定値) 設定値："" | M17: 設定不要(固定値) 設定値："" | N17: 値引理由は未使用の認識
A18: =A17+1 -> 15 | B18: GSFD_EVNT_NBR | C18: 企画No | D18: varchar | E18: 7 | F18: ● | I18: ①マークダウン（会員）・マークダウン（一般）・タイムサービス（会員）・タイムサービス（一般）・特売（会員）・特売（一般）の場合、「特売マスタ連携ファイル No.3 企画No.」を設定 ②バンドル・ミックス（会員）・バンドル・ミックス（一般）・ペアマッチ（会員）・ペアマッチ（一般）の場合、「組合せマスタ連携ファイル No.4 企画No.」を設定 ③中分類自動値引除外・中分類自動値引・大分類自動値引除外・大分類自動値引の場合、""を設定 ④その他の値引は""を設定 | J18: ignicaPOS | K18: ◎ | L18: 設定値：対象の値引の企画No.を設定 | M18: 設定値：対象の値引の企画No.を設定 | O18: *1.0
A19: =A18+1 -> 16 | B19: GSFD_EVENT_CST_DESCR | D19: varchar | E19: 60 | F19: ● | J19: TS/M | K19: ● | L19: 設定不要(固定値) | M19: 設定不要(固定値) | N19: 未使用領域の認識。
A20: =A19+1 -> 17 | B20: GSFD_DISCOUNT_ITM_LIMIT_INIT | D20: float | I20: 0を設定 ※限定販売のため導入ユーザー使用時に個別対応 | J20: TS/M | K20: ● | L20: TSM側で設定となるため、設定不要（固定値） 設定値：""(空) | M20: TSM側で設定となるため、設定不要（固定値） 設定値：""(空) | N20: 限定販売
A21: =A20+1 -> 18 | B21: GSFD_DISCOUNT_ITM_LIMIT | D21: float | I21: 0を設定 ※限定販売のため導入ユーザー使用時に個別対応 | J21: TS/M | K21: ● | L21: TSM側で設定となるため、設定不要（固定値） 設定値：""(空) | M21: TSM側で設定となるため、設定不要（固定値） 設定値：""(空) | N21: 限定販売
A22: =A21+1 -> 19 | B22: GSFD_DISCOUNT_PRE_KEYCODE | D22: int | F22: ● | I22: 0を設定 | J22: TS/M | K22: ● | L22: 設定不要(固定値) 設定値："" | M22: 設定不要(固定値) 設定値："" | N22: 出資金は対応不要
A23: =A22+1 -> 20 | B23: GSFD_DISCOUNT_ITM_PROMO_LMT | D23: float | I23: 0を設定 | J23: TS/M | K23: ● | L23: 設定不要(固定値) 設定値："" | M23: 設定不要(固定値) 設定値："" | N23: 限定販売 未使用領域の認識。
A24: =A23+1 -> 21 | B24: GSFD_CUPON_CODE | D24: varchar | E24: 26 | F24: ● | I24: 空文字を設定 | J24: TS/M | K24: ● | L24: 設定不要(固定値) 設定値："" | M24: 設定不要(固定値) 設定値：""
A25: =A24+1 -> 22 | B25: GSFD_DMSEAL | D25: varchar | E25: 15 | F25: ● | I25: 空文字を設定 | J25: TS/M | K25: ● | L25: 設定不要(固定値) 設定値："" | M25: 設定不要(固定値) 設定値：""
A26: =A25+1 -> 23 | B26: GSFD_MD_DIFF_AMT | D26: money | I26: 0を設定 | J26: TS/M | K26: ● | L26: 設定不要(固定値) 設定値："" | M26: 設定不要(固定値) 設定値：""
A27: =A26+1 -> 24 | B27: GSFD_COMBO_BMP | D27: smallint | F27: ● | I27: 0を設定 | J27: TS/M | K27: ● | L27: 設定不要(固定値) 設定値："" | M27: 設定不要(固定値) 設定値：""
A28: =A27+1 -> 25 | B28: GSFD_RECEIPT_COUPON | D28: varchar | E28: 26 | F28: ● | I28: 空文字を設定 | J28: TS/M | K28: ● | L28: 設定不要(固定値) 設定値："" | M28: 設定不要(固定値) 設定値：""
A29: =A28+1 -> 26 | B29: DISC_VALUE2 | C29: ディスカウント値2 | D29: float | F29: ● | H29: 小計値引(%引)・小計自動割引(%引)の場合、割引率を設定する | I29: 小計値引(%引)・小計自動割引(%引)の時、値引率を設定。 | J29: ignicaPOS | K29: ◎ | L29: 設定値：小計値引(%引)の時、値引率を設定。 | M29: 設定値：小計値引(%引)の時、値引率を設定。
A30: =A29+1 -> 27 | B30: GSFD_STEP_INFO | C30: バンドルの成立ステップ情報 | D30: varchar | E30: 18 | F30: ● | H30: BMPの時、多段設定の段数を設定する。 | J30: ignicaPOS | K30: 〇 | L30: 設定値：BMPの時、BMPの成立情報を"|"で区切り設定。 2段目以降の設定がある場合は","で区切って段数分を設定。 設定値：99999(成立個数 Or 成立組数) + "|" + 99999999(成立金額) (2段目がある場合) + "," + 99999(成立個数 Or 成立組数) + "|" + 99999999(成立金額) (3段目以降がある場合は同様に繰り返し設定) ※バンドルの場合は成立個数、ペアの場合は成立組数 <例1> バンドルミックスマッチのマスタ設定が 1段：3個 \300 のみの場合 設定値 3|300 <例2> バンドルミックスマッチのマスタ設定が 1段：2個 \220、2段：4個 \400の場合 設定値 2|220,4|400 | M30: 設定値：BMPの時、BMPの成立情報を"|"で区切り設定。 2段目以降の設定がある場合は","で区切って段数分を設定。 設定値：99999(成立個数 Or 成立組数) + "|" + 99999999(成立金額) (2段目がある場合) + "," + 99999(成立個数 Or 成立組数) + "|" + 99999999(成立金額) (3段目以降がある場合は同様に繰り返し設定) ※バンドルの場合は成立個数、ペアの場合は成立組数 <例1> バンドルミックスマッチのマスタ設定が 1段：3個 \300 のみの場合 設定値 3|300 <例2> バンドルミックスマッチのマスタ設定が 1段：2個 \220、2段：4個 \400の場合 設定値 2|220,4|400 | O30: *1.5

Sheet TRANSACTION_TAX
A1: トラン連携ファイルレイアウト | C1: 対象テーブル：TRANSACTION_TAX 形式：TSV
A2: NO | B2: 項目 | H2: 説明 | I2: 取得元マスタ項目 | J2: 設定元 | K2: 一次開発 必須項目 | L2: ignicaPOS・Scan&Go設定値 | N2: 備考
B3: カラム名称 | C3: 日本語名称 | D3: 型 | E3: サイズ | F3: NULL 許可 | G3: KEY | L3: 売上 | M3: 売上中止
A4: 1 | B4: TRAN_ID | C4: 取引通番 | D4: int | G4: PK | H4: 取引の識別子 | I4: - | J4: TS/M | K4: ● | L4: TSM側で設定となるため、設定不要（固定値） 設定値：""(空) | M4: TSM側で設定となるため、設定不要（固定値） 設定値：""(空)
A5: =A4+1 -> 2 | B5: TRAN_LN_NBR | C5: 取引明細番号 | D5: smallint | G5: PK | H5: 取引の明細レベルに割当てられるライン番号 | I5: - | J5: ignicaPOS | K5: ◎ | L5: 設定値： 1取引内の下記テーブルのレコードの同一カラム名に通し番号を振る(番号が重複しなければ順不同で構わない) ・LN_DETAIL ・LN_DISCOUNT ・TRANSACTION_TAX ・TRANSACTION_TENDER | M5: 設定値： 1取引内の下記テーブルのレコードの同一カラム名に通し番号を振る(番号が重複しなければ順不同で構わない) ・LN_DETAIL ・LN_DISCOUNT ・TRANSACTION_TAX ・TRANSACTION_TENDER
A6: =A5+1 -> 3 | B6: STR_ID | C6: 店舗番号 | D6: int | G6: PK | I6: 店舗番号 | J6: ignicaPOS | K6: ◎ | L6: 設定値：店舗番号×10000 | M6: 設定値：店舗番号×10000
A7: =A6+1 -> 4 | B7: TAX_CD | C7: 税種別コード | D7: smallint | F7: ● | I7: 商品マスタ連携ファイル No.4 税種別コード | J7: ignicaPOS | K7: ◎ | L7: 設定値： 税種別コードを設定 | M7: 設定値： 税種別コードを設定
A8: =A7+1 -> 5 | B8: TAX_MODIF | C8: 税変更コード | D8: smallint | F8: ● | H8: 内税商品を税率変更(10%⇒8%、8%⇒10%等）した場合は5、それ以外は1を設定する | I8: - | J8: ignicaPOS | K8: ◎ | L8: 設定値：1 or 5 ※内税商品を税率変更(10%⇒8%、8%⇒10%等）した場合は5、それ以外は1を設定する | M8: 設定値：1 or 5 ※内税商品を税率変更(10%⇒8%、8%⇒10%等）した場合は5、それ以外は1を設定する
A9: =A8+1 -> 6 | B9: TAX_AMT | C9: 税金総額 | D9: money | I9: - | J9: ignicaPOS | K9: ◎ | L9: 設定値：外税額を設定 | M9: 設定値：外税額を設定
A10: =A9+1 -> 7 | B10: VOID_CD | C10: 取消コード | D10: smallint | H10: 税金がボイドになった場合は、ゼロ以外の値に設定します。 | I10: - | J10: TS/M | K10: ● | L10: 設定不要(固定値) 設定値："" | M10: 設定不要(固定値) 設定値："" | N10: 取消明細はignicaPOS側から連携しない
A11: =A10+1 -> 8 | B11: VAT_AMT | C11: 内税総額 | D11: money | F11: ● | H11: 取引に対する累加の内税を示します。 | I11: - | J11: ignicaPOS | K11: ◎ | L11: 設定値：内税の総額を設定 ※TAX_CD=99のレコードは0 | M11: 設定値：内税の総額を設定 ※TAX_CD=99のレコードは0
A12: =A11+1 -> 9 | B12: VATBL_AMT | C12: 内税金額 | D12: money | F12: ● | H12: 内税扱い商品の売上額（内税抜き） | I12: - | J12: ignicaPOS | K12: ◎ | L12: 設定値：内税扱い商品の売上の総額（内税抜き） ※TAX_CD=99のレコードは0 | M12: 設定値：内税扱い商品の売上の総額（内税抜き） ※TAX_CD=99のレコードは0
A13: =A12+1 -> 10 | B13: TAXBLE_AMT | C13: 課税対象金額 | D13: money | H13: 商品売上額（外税抜き、内税込み） | I13: - | J13: ignicaPOS | K13: ◎ | L13: 設定値：商品売上額（外税抜き、内税込み）を設定 ※TAX_CD=99のレコードは 全内税の合計課税対象金額 | M13: 設定値：商品売上額（外税抜き、内税込み）を設定 ※TAX_CD=99のレコードは 全内税の合計課税対象金額
A14: =A13+1 -> 11 | B14: TAX_EXMPT_AMT | C14: 免税金額 | D14: money | H14: TaxAmountを計算するときに課税免除された額 | I14: - | J14: TS/M | K14: ● | L14: 設定不要(固定値) 設定値："" | M14: 設定不要(固定値) 設定値："" | N14: ignicaPOS側で免税しない前提
A15: =A14+1 -> 12 | B15: TAX_FORGV_AMT | C15: 免税金額（食料キップ） | D15: money | F15: ● | H15: 取引に対する支払に食料キップが使用されたために、計算され、「免除」された税額を示します。 | I15: - | J15: TS/M | K15: ● | L15: 設定不要(固定値) 設定値："" | M15: 設定不要(固定値) 設定値："" | N15: ignicaPOS側で免税しない前提

Sheet TRANSACTION_TENDER
A1: トラン連携ファイルレイアウト | C1: 対象テーブル：TRANSACTION_TENDER 形式：TSV | M1: (補足説明) 現外支払い後に中止した場合 にのみ作成 | Q1: *1.4
A2: NO | B2: 項目 | H2: 説明 | I2: 取得元マスタ項目 | J2: 設定元 | K2: 一次開発 必須項目 | L2: ignicaPOS・Scan&Go設定値 | P2: 備考
B3: カラム名称 | C3: 日本語名称 | D3: 型 | E3: サイズ | F3: NULL 許可 | G3: KEY | L3: 売上 | M3: 売上中止 | N3: 入金 | O3: 出金
A4: 1 | B4: TRAN_LN_NBR | C4: 取引明細番号 | D4: smallint | G4: PK | H4: 取引の明細レベルに割当てられるライン番号 | I4: - | J4: ignicaPOS | K4: ◎ | L4: 設定値： 1取引内の下記テーブルのレコードの同一カラム名に通し番号を振る(番号が重複しなければ順不同で構わない) ・LN_DETAIL ・LN_DISCOUNT ・TRANSACTION_TAX ・TRANSACTION_TENDER | M4: 設定値： 1取引内の下記テーブルのレコードの同一カラム名に通し番号を振る(番号が重複しなければ順不同で構わない) ・LN_DETAIL ・LN_DISCOUNT ・TRANSACTION_TAX ・TRANSACTION_TENDER | N4: 設定値： 1取引内の下記テーブルのレコードの同一カラム名に通し番号を振る(番号が重複しなければ順不同で構わない) ・GL_TRAN ・TRANSACTION_TENDER | O4: 設定値： 1取引内の下記テーブルのレコードの同一カラム名に通し番号を振る(番号が重複しなければ順不同で構わない) ・GL_TRAN ・TRANSACTION_TENDER
A5: =A4+1 -> 2 | B5: TRAN_ID | C5: 取引通番 | D5: int | G5: PK | H5: 取引の識別子 | I5: - | J5: TS/M | K5: ● | L5: TSM側で設定となるため、設定不要（固定値） 設定値：""(空) | M5: TSM側で設定となるため、設定不要（固定値） 設定値：""(空) | N5: TSM側で設定となるため、設定不要（固定値） 設定値：""(空) | O5: TSM側で設定となるため、設定不要（固定値） 設定値：""(空)
A6: =A5+1 -> 3 | B6: STR_ID | C6: 店舗番号 | D6: int | G6: PK | H6: 店舗番号 | I6: 店舗番号 | J6: ignicaPOS | K6: ◎ | L6: 設定値：店舗番号×10000 | M6: 設定値：店舗番号×10000 | N6: 設定値：店舗番号×10000 | O6: 設定値：店舗番号×10000
A7: =A6+1 -> 4 | B7: TND_CD | C7: 支払種別コード | D7: smallint | F7: ● | H7: 1～99 ：現金支払 100～199：券支払 200～299：クレジット支払 300～399：掛け支払 400～499：その他支払 | I7: 現外設定マスタ連携 No.1 支払種別コード | J7: ignicaPOS | K7: ◎ | L7: 設定値：支払われた現外券の支払種別コード | M7: 設定値：支払われた現外券の支払種別コード | N7: 設定値：1(固定) ※1:現金のみ | O7: 設定値：1(固定) ※1:現金のみ
A8: =A7+1 -> 5 | B8: TND_TS | C8: 支払日時 | D8: datetime | H8: テンダー情報が取引に入力された日付と時間 | I8: - | J8: ignicaPOS | K8: ◎ | L8: 設定値：テンダー情報が取引に追加された日付と時間 <例> 2018-04-15 15:0:15.000 | M8: 設定値：テンダー情報が取引に追加された日付と時間 <例> 2018-04-15 15:0:15.000 | N8: 設定値：テンダー情報が取引に追加された日付と時間 <例> 2018-04-15 15:0:15.000 | O8: 設定値：テンダー情報が取引に追加された日付と時間 <例> 2018-04-15 15:0:15.000 | P8: 取引終了時刻しか持っていない場合は取引終了時刻を設定する。
A9: =A8+1 -> 6 | B9: AMT | C9: 合計金額 | D9: money | H9: 合計金額 釣りの時は､お釣りがマイナス値として 設定される。 | I9: - | J9: ignicaPOS | K9: ◎ | L9: 設定値：支払金額×券枚数 ＜例＞ -20 | M9: 設定値：支払金額×券枚数 ＜例＞ -20 | N9: 設定値：支払金額×券枚数 ＜例＞ -20 | O9: 設定値：支払金額×券枚数 ＜例＞ 20
A10: =A9+1 -> 7 | B10: ENTRY_MTHD | C10: 登録方法コード | D10: smallint | H10: このテンダータイプがPOSデバイスに認識される方法 オペレータ入力､カード入力等の種別を設定する。 | I10: - | J10: TS/M | K10: ● | L10: 設定不要(固定値) 設定値：""(空) | M10: 設定不要(固定値) 設定値：""(空) | N10: 設定不要(固定値) 設定値：""(空) | O10: 設定不要(固定値) 設定値：""(空)
A11: =A10+1 -> 8 | B11: TND_AMT | C11: 支払総額 | D11: money | H11: 支払総額 Amountと同じ値が設定される。 | I11: - | J11: ignicaPOS | K11: ◎ | L11: 設定値：No.6 合計金額と同じ値を設定 ＜例＞ -20 | M11: 設定値：No.6 合計金額と同じ値を設定 ＜例＞ -20 | N11: 設定値：No.6 合計金額と同じ値を設定 ＜例＞ -20 | O11: 設定値：No.6 合計金額と同じ値を設定 ＜例＞ 20
A12: =A11+1 -> 9 | B12: VOID_CD | C12: 取消コード | D12: smallint | F12: ● | H12: テンダーがボイドにされた場合は、ゼロ以外の値に設定します。 0：通常 11：直前訂正 12：行№訂正 13：一括訂正 15：指定訂正 18：Dummy Void (現外支払) 19：タッチ訂正 | I12: - | J12: ignicaPOS | K12: ◎ | L12: 設定値：Dummy明細の場合は18、それ以外は0 | M12: 設定値：Dummy明細の場合は18、それ以外は0 | N12: 設定値：0（固定） | O12: 設定値：0（固定） | P12: 現外支払時にDummy明細が作成される。ダミー明細の作成仕様は別途記述。
A13: =A12+1 -> 10 | B13: CURR_ID | C13: 通貨コード | D13: smallint | F13: ● | H13: テンダーに使用される、国の通貨 | I13: - | J13: TS/M | K13: ● | L13: 設定不要(固定値) 設定値：""(空) | M13: 設定不要(固定値) 設定値：""(空) | N13: 設定不要(固定値) 設定値：""(空) | O13: 設定不要(固定値) 設定値：""(空) | P13: 未使用
A14: =A13+1 -> 11 | B14: CURR_DENOM_ID | D14: smallint | E14: 2 | F14: ● | I14: - | J14: TS/M | K14: ● | L14: 設定不要(固定値) 設定値：""(空) | M14: 設定不要(固定値) 設定値：""(空) | N14: 設定不要(固定値) 設定値：""(空) | O14: 設定不要(固定値) 設定値：""(空) | P14: 未使用
A15: =A14+1 -> 12 | B15: DENOM_CNT | D15: smallint | E15: 2 | F15: ● | I15: - | J15: TS/M | K15: ● | L15: 設定不要(固定値) 設定値：""(空) | M15: 設定不要(固定値) 設定値：""(空) | N15: 設定不要(固定値) 設定値：""(空) | O15: 設定不要(固定値) 設定値：""(空) | P15: 未使用
A16: =A15+1 -> 13 | B16: GSFD_CHG_NON_CASH_AMT | C16: 券換金 | D16: money | F16: ● | H16: 券換金（釣有券の釣銭額） | I16: - | J16: ignicaPOS | K16: ◎ | L16: 設定値：釣有現外券の釣銭金額 券換金（釣有券の釣銭額） TND_CD=1の現金明細（お釣り）に設定される | M16: 設定値：釣有現外券の釣銭金額 券換金（釣有券の釣銭額） TND_CD=1の現金明細（お釣り）に設定される | N16: 設定値：0 現外券支払はないため0固定 | O16: 設定値：0 現外券支払はないため0固定
A17: =A16+1 -> 14 | B17: GSFD_SPLS_NON_CASH_AMT | C17: 釣銭超過金 | D17: money | F17: ● | H17: 釣銭超過金（釣無券の釣銭額） | I17: - | J17: TS/M | K17: ● | L17: 設定不要(固定値) 設定値：""(空) | M17: 設定不要(固定値) 設定値：""(空) | N17: 設定不要(固定値) 設定値：""(空) | O17: 設定不要(固定値) 設定値：""(空) | P17: いなげやでは、過剰現外券を使用していない認識
A18: =A17+1 -> 15 | B18: GSFD_GIFT_CERT_CNT | C18: 券枚数 | D18: smallint | F18: ● | I18: - | J18: ignicaPOS | K18: ◎ | L18: 設定値：現外券枚数 | M18: 設定値：現外券枚数 | N18: 設定値：0 現外券支払はないため0固定 | O18: 設定値：0 現外券支払はないため0固定 | P18: ignicaPOS側で現外券支払を行った場合に設定
A19: =A18+1 -> 16 | B19: GSFD_DFRD_MEMBER_ID | C19: 掛け支払顧客ｺｰﾄﾞ | D19: varchar | E19: 20 | F19: ● | H19: 掛け支払時、掛け支払顧客コードが入る。 | I19: - | J19: TS/M | K19: ● | L19: 設定不要(固定値) 設定値：""(空) | M19: 設定不要(固定値) 設定値：""(空) | N19: 設定不要(固定値) 設定値：""(空) | O19: 設定不要(固定値) 設定値：""(空) | P19: 掛支払は対象外
A20: =A19+1 -> 17 | B20: GSFD_BILL_CNT | C20: 万券枚数 | D20: int | F20: ● | H20: 万券枚数。万券登録を行った際の枚数が入る。万券登録を行わなかった場合は"0"が入る。 | I20: - | J20: TS/M | K20: ● | L20: 設定値：0(固定) | M20: 設定値：0(固定) | N20: 設定値：0(固定) | O20: 設定値：0(固定)
A21: =A20+1 -> 18 | B21: GSFD_GCAT_CLS | C21: CATｵﾌﾟｼｮﾝ情報 | D21: smallint | F21: ● | I21: - | J21: TS/M | K21: ● | L21: 設定不要(固定値) 設定値：""(空) | M21: 設定不要(固定値) 設定値：""(空) | N21: 設定不要(固定値) 設定値：""(空) | O21: 設定不要(固定値) 設定値：""(空) | P21: ignicaPOS側でCATは使用しない
A22: =A21+1 -> 19 | B22: GSFD_GCAT_CARD | C22: CATｵﾌﾟｼｮﾝ情報 | D22: varchar | E22: 100 | F22: ● | I22: - | J22: TS/M | K22: ● | L22: 設定不要(固定値) 設定値：""(空) | M22: 設定不要(固定値) 設定値：""(空) | N22: 設定不要(固定値) 設定値：""(空) | O22: 設定不要(固定値) 設定値：""(空) | P22: ignicaPOS側でCATは使用しない
A23: =A22+1 -> 20 | B23: GSFD_CARD_COMPANY_CD | C23: CATｵﾌﾟｼｮﾝ情報 | D23: varchar | E23: 3 | F23: ● | I23: - | J23: TS/M | K23: ● | L23: 設定不要(固定値) 設定値：""(空) | M23: 設定不要(固定値) 設定値：""(空) | N23: 設定不要(固定値) 設定値：""(空) | O23: 設定不要(固定値) 設定値：""(空) | P23: ignicaPOS側でCATは使用しない
A24: =A23+1 -> 21 | B24: GSFD_CARD_COMPANY_NAME | C24: CATｵﾌﾟｼｮﾝ情報 | D24: varchar | E24: 10 | F24: ● | I24: - | J24: TS/M | K24: ● | L24: 設定不要(固定値) 設定値：""(空) | M24: 設定不要(固定値) 設定値：""(空) | N24: 設定不要(固定値) 設定値：""(空) | O24: 設定不要(固定値) 設定値：""(空) | P24: ignicaPOS側でCATは使用しない
A25: =A24+1 -> 22 | B25: GSFD_CARD_ACCT_NBR | C25: CATｵﾌﾟｼｮﾝ情報 | D25: varchar | E25: 20 | F25: ● | I25: - | J25: TS/M | K25: ● | L25: 設定不要(固定値) 設定値：""(空) | M25: 設定不要(固定値) 設定値：""(空) | N25: 設定不要(固定値) 設定値：""(空) | O25: 設定不要(固定値) 設定値：""(空) | P25: ignicaPOS側でCATは使用しない
A26: =A25+1 -> 23 | B26: GSFD_GCAT_DOC_NO | C26: CATｵﾌﾟｼｮﾝ情報 | D26: varchar | E26: 20 | F26: ● | I26: - | J26: TS/M | K26: ● | L26: 設定不要(固定値) 設定値：""(空) | M26: 設定不要(固定値) 設定値：""(空) | N26: 設定不要(固定値) 設定値：""(空) | O26: 設定不要(固定値) 設定値：""(空) | P26: ignicaPOS側でCATは使用しない
A27: =A26+1 -> 24 | B27: GSFD_GIFT_BARCODE | C27: 商品券/値引券 | D27: varchar | E27: 75 | F27: ● | H27: スキャンしたクーポンバーコードを格納 | I27: 商品券バーコードマスタ連携ファイル No.1 スキャンコード | J27: ignicaPOS | K27: ◎ | L27: 設定値：現外券バーコード | M27: 設定値：現外券バーコード | N27: 設定値：""(空) 現外券支払はないため""(空)固定 | O27: 設定値：""(空) 現外券支払はないため""(空)固定 | P27: ignicaPOS側で現外券バーコード登録を行った場合に設定
A28: =A27+1 -> 25 | B28: GSFD_INVALIDCASH_FLG | D28: smallint | F28: ● | I28: - | J28: TS/M | K28: ● | L28: 設定不要(固定値) 設定値：""(空) | M28: 設定不要(固定値) 設定値：""(空) | N28: 設定不要(固定値) 設定値：""(空) | O28: 設定不要(固定値) 設定値：""(空) | P28: 券支払の集計補正 通番修正時に設定されるため、ignicaPOS側では設定なし
A29: =A28+1 -> 26 | B29: GSFD_EDY_CARD | C29: Edy情報 | D29: varchar | E29: 120 | F29: ● | H29: 以下の項目をｶﾝﾏ区切りで設定 Edy売上年月日,Edy売上時刻,上位端末ID,TerminalID, EM取扱通番,カード取扱通番,Edyｶｰﾄﾞ番号,取引区分, 売上金額,カード残高,取引前残高 例) 20060728,101625,07100005,00000004,5021000014,00050,1234567890123456,1500,3000,44,2058 | I29: - | J29: TS/M | K29: ● | L29: 設定不要(固定値) 設定値：""(空) | M29: 設定不要(固定値) 設定値：""(空) | N29: 設定不要(固定値) 設定値：""(空) | O29: 設定不要(固定値) 設定値：""(空) | P29: Edy支払は対応しない
A30: =A29+1 -> 27 | B30: GSFD_SUICA_CARD | D30: varchar | E30: 100 | F30: ● | I30: - | J30: TS/M | K30: ● | L30: 設定不要(固定値) 設定値：""(空) | M30: 設定不要(固定値) 設定値：""(空) | N30: 設定不要(固定値) 設定値：""(空) | O30: 設定不要(固定値) 設定値：""(空) | P30: Suica支払は対応しない
A31: =A30+1 -> 28 | B31: GSFD_PNT_TCKT_NBR | C31: 新満点券発券番号 | D31: varchar | E31: 20 | F31: ● | H31: 新満点券発券番号 新満点券の発券番号を格納する ※満点券使用時にSET | I31: - | J31: TS/M | K31: ● | L31: 設定不要(固定値) 設定値：""(空) | M31: 設定不要(固定値) 設定値：""(空) | N31: 設定不要(固定値) 設定値：""(空) | O31: 設定不要(固定値) 設定値：""(空) | P31: 現外券支払時に設定 いなげやは満点券なし
A32: =A31+1 -> 29 | B32: GSFD_PNT_TCKT_US_STATE | C32: 使用情報更新時状態コード | D32: smallint | E32: 2 | F32: ● | H32: 使用情報更新時状態コード ０：未使用、１：正常更新、２：未発行使用、３：有効期限切れ使用、４：オフライン使用 ※満点券使用時にSET | I32: - | J32: TS/M | K32: ● | L32: 設定不要(固定値) 設定値：""(空) | M32: 設定不要(固定値) 設定値：""(空) | N32: 設定不要(固定値) 設定値：""(空) | O32: 設定不要(固定値) 設定値：""(空) | P32: 現外券支払時に設定 満点券なし
A33: =A32+1 -> 30 | B33: GSFD_CARD_COMPCODE | D33: smallint | I33: - | J33: TS/M | K33: ● | L33: 設定不要(固定値) 設定値：""(空) | M33: 設定不要(固定値) 設定値：""(空) | N33: 設定不要(固定値) 設定値：""(空) | O33: 設定不要(固定値) 設定値：""(空)
A34: =A33+1 -> 31 | B34: GSFD_CARD_COMPNAME | D34: varchar | E34: 40 | F34: ● | I34: - | J34: TS/M | K34: ● | L34: 設定不要(固定値) 設定値：""(空) | M34: 設定不要(固定値) 設定値：""(空) | N34: 設定不要(固定値) 設定値：""(空) | O34: 設定不要(固定値) 設定値：""(空)
A35: =A34+1 -> 32 | B35: GSFD_CARD_HTNO | D35: smallint | I35: - | J35: TS/M | K35: ● | L35: 設定不要(固定値) 設定値：""(空) | M35: 設定不要(固定値) 設定値：""(空) | N35: 設定不要(固定値) 設定値：""(空) | O35: 設定不要(固定値) 設定値：""(空)
A36: =A35+1 -> 33 | B36: GSFD_EDY_AMOUNT | D36: money | F36: ● | I36: - | J36: TS/M | K36: ● | L36: 設定不要(固定値) 設定値：""(空) | M36: 設定不要(固定値) 設定値：""(空) | N36: 設定不要(固定値) 設定値：""(空) | O36: 設定不要(固定値) 設定値：""(空) | P36: Edy支払は対応しない
A37: =A36+1 -> 34 | B37: GSFD_EDY_CARD_ID | D37: varchar | E37: 16 | F37: ● | I37: - | J37: TS/M | K37: ● | L37: 設定不要(固定値) 設定値：""(空) | M37: 設定不要(固定値) 設定値：""(空) | N37: 設定不要(固定値) 設定値：""(空) | O37: 設定不要(固定値) 設定値：""(空) | P37: Edy支払は対応しない
A38: =A37+1 -> 35 | B38: GSFD_EDY_PRESALES_REMAINDER | D38: money | F38: ● | I38: - | J38: TS/M | K38: ● | L38: 設定不要(固定値) 設定値：""(空) | M38: 設定不要(固定値) 設定値：""(空) | N38: 設定不要(固定値) 設定値：""(空) | O38: 設定不要(固定値) 設定値：""(空) | P38: Edy支払は対応しない
A39: =A38+1 -> 36 | B39: GSFD_EDY_REMAIN | D39: money | F39: ● | I39: - | J39: TS/M | K39: ● | L39: 設定不要(固定値) 設定値：""(空) | M39: 設定不要(固定値) 設定値：""(空) | N39: 設定不要(固定値) 設定値：""(空) | O39: 設定不要(固定値) 設定値：""(空) | P39: Edy支払は対応しない
A40: =A39+1 -> 37 | B40: GSFD_EDY_HIGH_TERMINAL_ID | D40: varchar | E40: 16 | F40: ● | I40: - | J40: TS/M | K40: ● | L40: 設定不要(固定値) 設定値：""(空) | M40: 設定不要(固定値) 設定値：""(空) | N40: 設定不要(固定値) 設定値：""(空) | O40: 設定不要(固定値) 設定値：""(空) | P40: Edy支払は対応しない
A41: =A40+1 -> 38 | B41: GSFD_POSI_CHECK_INFO | D41: varchar | E41: 50 | F41: ● | I41: - | J41: TS/M | K41: ● | L41: 設定不要(固定値) 設定値：""(空) | M41: 設定不要(固定値) 設定値：""(空) | N41: 設定不要(固定値) 設定値：""(空) | O41: 設定不要(固定値) 設定値：""(空)
A42: =A41+1 -> 39 | B42: GSFD_GIFT_CHANGE | D42: varchar | E42: 1 | F42: ● | I42: - | J42: TS/M | K42: ● | L42: 設定不要(固定値) 設定値：""(空) | M42: 設定不要(固定値) 設定値：""(空) | N42: 設定不要(固定値) 設定値：""(空) | O42: 設定不要(固定値) 設定値：""(空) | P42: 通番取消時に設定
A43: =A42+1 -> 40 | B43: GSFD_ID_CARD | D43: varchar | E43: 100 | F43: ● | I43: - | J43: TS/M | K43: ● | L43: 設定不要(固定値) 設定値：""(空) | M43: 設定不要(固定値) 設定値：""(空) | N43: 設定不要(固定値) 設定値：""(空) | O43: 設定不要(固定値) 設定値：""(空) | P43: iD支払は対応しない
A44: =A43+1 -> 41 | B44: GSFD_CARD_LOG_DATA_TOM | D44: text | F44: ● | I44: - | J44: TS/M | K44: ● | L44: 設定不要(固定値) 設定値：""(空) | M44: 設定不要(固定値) 設定値：""(空) | N44: 設定不要(固定値) 設定値：""(空) | O44: 設定不要(固定値) 設定値：""(空)
A45: =A44+1 -> 42 | B45: GSFD_CARD_LOG_DATA_HOUSE | C45: コード決済ログ情報 | D45: text | F45: ● | I45: - | J45: ignicaPOS | K45: ◎ | L45: 設定値：コード決済のログ情報を設定する。 | M45: 設定値：コード決済のログ情報を設定する。 | N45: 設定値：""(空) | O45: 設定値：""(空) | P45: イオンフィナンシャルからのコード決済応答値を設定する。 設定形式は「■コード決済取引明細ログレイアウト」参照 | Q45: *1.1
A46: =A45+1 -> 43 | B46: GSFD_POSI_CHECK_INFO2 | D46: varchar | E46: 50 | F46: ● | I46: - | J46: TS/M | K46: ● | L46: 設定不要(固定値) 設定値：""(空) | M46: 設定不要(固定値) 設定値：""(空) | N46: 設定不要(固定値) 設定値：""(空) | O46: 設定不要(固定値) 設定値：""(空)
A47: =A46+1 -> 44 | B47: GSFD_CARD_NAME_HOUSE | C47: ハウスカード名称 | D47: varchar | E47: 26 | F47: ● | I47: - | J47: TS/M | K47: ● | L47: 設定不要(固定値) 設定値：""(空) | M47: 設定不要(固定値) 設定値：""(空) | N47: 設定不要(固定値) 設定値：""(空) | O47: 設定不要(固定値) 設定値：""(空)
A48: =A47+1 -> 45 | B48: GSFD_QP_CARD | C48: QuicPay情報 | D48: varchar | E48: 100 | F48: ● | I48: - | J48: TS/M | K48: ● | L48: 設定不要(固定値) 設定値：""(空) | M48: 設定不要(固定値) 設定値：""(空) | N48: 設定不要(固定値) 設定値：""(空) | O48: 設定不要(固定値) 設定値：""(空)
A49: =A48+1 -> 46 | B49: GSFD_TENDER_PRO_RATE | C49: 収益認識会計基準 | D49: varchar | E49: 240 | F49: ● | I49: - | J49: TS/M | K49: ● | L49: 設定不要(固定値) 設定値：""(空) | M49: 設定不要(固定値) 設定値：""(空) | N49: 設定不要(固定値) 設定値：""(空) | O49: 設定不要(固定値) 設定値：""(空)
A50: =A49+1 -> 47 | B50: GSFD_DISC_TND_LOG | C50: 値引扱い現外減算後税情報 | D50: varchar | E50: 200 | F50: ● | I50: - | J50: TS/M | K50: ● | L50: 設定不要(固定値) 設定値：""(空) | M50: 設定不要(固定値) 設定値：""(空) | N50: 設定不要(固定値) 設定値：""(空) | O50: 設定不要(固定値) 設定値：""(空)
M51: *1.4

Sheet GIFT_CERT_TENDER
A1: トラン連携ファイルレイアウト | C1: 対象テーブル：GIFT_CERT_TENDER 形式：TSV | M1: (補足説明) 現外支払い後に中止した場合 にのみ作成 | O1: *1.4
A2: NO | B2: 項目 | H2: 説明 | I2: 取得元マスタ項目 | J2: 設定元 | K2: 一次開発 必須項目 | L2: ignicaPOS・Scan&Go設定値 | N2: 備考
B3: カラム名称 | C3: 日本語名称 | D3: 型 | E3: サイズ | F3: NULL 許可 | G3: KEY | L3: 売上 | M3: 売上中止
A4: 1 | B4: SRC_STR_ID | C4: 発行店舗番号 | D4: int | I4: - | J4: TS/M | K4: ● | L4: 設定不要(固定値) 設定値：""(空) | M4: 設定不要(固定値) 設定値：""(空)
A5: =A4+1 -> 2 | B5: GFT_CERT_ID | C5: 商品券番号 | D5: varchar | E5: 24 | I5: - | J5: TS/M | K5: ● | L5: 設定不要(固定値) 設定値：""(空) | M5: 設定不要(固定値) 設定値：""(空)
A6: =A5+1 -> 3 | B6: STR_ID | C6: 店舗番号 | D6: int | G6: PK | I6: 店舗番号 | J6: ignicaPOS | K6: ◎ | L6: 設定値：店舗番号×10000 | M6: 設定値：店舗番号×10000 | N6: TRANS_HEADERと同じ
A7: =A6+1 -> 4 | B7: TRAN_LN_NBR | C7: 取引明細番号 | D7: smallint | G7: PK | H7: 取引の明細レベルに割当てられるライン番号 | I7: - | J7: ignicaPOS | K7: ◎ | L7: 設定値： 対応するTRANSACTION_TENDERのレコードのTRAN_LN_NBRを設定 (TRANSACTION_TENDERの1レコードに対して1レコード作成する) | M7: 設定値： 対応するTRANSACTION_TENDERのレコードのTRAN_LN_NBRを設定 (TRANSACTION_TENDERの1レコードに対して1レコード作成する)
A8: =A7+1 -> 5 | B8: TRAN_ID | C8: 取引ID | D8: int | G8: PK | H8: 取引の識別子 | I8: - | J8: TS/M | K8: ● | L8: TSM側で設定となるため、設定不要（固定値） 設定値：""(空) | M8: TSM側で設定となるため、設定不要（固定値） 設定値：""(空)
A9: =A8+1 -> 6 | B9: GFT_CERT_AMT | C9: 商品券価格 | D9: money | H9: 商品券の額面価格 | I9: - | J9: ignicaPOS | K9: ◎ | L9: 設定値：現外の支払額を設定 | M9: 設定値：現外の支払額を設定
A10: 7 | B10: CHANGE_AMT | C10: 釣銭金額 | D10: money | I10: - | J10: TS/M | K10: ● | L10: TSM側で設定となるため、設定不要（固定値） 設定値：""(空) | M10: TSM側で設定となるため、設定不要（固定値） 設定値：""(空) | N10: 釣銭は出ないので０固定 釣りあり現金でお釣り排出時も０
M11: *1.4

Sheet GSFD_PNT_TRANS_HEADER
A1: トラン連携ファイルレイアウト | C1: 対象テーブル：GSFD_PNT_TRANS_HEADER 形式：TSV
A2: NO | B2: 項目 | H2: 説明 | I2: 取得元マスタ項目 | J2: 設定元 | K2: 一次開発 必須項目 | L2: ignicaPOS・Scan&Go設定値 | M2: 備考
B3: カラム名称 | C3: 日本語名称 | D3: 型 | E3: サイズ | F3: NULL 許可 | G3: KEY | L3: 売上
A4: 1 | B4: TRAN_ID | C4: 取引通番 | D4: int | G4: PK | I4: - | J4: TS/M | K4: ● | L4: TSM側で設定となるため、設定不要（固定値） 設定値：""(空) | M4: 顧客あり取引で出力される TRANS_HEADERと同じ
A5: =A4+1 -> 2 | B5: STR_ID | C5: 店舗番号 | D5: int | G5: PK | I5: 店舗番号 | J5: ignicaPOS | K5: ◎ | L5: 設定値：店舗番号×10000 | M5: TRANS_HEADERと同じ
A6: =A5+1 -> 3 | B6: RGST_TRAN_NBR | C6: POS取引通番 | D6: smallint | I6: - | J6: ignicaPOS | K6: ◎ | L6: 設定値：取引通番 | M6: TRANS_HEADERと同じ
A7: =A6+1 -> 4 | B7: RGST_ID | C7: POS番号 | D7: int | I7: - | J7: ignicaPOS | K7: ◎ | L7: ignicaPOS側で設定 設定値：POS番号を設定 | M7: TRANS_HEADERと同じ
A8: =A7+1 -> 5 | B8: TRAN_STRT_TS | C8: 取引開始日時 | D8: datetime | I8: - | J8: ignicaPOS | K8: ◎ | L8: 設定値：取引開始時刻を設定 9999-99-99 99:99:99.000 <例> 2021-02-04 10:4:57.000 | M8: TRANS_HEADERと同じ
A9: =A8+1 -> 6 | B9: CUST_ID | C9: 顧客コード | D9: varchar | E9: 24 | F9: ● | I9: - | J9: ignicaPOS | K9: ◎ | L9: 設定値：登録した顧客コード。プリンスポイント対象金額が存在する場合はプリンスポイント対象金額を設定 上記以外の場合は、""(空) | M9: TRANS_HEADERと同じ
A10: =A9+1 -> 7 | B10: GSTP_DAILY_RATE | C10: スケジュール倍率 | D10: float | F10: ● | H10: 採用したスケジュール倍率を出力する。(1.0～99.9) | I10: - | J10: TS/M | K10: ● | L10: 設定不要(固定値) 設定値：""(空) | M10: スケジュール倍率を使用する場合設定 TSMでは、スケジュール倍率が設定される 未使用の場合、１ | N10: *1.0
A11: =A10+1 -> 8 | B11: GSTP_UCST_RSV01 | C11: ＤＭポイント | D11: varchar | E11: 10 | F11: ● | I11: - | J11: TS/M | K11: ● | L11: 設定不要(固定値) 設定値：""(空) | M11: カスタマイズ領域のため設定不要
A12: =A11+1 -> 9 | B12: GSTP_UCST_RSV02 | C12: スタンプラリーポイント | D12: varchar | E12: 10 | F12: ● | I12: - | J12: TS/M | K12: ● | L12: 設定不要(固定値) 設定値：""(空) | M12: カスタマイズ領域のため設定不要
A13: =A12+1 -> 10 | B13: GSTP_UCST_RSV03 | C13: サービスポイント | D13: varchar | E13: 10 | F13: ● | I13: - | J13: TS/M | K13: ● | L13: 設定不要(固定値) 設定値：""(空) | M13: カスタマイズ領域のため設定不要
A14: =A13+1 -> 11 | B14: GSTP_UCST_RSV04 | C14: EDYポイント | D14: varchar | E14: 10 | F14: ● | I14: - | J14: TS/M | K14: ● | L14: 設定不要(固定値) 設定値：""(空) | M14: カスタマイズ領域のため設定不要
A15: =A14+1 -> 12 | B15: GSTP_UCST_RSV05 | C15: ポイント対象支払率 | D15: varchar | E15: 10 | F15: ● | I15: - | J15: TS/M | K15: ● | L15: 設定不要(固定値) 設定値：""(空) | M15: カスタマイズ領域のため設定不要
A16: =A15+1 -> 13 | B16: GSTP_UCST_RSV06 | C16: バーコードポイント枚数 | D16: varchar | E16: 10 | F16: ● | I16: - | J16: TS/M | K16: ● | L16: 設定不要(固定値) 設定値：""(空) | M16: カスタマイズ領域のため設定不要
A17: =A16+1 -> 14 | B17: GSTP_UCST_RSV07 | C17: リザーブ７ | D17: varchar | E17: 10 | F17: ● | I17: - | J17: TS/M | K17: ● | L17: 設定不要(固定値) 設定値：""(空) | M17: カスタマイズ領域のため設定不要
A18: =A17+1 -> 15 | B18: GSTP_UCST_RSV08 | C18: リザーブ８ | D18: varchar | E18: 10 | F18: ● | I18: - | J18: TS/M | K18: ● | L18: 設定不要(固定値) 設定値：""(空) | M18: カスタマイズ領域のため設定不要
A19: =A18+1 -> 16 | B19: GSTP_UCST_RSV09 | C19: リザーブ９ | D19: varchar | E19: 10 | F19: ● | I19: - | J19: TS/M | K19: ● | L19: 設定不要(固定値) 設定値：""(空) | M19: カスタマイズ領域のため設定不要
A20: =A19+1 -> 17 | B20: GSTP_UCST_RSV10 | C20: リザーブ１０ | D20: varchar | E20: 10 | F20: ● | I20: - | J20: TS/M | K20: ● | L20: 設定不要(固定値) 設定値：""(空) | M20: カスタマイズ領域のため設定不要
A21: =A20+1 -> 18 | B21: GSTP_UCST_RSV11 | C21: リザーブ１１ | D21: varchar | E21: 20 | F21: ● | I21: - | J21: TS/M | K21: ● | L21: 設定不要(固定値) 設定値：""(空) | M21: カスタマイズ領域のため設定不要
A22: =A21+1 -> 19 | B22: GSTP_UCST_RSV12 | C22: リザーブ１２ | D22: varchar | E22: 20 | F22: ● | I22: - | J22: TS/M | K22: ● | L22: 設定不要(固定値) 設定値：""(空) | M22: カスタマイズ領域のため設定不要
A23: =A22+1 -> 20 | B23: GSTP_INVALID_POINT | C23: 失効ポイント数 | D23: int | F23: ● | I23: - | J23: TS/M | K23: ● | L23: 設定不要(固定値) 設定値：""(空) | M23: Satisfaでは未使用
A24: =A23+1 -> 21 | B24: GSTP_BONUS_POINT | C24: ボーナスポイント | D24: int | F24: ● | I24: - | J24: TS/M | K24: ● | L24: 設定不要(固定値) 設定値：""(空) | M24: ポイントPC設定の機能
A25: =A24+1 -> 22 | B25: GSTP_BONUS_RATE | C25: ボーナスポイント率 | D25: float | F25: ● | I25: - | J25: TS/M | K25: ● | L25: 設定不要(固定値) 設定値：""(空) | M25: ポイントPC設定の機能
A26: =A25+1 -> 23 | B26: GSTP_POINT_AMOUNT | C26: ボーナスポイント金額 | D26: money | F26: ● | I26: - | J26: TS/M | K26: ● | L26: 設定不要(固定値) 設定値：""(空)
A27: =A26+1 -> 24 | B27: GSTP_SHOP_TRAN_ID | C27: 加盟店トランザクションID | D27: text | F27: ● | I27: - | J27: TS/M | K27: ● | L27: 設定不要(固定値) 設定値：""(空)
A28: =A27+1 -> 25 | B28: GSTP_POINT_TRAN_ID | C28: ポイントセンタ・トランザクションID | D28: text | F28: ● | I28: - | J28: TS/M | K28: ● | L28: 設定不要(固定値) 設定値：""(空)
A29: =A28+1 -> 26 | B29: GSTP_PNT_SPLS_NON_CASH_AMT | C29: ポイント過剰現外額 | D29: money | F29: ● | I29: - | J29: TS/M | K29: ● | L29: 設定不要(固定値) 設定値：""(空)
A30: =A29+1 -> 27 | B30: GSTP_SATISFA_OUT_SIDE_TAX | C30: 外税対象金額 | D30: money | F30: ● | I30: - | J30: ignicaPOS | K30: ◎ | L30: 設定値： 外税対象金額を設定 | M30: 取引の外税対象金額を設定

Sheet MANUAL_PRICE
A1: トラン連携ファイルレイアウト | C1: 対象テーブル：MANUAL_PRICE 形式：TSV
A2: NO | B2: 項目 | H2: 説明 | I2: 取得元マスタ項目 | J2: 設定元 | K2: 一次開発 必須項目 | L2: ignicaPOS・Scan&Go設定値 | N2: 備考
B3: カラム名称 | C3: 日本語名称 | D3: 型 | E3: サイズ | F3: NULL 許可 | G3: KEY | L3: 売上 | M3: 売上 中止
A4: 1 | B4: TRAN_LN_NBR | C4: 取引明細番号 | D4: smallint | G4: PK | H4: 取引の明細レベルに割当てられるライン番号 | I4: LN_DETAILの取引明細番号（TRAN_LN_NBR）と同じ値を設定する。 | J4: ignicaPOS | K4: ◎ | L4: 設定値：LN_DETAILのTRAN_LN_NBRと同じ値を設定 | M4: 設定値：LN_DETAILのTRAN_LN_NBRと同じ値を設定
A5: =A4+1 -> 2 | B5: ORIG_PRC | C5: 変更前価格 | D5: money | G5: PK | H5: 変更前の価格 価格手入力の場合は"0"が入る。 | I5: 商品マスタ連携ファイル No.22 売価 × 数量 | J5: ignicaPOS | K5: ◎ | L5: 設定値：「商品マスタ連携ファイル No.22 売価」）× 数量の金額を設定。部門登録、売価強制（価格手入力）商品の場合は"0"が入る。 | M5: 設定値：「商品マスタ連携ファイル No.22 売価」）× 数量の金額を設定。部門登録、売価強制（価格手入力）商品の場合は"0"が入る。 | O5: *1.5
A6: =A5+1 -> 3 | B6: TRAN_ID | C6: 取引通番 | D6: int | G6: PK | H6: 変更実施時の取引通番 | I6: - | J6: TS/M | K6: ● | L6: TSM側で設定となるため、設定不要（固定値） 設定値：""(空) | M6: TSM側で設定となるため、設定不要（固定値） 設定値：""(空)
A7: =A6+1 -> 4 | B7: STR_ID | C7: 店舗番号 | D7: int | G7: PK | I7: 店舗番号 | J7: ignicaPOS | K7: ◎ | L7: 設定値：店舗番号×10000 | M7: 設定値：店舗番号×10000
A8: =A7+1 -> 5 | B8: AUTH_EMP_ID | C8: 承認従業員ID | D8: varchar | E8: 12 | H8: 販売価格変更権限を持つ担当者コード | I8: 担当者マスタ連携ﾌｧｲﾙ No3 従業員コード | J8: ignicaPOS | K8: ◎ | L8: 設定値：取引を入力した従業員番号を設定 | M8: 設定値：取引を入力した従業員番号を設定
A9: =A8+1 -> 6 | B9: OVRD_PRC | C9: 変更価格 | D9: money | H9: 変更後の価格 変更後価格×数量の金額が入る。 | I9: - | J9: ignicaPOS | K9: ◎ | L9: 設定値：変更後価格×数量の金額 | M9: 設定値：変更後価格×数量の金額
A10: =A9+1 -> 7 | B10: PRC_OVRD_REAS_CD | C10: 理由コード | D10: smallint | H10: 変更の理由コード 10：部門登録 11：価格手入力(PLU) 12：値下げ売価変更 13：値上げ売価変更 | I10: - | J10: ignicaPOS | K10: ◎ | L10: 設定値：10：部門登録 11：価格手入力(PLU) 12：値下げ売価変更 13：値上げ売価変更256：会員ペアマッチ | M10: 設定値：10：部門登録 11：価格手入力(PLU) 12：値下げ売価変更 13：値上げ売価変更256：会員ペアマッチ
A11: =A10+1 -> 8 | B11: OVRD_TS | C11: 価格変更日時 | D11: datetime | H11: 変更が記録された日時 | I11: - | J11: ignicaPOS | K11: ◎ | L11: 設定値：取引開始時刻を設定 9999-99-99 99:99:99.000 <例> 2021-02-04 10:4:57.000 | M11: 設定値：取引開始時刻を設定 9999-99-99 99:99:99.000 <例> 2021-02-04 10:4:57.000 | N11: 取引開始時刻を持っていない場合は取引終了時刻を設定する。

Sheet GL_TRAN
A1: トラン連携ファイルレイアウト | C1: 対象テーブル：GL_TRAN 形式：TSV | M1: *1.5 「入金 中止」は、ignicaPOS側からトラン連携無し | O1: *1.5 「出金 中止」は、ignicaPOS側からトラン連携無し
A2: NO | B2: 項目 | H2: 説明 | I2: 取得元マスタ項目 | J2: 設定元 | K2: 一次開発 必須項目 | L2: ignicaPOS・Scan&Go設定値 | P2: 備考
B3: カラム名称 | C3: 日本語名称 | D3: 型 | E3: サイズ | F3: NULL 許可 | G3: KEY | L3: 入金 | M3: 入金 中止 | N3: 出金 | O3: 出金 中止
A4: 1 | B4: TRAN_ID | C4: 取引通番 | D4: int | G4: PK | H4: 取引の識別子 | I4: - | J4: TS/M | K4: =IF(J4="ignicaPOS",IF(#REF!<>"〇",IF(#REF!<>"〇","〇","◎"),"◎"),"●") -> ● | L4: TSM側で設定となるため、設定不要（固定値） 設定値：""(空) | M4: TSM側で設定となるため、設定不要（固定値） 設定値：""(空) | N4: TSM側で設定となるため、設定不要（固定値） 設定値：""(空) | O4: TSM側で設定となるため、設定不要（固定値） 設定値：""(空)
A5: =A4+1 -> 2 | B5: TRAN_LN_NBR | C5: 取引明細番号 | D5: smallint | G5: PK | H5: 取引の明細レベルに割り当てられるライン番号 | I5: TRANSACTION_TENDERの取引明細番号（TRAN_LN_NBR）と同じ値が設定される。 TRANSACTION_TENDER.TRAN_LN_NBR | J5: ignicaPOS | K5: =IF(J5="ignicaPOS",IF(#REF!<>"〇",IF(#REF!<>"〇","〇","◎"),"◎"),"●") -> #REF! | L5: 設定値：TRANSACTION_TENDERの取引明細番号（TRAN_LN_NBR）と同じ値 | M5: 設定値：TRANSACTION_TENDERの取引明細番号（TRAN_LN_NBR）と同じ値 | N5: 設定値：TRANSACTION_TENDERの取引明細番号（TRAN_LN_NBR）と同じ値 | O5: 設定値：TRANSACTION_TENDERの取引明細番号（TRAN_LN_NBR）と同じ値
A6: =A5+1 -> 3 | B6: GL_TRAN_TS | C6: 取引日時 | D6: datetime | H6: 明細を設定した日付 | I6: - | J6: ignicaPOS | K6: ◎ | L6: 設定値：取引開始時刻を設定 9999-99-99 99:99:99.000 <例> 2021-02-04 10:4:57.000 | M6: 設定値：取引開始時刻を設定 9999-99-99 99:99:99.000 <例> 2021-02-04 10:4:57.000 | N6: 設定値：取引開始時刻を設定 9999-99-99 99:99:99.000 <例> 2021-02-04 10:4:57.000 | O6: 設定値：取引開始時刻を設定 9999-99-99 99:99:99.000 <例> 2021-02-04 10:4:57.000
A7: =A6+1 -> 4 | B7: VOID_CD | C7: 取消コード | D7: smallint | H7: 明細をボイドにする理由を記述する理由コード 0：通常 1：取引中止 2：通番取消 | I7: - | J7: ignicaPOS | K7: ◎ | L7: 設定値：0固定 | M7: 設定値：1固定 | N7: 設定値：0固定 | O7: 設定値：1固定 | P7: 訂正明細は引き継がない。
A8: =A7+1 -> 5 | B8: TND_CD | C8: 支払種別 | D8: smallint | H8: 現金、クレジットカード等 1～99 ：現金支払 100～199：券支払 200～299：クレジット支払 300～399：掛け支払 400～499：その他支払 501～599：入金 601～699：出金 | I8: - | J8: TS/M | K8: ● | L8: 設定値：""(空) | M8: 設定値：""(空) | N8: 設定値：""(空) | O8: 設定値：""(空)
A9: =A8+1 -> 6 | B9: STAT | C9: ステータス | D9: smallint | H9: Ｇ／Ｌアカウント明細のステータス | I9: - | J9: TS/M | K9: ● | L9: 設定値：""(空) | M9: 設定値：""(空) | N9: 設定値：""(空) | O9: 設定値：""(空)
A10: =A9+1 -> 7 | B10: GL_ACCT_ID | C10: G/LアカウントID | D10: varchar | E10: 20 | H10: アカウントシステムの識別子 | I10: - | J10: TS/M | K10: ● | L10: 設定値：""(空) | M10: 設定値：""(空) | N10: 設定値：""(空) | O10: 設定値：""(空)
A11: =A10+1 -> 8 | B11: GL_AMT | C11: 金額 | D11: money | H11: Ｇ／Ｌアカウント明細額 入出金額。入金時の釣銭金額は含まない。独立現外時は"0"が入る。 | I11: - | J11: ignicaPOS | K11: ◎ | L11: 設定値：入金額 ＜例＞ 10 | M11: 設定値：入金額 ＜例＞ 10 | N11: 設定値：出金額 ＜例＞ -10 | O11: 設定値：出金額 ＜例＞ -10
A12: =A11+1 -> 9 | B12: REAS_CD | C12: 理由コード | D12: smallint | F12: ● | H12: 取引明細の理由コード | I12: 入出金マスタ連携ファイル No1.入出金種別コード | J12: ignicaPOS | K12: ◎ | L12: 設定値：入出金種別コード | M12: 設定値：入出金種別コード | N12: 設定値：入出金種別コード | O12: 設定値：入出金種別コード | Q12: *1.0
A13: =A12+1 -> 10 | B13: DESCR | C13: 入出金名称 | D13: varchar | E13: 20 | F13: ● | H13: 収入／支出アカウント説明 独立現外時は""が入る。 | I13: 入出金マスタ連携ファイル No2.入出金名称 | J13: ignicaPOS | K13: ◎ | L13: 設定値：入出金名称 | M13: 設定値：入出金名称 | N13: 設定値：入出金名称 | O13: 設定値：入出金名称
A14: =A13+1 -> 11 | B14: STR_ID | C14: 店舗番号 | D14: int | G14: PK | I14: 店舗番号 | J14: ignicaPOS | K14: ◎ | L14: 設定値：店舗番号×10000 | M14: 設定値：店舗番号×10000 | N14: 設定値：店舗番号×10000 | O14: 設定値：店舗番号×10000

Sheet LOAN_PICKUP
A1: トラン連携ファイルレイアウト | C1: 対象テーブル：LOAN_PICKUP 形式：TSV | M1: *1.5 「釣銭準備金 中止」は、ignicaPOS側からトラン連携無し | O1: *1.5 「中間回収 中止」は、ignicaPOS側からトラン連携無し
A2: NO | B2: 項目 | H2: 説明 | I2: 取得元マスタ項目 | J2: 設定元 | K2: 一次開発 必須項目 | L2: ignicaPOS・Scan&Go設定値 | P2: 備考
B3: カラム名称 | C3: 日本語名称 | D3: 型 | E3: サイズ | F3: NULL 許可 | G3: KEY | L3: 釣銭準備金 | M3: 釣銭準備金 中止 | N3: 中間回収 | O3: 中間回収 中止
A4: 1 | B4: LOAN_PKUP_TS | C4: 日時情報 | D4: datetime | G4: PK | H4: システムに記録される、Loan/Pickupの日付と時間 | I4: - | J4: ignicaPOS | K4: 〇 | L4: 設定値：取引開始時刻を設定 9999-99-99 99:99:99.000 <例> 2021-02-04 10:4:57.000 | M4: 設定値：取引開始時刻を設定 9999-99-99 99:99:99.000 <例> 2021-02-04 10:4:57.000 | N4: 設定値：取引開始時刻を設定 9999-99-99 99:99:99.000 <例> 2021-02-04 10:4:57.000 | O4: 設定値：取引開始時刻を設定 9999-99-99 99:99:99.000 <例> 2021-02-04 10:4:57.000 | P4: 取引終了時刻しか持っていない場合は取引終了時刻を設定する。
A5: =A4+1 -> 2 | B5: TILL_ID | C5: ティルＩＤ | D5: varchar | E5: 12 | G5: PK | I5: - | J5: TS/M | K5: ● | L5: TSM側で設定となるため、設定不要（固定値） 設定値：""(空) | M5: TSM側で設定となるため、設定不要（固定値） 設定値：""(空) | N5: TSM側で設定となるため、設定不要（固定値） 設定値：""(空) | O5: TSM側で設定となるため、設定不要（固定値） 設定値：""(空)
A6: =A5+1 -> 3 | B6: STR_ID | C6: 店舗番号 | D6: int | G6: PK | H6: 店舗番号 | I6: 店舗番号 | J6: ignicaPOS | K6: 〇 | L6: 設定値：店舗番号×10000 | M6: 設定値：店舗番号×10000 | N6: 設定値：店舗番号×10000 | O6: 設定値：店舗番号×10000
A7: =A6+1 -> 4 | B7: TND_CD | C7: 支払種別 | D7: smallint | G7: PK | H7: このLoan/Pickupの支払種別 1～99 ：現金支払 100～199：券支払 200～299：クレジット支払 300～399：掛け支払 400～499：その他支払 501～599：入金 601～699：出金 | I7: - | J7: TS/M | K7: ● | L7: TSM側で設定となるため、設定不要（固定値） 設定値：""(空) | M7: TSM側で設定となるため、設定不要（固定値） 設定値：""(空) | N7: TSM側で設定となるため、設定不要（固定値） 設定値：""(空) | O7: TSM側で設定となるため、設定不要（固定値） 設定値：""(空)
A8: =A7+1 -> 5 | B8: TRAN_ID | C8: 取引通番 | D8: int | F8: ● | H8: (該当する場合は) Loan/Pickup含むPOS取引 | I8: - | J8: TS/M | K8: ● | L8: TSM側で設定となるため、設定不要（固定値） 設定値：""(空) | M8: TSM側で設定となるため、設定不要（固定値） 設定値：""(空) | N8: TSM側で設定となるため、設定不要（固定値） 設定値：""(空) | O8: TSM側で設定となるため、設定不要（固定値） 設定値：""(空)
A9: =A8+1 -> 6 | B9: TRAN_LN_NBR | C9: 取引明細番号 | D9: smallint | F9: ● | H9: （該当する場合は）Loan/Pickupが発生した取引のライン番号 | I9: - | J9: ignicaPOS | K9: ◎ | L9: 設定値： 1取引内の下記テーブルのレコードの同一カラム名に通し番号を振る(番号が重複しなければ順不同で構わない) ・LOAN_PICKUP | M9: 設定値： 1取引内の下記テーブルのレコードの同一カラム名に通し番号を振る(番号が重複しなければ順不同で構わない) ・LOAN_PICKUP | N9: 設定値： 1取引内の下記テーブルのレコードの同一カラム名に通し番号を振る(番号が重複しなければ順不同で構わない) ・LOAN_PICKUP | O9: 設定値： 1取引内の下記テーブルのレコードの同一カラム名に通し番号を振る(番号が重複しなければ順不同で構わない) ・LOAN_PICKUP
A10: =A9+1 -> 7 | B10: EMP_ID | C10: 従業員コード | D10: varchar | E10: 12 | H10: Loan/Pickupを実施した従業員 | I10: 担当者マスタ連携ﾌｧｲﾙ No3 従業員コード | J10: ignicaPOS | K10: ◎ | L10: 設定値：取引を入力した従業員番号を設定 | M10: 設定値：取引を入力した従業員番号を設定 | N10: 設定値：取引を入力した従業員番号を設定 | O10: 設定値：取引を入力した従業員番号を設定
A11: =A10+1 -> 8 | B11: DEST_TILL_ID | C11: 地域ティルＩＤ | D11: varchar | E11: 12 | H11: 移動先テイル番号。釣銭準備金、中間回収時は""が入る。 | I11: - | J11: TS/M | K11: ● | L11: 設定不要(固定値) 設定値：""(空) | M11: 設定不要(固定値) 設定値：""(空) | N11: 設定不要(固定値) 設定値：""(空) | O11: 設定不要(固定値) 設定値：""(空)
A12: =A11+1 -> 9 | B12: ENVLP_ID | C12: 袋ＩＤ | D12: varchar | E12: 12 | F12: ● | H12: Loan/Pickupに使う袋の識別子 ピックアップオプション識別子。釣銭準備金、中間回収時は""が入る。 | I12: - | J12: TS/M | K12: ● | L12: 設定不要(固定値) 設定値：""(空) | M12: 設定不要(固定値) 設定値：""(空) | N12: 設定不要(固定値) 設定値：""(空) | O12: 設定不要(固定値) 設定値：""(空)
A13: =A12+1 -> 10 | B13: AMT | C13: 合計金額 | D13: money | H13: ティルの収支という視点から見た、この移行を現金に換算した金額（つまり、ローンはプラスで、引き出しはマイナス） 取引金額 | I13: - | J13: ignicaPOS | K13: ◎ | L13: 設定値：金額 ＜例＞ 100 | M13: 設定値：0 中止は、0 | N13: 設定値：金額 ＜例＞ -100 | O13: 設定値：0 中止は、0
A14: =A13+1 -> 11 | B14: TND_CNT | C14: テンダーユニット数 | D14: int | F14: ● | H14: Loan/Pickupにおける個々のテンダーユニットの数 支払回数 | I14: - | J14: TS/M | K14: ● | L14: 設定値：0(固定) | M14: 設定値：0(固定) | N14: 設定値：0(固定) | O14: 設定値：0(固定)
A15: =A14+1 -> 12 | B15: DECLR_CD | C15: 申告タイプ | D15: smallint | H15: Loan/Pickupの種別 1：loan (釣銭準備金) 2：pickup(中間回収) | I15: - | J15: ignicaPOS | K15: ◎ | L15: 設定値：1 1:釣銭準備金、2:中間回収 | M15: 設定値：1 1:釣銭準備金、2:中間回収 | N15: 設定値：2 1:釣銭準備金、2:中間回収 | O15: 設定値：2 1:釣銭準備金、2:中間回収
A16: =A15+1 -> 13 | B16: REAS_CD | C16: 理由コード | D16: smallint | H16: Loan/Pickupの理由です。たとえば釣銭の補充や中間回収等。 取引理由コード。釣銭準備金、中間回収時は"0"が入る。 | I16: - | J16: TS/M | K16: ● | L16: 設定不要(固定値) 設定値：""(空) | M16: 設定不要(固定値) 設定値：""(空) | N16: 設定不要(固定値) 設定値：""(空) | O16: 設定不要(固定値) 設定値：""(空)
A17: =A16+1 -> 14 | B17: VOID_CD | C17: 取消コード | D17: smallint | H17: ボイドの理由コード 0：通常 1：取引中止 2：通番取消 999：保留取引 | I17: - | J17: ignicaPOS | K17: ◎ | L17: 設定値：0 0:通常、1:中止 | M17: 設定値：1 0:通常、1:中止 | N17: 設定値：0 0:通常、1:中止 | O17: 設定値：1 0:通常、1:中止
A18: =A17+1 -> 15 | B18: GSFD_TRNING_MDE_FG | C18: 練習モードフラグ | D18: smallint | F18: ● | H18: 練習モードフラグ 0：一般モード 1：練習モード | I18: - | J18: ignicaPOS | K18: ◎ | L18: 設定値： 0：一般モード 1：練習モード | M18: 設定値： 0：一般モード 1：練習モード | N18: 設定値： 0：一般モード 1：練習モード | O18: 設定値： 0：一般モード 1：練習モード

Sheet コード決済取引明細ログレイアウト
C3: ■コード決済取引明細ログレイアウト
D5: コード決済取引明細ログは以下に格納されているものとする。
E6: ・コード決済売上： | K6: TRANSACTION_TENDERテーブル - GSFD_CARD_LOG_DATA_HOUSEカラム
E7: ・コード決済取消： | K7: TRANSACTION_TENDERテーブル - GSFD_CARD_LOG_DATA_HOUSEカラム
C14: ①固定部 | AL14: 業務
D15: 項番 | F15: 項目名 | N15: 桁数 | P15: 形式 | R15: 項目説明 | AL15: 売上 （出金） | AO15: 取消返品 | AR15: 備考 | BD15: カラム 格納 形式
C18: 固定部 | D18: 1 | F18: メッセージレングス | N18: 6 | P18: 9 | R18: レコード長（カンマ、シングルコーテーションを含む） | AL18: ● | BD18: 固
D19: =D18+1 -> 2 | F19: システム予約領域 | N19: 4 | P19: X | R19: "3202" 固定 | AL19: ○ | BD19: 固
D20: =D19+1 -> 3 | F20: アイテム識別 | N20: 2 | P20: X | R20: "U1" 固定 | AL20: ○ | BD20: 固
D21: =D20+1 -> 4 | F21: システム予約領域 | N21: 9 | P21: 9 | R21: "000130000" 固定 | AL21: ○ | BD21: 固
D22: =D21+1 -> 5 | F22: システム予約領域 | N22: 4 | P22: 9 | R22: "0000" 固定 | AL22: ○ | BD22: 固
D23: =D22+1 -> 6 | F23: カウンタ精査フラグ | N23: 1 | P23: 9 | R23: "0" 固定 | AL23: ○ | BD23: 固
D24: =D23+1 -> 7 | F24: システム予約領域 | N24: 3 | P24: 9 | R24: "000" 固定 | AL24: ○ | BD24: 固
D25: =D24+1 -> 8 | F25: 電文種別 | N25: 1 | P25: 9 | R25: 0: 要求 | AL25: ○ | BD25: 固
D26: =D25+1 -> 9 | F26: 発生元フラグ | N26: 1 | P26: 9 | R26: "0" 固定 | AL26: ○ | BD26: 固
D27: 10 | F27: アプリケーションエラーフラグ | N27: 1 | P27: X | R27: "0" 固定 | AL27: ○ | BD27: 固
D28: 11 | F28: 最終結果フラグ | N28: 1 | P28: X | R28: "0" 固定 | AL28: ○ | BD28: 固
D29: 12 | F29: 固定部予備 | N29: 10 | P29: 9 | R29: "0000100001" 固定 | AL29: ○ | BD29: 固
D30: 13 | F30: システム予約領域 | N30: 4 | P30: 9 | R30: "0000" 固定 | AL30: ○ | BD30: 固
D31: 14 | F31: 障害取消フラグ | N31: 1 | P31: 9 | R31: "0" 固定 | AL31: ○ | BD31: 固
D32: 15 | F32: 店コード | N32: 4 | P32: 9 | R32: 店コード | AL32: ● | BD32: 固
D33: 16 | F33: POS№ | N33: 4 | P33: 9 | R33: POS端末№ | AL33: ● | BD33: 固
D34: 17 | F34: 取引通番 | N34: 4 | P34: 9 | R34: POS内の取引通番(0001～9999のサイクリック) | AL34: ● | BD34: 固
D35: 18 | F35: POS処理時間 | N35: 14 | P35: 9 | R35: 取引開始時間の西暦年月日及び時刻（YYYYMMDDHHMMSS） | AL35: ● | BD35: 固
D36: 19 | F36: システム予約領域 | N36: 3 | P36: X | R36: "111"固定 | AL36: ○ | BD36: 固
D37: 20 | F37: 終了判定 | N37: 3 | P37: X | R37: ALL SPACE | AL37: ○ | BD37: 固
AL38: ○：既定の値をセット、●：条件によりセットする値が異なる
C39: 形式 | E39: タイプ | I39: 備考
C40: 9 | E40: 数値タイプ | I40: 桁数以下の場合、先頭0固定
C41: X | E41: 文字タイプ | I41: 桁数以下の場合、左詰め 残りSPACE
C54: ■データ部:H1アイテムフォーマット
D55: 項番 | E55: 項目名 | N55: 桁数 | O55: 形式 | P55: 項目説明 | AL55: 売上 （出金） | AO55: 取消返品 | AR55: 備考 | BD55: カラム 格納 形式
C58: データ部 | D58: 1 | E58: 桁数 | N58: 4 | O58: 9 | P58: "16" 固定 | AL58: ○ | BD58: ,数値
D59: =D58+1 -> 2 | E59: アイテム識別 | N59: 2 | O59: X | P59: "H1" 固定 | AL59: ○ | BD59: ,'文字'
D60: 3 | E60: 業務区分コード | N60: 4 | O60: X | P60: 処理する業務の区分（2003 or 2005） | AL60: 2003 | AO60: 2005 | BD60: ,'文字'
D61: 4 | E61: 暗号化フラグ | N61: 1 | O61: 9 | P61: "0" 固定 | AL61: ○ | BD61: ,数値
D62: 5 | E62: 仕向け会社コード | N62: 11 | O62: X | P62: "ALL 0"固定 | AL62: ○ | BD62: ,'文字'
D63: 6 | E63: 端末識別コード | N63: 30 | O63: X | P63: 端末を識別するためのコード | AL63: ● | BD63: ,'文字'
P64: 識別コード＋店コード＋POS番号を設定する。
Q65: 識別コード …5桁 "00000"（固定）
Q66: 店コード …4桁 店コード4桁(前0埋め)
Q67: POS番号 …4桁 POS番号4桁(前0埋め)
A69: *1.5 | D69: 7 | E69: 伝票番号 | N69: 20 | O69: X | P69: 固定値+POS番号+取引通番+取引内通番+予備 | AL69: ● | AR69: 取引内通番・・・1取引内で複数回のコード決済の | BD69: ,'文字'
A70: *1.5 | Q70: 固定値 …3桁 "000"固定 | AR70: センター通信をした場合、伝票番号が「固定値
A71: *1.5 | Q71: POS番号 …4桁 POS番号4桁(前0埋め) | AR71: +POS番号+取引通番」であると,伝票番号重複エラー
A72: *1.5 | Q72: 取引通番 …4桁 取引通番(前0埋め) | AR72: となるため、00～99（サイクリック）の値をセット。
Q73: 取引内通番 …2桁 取引内通番(前0埋め)
Q74: 予備 …7桁 スペース固定
D75: 8 | E75: カード入力区分 | N75: 1 | O75: 9 | P75: "1"固定 | AL75: ○ | BD75: ,数値
D76: 9 | E76: カード情報 | N76: 80 | O76: X | P76: バーコード情報を設定。（表B参照） | AL76: ● | BD76: ,'文字'
P77: 残りにスペースを設定する
A79: *1.3 | D79: 10 | E79: 有効期限 | N79: 16 | O79: X | P79: 決済ブランド(有効期限(8桁)+スペース(8桁))を設定する。 | AL79: ● | AR79: ・PayPay：'89250101' | AX79: ・メルペイ：'89280101' | BD79: ,'文字'
A80: *1.3 | E80: （決済ブランド） | P80: ※決済ブランド（有効期限）は、センターからの応答値。 | AR80: ・d払い：'89270101' | AX80: ・楽天ペイ：'89260101'
A81: *1.3 | P81: 例）'12340101'：先頭4桁は決済ブランドのサービス識別コード、先頭5桁目からの"0101"は固定値 | AR81: ・au Pay：'89290101' | AX81: ・AEON Pay：'89430101'
D82: 11 | E82: 商品コード | N82: 7 | O82: X | P82: "ALL 0"固定 | AL82: 〇 | BD82: ,'文字'
D83: 12 | E83: 利用ポイント（金額） | N83: 8 | O83: 9 | P83: 1点=1円換算、右詰め先頭0固定、00000000～09999999の範囲で有効 | AL83: ● | BD83: ,数値
P84: 取消返品時=元取引の金額を設定 ※桁数以下でも前ゼロパディングしない。
D85: 13 | E85: 取引ID | N85: 32 | O85: X | P85: 取引ID(22桁) ＋スペース(10桁) ※スペースは不要 | AL85: ● | BD85: ,'文字'
P86: 取引IDは実施業務により以下を設定する。
P87: 与信同時売上時：店コード(4) + POS番号(4) + 取引日付(8) + 取引通番(4) + 取引内通番(2)
P88: 返金時：返金をおこなう売上の元取引ID
D89: 14 | E89: 元伝票番号 | N89: 20 | O89: X | P89: 取消返品時、元取引の伝票番号を入れる。 （※右詰め、先頭0固定） | AL89: ALL 0 | AO89: ● | BD89: ,'文字'
P90: 売上（出金）時は"ALL 0"を設定（設定値無視）
D91: 15 | E91: キャンペーン付与拒否フラグ | N91: 1 | O91: X | P91: スペース固定 | AL91: ○ | BD91: ,'文字'
D93: 16 | E93: サブ店コード | N93: 12 | O93: 9 | P93: "0"固定 ※桁数以下でも前ゼロパディングしない。 | AL93: 〇 | BD93: ,数値
N95: ※データ部の桁数については可変長項目の為、項目の最大桁数になります。 | AL95: ○：既定の値をセット、●：条件によりセットする値が異なる
C96: 形式 | E96: タイプ | I96: 備考
C97: 9 | E97: 数値タイプ | I97: 桁数以下の場合、先頭0固定
C98: X | E98: 文字タイプ | I98: 桁数以下の場合、左詰め 残りSPACE
C103: 表A. カード情報設定データ | AN103: 表B.カード情報
D104: カード入力区分 | K104: 桁数 | N104: 説明 | AN104: 【 JISⅠストライプ情報の場合】
D105: １：JISⅠ（ABA）の時 | K105: 39 | N105: カード裏面第二トラックの開始符号から終了符号までの39バイトをASCⅡコードに変換して設定する | AN105: 項番 | AP105: 項目 | AT105: 桁数 | AU105: 属性 | AW105: 自動ブランド判定 設定値
K106: 41 | N106: ALL SPACE | AN106: 1 | AP106: 開始符号 | AT106: 1 | AU106: a | AW106: 「；」 0x3B：固定
D107: 2：JISⅡの時 | K107: 71 | N107: カード表面のj開始符号から終了符号までの71バイトをASCⅡコードに変換して設定する | AN107: 2 | AP107: バーコード１ | AT107: 16 | AU107: n | AW107: 項目内 固定文字4桁「8900」 + バーコード1～12桁目 ※バーコード桁数が12桁以上の可変長の場合、 分割して設定
K108: 9 | N108: ALL SPACE
AN111: 3 | AP111: セパレータ | AT111: 1 | AU111: a | AW111: 「=」 0x3D：固定
AN112: 4 | AP112: サービス識別 | AT112: 4 | AU112: n | AW112: 自動ブランド判定 → 8912
AN113: 5 | AP113: バーコード2 | AT113: 16 | AU113: n | AW113: 項目内 バーコード桁数が28桁未満の場合、バーコード 13～末桁目（0～最大15桁）+ バーコード終了文字１桁（固定文字"@"） ※左詰、残り０埋め バーコード桁数が28桁以上の場合、バーコード 13～28桁目
AN117: 6 | AP117: 終了符号 | AT117: 1 | AU117: a | AW117: 「?」 0x3F：固定
AN118: 7 | AP118: 予備 | AT118: 41 | AU118: p | AW118: スペース バーコード桁数が28桁以上の場合、バーコード 29桁～末桁目（0～最大29桁）+ バーコード終了文字１桁（固定文字"@"） ※左詰、残り半角空白埋め | BH118: ※CVセンタへ送信出来るバーコード桁数のMAX桁数は
BH119: 57桁(バーコード1:12桁+バーコード2:16桁+予備:29桁)まで。
C120: ■売上（出金） レコード例（△：半角スペース）
D123: ①固定部（△：半角スペース）
E126: ※1～20の項番は、P.1の表中の項番に対応します。
E127: ※固定部の各項目は、形式（数値/文字）に関わらず、全項目を連結して1項目としてレコード出力されます。
D129: ②データ部（△：半角スペース）
E135: ※1～16の項番は、P.2の表中の項番に対応します。
E136: ※データ部の各項目は、形式が数値ならば数値のみ、形式が文字ならば 「’」（シングルクォーテーション）で括られた状態で、それぞれ1項目としてカンマ区切りでレコード出力されます。
C138: ■取消返品 レコード例（△：半角スペース）
D141: ①固定部（△：半角スペース）
E144: ※1～20の項番は、P.1の表中の項番に対応します。
E145: ※固定部の各項目は、形式（数値/文字）に関わらず、全項目を連結して1項目としてレコード出力されます。
D147: ②データ部（△：半角スペース）
E153: ※1～16の項番は、P.2の表中の項番に対応します。
E154: ※データ部の各項目は、形式が数値ならば数値のみ、形式が文字ならば 「’」（シングルクォーテーション）で括られた状態で、それぞれ1項目としてカンマ区切りでレコード出力されます。

Sheet 《貼付元》価格マトリクス
D2: ① マークダウン （売価） | E2: ② タイムサービス特売 （売価） | F2: ③ 期間特売 （売価） | G2: ④ 自動値引/割引 （割引） | I2: ⑤ バンドルミックスマッチ （売価） | J2: ⑥ マニュアル（売価） | K2: ⑦ マニュアル（値引） | L2: ⑧ マニュアル（割引） | M2: ⑨ 値引バーコード （売価） | N2: ⑩ 値引バーコード （値引） | O2: ⑪ 値引バーコード （割引） | P2: ⑫ 値引バーコード （カット品） | Q2: ⑬ 値引バーコード （クーポン値引額） | R2: ⑭ 値引バーコード （クーポン値引率）
G3: A④ 大分類 | H3: B④ 中分類
C4: DISC_CLSS_ID→ | D4: 91111 | E4: 91121 | F4: 91141 | G4: 91326 | H4: 91324 | I4: 91316 | J4: 91220 | K4: 91220 | L4: 91220 | M4: 91220 | N4: 91220 | O4: 91220 | P4: 91220 | Q4: 91220 | R4: 91220
B5: ① マークダウン （売価） | D5: 重複不可
B7: ② タイムサービス特売 （売価） | D7: ① | E7: 安価 ②/② ※1
D8: 【トラン】①+②0 | E8: 【トラン】②安価
B9: ③ 期間特売（売価） | D9: ① | E9: ② | F9: 安価 ③/③ ※1
D10: 【トラン】①+③0 | E10: 【トラン】②+③0 | F10: 【トラン】③安価
B11: ④ 自動値引/割引 （割引） | D11: ① | E11: 両立 ②→④ | F11: 両立 ③→④ | G11: 安価 ④/④ ※1 ※2
C12: A④ 大分類 | D12: 【トラン】①+④0 | E12: 【トラン】②+④ | F12: 【トラン】③+④ | G12: 【トラン】A④安価
C13: B④ 中分類 | G13: 【トラン】 A④安価：A④+B④0 B④安価：A④0+B④ | H13: 【トラン】B④安価
B14: ⑤ バンドルミックスマッチ （売価） | D14: 安価 ①/⑤ | E14: 安価 ②/⑤ | F14: 安価 ③/⑤ | G14: 安価 ④/⑤ | I14: 安価 ⑤/⑤ ※4
D15: 【トラン】 ①安価：①+⑤0 ⑤安価：①+⑤差 | E15: 【トラン】 ②安価：②+⑤0 ⑤安価：②+⑤差 | F15: 【トラン】 ③安価：③+⑤0 ⑤安価：③+⑤差 | G15: 【トラン】 ④安価：④+⑤0 ⑤安価：④+⑤差 | I15: 【トラン】⑤安価
B16: ⑥ マニュアル（売価） ※5 | D16: ⑥ | E16: ⑥ | F16: ⑥ | G16: ⑥ | I16: ⑥ | J16: 重複不可 操作エラー
D17: 【トラン】①+⑥差 | E17: 【トラン】②+⑥差 | F17: 【トラン】③+⑥差 | G17: 【トラン】④0+⑥ | I17: 【トラン】⑤0+⑥
B18: ⑦ マニュアル（値引） | D18: 両立 ①→⑦ | E18: 両立 ②→⑦ | F18: 両立 ③→⑦ | G18: 両立 ④→⑦ | I18: 両立 ⑤→⑦ ※3 | J18: 重複不可 操作エラー | K18: 重複不可 操作エラー
D19: 【トラン】①+⑦ | E19: 【トラン】②+⑦ | F19: 【トラン】③+⑦ | G19: 【トラン】④+⑦ | I19: 【トラン】⑤+⑦
B20: ⑧ マニュアル（割引） | D20: 両立 ①→⑧ | E20: 両立 ②→⑧ | F20: 両立 ③→⑧ | G20: 両立 ④→⑧ | I20: 両立 ⑤→⑧ ※3 | J20: 重複不可 操作エラー | K20: 重複不可 操作エラー | L20: 重複不可 操作エラー
D21: 【トラン】①+⑧ | E21: 【トラン】②+⑧ | F21: 【トラン】③+⑧ | G21: 【トラン】④+⑧ | I21: 【トラン】⑤+⑧
B22: ⑨ 値引バーコード （売価） ※5 | D22: ⑨ | E22: ⑨ | F22: ⑨ | G22: ⑨ | I22: ⑨ | J22: 重複不可 ⑨ 操作エラー | K22: 重複不可 ⑨ 操作エラー | L22: 重複不可 ⑨ 操作エラー | M22: 重複不可
D23: 【トラン】①+⑨差 | E23: 【トラン】②+⑨差 | F23: 【トラン】③+⑨差 | G23: 【トラン】④0+⑨ | I23: 【トラン】⑤0+⑨
B24: ⑩ 値引バーコード （値引） | D24: 両立 ①→⑩ | E24: 両立 ②→⑩ | F24: 両立 ③→⑩ | G24: 両立 ④→⑩ | I24: 両立 ⑤→⑩ ※3 | J24: 重複不可 ⑩ 操作エラー | K24: 重複不可 ⑩ 操作エラー | L24: 重複不可 ⑩ 操作エラー | M24: 重複不可 | N24: 重複不可
D25: 【トラン】①+⑩ | E25: 【トラン】②+⑩ | F25: 【トラン】③+⑩ | G25: 【トラン】④+⑩ | I25: 【トラン】⑤+⑩
B26: ⑪ 値引バーコード （割引） | D26: 両立 ①→⑪ | E26: 両立 ②→⑪ | F26: 両立 ③→⑪ | G26: 両立 ④→⑪ | I26: 両立 ⑤→⑪ ※3 | J26: 重複不可 ⑪ 操作エラー | K26: 重複不可 ⑪ 操作エラー | L26: 重複不可 ⑪ 操作エラー | M26: 重複不可 | N26: 重複不可 | O26: 重複不可
D27: 【トラン】①+⑪ | E27: 【トラン】②+⑪ | F27: 【トラン】③+⑪ | G27: 【トラン】④+⑪ | I27: 【トラン】⑤+⑪
B28: ⑫ 値引バーコード（カット品） （売価） ※5 | D28: ⑫ | E28: ⑫ | F28: ⑫ | G28: ⑫ | I28: ⑫ | J28: 重複不可 ⑫ 操作エラー | K28: 重複不可 ⑫ 操作エラー | L28: 重複不可 ⑫ 操作エラー | M28: 重複不可 | N28: 重複不可 | O28: 重複不可 | P28: 重複不可
D29: 【トラン】①+⑫差 | E29: 【トラン】②+⑫差 | F29: 【トラン】③+⑫差 | G29: 【トラン】④0+⑫ | I29: 【トラン】⑤0+⑫
B30: ⑬ 値引バーコード （クーポン値引額） | D30: 両立 ①→⑬ | E30: 両立 ②→⑬ | F30: 両立 ③→⑬ | G30: 両立 ④→⑬ | I30: 両立 ⑤→⑬ ※3 | J30: 重複不可 ⑥ 割引済エラー （⑬→⑥：操作エラー） | K30: 重複不可 ⑦ 割引済エラー （⑬→⑦：操作エラー） | L30: 重複不可 ⑧ 割引済エラー （⑬→⑧：操作エラー） | M30: 重複不可 ⑨ 割引済エラー | N30: 重複不可 ⑩ 割引済エラー | O30: 重複不可 ⑪ 割引済エラー | P30: 重複不可 ⑫ 割引済エラー | Q30: 重複不可 割引済エラー
D31: 【トラン】①+⑬ | E31: 【トラン】②+⑬ | F31: 【トラン】③+⑬ | G31: 【トラン】④+⑬ | I31: 【トラン】⑤+⑬
B32: ⑭ 値引バーコード （クーポン値引率） | D32: 両立 ①→⑭ | E32: 両立 ②→⑭ | F32: 両立 ③→⑭ | G32: 両立 ④→⑭ | I32: 両立 ⑤→⑭ ※3 | J32: 重複不可 ⑥ 割引済エラー （⑭→⑥：操作エラー） | K32: 重複不可 ⑦ 割引済エラー （⑭→⑦：操作エラー） | L32: 重複不可 ⑧ 割引済エラー （⑭→⑧：操作エラー） | M32: 重複不可 ⑨ 割引済エラー | N32: 重複不可 ⑩ 割引済エラー | O32: 重複不可 ⑪ 割引済エラー | P32: 重複不可 ⑫ 割引済エラー | Q32: 重複不可 割引済エラー | R32: 重複不可 割引済エラー
D33: 【トラン】①+⑭ | E33: 【トラン】②+⑭ | F33: 【トラン】③+⑭ | G33: 【トラン】④+⑭ | I33: 【トラン】⑤+⑭
B34: ※1：価格や割引率が当日付で緊急登録された場合は、価格が高くても緊急登録された価格・割引設定を採用する。
B35: ※2：期間指定、時間指定、曜日指定のどのパターン設定にもかかわらず、安価採用となる。
B36: ※3：バンドルミックスマッチ対象商品価格－バンドルミックスマッチ値引按分額(「対象商品合計金額ーバンドルミックスマッチ成立額」を対象商品ごとに按分した価格)から、値引額・割引額を減算する。
B37: ※4：翌日以降に適用開始となる設定は重複可。ただし、当日付で適用開始となる設定を重複して設定しようとした場合、グループ重複エラーとなり設定不可。
B38: ※5：マニュアル/値引バーコード（売価）は、値下げの場合は、値引として扱ってLN_DISCOUNTを作成する(MANUAL_PRICEは作成しない)。
B39: 値上げ(マニュアルのみ可能)および同額(マニュアル/値引きバーコードの両方とも可能)の場合は、値引として扱わずにMANUAL_PRICEを作成する(LN_DISCOUNTは作成しない)。
