Workbook

Sheet 表紙
A1: システム名 | K1: システム種別 | W1: 概要設計 | AP1: 作成者 | AT1: 作成日 | AY1: 更新者 | BC1: 更新日 | BH1: 版数
A2: POSサーバ | K2: 全般 | AP2: Huy Nguyen | AT2: =改廃履歴!$B$11 -> 45532 | BH2: =LOOKUP(2,1/(改廃履歴!O11:O30000<>""),改廃履歴!O11:O30000) -> 0.31
A4: 機能カテゴリ | H4: 機能一覧 | U4: 項目 | Z4: いなげや様向け | AP4: {=RIGHT(CELL("filename",$A$1),LEN(CELL("filename",$A$1))-FIND("]",CELL("filename",$A$1)))} -> #VALUE!
L16: 現金専用簡易セルフPOS 基本設計書
L24: =K2&"/"&H4&"/"&Z4 -> 全般/機能一覧/いなげや様向け
Q44: 承認日 | AA44: 承認者 | AQ44: 版数

Sheet 改廃履歴
A1: システム名 | K1: システム種別 | W1: =IF(表紙!W1="","",表紙!W1) -> 概要設計 | AP1: 作成者 | AT1: 作成日 | AY1: 更新者 | BC1: 更新日 | BH1: 版数
A2: =IF(表紙!A2="","",表紙!A2) -> POSサーバ | K2: =IF(表紙!K2="","",表紙!K2) -> 全般 | AP2: =IF(表紙!AP2="","",表紙!AP2) -> Huy Nguyen | AT2: =IF(表紙!AT2="","",表紙!AT2) -> 45532 | AY2: =IF(表紙!AY2="","",表紙!AY2) | BC2: =IF(表紙!BC2="","",表紙!BC2) | BH2: =IF(表紙!BH2="","",表紙!BH2) -> 0.31
A4: 機能カテゴリ | H4: =IF(表紙!H4="","",表紙!H4) -> 機能一覧 | U4: 項目 | Z4: =IF(表紙!Z4="","",表紙!Z4) -> いなげや様向け | AP4: {=RIGHT(CELL("filename",$A$1),LEN(CELL("filename",$A$1))-FIND("]",CELL("filename",$A$1)))} -> #VALUE!
B8: ■改廃履歴
B10: 更新日付 | H10: 更新者 | O10: 版数 | S10: 変更内容 | AX10: 承認日付 | BD10: 承認者
B11: 45532 | H11: Huy Nguyen | O11: 0.1 | S11: 初版作成
B13: 45769 | H13: Thanh Nguyên | O13: 0.3 | S13: 機能一覧（POSサーバ2.0）シートを大幅更新
B15: 45770 | H15: Thanh Nguyên | O15: 0.31 | S15: 追記

Sheet 全体構成
A1: システム名 | K1: システム種別 | W1: =IF(表紙!W1="","",表紙!W1) -> 概要設計 | AP1: 作成者 | AT1: 作成日 | AY1: 更新者 | BC1: 更新日 | BH1: 版数
A2: =IF(表紙!A2="","",表紙!A2) -> POSサーバ | K2: =IF(表紙!K2="","",表紙!K2) -> 全般 | AP2: =IF(表紙!AP2="","",表紙!AP2) -> Huy Nguyen | AT2: =IF(表紙!AT2="","",表紙!AT2) -> 45532 | AY2: =IF(表紙!AY2="","",表紙!AY2) | BC2: =IF(表紙!BC2="","",表紙!BC2) | BH2: =IF(表紙!BH2="","",表紙!BH2) -> 0.31
A4: 機能カテゴリ | H4: =IF(表紙!H4="","",表紙!H4) -> 機能一覧 | U4: 項目 | Z4: =IF(表紙!Z4="","",表紙!Z4) -> いなげや様向け | AP4: {=RIGHT(CELL("filename",$A$1),LEN(CELL("filename",$A$1))-FIND("]",CELL("filename",$A$1)))} -> #VALUE!

Sheet 機能一覧（POSサーバ2.0）
B1: 〇：対象 △：開発中 -：未着手 ×：想定外
W5: MM | X5: =X6/20 -> 36.915 | Y5: =Y6/20 -> 2.0825 | Z5: =Z6/20 -> 43.4625 | AA5: =AA6/20 -> 49.1435 | AB5: =AB6/20 -> 14.381 | AC5: =AC6/20 -> 14.381 | AD5: =AD6/20 -> 160.3655 | AE5: =AD5*1.15 -> 184.42032 | AF5: =AE5*350000 -> 64547114
B6: 機能概要 | H6: 説明 | I6: いなげや | J6: カスミ | M6: 重複 | N6: 20_画面設計 | O6: 画面ID | P6: 30_機能設計 | Q6: 機能ID | R6: 40_API設計 | S6: APIID | T6: DB設計 | U6: DB_ID | W6: MD | X6: =SUMIF($W$7:$W$529,"*",X$7:X$529) -> 738.3 | Y6: =SUMIF($W$7:$W$529,"*",Y$7:Y$529) -> 41.65 | Z6: =SUMIF($W$7:$W$529,"*",Z$7:Z$529) -> 869.25 | AA6: =SUMIF($W$7:$W$529,"*",AA$7:AA$529) -> 982.87 | AB6: =SUMIF($W$7:$W$529,"*",AB$7:AB$529) -> 287.62 | AC6: =SUMIF($W$7:$W$529,"*",AC$7:AC$529) -> 287.62 | AD6: =SUMIF($W$7:$W$529,"*",AD$7:AD$529) -> 3207.31
J7: 電子棚札 | K7: LABO | L7: 筑波大学 | W7: 難易度 | X7: 設計 | Y7: モック | Z7: Code | AA7: FT | AB7: IT | AC7: PT | AD7: 合計
B8: 00_インフラ | X8: =SUM(X9:X30) -> 160.66 | Y8: =SUM(Y9:Y30) -> 0 | Z8: =SUM(Z9:Z30) -> 189 | AA8: =SUM(AA9:AA30) -> 213.58 | AB8: =SUM(AB9:AB30) -> 62.38 | AC8: =SUM(AC9:AC30) -> 62.38 | AD8: =SUM(AD9:AD30) -> 688 | AE8: =AD8/20 -> 34.4 | AF8: =AE8*350000 -> 12040000
B9: AWS構築 | X9: =_xlfn.XLOOKUP(W9,マスタ!A:A,マスタ!C:C,0)*M9 -> 0 | Y9: =IF(N9="",0,_xlfn.XLOOKUP(W9,マスタ!A:A,マスタ!D:D,0)*M9) -> 0 | Z9: =_xlfn.XLOOKUP(W9,マスタ!A:A,マスタ!E:E,0)*M9 -> 0 | AA9: =_xlfn.XLOOKUP(W9,マスタ!A:A,マスタ!F:F,0)*M9 -> 0 | AB9: =_xlfn.XLOOKUP(W9,マスタ!A:A,マスタ!G:G,0)*M9 -> 0 | AC9: =_xlfn.XLOOKUP(W9,マスタ!A:A,マスタ!H:H,0)*M9 -> 0 | AD9: =SUM(X9:AC9) -> 0
C10: ステージング環境構築 | X10: =_xlfn.XLOOKUP(W10,マスタ!A:A,マスタ!C:C,0)*M10 -> 0 | Y10: =IF(N10="",0,_xlfn.XLOOKUP(W10,マスタ!A:A,マスタ!D:D,0)*M10) -> 0 | Z10: =_xlfn.XLOOKUP(W10,マスタ!A:A,マスタ!E:E,0)*M10 -> 0 | AA10: =_xlfn.XLOOKUP(W10,マスタ!A:A,マスタ!F:F,0)*M10 -> 0 | AB10: =_xlfn.XLOOKUP(W10,マスタ!A:A,マスタ!G:G,0)*M10 -> 0 | AC10: =_xlfn.XLOOKUP(W10,マスタ!A:A,マスタ!H:H,0)*M10 -> 0 | AD10: =SUM(X10:AC10) -> 0
D11: フェーズ１：外部連携(マスタ) | I11: 〇 | J11: 〇 | K11: 〇 | L11: 〇 | M11: 2 | W11: 複雑 | X11: =_xlfn.XLOOKUP(W11,マスタ!A:A,マスタ!C:C,0)*M11 -> 5.96 | Y11: =IF(N11="",0,_xlfn.XLOOKUP(W11,マスタ!A:A,マスタ!D:D,0)*M11) -> 0 | Z11: =_xlfn.XLOOKUP(W11,マスタ!A:A,マスタ!E:E,0)*M11 -> 7 | AA11: =_xlfn.XLOOKUP(W11,マスタ!A:A,マスタ!F:F,0)*M11 -> 7.92 | AB11: =_xlfn.XLOOKUP(W11,マスタ!A:A,マスタ!G:G,0)*M11 -> 2.32 | AC11: =_xlfn.XLOOKUP(W11,マスタ!A:A,マスタ!H:H,0)*M11 -> 2.32 | AD11: =SUM(X11:AC11) -> 25.52
D12: フェーズ２：POSアプリ反映 | I12: 〇 | J12: 〇 | K12: 〇 | L12: 〇 | M12: 2 | W12: より複雑 | X12: =_xlfn.XLOOKUP(W12,マスタ!A:A,マスタ!C:C,0)*M12 -> 11.9 | Y12: =IF(N12="",0,_xlfn.XLOOKUP(W12,マスタ!A:A,マスタ!D:D,0)*M12) -> 0 | Z12: =_xlfn.XLOOKUP(W12,マスタ!A:A,マスタ!E:E,0)*M12 -> 14 | AA12: =_xlfn.XLOOKUP(W12,マスタ!A:A,マスタ!F:F,0)*M12 -> 15.82 | AB12: =_xlfn.XLOOKUP(W12,マスタ!A:A,マスタ!G:G,0)*M12 -> 4.62 | AC12: =_xlfn.XLOOKUP(W12,マスタ!A:A,マスタ!H:H,0)*M12 -> 4.62 | AD12: =SUM(X12:AC12) -> 50.96
D13: フェーズ３：POSアプリ実績連携 | I13: 〇 | J13: 〇 | K13: 〇 | L13: 〇 | M13: 2 | W13: より複雑 | X13: =_xlfn.XLOOKUP(W13,マスタ!A:A,マスタ!C:C,0)*M13 -> 11.9 | Y13: =IF(N13="",0,_xlfn.XLOOKUP(W13,マスタ!A:A,マスタ!D:D,0)*M13) -> 0 | Z13: =_xlfn.XLOOKUP(W13,マスタ!A:A,マスタ!E:E,0)*M13 -> 14 | AA13: =_xlfn.XLOOKUP(W13,マスタ!A:A,マスタ!F:F,0)*M13 -> 15.82 | AB13: =_xlfn.XLOOKUP(W13,マスタ!A:A,マスタ!G:G,0)*M13 -> 4.62 | AC13: =_xlfn.XLOOKUP(W13,マスタ!A:A,マスタ!H:H,0)*M13 -> 4.62 | AD13: =SUM(X13:AC13) -> 50.96
D14: フェーズ４：各種集計 | I14: 〇 | J14: 〇 | K14: 〇 | L14: 〇 | M14: 2 | W14: より複雑 | X14: =_xlfn.XLOOKUP(W14,マスタ!A:A,マスタ!C:C,0)*M14 -> 11.9 | Y14: =IF(N14="",0,_xlfn.XLOOKUP(W14,マスタ!A:A,マスタ!D:D,0)*M14) -> 0 | Z14: =_xlfn.XLOOKUP(W14,マスタ!A:A,マスタ!E:E,0)*M14 -> 14 | AA14: =_xlfn.XLOOKUP(W14,マスタ!A:A,マスタ!F:F,0)*M14 -> 15.82 | AB14: =_xlfn.XLOOKUP(W14,マスタ!A:A,マスタ!G:G,0)*M14 -> 4.62 | AC14: =_xlfn.XLOOKUP(W14,マスタ!A:A,マスタ!H:H,0)*M14 -> 4.62 | AD14: =SUM(X14:AC14) -> 50.96
D15: フェーズ５：外部連携(実績) | I15: 〇 | J15: 〇 | K15: 〇 | L15: 〇 | M15: 2 | W15: より複雑 | X15: =_xlfn.XLOOKUP(W15,マスタ!A:A,マスタ!C:C,0)*M15 -> 11.9 | Y15: =IF(N15="",0,_xlfn.XLOOKUP(W15,マスタ!A:A,マスタ!D:D,0)*M15) -> 0 | Z15: =_xlfn.XLOOKUP(W15,マスタ!A:A,マスタ!E:E,0)*M15 -> 14 | AA15: =_xlfn.XLOOKUP(W15,マスタ!A:A,マスタ!F:F,0)*M15 -> 15.82 | AB15: =_xlfn.XLOOKUP(W15,マスタ!A:A,マスタ!G:G,0)*M15 -> 4.62 | AC15: =_xlfn.XLOOKUP(W15,マスタ!A:A,マスタ!H:H,0)*M15 -> 4.62 | AD15: =SUM(X15:AC15) -> 50.96
D16: フェーズ６：監視環境構築 | I16: 〇 | J16: 〇 | K16: 〇 | L16: 〇 | M16: 2 | W16: より複雑 | X16: =_xlfn.XLOOKUP(W16,マスタ!A:A,マスタ!C:C,0)*M16 -> 11.9 | Y16: =IF(N16="",0,_xlfn.XLOOKUP(W16,マスタ!A:A,マスタ!D:D,0)*M16) -> 0 | Z16: =_xlfn.XLOOKUP(W16,マスタ!A:A,マスタ!E:E,0)*M16 -> 14 | AA16: =_xlfn.XLOOKUP(W16,マスタ!A:A,マスタ!F:F,0)*M16 -> 15.82 | AB16: =_xlfn.XLOOKUP(W16,マスタ!A:A,マスタ!G:G,0)*M16 -> 4.62 | AC16: =_xlfn.XLOOKUP(W16,マスタ!A:A,マスタ!H:H,0)*M16 -> 4.62 | AD16: =SUM(X16:AC16) -> 50.96
D17: フェーズ７：負荷試験 | I17: 〇 | J17: 〇 | K17: 〇 | L17: 〇 | M17: 2 | W17: より複雑 | X17: =_xlfn.XLOOKUP(W17,マスタ!A:A,マスタ!C:C,0)*M17 -> 11.9 | Y17: =IF(N17="",0,_xlfn.XLOOKUP(W17,マスタ!A:A,マスタ!D:D,0)*M17) -> 0 | Z17: =_xlfn.XLOOKUP(W17,マスタ!A:A,マスタ!E:E,0)*M17 -> 14 | AA17: =_xlfn.XLOOKUP(W17,マスタ!A:A,マスタ!F:F,0)*M17 -> 15.82 | AB17: =_xlfn.XLOOKUP(W17,マスタ!A:A,マスタ!G:G,0)*M17 -> 4.62 | AC17: =_xlfn.XLOOKUP(W17,マスタ!A:A,マスタ!H:H,0)*M17 -> 4.62 | AD17: =SUM(X17:AC17) -> 50.96
C18: 本番環境構築 | X18: =_xlfn.XLOOKUP(W18,マスタ!A:A,マスタ!C:C,0)*M18 -> 0 | Y18: =IF(N18="",0,_xlfn.XLOOKUP(W18,マスタ!A:A,マスタ!D:D,0)*M18) -> 0 | Z18: =_xlfn.XLOOKUP(W18,マスタ!A:A,マスタ!E:E,0)*M18 -> 0 | AA18: =_xlfn.XLOOKUP(W18,マスタ!A:A,マスタ!F:F,0)*M18 -> 0 | AB18: =_xlfn.XLOOKUP(W18,マスタ!A:A,マスタ!G:G,0)*M18 -> 0 | AC18: =_xlfn.XLOOKUP(W18,マスタ!A:A,マスタ!H:H,0)*M18 -> 0 | AD18: =SUM(X18:AC18) -> 0
D19: フェーズ１：01_外部連携(マスタ) | I19: 〇 | J19: 〇 | K19: 〇 | L19: 〇 | M19: 2 | W19: より複雑 | X19: =_xlfn.XLOOKUP(W19,マスタ!A:A,マスタ!C:C,0)*M19 -> 11.9 | Y19: =IF(N19="",0,_xlfn.XLOOKUP(W19,マスタ!A:A,マスタ!D:D,0)*M19) -> 0 | Z19: =_xlfn.XLOOKUP(W19,マスタ!A:A,マスタ!E:E,0)*M19 -> 14 | AA19: =_xlfn.XLOOKUP(W19,マスタ!A:A,マスタ!F:F,0)*M19 -> 15.82 | AB19: =_xlfn.XLOOKUP(W19,マスタ!A:A,マスタ!G:G,0)*M19 -> 4.62 | AC19: =_xlfn.XLOOKUP(W19,マスタ!A:A,マスタ!H:H,0)*M19 -> 4.62 | AD19: =SUM(X19:AC19) -> 50.96
D20: フェーズ２：POSアプリ反映 | I20: 〇 | J20: 〇 | K20: 〇 | L20: 〇 | M20: 2 | W20: より複雑 | X20: =_xlfn.XLOOKUP(W20,マスタ!A:A,マスタ!C:C,0)*M20 -> 11.9 | Y20: =IF(N20="",0,_xlfn.XLOOKUP(W20,マスタ!A:A,マスタ!D:D,0)*M20) -> 0 | Z20: =_xlfn.XLOOKUP(W20,マスタ!A:A,マスタ!E:E,0)*M20 -> 14 | AA20: =_xlfn.XLOOKUP(W20,マスタ!A:A,マスタ!F:F,0)*M20 -> 15.82 | AB20: =_xlfn.XLOOKUP(W20,マスタ!A:A,マスタ!G:G,0)*M20 -> 4.62 | AC20: =_xlfn.XLOOKUP(W20,マスタ!A:A,マスタ!H:H,0)*M20 -> 4.62 | AD20: =SUM(X20:AC20) -> 50.96
D21: フェーズ３：POSアプリ実績連携 | I21: 〇 | J21: 〇 | K21: 〇 | L21: 〇 | M21: 2 | W21: より複雑 | X21: =_xlfn.XLOOKUP(W21,マスタ!A:A,マスタ!C:C,0)*M21 -> 11.9 | Y21: =IF(N21="",0,_xlfn.XLOOKUP(W21,マスタ!A:A,マスタ!D:D,0)*M21) -> 0 | Z21: =_xlfn.XLOOKUP(W21,マスタ!A:A,マスタ!E:E,0)*M21 -> 14 | AA21: =_xlfn.XLOOKUP(W21,マスタ!A:A,マスタ!F:F,0)*M21 -> 15.82 | AB21: =_xlfn.XLOOKUP(W21,マスタ!A:A,マスタ!G:G,0)*M21 -> 4.62 | AC21: =_xlfn.XLOOKUP(W21,マスタ!A:A,マスタ!H:H,0)*M21 -> 4.62 | AD21: =SUM(X21:AC21) -> 50.96
D22: フェーズ４：各種集計 | I22: 〇 | J22: 〇 | K22: 〇 | L22: 〇 | M22: 2 | W22: より複雑 | X22: =_xlfn.XLOOKUP(W22,マスタ!A:A,マスタ!C:C,0)*M22 -> 11.9 | Y22: =IF(N22="",0,_xlfn.XLOOKUP(W22,マスタ!A:A,マスタ!D:D,0)*M22) -> 0 | Z22: =_xlfn.XLOOKUP(W22,マスタ!A:A,マスタ!E:E,0)*M22 -> 14 | AA22: =_xlfn.XLOOKUP(W22,マスタ!A:A,マスタ!F:F,0)*M22 -> 15.82 | AB22: =_xlfn.XLOOKUP(W22,マスタ!A:A,マスタ!G:G,0)*M22 -> 4.62 | AC22: =_xlfn.XLOOKUP(W22,マスタ!A:A,マスタ!H:H,0)*M22 -> 4.62 | AD22: =SUM(X22:AC22) -> 50.96
D23: フェーズ５：外部連携(実績) | I23: 〇 | J23: 〇 | K23: 〇 | L23: 〇 | M23: 2 | W23: より複雑 | X23: =_xlfn.XLOOKUP(W23,マスタ!A:A,マスタ!C:C,0)*M23 -> 11.9 | Y23: =IF(N23="",0,_xlfn.XLOOKUP(W23,マスタ!A:A,マスタ!D:D,0)*M23) -> 0 | Z23: =_xlfn.XLOOKUP(W23,マスタ!A:A,マスタ!E:E,0)*M23 -> 14 | AA23: =_xlfn.XLOOKUP(W23,マスタ!A:A,マスタ!F:F,0)*M23 -> 15.82 | AB23: =_xlfn.XLOOKUP(W23,マスタ!A:A,マスタ!G:G,0)*M23 -> 4.62 | AC23: =_xlfn.XLOOKUP(W23,マスタ!A:A,マスタ!H:H,0)*M23 -> 4.62 | AD23: =SUM(X23:AC23) -> 50.96
D24: フェーズ６：監視環境構築 | I24: 〇 | J24: 〇 | K24: 〇 | L24: 〇 | M24: 2 | W24: より複雑 | X24: =_xlfn.XLOOKUP(W24,マスタ!A:A,マスタ!C:C,0)*M24 -> 11.9 | Y24: =IF(N24="",0,_xlfn.XLOOKUP(W24,マスタ!A:A,マスタ!D:D,0)*M24) -> 0 | Z24: =_xlfn.XLOOKUP(W24,マスタ!A:A,マスタ!E:E,0)*M24 -> 14 | AA24: =_xlfn.XLOOKUP(W24,マスタ!A:A,マスタ!F:F,0)*M24 -> 15.82 | AB24: =_xlfn.XLOOKUP(W24,マスタ!A:A,マスタ!G:G,0)*M24 -> 4.62 | AC24: =_xlfn.XLOOKUP(W24,マスタ!A:A,マスタ!H:H,0)*M24 -> 4.62 | AD24: =SUM(X24:AC24) -> 50.96
D25: フェーズ７：負荷試験 | I25: 〇 | J25: 〇 | K25: 〇 | L25: 〇 | M25: 2 | W25: より複雑 | X25: =_xlfn.XLOOKUP(W25,マスタ!A:A,マスタ!C:C,0)*M25 -> 11.9 | Y25: =IF(N25="",0,_xlfn.XLOOKUP(W25,マスタ!A:A,マスタ!D:D,0)*M25) -> 0 | Z25: =_xlfn.XLOOKUP(W25,マスタ!A:A,マスタ!E:E,0)*M25 -> 14 | AA25: =_xlfn.XLOOKUP(W25,マスタ!A:A,マスタ!F:F,0)*M25 -> 15.82 | AB25: =_xlfn.XLOOKUP(W25,マスタ!A:A,マスタ!G:G,0)*M25 -> 4.62 | AC25: =_xlfn.XLOOKUP(W25,マスタ!A:A,マスタ!H:H,0)*M25 -> 4.62 | AD25: =SUM(X25:AC25) -> 50.96
B26: ネットワーク構築 | X26: =_xlfn.XLOOKUP(W26,マスタ!A:A,マスタ!C:C,0)*M26 -> 0 | Y26: =IF(N26="",0,_xlfn.XLOOKUP(W26,マスタ!A:A,マスタ!D:D,0)*M26) -> 0 | Z26: =_xlfn.XLOOKUP(W26,マスタ!A:A,マスタ!E:E,0)*M26 -> 0 | AA26: =_xlfn.XLOOKUP(W26,マスタ!A:A,マスタ!F:F,0)*M26 -> 0 | AB26: =_xlfn.XLOOKUP(W26,マスタ!A:A,マスタ!G:G,0)*M26 -> 0 | AC26: =_xlfn.XLOOKUP(W26,マスタ!A:A,マスタ!H:H,0)*M26 -> 0 | AD26: =SUM(X26:AC26) -> 0
C27: カスミ→いなげや | H27: いなげやPOSをKTCでのテストのため（Satsfa,カード決済など。） | I27: △ | J27: ー | K27: ー | L27: ー | M27: 0 | W27: より複雑 | X27: =_xlfn.XLOOKUP(W27,マスタ!A:A,マスタ!C:C,0)*M27 -> 0 | Y27: =IF(N27="",0,_xlfn.XLOOKUP(W27,マスタ!A:A,マスタ!D:D,0)*M27) -> 0 | Z27: =_xlfn.XLOOKUP(W27,マスタ!A:A,マスタ!E:E,0)*M27 -> 0 | AA27: =_xlfn.XLOOKUP(W27,マスタ!A:A,マスタ!F:F,0)*M27 -> 0 | AB27: =_xlfn.XLOOKUP(W27,マスタ!A:A,マスタ!G:G,0)*M27 -> 0 | AC27: =_xlfn.XLOOKUP(W27,マスタ!A:A,マスタ!H:H,0)*M27 -> 0 | AD27: =SUM(X27:AC27) -> 0
C28: いなげや→AFS | H28: いなげや様でのWAONチャージ、決済のため | I28: 〇 | J28: ー | K28: ー | L28: ー | M28: 0 | W28: より複雑 | X28: =_xlfn.XLOOKUP(W28,マスタ!A:A,マスタ!C:C,0)*M28 -> 0 | Y28: =IF(N28="",0,_xlfn.XLOOKUP(W28,マスタ!A:A,マスタ!D:D,0)*M28) -> 0 | Z28: =_xlfn.XLOOKUP(W28,マスタ!A:A,マスタ!E:E,0)*M28 -> 0 | AA28: =_xlfn.XLOOKUP(W28,マスタ!A:A,マスタ!F:F,0)*M28 -> 0 | AB28: =_xlfn.XLOOKUP(W28,マスタ!A:A,マスタ!G:G,0)*M28 -> 0 | AC28: =_xlfn.XLOOKUP(W28,マスタ!A:A,マスタ!H:H,0)*M28 -> 0 | AD28: =SUM(X28:AC28) -> 0
C29: Luvina→AFS | H29: カスミ様カード決済、WAONチャージ等 | I29: 〇 | J29: 〇 | K29: 〇 | L29: 〇 | M29: 0 | W29: より複雑 | X29: =_xlfn.XLOOKUP(W29,マスタ!A:A,マスタ!C:C,0)*M29 -> 0 | Y29: =IF(N29="",0,_xlfn.XLOOKUP(W29,マスタ!A:A,マスタ!D:D,0)*M29) -> 0 | Z29: =_xlfn.XLOOKUP(W29,マスタ!A:A,マスタ!E:E,0)*M29 -> 0 | AA29: =_xlfn.XLOOKUP(W29,マスタ!A:A,マスタ!F:F,0)*M29 -> 0 | AB29: =_xlfn.XLOOKUP(W29,マスタ!A:A,マスタ!G:G,0)*M29 -> 0 | AC29: =_xlfn.XLOOKUP(W29,マスタ!A:A,マスタ!H:H,0)*M29 -> 0 | AD29: =SUM(X29:AC29) -> 0
C30: Luvina→VD | H30: ignicaPOINTチャージ、決済 | I30: 〇 | J30: 〇 | K30: 〇 | L30: 〇 | M30: 0 | W30: より複雑 | X30: =_xlfn.XLOOKUP(W30,マスタ!A:A,マスタ!C:C,0)*M30 -> 0 | Y30: =IF(N30="",0,_xlfn.XLOOKUP(W30,マスタ!A:A,マスタ!D:D,0)*M30) -> 0 | Z30: =_xlfn.XLOOKUP(W30,マスタ!A:A,マスタ!E:E,0)*M30 -> 0 | AA30: =_xlfn.XLOOKUP(W30,マスタ!A:A,マスタ!F:F,0)*M30 -> 0 | AB30: =_xlfn.XLOOKUP(W30,マスタ!A:A,マスタ!G:G,0)*M30 -> 0 | AC30: =_xlfn.XLOOKUP(W30,マスタ!A:A,マスタ!H:H,0)*M30 -> 0 | AD30: =SUM(X30:AC30) -> 0
B31: 01_ファイルコピー | X31: =SUM(X32:X33) -> 0 | Y31: =SUM(Y32:Y33) -> 0 | Z31: =SUM(Z32:Z33) -> 0 | AA31: =SUM(AA32:AA33) -> 0 | AB31: =SUM(AB32:AB33) -> 0 | AC31: =SUM(AC32:AC33) -> 0 | AD31: =SUM(AD32:AD33) -> 0 | AE31: =AD31/20 -> 0 | AF31: =AE31*350000 -> 0
B32: Scan&GoServerより、いなげやマスタ連携 | I32: 〇 | K32: ー | L32: ー | M32: 0 | W32: 複雑 | X32: =_xlfn.XLOOKUP(W32,マスタ!A:A,マスタ!C:C,0)*M32 -> 0 | Y32: =IF(N32="",0,_xlfn.XLOOKUP(W32,マスタ!A:A,マスタ!D:D,0)*M32) -> 0 | Z32: =_xlfn.XLOOKUP(W32,マスタ!A:A,マスタ!E:E,0)*M32 -> 0 | AA32: =_xlfn.XLOOKUP(W32,マスタ!A:A,マスタ!F:F,0)*M32 -> 0 | AB32: =_xlfn.XLOOKUP(W32,マスタ!A:A,マスタ!G:G,0)*M32 -> 0 | AC32: =_xlfn.XLOOKUP(W32,マスタ!A:A,マスタ!H:H,0)*M32 -> 0 | AD32: =SUM(X32:AC32) -> 0
B33: 01_BIPROGY様により、マスタファイルの送信先追加 | I33: ー | K33: 〇 | L33: 〇 | M33: 0 | W33: 複雑 | X33: =_xlfn.XLOOKUP(W33,マスタ!A:A,マスタ!C:C,0)*M33 -> 0 | Y33: =IF(N33="",0,_xlfn.XLOOKUP(W33,マスタ!A:A,マスタ!D:D,0)*M33) -> 0 | Z33: =_xlfn.XLOOKUP(W33,マスタ!A:A,マスタ!E:E,0)*M33 -> 0 | AA33: =_xlfn.XLOOKUP(W33,マスタ!A:A,マスタ!F:F,0)*M33 -> 0 | AB33: =_xlfn.XLOOKUP(W33,マスタ!A:A,マスタ!G:G,0)*M33 -> 0 | AC33: =_xlfn.XLOOKUP(W33,マスタ!A:A,マスタ!H:H,0)*M33 -> 0 | AD33: =SUM(X33:AC33) -> 0
B34: 02_外部連携(マスタ) | X34: =SUM(X35:X168) -> 101 | Y34: =SUM(Y35:Y168) -> 5.24 | Z34: =SUM(Z35:Z168) -> 119.28 | AA34: =SUM(AA35:AA168) -> 134.64 | AB34: =SUM(AB35:AB168) -> 39.72 | AC34: =SUM(AC35:AC168) -> 39.72 | AD34: =SUM(AD35:AD168) -> 439.6 | AE34: =AD34/20 -> 21.98 | AF34: =AE34*350000 -> 7693000
B35: 00_sftpサーバー設定 | H35: ファイル受信用にSFTPサーバーの構築 | X35: =_xlfn.XLOOKUP(W35,マスタ!A:A,マスタ!C:C,0)*M35 -> 0 | Y35: =IF(N35="",0,_xlfn.XLOOKUP(W35,マスタ!A:A,マスタ!D:D,0)*M35) -> 0 | Z35: =_xlfn.XLOOKUP(W35,マスタ!A:A,マスタ!E:E,0)*M35 -> 0 | AA35: =_xlfn.XLOOKUP(W35,マスタ!A:A,マスタ!F:F,0)*M35 -> 0 | AB35: =_xlfn.XLOOKUP(W35,マスタ!A:A,マスタ!G:G,0)*M35 -> 0 | AC35: =_xlfn.XLOOKUP(W35,マスタ!A:A,マスタ!H:H,0)*M35 -> 0 | AD35: =SUM(X35:AC35) -> 0
C36: 01_BIPROGY
D37: ディレクトリ作成 | I37: ー | J37: 〇 | K37: 〇 | L37: 〇 | M37: 1 | W37: 簡単 | X37: =_xlfn.XLOOKUP(W37,マスタ!A:A,マスタ!C:C,0)*M37 -> 0.99 | Y37: =IF(N37="",0,_xlfn.XLOOKUP(W37,マスタ!A:A,マスタ!D:D,0)*M37) -> 0 | Z37: =_xlfn.XLOOKUP(W37,マスタ!A:A,マスタ!E:E,0)*M37 -> 1.17 | AA37: =_xlfn.XLOOKUP(W37,マスタ!A:A,マスタ!F:F,0)*M37 -> 1.32 | AB37: =_xlfn.XLOOKUP(W37,マスタ!A:A,マスタ!G:G,0)*M37 -> 0.39 | AC37: =_xlfn.XLOOKUP(W37,マスタ!A:A,マスタ!H:H,0)*M37 -> 0.39 | AD37: =SUM(X37:AC37) -> 4.26
D38: アカウント作成(秘密キー含む) | I38: ー | J38: 〇 | K38: 〇 | L38: 〇 | M38: 1 | W38: 簡単 | X38: =_xlfn.XLOOKUP(W38,マスタ!A:A,マスタ!C:C,0)*M38 -> 0.99 | Y38: =IF(N38="",0,_xlfn.XLOOKUP(W38,マスタ!A:A,マスタ!D:D,0)*M38) -> 0 | Z38: =_xlfn.XLOOKUP(W38,マスタ!A:A,マスタ!E:E,0)*M38 -> 1.17 | AA38: =_xlfn.XLOOKUP(W38,マスタ!A:A,マスタ!F:F,0)*M38 -> 1.32 | AB38: =_xlfn.XLOOKUP(W38,マスタ!A:A,マスタ!G:G,0)*M38 -> 0.39 | AC38: =_xlfn.XLOOKUP(W38,マスタ!A:A,マスタ!H:H,0)*M38 -> 0.39 | AD38: =SUM(X38:AC38) -> 4.26
C39: 31_Scan&Go(カスミ)
D40: ディレクトリ作成 | I40: ー | J40: 〇 | K40: 〇 | L40: 〇 | M40: 1 | W40: 簡単 | X40: =_xlfn.XLOOKUP(W40,マスタ!A:A,マスタ!C:C,0)*M40 -> 0.99 | Y40: =IF(N40="",0,_xlfn.XLOOKUP(W40,マスタ!A:A,マスタ!D:D,0)*M40) -> 0 | Z40: =_xlfn.XLOOKUP(W40,マスタ!A:A,マスタ!E:E,0)*M40 -> 1.17 | AA40: =_xlfn.XLOOKUP(W40,マスタ!A:A,マスタ!F:F,0)*M40 -> 1.32 | AB40: =_xlfn.XLOOKUP(W40,マスタ!A:A,マスタ!G:G,0)*M40 -> 0.39 | AC40: =_xlfn.XLOOKUP(W40,マスタ!A:A,マスタ!H:H,0)*M40 -> 0.39 | AD40: =SUM(X40:AC40) -> 4.26
D41: アカウント作成(秘密キー含む) | I41: ー | J41: 〇 | K41: 〇 | L41: 〇 | M41: 1 | W41: 簡単 | X41: =_xlfn.XLOOKUP(W41,マスタ!A:A,マスタ!C:C,0)*M41 -> 0.99 | Y41: =IF(N41="",0,_xlfn.XLOOKUP(W41,マスタ!A:A,マスタ!D:D,0)*M41) -> 0 | Z41: =_xlfn.XLOOKUP(W41,マスタ!A:A,マスタ!E:E,0)*M41 -> 1.17 | AA41: =_xlfn.XLOOKUP(W41,マスタ!A:A,マスタ!F:F,0)*M41 -> 1.32 | AB41: =_xlfn.XLOOKUP(W41,マスタ!A:A,マスタ!G:G,0)*M41 -> 0.39 | AC41: =_xlfn.XLOOKUP(W41,マスタ!A:A,マスタ!H:H,0)*M41 -> 0.39 | AD41: =SUM(X41:AC41) -> 4.26
C42: 32_Scan&Go(いなげや)
D43: ディレクトリ作成 | I43: 〇 | J43: ー | K43: ー | L43: ー | M43: 1 | W43: 簡単 | X43: =_xlfn.XLOOKUP(W43,マスタ!A:A,マスタ!C:C,0)*M43 -> 0.99 | Y43: =IF(N43="",0,_xlfn.XLOOKUP(W43,マスタ!A:A,マスタ!D:D,0)*M43) -> 0 | Z43: =_xlfn.XLOOKUP(W43,マスタ!A:A,マスタ!E:E,0)*M43 -> 1.17 | AA43: =_xlfn.XLOOKUP(W43,マスタ!A:A,マスタ!F:F,0)*M43 -> 1.32 | AB43: =_xlfn.XLOOKUP(W43,マスタ!A:A,マスタ!G:G,0)*M43 -> 0.39 | AC43: =_xlfn.XLOOKUP(W43,マスタ!A:A,マスタ!H:H,0)*M43 -> 0.39 | AD43: =SUM(X43:AC43) -> 4.26
D44: アカウント作成(秘密キー含む) | I44: 〇 | J44: ー | K44: ー | L44: ー | M44: 1 | W44: 簡単 | X44: =_xlfn.XLOOKUP(W44,マスタ!A:A,マスタ!C:C,0)*M44 -> 0.99 | Y44: =IF(N44="",0,_xlfn.XLOOKUP(W44,マスタ!A:A,マスタ!D:D,0)*M44) -> 0 | Z44: =_xlfn.XLOOKUP(W44,マスタ!A:A,マスタ!E:E,0)*M44 -> 1.17 | AA44: =_xlfn.XLOOKUP(W44,マスタ!A:A,マスタ!F:F,0)*M44 -> 1.32 | AB44: =_xlfn.XLOOKUP(W44,マスタ!A:A,マスタ!G:G,0)*M44 -> 0.39 | AC44: =_xlfn.XLOOKUP(W44,マスタ!A:A,マスタ!H:H,0)*M44 -> 0.39 | AD44: =SUM(X44:AC44) -> 4.26
B45: 01_BIPROGY | H45: BIPROGY様用、基本バッチ処理作成 | I45: ー | K45: 〇 | L45: 〇 | M45: 1 | W45: 簡単 | X45: =_xlfn.XLOOKUP(W45,マスタ!A:A,マスタ!C:C,0)*M45 -> 0.99 | Y45: =IF(N45="",0,_xlfn.XLOOKUP(W45,マスタ!A:A,マスタ!D:D,0)*M45) -> 0 | Z45: =_xlfn.XLOOKUP(W45,マスタ!A:A,マスタ!E:E,0)*M45 -> 1.17 | AA45: =_xlfn.XLOOKUP(W45,マスタ!A:A,マスタ!F:F,0)*M45 -> 1.32 | AB45: =_xlfn.XLOOKUP(W45,マスタ!A:A,マスタ!G:G,0)*M45 -> 0.39 | AC45: =_xlfn.XLOOKUP(W45,マスタ!A:A,マスタ!H:H,0)*M45 -> 0.39 | AD45: =SUM(X45:AC45) -> 4.26
C46: ＰＬＵメンテ | I46: ー | K46: ー | L46: ー | M46: 0 | W46: 簡単 | X46: =_xlfn.XLOOKUP(W46,マスタ!A:A,マスタ!C:C,0)*M46 -> 0 | Y46: =IF(N46="",0,_xlfn.XLOOKUP(W46,マスタ!A:A,マスタ!D:D,0)*M46) -> 0 | Z46: =_xlfn.XLOOKUP(W46,マスタ!A:A,マスタ!E:E,0)*M46 -> 0 | AA46: =_xlfn.XLOOKUP(W46,マスタ!A:A,マスタ!F:F,0)*M46 -> 0 | AB46: =_xlfn.XLOOKUP(W46,マスタ!A:A,マスタ!G:G,0)*M46 -> 0 | AC46: =_xlfn.XLOOKUP(W46,マスタ!A:A,マスタ!H:H,0)*M46 -> 0 | AD46: =SUM(X46:AC46) -> 0
E47: サブバッチ作成 | I47: ー | K47: 〇 | L47: 〇 | M47: 1 | W47: 簡単 | X47: =_xlfn.XLOOKUP(W47,マスタ!A:A,マスタ!C:C,0)*M47 -> 0.99 | Y47: =IF(N47="",0,_xlfn.XLOOKUP(W47,マスタ!A:A,マスタ!D:D,0)*M47) -> 0 | Z47: =_xlfn.XLOOKUP(W47,マスタ!A:A,マスタ!E:E,0)*M47 -> 1.17 | AA47: =_xlfn.XLOOKUP(W47,マスタ!A:A,マスタ!F:F,0)*M47 -> 1.32 | AB47: =_xlfn.XLOOKUP(W47,マスタ!A:A,マスタ!G:G,0)*M47 -> 0.39 | AC47: =_xlfn.XLOOKUP(W47,マスタ!A:A,マスタ!H:H,0)*M47 -> 0.39 | AD47: =SUM(X47:AC47) -> 4.26
E48: データチェック機能 | I48: ー | K48: 〇 | L48: 〇 | M48: 1 | W48: 簡単 | X48: =_xlfn.XLOOKUP(W48,マスタ!A:A,マスタ!C:C,0)*M48 -> 0.99 | Y48: =IF(N48="",0,_xlfn.XLOOKUP(W48,マスタ!A:A,マスタ!D:D,0)*M48) -> 0 | Z48: =_xlfn.XLOOKUP(W48,マスタ!A:A,マスタ!E:E,0)*M48 -> 1.17 | AA48: =_xlfn.XLOOKUP(W48,マスタ!A:A,マスタ!F:F,0)*M48 -> 1.32 | AB48: =_xlfn.XLOOKUP(W48,マスタ!A:A,マスタ!G:G,0)*M48 -> 0.39 | AC48: =_xlfn.XLOOKUP(W48,マスタ!A:A,マスタ!H:H,0)*M48 -> 0.39 | AD48: =SUM(X48:AC48) -> 4.26
C49: 企画メンテ | I49: ー | K49: ー | L49: ー | M49: 0 | W49: 簡単 | X49: =_xlfn.XLOOKUP(W49,マスタ!A:A,マスタ!C:C,0)*M49 -> 0 | Y49: =IF(N49="",0,_xlfn.XLOOKUP(W49,マスタ!A:A,マスタ!D:D,0)*M49) -> 0 | Z49: =_xlfn.XLOOKUP(W49,マスタ!A:A,マスタ!E:E,0)*M49 -> 0 | AA49: =_xlfn.XLOOKUP(W49,マスタ!A:A,マスタ!F:F,0)*M49 -> 0 | AB49: =_xlfn.XLOOKUP(W49,マスタ!A:A,マスタ!G:G,0)*M49 -> 0 | AC49: =_xlfn.XLOOKUP(W49,マスタ!A:A,マスタ!H:H,0)*M49 -> 0 | AD49: =SUM(X49:AC49) -> 0
E50: サブバッチ作成 | I50: ー | K50: 〇 | L50: 〇 | M50: 1 | W50: 簡単 | X50: =_xlfn.XLOOKUP(W50,マスタ!A:A,マスタ!C:C,0)*M50 -> 0.99 | Y50: =IF(N50="",0,_xlfn.XLOOKUP(W50,マスタ!A:A,マスタ!D:D,0)*M50) -> 0 | Z50: =_xlfn.XLOOKUP(W50,マスタ!A:A,マスタ!E:E,0)*M50 -> 1.17 | AA50: =_xlfn.XLOOKUP(W50,マスタ!A:A,マスタ!F:F,0)*M50 -> 1.32 | AB50: =_xlfn.XLOOKUP(W50,マスタ!A:A,マスタ!G:G,0)*M50 -> 0.39 | AC50: =_xlfn.XLOOKUP(W50,マスタ!A:A,マスタ!H:H,0)*M50 -> 0.39 | AD50: =SUM(X50:AC50) -> 4.26
E51: データチェック機能 | I51: ー | K51: 〇 | L51: 〇 | M51: 1 | W51: 簡単 | X51: =_xlfn.XLOOKUP(W51,マスタ!A:A,マスタ!C:C,0)*M51 -> 0.99 | Y51: =IF(N51="",0,_xlfn.XLOOKUP(W51,マスタ!A:A,マスタ!D:D,0)*M51) -> 0 | Z51: =_xlfn.XLOOKUP(W51,マスタ!A:A,マスタ!E:E,0)*M51 -> 1.17 | AA51: =_xlfn.XLOOKUP(W51,マスタ!A:A,マスタ!F:F,0)*M51 -> 1.32 | AB51: =_xlfn.XLOOKUP(W51,マスタ!A:A,マスタ!G:G,0)*M51 -> 0.39 | AC51: =_xlfn.XLOOKUP(W51,マスタ!A:A,マスタ!H:H,0)*M51 -> 0.39 | AD51: =SUM(X51:AC51) -> 4.26
C52: 組合せメンテ | I52: ー | K52: ー | L52: ー | M52: 0 | W52: 簡単 | X52: =_xlfn.XLOOKUP(W52,マスタ!A:A,マスタ!C:C,0)*M52 -> 0 | Y52: =IF(N52="",0,_xlfn.XLOOKUP(W52,マスタ!A:A,マスタ!D:D,0)*M52) -> 0 | Z52: =_xlfn.XLOOKUP(W52,マスタ!A:A,マスタ!E:E,0)*M52 -> 0 | AA52: =_xlfn.XLOOKUP(W52,マスタ!A:A,マスタ!F:F,0)*M52 -> 0 | AB52: =_xlfn.XLOOKUP(W52,マスタ!A:A,マスタ!G:G,0)*M52 -> 0 | AC52: =_xlfn.XLOOKUP(W52,マスタ!A:A,マスタ!H:H,0)*M52 -> 0 | AD52: =SUM(X52:AC52) -> 0
E53: サブバッチ作成 | I53: ー | K53: 〇 | L53: 〇 | M53: 1 | W53: 簡単 | X53: =_xlfn.XLOOKUP(W53,マスタ!A:A,マスタ!C:C,0)*M53 -> 0.99 | Y53: =IF(N53="",0,_xlfn.XLOOKUP(W53,マスタ!A:A,マスタ!D:D,0)*M53) -> 0 | Z53: =_xlfn.XLOOKUP(W53,マスタ!A:A,マスタ!E:E,0)*M53 -> 1.17 | AA53: =_xlfn.XLOOKUP(W53,マスタ!A:A,マスタ!F:F,0)*M53 -> 1.32 | AB53: =_xlfn.XLOOKUP(W53,マスタ!A:A,マスタ!G:G,0)*M53 -> 0.39 | AC53: =_xlfn.XLOOKUP(W53,マスタ!A:A,マスタ!H:H,0)*M53 -> 0.39 | AD53: =SUM(X53:AC53) -> 4.26
E54: データチェック機能 | I54: ー | K54: 〇 | L54: 〇 | M54: 1 | W54: 簡単 | X54: =_xlfn.XLOOKUP(W54,マスタ!A:A,マスタ!C:C,0)*M54 -> 0.99 | Y54: =IF(N54="",0,_xlfn.XLOOKUP(W54,マスタ!A:A,マスタ!D:D,0)*M54) -> 0 | Z54: =_xlfn.XLOOKUP(W54,マスタ!A:A,マスタ!E:E,0)*M54 -> 1.17 | AA54: =_xlfn.XLOOKUP(W54,マスタ!A:A,マスタ!F:F,0)*M54 -> 1.32 | AB54: =_xlfn.XLOOKUP(W54,マスタ!A:A,マスタ!G:G,0)*M54 -> 0.39 | AC54: =_xlfn.XLOOKUP(W54,マスタ!A:A,マスタ!H:H,0)*M54 -> 0.39 | AD54: =SUM(X54:AC54) -> 4.26
C55: 特売メンテ | I55: ー | K55: ー | L55: ー | M55: 0 | W55: 簡単 | X55: =_xlfn.XLOOKUP(W55,マスタ!A:A,マスタ!C:C,0)*M55 -> 0 | Y55: =IF(N55="",0,_xlfn.XLOOKUP(W55,マスタ!A:A,マスタ!D:D,0)*M55) -> 0 | Z55: =_xlfn.XLOOKUP(W55,マスタ!A:A,マスタ!E:E,0)*M55 -> 0 | AA55: =_xlfn.XLOOKUP(W55,マスタ!A:A,マスタ!F:F,0)*M55 -> 0 | AB55: =_xlfn.XLOOKUP(W55,マスタ!A:A,マスタ!G:G,0)*M55 -> 0 | AC55: =_xlfn.XLOOKUP(W55,マスタ!A:A,マスタ!H:H,0)*M55 -> 0 | AD55: =SUM(X55:AC55) -> 0
E56: サブバッチ作成 | I56: ー | K56: 〇 | L56: 〇 | M56: 1 | W56: 簡単 | X56: =_xlfn.XLOOKUP(W56,マスタ!A:A,マスタ!C:C,0)*M56 -> 0.99 | Y56: =IF(N56="",0,_xlfn.XLOOKUP(W56,マスタ!A:A,マスタ!D:D,0)*M56) -> 0 | Z56: =_xlfn.XLOOKUP(W56,マスタ!A:A,マスタ!E:E,0)*M56 -> 1.17 | AA56: =_xlfn.XLOOKUP(W56,マスタ!A:A,マスタ!F:F,0)*M56 -> 1.32 | AB56: =_xlfn.XLOOKUP(W56,マスタ!A:A,マスタ!G:G,0)*M56 -> 0.39 | AC56: =_xlfn.XLOOKUP(W56,マスタ!A:A,マスタ!H:H,0)*M56 -> 0.39 | AD56: =SUM(X56:AC56) -> 4.26
E57: データチェック機能 | I57: ー | K57: 〇 | L57: 〇 | M57: 1 | W57: 簡単 | X57: =_xlfn.XLOOKUP(W57,マスタ!A:A,マスタ!C:C,0)*M57 -> 0.99 | Y57: =IF(N57="",0,_xlfn.XLOOKUP(W57,マスタ!A:A,マスタ!D:D,0)*M57) -> 0 | Z57: =_xlfn.XLOOKUP(W57,マスタ!A:A,マスタ!E:E,0)*M57 -> 1.17 | AA57: =_xlfn.XLOOKUP(W57,マスタ!A:A,マスタ!F:F,0)*M57 -> 1.32 | AB57: =_xlfn.XLOOKUP(W57,マスタ!A:A,マスタ!G:G,0)*M57 -> 0.39 | AC57: =_xlfn.XLOOKUP(W57,マスタ!A:A,マスタ!H:H,0)*M57 -> 0.39 | AD57: =SUM(X57:AC57) -> 4.26
C58: 商品階層メンテデータ | I58: ー | K58: ー | L58: ー | M58: 0 | W58: 簡単 | X58: =_xlfn.XLOOKUP(W58,マスタ!A:A,マスタ!C:C,0)*M58 -> 0 | Y58: =IF(N58="",0,_xlfn.XLOOKUP(W58,マスタ!A:A,マスタ!D:D,0)*M58) -> 0 | Z58: =_xlfn.XLOOKUP(W58,マスタ!A:A,マスタ!E:E,0)*M58 -> 0 | AA58: =_xlfn.XLOOKUP(W58,マスタ!A:A,マスタ!F:F,0)*M58 -> 0 | AB58: =_xlfn.XLOOKUP(W58,マスタ!A:A,マスタ!G:G,0)*M58 -> 0 | AC58: =_xlfn.XLOOKUP(W58,マスタ!A:A,マスタ!H:H,0)*M58 -> 0 | AD58: =SUM(X58:AC58) -> 0
E59: サブバッチ作成 | I59: ー | K59: 〇 | L59: 〇 | M59: 1 | W59: 簡単 | X59: =_xlfn.XLOOKUP(W59,マスタ!A:A,マスタ!C:C,0)*M59 -> 0.99 | Y59: =IF(N59="",0,_xlfn.XLOOKUP(W59,マスタ!A:A,マスタ!D:D,0)*M59) -> 0 | Z59: =_xlfn.XLOOKUP(W59,マスタ!A:A,マスタ!E:E,0)*M59 -> 1.17 | AA59: =_xlfn.XLOOKUP(W59,マスタ!A:A,マスタ!F:F,0)*M59 -> 1.32 | AB59: =_xlfn.XLOOKUP(W59,マスタ!A:A,マスタ!G:G,0)*M59 -> 0.39 | AC59: =_xlfn.XLOOKUP(W59,マスタ!A:A,マスタ!H:H,0)*M59 -> 0.39 | AD59: =SUM(X59:AC59) -> 4.26
E60: データチェック機能 | I60: ー | K60: 〇 | L60: 〇 | M60: 1 | W60: 簡単 | X60: =_xlfn.XLOOKUP(W60,マスタ!A:A,マスタ!C:C,0)*M60 -> 0.99 | Y60: =IF(N60="",0,_xlfn.XLOOKUP(W60,マスタ!A:A,マスタ!D:D,0)*M60) -> 0 | Z60: =_xlfn.XLOOKUP(W60,マスタ!A:A,マスタ!E:E,0)*M60 -> 1.17 | AA60: =_xlfn.XLOOKUP(W60,マスタ!A:A,マスタ!F:F,0)*M60 -> 1.32 | AB60: =_xlfn.XLOOKUP(W60,マスタ!A:A,マスタ!G:G,0)*M60 -> 0.39 | AC60: =_xlfn.XLOOKUP(W60,マスタ!A:A,マスタ!H:H,0)*M60 -> 0.39 | AD60: =SUM(X60:AC60) -> 4.26
C61: 商品ポイント加算 | I61: ー | K61: ー | L61: ー | M61: 0 | W61: 簡単 | X61: =_xlfn.XLOOKUP(W61,マスタ!A:A,マスタ!C:C,0)*M61 -> 0 | Y61: =IF(N61="",0,_xlfn.XLOOKUP(W61,マスタ!A:A,マスタ!D:D,0)*M61) -> 0 | Z61: =_xlfn.XLOOKUP(W61,マスタ!A:A,マスタ!E:E,0)*M61 -> 0 | AA61: =_xlfn.XLOOKUP(W61,マスタ!A:A,マスタ!F:F,0)*M61 -> 0 | AB61: =_xlfn.XLOOKUP(W61,マスタ!A:A,マスタ!G:G,0)*M61 -> 0 | AC61: =_xlfn.XLOOKUP(W61,マスタ!A:A,マスタ!H:H,0)*M61 -> 0 | AD61: =SUM(X61:AC61) -> 0
E62: サブバッチ作成 | I62: ー | K62: 〇 | L62: 〇 | M62: 1 | W62: 簡単 | X62: =_xlfn.XLOOKUP(W62,マスタ!A:A,マスタ!C:C,0)*M62 -> 0.99 | Y62: =IF(N62="",0,_xlfn.XLOOKUP(W62,マスタ!A:A,マスタ!D:D,0)*M62) -> 0 | Z62: =_xlfn.XLOOKUP(W62,マスタ!A:A,マスタ!E:E,0)*M62 -> 1.17 | AA62: =_xlfn.XLOOKUP(W62,マスタ!A:A,マスタ!F:F,0)*M62 -> 1.32 | AB62: =_xlfn.XLOOKUP(W62,マスタ!A:A,マスタ!G:G,0)*M62 -> 0.39 | AC62: =_xlfn.XLOOKUP(W62,マスタ!A:A,マスタ!H:H,0)*M62 -> 0.39 | AD62: =SUM(X62:AC62) -> 4.26
E63: データチェック機能 | I63: ー | K63: 〇 | L63: 〇 | M63: 1 | W63: 簡単 | X63: =_xlfn.XLOOKUP(W63,マスタ!A:A,マスタ!C:C,0)*M63 -> 0.99 | Y63: =IF(N63="",0,_xlfn.XLOOKUP(W63,マスタ!A:A,マスタ!D:D,0)*M63) -> 0 | Z63: =_xlfn.XLOOKUP(W63,マスタ!A:A,マスタ!E:E,0)*M63 -> 1.17 | AA63: =_xlfn.XLOOKUP(W63,マスタ!A:A,マスタ!F:F,0)*M63 -> 1.32 | AB63: =_xlfn.XLOOKUP(W63,マスタ!A:A,マスタ!G:G,0)*M63 -> 0.39 | AC63: =_xlfn.XLOOKUP(W63,マスタ!A:A,マスタ!H:H,0)*M63 -> 0.39 | AD63: =SUM(X63:AC63) -> 4.26
C64: POP商品マスター | I64: ー | K64: ー | L64: ー | M64: 0 | W64: 簡単 | X64: =_xlfn.XLOOKUP(W64,マスタ!A:A,マスタ!C:C,0)*M64 -> 0 | Y64: =IF(N64="",0,_xlfn.XLOOKUP(W64,マスタ!A:A,マスタ!D:D,0)*M64) -> 0 | Z64: =_xlfn.XLOOKUP(W64,マスタ!A:A,マスタ!E:E,0)*M64 -> 0 | AA64: =_xlfn.XLOOKUP(W64,マスタ!A:A,マスタ!F:F,0)*M64 -> 0 | AB64: =_xlfn.XLOOKUP(W64,マスタ!A:A,マスタ!G:G,0)*M64 -> 0 | AC64: =_xlfn.XLOOKUP(W64,マスタ!A:A,マスタ!H:H,0)*M64 -> 0 | AD64: =SUM(X64:AC64) -> 0
E65: サブバッチ作成 | I65: ー | K65: 〇 | L65: 〇 | M65: 1 | W65: 簡単 | X65: =_xlfn.XLOOKUP(W65,マスタ!A:A,マスタ!C:C,0)*M65 -> 0.99 | Y65: =IF(N65="",0,_xlfn.XLOOKUP(W65,マスタ!A:A,マスタ!D:D,0)*M65) -> 0 | Z65: =_xlfn.XLOOKUP(W65,マスタ!A:A,マスタ!E:E,0)*M65 -> 1.17 | AA65: =_xlfn.XLOOKUP(W65,マスタ!A:A,マスタ!F:F,0)*M65 -> 1.32 | AB65: =_xlfn.XLOOKUP(W65,マスタ!A:A,マスタ!G:G,0)*M65 -> 0.39 | AC65: =_xlfn.XLOOKUP(W65,マスタ!A:A,マスタ!H:H,0)*M65 -> 0.39 | AD65: =SUM(X65:AC65) -> 4.26
E66: データチェック機能 | I66: ー | K66: 〇 | L66: 〇 | M66: 1 | W66: 簡単 | X66: =_xlfn.XLOOKUP(W66,マスタ!A:A,マスタ!C:C,0)*M66 -> 0.99 | Y66: =IF(N66="",0,_xlfn.XLOOKUP(W66,マスタ!A:A,マスタ!D:D,0)*M66) -> 0 | Z66: =_xlfn.XLOOKUP(W66,マスタ!A:A,マスタ!E:E,0)*M66 -> 1.17 | AA66: =_xlfn.XLOOKUP(W66,マスタ!A:A,マスタ!F:F,0)*M66 -> 1.32 | AB66: =_xlfn.XLOOKUP(W66,マスタ!A:A,マスタ!G:G,0)*M66 -> 0.39 | AC66: =_xlfn.XLOOKUP(W66,マスタ!A:A,マスタ!H:H,0)*M66 -> 0.39 | AD66: =SUM(X66:AC66) -> 4.26
C67: 予算 | I67: ー | K67: ー | L67: ー | M67: 0 | W67: 簡単 | X67: =_xlfn.XLOOKUP(W67,マスタ!A:A,マスタ!C:C,0)*M67 -> 0 | Y67: =IF(N67="",0,_xlfn.XLOOKUP(W67,マスタ!A:A,マスタ!D:D,0)*M67) -> 0 | Z67: =_xlfn.XLOOKUP(W67,マスタ!A:A,マスタ!E:E,0)*M67 -> 0 | AA67: =_xlfn.XLOOKUP(W67,マスタ!A:A,マスタ!F:F,0)*M67 -> 0 | AB67: =_xlfn.XLOOKUP(W67,マスタ!A:A,マスタ!G:G,0)*M67 -> 0 | AC67: =_xlfn.XLOOKUP(W67,マスタ!A:A,マスタ!H:H,0)*M67 -> 0 | AD67: =SUM(X67:AC67) -> 0
E68: サブバッチ作成 | I68: ー | K68: 〇 | L68: 〇 | M68: 1 | W68: 簡単 | X68: =_xlfn.XLOOKUP(W68,マスタ!A:A,マスタ!C:C,0)*M68 -> 0.99 | Y68: =IF(N68="",0,_xlfn.XLOOKUP(W68,マスタ!A:A,マスタ!D:D,0)*M68) -> 0 | Z68: =_xlfn.XLOOKUP(W68,マスタ!A:A,マスタ!E:E,0)*M68 -> 1.17 | AA68: =_xlfn.XLOOKUP(W68,マスタ!A:A,マスタ!F:F,0)*M68 -> 1.32 | AB68: =_xlfn.XLOOKUP(W68,マスタ!A:A,マスタ!G:G,0)*M68 -> 0.39 | AC68: =_xlfn.XLOOKUP(W68,マスタ!A:A,マスタ!H:H,0)*M68 -> 0.39 | AD68: =SUM(X68:AC68) -> 4.26
E69: データチェック機能 | I69: ー | K69: 〇 | L69: 〇 | M69: 1 | W69: 簡単 | X69: =_xlfn.XLOOKUP(W69,マスタ!A:A,マスタ!C:C,0)*M69 -> 0.99 | Y69: =IF(N69="",0,_xlfn.XLOOKUP(W69,マスタ!A:A,マスタ!D:D,0)*M69) -> 0 | Z69: =_xlfn.XLOOKUP(W69,マスタ!A:A,マスタ!E:E,0)*M69 -> 1.17 | AA69: =_xlfn.XLOOKUP(W69,マスタ!A:A,マスタ!F:F,0)*M69 -> 1.32 | AB69: =_xlfn.XLOOKUP(W69,マスタ!A:A,マスタ!G:G,0)*M69 -> 0.39 | AC69: =_xlfn.XLOOKUP(W69,マスタ!A:A,マスタ!H:H,0)*M69 -> 0.39 | AD69: =SUM(X69:AC69) -> 4.26
C70: POP棚番マスタ | I70: ー | K70: ー | L70: ー | M70: 0 | W70: 簡単 | X70: =_xlfn.XLOOKUP(W70,マスタ!A:A,マスタ!C:C,0)*M70 -> 0 | Y70: =IF(N70="",0,_xlfn.XLOOKUP(W70,マスタ!A:A,マスタ!D:D,0)*M70) -> 0 | Z70: =_xlfn.XLOOKUP(W70,マスタ!A:A,マスタ!E:E,0)*M70 -> 0 | AA70: =_xlfn.XLOOKUP(W70,マスタ!A:A,マスタ!F:F,0)*M70 -> 0 | AB70: =_xlfn.XLOOKUP(W70,マスタ!A:A,マスタ!G:G,0)*M70 -> 0 | AC70: =_xlfn.XLOOKUP(W70,マスタ!A:A,マスタ!H:H,0)*M70 -> 0 | AD70: =SUM(X70:AC70) -> 0
E71: サブバッチ作成 | I71: ー | K71: 〇 | L71: 〇 | M71: 1 | W71: 簡単 | X71: =_xlfn.XLOOKUP(W71,マスタ!A:A,マスタ!C:C,0)*M71 -> 0.99 | Y71: =IF(N71="",0,_xlfn.XLOOKUP(W71,マスタ!A:A,マスタ!D:D,0)*M71) -> 0 | Z71: =_xlfn.XLOOKUP(W71,マスタ!A:A,マスタ!E:E,0)*M71 -> 1.17 | AA71: =_xlfn.XLOOKUP(W71,マスタ!A:A,マスタ!F:F,0)*M71 -> 1.32 | AB71: =_xlfn.XLOOKUP(W71,マスタ!A:A,マスタ!G:G,0)*M71 -> 0.39 | AC71: =_xlfn.XLOOKUP(W71,マスタ!A:A,マスタ!H:H,0)*M71 -> 0.39 | AD71: =SUM(X71:AC71) -> 4.26
E72: データチェック機能 | I72: ー | K72: 〇 | L72: 〇 | M72: 1 | W72: 簡単 | X72: =_xlfn.XLOOKUP(W72,マスタ!A:A,マスタ!C:C,0)*M72 -> 0.99 | Y72: =IF(N72="",0,_xlfn.XLOOKUP(W72,マスタ!A:A,マスタ!D:D,0)*M72) -> 0 | Z72: =_xlfn.XLOOKUP(W72,マスタ!A:A,マスタ!E:E,0)*M72 -> 1.17 | AA72: =_xlfn.XLOOKUP(W72,マスタ!A:A,マスタ!F:F,0)*M72 -> 1.32 | AB72: =_xlfn.XLOOKUP(W72,マスタ!A:A,マスタ!G:G,0)*M72 -> 0.39 | AC72: =_xlfn.XLOOKUP(W72,マスタ!A:A,マスタ!H:H,0)*M72 -> 0.39 | AD72: =SUM(X72:AC72) -> 4.26
C73: マスタ手動取込 | H73: エラー時などのイレギュラー対応時に、手動でファイルを更新し、アップロードできるようにする。 | I73: ー | K73: 〇 | L73: 〇 | M73: 1 | N73: マスタ取込(手動) OC取込マスタ | O73: SC9401 | W73: 簡単 | X73: =_xlfn.XLOOKUP(W73,マスタ!A:A,マスタ!C:C,0)*M73 -> 0.99 | Y73: =IF(N73="",0,_xlfn.XLOOKUP(W73,マスタ!A:A,マスタ!D:D,0)*M73) -> 0.29 | Z73: =_xlfn.XLOOKUP(W73,マスタ!A:A,マスタ!E:E,0)*M73 -> 1.17 | AA73: =_xlfn.XLOOKUP(W73,マスタ!A:A,マスタ!F:F,0)*M73 -> 1.32 | AB73: =_xlfn.XLOOKUP(W73,マスタ!A:A,マスタ!G:G,0)*M73 -> 0.39 | AC73: =_xlfn.XLOOKUP(W73,マスタ!A:A,マスタ!H:H,0)*M73 -> 0.39 | AD73: =SUM(X73:AC73) -> 4.55
C74: 10日以前データのアーカーイブ機能 | H74: 10日より以前に連携されたデータは、アーカイブ領域に移行する。 １日一回、決められた時間に稼働する。 | I74: ー | K74: 〇 | L74: 〇 | M74: 1 | N74: ？ | W74: 簡単 | X74: =_xlfn.XLOOKUP(W74,マスタ!A:A,マスタ!C:C,0)*M74 -> 0.99 | Y74: =IF(N74="",0,_xlfn.XLOOKUP(W74,マスタ!A:A,マスタ!D:D,0)*M74) -> 0.29 | Z74: =_xlfn.XLOOKUP(W74,マスタ!A:A,マスタ!E:E,0)*M74 -> 1.17 | AA74: =_xlfn.XLOOKUP(W74,マスタ!A:A,マスタ!F:F,0)*M74 -> 1.32 | AB74: =_xlfn.XLOOKUP(W74,マスタ!A:A,マスタ!G:G,0)*M74 -> 0.39 | AC74: =_xlfn.XLOOKUP(W74,マスタ!A:A,マスタ!H:H,0)*M74 -> 0.39 | AD74: =SUM(X74:AC74) -> 4.55
B75: 31_Scan&Go(カスミ) | I75: 〇 | K75: ー | L75: ー | M75: 1 | W75: 簡単 | X75: =_xlfn.XLOOKUP(W75,マスタ!A:A,マスタ!C:C,0)*M75 -> 0.99 | Y75: =IF(N75="",0,_xlfn.XLOOKUP(W75,マスタ!A:A,マスタ!D:D,0)*M75) -> 0 | Z75: =_xlfn.XLOOKUP(W75,マスタ!A:A,マスタ!E:E,0)*M75 -> 1.17 | AA75: =_xlfn.XLOOKUP(W75,マスタ!A:A,マスタ!F:F,0)*M75 -> 1.32 | AB75: =_xlfn.XLOOKUP(W75,マスタ!A:A,マスタ!G:G,0)*M75 -> 0.39 | AC75: =_xlfn.XLOOKUP(W75,マスタ!A:A,マスタ!H:H,0)*M75 -> 0.39 | AD75: =SUM(X75:AC75) -> 4.26
C76: 全件 | E76: いなげやPOSServer用、全件バッチ処理作成 | I76: 〇 | K76: ー | L76: ー | M76: 1 | W76: 簡単 | X76: =_xlfn.XLOOKUP(W76,マスタ!A:A,マスタ!C:C,0)*M76 -> 0.99 | Y76: =IF(N76="",0,_xlfn.XLOOKUP(W76,マスタ!A:A,マスタ!D:D,0)*M76) -> 0 | Z76: =_xlfn.XLOOKUP(W76,マスタ!A:A,マスタ!E:E,0)*M76 -> 1.17 | AA76: =_xlfn.XLOOKUP(W76,マスタ!A:A,マスタ!F:F,0)*M76 -> 1.32 | AB76: =_xlfn.XLOOKUP(W76,マスタ!A:A,マスタ!G:G,0)*M76 -> 0.39 | AC76: =_xlfn.XLOOKUP(W76,マスタ!A:A,マスタ!H:H,0)*M76 -> 0.39 | AD76: =SUM(X76:AC76) -> 4.26
D77: 商品マスタ | H77: ItemMaster_YYYYMMDDHHMMSS.csv | I77: ー | J77: ー | K77: ー | L77: ー | M77: 0 | W77: 簡単 | X77: =_xlfn.XLOOKUP(W77,マスタ!A:A,マスタ!C:C,0)*M77 -> 0 | Y77: =IF(N77="",0,_xlfn.XLOOKUP(W77,マスタ!A:A,マスタ!D:D,0)*M77) -> 0 | Z77: =_xlfn.XLOOKUP(W77,マスタ!A:A,マスタ!E:E,0)*M77 -> 0 | AA77: =_xlfn.XLOOKUP(W77,マスタ!A:A,マスタ!F:F,0)*M77 -> 0 | AB77: =_xlfn.XLOOKUP(W77,マスタ!A:A,マスタ!G:G,0)*M77 -> 0 | AC77: =_xlfn.XLOOKUP(W77,マスタ!A:A,マスタ!H:H,0)*M77 -> 0 | AD77: =SUM(X77:AC77) -> 0
E78: サブバッチ作成 | I78: ー | J78: 〇 | K78: 〇 | L78: 〇 | M78: 1 | W78: 簡単 | X78: =_xlfn.XLOOKUP(W78,マスタ!A:A,マスタ!C:C,0)*M78 -> 0.99 | Y78: =IF(N78="",0,_xlfn.XLOOKUP(W78,マスタ!A:A,マスタ!D:D,0)*M78) -> 0 | Z78: =_xlfn.XLOOKUP(W78,マスタ!A:A,マスタ!E:E,0)*M78 -> 1.17 | AA78: =_xlfn.XLOOKUP(W78,マスタ!A:A,マスタ!F:F,0)*M78 -> 1.32 | AB78: =_xlfn.XLOOKUP(W78,マスタ!A:A,マスタ!G:G,0)*M78 -> 0.39 | AC78: =_xlfn.XLOOKUP(W78,マスタ!A:A,マスタ!H:H,0)*M78 -> 0.39 | AD78: =SUM(X78:AC78) -> 4.26
E79: データチェック機能 | I79: ー | J79: 〇 | K79: 〇 | L79: 〇 | M79: 1 | W79: 簡単 | X79: =_xlfn.XLOOKUP(W79,マスタ!A:A,マスタ!C:C,0)*M79 -> 0.99 | Y79: =IF(N79="",0,_xlfn.XLOOKUP(W79,マスタ!A:A,マスタ!D:D,0)*M79) -> 0 | Z79: =_xlfn.XLOOKUP(W79,マスタ!A:A,マスタ!E:E,0)*M79 -> 1.17 | AA79: =_xlfn.XLOOKUP(W79,マスタ!A:A,マスタ!F:F,0)*M79 -> 1.32 | AB79: =_xlfn.XLOOKUP(W79,マスタ!A:A,マスタ!G:G,0)*M79 -> 0.39 | AC79: =_xlfn.XLOOKUP(W79,マスタ!A:A,マスタ!H:H,0)*M79 -> 0.39 | AD79: =SUM(X79:AC79) -> 4.26
D80: 商品拡張マスタ | H80: ItemExMvkMaster_YYYYMMDDHHMMSS.csv | I80: ー | J80: ー | K80: ー | L80: ー | M80: 0 | W80: 簡単 | X80: =_xlfn.XLOOKUP(W80,マスタ!A:A,マスタ!C:C,0)*M80 -> 0 | Y80: =IF(N80="",0,_xlfn.XLOOKUP(W80,マスタ!A:A,マスタ!D:D,0)*M80) -> 0 | Z80: =_xlfn.XLOOKUP(W80,マスタ!A:A,マスタ!E:E,0)*M80 -> 0 | AA80: =_xlfn.XLOOKUP(W80,マスタ!A:A,マスタ!F:F,0)*M80 -> 0 | AB80: =_xlfn.XLOOKUP(W80,マスタ!A:A,マスタ!G:G,0)*M80 -> 0 | AC80: =_xlfn.XLOOKUP(W80,マスタ!A:A,マスタ!H:H,0)*M80 -> 0 | AD80: =SUM(X80:AC80) -> 0
E81: サブバッチ作成 | I81: ー | J81: 〇 | K81: 〇 | L81: 〇 | M81: 1 | W81: 簡単 | X81: =_xlfn.XLOOKUP(W81,マスタ!A:A,マスタ!C:C,0)*M81 -> 0.99 | Y81: =IF(N81="",0,_xlfn.XLOOKUP(W81,マスタ!A:A,マスタ!D:D,0)*M81) -> 0 | Z81: =_xlfn.XLOOKUP(W81,マスタ!A:A,マスタ!E:E,0)*M81 -> 1.17 | AA81: =_xlfn.XLOOKUP(W81,マスタ!A:A,マスタ!F:F,0)*M81 -> 1.32 | AB81: =_xlfn.XLOOKUP(W81,マスタ!A:A,マスタ!G:G,0)*M81 -> 0.39 | AC81: =_xlfn.XLOOKUP(W81,マスタ!A:A,マスタ!H:H,0)*M81 -> 0.39 | AD81: =SUM(X81:AC81) -> 4.26
E82: データチェック機能 | I82: ー | J82: 〇 | K82: 〇 | L82: 〇 | M82: 1 | W82: 簡単 | X82: =_xlfn.XLOOKUP(W82,マスタ!A:A,マスタ!C:C,0)*M82 -> 0.99 | Y82: =IF(N82="",0,_xlfn.XLOOKUP(W82,マスタ!A:A,マスタ!D:D,0)*M82) -> 0 | Z82: =_xlfn.XLOOKUP(W82,マスタ!A:A,マスタ!E:E,0)*M82 -> 1.17 | AA82: =_xlfn.XLOOKUP(W82,マスタ!A:A,マスタ!F:F,0)*M82 -> 1.32 | AB82: =_xlfn.XLOOKUP(W82,マスタ!A:A,マスタ!G:G,0)*M82 -> 0.39 | AC82: =_xlfn.XLOOKUP(W82,マスタ!A:A,マスタ!H:H,0)*M82 -> 0.39 | AD82: =SUM(X82:AC82) -> 4.26
D83: MMマスタ | H83: CombinationKsmMaster_YYYYMMDDHHMMSS.csv | I83: ー | J83: ー | K83: ー | L83: ー | M83: 0 | W83: 簡単 | X83: =_xlfn.XLOOKUP(W83,マスタ!A:A,マスタ!C:C,0)*M83 -> 0 | Y83: =IF(N83="",0,_xlfn.XLOOKUP(W83,マスタ!A:A,マスタ!D:D,0)*M83) -> 0 | Z83: =_xlfn.XLOOKUP(W83,マスタ!A:A,マスタ!E:E,0)*M83 -> 0 | AA83: =_xlfn.XLOOKUP(W83,マスタ!A:A,マスタ!F:F,0)*M83 -> 0 | AB83: =_xlfn.XLOOKUP(W83,マスタ!A:A,マスタ!G:G,0)*M83 -> 0 | AC83: =_xlfn.XLOOKUP(W83,マスタ!A:A,マスタ!H:H,0)*M83 -> 0 | AD83: =SUM(X83:AC83) -> 0
E84: サブバッチ作成 | I84: ー | J84: 〇 | K84: 〇 | L84: 〇 | M84: 1 | W84: 簡単 | X84: =_xlfn.XLOOKUP(W84,マスタ!A:A,マスタ!C:C,0)*M84 -> 0.99 | Y84: =IF(N84="",0,_xlfn.XLOOKUP(W84,マスタ!A:A,マスタ!D:D,0)*M84) -> 0 | Z84: =_xlfn.XLOOKUP(W84,マスタ!A:A,マスタ!E:E,0)*M84 -> 1.17 | AA84: =_xlfn.XLOOKUP(W84,マスタ!A:A,マスタ!F:F,0)*M84 -> 1.32 | AB84: =_xlfn.XLOOKUP(W84,マスタ!A:A,マスタ!G:G,0)*M84 -> 0.39 | AC84: =_xlfn.XLOOKUP(W84,マスタ!A:A,マスタ!H:H,0)*M84 -> 0.39 | AD84: =SUM(X84:AC84) -> 4.26
E85: データチェック機能 | I85: ー | J85: 〇 | K85: 〇 | L85: 〇 | M85: 1 | W85: 簡単 | X85: =_xlfn.XLOOKUP(W85,マスタ!A:A,マスタ!C:C,0)*M85 -> 0.99 | Y85: =IF(N85="",0,_xlfn.XLOOKUP(W85,マスタ!A:A,マスタ!D:D,0)*M85) -> 0 | Z85: =_xlfn.XLOOKUP(W85,マスタ!A:A,マスタ!E:E,0)*M85 -> 1.17 | AA85: =_xlfn.XLOOKUP(W85,マスタ!A:A,マスタ!F:F,0)*M85 -> 1.32 | AB85: =_xlfn.XLOOKUP(W85,マスタ!A:A,マスタ!G:G,0)*M85 -> 0.39 | AC85: =_xlfn.XLOOKUP(W85,マスタ!A:A,マスタ!H:H,0)*M85 -> 0.39 | AD85: =SUM(X85:AC85) -> 4.26
D86: MM商品マスタ | H86: CombinationItemKsmMaster_YYYYMMDDHHMMSS.csv | I86: ー | J86: ー | K86: ー | L86: ー | M86: 0 | W86: 簡単 | X86: =_xlfn.XLOOKUP(W86,マスタ!A:A,マスタ!C:C,0)*M86 -> 0 | Y86: =IF(N86="",0,_xlfn.XLOOKUP(W86,マスタ!A:A,マスタ!D:D,0)*M86) -> 0 | Z86: =_xlfn.XLOOKUP(W86,マスタ!A:A,マスタ!E:E,0)*M86 -> 0 | AA86: =_xlfn.XLOOKUP(W86,マスタ!A:A,マスタ!F:F,0)*M86 -> 0 | AB86: =_xlfn.XLOOKUP(W86,マスタ!A:A,マスタ!G:G,0)*M86 -> 0 | AC86: =_xlfn.XLOOKUP(W86,マスタ!A:A,マスタ!H:H,0)*M86 -> 0 | AD86: =SUM(X86:AC86) -> 0
E87: サブバッチ作成 | I87: ー | J87: 〇 | K87: 〇 | L87: 〇 | M87: 1 | W87: 簡単 | X87: =_xlfn.XLOOKUP(W87,マスタ!A:A,マスタ!C:C,0)*M87 -> 0.99 | Y87: =IF(N87="",0,_xlfn.XLOOKUP(W87,マスタ!A:A,マスタ!D:D,0)*M87) -> 0 | Z87: =_xlfn.XLOOKUP(W87,マスタ!A:A,マスタ!E:E,0)*M87 -> 1.17 | AA87: =_xlfn.XLOOKUP(W87,マスタ!A:A,マスタ!F:F,0)*M87 -> 1.32 | AB87: =_xlfn.XLOOKUP(W87,マスタ!A:A,マスタ!G:G,0)*M87 -> 0.39 | AC87: =_xlfn.XLOOKUP(W87,マスタ!A:A,マスタ!H:H,0)*M87 -> 0.39 | AD87: =SUM(X87:AC87) -> 4.26
E88: データチェック機能 | I88: ー | J88: 〇 | K88: 〇 | L88: 〇 | M88: 1 | W88: 簡単 | X88: =_xlfn.XLOOKUP(W88,マスタ!A:A,マスタ!C:C,0)*M88 -> 0.99 | Y88: =IF(N88="",0,_xlfn.XLOOKUP(W88,マスタ!A:A,マスタ!D:D,0)*M88) -> 0 | Z88: =_xlfn.XLOOKUP(W88,マスタ!A:A,マスタ!E:E,0)*M88 -> 1.17 | AA88: =_xlfn.XLOOKUP(W88,マスタ!A:A,マスタ!F:F,0)*M88 -> 1.32 | AB88: =_xlfn.XLOOKUP(W88,マスタ!A:A,マスタ!G:G,0)*M88 -> 0.39 | AC88: =_xlfn.XLOOKUP(W88,マスタ!A:A,マスタ!H:H,0)*M88 -> 0.39 | AD88: =SUM(X88:AC88) -> 4.26
D89: MD階層値引マスタ | H89: DiscountMDHierarchyMVKMaster_YYYYMMDDHHMMSS.csv | I89: ー | J89: ー | K89: ー | L89: ー | M89: 0 | W89: 簡単 | X89: =_xlfn.XLOOKUP(W89,マスタ!A:A,マスタ!C:C,0)*M89 -> 0 | Y89: =IF(N89="",0,_xlfn.XLOOKUP(W89,マスタ!A:A,マスタ!D:D,0)*M89) -> 0 | Z89: =_xlfn.XLOOKUP(W89,マスタ!A:A,マスタ!E:E,0)*M89 -> 0 | AA89: =_xlfn.XLOOKUP(W89,マスタ!A:A,マスタ!F:F,0)*M89 -> 0 | AB89: =_xlfn.XLOOKUP(W89,マスタ!A:A,マスタ!G:G,0)*M89 -> 0 | AC89: =_xlfn.XLOOKUP(W89,マスタ!A:A,マスタ!H:H,0)*M89 -> 0 | AD89: =SUM(X89:AC89) -> 0
E90: サブバッチ作成 | I90: ー | J90: 〇 | K90: 〇 | L90: 〇 | M90: 1 | W90: 簡単 | X90: =_xlfn.XLOOKUP(W90,マスタ!A:A,マスタ!C:C,0)*M90 -> 0.99 | Y90: =IF(N90="",0,_xlfn.XLOOKUP(W90,マスタ!A:A,マスタ!D:D,0)*M90) -> 0 | Z90: =_xlfn.XLOOKUP(W90,マスタ!A:A,マスタ!E:E,0)*M90 -> 1.17 | AA90: =_xlfn.XLOOKUP(W90,マスタ!A:A,マスタ!F:F,0)*M90 -> 1.32 | AB90: =_xlfn.XLOOKUP(W90,マスタ!A:A,マスタ!G:G,0)*M90 -> 0.39 | AC90: =_xlfn.XLOOKUP(W90,マスタ!A:A,マスタ!H:H,0)*M90 -> 0.39 | AD90: =SUM(X90:AC90) -> 4.26
E91: データチェック機能 | I91: ー | J91: 〇 | K91: 〇 | L91: 〇 | M91: 1 | W91: 簡単 | X91: =_xlfn.XLOOKUP(W91,マスタ!A:A,マスタ!C:C,0)*M91 -> 0.99 | Y91: =IF(N91="",0,_xlfn.XLOOKUP(W91,マスタ!A:A,マスタ!D:D,0)*M91) -> 0 | Z91: =_xlfn.XLOOKUP(W91,マスタ!A:A,マスタ!E:E,0)*M91 -> 1.17 | AA91: =_xlfn.XLOOKUP(W91,マスタ!A:A,マスタ!F:F,0)*M91 -> 1.32 | AB91: =_xlfn.XLOOKUP(W91,マスタ!A:A,マスタ!G:G,0)*M91 -> 0.39 | AC91: =_xlfn.XLOOKUP(W91,マスタ!A:A,マスタ!H:H,0)*M91 -> 0.39 | AD91: =SUM(X91:AC91) -> 4.26
D92: 特売マスタ | H92: SpecialPriceKsmMaster_YYYYMMDDHHMMSS.csv | I92: ー | J92: ー | K92: ー | L92: ー | M92: 0 | W92: 簡単 | X92: =_xlfn.XLOOKUP(W92,マスタ!A:A,マスタ!C:C,0)*M92 -> 0 | Y92: =IF(N92="",0,_xlfn.XLOOKUP(W92,マスタ!A:A,マスタ!D:D,0)*M92) -> 0 | Z92: =_xlfn.XLOOKUP(W92,マスタ!A:A,マスタ!E:E,0)*M92 -> 0 | AA92: =_xlfn.XLOOKUP(W92,マスタ!A:A,マスタ!F:F,0)*M92 -> 0 | AB92: =_xlfn.XLOOKUP(W92,マスタ!A:A,マスタ!G:G,0)*M92 -> 0 | AC92: =_xlfn.XLOOKUP(W92,マスタ!A:A,マスタ!H:H,0)*M92 -> 0 | AD92: =SUM(X92:AC92) -> 0
E93: サブバッチ作成 | I93: ー | J93: 〇 | K93: 〇 | L93: 〇 | M93: 1 | W93: 簡単 | X93: =_xlfn.XLOOKUP(W93,マスタ!A:A,マスタ!C:C,0)*M93 -> 0.99 | Y93: =IF(N93="",0,_xlfn.XLOOKUP(W93,マスタ!A:A,マスタ!D:D,0)*M93) -> 0 | Z93: =_xlfn.XLOOKUP(W93,マスタ!A:A,マスタ!E:E,0)*M93 -> 1.17 | AA93: =_xlfn.XLOOKUP(W93,マスタ!A:A,マスタ!F:F,0)*M93 -> 1.32 | AB93: =_xlfn.XLOOKUP(W93,マスタ!A:A,マスタ!G:G,0)*M93 -> 0.39 | AC93: =_xlfn.XLOOKUP(W93,マスタ!A:A,マスタ!H:H,0)*M93 -> 0.39 | AD93: =SUM(X93:AC93) -> 4.26
E94: データチェック機能 | I94: ー | J94: 〇 | K94: 〇 | L94: 〇 | M94: 1 | W94: 簡単 | X94: =_xlfn.XLOOKUP(W94,マスタ!A:A,マスタ!C:C,0)*M94 -> 0.99 | Y94: =IF(N94="",0,_xlfn.XLOOKUP(W94,マスタ!A:A,マスタ!D:D,0)*M94) -> 0 | Z94: =_xlfn.XLOOKUP(W94,マスタ!A:A,マスタ!E:E,0)*M94 -> 1.17 | AA94: =_xlfn.XLOOKUP(W94,マスタ!A:A,マスタ!F:F,0)*M94 -> 1.32 | AB94: =_xlfn.XLOOKUP(W94,マスタ!A:A,マスタ!G:G,0)*M94 -> 0.39 | AC94: =_xlfn.XLOOKUP(W94,マスタ!A:A,マスタ!H:H,0)*M94 -> 0.39 | AD94: =SUM(X94:AC94) -> 4.26
D95: 分類マスタ | H95: MDHierarchyMaster_YYYYMMDDHHMMSS.csv | I95: ー | J95: ー | K95: ー | L95: ー | M95: 0 | W95: 簡単 | X95: =_xlfn.XLOOKUP(W95,マスタ!A:A,マスタ!C:C,0)*M95 -> 0 | Y95: =IF(N95="",0,_xlfn.XLOOKUP(W95,マスタ!A:A,マスタ!D:D,0)*M95) -> 0 | Z95: =_xlfn.XLOOKUP(W95,マスタ!A:A,マスタ!E:E,0)*M95 -> 0 | AA95: =_xlfn.XLOOKUP(W95,マスタ!A:A,マスタ!F:F,0)*M95 -> 0 | AB95: =_xlfn.XLOOKUP(W95,マスタ!A:A,マスタ!G:G,0)*M95 -> 0 | AC95: =_xlfn.XLOOKUP(W95,マスタ!A:A,マスタ!H:H,0)*M95 -> 0 | AD95: =SUM(X95:AC95) -> 0
E96: サブバッチ作成 | I96: ー | J96: 〇 | K96: 〇 | L96: 〇 | M96: 1 | W96: 簡単 | X96: =_xlfn.XLOOKUP(W96,マスタ!A:A,マスタ!C:C,0)*M96 -> 0.99 | Y96: =IF(N96="",0,_xlfn.XLOOKUP(W96,マスタ!A:A,マスタ!D:D,0)*M96) -> 0 | Z96: =_xlfn.XLOOKUP(W96,マスタ!A:A,マスタ!E:E,0)*M96 -> 1.17 | AA96: =_xlfn.XLOOKUP(W96,マスタ!A:A,マスタ!F:F,0)*M96 -> 1.32 | AB96: =_xlfn.XLOOKUP(W96,マスタ!A:A,マスタ!G:G,0)*M96 -> 0.39 | AC96: =_xlfn.XLOOKUP(W96,マスタ!A:A,マスタ!H:H,0)*M96 -> 0.39 | AD96: =SUM(X96:AC96) -> 4.26
E97: データチェック機能 | I97: ー | J97: 〇 | K97: 〇 | L97: 〇 | M97: 1 | W97: 簡単 | X97: =_xlfn.XLOOKUP(W97,マスタ!A:A,マスタ!C:C,0)*M97 -> 0.99 | Y97: =IF(N97="",0,_xlfn.XLOOKUP(W97,マスタ!A:A,マスタ!D:D,0)*M97) -> 0 | Z97: =_xlfn.XLOOKUP(W97,マスタ!A:A,マスタ!E:E,0)*M97 -> 1.17 | AA97: =_xlfn.XLOOKUP(W97,マスタ!A:A,マスタ!F:F,0)*M97 -> 1.32 | AB97: =_xlfn.XLOOKUP(W97,マスタ!A:A,マスタ!G:G,0)*M97 -> 0.39 | AC97: =_xlfn.XLOOKUP(W97,マスタ!A:A,マスタ!H:H,0)*M97 -> 0.39 | AD97: =SUM(X97:AC97) -> 4.26
B98: 32_Scan&Go(いなげや) | I98: 〇 | K98: ー | L98: ー | M98: 1 | W98: 簡単 | X98: =_xlfn.XLOOKUP(W98,マスタ!A:A,マスタ!C:C,0)*M98 -> 0.99 | Y98: =IF(N98="",0,_xlfn.XLOOKUP(W98,マスタ!A:A,マスタ!D:D,0)*M98) -> 0 | Z98: =_xlfn.XLOOKUP(W98,マスタ!A:A,マスタ!E:E,0)*M98 -> 1.17 | AA98: =_xlfn.XLOOKUP(W98,マスタ!A:A,マスタ!F:F,0)*M98 -> 1.32 | AB98: =_xlfn.XLOOKUP(W98,マスタ!A:A,マスタ!G:G,0)*M98 -> 0.39 | AC98: =_xlfn.XLOOKUP(W98,マスタ!A:A,マスタ!H:H,0)*M98 -> 0.39 | AD98: =SUM(X98:AC98) -> 4.26
C99: 全件 | E99: いなげやPOSServer用、全件バッチ処理作成 | I99: 〇 | K99: ー | L99: ー | M99: 1 | W99: 簡単 | X99: =_xlfn.XLOOKUP(W99,マスタ!A:A,マスタ!C:C,0)*M99 -> 0.99 | Y99: =IF(N99="",0,_xlfn.XLOOKUP(W99,マスタ!A:A,マスタ!D:D,0)*M99) -> 0 | Z99: =_xlfn.XLOOKUP(W99,マスタ!A:A,マスタ!E:E,0)*M99 -> 1.17 | AA99: =_xlfn.XLOOKUP(W99,マスタ!A:A,マスタ!F:F,0)*M99 -> 1.32 | AB99: =_xlfn.XLOOKUP(W99,マスタ!A:A,マスタ!G:G,0)*M99 -> 0.39 | AC99: =_xlfn.XLOOKUP(W99,マスタ!A:A,マスタ!H:H,0)*M99 -> 0.39 | AD99: =SUM(X99:AC99) -> 4.26
D100: 商品階層マスタ | I100: ー | K100: ー | L100: ー | M100: 0 | W100: 簡単 | X100: =_xlfn.XLOOKUP(W100,マスタ!A:A,マスタ!C:C,0)*M100 -> 0 | Y100: =IF(N100="",0,_xlfn.XLOOKUP(W100,マスタ!A:A,マスタ!D:D,0)*M100) -> 0 | Z100: =_xlfn.XLOOKUP(W100,マスタ!A:A,マスタ!E:E,0)*M100 -> 0 | AA100: =_xlfn.XLOOKUP(W100,マスタ!A:A,マスタ!F:F,0)*M100 -> 0 | AB100: =_xlfn.XLOOKUP(W100,マスタ!A:A,マスタ!G:G,0)*M100 -> 0 | AC100: =_xlfn.XLOOKUP(W100,マスタ!A:A,マスタ!H:H,0)*M100 -> 0 | AD100: =SUM(X100:AC100) -> 0
E101: サブバッチ作成 | I101: 〇 | K101: ー | L101: ー | M101: 1 | W101: 簡単 | X101: =_xlfn.XLOOKUP(W101,マスタ!A:A,マスタ!C:C,0)*M101 -> 0.99 | Y101: =IF(N101="",0,_xlfn.XLOOKUP(W101,マスタ!A:A,マスタ!D:D,0)*M101) -> 0 | Z101: =_xlfn.XLOOKUP(W101,マスタ!A:A,マスタ!E:E,0)*M101 -> 1.17 | AA101: =_xlfn.XLOOKUP(W101,マスタ!A:A,マスタ!F:F,0)*M101 -> 1.32 | AB101: =_xlfn.XLOOKUP(W101,マスタ!A:A,マスタ!G:G,0)*M101 -> 0.39 | AC101: =_xlfn.XLOOKUP(W101,マスタ!A:A,マスタ!H:H,0)*M101 -> 0.39 | AD101: =SUM(X101:AC101) -> 4.26
E102: データチェック機能 | I102: 〇 | K102: ー | L102: ー | M102: 1 | W102: 簡単 | X102: =_xlfn.XLOOKUP(W102,マスタ!A:A,マスタ!C:C,0)*M102 -> 0.99 | Y102: =IF(N102="",0,_xlfn.XLOOKUP(W102,マスタ!A:A,マスタ!D:D,0)*M102) -> 0 | Z102: =_xlfn.XLOOKUP(W102,マスタ!A:A,マスタ!E:E,0)*M102 -> 1.17 | AA102: =_xlfn.XLOOKUP(W102,マスタ!A:A,マスタ!F:F,0)*M102 -> 1.32 | AB102: =_xlfn.XLOOKUP(W102,マスタ!A:A,マスタ!G:G,0)*M102 -> 0.39 | AC102: =_xlfn.XLOOKUP(W102,マスタ!A:A,マスタ!H:H,0)*M102 -> 0.39 | AD102: =SUM(X102:AC102) -> 4.26
D103: 商品マスタ | I103: ー | K103: ー | L103: ー | M103: 0 | W103: 簡単 | X103: =_xlfn.XLOOKUP(W103,マスタ!A:A,マスタ!C:C,0)*M103 -> 0 | Y103: =IF(N103="",0,_xlfn.XLOOKUP(W103,マスタ!A:A,マスタ!D:D,0)*M103) -> 0 | Z103: =_xlfn.XLOOKUP(W103,マスタ!A:A,マスタ!E:E,0)*M103 -> 0 | AA103: =_xlfn.XLOOKUP(W103,マスタ!A:A,マスタ!F:F,0)*M103 -> 0 | AB103: =_xlfn.XLOOKUP(W103,マスタ!A:A,マスタ!G:G,0)*M103 -> 0 | AC103: =_xlfn.XLOOKUP(W103,マスタ!A:A,マスタ!H:H,0)*M103 -> 0 | AD103: =SUM(X103:AC103) -> 0
...

Sheet データ連携先
B2: ※カスミ | D2: ID | E2: PASS | G2: 転送手段 | H2: ディレクトリ | I2: ファイル名 | K2: タイミング | L2: ステータス
B3: 11 | C3: BIPROGY株式会社 | F3: INPUT | H3: /IN_BIPROGY/Master/GHPLUM/ | I3: ＰＬＵメンテ | J3: GHPLUM.CSV | K3: 日次マスタ：21時30分 | L3: 青柳さんにお願い
I4: 企画メンテ | J4: GHEVENTM.CSV | K4: 日次マスタ：21時30分
I5: 組合せメンテ | J5: GHBUNDLEM.CSV | K5: 日次マスタ：21時30分
I6: 特売メンテ | J6: GHDISCOUNTM.CSV | K6: 日次マスタ：21時30分
I7: 商品階層メンテデータ | J7: GMMDSEM.CSV | K7: 日次マスタ：21時30分
I8: 商品ポイント加算 | J8: GHPLUPOINT.CSV | K8: 日次マスタ：21時30分
I9: POPマスター(商品情報) | J9: P001 | K9: 日次マスタ：21時30分
I10: 棚番マスタ(P003)(出力もとはシャープどうする？) | J10: P003 | K10: 日次マスタ：22時
I11: 予算 | J11: plbc9176.s01 | K11: 月次マスタ（予算マスタ）：18時00分 月末日マイナス+5
F12: OUTPU | H12: /OUT_BIPROGY/Result/{店舗番号} | I12: 情報系時間帯実績 | J12: PLUFLASH_YYYYMMDD.CSV | K12: ・前日分：AM７時５分にGETする。※過去７日分まで取込可能
K13: ・毎時：９時～２４時に毎時５分にGETする。
H14: /OUT_BIPROGY/Result/ | I14: 単品別売上合計 | J14: GHPLUSUM.CSV | K14: 日次データは [テーブル名].CSVを作成する。2時00分迄 日次データは [テーブル名].CSVを作成する。2時15分 受信開始 レジ精算は、2時に間に合わなかった場合は7時に差分だけ送る。
I15: 単品別売上値引 | J15: GHPLUDISC.CSV
I16: 特売実施実績 | J16: KDISCRESULT.CSV
I17: 廃棄実施実績 | J17: KSCRAPSND.CSV
I18: レジ精算データ | J18: KSTORECLOSE.CSV
I19: 店内使用（経費） | J19: GHPLUTASTE.CSV
B20: 12 | C20: 株式会社アイネス | F20: INPUT | G20: ー | H20: ー | K20: ー
F21: OUTPU | G21: PUT | I21: スマートPOSクレジット対応_IFファイル (スーパーストリーム) | J21: 00100_店番前ゼロ4桁+00_YYYYMMDDHHMMSS.CSV | K21: 3時00分受信開始
H22: {アイネス様FTPサーバー}/posvinx | I22: POS分析：POSデータ(ｲｸﾞﾆｶﾏﾈｰ支払情報アリ）タイトル | J22: YYYYMMDD_店番前ゼロ6桁_ts.tar.gz | K22: 3時00分受信開始
I23: POS分析：POSデータ(ｲｸﾞﾆｶﾏﾈｰ支払情報ナシ）明細この中にWAONポイント
I24: POS分析：WAONポイントデータクレジット | J24: 圧縮
B25: 13 | C25: 株式会社ソフテック | F25: INPUT
F26: OUTPU
B27: 14 | C27: イオンフィナンシャルサービス株式会社 (GC企画) | F27: INPUT
F28: OUTPU | H28: 売上確定累積データ(IC対応) | I28: 売上確定累積データ(IC対応) | J28: Ruriic.dat
B29: 15 | C29: シャープマーケティングジャパン株式会社 | F29: INPUT | I29: 棚番マスタ(P003) | J29: P003 | K29: 日次マスタ：21時30分
F30: OUTPU | I30: 店舗マスタ | J30: RM_STRMyyyyMMddHHmmsssss.tsv | K30: マスター更新は、日中の差分更新、夜間のメンテナンス処理時の２通りあります。 AM 03:00 ～ 06:00 は メンテナンス時間帯となります。SHARPOPサーバーの再起動を行うため、差分更新用のファイルの配置をしないようにお願いいたします。
I31: 大分類(部門)マスタ | J31: RM_MGRMyyyyMMddHHmmsssss.tsv
I32: 中分類(品群)マスタ | J32: RM_MIDMyyyyMMddHHmmsssss.tsv
I33: 小分類(品種)マスタ | J33: RM_MNRMyyyyMMddHHmmsssss.tsv
I34: 分類マスタ | J34: RM_DIVMyyyyMMddHHmmsssss.tsv
I35: 消費税率マスタ | J35: RM_SZEIyyyyMMddHHmmsssss.txt
I36: 大分類別消費税率マスタ | J36: RM_DAIZyyyyMMddHHmmsssss.tsv
I37: 産地マスタ | J37: RM_SANMyyyyMMddHHmmsssss.tsv
B38: 16 | C38: 株式会社 イシダ | F38: INPUT | G38: ー | H38: ー
F39: OUTPU | G39: ？ | H39: /OUT_ISHIDA/{店舗番号} | I39: 商品マスタ送信 | J39: [店舗番号下3桁]＋[固定 "000"3桁]＋[年月日8桁]＋[時刻6桁]SHOHIN.TXT | K39: ■全件 新店時のみ ■差分 毎朝5:00頃
I40: 売価送信(一括) | J40: [店舗番号下3桁]＋[固定 "000"3桁]＋[年月日8桁]＋[時刻6桁]ESLDATA.TXT | K40: ■全件 毎朝5:30頃 ■差分 日中
I41: 売価送信(更新)
B42: 21 | C42: ダイソー連携 | F42: INPUT | G42: GET | I42: 商品マスタ(共通フォーマット) | J42: md_md_mst_sku_companynae_yyyymmddhhmmssmm.csv | K42: 日次：21時30分
F43: OUTPU | G43: PUT | I43: 標準売上サマリデータ | J43: 大創店舗コード(6桁)_YYYYMMDD_HHMMSS_SUMMARY.CSV | K43: 日次：０時
B44: 22 | C44: ウエルシア
B47: 31 | C47: POS→Scan&Go(カスミ) | F47: INPUT
F48: OUTPU
B49: 32 | C49: POS→Scan&Go(いなげや) | F49: INPUT
F50: OUTPU
B57: ※いなげや | D57: ID | E57: PASS | H57: ディレクトリ
B58: 81 | C58: Scan＆Go(富士通＆VTI) | F58: INPUT
F59: OUTPU

Sheet マスタ
A1: ー | C1: 設計 | D1: モック | E1: Code | F1: FT | G1: IT | H1: PT
A2: より簡単 | B2: Rất Dễ | C2: 0.5 | D2: 0.15 | E2: 0.58 | F2: 0.66 | G2: 0.19 | H2: 0.19
A3: 簡単 | B3: Dễ | C3: 0.99 | D3: 0.29 | E3: 1.17 | F3: 1.32 | G3: 0.39 | H3: 0.39
A4: 普通 | B4: Trung bình | C4: 1.98 | D4: 0.58 | E4: 2.33 | F4: 2.64 | G4: 0.77 | H4: 0.77
A5: 複雑 | B5: Khó | C5: 2.98 | D5: 0.88 | E5: 3.5 | F5: 3.96 | G5: 1.16 | H5: 1.16
A6: より複雑 | B6: Rất khó | C6: 5.95 | D6: 1.75 | E6: 7 | F6: 7.91 | G6: 2.31 | H6: 2.31
A8: 【重複】より簡単 | B8: Rất Dễ | C8: 0.5 | D8: 0.15 | E8: 0.58 | F8: 0.66 | G8: 0.19 | H8: 0.19
A9: 【重複】簡単 | B9: Dễ | C9: 0.99 | D9: 0.29 | E9: 1.17 | F9: 1.32 | G9: 0.39 | H9: 0.39
A10: 【重複】普通 | B10: Trung bình | C10: 1.98 | D10: 0.58 | E10: 2.33 | F10: 2.64 | G10: 0.77 | H10: 0.77
A11: 【重複】複雑 | B11: Khó | C11: 2.98 | D11: 0.88 | E11: 3.5 | F11: 3.96 | G11: 1.16 | H11: 1.16
A12: 【重複】より複雑 | B12: Rất khó | C12: 5.95 | D12: 1.75 | E12: 7 | F12: 7.91 | G12: 2.31 | H12: 2.31

Sheet 機能一覧（POSサーバー）
B1: 〇：対象 △：開発中 -：未着手 ×：想定外 | U1: 行高さ調整
B3: 機能概要 | E3: 残工数 （人月） | F3: POSサーバ | T3: 進捗
F4: 1.5 いなげや | M4: 2.0 カスミ・いなげや
F6: 設計 | H6: 製造 | I6: 試験 | J6: 修正・ 調整 | K6: 完了予定 | L6: 完了実績 | M6: 設計 | O6: 製造 | P6: 試験 | Q6: 修正・ 調整 | R6: 完了予定 | S6: 完了実績
F7: 基本 | G7: 詳細 | M7: 基本 | N7: 詳細
B8: インフラ | U8: =REPT("a"&CHAR(10)&"b",INT(LENB(SUBSTITUTE(T8,CHAR(10),""))/70))
C9: AWS構築 | D9: ステージング環境構築 | E9: 0 | F9: 〇 8/14 | H9: 〇 8/21 | I9: 〇 | J9: 〇 | K9: 2024年9月 | L9: 45566 | M9: 〇 8/14 | O9: 〇 8/21 | P9: 〇 | Q9: 〇 | R9: 2024年9月 | S9: 45566 | T9: 構築済み・9月第1週までに検証作業を完成させる 10月中からS＆Gのマスタと同じようデータベースの構成を見直し
D10: 本番環境構築 | F10: - | H10: - | I10: - | J10: - | K10: - | L10: - | M10: - | O10: - | P10: - | Q10: - | R10: - | S10: - | T10: 構築作業未着手 | U10: =REPT("a"&CHAR(10)&"b",INT(LENB(SUBSTITUTE(T10,CHAR(10),""))/70))
B11: ログイン・ログアウト | U11: =REPT("a"&CHAR(10)&"b",INT(LENB(SUBSTITUTE(T11,CHAR(10),""))/70))
B12: X0 | C12: ログイン機能 | D12: アカウントID、パスワードでシステムにログインを行う。 | E12: 0 | F12: 〇 6/11 | G12: △ 12月 | H12: 〇 8/16 | I12: 〇 | J12: △ | K12: 2024年9月 | L12: 2024年9月 | M12: 〇 6/11 | N12: △ 12月 | O12: 〇 8/16 | P12: 〇 | Q12: △ | R12: 2024年9月 | S12: 45536 | T12: 詳細設計指摘対応中 | U12: =REPT("a"&CHAR(10)&"b",INT(LENB(SUBSTITUTE(T12,CHAR(10),""))/70))
B13: メニュー | U13: =REPT("a"&CHAR(10)&"b",INT(LENB(SUBSTITUTE(T13,CHAR(10),""))/70))
B14: X1 | C14: メニュー機能 | D14: 機能一覧を表示する。 | E14: 0 | F14: 〇 7/26 | G14: △ 11/14 | H14: 〇 8/16 | I14: 〇 ９/13 | J14: △ | K14: 2024年9月 | L14: 45566 | M14: 〇 7/26 | N14: △ 11/14 | O14: 〇 8/16 | P14: 〇 ９/13 | Q14: △ | R14: 2024年9月 | S14: 45566 | T14: 自社での詳細設計が完了。カスミ様確認待ち | U14: =REPT("a"&CHAR(10)&"b",INT(LENB(SUBSTITUTE(T14,CHAR(10),""))/70))
B15: プリセット系 | U15: =REPT("a"&CHAR(10)&"b",INT(LENB(SUBSTITUTE(T15,CHAR(10),""))/70))
B16: 15 | C16: タッチメニュー設定 | D16: タッチメニュー設定機能により、次のことが可能になる。 ・店舗のレイアウトプリセットを管理する。 ‣ビジネスレイアウト一覧を見る。 ‣1種類のビジネスレイアウトの詳細を見る。 ‣ビジネスレイアウトを検索する。 ・店舗のビジネスレイアウトを設定する。 ‣新規作成 ‣編集 ‣削除 ‣コピー ・1種類のビジネスレイアウトの詳細を設定する。 ‣ ビジネスレイアウトのレイアウトプリセットの変更：名称、色など ‣ボタンレイアウトプリセットを変更する。 ●色、イメージ、名称、サイズ、有効・無効など ●ボタンレイアウトプリセットの機能：商品、クーポン、割引など | E16: 0 | F16: △ 7/19 | G16: △ 11/9 | H16: 〇 ９/13 | I16: 〇 | J16: 〇 | K16: 2024年9月 | L16: 45597 | M16: △ 7/19 | N16: △ 11/19 | O16: 〇 ９/13 | P16: 〇 | Q16: 〇 | R16: 2024年9月 | S16: 45597 | T16: 自社での詳細設計が完了。カスミ様確認待ち | U16: =REPT("a"&CHAR(10)&"b",INT(LENB(SUBSTITUTE(T16,CHAR(10),""))/70))
B17: 62 | C17: 画像アップロード | D17: 画像アップロード機能では次のことが可能になる。 店舗のプリセット画像、レシートロゴを説明する画像を管理する。 ・現存説明画像の一覧を閲覧する。 ・説明画像を追加する。 ・現存説明画像を削除する。 | E17: 0 | F17: △ | G17: △ | H17: × | I17: × | J17: × | K17: × | L17: × | M17: △ | N17: △ | O17: - | P17: - | Q17: - | R17: 45689 | S17: - | T17: 基本設計指摘対応中 | U17: =REPT("a"&CHAR(10)&"b",INT(LENB(SUBSTITUTE(T17,CHAR(10),""))/70))
B18: ジャーナル系 | U18: =REPT("a"&CHAR(10)&"b",INT(LENB(SUBSTITUTE(T18,CHAR(10),""))/70))
B19: 21 | C19: ジャーナル検索 | D19: 開始・終了日、開始・終了時刻の時間帯、最大検索件数によりジャーナル一覧を検索する。 また、レシートNo.、担当者、任意文字列（キーワード）からも検索できる。 検索結果取得後、選択されたレシートのイメージ一覧を表示でき、印刷できる。 | E19: 2.5 | F19: 〇 10/01 | G19: 〇 11/15 | H19: 〇 | I19: 〇 | J19: △ | K19: 2024年9月 | L19: 45597 | M19: △ 8/23 | N19: 〇 11/15 | O19: 〇 | P19: 〇 | Q19: △ | R19: 2024年9月 | S19: 45597 | T19: 自社での詳細設計が完了。カスミ様確認待ち | U19: =REPT("a"&CHAR(10)&"b",INT(LENB(SUBSTITUTE(T19,CHAR(10),""))/70))
B20: レジ系・釣銭機関連 | U20: =REPT("a"&CHAR(10)&"b",INT(LENB(SUBSTITUTE(T20,CHAR(10),""))/70))
B21: 33 | C21: 釣銭機状況照会 | D21: 釣銭機状況照会機能では次のことが可能になる。 ・¥1, ¥5, ¥10, ¥50, ¥100, ¥500, ¥1000, ¥2000, ¥5000, ¥10000の金種の保留枚数に応じて各レジの残額と補充額を閲覧する ・各レジの補充金額情報をpdfファイルで出力する。 | E21: 0.68 | F21: △ 8/19 | G21: △ 8/19 | H21: 〇 | I21: 〇 | J21: △ | K21: 45597 | L21: 45597 | M21: △ 8/19 | N21: △ 8/19 | O21: 〇 | P21: 〇 | Q21: △ | R21: 45597 | S21: 45597 | T21: ` | U21: =REPT("a"&CHAR(10)&"b",INT(LENB(SUBSTITUTE(T21,CHAR(10),""))/70))
B22: 71 | C22: レジマスタ設定 | D22: レジマスタ設定機能では次のことが可能になる。 レジのマスタ情報を表示する。 レジのマスタ情報を追加・編集・削除する。 レジのマスタ情報をCSVファイルで取込・出力。 | E22: 0 | F22: △ 8/23 | G22: △ 11/6 | H22: 〇 | I22: △ | J22: △ | K22: 45536 | L22: 45597 | M22: △ 8/23 | N22: △ | O22: 〇 | P22: △ | Q22: △ | R22: 45536 | S22: 45597 | T22: 仕様変更により基本設計・詳細設計更新中 | U22: =REPT("a"&CHAR(10)&"b",INT(LENB(SUBSTITUTE(T22,CHAR(10),""))/70))
B23: 取引系 | U23: =REPT("a"&CHAR(10)&"b",INT(LENB(SUBSTITUTE(T23,CHAR(10),""))/70))
B24: 16 | C24: 保留_保留解除 | D24: レジ操作で、保留_保留解除作業を行う。 | E24: 0 | F24: △ | G24: - | H24: - | I24: - | J24: - | K24: × | L24: × | M24: △ | N24: - | O24: - | P24: - | Q24: - | R24: 未定 | S24: - | U24: =REPT("a"&CHAR(10)&"b",INT(LENB(SUBSTITUTE(T24,CHAR(10),""))/70))
B25: 商品系 | T25: 商品マスタの登録内容が不明 | U25: =REPT("a"&CHAR(10)&"b",INT(LENB(SUBSTITUTE(T25,CHAR(10),""))/70))
B26: 01 | C26: 商品管理 | D26: 商品管理機能は、 ・商品情報詳細をビューする。 ・1, 7, 8 定番売価変更が可能 ・当日の緊急売価を変更する。 ・特売売価設定を新規作成・編集する ・ミックスマッチ新規・編集機能 | E26: 5.52 | F26: △ 09/25 | G26: △ 12月 | H26: - | I26: - | J26: - | K26: × | L26: × | M26: 〇 7/24 | N26: 12月 | O26: - | P26: - | Q26: - | R26: 45627 | S26: - | T26: 削除機能についてカスミ様は検討中 | U26: =REPT("a"&CHAR(10)&"b",INT(LENB(SUBSTITUTE(T26,CHAR(10),""))/70))
B27: 02 | C27: 緊急売価変更 | D27: 緊急売価変更機能により、次のことが可能になる。 ・複数商品の緊急売価を同時に変更する。（変更日のみ店舗適用） ・変更日が過ぎると、緊急売価が無効になり、クリアする必要がある。 | E27: 0.41 | F27: 〇 7/29 | G27: △ 12月 | H27: - | I27: - | J27: - | K27: × | L27: × | M27: 〇 7/29 | N27: 12月 | O27: △ | P27: - | Q27: - | R27: 45627 | S27: - | U27: =REPT("a"&CHAR(10)&"b",INT(LENB(SUBSTITUTE(T27,CHAR(10),""))/70))
B28: 03 | C28: 店舗特売入力 | D28: 特売マスタ売価設定機能 ・商品コード、PLU入力を行い、登録情報の閲覧や、特売売価の変更を行う。 ・商品の特売売価設定または割引設定を行う。 ・夜間バッチを使用して特売売価を削除し、過去の特売割引を行う。 ・終了日が7日以前の特売情報を削除する。 ・当日の商品情報がない特売マスタを削除する。 ・当日の商品情報がないプロモーション情報を削除する。 | E28: 0 | F28: 〇 10/6 | G28: △ 12月 | H28: - | I28: - | J28: - | K28: × | L28: × | M28: 〇 | N28: △ 12月 | O28: 〇 | P28: 〇 | Q28: △ | R28: 45597 | S28: - | U28: =REPT("a"&CHAR(10)&"b",INT(LENB(SUBSTITUTE(T28,CHAR(10),""))/70))
B29: 04 | C29: 商品採用店舗確認 | D29: 商品採用店舗確認機能では次のことが可能になる。 ・PLUコード*を入力して、どのスーパーに商品があるか確認する。 ・「カスミ」又は「ウエルシア」の売上計算が必要な情報は編集可能。 | E29: 1.1 | F29: 〇 5/30 | G29: △ | H29: - | I29: - | J29: - | K29: × | L29: × | M29: 〇 5/30 | N29: △ | O29: - | P29: - | Q29: - | R29: 45717 | S29: - | U29: =REPT("a"&CHAR(10)&"b",INT(LENB(SUBSTITUTE(T29,CHAR(10),""))/70))
B30: 05 | C30: ミックスマッチ設定 | D30: ミックスマッチ設定機能 ・ミックスマッチ情報を設定する。 ‣新規作成 ‣修正 ‣削除：夜間バッチを使用して過去のミックスマッチ情報を削除する。 ●終了日が7日前のミックスマッチ情報を削除する。 ●現時点での商品情報がないミックスマッチ情報を削除する。 ●現時点でのプロモーション情報がないミックスマッチ情報を削除する。 ・商品コード、PLU入力を行い、登録情報の閲覧や、売価の変更を行う。 ・プロモーションコードに紐づけられたミックスマッチコードに従って商品を設定する。1 つのミックスマッチコードで複数の商品設定が可能 ・ミックスマッチの有効期間はプロモーション期間内のみ設定可能 ・ミックスマッチ設定を行う場合、商品の数量と売価を入力する必要がある。10つのミックスマッチオプション設定可能 ・売価、割引、値引によるミックスマッチ設定可能 | E30: 0.85 | F30: △ 8/2 | G30: △ 12月 | H30: - | I30: - | J30: - | K30: × | L30: × | M30: △ 8/2 | N30: 12月 | O30: 〇 | P30: - | Q30: - | R30: 45627 | S30: - | U30: =REPT("a"&CHAR(10)&"b",INT(LENB(SUBSTITUTE(T30,CHAR(10),""))/70))
B31: 06 | C31: 1, 7, 8 定番売価変更 | D31: 1, 7, 8 定番変更機能により次のことが可能になる。 ・1、7、8部門の各商品の定番売価を毎日変更する。売価は当日以降のみ変更可能。 ・定番売価変更履歴を日付・部門別に検索する。 ・ 売価変更金額は当日のみ有効、売価変更が最優先になる。 ・毎日バッチを実行して定番売価を更新する。 | E31: 0.31 | F31: 〇 10/14 | G31: △ 12月 | H31: - | I31: - | J31: - | K31: × | L31: × | M31: △ 8/2 | N31: 12月 | O31: - | P31: - | Q31: - | R31: 45627 | S31: - | T31: 詳細設計指摘あり | U31: =REPT("a"&CHAR(10)&"b",INT(LENB(SUBSTITUTE(T31,CHAR(10),""))/70))
B32: 07 | C32: セットマッチ設定 | D32: セットマッチ設定機能 ・セットマッチ情報を設定する。 ‣新規作成 ‣修正 ・削除：夜間実行セットマッチを削除するバッチ、または画面上で削除するバッチがある。 ・プロモーションコードに紐づけられたセットマッチコードに従って商品を設定する。1つのセットマッチコードで複数の設定が可能。 ・セットマッチの有効期間はプロモーション期間内のみ設定可能。 ・セットマッチ設定時にセットマッチの1つ製品グループの購入対象商品数を入力する必要がある。 ・売価、割引、値引によるセットマッチ設定可能。 | E32: 1.47 | F32: 〇 8/8 | G32: - | H32: - | I32: - | J32: - | K32: × | L32: × | M32: △ | N32: 6月 | O32: - | P32: - | Q32: - | R32: 45809 | S32: - | U32: =REPT("a"&CHAR(10)&"b",INT(LENB(SUBSTITUTE(T32,CHAR(10),""))/70))
B33: プリセット系 | U33: =REPT("a"&CHAR(10)&"b",INT(LENB(SUBSTITUTE(T33,CHAR(10),""))/70))
B34: 18 | C34: 小計タッチメニュー設定 | E34: 1.47 | F34: △ | G34: - | H34: - | I34: - | J34: - | K34: × | L34: × | M34: △ | N34: 2月 | O34: - | P34: - | Q34: - | R34: 45717 | S34: - | T34: 自社での基本設計が完了。カスミ様確認待ち | U34: =REPT("a"&CHAR(10)&"b",INT(LENB(SUBSTITUTE(T34,CHAR(10),""))/70))
B35: レジ系・釣銭機関連 | U35: =REPT("a"&CHAR(10)&"b",INT(LENB(SUBSTITUTE(T35,CHAR(10),""))/70))
B36: 20 | C36: レジ精算入力 | D36: レジ精算入力機能では次のことが可能になる。 ・店舗のレジの状態を表示する。 ・選択した日付ごとにより店舗全体の売上が出力可能 ‣ログインユーザーが管理者ユーザーの場合、62日以内選択可能 ‣ログインユーザーが管理者ユーザーではない場合、当日から直近3日選択可能 ・レジごとの詳細売上を表示して実際で金額が編集可能 ・レジが精算を忘れた場合、POSサーバーがバッチを使用して自動的に精算する。 | E36: 2.04 | F36: 〇 11/28 | G36: - | H36: - | I36: - | J36: - | K36: × | L36: × | M36: 〇 11/28 | N36: 4月 | O36: - | P36: - | Q36: - | R36: 45778 | S36: - | T36: 自社での基本設計が完了。カスミ様確認待ち | U36: =REPT("a"&CHAR(10)&"b",INT(LENB(SUBSTITUTE(T36,CHAR(10),""))/70))
B37: 81 | C37: 釣銭機警告設定 | D37: 釣銭機警告設定機能では次のことが可能になる。 ・釣銭機の補充警告を設定する。 ・釣銭機の回収警告を設定する。 | E37: 0.8 | F37: 〇 7/23 | G37: - | H37: - | I37: - | J37: - | K37: × | L37: × | M37: 〇 7/23 | N37: 1月 | O37: - | P37: - | Q37: - | R37: 2025年2月 | S37: -
B38: 73 | C38: レジ状況照会 | D38: レジ状況照会機能では次のことが可能になる。 ・日別（過去・未来の日も選択可能）に1つ又は複数の店舗のレジ状況照会一覧 とステータス(全通常と全異常）を検索して表示する。 ・各レジの状況詳細を以下のように閲覧する。状態, 営業日、営業回数、開設回数、担当者、ダウンロードマスターバージョン、反映済マスターパージョンなど | E38: 2.04 | F38: △ | G38: - | H38: - | I38: - | J38: - | K38: × | L38: × | M38: △ | N38: 2月 | O38: - | P38: - | Q38: - | R38: 2025年2月 | S38: - | T38: 基本設計指摘あり | U38: =REPT("a"&CHAR(10)&"b",INT(LENB(SUBSTITUTE(T38,CHAR(10),""))/70))
T39: 商品マスタの登録内容が不明 | U39: =REPT("a"&CHAR(10)&"b",INT(LENB(SUBSTITUTE(T39,CHAR(10),""))/70))
B40: 08 | C40: カテゴリ値引・割引設定 | D40: カテゴリ値引/割引設定機能によりカテゴリ値引・割引の新規作成・更新・削除が可能 カテゴリ階層は次の通りである。 01:部門 02.品群 03.品種 04.分類 | E40: 2.04 | F40: 〇 10/22 | G40: - | H40: - | I40: - | J40: - | K40: × | L40: × | M40: △ | N40: 12月 | O40: - | P40: - | Q40: - | R40: 45627 | S40: - | U40: =REPT("a"&CHAR(10)&"b",INT(LENB(SUBSTITUTE(T40,CHAR(10),""))/70))
B41: 10 | C41: プロモーションメンテ | D41: プロモーションメンテには次のことが可能になる。 ・プロモーション検索 ・プロモーション情報表示 ・プロモーション設定編集 ・プロモーション新規作成 ・プロモーション削除 ・毎晩バッチ処理により、終了日が現在日より7日以上前のプロモーションコードを削除する。 | E41: 0 | F41: 〇 7/31 | G41: △ 12月 | H41: - | I41: - | J41: - | K41: × | L41: × | M41: 〇 7/31 | N41: 12月 | O41: - | P41: - | Q41: - | R41: 45627 | S41: - | U41: =REPT("a"&CHAR(10)&"b",INT(LENB(SUBSTITUTE(T41,CHAR(10),""))/70))
B42: 22 | C42: クレジット小計割引設定 | D42: クレジット小計割引設定機能では次のことが可能になる。 ・クレジットカードで支払う時の毎週又は毎月の割引を閲覧、設定する。 ・その後の全ての月に適用される。 ・バッチを実行してクレジット小計割引日を設定する。 ・会社のクレジットカードを使用してその会社の店舗で購入した顧客に直接割引を適用する。 | E42: 0.8 | F42: 〇 6/13 | G42: - | H42: - | I42: - | J42: - | K42: × | L42: × | M42: 〇 6/13 | N42: 2月 | O42: - | P42: - | Q42: - | R42: 45689 | S42: - | U42: =REPT("a"&CHAR(10)&"b",INT(LENB(SUBSTITUTE(T42,CHAR(10),""))/70))
B43: 28 | C43: レシートクーポン設定 | D43: レシートクーポン設定機能は次のことが可能になる。 ・1つ以上の店舗のレシートクーポンの閲覧、追加、編集、削除 ・レシートクーポンは、ユーザーが発券期間内にお買い物をした場合にお買い上げレシートの後に印刷されるクーポン券である。 ・また、クーポン券に印字されている期間内でのお買い物時に使用できるものとなる。 | E43: 1.47 | F43: △ 11/19 | G43: - | H43: - | I43: - | J43: - | K43: × | L43: × | M43: △ 11/19 | N43: 2月 | O43: - | P43: - | Q43: - | R43: 45717 | S43: - | T43: コピー機能追加 | U43: =REPT("a"&CHAR(10)&"b",INT(LENB(SUBSTITUTE(T43,CHAR(10),""))/70))
B44: 37 | C44: メガ割設定 | D44: メガ割設定機能では次のことが可能になる。 ・曜日、日で商品部門の割引率を閲覧、設定する。 ・割引は終日適用され、毎週及び毎月繰り返される。 ・フローには編集モードのみがある。 | E44: 1.47 | F44: 〇 8/13 | G44: - | H44: - | I44: - | J44: - | K44: × | L44: × | M44: 〇 8/13 | N44: 1月 | O44: - | P44: - | Q44: - | R44: 45658 | S44: - | U44: =REPT("a"&CHAR(10)&"b",INT(LENB(SUBSTITUTE(T44,CHAR(10),""))/70))
B45: 38 | C45: 朝割設定 | D45: 朝割設定機能では次のことが可能になる。 ・部門の曜日別の朝割の時間帯、割引率を閲覧、設定する。 ・適用が毎週及び毎月繰り返される。 ・朝割プログラムを解除する。 | E45: 1.47 | F45: 〇 8/13 | G45: - | H45: - | I45: - | J45: - | K45: × | L45: × | M45: 〇 8/13 | N45: 1月 | O45: - | P45: - | Q45: - | R45: 45689 | S45: - | U45: =REPT("a"&CHAR(10)&"b",INT(LENB(SUBSTITUTE(T45,CHAR(10),""))/70))
B46: 96 | C46: カテゴリ割引レシートクーポン設定 | D46: カテゴリ割引レシートクーポン設定機能では次のことが可能になる。 ・1つ又は複数の店舗のカテゴリのレシートクーポンを閲覧、追加、編集、削除する。 ・カテゴリ割引レシートクーポンは、ユーザーが発券期間内にお買い物をした場合にお買い上げレシートの後に印刷されるカテゴリのクーポン券である。 ・また、クーポン券に印字されている期間内でのお買い物時に使用できるものとなる。 | E46: 1.47 | F46: △ 10/29 | G46: - | H46: - | I46: - | J46: - | K46: × | L46: × | M46: △ 10/29 | N46: 2月 | O46: - | P46: - | Q46: - | R46: 45717 | S46: - | T46: 自社での基本設計が完了。カスミ様確認待ち | U46: =REPT("a"&CHAR(10)&"b",INT(LENB(SUBSTITUTE(T46,CHAR(10),""))/70))
B47: ポイント系 | T47: 商品マスタの登録内容が不明 | U47: =REPT("a"&CHAR(10)&"b",INT(LENB(SUBSTITUTE(T47,CHAR(10),""))/70))
B48: 23 | C48: ポイント単位使用設定 | D48: ポイント単位使用設定機能では次のことが可能になる。 店舗ID別、利用期限別のポイント単位一覧を表示する。 店舗別、適用期間別のポイント単位を追加・編集・削除する。 | E48: 1.47 | F48: △ | G48: - | H48: - | I48: - | J48: - | K48: × | L48: × | M48: △ | N48: 6月 | O48: - | P48: - | Q48: - | R48: 45809 | S48: - | T48: 指摘により基本設計更新中 | U48: =REPT("a"&CHAR(10)&"b",INT(LENB(SUBSTITUTE(T48,CHAR(10),""))/70))
B49: 39 | C49: WAONポイントN倍設定 | D49: システム権限を持つアカウントのみがこの機能を使用する権利を持っている。 WAONカード利用200円(税込)ごとにWAONポイントN倍設定 | E49: 0.8 | F49: 〇 11/03 | G49: - | H49: - | I49: - | J49: - | K49: × | L49: × | M49: 〇 11/03 | N49: 6月 | O49: - | P49: - | Q49: - | R49: 45839 | S49: - | U49: =REPT("a"&CHAR(10)&"b",INT(LENB(SUBSTITUTE(T49,CHAR(10),""))/70))
B50: レポート | T50: 商品マスタの登録内容が不明 | U50: =REPT("a"&CHAR(10)&"b",INT(LENB(SUBSTITUTE(T50,CHAR(10),""))/70))
B51: 11 | C51: 部門別売上速報・日報 | D51: 本機能では次のことが可能になる。 ・部門別売上速報を作成する。 ‣売上速報を印刷する。 ‣商品部門レベルの拡大と絞り込みを行う。 ・商品部門と日報のオプションにより売上日報を作成する。 ‣売上日報を印刷する。 ‣商品部門レベルの拡大と絞り込みを行う。 ・時間帯と日報のオプションにより売上レポートを作成する。 ‣売上レポートを印刷する。 | E51: 2.04 | F51: 〇 10/1 | G51: - | H51: - | I51: - | J51: - | K51: × | L51: × | M51: 〇 10/1 | N51: 3月 | O51: - | P51: - | Q51: - | R51: 45717 | S51: - | U51: =REPT("a"&CHAR(10)&"b",INT(LENB(SUBSTITUTE(T51,CHAR(10),""))/70))
B52: 12 | C52: 単品速報・日報 | D52: 単品速報/日報 ・商品又は部門～分類を指定して売上等を単品別と時間帯別に表示する。 ・速報又は日報別売上情報を選択して表示可能 ・商品又はカテゴリ指定単品速報/日報をPDFで出力可能。 | E52: 2.04 | F52: 〇 10/1 | G52: - | H52: - | I52: - | J52: - | K52: × | L52: × | M52: 〇 10/1 | N52: 3月 | O52: - | P52: - | Q52: - | R52: 45748 | S52: - | U52: =REPT("a"&CHAR(10)&"b",INT(LENB(SUBSTITUTE(T52,CHAR(10),""))/70))
B53: 14 | C53: テナント売上速報・日報 | D53: テナント売上速報/日報では次のことが可能になる。 ・店舗内のテナントの売上速報（現在日）を作成する。アクションを追加で実行できる。 ‣売上速報を印刷する。 ・店舗内のテナントの売上日報を作成する。アクションを追加で実行できる。 ‣レポートの出力日を選択する。 ‣売上日報を印刷する。 | E53: 1.47 | F53: 〇 9/1 | G53: - | H53: - | I53: - | J53: - | K53: × | L53: × | M53: 〇 9/1 | N53: 3月 | O53: - | P53: - | Q53: - | R53: 45748 | S53: - | U53: =REPT("a"&CHAR(10)&"b",INT(LENB(SUBSTITUTE(T53,CHAR(10),""))/70))
B54: 19 | C54: 売価変更勧告リスト | D54: 19_売価変更勧告リスト機能では以下の検索条件で変更売価リストが印刷可能になる。 ・対象日 ・変更区分 (以下の区分から1つの区分を選択する。）全部、緊急売価戻、特売開始、特売開始T、 区分変更、特売終了、売価変更、緊急売価 ・同一売価（出力しない・出力する） ・NON-PLUコード（出力しない・出力する） 変更売価リストはユーザーが選択した順序で表示される。 ・分類構成順 ・変更区分順 | E54: 0.8 | F54: 〇 11/18 | G54: - | H54: - | I54: - | J54: - | K54: × | L54: × | M54: 〇 11/18 | N54: 2月 | O54: - | P54: - | Q54: - | R54: 45717 | S54: - | U54: =REPT("a"&CHAR(10)&"b",INT(LENB(SUBSTITUTE(T54,CHAR(10),""))/70))
B55: 29 | C55: レジ別時間帯別点検 | D55: レジ別時間帯別点検機能では次のことが可能になる。 ・各時間帯に従って店舗の各レジの日報を印刷する。レポート情報には以下が含まれている。 ‣営業日の各時間帯に従う各レジの客数、点数、金額 ‣各レジの1営業日の総客数、総点数、総金額 | E55: 1.47 | F55: 〇 10/22 | G55: - | H55: - | I55: - | J55: - | K55: × | L55: × | M55: 〇 10/22 | N55: 3月 | O55: - | P55: - | Q55: - | R55: 45748 | S55: - | U55: =REPT("a"&CHAR(10)&"b",INT(LENB(SUBSTITUTE(T55,CHAR(10),""))/70))
B56: 31 | C56: レジ別速報・日報 | D56: レジ別速報/日報機能では次のことが可能になる。 ・現在日の速報と日報により各レジのレポート一覧を検索する。 ・全てレジの合計レポートを統計する。 ・各レジのレポート詳細を速報、日報、月報の形式で閲覧する。 ・レポート詳細情報：売上部門、税・決済、入金・出、在高・値引、操作 ・レジのレポートを印刷する。 | E56: 2.04 | F56: 〇 10/29 | G56: - | H56: - | I56: - | J56: - | K56: × | L56: × | M56: 〇 10/29 | N56: 4月 | O56: - | P56: - | Q56: - | R56: 45748 | S56: - | U56: =REPT("a"&CHAR(10)&"b",INT(LENB(SUBSTITUTE(T56,CHAR(10),""))/70))
B57: 32 | C57: レジ別単品別売上点検 | D57: レジ別単品別売上点検機能では次のことが可能になる。 ・レジ別商品売上を検索する。 ・レジ別時間帯別売上を表示する。 | E57: 1.47 | F57: 〇 9/11 | G57: - | H57: - | I57: - | J57: - | K57: × | L57: × | M57: 〇 9/11 | N57: 4月 | O57: - | P57: - | Q57: - | R57: 45778 | S57: - | U57: =REPT("a"&CHAR(10)&"b",INT(LENB(SUBSTITUTE(T57,CHAR(10),""))/70))
B58: マスタ設定 | U58: =REPT("a"&CHAR(10)&"b",INT(LENB(SUBSTITUTE(T58,CHAR(10),""))/70))
B59: 25 | C59: 取扱設定マスタ設定(KSM) | D59: 取扱設定マスタ設定(KSM)では次のことが可能になる。 ・各レベルに分類された商品部門を閲覧する。 ・商品部門の取扱有無を設定: 有、無 ・部門の一括取扱有無を設定する。 ・この設定は商品部門に関連する画面、機能に適用される。 ・カスミ様の店舗のみ適用 | E59: 2.04 | F59: 〇 10/08 | G59: - | H59: - | I59: - | J59: - | K59: × | L59: × | M59: 〇 10/08 | N59: 7月 | O59: - | P59: - | Q59: - | R59: 45839 | S59: - | U59: =REPT("a"&CHAR(10)&"b",INT(LENB(SUBSTITUTE(T59,CHAR(10),""))/70))
B60: 26 | C60: 取扱設定マスタ設定(Welcia) | D60: 取扱設定マスタ設定(Welcia)では次のことが可能になる。 ・各レベルに分類された分類一覧を閲覧する。 ・以下のように分類の取扱有無を設定する。 有、無 ・以下のように分類の医薬品有無を設定する。 有、無 ・この設定は分類に関連する画面、機能に適用される。 ・Welcia連携店舗のみが対象となる。 | E60: 1.73 | F60: 〇 10/08 | G60: - | H60: - | I60: - | J60: - | K60: × | L60: × | M60: 〇 10/08 | N60: 7月 | O60: - | P60: - | Q60: - | R60: 45870 | S60: - | U60: =REPT("a"&CHAR(10)&"b",INT(LENB(SUBSTITUTE(T60,CHAR(10),""))/70))
B61: 66 | C61: 券マスタ設定 | D61: 券マスタ設定機能では次のことが可能になる。 ・フローはシステム権限を持つアカウントのみが使用可能 ・支払券、値引券の一覧を表示する。 ・支払券、値引券を券名称で検索する。 ・支払券又は値引券を新規追加・編集・削除する。 ・作成した値引券が28_レシートクーポン設定のフローで使用される。 ・支払券が15_タッチメニュー設定のフローで使用される。 | E61: 1.47 | F61: △ | G61: - | H61: - | I61: - | J61: - | K61: × | L61: × | M61: △ | N61: 1月 | O61: - | P61: - | Q61: - | R61: 2025年2月 | S61: - | T61: Q＆Aにより基本設計更新中 | U61: =REPT("a"&CHAR(10)&"b",INT(LENB(SUBSTITUTE(T61,CHAR(10),""))/70))
B62: 店舗系 | U62: =REPT("a"&CHAR(10)&"b",INT(LENB(SUBSTITUTE(T62,CHAR(10),""))/70))
B63: 40 | C63: 従業員設定 | D63: この機能は、 ・従業員一覧の検索・表示を行う。 ・従業員情報の追加・編集・削除などを行う。 | E63: 0 | F63: 〇 10/21 | G63: - | H63: - | I63: - | J63: - | K63: × | L63: × | M63: 〇 10/21 | N63: 12月 | O63: - | P63: - | Q63: - | R63: 45658 | S63: - | U63: =REPT("a"&CHAR(10)&"b",INT(LENB(SUBSTITUTE(T63,CHAR(10),""))/70))
B64: 74 | C64: 予算登録 | D64: 予算登録機能では次のことが可能になる。 当月と来月の部門ごとの予算額を登録・編集する。 月別または部門別の合計予算を日付ごとに表示する。 | E64: 1.47 | F64: △ | G64: - | H64: - | I64: - | J64: - | K64: × | L64: × | M64: △ | N64: 5月 | O64: - | P64: - | Q64: - | R64: 45809 | S64: - | T64: 基本設計指摘あり | U64: =REPT("a"&CHAR(10)&"b",INT(LENB(SUBSTITUTE(T64,CHAR(10),""))/70))
B65: 82 | C65: 店舗マスタ設定 | D65: 店舗マスタ設定機能では次のことが可能になる。 ・店舗マスタを新規作成する。 ・店舗マスタ情報を更新する。 ・店舗マスタを削除する。 ・既存の店舗から店舗の新規作成をコピーする。 | E65: 0 | F65: 〇 | G65: 12月 | H65: - | I65: - | J65: - | K65: × | L65: × | M65: 〇 | N65: 12月 | O65: - | P65: - | Q65: - | R65: 45597 | S65: - | U65: =REPT("a"&CHAR(10)&"b",INT(LENB(SUBSTITUTE(T65,CHAR(10),""))/70))
B66: その他 | U66: =REPT("a"&CHAR(10)&"b",INT(LENB(SUBSTITUTE(T66,CHAR(10),""))/70))
B67: 68 | C67: サイトログインユーザマスタ設定 | D67: サイトログインユーザマスタ設定機能では次のことが可能になる。 ログインユーザのマスタ情報を表示する。 以下を含むログインユーザーのマスタ情報を追加・編集・削除する。 ・ユーザーの基本情報 ・ユーザー権限 ・連携店舗 | E67: 2.04 | F67: 〇 7/23 | G67: - | H67: - | I67: - | J67: - | K67: × | L67: × | M67: 〇 7/23 | N67: 1月 | O67: - | P67: - | Q67: - | R67: 45658 | S67: - | U67: =REPT("a"&CHAR(10)&"b",INT(LENB(SUBSTITUTE(T67,CHAR(10),""))/70))
B68: 72 | C68: パスワード変更 | D68: パスワード変更機能では次のことが可能になる。 ・ログインしているユーザーのパスワード情報を変更する。 | E68: 1.47 | F68: 〇 6/11 | G68: - | H68: - | I68: - | J68: - | K68: × | L68: × | M68: 〇 6/11 | N68: 12月 | O68: - | P68: - | Q68: - | R68: 45658 | S68: - | U68: =REPT("a"&CHAR(10)&"b",INT(LENB(SUBSTITUTE(T68,CHAR(10),""))/70))
B69: 80 | C69: Scan&Go商品マスタ再配信 | D69: Scan&Go商品マスタ再配信機能では次のことが可能になる。 システム権限を持つアカウントのみがこの機能を使用できる。 ・各商品の売価をScan&Goサーバーに再配信してScan&Goに提供する。 ・それぞれのScan&Go店舗に適用する。 ・バッチを実行して売価をScan&Goサーバーに配信する。 | E69: 0.41 | F69: 〇 8/15 | G69: - | H69: - | I69: - | J69: - | K69: × | L69: × | M69: 〇 8/15 | N69: 2月 | O69: - | P69: - | Q69: - | R69: 45717 | S69: - | U69: =REPT("a"&CHAR(10)&"b",INT(LENB(SUBSTITUTE(T69,CHAR(10),""))/70))
C70: メッセージマスタ設定 | D70: メッセージマスタ設定機能では次のことが可能になる。 ・種類、メッセージコード、メッセージ種別、メッセージに従って1つ又は複数の店舗のメッセージマスタリストを検索して表示する。 ・1つ又は複数の店舗のメッセージマスタを設定する。 ‣新規作成 ‣編集 ‣削除 ‣コピー ・種類をレシート、ラインディスプレイとしてメッセージマスタを新規作成する。 ・28_レシートクーポン設定のフローでレシートが使用される。 ・ラインディスプレイはどの機能で使用されますが、分かりませんのでご教示お願い致します。 | E70: 1.47 | F70: △ | G70: - | H70: - | I70: - | J70: - | K70: × | L70: × | M70: △ | N70: - | O70: - | P70: - | Q70: - | R70: × | S70: × | T70: 除外対象 | U70: =REPT("a"&CHAR(10)&"b",INT(LENB(SUBSTITUTE(T70,CHAR(10),""))/70))
C71: X_新規_ログ確認（夜間バッチエラー確認他） | E71: 2.03 | F71: - | G71: - | H71: - | I71: - | J71: - | K71: × | L71: × | M71: - | N71: 7月 | O71: - | P71: - | Q71: - | R71: 45870 | S71: -
C72: X_新規_レジクーポン発券設定ヘッダー（概要文言期間金額設定） | E72: 2.03 | F72: - | G72: - | H72: - | I72: - | J72: - | K72: × | L72: × | M72: - | N72: 8月 | O72: - | P72: - | Q72: - | R72: 45870 | S72: -
C73: X_新規_マスタダウンロード | E73: 2.03 | F73: - | G73: - | H73: - | I73: - | J73: - | K73: × | L73: × | M73: - | N73: 8月 | O73: - | P73: - | Q73: - | R73: 45878 | S73: -
C74: X_新規_レシートクーポン商品設定 | E74: 2.03 | F74: - | G74: - | H74: - | I74: - | J74: - | K74: × | L74: × | M74: - | N74: 8月 | O74: - | P74: - | Q74: - | R74: 45901 | S74: -
C75: X_グループ売価 | E75: 2.03 | F75: - | G75: - | H75: - | I75: - | J75: - | K75: × | L75: × | M75: - | N75: 9月 | O75: - | P75: - | Q75: - | R75: 45901 | S75: -
B76: 94 | C76: OCマスタ取り込み | E76: 1.47 | F76: - | G76: - | H76: - | I76: - | J76: - | K76: × | L76: × | M76: - | N76: 9月 | O76: - | P76: - | Q76: - | R76: 45931 | S76: -
B77: ●バッチ処理向け
B78: 基幹システムよりマスタ交換・取込み | U78: =REPT("a"&CHAR(10)&"b",INT(LENB(SUBSTITUTE(T78,CHAR(10),""))/70))
C79: 店舗マスタ | F79: - | G79: - | H79: - | I79: - | J79: - | K79: - | L79: - | M79: - | N79: - | O79: - | P79: - | Q79: - | R79: - | S79: - | U79: =REPT("a"&CHAR(10)&"b",INT(LENB(SUBSTITUTE(T79,CHAR(10),""))/70))
C80: 商品マスタ | F80: - | G80: - | H80: - | I80: - | J80: - | K80: - | L80: - | M80: - | N80: - | O80: - | P80: - | Q80: - | R80: - | S80: - | U80: =REPT("a"&CHAR(10)&"b",INT(LENB(SUBSTITUTE(T80,CHAR(10),""))/70))
C81: 商品階層マスタ | F81: - | G81: - | H81: - | I81: - | J81: - | K81: - | L81: - | M81: - | N81: - | O81: - | P81: - | Q81: - | R81: - | S81: - | U81: =REPT("a"&CHAR(10)&"b",INT(LENB(SUBSTITUTE(T81,CHAR(10),""))/70))
C82: 緊急売価マスタ | F82: - | G82: - | H82: - | I82: - | J82: - | K82: - | L82: - | M82: - | N82: - | O82: - | P82: - | Q82: - | R82: - | S82: - | U82: =REPT("a"&CHAR(10)&"b",INT(LENB(SUBSTITUTE(T82,CHAR(10),""))/70))
C83: 特売マスタ | F83: - | G83: - | H83: - | I83: - | J83: - | K83: - | L83: - | M83: - | N83: - | O83: - | P83: - | Q83: - | R83: - | S83: - | U83: =REPT("a"&CHAR(10)&"b",INT(LENB(SUBSTITUTE(T83,CHAR(10),""))/70))
C84: ミックスマッチマスタ | F84: - | G84: - | H84: - | I84: - | J84: - | K84: - | L84: - | M84: - | N84: - | O84: - | P84: - | Q84: - | R84: - | S84: - | U84: =REPT("a"&CHAR(10)&"b",INT(LENB(SUBSTITUTE(T84,CHAR(10),""))/70))
C85: 商品階層値引マスタ | F85: - | G85: - | H85: - | I85: - | J85: - | K85: - | L85: - | M85: - | N85: - | O85: - | P85: - | Q85: - | R85: - | S85: -
C86: 券マスタ | F86: - | G86: - | H86: - | I86: - | J86: - | K86: - | L86: - | M86: - | N86: - | O86: - | P86: - | Q86: - | R86: - | S86: -
C87: メガ割・朝割マスタ | F87: - | G87: - | H87: - | I87: - | J87: - | K87: - | L87: - | M87: - | N87: - | O87: - | P87: - | Q87: - | R87: - | S87: -
C88: 営業日マスタ（開設） | F88: - | G88: - | H88: - | I88: - | J88: - | K88: - | L88: - | M88: - | N88: - | O88: - | P88: - | Q88: - | R88: - | S88: -
C89: プロモーションマスタ | F89: - | G89: - | H89: - | I89: - | J89: - | K89: - | L89: - | M89: - | N89: - | O89: - | P89: - | Q89: - | R89: - | S89: -
C90: 従業員マスタ | F90: - | G90: - | H90: - | I90: - | J90: - | K90: - | L90: - | M90: - | N90: - | O90: - | P90: - | Q90: - | R90: - | S90: -
C91: WAONポイント | F91: - | G91: - | H91: - | I91: - | J91: - | K91: - | L91: - | M91: - | N91: - | O91: - | P91: - | Q91: - | R91: - | S91: -
C92: 商品ﾏｽﾀｰｲﾆｼｬﾙﾃﾞｰﾀ | D92: 新店 | F92: - | G92: - | H92: - | I92: - | J92: - | K92: - | L92: - | M92: - | N92: - | O92: - | P92: - | Q92: - | R92: - | S92: -
C93: 部門ﾏｽﾀｰｲﾆｼｬﾙﾃﾞｰﾀ | D93: 新店 | F93: - | G93: - | H93: - | I93: - | J93: - | K93: - | L93: - | M93: - | N93: - | O93: - | P93: - | Q93: - | R93: - | S93: -
C94: 大分類ﾏｽﾀｰｲﾆｼｬﾙﾃﾞｰﾀ | D94: 新店 | F94: - | G94: - | H94: - | I94: - | J94: - | K94: - | L94: - | M94: - | N94: - | O94: - | P94: - | Q94: - | R94: - | S94: -
C95: 中分類ﾏｽﾀｰｲﾆｼｬﾙﾃﾞｰﾀ | D95: 新店 | F95: - | G95: - | H95: - | I95: - | J95: - | K95: - | L95: - | M95: - | N95: - | O95: - | P95: - | Q95: - | R95: - | S95: -
C96: 小分類ﾏｽﾀｰｲﾆｼｬﾙﾃﾞｰﾀ | D96: 新店 | F96: - | G96: - | H96: - | I96: - | J96: - | K96: - | L96: - | M96: - | N96: - | O96: - | P96: - | Q96: - | R96: - | S96: -
C97: 大分類構成比ﾏｽﾀｰｲﾆｼｬﾙﾃﾞｰﾀ | D97: 新店 | F97: - | G97: - | H97: - | I97: - | J97: - | K97: - | L97: - | M97: - | N97: 5月 | O97: - | P97: - | Q97: - | R97: 45870 | S97: -
C98: 商品マスターメンテデータ | D98: 日次 | F98: - | G98: - | H98: - | I98: - | J98: - | K98: - | L98: - | M98: - | N98: - | O98: - | P98: - | Q98: - | R98: 45748 | S98: -
C99: 部門マスターメンテデータ | D99: 日次 | F99: - | G99: - | H99: - | I99: - | J99: - | K99: - | L99: - | M99: - | N99: 3月 | O99: - | P99: - | Q99: - | R99: 45748 | S99: -
C100: 大分類マスターメンテデータ | D100: 日次 | F100: - | G100: - | H100: - | I100: - | J100: - | K100: - | L100: - | M100: - | N100: 3月 | O100: - | P100: - | Q100: - | R100: 45778 | S100: -
C101: 中分類マスターメンテデータ | D101: 日次 | F101: - | G101: - | H101: - | I101: - | J101: - | K101: - | L101: - | M101: - | N101: 3月 | O101: - | P101: - | Q101: - | R101: 45809 | S101: -
C102: 小分類マスターメンテデータ | D102: 日次 | F102: - | G102: - | H102: - | I102: - | J102: - | K102: - | L102: - | M102: - | N102: 3月 | O102: - | P102: - | Q102: - | R102: 45809 | S102: -
...

Sheet テンプレート
A1: システム名 | K1: システム種別 | W1: =IF(表紙!W1="","",表紙!W1) -> 概要設計 | AP1: 作成者 | AT1: 作成日 | AY1: 更新者 | BC1: 更新日 | BH1: 版数
A2: =IF(表紙!A2="","",表紙!A2) -> POSサーバ | K2: =IF(表紙!K2="","",表紙!K2) -> 全般 | AP2: =IF(表紙!AP2="","",表紙!AP2) -> Huy Nguyen | AT2: =IF(表紙!AT2="","",表紙!AT2) -> 45532 | AY2: =IF(表紙!AY2="","",表紙!AY2) | BC2: =IF(表紙!BC2="","",表紙!BC2) | BH2: =IF(表紙!BH2="","",表紙!BH2) -> 0.31
A4: 機能カテゴリ | H4: =IF(表紙!H4="","",表紙!H4) -> 機能一覧 | U4: 項目 | Z4: =IF(表紙!Z4="","",表紙!Z4) -> いなげや様向け | AP4: {=RIGHT(CELL("filename",$A$1),LEN(CELL("filename",$A$1))-FIND("]",CELL("filename",$A$1)))} -> #VALUE!
