Workbook
Name _1Nagaoka_障害一覧_発生_改修: #REF!
Name _2Nagaoka_障害一覧_発生_改修: #REF!
Name _2Nagaoka_障害一覧_発生_改修: #REF!
Name _2Nagaoka_障害一覧_発生_改修: #REF!
Name _2Nagaoka_障害一覧_発生_改修: #REF!
Name _2Nagaoka_障害一覧_発生_改修: #REF!
Name _2Nagaoka_障害一覧_発生_改修: #REF!
Name _2Nagaoka_障害一覧_発生_改修: #REF!
Name _2Nagaoka_障害一覧_発生_改修: #REF!
Name _2Nagaoka_障害一覧_発生_改修: #REF!
Name _3Nagaoka_障害一覧_発生_改修: #REF!
Name _ctb１: '[1]現行DB一覧2(CT)'!$A$2:$E$220
Name _PFM2: [2]pfm002!$D$314:$D$316
Name _PFM21: [2]pfm002!$D$314:$D$316
Name _pfm3: #REF!
Name _pfm3: #REF!
Name _pfm3: #REF!
Name _pfm3: #REF!
Name _pfm3: #REF!
Name _pfm3: #REF!
Name _pfm3: #REF!
Name _pfm3: #REF!
Name _pfm3: #REF!
Name _pfm3: #REF!
Name _pfm3: #REF!
Name a: #REF!
Name DISC_CLASS_LVL: [3]DISC_CLASS_LVL!#REF!
Name DISC_CLASS_LVL: [3]DISC_CLASS_LVL!#REF!
Name DISC_CLASS_LVL: [3]DISC_CLASS_LVL!#REF!
Name DISC_CLASS_LVL: [3]DISC_CLASS_LVL!#REF!
Name DISC_CLASS_LVL: [3]DISC_CLASS_LVL!#REF!
Name DISC_CLASS_LVL: [3]DISC_CLASS_LVL!#REF!
Name DISC_CLASS_LVL: [3]DISC_CLASS_LVL!#REF!
Name DISC_CLASS_LVL: [3]DISC_CLASS_LVL!#REF!
Name DISC_CLASS_LVL: [3]DISC_CLASS_LVL!#REF!
Name DISC_CLASS_LVL: [3]DISC_CLASS_LVL!#REF!
Name DISC_EXCEPTION: #REF!
Name DISC_EXCEPTION: #REF!
Name DISC_EXCEPTION: #REF!
Name DISC_EXCEPTION: #REF!
Name DISC_EXCEPTION: #REF!
Name DISC_EXCEPTION: #REF!
Name DISC_EXCEPTION: #REF!
Name DISC_EXCEPTION: #REF!
Name DISC_EXCEPTION: #REF!
Name DISC_EXCEPTION: #REF!
Name DISC_EXCEPTION: #REF!
Name DISC_STEP: #REF!
Name DISC_STEP: #REF!
Name DISC_STEP: #REF!
Name DISC_STEP: #REF!
Name DISC_STEP: #REF!
Name DISC_STEP: #REF!
Name DISC_STEP: #REF!
Name DISC_STEP: #REF!
Name DISC_STEP: #REF!
Name DISC_STEP: #REF!
Name DISC_STEP: #REF!
Name DISC_TARGET: #REF!
Name DISC_TARGET: #REF!

Sheet 集計
C2: 予定項目数 | D2: 実績項目数 | E2: 残項目数 | F2: 完了率
B3: パッケージ系 | C3: =パッケージ系!$D$109 -> 130 | D3: =パッケージ系!$D$107 -> 0 | E3: =C3-D3 -> 130 | F3: =D3/C3 -> 0
B4: パッケージ系 (SS) | C4: ='パッケージ系 (SS)'!$D$109 -> 111 | D4: ='パッケージ系 (SS)'!$D$107 -> 0 | E4: =C4-D4 -> 111 | F4: =D4/C4 -> 0
B5: SPS系 | E5: =C5-D5 -> 0 | F5: =D5/C5 -> #DIV/0! | G5: ???
B6: パッケージ系 (PS) | C6: ='パッケージ系 (PS)'!$D$109 -> 128 | D6: ='パッケージ系 (PS)'!$D$107 -> 0 | E6: =C6-D6 -> 128 | F6: =D6/C6 -> 0
B7: サーバ系 | C7: 56 | D7: 56 | E7: =C7-D7 -> 0 | F7: =D7/C7 -> 1
B8: Win10対応_POS | C8: =Win10対応_POS!$D$94 -> 204 | D8: =Win10対応_POS!$D$92 -> 0 | E8: =C8-D8 -> 204 | F8: =D8/C8 -> 0
B9: Win10対応_SS | C9: =Win10対応_SS!$D$76 -> 47 | D9: =Win10対応_SS!$D$74 -> 0 | E9: =C9-D9 -> 47 | F9: =D9/C9 -> 0
B10: Win10対応_PS | C10: =Win10対応_PS!$D$76 -> 159 | D10: =Win10対応_PS!$D$74 -> 0 | E10: =C10-D10 -> 159 | F10: =D10/C10 -> 0
B11: Win10対応_フルセルフ | C11: =Win10対応_フルセルフ!$D$77 -> 184 | D11: =Win10対応_フルセルフ!$D$75 -> 0 | E11: =C11-D11 -> 184 | F11: =D11/C11 -> 0
B12: Win10対応_サーバ | C12: =Win10対応_サーバ!$D$25 -> 32 | D12: =Win10対応_サーバ!$D$23 -> 0 | E12: =C12-D12 -> 32 | F12: =D12/C12 -> 0
B13: 合計 | C13: =SUM(C3:C12) -> 1051 | D13: =SUM(D3:D12) -> 56 | E13: =SUM(E3:E12) -> 995 | F13: =D13/C13 -> 0.053282588

Sheet ST仕様書表紙
C4: TeamStore/M
C7: システムテスト仕様書兼完了報告書
C9: リグレッション（定型確認）
E15: 第１．７版 ２０２４年９月１３日
F26: 富士通株式会社
B27: GCSBG Retail事業本部 リテールチェーン事業部

Sheet 改版履歴
B2: TeamStore/M POSシステム | O2: システム名 | U2: 業務名 | Z2: リグレッションテスト
O3: TeamStore/M
C6: 改版履歴
C8: 日付 | G8: 版数 | I8: 章番号 | L8: 修正内容 | AM8: 担当
C10: 43650 | G10: 1 | L10: 新規作成 | AM10: 富士通
C12: 44225 | G12: 1.1 | L12: レイアウト変更 | AM12: 富士通
C14: 44229 | G14: 1.2 | L14: 標準PTFベースアップ項目追記 | AM14: 富士通
C16: 44230 | G16: 1.3 | L16: 項目精査実施 | AM16: 富士通
C18: 44245 | G18: 1.4 | L18: とくし丸リグレッションシート作成 | AM18: 富士通
C20: 44909 | G20: 1.5 | L20: Windows10対応シート作成 | AM20: 富士通
C22: 44970 | G22: 1.6 | L22: フルセルフシート作成 | AM22: 富士通
C24: 45548 | G24: 1.7 | L24: 交通系電子マネー項目追加 | AM24: 富士通

Sheet パッケージ系
B1: いなげや様 パッケージ リグレッションテスト仕様書
B2: 大分類 | C2: 中分類 | D2: 小分類 | E2: テスト項目 | H2: POS | Q2: チェック日付 | T2: 担当 | U2: 備考
E3: No | F3: POS操作 | G3: 結果 | H3: 動作 | I3: DB | J3: ｶｽﾀﾏ | K3: 画面 | L3: ﾚｼｰﾄ | M3: ｼﾞｬｰﾅﾙ | N3: 音声 | O3: ﾛｸﾞ | P3: 小型 LCD | Q3: OK | R3: NG | S3: 修正 OK
B4: 適用確認 | C4: リモメン | D4: PTFLOG | E4: =ROW()-3 -> 1 | F4: ログ確認 対象POS C:\GSFD直下 | G4: PTFLOGを開き、エラーが出力されていないこと | H4: ー | I4: ー | J4: ー | K4: ー | L4: ー | M4: ー | N4: ー | O4: □ | P4: ー
D5: PTFLOG2 | E5: =ROW()-3 -> 2 | F5: ログ確認 対象POS C:\GSFD直下 | G5: PTFLOG2を開き、エラーが出力されていないこと | H5: ー | I5: ー | J5: ー | K5: ー | L5: ー | M5: ー | N5: ー | O5: □ | P5: ー
C6: 外付けPTF適用 | D6: CTKYLOG | E6: =ROW()-3 -> 3 | F6: ログ確認 対象POS C:\CTKY直下 | G6: CTKYLOGを開き、エラーが出力されていないこと | H6: ー | I6: ー | J6: ー | K6: ー | L6: ー | M6: ー | N6: ー | O6: ー | P6: ー | U6: SSVで確認
D7: CTKYLOG2 | E7: =ROW()-3 -> 4 | F7: ログ確認 対象POS C:\CTKY直下 | G7: CTKYLOG2を開き、エラーが出力されていないこと | H7: ー | I7: ー | J7: ー | K7: ー | L7: ー | M7: ー | N7: ー | O7: ー | P7: ー | U7: SSVで確認
B8: 開局 | D8: 正常開局 | E8: =ROW()-3 -> 5 | G8: 正常に開局されること。決済端末が待機画面になること。 | H8: ー | I8: ー | J8: ー | K8: □ | L8: ー | M8: ー | N8: ー | O8: ー | P8: ー
D9: キーレイアウト | E9: =ROW()-3 -> 6 | G9: キーレイアウト反映の確認 （サーバのテストで、機能キーとプリセットの変更を行い反映されることを確認する） | H9: □ | I9: ー | J9: ー | K9: □ | L9: ー | M9: ー | N9: ー | O9: ー | P9: ー
C10: レシート | D10: さんにち割引 | E10: =ROW()-3 -> 7 | G10: 「さんにち割引」が表示されていること 対象日付が表示されていること | H10: ー | I10: ー | J10: ー | K10: ー | L10: □ | M10: □ | N10: ー | O10: ー | P10: ー
B11: OPキー | C11: 売上 | D11: 部門入力 | E11: =ROW()-3 -> 8 | F11: 動作確認 部門コード クラスボタン | G11: 部門コードを手入力して登録し、正常に登録できることを確認 | H11: □ | I11: ー | J11: ー | K11: □ | L11: ー | M11: ー | N11: ー | O11: ー | P11: ー
D12: フル部門キー登録 | E12: =ROW()-3 -> 9 | F12: プリセットは電子多項目で 登録されているボタン ・部門 フル部門キーはフルの部門キー | G12: プリセットで登録してあるフル部門キーを使用して登録し、 正常に登録できることを確認 | H12: □ | I12: ー | J12: ー | K12: □ | L12: ー | M12: ー | N12: ー | O12: ー | P12: ー
D13: 特売 | E13: =ROW()-3 -> 10 | G13: サーバで特売を登録し、正常にPOSに反映すること（リアルメンテ確認） | H13: □ | I13: ー | J13: ー | K13: □ | L13: ー | M13: ー | N13: ー | O13: ー | P13: ー
D14: キーPLU | E14: =ROW()-3 -> 11 | F14: 商品JANコードを入力しPLUボタン | G14: 正常に売上登録できること | H14: ー | I14: ー | J14: ー | K14: ー | L14: ー | M14: ー | N14: ー | O14: ー | P14: ー | U14: 運用未使用
D15: 保留 | E15: =ROW()-3 -> 12 | G15: 正常に取引を保留できること | H15: □ | I15: ー | J15: ー | K15: ー | L15: ー | M15: ー | N15: ー | O15: ー | P15: ー
D16: 復元 | E16: =ROW()-3 -> 13 | G16: 保留した取引を復元でき、追加で商品登録できること | H16: □ | I16: ー | J16: ー | K16: ー | L16: ー | M16: ー | N16: ー | O16: ー | P16: ー
D17: 乗算登録 | E17: =ROW()-3 -> 14 | G17: 乗算登録が正しくできること（前・後が正しく動作すること） | H17: □ | I17: ー | J17: ー | K17: ー | L17: ー | M17: ー | N17: ー | O17: ー | P17: ー
D18: 値引操作 | E18: =ROW()-3 -> 15 | G18: マニュアル値引が正しく動作すること（前・後が正しく動作すること） | H18: □ | I18: ー | J18: ー | K18: ー | L18: ー | M18: ー | N18: ー | O18: ー | P18: ー
E19: =ROW()-3 -> 16 | G19: 2人制時、明細一覧画面にて、マニュアル値引が正しく動作すること | H19: ー | I19: ー | J19: ー | K19: ー | L19: ー | M19: ー | N19: ー | O19: ー | P19: ー | U19: 電子多項目無し
E20: =ROW()-3 -> 17 | G20: 売価変更が正しくできること | H20: □ | I20: ー | J20: ー | K20: □ | L20: ー | M20: ー | N20: ー | O20: ー | P20: ー
D21: 訂正 | E21: =ROW()-3 -> 18 | G21: 指定訂正／直前訂正が正しくできること | H21: □ | I21: ー | J21: ー | K21: □ | L21: ー | M21: ー | N21: ー | O21: ー | P21: ー
D22: 現外券 | E22: =ROW()-3 -> 19 | F22: 商品券（支払い一覧にて選択） | G22: 現外券での支払い登録が正常にできること | H22: □ | I22: ー | J22: ー | K22: □ | L22: ー | M22: ー | N22: ー | O22: ー | P22: ー
D23: 再登録 | E23: =ROW()-3 -> 20 | G23: 再登録後、再度商品登録できること | H23: □ | I23: ー | J23: ー | K23: ー | L23: ー | M23: ー | N23: ー | O23: ー | P23: ー
D24: レシート印字 | E24: =ROW()-3 -> 21 | G24: 「今回ポイント **p」が表示されること | H24: ー | I24: ー | J24: ー | K24: ー | L24: □ | M24: □ | N24: ー | O24: ー | P24: ー
E25: =ROW()-3 -> 22 | G25: 「現在ポイント **p」が表示されること | H25: ー | I25: ー | J25: ー | K25: ー | L25: □ | M25: □ | N25: ー | O25: ー | P25: ー
E26: =ROW()-3 -> 23 | G26: 今回ポイント、現在ポイントのみ表示されること | H26: ー | I26: ー | J26: ー | K26: ー | L26: □ | M26: □ | N26: ー | O26: ー | P26: ー
D27: レシート印字（クレジット） | E27: =ROW()-3 -> 24 | G27: クレジットレシートのクレジット会社名が正しく印字されること | H27: ー | I27: ー | J27: ー | K27: ー | L27: □ | M27: □ | N27: ー | O27: ー | P27: ー
C28: デバイス | D28: 固定スキャナ | E28: =ROW()-3 -> 25 | G28: 商品登録できること | H28: ー | I28: ー | J28: ー | K28: ー | L28: ー | M28: ー | N28: ー | O28: ー | P28: ー | U28: 固定スキャナ無し
D29: タッチスキャナ | E29: =ROW()-3 -> 26 | G29: 商品登録できること | H29: □ | I29: ー | J29: ー | K29: ー | L29: ー | M29: ー | N29: ー | O29: ー | P29: ー
D30: IC決済端末 | E30: =ROW()-3 -> 27 | G30: カードの読み込みができること（ＩＣあり・ＩＣなし） | H30: □ | I30: ー | J30: ー | K30: ー | L30: ー | M30: ー | N30: ー | O30: ー | P30: ー
E31: =ROW()-3 -> 28 | G31: Vカード会員宣言ができること | H31: □ | I31: ー | J31: ー | K31: ー | L31: ー | M31: ー | N31: ー | O31: ー | P31: ー
D32: MSR（カードリーダ） | E32: =ROW()-3 -> 29 | G32: カードの読取できないこと | H32: ー | I32: ー | J32: ー | K32: ー | L32: ー | M32: ー | N32: ー | O32: ー | P32: ー | U32: MSR部がハード的に埋め込まれている
D33: MSR2（カードリーダ） | E33: =ROW()-3 -> 30 | G33: カードの読取できないこと（電子多項目横） | H33: ー | I33: ー | J33: ー | K33: ー | L33: ー | M33: ー | N33: ー | O33: ー | P33: ー | U33: 電子多項目無し
D34: メインキー | E34: =ROW()-3 -> 31 | G34: 動作すること | H34: □ | I34: ー | J34: ー | K34: ー | L34: ー | M34: ー | N34: ー | O34: ー | P34: ー
D35: ファンクションキー | E35: =ROW()-3 -> 32 | G35: 動作すること | H35: □ | I35: ー | J35: ー | K35: ー | L35: ー | M35: ー | N35: ー | O35: ー | P35: ー
D36: 電子多項目 物理キー | E36: =ROW()-3 -> 33 | G36: 動作すること | H36: ー | I36: ー | J36: ー | K36: ー | L36: ー | M36: ー | N36: ー | O36: ー | P36: ー | U36: 電子多項目無し
D37: 電子多項目 電子キー | E37: =ROW()-3 -> 34 | G37: 動作すること | H37: ー | I37: ー | J37: ー | K37: ー | L37: ー | M37: ー | N37: ー | O37: ー | P37: ー | U37: 電子多項目無し
D38: 単品一覧 | E38: =ROW()-3 -> 35 | G38: 登録できること | H38: □ | I38: ー | J38: ー | K38: □ | L38: ー | M38: ー | N38: ー | O38: ー | P38: ー
C39: バーコード | D39: JANコード 13桁/8桁 | E39: =ROW()-3 -> 36 | G39: 登録できること | H39: □ | I39: ー | J39: ー | K39: ー | L39: ー | M39: ー | N39: ー | O39: ー | P39: ー
D40: NON－PLUコード | E40: =ROW()-3 -> 37 | F40: 02から始まるバーコード 肉魚量売りバーコード バーコード後ろ下2桁から値段となる。 | G40: 登録できること | H40: □ | I40: ー | J40: ー | K40: ー | L40: ー | M40: ー | N40: ー | O40: ー | P40: ー
D41: 新雑誌コード（18桁） | E41: =ROW()-3 -> 38 | G41: 登録できること（491021104117300314） | H41: □ | I41: ー | J41: ー | K41: ー | L41: ー | M41: ー | N41: ー | O41: ー | P41: ー
D42: 書籍コード | E42: =ROW()-3 -> 39 | G42: 登録できること | H42: □ | I42: ー | J42: ー | K42: ー | L42: ー | M42: ー | N42: ー | O42: ー | P42: ー
D43: 1段値引バーコード（CODE128） | E43: =ROW()-3 -> 40 | F43: NONPLUで束になっているバーコードを使う | G43: 登録できること | H43: ー | I43: ー | J43: ー | K43: ー | L43: ー | M43: ー | N43: ー | O43: ー | P43: ー | U43: バーコードなし
D44: UPC A/E | E44: =ROW()-3 -> 41 | F44: UPCは輸入されたワインのバーコード、タバコ（ケント） | G44: 登録できること | H44: □ | I44: ー | J44: ー | K44: ー | L44: ー | M44: ー | N44: ー | O44: ー | P44: ー
D45: ITF（14桁） | E45: =ROW()-3 -> 42 | F45: 通番修正のバーコード | G45: 登録できること | H45: □ | I45: ー | J45: ー | K45: ー | L45: ー | M45: ー | N45: ー | O45: ー | P45: ー
D46: ingfan会員バーコード | E46: =ROW()-3 -> 43 | F46: ポイントカードに印字されているバーコード | G46: 登録できること | H46: ー | I46: ー | J46: ー | K46: ー | L46: ー | M46: ー | N46: ー | O46: ー | P46: ー | U46: Win10対応で実施
E47: =ROW()-3 -> 44 | F47: 読取エラーを想定し、会員識別外のバーコード 2899999999994 | G47: 入力エラーとなること | H47: □ | I47: ー | J47: ー | K47: □ | L47: ー | M47: ー | N47: ー | O47: ー | P47: ー
E48: =ROW()-3 -> 45 | F48: 読取エラーを想定し、 チェックデジット不一致のバーコード 2818208658799 | G48: 読取りできないこと | H48: □ | I48: ー | J48: ー | K48: ー | L48: ー | M48: ー | N48: ー | O48: ー | P48: ー
C49: 2人制 | D49: 1人2人制 | E49: =ROW()-3 -> 46 | G49: 正常に取引が行えることを確認 | H49: ー | I49: ー | J49: ー | K49: ー | L49: ー | M49: ー | N49: ー | O49: ー | P49: ー | U49: 電子多項目無し
D50: 1人2人制 | E50: =ROW()-3 -> 47 | G50: 正常に取引が行えることを確認 | H50: ー | I50: ー | J50: ー | K50: ー | L50: ー | M50: ー | N50: ー | O50: ー | P50: ー | U50: 電子多項目無し
E51: =ROW()-3 -> 48 | G51: 明細一覧画面にて、マニュアル値引が正しく動作すること | H51: ー | I51: ー | J51: ー | K51: ー | L51: ー | M51: ー | N51: ー | O51: ー | P51: ー | U51: 電子多項目無し
C52: 支払 | D52: 釣銭機動作 | E52: =ROW()-3 -> 49 | G52: 現金支払ができること | H52: □ | I52: ー | J52: ー | K52: ー | L52: ー | M52: ー | N52: ー | O52: ー | P52: ー
D53: クレジット | E53: =ROW()-3 -> 50 | G53: クレジット払いができること | H53: ー | I53: ー | J53: ー | K53: ー | L53: ー | M53: ー | N53: ー | O53: ー | P53: ー | U53: Win10対応で実施
D54: Suica | E54: =ROW()-3 -> 51 | G54: Suica支払が行えること | H54: □ | I54: ー | J54: ー | K54: ー | L54: ー | M54: ー | N54: ー | O54: ー | P54: ー
D55: Edy | E55: =ROW()-3 -> 52 | G55: Edy支払が行えること | H55: ー | I55: ー | J55: ー | K55: ー | L55: ー | M55: ー | N55: ー | O55: ー | P55: ー | U55: Edyは検証環境で使用不可
C56: その他 | D56: ジャーナル照会 | E56: =ROW()-3 -> 53 | G56: 取引の照会ができること | H56: ー | I56: ー | J56: ー | K56: □ | L56: ー | M56: □ | N56: ー | O56: ー | P56: ー
D57: クレジット | E57: =ROW()-3 -> 54 | F57: 支払時にクレジット宣言後カードを挿入し、 POSのガイダンスが「小計を押してください」に なる直前にクリア押下 | G57: アプリケーションエラーが表示されPOSが落ちないこと 「決済端末がキャンセルできません」と表示され、そのまま操作を継続し「小計を押してください」が表示されること | H57: □ | I57: ー | J57: ー | K57: □ | L57: ー | M57: ー | N57: ー | O57: ー | P57: ー
C58: 入／出金 | D58: 入金 | E58: =ROW()-3 -> 55 | G58: 入金処理が正常に終了すること（入金コード手入力・金種指定無し） | H58: □ | I58: ー | J58: ー | K58: ー | L58: ー | M58: ー | N58: ー | O58: ー | P58: ー
D59: 出金 | E59: =ROW()-3 -> 56 | G59: 出金処理が正常に終了すること（出金コード手入力・金種指定無し） | H59: □ | I59: ー | J59: ー | K59: ー | L59: ー | M59: ー | N59: ー | O59: ー | P59: ー
D60: 釣銭機出金 | E60: =ROW()-3 -> 57 | G60: 釣銭機出金が正常に終了すること | H60: □ | I60: ー | J60: ー | K60: ー | L60: ー | M60: ー | N60: ー | O60: ー | P60: ー | U60: 回収ボタンで実施
D61: 釣銭機両替 | E61: =ROW()-3 -> 58 | G61: 釣銭機両替が正常に終了すること | H61: □ | I61: ー | J61: ー | K61: ー | L61: ー | M61: ー | N61: ー | O61: ー | P61: ー
D62: 釣銭補充 | E62: =ROW()-3 -> 59 | G62: 正常動作すること | H62: □ | I62: ー | J62: ー | K62: ー | L62: ー | M62: ー | N62: ー | O62: ー | P62: ー
D63: 釣銭追加 | E63: =ROW()-3 -> 60 | G63: 正常動作すること | H63: □ | I63: ー | J63: ー | K63: ー | L63: ー | M63: ー | N63: ー | O63: ー | P63: ー
D64: 棒金ドロア追加 | E64: =ROW()-3 -> 61 | G64: 正常動作すること | H64: □ | I64: ー | J64: ー | K64: ー | L64: ー | M64: ー | N64: ー | O64: ー | P64: ー
C65: NONPLU | D65: バーコード価格 特売（売価設定） | E65: =ROW()-3 -> 62 | G65: NONPLUで束になっているバーコードを使う | H65: ー | I65: ー | J65: ー | K65: ー | L65: ー | M65: ー | N65: ー | O65: ー | P65: ー | U65: バーコードなし
D66: バーコード価格 特売（値引設定） | E66: =ROW()-3 -> 63 | G66: NONPLUで束になっているバーコードを使う | H66: ー | I66: ー | J66: ー | K66: ー | L66: ー | M66: ー | N66: ー | O66: ー | P66: ー | U66: 〃
D67: バーコード価格 特売（割引設定） | E67: =ROW()-3 -> 64 | G67: NONPLUで束になっているバーコードを使う | H67: ー | I67: ー | J67: ー | K67: ー | L67: ー | M67: ー | N67: ー | O67: ー | P67: ー | U67: 〃
C68: ポイント | D68: ポイント計算 （レシート確認） | E68: =ROW()-3 -> 65 | G68: 今回ポイント、現在ポイントのみ表示されていること 計算が正しいこと | H68: □ | I68: ー | J68: ー | K68: ー | L68: □ | M68: □ | N68: ー | O68: ー | P68: ー
D69: ポイント更新 （レシート確認） | E69: =ROW()-3 -> 66 | G69: 同一ポイントカードで、2回続けて、売上登録を行い、正常にポイントが更新されていることを確認する | H69: □ | I69: ー | J69: ー | K69: ー | L69: □ | M69: □ | N69: ー | O69: ー | P69: ー
D70: ポイント計算 （判定） | E70: =ROW()-3 -> 67 | G70: ポイント計算の自クレ判定（顧客コードの先頭）が正しく行えること Vカード支払い時、200円で２ポイントの付与 | H70: □ | I70: ー | J70: ー | K70: ー | L70: □ | M70: □ | N70: ー | O70: ー | P70: ー
D71: オフライン | E71: =ROW()-3 -> 68 | G71: オンラインからオフラインになった直後に、顧客登録を行い、正常に登録されること。レシートに今回ポイントが印字されること | H71: □ | I71: ー | J71: ー | K71: ー | L71: □ | M71: □ | N71: ー | O71: ー | P71: ー
D72: オフラインポイントデータ | E72: =ROW()-3 -> 69 | F72: ネットワークトラブルでsatisfaと連携されない場合、POSにて記録しsatisfaと連携された後のち、ポイント付与をする機能 | G72: オフラインポイントデータが、閉店でHPSに送信されること。翌日、オフラインポイント分が更新されていること | H72: ー | I72: ー | J72: ー | K72: ー | L72: ー | M72: ー | N72: ー | O72: ー | P72: ー
B73: Xモード | C73: 練習モード | D73: 通常売上 | E73: =ROW()-3 -> 70 | F73: 現金支払い | G73: 正常に動作すること（印字は？マーク。集計されない） | H73: □ | I73: ー | J73: ー | K73: ー | L73: □ | M73: ー | N73: ー | O73: ー | P73: ー
C74: レポート/オンライン | D74: 取引別 | E74: =ROW()-3 -> 71 | G74: 上記テストでの売上登録が集計されていること | H74: □ | I74: ー | J74: ー | K74: □ | L74: ー | M74: ー | N74: ー | O74: ー | P74: ー
D75: 商品階層別 | E75: =ROW()-3 -> 72 | F75: Xモード 商品階層別 | G75: 上記テストでの売上登録が集計されていること | H75: □ | I75: ー | J75: ー | K75: □ | L75: ー | M75: ー | N75: ー | O75: ー | P75: ー
D76: 担当者別 | E76: =ROW()-3 -> 73 | F76: Xモード 担当者別 | G76: 上記テストでの売上登録が集計されていること | H76: □ | I76: ー | J76: ー | K76: □ | L76: ー | M76: ー | N76: ー | O76: ー | P76: ー
D77: 客層別 | E77: =ROW()-3 -> 74 | F77: Xモード 客層別 | G77: 正常に動作することを確認 | H77: □ | I77: ー | J77: ー | K77: □ | L77: ー | M77: ー | N77: ー | O77: ー | P77: ー
D78: 商品階層別時間帯 | E78: =ROW()-3 -> 75 | F78: Xモード 商品階層別時間帯 | G78: 上記テストでの売上登録が集計されていること | H78: □ | I78: ー | J78: ー | K78: □ | L78: ー | M78: ー | N78: ー | O78: ー | P78: ー
D79: 全点検レシート | E79: =ROW()-3 -> 76 | F79: Xモード 全点検レシート | G79: 上記テストでの売上登録が集計されていること | H79: □ | I79: ー | J79: ー | K79: ー | L79: □ | M79: ー | N79: ー | O79: ー | P79: ー
D80: 在高点検レシート | E80: =ROW()-3 -> 77 | F80: Xモード 在高点検レシート | G80: 上記テストでの売上登録が集計されていること | H80: □ | I80: ー | J80: ー | K80: ー | L80: □ | M80: ー | N80: ー | O80: ー | P80: ー
C81: レポート/オフライン | D81: 取引別 | E81: =ROW()-3 -> 78 | F81: Xモード 取引別 | G81: 上記テストでの売上登録が集計されていること | H81: □ | I81: ー | J81: ー | K81: □ | L81: ー | M81: ー | N81: ー | O81: ー | P81: ー
D82: 担当者別時間帯 | E82: =ROW()-3 -> 79 | F82: Xモード 担当者別時間帯 | G82: 上記テストでの売上登録が集計されていること | H82: □ | I82: ー | J82: ー | K82: □ | L82: ー | M82: ー | N82: ー | O82: ー | P82: ー
D83: 全点検 | E83: =ROW()-3 -> 80 | F83: Xモード 全点検 | G83: 上記テストでの売上登録が集計されていること | H83: □ | I83: ー | J83: ー | K83: ー | L83: □ | M83: ー | N83: ー | O83: ー | P83: ー
D84: 在高点検 | E84: =ROW()-3 -> 81 | F84: Xモード 在高点検 | G84: 上記テストでの売上登録が集計されていること | H84: □ | I84: ー | J84: ー | K84: ー | L84: □ | M84: ー | N84: ー | O84: ー | P84: ー
C85: 電子ジャーナル | D85: 正常動作確認 | E85: =ROW()-3 -> 82 | F85: Xモード | G85: 正常に動作することを確認 | H85: □ | I85: ー | J85: ー | K85: □ | L85: ー | M85: ー | N85: ー | O85: ー | P85: ー
D86: レシート印字 | E86: =ROW()-3 -> 83 | F86: Xモード レシート印字 | G86: 「今回ポイント **p」が表示されること | H86: □ | I86: ー | J86: ー | K86: ー | L86: □ | M86: □ | N86: ー | O86: ー | P86: ー
E87: =ROW()-3 -> 84 | F87: Xモード | G87: 「現在ポイント **p」が表示されること | H87: □ | I87: ー | J87: ー | K87: ー | L87: □ | M87: □ | N87: ー | O87: ー | P87: ー
C88: テストスキャン | D88: テストスキャン | E88: =ROW()-3 -> 85 | F88: Xモード テストスキャン | G88: 正常に動作することを確認する | H88: □ | I88: ー | J88: ー | K88: □ | L88: ー | M88: ー | N88: ー | O88: ー | P88: ー
D89: 印字開始 | E89: =ROW()-3 -> 86 | F89: Xモード 印字開始 | G89: 正常に動作することを確認する | H89: □ | I89: ー | J89: ー | K89: ー | L89: □ | M89: ー | N89: ー | O89: ー | P89: ー
B90: Zモード | C90: 精算 | D90: 精算業務 | E90: =ROW()-3 -> 87 | G90: 正常に動作することを確認する | H90: □ | I90: ー | J90: ー | K90: □ | L90: □ | M90: ー | N90: ー | O90: ー | P90: ー
D91: 棒金ドロア | E91: =ROW()-3 -> 88 | G91: ドロアがオープンすること ※RT-200→自動オープン ※RT-500→手動オープン ※RT-300→「棒金ドロア追加ボタン」押下でオープン | H91: □ | I91: ー | J91: ー | K91: ー | L91: ー | M91: ー | N91: ー | O91: ー | P91: ー | U91: RT-500でBOX回収ボタンを押しても回収できない。 RT-200用にBOX回収ボタンがある。 BOX回収するには全回収か紙幣途中回収でBOX回収ができる。 BOXにはその日の売上金が入っている。そのまま釣銭機にいれる。
C92: マイナス | D92: 通常売上 | E92: =ROW()-3 -> 89 | G92: 正常に動作すること（ﾏｲﾅｽ集計する/しないはシステム設定） | H92: □ | I92: ー | J92: ー | K92: □ | L92: □ | M92: □ | N92: ー | O92: ー | P92: ー
C93: 通番修正 | D93: 通番修正 | E93: =ROW()-3 -> 90 | G93: 正常に動作することを確認 | H93: ー | I93: ー | J93: ー | K93: ー | L93: ー | M93: ー | N93: ー | O93: ー | P93: ー | U93: Win10対応で実施
C94: 通番取消 | D94: 通番取消 | E94: =ROW()-3 -> 91 | G94: 正常に動作することを確認 | H94: ー | I94: ー | J94: ー | K94: ー | L94: ー | M94: ー | N94: ー | O94: ー | P94: ー | U94: Win10対応で実施
C95: ポイント修正 | D95: ポイント修正 | E95: =ROW()-3 -> 92 | G95: ポイント修正を実施して正常にポイントの加算・減算ができること。 | H95: ー | I95: ー | J95: ー | K95: ー | L95: ー | M95: ー | N95: ー | O95: ー | P95: ー | U95: Win10対応で実施
E96: =ROW()-3 -> 93 | G96: ポイント修正で顧客登録後に中止できること。 | H96: □ | I96: ー | J96: ー | K96: ー | L96: ー | M96: ー | N96: ー | O96: ー | P96: ー
E97: =ROW()-3 -> 94 | G97: ポイント修正でingfanクラブカードをスキャンした時、 決済端末に対しカード読み込みのキャンセルを依頼した後に、 スキャナのデバイス停止を行い連続スキャンが抑止されていること。 また、キャンセル結果の応答を受信後、スキャナのデバイスが再開されること。 | H97: □ | I97: ー | J97: ー | K97: □ | L97: ー | M97: ー | N97: ー | O97: ー | P97: ー
E98: =ROW()-3 -> 95 | G98: ポイント修正でingfanクラブカードをスキャンした時、 決済端末に対しカード読み込みのキャンセルを依頼した後に、 登録キーが入力された場合無効音を鳴動し、入力無効となること。 | H98: □ | I98: ー | J98: ー | K98: ー | L98: ー | M98: ー | N98: ー | O98: ー | P98: ー
C99: 全回収 | D99: 正常動作確認 | E99: =ROW()-3 -> 96 | F99: 全回収（Zモード） | G99: 正しく動作することを確認 | H99: □ | I99: ー | J99: ー | K99: ー | L99: ー | M99: ー | N99: ー | O99: ー | P99: ー
C100: 紙幣途中回収（移動） | D100: 正常動作確認 | E100: =ROW()-3 -> 97 | F100: 紙幣途中回収（移動）（Zモード） | G100: 正しく動作することを確認 | H100: □ | I100: ー | J100: ー | K100: ー | L100: ー | M100: ー | N100: ー | O100: ー | P100: ー | U100: RT-300の場合、BOXがでてくるので鍵で開けてとる
...

Sheet パッケージ系 (SS)
B1: いなげや様 パッケージ リグレッションテスト仕様書
B2: 大分類 | C2: 中分類 | D2: 小分類 | E2: テスト項目 | H2: SS | Q2: チェック日付 | T2: 担当 | U2: 備考
E3: No | F3: POS操作 | G3: 結果 | H3: 動作 | I3: DB | J3: ｶｽﾀﾏ | K3: 画面 | L3: ﾚｼｰﾄ | M3: ｼﾞｬｰﾅﾙ | N3: 音声 | O3: ﾛｸﾞ | P3: 小型 LCD | Q3: OK | R3: NG | S3: 修正 OK
B4: 適用確認 | C4: リモメン | D4: PTFLOG | E4: =ROW()-3 -> 1 | F4: ログ確認 対象POS C:\GSFD直下 | G4: PTFLOGを開き、エラーが出力されていないこと | H4: ー | I4: ー | J4: ー | K4: ー | L4: ー | M4: ー | N4: ー | O4: □ | P4: ー
D5: PTFLOG2 | E5: =ROW()-3 -> 2 | F5: ログ確認 対象POS C:\GSFD直下 | G5: PTFLOG2を開き、エラーが出力されていないこと | H5: ー | I5: ー | J5: ー | K5: ー | L5: ー | M5: ー | N5: ー | O5: □ | P5: ー
C6: 外付けPTF適用 | D6: CTKYLOG | E6: =ROW()-3 -> 3 | F6: ログ確認 対象POS C:\CTKY直下 | G6: CTKYLOGを開き、エラーが出力されていないこと | H6: ー | I6: ー | J6: ー | K6: ー | L6: ー | M6: ー | N6: ー | O6: ー | P6: ー | U6: SSVで確認
D7: CTKYLOG2 | E7: =ROW()-3 -> 4 | F7: ログ確認 対象POS C:\CTKY直下 | G7: CTKYLOG2を開き、エラーが出力されていないこと | H7: ー | I7: ー | J7: ー | K7: ー | L7: ー | M7: ー | N7: ー | O7: ー | P7: ー | U7: SSVで確認
B8: 開局 | D8: 正常開局 | E8: =ROW()-3 -> 5 | G8: 正常に開局されること | H8: ー | I8: ー | J8: ー | K8: □ | L8: ー | M8: ー | N8: ー | O8: ー | P8: ー
D9: キーレイアウト | E9: =ROW()-3 -> 6 | G9: キーレイアウト反映の確認 （サーバのテストで、機能キーとプリセットの変更を行い反映されることを確認する） | H9: □ | I9: ー | J9: ー | K9: □ | L9: ー | M9: ー | N9: ー | O9: ー | P9: ー
C10: レシート | D10: さんにち割引 | E10: =ROW()-3 -> 7 | G10: 「さんにち割引」が表示されていること 対象日付が表示されていること | H10: ー | I10: ー | J10: ー | K10: ー | L10: □ | M10: □ | N10: ー | O10: ー | P10: ー
B11: OPキー | C11: 売上 | D11: 部門入力 | E11: =ROW()-3 -> 8 | F11: 動作確認 部門コード クラスボタン | G11: 部門コードを手入力して登録し、正常に登録できることを確認 | H11: □ | I11: ー | J11: ー | K11: □ | L11: ー | M11: ー | N11: ー | O11: ー | P11: ー
D12: フル部門キー登録 | E12: =ROW()-3 -> 9 | F12: プリセットは電子多項目で 登録されているボタン ・部門 フル部門キーはフルの部門キー | G12: プリセットで登録してあるフル部門キーを使用して登録し、 正常に登録できることを確認 | H12: □ | I12: ー | J12: ー | K12: □ | L12: ー | M12: ー | N12: ー | O12: ー | P12: ー
D13: 特売 | E13: =ROW()-3 -> 10 | G13: サーバで特売を登録し、正常にPOSに反映すること（リアルメンテ確認） | H13: □ | I13: ー | J13: ー | K13: □ | L13: ー | M13: ー | N13: ー | O13: ー | P13: ー
D14: キーPLU | E14: =ROW()-3 -> 11 | F14: 商品JANコードを入力しPLUボタン | G14: 正常に売上登録できること | H14: ー | I14: ー | J14: ー | K14: ー | L14: ー | M14: ー | N14: ー | O14: ー | P14: ー | U14: 運用未使用
D15: 保留 | E15: =ROW()-3 -> 12 | G15: 正常に取引を保留できること | H15: □ | I15: ー | J15: ー | K15: ー | L15: ー | M15: ー | N15: ー | O15: ー | P15: ー
D16: 復元 | E16: =ROW()-3 -> 13 | G16: 保留した取引を復元でき、追加で商品登録できること | H16: □ | I16: ー | J16: ー | K16: ー | L16: ー | M16: ー | N16: ー | O16: ー | P16: ー
D17: 乗算登録 | E17: =ROW()-3 -> 14 | G17: 乗算登録が正しくできること（前・後が正しく動作すること） | H17: □ | I17: ー | J17: ー | K17: ー | L17: ー | M17: ー | N17: ー | O17: ー | P17: ー
D18: 値引操作 | E18: =ROW()-3 -> 15 | G18: マニュアル値引が正しく動作すること（前・後が正しく動作すること） | H18: □ | I18: ー | J18: ー | K18: ー | L18: ー | M18: ー | N18: ー | O18: ー | P18: ー
E19: =ROW()-3 -> 16 | G19: 2人制時、明細一覧画面にて、マニュアル値引が正しく動作すること | H19: ー | I19: ー | J19: ー | K19: ー | L19: ー | M19: ー | N19: ー | O19: ー | P19: ー | U19: 2人制運用なし
E20: =ROW()-3 -> 17 | G20: 売価変更が正しくできること | H20: □ | I20: ー | J20: ー | K20: □ | L20: ー | M20: ー | N20: ー | O20: ー | P20: ー
D21: 訂正 | E21: =ROW()-3 -> 18 | G21: 指定訂正／直前訂正が正しくできること | H21: □ | I21: ー | J21: ー | K21: □ | L21: ー | M21: ー | N21: ー | O21: ー | P21: ー
D22: 現外券 | E22: =ROW()-3 -> 19 | F22: 商品券（支払い一覧にて選択） | G22: 現外券での支払い登録が正常にできること | H22: □ | I22: ー | J22: ー | K22: □ | L22: ー | M22: ー | N22: ー | O22: ー | P22: ー
D23: 再登録 | E23: =ROW()-3 -> 20 | G23: 再登録後、再度商品登録できること | H23: □ | I23: ー | J23: ー | K23: ー | L23: ー | M23: ー | N23: ー | O23: ー | P23: ー
D24: レシート印字 | E24: =ROW()-3 -> 21 | G24: 「今回ポイント **p」が表示されること | H24: ー | I24: ー | J24: ー | K24: ー | L24: □ | M24: □ | N24: ー | O24: ー | P24: ー
E25: =ROW()-3 -> 22 | G25: 「現在ポイント **p」が表示されること | H25: ー | I25: ー | J25: ー | K25: ー | L25: □ | M25: □ | N25: ー | O25: ー | P25: ー
E26: =ROW()-3 -> 23 | G26: 今回ポイント、現在ポイントのみ表示されること | H26: ー | I26: ー | J26: ー | K26: ー | L26: □ | M26: □ | N26: ー | O26: ー | P26: ー
D27: レシート印字（クレジット） | E27: =ROW()-3 -> 24 | G27: クレジットレシートのクレジット会社名が正しく印字されること | H27: ー | I27: ー | J27: ー | K27: ー | L27: ー | M27: ー | N27: ー | O27: ー | P27: ー | U27: 決済端末未接続
C28: デバイス | D28: 固定スキャナ | E28: =ROW()-3 -> 25 | G28: 商品登録できること | H28: □ | I28: ー | J28: ー | K28: ー | L28: ー | M28: ー | N28: ー | O28: ー | P28: ー
D29: タッチスキャナ | E29: =ROW()-3 -> 26 | G29: 商品登録できること | H29: □ | I29: ー | J29: ー | K29: ー | L29: ー | M29: ー | N29: ー | O29: ー | P29: ー
D30: IC決済端末 | E30: =ROW()-3 -> 27 | G30: カードの読み込みができること（ＩＣあり・ＩＣなし） | H30: ー | I30: ー | J30: ー | K30: ー | L30: ー | M30: ー | N30: ー | O30: ー | P30: ー
E31: =ROW()-3 -> 28 | G31: Vカード会員宣言ができること | H31: ー | I31: ー | J31: ー | K31: ー | L31: ー | M31: ー | N31: ー | O31: ー | P31: ー
D32: MSR（カードリーダ） | E32: =ROW()-3 -> 29 | G32: カードの読取できないこと | H32: ー | I32: ー | J32: ー | K32: ー | L32: ー | M32: ー | N32: ー | O32: ー | P32: ー | U32: MSR設置なし
D33: MSR2（カードリーダ） | E33: =ROW()-3 -> 30 | G33: カードの読取できないこと（電子多項目横） | H33: ー | I33: ー | J33: ー | K33: ー | L33: ー | M33: ー | N33: ー | O33: ー | P33: ー | U33: MSR設置なし
D34: メインキー | E34: =ROW()-3 -> 31 | G34: 動作すること | H34: □ | I34: ー | J34: ー | K34: ー | L34: ー | M34: ー | N34: ー | O34: ー | P34: ー
D35: ファンクションキー | E35: =ROW()-3 -> 32 | G35: 動作すること | H35: □ | I35: ー | J35: ー | K35: ー | L35: ー | M35: ー | N35: ー | O35: ー | P35: ー
D36: 電子多項目 物理キー | E36: =ROW()-3 -> 33 | G36: 動作すること | H36: □ | I36: ー | J36: ー | K36: ー | L36: ー | M36: ー | N36: ー | O36: ー | P36: ー
D37: 電子多項目 電子キー | E37: =ROW()-3 -> 34 | G37: 動作すること | H37: □ | I37: ー | J37: ー | K37: ー | L37: ー | M37: ー | N37: ー | O37: ー | P37: ー
D38: 単品一覧 | E38: =ROW()-3 -> 35 | G38: 登録できること | H38: □ | I38: ー | J38: ー | K38: □ | L38: ー | M38: ー | N38: ー | O38: ー | P38: ー
C39: バーコード | D39: JANコード 13桁/8桁 | E39: =ROW()-3 -> 36 | G39: 登録できること | H39: □ | I39: ー | J39: ー | K39: ー | L39: ー | M39: ー | N39: ー | O39: ー | P39: ー
D40: NON－PLUコード | E40: =ROW()-3 -> 37 | F40: 02から始まるバーコード 肉魚量売りバーコード バーコード後ろ下2桁から値段となる。 | G40: 登録できること | H40: □ | I40: ー | J40: ー | K40: ー | L40: ー | M40: ー | N40: ー | O40: ー | P40: ー
D41: 新雑誌コード（18桁） | E41: =ROW()-3 -> 38 | G41: 登録できること（491021104117300314） | H41: □ | I41: ー | J41: ー | K41: ー | L41: ー | M41: ー | N41: ー | O41: ー | P41: ー
D42: 書籍コード | E42: =ROW()-3 -> 39 | G42: 登録できること | H42: □ | I42: ー | J42: ー | K42: ー | L42: ー | M42: ー | N42: ー | O42: ー | P42: ー
D43: 1段値引バーコード（CODE128） | E43: =ROW()-3 -> 40 | F43: NONPLUで束になっているバーコードを使う | G43: 登録できること | H43: ー | I43: ー | J43: ー | K43: ー | L43: ー | M43: ー | N43: ー | O43: ー | P43: ー | U43: バーコードなし
D44: UPC A/E | E44: =ROW()-3 -> 41 | F44: UPCは輸入されたワインのバーコード、タバコ（ケント） | G44: 登録できること | H44: □ | I44: ー | J44: ー | K44: ー | L44: ー | M44: ー | N44: ー | O44: ー | P44: ー
D45: ITF（14桁） | E45: =ROW()-3 -> 42 | F45: 通番修正のバーコード | G45: 登録できること | H45: □ | I45: ー | J45: ー | K45: ー | L45: ー | M45: ー | N45: ー | O45: ー | P45: ー | U45: タッチスキャナのみ読取可
D46: ingfan会員バーコード | E46: =ROW()-3 -> 43 | F46: ポイントカードに印字されているバーコード | G46: 登録できること | H46: ー | I46: ー | J46: ー | K46: ー | L46: ー | M46: ー | N46: ー | O46: ー | P46: ー | U46: Win10対応_SSで実施
E47: =ROW()-3 -> 44 | F47: 読取エラーを想定し、会員識別外のバーコード 2899999999994 | G47: 入力エラーとなること | H47: □ | I47: ー | J47: ー | K47: □ | L47: ー | M47: ー | N47: ー | O47: ー | P47: ー
E48: =ROW()-3 -> 45 | F48: 読取エラーを想定し、 チェックデジット不一致のバーコード 2818208658799 | G48: 読取りできないこと | H48: □ | I48: ー | J48: ー | K48: ー | L48: ー | M48: ー | N48: ー | O48: ー | P48: ー
C49: 2人制 | D49: 1人2人制 | E49: =ROW()-3 -> 46 | G49: 正常に取引が行えることを確認 | H49: ー | I49: ー | J49: ー | K49: ー | L49: ー | M49: ー | N49: ー | O49: ー | P49: ー | U49: 2人制運用なし
D50: 1人2人制 | E50: =ROW()-3 -> 47 | G50: 正常に取引が行えることを確認 | H50: ー | I50: ー | J50: ー | K50: ー | L50: ー | M50: ー | N50: ー | O50: ー | P50: ー | U50: 2人制運用なし
E51: =ROW()-3 -> 48 | G51: 明細一覧画面にて、マニュアル値引が正しく動作すること | H51: ー | I51: ー | J51: ー | K51: ー | L51: ー | M51: ー | N51: ー | O51: ー | P51: ー | U51: 2人制運用なし
C52: 支払 | D52: 釣銭機動作 | E52: =ROW()-3 -> 49 | G52: 支払ができること | H52: ー | I52: ー | J52: ー | K52: ー | L52: ー | M52: ー | N52: ー | O52: ー | P52: ー | U52: 釣銭機接続なし
D53: クレジット | E53: =ROW()-3 -> 50 | G53: クレジット払いができること | H53: ー | I53: ー | J53: ー | K53: ー | L53: ー | M53: ー | N53: ー | O53: ー | P53: ー
D54: Suica | E54: =ROW()-3 -> 51 | G54: Suica支払が行えること | H54: ー | I54: ー | J54: ー | K54: ー | L54: ー | M54: ー | N54: ー | O54: ー | P54: ー | U54: 決済端末未接続
D55: Edy | E55: =ROW()-3 -> 52 | G55: Edy支払が行えること | H55: ー | I55: ー | J55: ー | K55: ー | L55: ー | M55: ー | N55: ー | O55: ー | P55: ー | U55: Edyは検証環境で使用不可
C56: その他 | D56: ジャーナル照会 | E56: =ROW()-3 -> 53 | G56: 取引の照会ができること | H56: ー | I56: ー | J56: ー | K56: □ | L56: ー | M56: □ | N56: ー | O56: ー | P56: ー
D57: クレジット | E57: =ROW()-3 -> 54 | F57: 支払時にクレジット宣言後カードを挿入し、 POSのガイダンスが「小計を押してください」に なる直前にクリア押下 | G57: アプリケーションエラーが表示されPOSが落ちないこと 「決済端末がキャンセルできません」と表示され、そのまま操作を継続し「小計を押してください」が表示されること | H57: ー | I57: ー | J57: ー | K57: ー | L57: ー | M57: ー | N57: ー | O57: ー | P57: ー | U57: 決済端末未接続
C58: 入／出金 | D58: 入金 | E58: =ROW()-3 -> 55 | G58: 入金処理が正常に終了すること（入金コード手入力・金種指定無し） | H58: ー | I58: ー | J58: ー | K58: ー | L58: ー | M58: ー | N58: ー | O58: ー | P58: ー | U58: 釣銭機接続なし
D59: 出金 | E59: =ROW()-3 -> 56 | G59: 出金処理が正常に終了すること（出金コード手入力・金種指定無し） | H59: ー | I59: ー | J59: ー | K59: ー | L59: ー | M59: ー | N59: ー | O59: ー | P59: ー | U59: 釣銭機接続なし
D60: 釣銭機出金 | E60: =ROW()-3 -> 57 | G60: 釣銭機出金が正常に終了すること | H60: ー | I60: ー | J60: ー | K60: ー | L60: ー | M60: ー | N60: ー | O60: ー | P60: ー | U60: 釣銭機接続なし
D61: 釣銭機両替 | E61: =ROW()-3 -> 58 | G61: 釣銭機両替が正常に終了すること | H61: ー | I61: ー | J61: ー | K61: ー | L61: ー | M61: ー | N61: ー | O61: ー | P61: ー | U61: 釣銭機接続なし
D62: 釣銭補充 | E62: =ROW()-3 -> 59 | G62: 正常動作すること | H62: ー | I62: ー | J62: ー | K62: ー | L62: ー | M62: ー | N62: ー | O62: ー | P62: ー | U62: 釣銭機接続なし
D63: 釣銭追加 | E63: =ROW()-3 -> 60 | G63: 正常動作すること | H63: ー | I63: ー | J63: ー | K63: ー | L63: ー | M63: ー | N63: ー | O63: ー | P63: ー | U63: 釣銭機接続なし
D64: 棒金ドロア追加 | E64: =ROW()-3 -> 61 | G64: 正常動作すること | H64: ー | I64: ー | J64: ー | K64: ー | L64: ー | M64: ー | N64: ー | O64: ー | P64: ー | U64: 釣銭機接続なし
C65: NONPLU | D65: バーコード価格 特売（売価設定） | E65: =ROW()-3 -> 62 | G65: NONPLUで束になっているバーコードを使う | H65: ー | I65: ー | J65: ー | K65: ー | L65: ー | M65: ー | N65: ー | O65: ー | P65: ー | U65: バーコードなし
D66: バーコード価格 特売（値引設定） | E66: =ROW()-3 -> 63 | G66: NONPLUで束になっているバーコードを使う | H66: ー | I66: ー | J66: ー | K66: ー | L66: ー | M66: ー | N66: ー | O66: ー | P66: ー | U66: 〃
D67: バーコード価格 特売（割引設定） | E67: =ROW()-3 -> 64 | G67: NONPLUで束になっているバーコードを使う | H67: ー | I67: ー | J67: ー | K67: ー | L67: ー | M67: ー | N67: ー | O67: ー | P67: ー | U67: 〃
C68: ポイント | D68: ポイント計算 （レシート確認） | E68: =ROW()-3 -> 65 | G68: 今回ポイント、現在ポイントのみ表示されていること 計算が正しいこと | H68: ー | I68: ー | J68: ー | K68: ー | L68: ー | M68: ー | N68: ー | O68: ー | P68: ー | U68: Win10対応_SSで実施
D69: ポイント更新 （レシート確認） | E69: =ROW()-3 -> 66 | G69: 同一ポイントカードで、2回続けて、売上登録を行い、正常にポイントが更新されていることを確認する | H69: □ | I69: ー | J69: ー | K69: ー | L69: □ | M69: □ | N69: ー | O69: ー | P69: ー
D70: ポイント計算 （判定） | E70: =ROW()-3 -> 67 | G70: ポイント計算の自クレ判定（顧客コードの先頭）が正しく行えること Vカード支払い時、200円で２ポイントの付与 | H70: ー | I70: ー | J70: ー | K70: ー | L70: ー | M70: ー | N70: ー | O70: ー | P70: ー | U70: 決済端末未接続のため、Vカード支払不可
D71: オフライン | E71: =ROW()-3 -> 68 | G71: オンラインからオフラインになった直後に、顧客登録を行い、正常に登録されること。レシートに今回ポイントが印字されること | H71: □ | I71: ー | J71: ー | K71: ー | L71: □ | M71: □ | N71: ー | O71: ー | P71: ー
D72: オフラインポイントデータ | E72: =ROW()-3 -> 69 | F72: ネットワークトラブルでsatisfaと連携されない場合、POSにて記録しsatisfaと連携された後のち、ポイント付与をする機能 | G72: オフラインポイントデータが、閉店でHPSに送信されること。翌日、オフラインポイント分が更新されていること | H72: ー | I72: ー | J72: ー | K72: ー | L72: ー | M72: ー | N72: ー | O72: ー | P72: ー
B73: Xモード | C73: 練習モード | D73: 通常売上 | E73: =ROW()-3 -> 70 | G73: 正常に動作すること（印字は？マーク。集計されない） | H73: □ | I73: ー | J73: ー | K73: ー | L73: □ | M73: ー | N73: ー | O73: ー | P73: ー
C74: レポート/オンライン | D74: 取引別 | E74: =ROW()-3 -> 71 | G74: 上記テストでの売上登録が集計されていること | H74: □ | I74: ー | J74: ー | K74: □ | L74: ー | M74: ー | N74: ー | O74: ー | P74: ー
D75: 商品階層別 | E75: =ROW()-3 -> 72 | F75: Xモード 商品階層別 | G75: 上記テストでの売上登録が集計されていること | H75: □ | I75: ー | J75: ー | K75: □ | L75: ー | M75: ー | N75: ー | O75: ー | P75: ー
D76: 担当者別 | E76: =ROW()-3 -> 73 | F76: Xモード 担当者別 | G76: 上記テストでの売上登録が集計されていること | H76: □ | I76: ー | J76: ー | K76: □ | L76: ー | M76: ー | N76: ー | O76: ー | P76: ー
D77: 客層別 | E77: =ROW()-3 -> 74 | F77: Xモード 客層別 | G77: 正常に動作することを確認 | H77: □ | I77: ー | J77: ー | K77: □ | L77: ー | M77: ー | N77: ー | O77: ー | P77: ー
D78: 商品階層別時間帯 | E78: =ROW()-3 -> 75 | F78: Xモード 商品階層別時間帯 | G78: 上記テストでの売上登録が集計されていること | H78: □ | I78: ー | J78: ー | K78: □ | L78: ー | M78: ー | N78: ー | O78: ー | P78: ー
D79: 全点検レシート | E79: =ROW()-3 -> 76 | F79: Xモード 全点検レシート | G79: 上記テストでの売上登録が集計されていること | H79: □ | I79: ー | J79: ー | K79: ー | L79: □ | M79: ー | N79: ー | O79: ー | P79: ー
D80: 在高点検レシート | E80: =ROW()-3 -> 77 | F80: Xモード 在高点検レシート | G80: 上記テストでの売上登録が集計されていること | H80: □ | I80: ー | J80: ー | K80: ー | L80: □ | M80: ー | N80: ー | O80: ー | P80: ー
C81: レポート/オフライン | D81: 取引別 | E81: =ROW()-3 -> 78 | F81: Xモード 取引別 | G81: 上記テストでの売上登録が集計されていること | H81: □ | I81: ー | J81: ー | K81: □ | L81: ー | M81: ー | N81: ー | O81: ー | P81: ー
D82: 担当者別時間帯 | E82: =ROW()-3 -> 79 | F82: Xモード 担当者別時間帯 | G82: 上記テストでの売上登録が集計されていること | H82: □ | I82: ー | J82: ー | K82: □ | L82: ー | M82: ー | N82: ー | O82: ー | P82: ー
D83: 全点検 | E83: =ROW()-3 -> 80 | F83: Xモード 全点検 | G83: 上記テストでの売上登録が集計されていること | H83: □ | I83: ー | J83: ー | K83: ー | L83: □ | M83: ー | N83: ー | O83: ー | P83: ー | U83: オフライン警告印字あり
D84: 在高点検 | E84: =ROW()-3 -> 81 | F84: Xモード 在高点検 | G84: 上記テストでの売上登録が集計されていること | H84: □ | I84: ー | J84: ー | K84: ー | L84: □ | M84: ー | N84: ー | O84: ー | P84: ー | U84: オフライン警告印字あり
C85: 電子ジャーナル | D85: 正常動作確認 | E85: =ROW()-3 -> 82 | F85: Xモード | G85: 正常に動作することを確認 | H85: □ | I85: ー | J85: ー | K85: □ | L85: ー | M85: ー | N85: ー | O85: ー | P85: ー
D86: レシート印字 | E86: =ROW()-3 -> 83 | F86: Xモード レシート印字 | G86: 「今回ポイント **p」が表示されること | H86: □ | I86: ー | J86: ー | K86: ー | L86: □ | M86: □ | N86: ー | O86: ー | P86: ー
E87: =ROW()-3 -> 84 | F87: Xモード | G87: 「現在ポイント **p」が表示されること | H87: □ | I87: ー | J87: ー | K87: ー | L87: □ | M87: □ | N87: ー | O87: ー | P87: ー
C88: テストスキャン | D88: テストスキャン | E88: =ROW()-3 -> 85 | F88: Xモード テストスキャン | G88: 正常に動作することを確認する | H88: □ | I88: ー | J88: ー | K88: □ | L88: ー | M88: ー | N88: ー | O88: ー | P88: ー
D89: 印字開始 | E89: =ROW()-3 -> 86 | F89: Xモード 印字開始 | G89: 正常に動作することを確認する | H89: □ | I89: ー | J89: ー | K89: ー | L89: □ | M89: ー | N89: ー | O89: ー | P89: ー
B90: Zモード | C90: 精算 | D90: 精算業務 | E90: =ROW()-3 -> 87 | G90: 正しく動作することを確認 | H90: □ | I90: ー | J90: ー | K90: □ | L90: □ | M90: ー | N90: ー | O90: ー | P90: ー
D91: 棒金ドロア | E91: =ROW()-3 -> 88 | G91: ドロアがオープンすること ※RT-200→自動オープン ※RT-500→手動オープン | H91: ー | I91: ー | J91: ー | K91: ー | L91: ー | M91: ー | N91: ー | O91: ー | P91: ー | U91: RT-500で+K142:X142BOX回収ボタンを押しても回収できない。 RT-200用にBOX回収ボタンがある。 BOX回収するには全回収か紙幣途中回収でBOX回収ができる。 BOXにはその日の売上金が入っている。そのまま釣銭機にいれる。
C92: マイナス | D92: 通常売上 | E92: =ROW()-3 -> 89 | G92: 正常に動作すること（ﾏｲﾅｽ集計する/しないはシステム設定） | H92: □ | I92: ー | J92: ー | K92: □ | L92: □ | M92: □ | N92: ー | O92: ー | P92: ー
C93: 通番修正 | D93: 通番修正 | E93: =ROW()-3 -> 90 | G93: 正常に動作することを確認 | H93: □ | I93: ー | J93: ー | K93: □ | L93: □ | M93: □ | N93: ー | O93: ー | P93: ー
C94: 通番取消 | D94: 通番取消 | E94: =ROW()-3 -> 91 | G94: 正常に動作することを確認 | H94: □ | I94: ー | J94: ー | K94: □ | L94: □ | M94: □ | N94: ー | O94: ー | P94: ー
C95: ポイント修正 | D95: ポイント修正 | E95: =ROW()-3 -> 92 | G95: ポイント修正を実施して正常にポイントの加算・減算ができること。 | H95: ー | I95: ー | J95: ー | K95: ー | L95: ー | M95: ー | N95: ー | O95: ー | P95: ー | U95: SSでポイント修正の運用なし
E96: =ROW()-3 -> 93 | G96: ポイント修正で顧客登録後に中止できること。 | H96: ー | I96: ー | J96: ー | K96: ー | L96: ー | M96: ー | N96: ー | O96: ー | P96: ー | U96: SSでポイント修正の運用なし
E97: =ROW()-3 -> 94 | G97: ポイント修正でingfanクラブカードをスキャンした時、 決済端末に対しカード読み込みのキャンセルを依頼した後に、 スキャナのデバイス停止を行い連続スキャンが抑止されていること。 また、キャンセル結果の応答を受信後、スキャナのデバイスが再開されること。 | H97: ー | I97: ー | J97: ー | K97: ー | L97: ー | M97: ー | N97: ー | O97: ー | P97: ー | U97: SSでポイント修正の運用なし
E98: =ROW()-3 -> 95 | G98: ポイント修正でingfanクラブカードをスキャンした時、 決済端末に対しカード読み込みのキャンセルを依頼した後に、 登録キーが入力された場合無効音を鳴動し、入力無効となること。 | H98: ー | I98: ー | J98: ー | K98: ー | L98: ー | M98: ー | N98: ー | O98: ー | P98: ー | U98: SSでポイント修正の運用なし
C99: 全回収 | D99: 正常動作確認 | E99: =ROW()-3 -> 96 | G99: 正しく動作することを確認 | H99: ー | I99: ー | J99: ー | K99: ー | L99: ー | M99: ー | N99: ー | O99: ー | P99: ー
C100: 紙幣途中回収（移動） | D100: 正常動作確認 | E100: =ROW()-3 -> 97 | G100: 正しく動作することを確認 | H100: ー | I100: ー | J100: ー | K100: ー | L100: ー | M100: ー | N100: ー | O100: ー | P100: ー | U100: RT-500の場合、BOXがでてくるので鍵で開けてとる
...

Sheet パッケージ系 (PS)
B1: いなげや様 パッケージ リグレッションテスト仕様書
B2: 大分類 | C2: 中分類 | D2: 小分類 | E2: テスト項目 | H2: PS | Q2: チェック日付 | T2: 担当 | U2: 備考
E3: No | F3: POS操作 | G3: 結果 | H3: 動作 | I3: DB | J3: ｶｽﾀﾏ | K3: 画面 | L3: ﾚｼｰﾄ | M3: ｼﾞｬｰﾅﾙ | N3: 音声 | O3: ﾛｸﾞ | P3: 小型 LCD | Q3: OK | R3: NG | S3: 修正 OK
B4: 適用確認 | C4: リモメン | D4: PTFLOG | E4: =ROW()-3 -> 1 | F4: ログ確認 対象POS C:\GSFD直下 | G4: PTFLOGを開き、エラーが出力されていないこと | H4: ー | I4: ー | J4: ー | K4: ー | L4: ー | M4: ー | N4: ー | O4: □ | P4: ー
D5: PTFLOG2 | E5: =ROW()-3 -> 2 | F5: ログ確認 対象POS C:\GSFD直下 | G5: PTFLOG2を開き、エラーが出力されていないこと | H5: ー | I5: ー | J5: ー | K5: ー | L5: ー | M5: ー | N5: ー | O5: □ | P5: ー
C6: 外付けPTF適用 | D6: CTKYLOG | E6: =ROW()-3 -> 3 | F6: ログ確認 対象POS C:\CTKY直下 | G6: CTKYLOGを開き、エラーが出力されていないこと | H6: ー | I6: ー | J6: ー | K6: ー | L6: ー | M6: ー | N6: ー | O6: ー | P6: ー
D7: CTKYLOG2 | E7: =ROW()-3 -> 4 | F7: ログ確認 対象POS C:\CTKY直下 | G7: CTKYLOG2を開き、エラーが出力されていないこと | H7: ー | I7: ー | J7: ー | K7: ー | L7: ー | M7: ー | N7: ー | O7: ー | P7: ー
B8: 開局 | D8: 正常開局 | E8: =ROW()-3 -> 5 | G8: 正常に開局されること。決済端末が待機画面になること。 | H8: ー | I8: ー | J8: ー | K8: □ | L8: ー | M8: ー | N8: ー | O8: ー | P8: ー
D9: キーレイアウト | E9: =ROW()-3 -> 6 | G9: キーレイアウト反映の確認 （サーバのテストで、機能キーとプリセットの変更を行い反映されることを確認する） | H9: □ | I9: ー | J9: ー | K9: □ | L9: ー | M9: ー | N9: ー | O9: ー | P9: ー
C10: レシート | D10: さんにち割引 | E10: =ROW()-3 -> 7 | G10: 「さんにち割引」が表示されていること 対象日付が表示されていること | H10: ー | I10: ー | J10: ー | K10: ー | L10: □ | M10: □ | N10: ー | O10: ー | P10: ー
B11: OPキー | C11: 売上 | D11: 部門入力 | E11: =ROW()-3 -> 8 | F11: 動作確認 部門コード クラスボタン | G11: 部門コードを手入力して登録し、正常に登録できることを確認 | H11: □ | I11: ー | J11: ー | K11: □ | L11: ー | M11: ー | N11: ー | O11: ー | P11: ー
D12: フル部門キー登録 | E12: =ROW()-3 -> 9 | F12: プリセットは電子多項目で 登録されているボタン ・部門 フル部門キーはフルの部門キー | G12: プリセットで登録してあるフル部門キーを使用して登録し、 正常に登録できることを確認 | H12: □ | I12: ー | J12: ー | K12: □ | L12: ー | M12: ー | N12: ー | O12: ー | P12: ー
D13: 特売 | E13: =ROW()-3 -> 10 | G13: サーバで特売を登録し、正常にPOSに反映すること（リアルメンテ確認） | H13: □ | I13: ー | J13: ー | K13: □ | L13: ー | M13: ー | N13: ー | O13: ー | P13: ー
D14: キーPLU | E14: =ROW()-3 -> 11 | F14: 商品JANコードを入力しPLUボタン | G14: 正常に売上登録できること | H14: ー | I14: ー | J14: ー | K14: ー | L14: ー | M14: ー | N14: ー | O14: ー | P14: ー | U14: 運用で未使用
D15: 保留 | E15: =ROW()-3 -> 12 | G15: 正常に取引を保留できること | H15: ー | I15: ー | J15: ー | K15: ー | L15: ー | M15: ー | N15: ー | O15: ー | P15: ー | U15: 保留・復元キーなし
D16: 復元 | E16: =ROW()-3 -> 13 | G16: 保留した取引を復元でき、追加で商品登録できること | H16: ー | I16: ー | J16: ー | K16: ー | L16: ー | M16: ー | N16: ー | O16: ー | P16: ー | U16: 保留取引が復元できない（保留取引がある場合、OPモード「クローズ」、Zモード「精算」「保守」「閉局」操作不可）
D17: 乗算登録 | E17: =ROW()-3 -> 14 | G17: 乗算登録が正しくできること（前・後が正しく動作すること） | H17: □ | I17: ー | J17: ー | K17: ー | L17: ー | M17: ー | N17: ー | O17: ー | P17: ー
D18: 値引操作 | E18: =ROW()-3 -> 15 | G18: マニュアル値引が正しく動作すること（前・後が正しく動作すること） | H18: ー | I18: ー | J18: ー | K18: ー | L18: ー | M18: ー | N18: ー | O18: ー | P18: ー | U18: マニュアル値引ボタンなし
E19: =ROW()-3 -> 16 | G19: 2人制時、明細一覧画面にて、マニュアル値引が正しく動作すること | H19: ー | I19: ー | J19: ー | K19: ー | L19: ー | M19: ー | N19: ー | O19: ー | P19: ー | U19: マニュアル値引ボタンなし
E20: =ROW()-3 -> 17 | G20: 売価変更が正しくできること | H20: □ | I20: ー | J20: ー | K20: □ | L20: ー | M20: ー | N20: ー | O20: ー | P20: ー
D21: 訂正 | E21: =ROW()-3 -> 18 | G21: 指定訂正／直前訂正が正しくできること | H21: □ | I21: ー | J21: ー | K21: □ | L21: ー | M21: ー | N21: ー | O21: ー | P21: ー
D22: 現外券 | E22: =ROW()-3 -> 19 | F22: 商品券（支払い一覧にて選択） | G22: 現外券での支払い登録が正常にできること | H22: □ | I22: ー | J22: ー | K22: □ | L22: ー | M22: ー | N22: ー | O22: ー | P22: ー
D23: 再登録 | E23: =ROW()-3 -> 20 | G23: 再登録後、再度商品登録できること | H23: □ | I23: ー | J23: ー | K23: ー | L23: ー | M23: ー | N23: ー | O23: ー | P23: ー
D24: レシート印字 | E24: =ROW()-3 -> 21 | G24: 「今回ポイント **p」が表示されること | H24: ー | I24: ー | J24: ー | K24: ー | L24: □ | M24: □ | N24: ー | O24: ー | P24: ー
E25: =ROW()-3 -> 22 | G25: 「現在ポイント **p」が表示されること | H25: ー | I25: ー | J25: ー | K25: ー | L25: □ | M25: □ | N25: ー | O25: ー | P25: ー
E26: =ROW()-3 -> 23 | G26: 今回ポイント、現在ポイントのみ表示されること | H26: ー | I26: ー | J26: ー | K26: ー | L26: □ | M26: □ | N26: ー | O26: ー | P26: ー
D27: レシート印字（クレジット） | E27: =ROW()-3 -> 24 | G27: クレジットレシートのクレジット会社名印字が正しく印字されること | H27: ー | I27: ー | J27: ー | K27: ー | L27: □ | M27: □ | N27: ー | O27: ー | P27: ー
C28: デバイス | D28: 固定スキャナ | E28: =ROW()-3 -> 25 | G28: 商品登録できること | H28: □ | I28: ー | J28: ー | K28: ー | L28: ー | M28: ー | N28: ー | O28: ー | P28: ー
D29: タッチスキャナ | E29: =ROW()-3 -> 26 | G29: 商品登録できること | H29: ー | I29: ー | J29: ー | K29: ー | L29: ー | M29: ー | N29: ー | O29: ー | P29: ー | U29: PSタッチスキャナ接続なし
D30: IC決済端末 | E30: =ROW()-3 -> 27 | G30: カードの読み込みができること（ＩＣあり・ＩＣなし） | H30: □ | I30: ー | J30: ー | K30: ー | L30: ー | M30: ー | N30: ー | O30: ー | P30: ー
E31: =ROW()-3 -> 28 | G31: Vカード会員宣言ができること | H31: □ | I31: ー | J31: ー | K31: ー | L31: ー | M31: ー | N31: ー | O31: ー | P31: ー
D32: MSR（カードリーダ） | E32: =ROW()-3 -> 29 | G32: カードの読取できないこと | H32: ー | I32: ー | J32: ー | K32: ー | L32: ー | M32: ー | N32: ー | O32: ー | P32: ー
D33: MSR2（カードリーダ） | E33: =ROW()-3 -> 30 | G33: カードの読取できないこと（電子多項目横） | H33: ー | I33: ー | J33: ー | K33: ー | L33: ー | M33: ー | N33: ー | O33: ー | P33: ー
D34: メインキー | E34: =ROW()-3 -> 31 | G34: 動作すること | H34: ー | I34: ー | J34: ー | K34: ー | L34: ー | M34: ー | N34: ー | O34: ー | P34: ー
D35: ファンクションキー | E35: =ROW()-3 -> 32 | G35: 動作すること | H35: □ | I35: ー | J35: ー | K35: ー | L35: ー | M35: ー | N35: ー | O35: ー | P35: ー
D36: 電子多項目 物理キー | E36: =ROW()-3 -> 33 | G36: 動作すること | H36: ー | I36: ー | J36: ー | K36: ー | L36: ー | M36: ー | N36: ー | O36: ー | P36: ー
D37: 電子多項目 電子キー | E37: =ROW()-3 -> 34 | G37: 動作すること | H37: ー | I37: ー | J37: ー | K37: ー | L37: ー | M37: ー | N37: ー | O37: ー | P37: ー
D38: 単品一覧 | E38: =ROW()-3 -> 35 | G38: 登録できること | H38: □ | I38: ー | J38: ー | K38: □ | L38: ー | M38: ー | N38: ー | O38: ー | P38: ー
C39: バーコード | D39: JANコード 13桁/8桁 | E39: =ROW()-3 -> 36 | G39: 登録できること | H39: □ | I39: ー | J39: ー | K39: ー | L39: ー | M39: ー | N39: ー | O39: ー | P39: ー
D40: NON－PLUコード | E40: =ROW()-3 -> 37 | F40: 02から始まるバーコード 肉魚量売りバーコード バーコード後ろ下2桁から値段となる。 | G40: 登録できること | H40: □ | I40: ー | J40: ー | K40: ー | L40: ー | M40: ー | N40: ー | O40: ー | P40: ー
D41: 新雑誌コード（18桁） | E41: =ROW()-3 -> 38 | G41: 登録できること（491021104117300314） | H41: □ | I41: ー | J41: ー | K41: ー | L41: ー | M41: ー | N41: ー | O41: ー | P41: ー
D42: 書籍コード | E42: =ROW()-3 -> 39 | G42: 登録できること | H42: □ | I42: ー | J42: ー | K42: ー | L42: ー | M42: ー | N42: ー | O42: ー | P42: ー
D43: 1段値引バーコード（CODE128） | E43: =ROW()-3 -> 40 | F43: NONPLUで束になっているバーコードを使う | G43: 登録できること | H43: ー | I43: ー | J43: ー | K43: ー | L43: ー | M43: ー | N43: ー | O43: ー | P43: ー | U43: バーコードなし
D44: UPC A/E | E44: =ROW()-3 -> 41 | F44: UPCは輸入されたワインのバーコード、タバコ（ケント） | G44: 登録できること | H44: □ | I44: ー | J44: ー | K44: ー | L44: ー | M44: ー | N44: ー | O44: ー | P44: ー
D45: ITF（14桁） | E45: =ROW()-3 -> 42 | F45: 通番修正のバーコード | G45: 登録できること | H45: ー | I45: ー | J45: ー | K45: ー | L45: ー | M45: ー | N45: ー | O45: ー | P45: ー | U45: カメラスキャナでは不可
D46: ingfan会員バーコード | E46: =ROW()-3 -> 43 | F46: ポイントカードに印字されているバーコード | G46: 登録できること | H46: □ | I46: ー | J46: ー | K46: □ | L46: ー | M46: ー | N46: ー | O46: ー | P46: ー
E47: =ROW()-3 -> 44 | F47: 読取エラーを想定し、会員識別外のバーコード 2899999999994 | G47: 入力エラーとなること | H47: □ | I47: ー | J47: ー | K47: □ | L47: ー | M47: ー | N47: ー | O47: ー | P47: ー
E48: =ROW()-3 -> 45 | F48: 読取エラーを想定し、 チェックデジット不一致のバーコード 2818208658799 | G48: 読取りできないこと | H48: □ | I48: ー | J48: ー | K48: ー | L48: ー | M48: ー | N48: ー | O48: ー | P48: ー
C49: 2人制 | D49: 1人2人制 | E49: =ROW()-3 -> 46 | G49: 正常に取引が行えることを確認 | H49: ー | I49: ー | J49: ー | K49: ー | L49: ー | M49: ー | N49: ー | O49: ー | P49: ー
D50: 1人2人制 | E50: =ROW()-3 -> 47 | G50: 正常に取引が行えることを確認 | H50: ー | I50: ー | J50: ー | K50: ー | L50: ー | M50: ー | N50: ー | O50: ー | P50: ー
E51: =ROW()-3 -> 48 | G51: 明細一覧画面にて、マニュアル値引が正しく動作すること | H51: ー | I51: ー | J51: ー | K51: ー | L51: ー | M51: ー | N51: ー | O51: ー | P51: ー
C52: 支払 | D52: 釣銭機動作 | E52: =ROW()-3 -> 49 | G52: 支払ができること | H52: □ | I52: ー | J52: ー | K52: ー | L52: ー | M52: ー | N52: ー | O52: ー | P52: ー
D53: クレジット | E53: =ROW()-3 -> 50 | G53: クレジット払いができること | H53: □ | I53: ー | J53: ー | K53: ー | L53: ー | M53: ー | N53: ー | O53: ー | P53: ー
D54: Suica | E54: =ROW()-3 -> 51 | G54: Suica支払が行えること | H54: □ | I54: ー | J54: ー | K54: ー | L54: ー | M54: ー | N54: ー | O54: ー | P54: ー
D55: Edy | E55: =ROW()-3 -> 52 | G55: Edy支払が行えること | H55: ー | I55: ー | J55: ー | K55: ー | L55: ー | M55: ー | N55: ー | O55: ー | P55: ー | U55: Edyは検証環境で使用不可
C56: その他 | D56: ジャーナル照会 | E56: =ROW()-3 -> 53 | G56: 取引の照会ができること | H56: ー | I56: ー | J56: ー | K56: □ | L56: ー | M56: □ | N56: ー | O56: ー | P56: ー
D57: クレジット | E57: =ROW()-3 -> 54 | F57: 支払時にクレジット宣言後カードを挿入し、 POSのガイダンスが「小計を押してください」に なる直前にクリア押下 | G57: アプリケーションエラーが表示されPOSが落ちないこと。 | H57: □ | I57: ー | J57: ー | K57: □ | L57: ー | M57: ー | N57: ー | O57: ー | P57: ー
C58: 入／出金 | D58: 入金 | E58: =ROW()-3 -> 55 | G58: 入金処理が正常に終了すること（入金コード手入力・金種指定無し） | H58: □ | I58: ー | J58: ー | K58: ー | L58: ー | M58: ー | N58: ー | O58: ー | P58: ー
D59: 出金 | E59: =ROW()-3 -> 56 | G59: 出金処理が正常に終了すること（出金コード手入力・金種指定無し） | H59: □ | I59: ー | J59: ー | K59: ー | L59: ー | M59: ー | N59: ー | O59: ー | P59: ー
D60: 釣銭機出金 | E60: =ROW()-3 -> 57 | G60: 釣銭機出金が正常に終了すること | H60: □ | I60: ー | J60: ー | K60: ー | L60: ー | M60: ー | N60: ー | O60: ー | P60: ー
D61: 釣銭機両替 | E61: =ROW()-3 -> 58 | G61: 釣銭機両替が正常に終了すること | H61: □ | I61: ー | J61: ー | K61: ー | L61: ー | M61: ー | N61: ー | O61: ー | P61: ー
D62: 釣銭補充 | E62: =ROW()-3 -> 59 | G62: 正常動作すること | H62: 6y | I62: ー | J62: ー | K62: ー | L62: ー | M62: ー | N62: ー | O62: ー | P62: ー
D63: 釣銭追加 | E63: =ROW()-3 -> 60 | G63: 正常動作すること | H63: □ | I63: ー | J63: ー | K63: ー | L63: ー | M63: ー | N63: ー | O63: ー | P63: ー
D64: 棒金ドロア追加 | E64: =ROW()-3 -> 61 | G64: 正常動作すること | H64: □ | I64: ー | J64: ー | K64: ー | L64: ー | M64: ー | N64: ー | O64: ー | P64: ー
C65: NONPLU | D65: バーコード価格 特売（売価設定） | E65: =ROW()-3 -> 62 | G65: NONPLUで束になっているバーコードを使う | H65: ー | I65: ー | J65: ー | K65: ー | L65: ー | M65: ー | N65: ー | O65: ー | P65: ー | U65: バーコードなし
D66: バーコード価格 特売（値引設定） | E66: =ROW()-3 -> 63 | G66: NONPLUで束になっているバーコードを使う | H66: ー | I66: ー | J66: ー | K66: ー | L66: ー | M66: ー | N66: ー | O66: ー | P66: ー | U66: 〃
D67: バーコード価格 特売（割引設定） | E67: =ROW()-3 -> 64 | G67: NONPLUで束になっているバーコードを使う | H67: ー | I67: ー | J67: ー | K67: ー | L67: ー | M67: ー | N67: ー | O67: ー | P67: ー | U67: 〃
C68: ポイント | D68: ポイント計算 （レシート確認） | E68: =ROW()-3 -> 65 | G68: 今回ポイント、現在ポイントのみ表示されていること 計算が正しいこと | H68: □ | I68: ー | J68: ー | K68: ー | L68: □ | M68: □ | N68: ー | O68: ー | P68: ー
D69: ポイント更新 （レシート確認） | E69: =ROW()-3 -> 66 | G69: 同一ポイントカードで、2回続けて、売上登録を行い、正常にポイントが更新されていることを確認する | H69: □ | I69: ー | J69: ー | K69: ー | L69: □ | M69: □ | N69: ー | O69: ー | P69: ー
D70: ポイント計算 （判定） | E70: =ROW()-3 -> 67 | G70: ポイント計算の自クレ判定（顧客コードの先頭）が正しく行えること Vカード支払い時、200円で２ポイントの付与 | H70: □ | I70: ー | J70: ー | K70: ー | L70: □ | M70: □ | N70: ー | O70: ー | P70: ー
D71: オフライン | E71: =ROW()-3 -> 68 | G71: オンラインからオフラインになった直後に、顧客登録を行い、正常に登録されること。レシートに今回ポイントが印字されること | H71: □ | I71: ー | J71: ー | K71: ー | L71: □ | M71: □ | N71: ー | O71: ー | P71: ー
D72: オフラインポイントデータ | E72: =ROW()-3 -> 69 | F72: ネットワークトラブルでsatisfaと連携されない場合、POSにて記録しsatisfaと連携された後のち、ポイント付与をする機能 | G72: オフラインポイントデータが、閉店でHPSに送信されること。翌日、オフラインポイント分が更新されていること | H72: ー | I72: ー | J72: ー | K72: ー | L72: ー | M72: ー | N72: ー | O72: ー | P72: ー
B73: Xモード | C73: 練習モード | D73: 通常売上 | E73: =ROW()-3 -> 70 | G73: 正常に動作すること（印字は？マーク。集計されない） | H73: □ | I73: ー | J73: ー | L73: □ | M73: ー | N73: ー | O73: ー | P73: ー
C74: レポート/オンライン | D74: 取引別 | E74: =ROW()-3 -> 71 | G74: 上記テストでの売上登録が集計されていること | H74: □ | I74: ー | J74: ー | K74: □ | L74: ー | M74: ー | N74: ー | O74: ー | P74: ー
D75: 商品階層別 | E75: =ROW()-3 -> 72 | F75: Xモード 商品階層別 | G75: 上記テストでの売上登録が集計されていること | H75: □ | I75: ー | J75: ー | K75: □ | L75: ー | M75: ー | N75: ー | O75: ー | P75: ー
D76: 担当者別 | E76: =ROW()-3 -> 73 | F76: Xモード 担当者別 | G76: 上記テストでの売上登録が集計されていること | H76: □ | I76: ー | J76: ー | K76: □ | L76: ー | M76: ー | N76: ー | O76: ー | P76: ー
D77: 客層別 | E77: =ROW()-3 -> 74 | F77: Xモード 客層別 | G77: 正常に動作することを確認 | H77: □ | I77: ー | J77: ー | K77: □ | L77: ー | M77: ー | N77: ー | O77: ー | P77: ー
D78: 商品階層別時間帯 | E78: =ROW()-3 -> 75 | F78: Xモード 商品階層別時間帯 | G78: 上記テストでの売上登録が集計されていること | H78: □ | I78: ー | J78: ー | K78: □ | L78: ー | M78: ー | N78: ー | O78: ー | P78: ー
D79: 全点検レシート | E79: =ROW()-3 -> 76 | F79: Xモード 全点検レシート | G79: 上記テストでの売上登録が集計されていること | H79: □ | I79: ー | J79: ー | K79: ー | L79: □ | M79: ー | N79: ー | O79: ー | P79: ー
D80: 在高点検レシート | E80: =ROW()-3 -> 77 | F80: Xモード 在高点検レシート | G80: 上記テストでの売上登録が集計されていること | H80: □ | I80: ー | J80: ー | K80: ー | L80: □ | M80: ー | N80: ー | O80: ー | P80: ー
C81: レポート/オフライン | D81: 取引別 | E81: =ROW()-3 -> 78 | F81: Xモード 取引別 | G81: 上記テストでの売上登録が集計されていること | H81: □ | I81: ー | J81: ー | K81: □ | L81: ー | M81: ー | N81: ー | O81: ー | P81: ー
D82: 担当者別時間帯 | E82: =ROW()-3 -> 79 | F82: Xモード 担当者別時間帯 | G82: 上記テストでの売上登録が集計されていること | H82: □ | I82: ー | J82: ー | K82: □ | L82: ー | M82: ー | N82: ー | O82: ー | P82: ー
D83: 全点検 | E83: =ROW()-3 -> 80 | F83: Xモード 全点検 | G83: 上記テストでの売上登録が集計されていること | H83: □ | I83: ー | J83: ー | K83: ー | L83: □ | M83: ー | N83: ー | O83: ー | P83: ー
D84: 在高点検 | E84: =ROW()-3 -> 81 | F84: Xモード 在高点検 | G84: 上記テストでの売上登録が集計されていること | H84: □ | I84: ー | J84: ー | K84: ー | L84: □ | M84: ー | N84: ー | O84: ー | P84: ー
C85: 電子ジャーナル | D85: 正常動作確認 | E85: =ROW()-3 -> 82 | F85: Xモード | G85: 正常に動作することを確認 | H85: □ | I85: ー | J85: ー | K85: □ | L85: ー | M85: ー | N85: ー | O85: ー | P85: ー
D86: レシート印字 | E86: =ROW()-3 -> 83 | F86: Xモード レシート印字 | G86: 「今回ポイント **p」が表示されること | H86: □ | I86: ー | J86: ー | K86: ー | L86: □ | M86: □ | N86: ー | O86: ー | P86: ー
E87: =ROW()-3 -> 84 | F87: Xモード | G87: 「現在ポイント **p」が表示されること | H87: □ | I87: ー | J87: ー | K87: ー | L87: □ | M87: □ | N87: ー | O87: ー | P87: ー
C88: テストスキャン | D88: テストスキャン | E88: =ROW()-3 -> 85 | F88: Xモード テストスキャン | G88: 正常に動作することを確認する | H88: □ | I88: ー | J88: ー | K88: □ | L88: ー | M88: ー | N88: ー | O88: ー | P88: ー
D89: 印字開始 | E89: =ROW()-3 -> 86 | F89: Xモード 印字開始 | G89: 正常に動作することを確認する | H89: □ | I89: ー | J89: ー | K89: ー | L89: □ | M89: ー | N89: ー | O89: ー | P89: ー
B90: Zモード | C90: 精算 | D90: 精算業務 | E90: =ROW()-3 -> 87 | G90: 正しく動作することを確認 | H90: □ | I90: ー | J90: ー | K90: □ | L90: □ | M90: ー | N90: ー | O90: ー | P90: ー
D91: 棒金ドロア | E91: =ROW()-3 -> 88 | G91: ドロアがオープンすること ※RT-200→自動オープン ※RT-500→手動オープン | H91: □ | I91: ー | J91: ー | K91: ー | L91: ー | M91: ー | N91: ー | O91: ー | P91: ー | U91: ドロアは自動オープンしない
C92: マイナス | D92: 通常売上 | E92: =ROW()-3 -> 89 | G92: 正常に動作すること（ﾏｲﾅｽ集計する/しないはシステム設定） | H92: □ | I92: ー | J92: ー | K92: □ | L92: □ | M92: □ | N92: ー | O92: ー | P92: ー
C93: 通番修正 | D93: 通番修正 | E93: =ROW()-3 -> 90 | G93: 正常に動作することを確認 | H93: ー | I93: ー | J93: ー | K93: ー | L93: ー | M93: ー | N93: ー | O93: ー | P93: ー | U93: Win10対応(PS)で実施
C94: 通番取消 | D94: 通番取消 | E94: =ROW()-3 -> 91 | G94: 正常に動作することを確認 | H94: ー | I94: ー | J94: ー | K94: ー | L94: ー | M94: ー | N94: ー | O94: ー | P94: ー | U94: Win10対応(PS)で実施
C95: ポイント修正 | D95: ポイント修正 | E95: =ROW()-3 -> 92 | G95: ポイント修正を実施して正常にポイントの加算・減算ができること。 | H95: ー | I95: ー | J95: ー | K95: ー | L95: ー | M95: ー | N95: ー | O95: ー | P95: ー | U95: 通番バーコードがスキャナで読めないため実施不可
E96: =ROW()-3 -> 93 | G96: ポイント修正で顧客登録後に中止できること。 | H96: □ | I96: ー | J96: ー | K96: □ | L96: □ | M96: □ | N96: ー | O96: ー | P96: ー
E97: =ROW()-3 -> 94 | G97: ポイント修正でingfanクラブカードをスキャンした時、 決済端末に対しカード読み込みのキャンセルを依頼した後に、 スキャナのデバイス停止を行い連続スキャンが抑止されていること。 また、キャンセル結果の応答を受信後、スキャナのデバイスが再開されること。 | H97: ー | I97: ー | J97: ー | K97: ー | L97: ー | M97: ー | N97: ー | O97: ー | P97: ー | U97: 通番バーコードがスキャナで読めないため実施不可
E98: =ROW()-3 -> 95 | G98: ポイント修正でingfanクラブカードをスキャンした時、 決済端末に対しカード読み込みのキャンセルを依頼した後に、 登録キーが入力された場合無効音を鳴動し、入力無効となること。 | H98: ー | I98: ー | J98: ー | K98: ー | L98: ー | M98: ー | N98: ー | O98: ー | P98: ー | U98: 通番バーコードがスキャナで読めないため実施不可
C99: 全回収 | D99: 正常動作確認 | E99: =ROW()-3 -> 96 | G99: 正しく動作することを確認 | H99: □ | I99: ー | J99: ー | K99: ー | L99: ー | M99: ー | N99: ー | O99: ー | P99: ー
C100: 紙幣途中回収（移動） | D100: 正常動作確認 | E100: =ROW()-3 -> 97 | G100: 正しく動作することを確認 | H100: □ | I100: ー | J100: ー | K100: ー | L100: ー | M100: ー | N100: ー | O100: ー | P100: ー | U100: RT-500の場合、BOXがでてくるので鍵で開けてとる
...

Sheet サーバ系
B1: いなげや様 サーバ リグレッションテスト仕様書 | X1: 更新日：
B2: NO | C2: 大分類 | D2: 中分類 | E2: 小分類 | F2: テスト項目 | G2: 確認項目 | U2: 確認日 | V2: 担当者 | W2: 結果 | X2: 備考
G3: 画面 | H3: ｶｽﾀﾏ ﾃﾞｨｽ ﾌﾟﾚｲ | I3: 多項目 ｵﾍﾟﾚｰﾀ | J3: 多項目 ｶｽﾀﾏ | K3: ﾚｼｰﾄ | L3: ｼﾞｬｰﾅﾙ | M3: ﾄﾞﾛｱ | N3: ﾚﾎﾟｰﾄ | O3: KB操作 | P3: ﾌｧﾝｸｼｮﾝ 操作 | Q3: 集計 | R3: ﾌｧｲﾙ ﾚｲｱｳﾄ | S3: 帳票 | T3: ﾛｸﾞ
B4: =ROW()-3 -> 1 | C4: 適用確認 | D4: リモメン | E4: PTFLOG | F4: PTFLOGを開き、エラーが出力されていないこと | T4: ○ | X4: エラーという文言がでているとは限らない。 リモメン適用した個所だけ確認しおかしい文言がないか確認する。
B5: =ROW()-3 -> 2 | C5: 適用確認 | D5: リモメン | E5: PTFLOG2 | F5: PTFLOG2を開き、エラーが出力されていないこと | T5: ○ | X5: エラーという文言がでているとは限らない。 リモメン適用した個所だけ確認しおかしい文言がないか確認する。
B6: =ROW()-3 -> 3 | C6: 適用確認 | D6: 外付け適用 | E6: CTKYLOG | F6: CTKYLOGを開き、エラーが出力されていないこと | T6: ○ | X6: エラーという文言がでているとは限らない。 外付け適用した個所だけ確認しおかしい文言がないか確認する。
B7: =ROW()-3 -> 4 | C7: 適用確認 | D7: 外付け適用 | E7: CTKYLOG2 | F7: CTKYLOG2を開き、エラーが出力されていないこと | T7: ○ | X7: エラーという文言がでているとは限らない。 外付け適用した個所だけ確認しおかしい文言がないか確認する。
B8: =ROW()-3 -> 5 | C8: 適用確認 | D8: PTF戻し | E8: Restore | F8: PTF戻しを行えること
B9: =ROW()-3 -> 6 | C9: 開店 | D9: 開局処理 | F9: 開局処理が正常に行われること | G9: ○
B10: =ROW()-3 -> 7 | C10: 閉店 | D10: 閉局処理 | F10: 閉局処理が正常に行われること | G10: ○
B11: =ROW()-3 -> 8 | C11: 運用 | D11: 店舗状態管理 | E11: POS稼動状況確認 | F11: POSの現在の稼動状況が正しく表示されていること（稼働中／精算済等） | G11: ○
B12: =ROW()-3 -> 9 | C12: 店舗 | D12: 設定・照会 | E12: 担当者マスタ設定 | F12: 担当者の新規登録ができ、POSに反映すること | G12: ○ | X12: 店舗⇒設定・照会⇒担当者マスタ設定 ⇒従業員コードポップアップをキャンセル ⇒追加⇒担当者情報を入力※従業員コードは適当（番号を入力）
B13: =ROW()-3 -> 10 | C13: 店舗 | D13: 各種リスト出力 | E13: 担当者マスタ出力 | F13: 画面が正しく表示されること （プリンタがある環境の場合、正しく印刷できることを確認する） | G13: □ | S13: □ | X13: 担当者マスタ設定が出力されればOK
B14: =ROW()-3 -> 11 | C14: 店舗 | D14: 売変 | E14: 山積・企画設定 特売単品 | F14: 特売の設定ができ、POSに反映すること | G14: ○ | X14: 企画を適当に登録。 特売単品で商品を登録。
B15: =ROW()-3 -> 12 | C15: 店舗 | D15: 売変 | E15: 山積・企画設定 組合せグループ | F15: バンドル設定ができ、POSに反映すること | G15: □ | X15: 同一商品複数個で値引
B16: =ROW()-3 -> 13 | C16: 店舗 | D16: 売変 | E16: 山積・企画設定 組合せグループ | F16: ミックス販売設定ができ、POSに反映すること | G16: □ | X16: 不同商品複数個で値引
B17: =ROW()-3 -> 14 | C17: 店舗 | D17: 売変 | E17: 自動値引設定 | F17: 部門階層自動値引の設定ができ、POSに反映すること | G17: ○ | X17: 自動値引きする商品を選ぶ⇒店舗⇒売変⇒自動値引き設定 分類No. 開始日 終了日 大分類 中分類 値引き情報⇒更新
B18: =ROW()-3 -> 15 | C18: 店舗 | D18: 売変 | E18: 青果・単品グループ設定 | F18: 単品グループを新規登録でき、単品グループ単品の登録ができること | G18: ○ | X18: 野菜等、グループ設定し帳票出力に使っていた。 単品グループへの登録後は、「システム管理」→「設定・照会」→「商品管理」→「設定情報出力」→「単品グループ」→「印刷」
B19: =ROW()-3 -> 16 | C19: 店舗 | D19: 設定・照会 | E19: 電子多項目設定 | F19: 電子多項目の設定ができ、POSに反映すること | G19: ○ | X19: スキャンコードを先に入力しないと画像割り付けができない 何回か取引すると割り付けられる
B20: =ROW()-3 -> 17 | C20: 店舗 | D20: 設定・照会 | E20: 営業中メンテナンス | F20: 但し書の設定変更ができ、POSに反映すること （ｺﾏｰｼｬﾙﾒｯｾｰｼﾞについては、POS系テスト項目で確認） | G20: ○
B21: =ROW()-3 -> 18 | C21: 店舗 | D21: 設定・照会 | E21: お知らせメッセージメンテナンス | F21: お知らせメッセージの設定変更ができ、POSに反映すること | G21: ○
B22: =ROW()-3 -> 19 | C22: 店舗 | D22: 設定・照会 | E22: 電子ジャーナル照会 | F22: 画面が表示されること／設定操作が可能であること | G22: ○
B23: =ROW()-3 -> 20 | C23: 店舗 | D23: 設定・照会 | E23: 電子ジャーナル照会 (F3)詳細 | F23: 詳細検索条件を入力して、検索ができること | G23: ○
B24: =ROW()-3 -> 21 | C24: 店舗 | D24: 設定・照会 | E24: 電子ジャーナル照会 (F11)ﾃｷｽﾄ | F24: テキスト出力ができること | G24: ○
B25: =ROW()-3 -> 22 | C25: 店舗 | D25: 売上速報 | E25: 部門実績フラッシュ(速報) | F25: 売上登録した内容が正しく集計されていること | N25: △
B26: =ROW()-3 -> 23 | C26: 店舗 | D26: データ活用 | E26: 商品階層別 商品階層別速報 | F26: 売上登録した内容が正しく集計されていること | N26: △
B27: =ROW()-3 -> 24 | C27: 店舗 | D27: データ活用 | E27: 担当者別 担当者別速報 | F27: 売上登録した内容が正しく集計されていること | N27: △
B28: =ROW()-3 -> 25 | C28: 店舗 | D28: データ活用 | E28: 取引別 取引別速報 | F28: 売上登録した内容が正しく集計されていること | N28: △
B29: =ROW()-3 -> 26 | C29: 店舗 | D29: データ活用 | E29: 単品別 単品別速報 | F29: 売上登録した内容が正しく集計されていること | N29: △
B30: =ROW()-3 -> 27 | C30: 店舗 | D30: データ活用 | E30: 商品階層別 商品階層別時間帯別速報 | F30: 売上登録した内容が正しく集計されていること | N30: △
B31: =ROW()-3 -> 28 | C31: 店舗 | D31: データ活用 | E31: 商品階層別 商品階層別日報 | F31: 前日売上登録した内容が正しく集計されていること | N31: △
B32: =ROW()-3 -> 29 | C32: 店舗 | D32: データ活用 | E32: 担当者別 担当者別日報 | F32: 前日売上登録した内容が正しく集計されていること | N32: △
B33: =ROW()-3 -> 30 | C33: 店舗 | D33: データ活用 | E33: 取引別 取引別日報 | F33: 前日売上登録した内容が正しく集計されていること | N33: △
B34: =ROW()-3 -> 31 | C34: 店舗 | D34: データ活用 | E34: 単品別 単品別日報 | F34: 前日売上登録した内容が正しく集計されていること | N34: △ | X34: 単品別日別レポートなし 単品別日別日報ならあったので それで前日売上登録を確認した
B35: =ROW()-3 -> 32 | C35: 店舗 | D35: データ活用 | E35: 商品階層別 商品階層別時間帯別日報 | F35: 前日売上登録した内容が正しく集計されていること | N35: △
B36: =ROW()-3 -> 33 | C36: 店舗 | D36: データ活用 | E36: 商品階層別 商品階層別月報 | F36: 売上登録した内容が正しく集計されていること | N36: △
B37: =ROW()-3 -> 34 | C37: 店舗 | D37: データ活用 | E37: 商品階層別 商品階層別日別月報 | F37: 売上登録した内容が正しく集計されていること | N37: △
B38: =ROW()-3 -> 35 | C38: 店舗 | D38: データ活用 | E38: 単品別 単品別月報 | F38: 売上登録した内容が正しく集計されていること | N38: △
B39: =ROW()-3 -> 36 | C39: 店舗 | D39: 釣銭機レポート | E39: 釣銭機在高レポート | F39: 釣銭機在高内容が表示されること | N39: △ | S39: △ | X39: 店舗⇒釣銭機レポート
B40: =ROW()-3 -> 37 | C40: 店舗 | D40: 釣銭機レポート | E40: 釣銭機在高レポート | F40: 「あふれ」列が存在すること（最右列） | N40: △ | S40: △ | X40: 店舗⇒釣銭機レポート
B41: =ROW()-3 -> 38 | C41: システム管理 | D41: データ活用 | E41: 速報（当日分） POS別速報 | F41: 売上登録した内容が正しく集計されていること | N41: △
B42: =ROW()-3 -> 39 | C42: システム管理 | D42: データ活用 | E42: 時間帯別速報（当日分） 単品別時間帯別速報 | F42: 単品グループ設定した単品を売上登録し、正しく集計されていること | N42: △
B43: =ROW()-3 -> 40 | C43: システム管理 | D43: データ活用 | E43: 時間帯別速報（当日分） POS別時間帯別速報 | F43: 売上登録した内容が正しく集計されていること | N43: △
B44: =ROW()-3 -> 41 | C44: システム管理 | D44: データ活用 | E44: 時間帯別速報（当日分） 担当者別時間帯別速報 | F44: 売上登録した内容が正しく集計されていること | N44: △
B45: =ROW()-3 -> 42 | C45: システム管理 | D45: データ活用 | E45: 日報（前日営業日） 担当者別管理表 | N45: △
B46: =ROW()-3 -> 43 | C46: システム管理 | D46: データ活用 | E46: 日報（前日営業日） POS別日報 | F46: 売上登録した内容が正しく集計されていること | N46: △
B47: =ROW()-3 -> 44 | C47: システム管理 | D47: データ活用 | E47: 日報（前日営業日） 企画単品別日報 | F47: 売上登録した内容が正しく集計されていること | N47: △
B48: =ROW()-3 -> 45 | C48: システム管理 | D48: データ活用 | E48: 時間帯別日報（前日営業日） 担当者別時間帯別日報 | F48: 前日売上登録した内容が正しく集計されていること | N48: △
B49: =ROW()-3 -> 46 | C49: システム管理 | D49: データ活用 | E49: 時間帯別日報（前日営業日） POS別時間帯別日報 | F49: 前日売上登録した内容が正しく集計されていること | N49: △
B50: =ROW()-3 -> 47 | C50: システム管理 | D50: データ活用 | E50: 時間帯別日報（前日営業日） 単品別時間帯別日報 | F50: 前日売上登録した内容が正しく集計されていること | N50: △
B51: =ROW()-3 -> 48 | C51: システム管理 | D51: データ活用 | E51: 月報 担当者別月報 | F51: 売上登録した内容が正しく集計されていること | N51: △
B52: =ROW()-3 -> 49 | C52: システム管理 | D52: データ活用 | E52: 月報 取引別月報 | F52: 売上登録した内容が正しく集計されていること | N52: △
B53: =ROW()-3 -> 50 | C53: システム管理 | D53: データ活用 | E53: 月報 取引別日別月報 | F53: 売上登録した内容が正しく集計されていること | N53: △
B54: =ROW()-3 -> 51 | C54: システム管理 | D54: データ活用 | E54: 月報 POS別月報 | F54: 売上登録した内容が正しく集計されていること | N54: △
B55: =ROW()-3 -> 52 | C55: システム管理 | D55: 設定・照会 | E55: カレンダ情報マスタ設定 | F55: 定休日の設定ができること | G55: □ | X55: システム管理⇒設定・照会⇒店舗管理（設定）
B56: =ROW()-3 -> 53 | C56: システム管理 | D56: 設定・照会 | E56: 商品管理 単品設定 | F56: 新規で単品の登録ができ、POSに反映すること | G56: ○ | X56: 02XXXXXX0000Z（Zはチェックデジット）で適当に商品を登録 バーコードを作成し（0000は価格を入れる）POSで読み取り。
B57: =ROW()-3 -> 54 | C57: システム管理 | D57: 設定・照会 | E57: 商品管理 単品設定 マークダウン | F57: マークダウンの設定操作が可能であり、POSに反映すること | G57: ○ | X57: 在庫数を調節してPOSへ反映させる。 最初の値入れで決定した売価を値引きすること。
B58: =ROW()-3 -> 55 | C58: システム管理 | D58: システム設定 | E58: キーレイアウト設定 | F58: 割り付ける機能キーの変更ができること | G58: △
B59: =ROW()-3 -> 56 | C59: システム管理 | D59: システム設定 | E59: キーレイアウト設定 | F59: プリセット／値引項目の設定変更ができること | G59: △
B60: =ROW()-3 -> 57 | C60: システム管理 | D60: システム設定 | E60: システム設定検索 | F60: 任意のキーワードで、システム設定の検索ができること | G60: △
B61: =ROW()-3 -> 58 | C61: システム管理 | D61: システム設定 | E61: システム設定検索 | F61: 設定変更でき、POSに送信できること。 POSを再起動し、設定が反映すること。 | G61: △
B62: =ROW()-3 -> 59 | C62: システム管理 | D62: 保守 | E62: 閉店保守 強制精算 | F62: 一覧に接続しているPOSの状況（稼働中やオンライン等）が、 正しく表示されること | G62: □
B63: =ROW()-3 -> 60 | C63: ログ確認 | D63: イベントログ | E63: イベントログ | F63: イベントログ（アプリケーション、セキュリティ、システム）に エラーが出力されていないこと | T63: ○ | X63: Windowsログ TSM最小化し、イベントビューアを開く ESL関連のイベントは除く エラー内容確認
B64: =ROW()-3 -> 61 | C64: ログ確認 | D64: Runlog | E64: Runlog | F64: Runlogにエラーが出力されていないこと | T64: ○ | X64: 出力先：C:\GSTR\RAFT\log エラー内容確認
B65: =ROW()-3 -> 62 | C65: ログ確認 | D65: ESL | E65: ESLログ | F65: 商品階層自動値引実行中商品にて、 ESL連携ファイル出力コードが"000005"となっていること | R65: ○ | T65: ○ | X65: 出力先：C:\ESL\1\DATA\xxx000yyyymmddhhmmssESLDATA.txt
B66: =ROW()-3 -> 63 | C66: ログ確認 | D66: ESL | E66: ESLログ | F66: バンドル実行中商品にて、 ESL連携ファイルにバンドル情報が出力されること。 末尾（バンドル金額（税抜き（8桁）・税込み(8桁)） /成立個数(5桁)/特売終了日(8桁)） | R66: ○ | T66: ○ | X66: 出力先：C:\ESL\1\DATA\xxx000yyyymmddhhmmssESLDATA.txt
B67: =ROW()-3 -> 64 | C67: ログ確認 | D67: ESL | E67: ESLログ | F67: 売り切り商品のESL連携ファイルを確認すること ⇒催しコード：005xxxxxx、データ種別：000004 | X67: 出力先：C:\ESL\1\DATA\xxx000yyyymmddhhmmssESLDATA.txt
B68: =ROW()-3 -> 65 | C68: ログ確認 | D68: ESL | E68: ESLログ | F68: ドキップライスが設定された商品のESL連携ファイルを確認すること ⇒催しコード：106xxxxxx、データ種別：000006 | X68: 出力先：C:\ESL\1\DATA\xxx000yyyymmddhhmmssESLDATA.txt
B69: =ROW()-3 -> 66 | C69: 開店 | D69: 翌日の開店処理 | F69: 開局処理が正常に行われること | G69: ○ | X69: 出力先：C:\GSHI\n\DB システム管理⇒会閉店状況⇒開閉店状況照会 エラー項目を記載する。テストしているためエラーがでる。
B70: フル版 確認件数（○＋△＋□） | F70: =SUM(G70:T70) -> 68 | G70: =COUNTIF(G4:G69,"○")+COUNTIF(G4:G69,"△")+COUNTIF(G4:G69,"□")+COUNTIF(G4:G69,"●")+COUNTIF(G4:G69,"▲")+COUNTIF(G4:G69,"■") -> 25 | H70: =COUNTIF(H4:H69,"○")+COUNTIF(H4:H69,"△")+COUNTIF(H4:H69,"□")+COUNTIF(H4:H69,"●")+COUNTIF(H4:H69,"▲")+COUNTIF(H4:H69,"■") -> 0 | I70: =COUNTIF(I4:I69,"○")+COUNTIF(I4:I69,"△")+COUNTIF(I4:I69,"□")+COUNTIF(I4:I69,"●")+COUNTIF(I4:I69,"▲")+COUNTIF(I4:I69,"■") -> 0 | J70: =COUNTIF(J4:J69,"○")+COUNTIF(J4:J69,"△")+COUNTIF(J4:J69,"□")+COUNTIF(J4:J69,"●")+COUNTIF(J4:J69,"▲")+COUNTIF(J4:J69,"■") -> 0 | K70: =COUNTIF(K4:K69,"○")+COUNTIF(K4:K69,"△")+COUNTIF(K4:K69,"□")+COUNTIF(K4:K69,"●")+COUNTIF(K4:K69,"▲")+COUNTIF(K4:K69,"■") -> 0 | L70: =COUNTIF(L4:L69,"○")+COUNTIF(L4:L69,"△")+COUNTIF(L4:L69,"□")+COUNTIF(L4:L69,"●")+COUNTIF(L4:L69,"▲")+COUNTIF(L4:L69,"■") -> 0 | M70: =COUNTIF(M4:M69,"○")+COUNTIF(M4:M69,"△")+COUNTIF(M4:M69,"□")+COUNTIF(M4:M69,"●")+COUNTIF(M4:M69,"▲")+COUNTIF(M4:M69,"■") -> 0 | N70: =COUNTIF(N4:N69,"○")+COUNTIF(N4:N69,"△")+COUNTIF(N4:N69,"□")+COUNTIF(N4:N69,"●")+COUNTIF(N4:N69,"▲")+COUNTIF(N4:N69,"■") -> 30 | ... T70: =COUNTIF(T4:T69,"○")+COUNTIF(T4:T69,"△")+COUNTIF(T4:T69,"□")+COUNTIF(T4:T69,"●")+COUNTIF(T4:T69,"▲")+COUNTIF(T4:T69,"■") -> 8 | U70: 結果 件数 | V70: 〇 | W70: =COUNTIF(W4:W69,"○") -> 0
B71: 超簡易版 確認件数（○＋△） | F71: =SUM(G71:T71)&"件" -> 62件 | G71: =COUNTIF(G4:G69,"○")+COUNTIF(G4:G69,"△")+COUNTIF(G4:G69,"●")+COUNTIF(G4:G69,"▲") -> 20 | H71: =COUNTIF(H4:H69,"○")+COUNTIF(H4:H69,"△")+COUNTIF(H4:H69,"●")+COUNTIF(H4:H69,"▲") -> 0 | I71: =COUNTIF(I4:I69,"○")+COUNTIF(I4:I69,"△")+COUNTIF(I4:I69,"●")+COUNTIF(I4:I69,"▲") -> 0 | J71: =COUNTIF(J4:J69,"○")+COUNTIF(J4:J69,"△")+COUNTIF(J4:J69,"●")+COUNTIF(J4:J69,"▲") -> 0 | K71: =COUNTIF(K4:K69,"○")+COUNTIF(K4:K69,"△")+COUNTIF(K4:K69,"●")+COUNTIF(K4:K69,"▲") -> 0 | L71: =COUNTIF(L4:L69,"○")+COUNTIF(L4:L69,"△")+COUNTIF(L4:L69,"●")+COUNTIF(L4:L69,"▲") -> 0 | M71: =COUNTIF(M4:M69,"○")+COUNTIF(M4:M69,"△")+COUNTIF(M4:M69,"●")+COUNTIF(M4:M69,"▲") -> 0 | N71: =COUNTIF(N4:N69,"○")+COUNTIF(N4:N69,"△")+COUNTIF(N4:N69,"●")+COUNTIF(N4:N69,"▲") -> 30 | ... T71: =COUNTIF(T4:T69,"○")+COUNTIF(T4:T69,"△")+COUNTIF(T4:T69,"●")+COUNTIF(T4:T69,"▲") -> 8
B72: 超超簡易版 確認件数（○） | F72: =SUM(G72:T72)&"件" -> 26件 | G72: =COUNTIF(G4:G69,"○")+COUNTIF(G4:G69,"●") -> 16 | H72: =COUNTIF(H4:H69,"○")+COUNTIF(H4:H69,"●") -> 0 | I72: =COUNTIF(I4:I69,"○")+COUNTIF(I4:I69,"●") -> 0 | J72: =COUNTIF(J4:J69,"○")+COUNTIF(J4:J69,"●") -> 0 | K72: =COUNTIF(K4:K69,"○")+COUNTIF(K4:K69,"●") -> 0 | L72: =COUNTIF(L4:L69,"○")+COUNTIF(L4:L69,"●") -> 0 | M72: =COUNTIF(M4:M69,"○")+COUNTIF(M4:M69,"●") -> 0 | N72: =COUNTIF(N4:N69,"○")+COUNTIF(N4:N69,"●") -> 0 | ... T72: =COUNTIF(T4:T69,"○")+COUNTIF(T4:T69,"●") -> 8 | V72: × | W72: =COUNTIF(W4:W69,"×") -> 0
B73: 消化件数（○＋△＋□） | F73: =SUM(G73:T73)&"件" -> 0件 | G73: =COUNTIF(G4:G69,"●")+COUNTIF(G4:G69,"▲")+COUNTIF(G4:G69,"■") -> 0 | H73: =COUNTIF(H4:H69,"●")+COUNTIF(H4:H69,"▲")+COUNTIF(H4:H69,"■") -> 0 | I73: =COUNTIF(I4:I69,"●")+COUNTIF(I4:I69,"▲")+COUNTIF(I4:I69,"■") -> 0 | J73: =COUNTIF(J4:J69,"●")+COUNTIF(J4:J69,"▲")+COUNTIF(J4:J69,"■") -> 0 | K73: =COUNTIF(K4:K69,"●")+COUNTIF(K4:K69,"▲")+COUNTIF(K4:K69,"■") -> 0 | L73: =COUNTIF(L4:L69,"●")+COUNTIF(L4:L69,"▲")+COUNTIF(L4:L69,"■") -> 0 | M73: =COUNTIF(M4:M69,"●")+COUNTIF(M4:M69,"▲")+COUNTIF(M4:M69,"■") -> 0 | N73: =COUNTIF(N4:N69,"●")+COUNTIF(N4:N69,"▲")+COUNTIF(N4:N69,"■") -> 0 | ... T73: =COUNTIF(T4:T69,"●")+COUNTIF(T4:T69,"▲")+COUNTIF(T4:T69,"■") -> 0
D76: =SUM($F$70+Win10対応_サーバ!$D$25) -> 100

Sheet Win10対応_POS
B1: いなげや様 Win10対応（POS/SS/PS/CS） リグレッションテスト仕様書
B2: 大分類 | C2: 中分類 | D2: 小分類 | E2: テスト項目 | H2: POS | Q2: チェック日付 | T2: 担当 | U2: 備考
E3: No | F3: POS操作 | G3: 結果 | H3: 動作 | I3: DB | J3: ｶｽﾀﾏ | K3: 画面 | L3: ﾚｼｰﾄ | M3: ｼﾞｬｰﾅﾙ | N3: 音声 | O3: ﾛｸﾞ | P3: 小型 LCD | Q3: OK | R3: NG | S3: 修正 OK
B4: 決済端末 | C4: 開局 | E4: =ROW()-3 -> 1 | F4: 開局処理 | G4: 正常に開局されること。決済端末が待機画面になること。 | H4: ー | I4: ー | J4: ー | K4: ー | L4: ー | M4: ー | N4: ー | O4: ー | P4: ー | U4: パッケージ系にて実施
B5: （通常操作） | C5: 会員番号登録 | D5: Vカード | E5: =ROW()-3 -> 2 | F5: Vカードで会員登録 | G5: 正常に会員登録できること | H5: □ | I5: ー | J5: ー | K5: ー | L5: □ | M5: □ | N5: ー | O5: ー | P5: ー
C6: 支払い操作 | D6: 会員宣言：なし Vカード支払い（IC） | E6: =ROW()-3 -> 3 | F6: VカードをICで読み込み | G6: 正常に支払いが完了し売上登録できること | H6: □ | I6: ー | J6: ー | K6: ー | L6: □ | M6: □ | N6: ー | O6: ー | P6: ー | U6: 売上登録できないこと
D7: 会員宣言：なし 他クレ支払い（IC） | E7: =ROW()-3 -> 4 | F7: 他クレカードをICで読み込み | G7: 正常に支払いが完了し売上登録できること | H7: □ | I7: ー | J7: ー | K7: ー | L7: □ | M7: □ | N7: ー | O7: ー | P7: ー
D8: 会員宣言：なし 他クレ支払い（MSR） | E8: =ROW()-3 -> 5 | F8: 他クレカードをMSRで読み込み | G8: 正常に支払いが完了し売上登録できること | H8: □ | I8: ー | J8: ー | K8: ー | L8: □ | M8: □ | N8: ー | O8: ー | P8: ー
D9: 会員宣言：ingカード（ﾀｯﾁｽｷｬﾅ） Vカード支払い（IC） | E9: =ROW()-3 -> 6 | F9: VカードをICで読み込み | G9: 正常に支払いが完了し売上登録できること | H9: □ | I9: ー | J9: ー | K9: ー | L9: □ | M9: □ | N9: ー | O9: ー | P9: ー
D10: 会員宣言：ingカード（手入力） 他クレ支払い（IC） | E10: =ROW()-3 -> 7 | F10: 他クレカードをICで読み込み | G10: 正常に支払いが完了し売上登録できること | H10: □ | I10: ー | J10: ー | K10: ー | L10: □ | M10: □ | N10: ー | O10: ー | P10: ー
D11: 会員宣言：ingカード（ﾀｯﾁｽｷｬﾅ） 他クレ支払い（MSR） | E11: =ROW()-3 -> 8 | F11: 他クレカードをMSRで読み込み | G11: 正常に支払いが完了し売上登録できること | H11: □ | I11: ー | J11: ー | K11: ー | L11: □ | M11: □ | N11: ー | O11: ー | P11: ー
D12: 会員宣言：Vカード Vカード支払い（IC） | E12: =ROW()-3 -> 9 | F12: VカードをICで読み込み | G12: 正常に支払いが完了し売上登録できること | H12: □ | I12: ー | J12: ー | K12: ー | L12: □ | M12: □ | N12: ー | O12: ー | P12: ー
D13: 会員宣言：Vカード 他クレ支払い（IC） | E13: =ROW()-3 -> 10 | F13: 他クレカードをICで読み込み | G13: 正常に支払いが完了し売上登録できること | H13: □ | I13: ー | J13: ー | K13: ー | L13: □ | M13: □ | N13: ー | O13: ー | P13: ー
D14: 会員宣言：Vカード 他クレ支払い（MSR） | E14: =ROW()-3 -> 11 | F14: 他クレカードをMSRで読み込み | G14: 正常に支払いが完了し売上登録できること | H14: □ | I14: ー | J14: ー | K14: ー | L14: □ | M14: □ | N14: ー | O14: ー | P14: ー
C15: 通番取消 | D15: 元取引：会員宣言なし Vカード支払い | E15: =ROW()-3 -> 12 | F15: 元取引と同じVカードをICで読み込み | G15: 正常に取消処理が完了すること | H15: ー | I15: ー | J15: ー | K15: ー | L15: ー | M15: ー | N15: ー | O15: ー | P15: ー | U15: 売上登録不可
D16: 元取引：ingカードで会員宣言 Vカード支払い | E16: =ROW()-3 -> 13 | F16: 元取引と同じVカードをMSRで読み込み | G16: 正常に取消処理が完了すること | H16: □ | I16: ー | J16: ー | K16: ー | L16: □ | M16: □ | N16: ー | O16: ー | P16: ー
D17: 元取引：Vカードで会員宣言 Vカード支払い | E17: =ROW()-3 -> 14 | F17: 元取引と同じVカードをICで読み込み | G17: 正常に取消処理が完了すること | H17: □ | I17: ー | J17: ー | K17: ー | L17: □ | M17: □ | N17: ー | O17: ー | P17: ー
D18: 元取引：会員宣言なし 他クレ支払い | E18: =ROW()-3 -> 15 | F18: 元取引と同じ他クレカードをMSRで読み込み | G18: 正常に取消処理が完了すること | H18: □ | I18: ー | J18: ー | K18: ー | L18: □ | M18: □ | N18: ー | O18: ー | P18: ー
D19: 元取引がingカードで会員宣言 他クレ支払い | E19: =ROW()-3 -> 16 | F19: 元取引と同じ他クレカードをICで読み込み | G19: 正常に取消処理が完了すること | H19: □ | I19: ー | J19: ー | K19: ー | L19: □ | M19: □ | N19: ー | O19: ー | P19: ー
D20: 元取引がVカードで会員宣言 他クレ支払い | E20: =ROW()-3 -> 17 | F20: 元取引と同じ他クレカードをMSRで読み込み | G20: 正常に取消処理が完了すること | H20: □ | I20: ー | J20: ー | K20: ー | L20: □ | M20: □ | N20: ー | O20: ー | P20: ー
C21: 通番修正 | D21: 元取引がVカード支払い | E21: =ROW()-3 -> 18 | F21: 元取引と同じVカードで通番取消、同じVカードで支払い | G21: 元取引の取消処理と修正後の取引が正常に完了すること | H21: □ | I21: ー | J21: ー | K21: ー | L21: □ | M21: □ | N21: ー | O21: ー | P21: ー
E22: =ROW()-3 -> 19 | F22: 元取引と同じVカードで通番取消、他クレカードで支払い | G22: 元取引の取消処理と修正後の取引が正常に完了すること | H22: □ | I22: ー | J22: ー | K22: ー | L22: □ | M22: □ | N22: ー | O22: ー | P22: ー
E23: =ROW()-3 -> 20 | F23: 元取引と同じVカードで通番取消、現金で支払い | G23: 元取引の取消処理と修正後の取引が正常に完了すること | H23: □ | I23: ー | J23: ー | K23: ー | L23: □ | M23: □ | N23: ー | O23: ー | P23: ー
D24: 元取引が他クレ支払い | E24: =ROW()-3 -> 21 | F24: 元取引と同じ他クレで通番取消、同じカードで支払い | G24: 元取引の取消処理と修正後の取引が正常に完了すること | H24: □ | I24: ー | J24: ー | K24: ー | L24: □ | M24: □ | N24: ー | O24: ー | P24: ー
E25: =ROW()-3 -> 22 | F25: 元取引と同じ他クレで通番取消、Vカードで支払い | G25: 元取引の取消処理と修正後の取引が正常に完了すること | H25: □ | I25: ー | J25: ー | K25: ー | L25: □ | M25: □ | N25: ー | O25: ー | P25: ー | U25: 会員宣言必要
E26: =ROW()-3 -> 23 | F26: 元取引と同じ他クレで通番取消、現金で支払い | G26: 元取引の取消処理と修正後の取引が正常に完了すること | H26: □ | I26: ー | J26: ー | K26: ー | L26: □ | M26: □ | N26: ー | O26: ー | P26: ー
B27: 練習モード | C27: 会員番号登録 | D27: Vカード | E27: =ROW()-3 -> 24 | F27: Vカードで会員登録 | G27: 正常に会員登録できること | H27: □ | I27: ー | J27: ー | K27: ー | L27: □ | M27: □ | N27: ー | O27: ー | P27: ー
C28: 支払い操作 | D28: 会員宣言：なし Vカード支払い（IC） | E28: =ROW()-3 -> 25 | F28: VカードをICで読み込み | G28: 練習：正常に支払いが完了し売上登録できること | H28: ー | I28: ー | J28: ー | K28: ー | L28: ー | M28: ー | N28: ー | O28: ー | P28: ー | U28: 会員宣言なしVカード支払不可
D29: 会員宣言：なし 他クレ支払い（IC） | E29: =ROW()-3 -> 26 | F29: 他クレカードをICで読み込み | G29: 練習：正常に支払いが完了し売上登録できること | H29: □ | I29: ー | J29: ー | K29: ー | L29: □ | M29: □ | N29: ー | O29: ー | P29: ー
D30: 会員宣言：なし 他クレ支払い（MSR） | E30: =ROW()-3 -> 27 | F30: 他クレカードをMSRで読み込み | G30: 練習：正常に支払いが完了し売上登録できること | H30: □ | I30: ー | J30: ー | K30: ー | L30: □ | M30: □ | N30: ー | O30: ー | P30: ー
D31: 会員宣言：ingカード（ﾀｯﾁｽｷｬﾅ） Vカード支払い（IC） | E31: =ROW()-3 -> 28 | F31: VカードをICで読み込み | G31: 練習：正常に支払いが完了し売上登録できること | H31: □ | I31: ー | J31: ー | K31: ー | L31: □ | M31: □ | N31: ー | O31: ー | P31: ー
D32: 会員宣言：ingカード（手入力） 他クレ支払い（IC） | E32: =ROW()-3 -> 29 | F32: 他クレカードをICで読み込み | G32: 練習：正常に支払いが完了し売上登録できること | H32: □ | I32: ー | J32: ー | K32: ー | L32: □ | M32: □ | N32: ー | O32: ー | P32: ー
D33: 会員宣言：ingカード（ﾀｯﾁｽｷｬﾅ） 他クレ支払い（MSR） | E33: =ROW()-3 -> 30 | F33: 他クレカードをMSRで読み込み | G33: 練習：正常に支払いが完了し売上登録できること | H33: □ | I33: ー | J33: ー | K33: ー | L33: □ | M33: □ | N33: ー | O33: ー | P33: ー
D34: 会員宣言：Vカード Vカード支払い（IC） | E34: =ROW()-3 -> 31 | F34: VカードをICで読み込み | G34: 練習：正常に支払いが完了し売上登録できること | H34: □ | I34: ー | J34: ー | K34: ー | L34: □ | M34: □ | N34: ー | O34: ー | P34: ー
D35: 会員宣言：Vカード 他クレ支払い（IC） | E35: =ROW()-3 -> 32 | F35: 他クレカードをICで読み込み | G35: 練習：正常に支払いが完了し売上登録できること | H35: □ | I35: ー | J35: ー | K35: ー | L35: □ | M35: □ | N35: ー | O35: ー | P35: ー
D36: 会員宣言：Vカード 他クレ支払い（MSR） | E36: =ROW()-3 -> 33 | F36: 他クレカードをMSRで読み込み | G36: 練習：正常に支払いが完了し売上登録できること | H36: □ | I36: ー | J36: ー | K36: ー | L36: □ | M36: □ | N36: ー | O36: ー | P36: ー
C37: 通番取消 | D37: 元取引：会員宣言なし Vカード支払い | E37: =ROW()-3 -> 34 | F37: 元取引と同じVカードをICで読み込み | G37: 練習：正常に取消処理が完了すること | H37: ー | I37: ー | J37: ー | K37: ー | L37: ー | M37: ー | N37: ー | O37: ー | P37: ー | U37: 会員宣言なしVカード支払不可
D38: 元取引：ingカードで会員宣言 Vカード支払い | E38: =ROW()-3 -> 35 | F38: 元取引と同じVカードをMSRで読み込み | G38: 練習：正常に取消処理が完了すること | H38: □ | I38: ー | J38: ー | K38: ー | L38: □ | M38: □ | N38: ー | O38: ー | P38: ー
D39: 元取引：会員宣言なし 他クレ支払い | E39: =ROW()-3 -> 36 | F39: 元取引と同じ他クレカードをMSRで読み込み | G39: 練習：正常に取消処理が完了すること | H39: □ | I39: ー | J39: ー | K39: ー | L39: □ | M39: □ | N39: ー | O39: ー | P39: ー
D40: 元取引がVカードで会員宣言 他クレ支払い | E40: =ROW()-3 -> 37 | F40: 元取引と同じ他クレカードをMSRで読み込み | G40: 練習：正常に取消処理が完了すること | H40: □ | I40: ー | J40: ー | K40: ー | L40: □ | M40: □ | N40: ー | O40: ー | P40: ー
C41: 通番修正 | D41: 元取引がVカード支払い | E41: =ROW()-3 -> 38 | F41: 元取引と同じVカードで通番取消、同じVカードで支払い | G41: 練習：元取引の取消処理と修正後の取引が正常に完了すること | H41: □ | I41: ー | J41: ー | K41: ー | L41: □ | M41: □ | N41: ー | O41: ー | P41: ー
E42: =ROW()-3 -> 39 | F42: 元取引と同じVカードで通番取消、他クレカードで支払い | G42: 練習：元取引の取消処理と修正後の取引が正常に完了すること | H42: □ | I42: ー | J42: ー | K42: ー | L42: □ | M42: □ | N42: ー | O42: ー | P42: ー | U42: 練習モードは会員宣言するとVカード扱いになる
E43: =ROW()-3 -> 40 | F43: 元取引と同じVカードで通番取消、現金で支払い | G43: 練習：元取引の取消処理と修正後の取引が正常に完了すること | H43: □ | I43: ー | J43: ー | K43: ー | L43: □ | M43: □ | N43: ー | O43: ー | P43: ー
D44: 元取引が他クレ支払い | E44: =ROW()-3 -> 41 | F44: 元取引と同じ他クレで通番取消、同じカードで支払い | G44: 練習：元取引の取消処理と修正後の取引が正常に完了すること | H44: □ | I44: ー | J44: ー | K44: ー | L44: □ | M44: □ | N44: ー | O44: ー | P44: ー
E45: =ROW()-3 -> 42 | F45: 元取引と同じ他クレで通番取消、違うカードで支払い | G45: 練習：元取引の取消処理と修正後の取引が正常に完了すること | H45: □ | I45: ー | J45: ー | K45: ー | L45: □ | M45: □ | N45: ー | O45: ー | P45: ー
E46: =ROW()-3 -> 43 | F46: 元取引と同じ他クレで通番取消、現金で支払い | G46: 練習：元取引の取消処理と修正後の取引が正常に完了すること | H46: □ | I46: ー | J46: ー | K46: ー | L46: □ | M46: □ | N46: ー | O46: ー | P46: ー
B47: Satisfa | C47: 開局 | E47: =ROW()-3 -> 44 | F47: 開局処理 | G47: POS開局時にエラーが発生しないこと | H47: □ | I47: ー | J47: ー | K47: ー | L47: ー | M47: ー | N47: ー | O47: □ | P47: ー
C48: 会員番号登録 | D48: Vカード | E48: =ROW()-3 -> 45 | F48: Vカードで会員登録 | G48: 正常に会員登録できること。現在ポイントが正しく表示されること | H48: □ | I48: ー | J48: ー | K48: ー | L48: □ | M48: □ | N48: ー | O48: □ | P48: ー
D49: ingfanカード | E49: =ROW()-3 -> 46 | F49: ingfan会員バーコードで会員登録 | G49: 正常に会員登録できること。現在ポイントが正しく表示されること | H49: □ | I49: ー | J49: ー | K49: ー | L49: □ | M49: □ | N49: ー | O49: □ | P49: ー
D50: 手入力 | E50: =ROW()-3 -> 47 | F50: 手入力で会員登録 | G50: 正常に会員登録できること。現在ポイントが正しく表示されること | H50: □ | I50: ー | J50: ー | K50: ー | L50: □ | M50: □ | N50: ー | O50: □ | P50: ー
C51: ポイント付与 | D51: Vカード | E51: =ROW()-3 -> 48 | F51: Vカードで会員登録 | G51: 正常に取引が完了すること。今回ポイントが正しく付与されること | H51: □ | I51: ー | J51: ー | K51: ー | L51: □ | M51: □ | N51: ー | O51: □ | P51: ー
D52: ingfanカード | E52: =ROW()-3 -> 49 | F52: ingfan会員バーコードで会員登録 | G52: 正常に取引が完了すること。今回ポイントが正しく付与されること | H52: □ | I52: ー | J52: ー | K52: ー | L52: □ | M52: □ | N52: ー | O52: □ | P52: ー
D53: 手入力 | E53: =ROW()-3 -> 50 | F53: 手入力で会員登録 | G53: 正常に取引が完了すること。今回ポイントが正しく付与されること | H53: □ | I53: ー | J53: ー | K53: ー | L53: □ | M53: □ | N53: ー | O53: □ | P53: ー
C54: ポイント利用 | D54: Vカード | E54: =ROW()-3 -> 51 | F54: Vカードで会員登録 | G54: 正常に取引が完了すること。ポイント利用分が正しく反映されること | H54: □ | I54: ー | J54: ー | K54: ー | L54: □ | M54: □ | N54: ー | O54: □ | P54: ー
D55: ingfanカード | E55: =ROW()-3 -> 52 | F55: ingfan会員バーコードで会員登録 | G55: 正常に取引が完了すること。ポイント利用分が正しく反映されること | H55: □ | I55: ー | J55: ー | K55: ー | L55: □ | M55: □ | N55: ー | O55: □ | P55: ー
D56: 手入力 | E56: =ROW()-3 -> 53 | F56: 手入力で会員登録 | G56: 正常に取引が完了すること。ポイント利用分が正しく反映されること | H56: □ | I56: ー | J56: ー | K56: ー | L56: □ | M56: □ | N56: ー | O56: □ | P56: ー
C57: ポイント修正 | D57: Vカード | E57: =ROW()-3 -> 54 | F57: Vカードで会員登録 | G57: 正常に処理が完了すること。ポイント修正結果が正しく反映されること | H57: □ | I57: ー | J57: ー | K57: ー | L57: □ | M57: □ | N57: ー | O57: □ | P57: ー
D58: ingfanカード | E58: =ROW()-3 -> 55 | F58: ingfan会員バーコードで会員登録 | G58: 正常に処理が完了すること。ポイント修正結果が正しく反映されること | H58: □ | I58: ー | J58: ー | K58: ー | L58: □ | M58: □ | N58: ー | O58: □ | P58: ー
D59: 手入力 | E59: =ROW()-3 -> 56 | F59: 手入力で会員登録 | G59: 正常に処理が完了すること。ポイント修正結果が正しく反映されること | H59: □ | I59: ー | J59: ー | K59: ー | L59: □ | M59: □ | N59: ー | O59: □ | P59: ー
C60: レジマイナス | D60: 会員宣言なし | E60: =ROW()-3 -> 57 | F60: 会員宣言しない | G60: 正常にマイナス処理が完了すること（現在ポイントが減算されること） | H60: ー | I60: ー | J60: ー | K60: ー | L60: ー | M60: ー | N60: ー | O60: ー | P60: ー | U60: 会員宣言無の場合ポイント減産なし
D61: ingカードで会員宣言 | E61: =ROW()-3 -> 58 | F61: ingfan会員バーコードで会員宣言 | G61: 正常にマイナス処理が完了すること（現在ポイントが減算されること） | H61: □ | I61: ー | J61: ー | K61: □ | L61: □ | M61: □ | N61: ー | O61: □ | P61: ー
D62: Vカードで会員宣言 | E62: =ROW()-3 -> 59 | F62: Vカードで会員宣言 | G62: 正常にマイナス処理が完了すること （現在ポイントが200円1ポイントで減算されること） | H62: □ | I62: ー | J62: ー | K62: □ | L62: □ | M62: □ | N62: ー | O62: □ | P62: ー
C63: さんにち割 | D63: 開局 | E63: =ROW()-3 -> 60 | F63: 開局レシートを確認 | G63: 「さんにち割引」が表示されていること 対象日付が表示されていること | H63: ー | I63: ー | J63: ー | K63: ー | L63: ー | M63: ー | N63: ー | O63: ー | P63: ー | U63: パッケージ系にて実施
D64: 小計自動値引 | E64: =ROW()-3 -> 61 | F64: ingfan会員バーコードで会員登録 | G64: 自動小計値引が反映されないこと | H64: □ | I64: ー | J64: ー | K64: □ | L64: □ | M64: □ | N64: ー | O64: □ | P64: ー
E65: =ROW()-3 -> 62 | F65: Vカードで会員登録 | G65: 自動小計値引（5%）が反映されること | H65: □ | I65: ー | J65: ー | K65: □ | L65: □ | M65: □ | N65: ー | O65: □ | P65: ー
B66: 自動釣銭釣札機 | C66: POS連携 | D66: 預り金処理 | E66: =ROW()-3 -> 63 | F66: 預り金を投入 | G66: 正常に処理が完了すること。お釣りが正しく出金されること | H66: □ | I66: ー | J66: ー | K66: ー | L66: □ | M66: □ | N66: ー | O66: ー | P66: ー
B67: （POS / RT-300） | D67: 在高点検レシート（Xモード） | E67: =ROW()-3 -> 64 | F67: 在高点検レシート出力（Xモード） | G67: 正常に処理が完了すること。 | H67: □ | I67: ー | J67: ー | K67: ー | L67: □ | M67: □ | N67: ー | O67: ー | P67: ー | U67: エラーが出てパッケージが落ちる？ ⇒再起動後再度実行では問題なし
D68: 入金 | E68: =ROW()-3 -> 65 | F68: 入金処理（Xモード） | G68: 正常に処理が完了すること。 | H68: ー | I68: ー | J68: ー | K68: ー | L68: ー | M68: ー | N68: ー | O68: ー | P68: ー | U68: パッケージ系にて実施
D69: お客様両替 | E69: =ROW()-3 -> 66 | F69: お客様両替（Xモード） | G69: 正常に処理が完了すること。 | H69: □ | I69: ー | J69: ー | K69: □ | L69: □ | M69: □ | N69: ー | O69: ー | P69: ー
D70: 釣銭機接続・切離し | E70: =ROW()-3 -> 67 | F70: 釣銭機接続・切離し（Xモード） | G70: 正常に処理が完了すること。 | H70: □ | I70: ー | J70: ー | K70: ー | L70: ー | M70: ー | N70: ー | O70: ー | P70: ー
D71: 釣銭機接続・切離し | E71: =ROW()-3 -> 68 | F71: 釣銭機接続・切離し（Xモード：釣銭機メニュー） | G71: 正常に処理が完了すること。 | H71: □ | I71: ー | J71: ー | K71: ー | L71: ー | M71: ー | N71: ー | O71: ー | P71: ー
D72: 計数機能モード切替 | E72: =ROW()-3 -> 69 | F72: 計数機能モード切替（Xモード：釣銭機メニュー） | G72: 正常に処理が完了すること。 | H72: □ | I72: ー | J72: ー | K72: ー | L72: ー | M72: ー | N72: ー | O72: ー | P72: ー
D73: 釣銭在高確認 | E73: =ROW()-3 -> 70 | F73: 釣銭在高確認（Xモード：釣銭機メニュー） | G73: 正常に処理が完了すること。 | H73: □ | I73: ー | J73: ー | K73: ー | L73: ー | M73: ー | N73: ー | O73: ー | P73: ー | U73: 釣銭在高確認⇒釣銭残高確認
D74: 全回収 | E74: =ROW()-3 -> 71 | F74: 全回収（Zモード） | G74: 正常に処理が完了すること。 | H74: ー | I74: ー | J74: ー | K74: ー | L74: ー | M74: ー | N74: ー | O74: ー | P74: ー | U74: パッケージ系にて実施
D75: 紙幣途中回収（移動） | E75: =ROW()-3 -> 72 | F75: 紙幣途中回収（移動）（Zモード） | G75: 正常に処理が完了すること。 | H75: ー | I75: ー | J75: ー | K75: ー | L75: ー | M75: ー | N75: ー | O75: ー | P75: ー | U75: パッケージ系にて実施
D76: 硬貨途中回収 | E76: =ROW()-3 -> 73 | F76: 硬貨途中回収（Zモード） | G76: 正常に処理が完了すること。 | H76: ー | I76: ー | J76: ー | K76: ー | L76: ー | M76: ー | N76: ー | O76: ー | P76: ー | U76: パッケージ系にて実施
D77: ボックス回収 | E77: =ROW()-3 -> 74 | F77: ボックス回収（Zモード） | G77: 正常に処理が完了すること。 | H77: ー | I77: ー | J77: ー | K77: ー | L77: ー | M77: ー | N77: ー | O77: ー | P77: ー | U77: パッケージ系にて実施
D78: 出金 | E78: =ROW()-3 -> 75 | F78: 出金処理（Zモード） | G78: 正常に処理が完了すること。 | H78: ー | I78: ー | J78: ー | K78: ー | L78: ー | M78: ー | N78: ー | O78: ー | P78: ー | U78: パッケージ系にて実施
D79: あふれ金収納庫移動 | E79: =ROW()-3 -> 76 | F79: あふれ金収納庫移動（Zモード） | G79: メニューに無いことを確認する。 | H79: ー | I79: ー | J79: ー | K79: □ | L79: ー | M79: ー | N79: ー | O79: ー | P79: ー
B80: メニュー比較 | C80: Xモード | D80: Win7POSとWin10POSを比較 | E80: =ROW()-3 -> 77 | G80: メニューが正しく表示されること | H80: ー | I80: ー | J80: ー | K80: □ | L80: ー | M80: ー | N80: ー | O80: ー | P80: ー | U80: 決済端末関連の変更点以外一致
C81: Zモード | D81: Win7POSとWin10POSを比較 | E81: =ROW()-3 -> 78 | G81: メニューが正しく表示されること | H81: ー | I81: ー | J81: ー | K81: □ | L81: ー | M81: ー | N81: ー | O81: ー | P81: ー | U81: 「あふれ金収納庫移動」以外一致
B82: 自動釣銭釣札機 | C82: POS連携 | D82: 預り金処理 | E82: =ROW()-3 -> 79 | F82: 預り金を投入 | G82: 正常に処理が完了すること。お釣りが正しく出金されること | H82: ー | I82: ー | J82: ー | K82: ー | L82: ー | M82: ー | N82: ー | O82: ー | P82: ー
B83: （PS / RT-380） | D83: 入金処理（Xモード） | E83: =ROW()-3 -> 80 | F83: 入金処理（Xモード） | G83: 正常に処理が完了すること。 | H83: ー | I83: ー | J83: ー | K83: ー | L83: ー | M83: ー | N83: ー | O83: ー | P83: ー
D84: 在高点検 | E84: =ROW()-3 -> 81 | F84: 在高点検（Xモード） | G84: 正常に処理が完了すること。 | H84: ー | I84: ー | J84: ー | K84: ー | L84: ー | M84: ー | N84: ー | O84: ー | P84: ー
D85: 全回収 | E85: =ROW()-3 -> 82 | F85: 全回収（Zモード） | G85: 正常に処理が完了すること。 | H85: ー | I85: ー | J85: ー | K85: ー | L85: ー | M85: ー | N85: ー | O85: ー | P85: ー
D86: 紙幣途中回収（移動） | E86: =ROW()-3 -> 83 | F86: 紙幣途中回収（移動）（Zモード） | G86: 正常に処理が完了すること。 | H86: ー | I86: ー | J86: ー | K86: ー | L86: ー | M86: ー | N86: ー | O86: ー | P86: ー
D87: 硬貨途中回収 | E87: =ROW()-3 -> 84 | F87: 硬貨途中回収（Zモード） | G87: 正常に処理が完了すること。 | H87: ー | I87: ー | J87: ー | K87: ー | L87: ー | M87: ー | N87: ー | O87: ー | P87: ー
D88: ボックス回収 | E88: =ROW()-3 -> 85 | F88: ボックス回収（Zモード） | G88: 正常に処理が完了すること。 | H88: ー | I88: ー | J88: ー | K88: ー | L88: ー | M88: ー | N88: ー | O88: ー | P88: ー
D89: 出金処理 | E89: =ROW()-3 -> 86 | F89: 出金処理（Zモード） | G89: 正常に処理が完了すること。 | H89: ー | I89: ー | J89: ー | K89: ー | L89: ー | M89: ー | N89: ー | O89: ー | P89: ー
D90: あふれ金収納庫移動 | E90: =ROW()-3 -> 87 | F90: あふれ金収納庫移動（Zモード） | G90: 正常に処理が完了すること。 | H90: ー | I90: ー | J90: ー | K90: ー | L90: ー | M90: ー | N90: ー | O90: ー | P90: ー
H91: ー | I91: ー | J91: ー | K91: ー | L91: ー | M91: ー | N91: ー | O91: ー | P91: ー
B92: 消化ﾃｽﾄ項目数： | D92: =SUM(H94:P94) -> 0 | G92: OK数： | H92: =COUNTIF(H4:H91,"●")+COUNTIF(H4:H91,"■")+COUNTIF(H4:H91,"OK") -> 0 | I92: =COUNTIF(I4:I91,"●")+COUNTIF(I4:I91,"■")+COUNTIF(I4:I91,"OK") -> 0 | J92: =COUNTIF(J4:J91,"●")+COUNTIF(J4:J91,"■")+COUNTIF(J4:J91,"OK") -> 0 | K92: =COUNTIF(K4:K91,"●")+COUNTIF(K4:K91,"■")+COUNTIF(K4:K91,"OK") -> 0 | L92: =COUNTIF(L4:L91,"●")+COUNTIF(L4:L91,"■")+COUNTIF(L4:L91,"OK") -> 0 | M92: =COUNTIF(M4:M91,"●")+COUNTIF(M4:M91,"■")+COUNTIF(M4:M91,"OK") -> 0 | N92: =COUNTIF(N4:N91,"●")+COUNTIF(N4:N91,"■")+COUNTIF(N4:N91,"OK") -> 0 | O92: =COUNTIF(O4:O91,"●")+COUNTIF(O4:O91,"■")+COUNTIF(O4:O91,"OK") -> 0 | P92: =COUNTIF(P4:P91,"●")+COUNTIF(P4:P91,"■")+COUNTIF(P4:P91,"OK") -> 0 | Q92: 合計
G93: NG数： | H93: =COUNTIF(H4:H91,"×")+COUNTIF(H4:H91,"NG") -> 0 | I93: =COUNTIF(I4:I91,"×")+COUNTIF(I4:I91,"NG") -> 0 | J93: =COUNTIF(J4:J91,"×")+COUNTIF(J4:J91,"NG") -> 0 | K93: =COUNTIF(K4:K91,"×")+COUNTIF(K4:K91,"NG") -> 0 | L93: =COUNTIF(L4:L91,"×")+COUNTIF(L4:L91,"NG") -> 0 | M93: =COUNTIF(M4:M91,"×")+COUNTIF(M4:M91,"NG") -> 0 | N93: =COUNTIF(N4:N91,"×")+COUNTIF(N4:N91,"NG") -> 0 | O93: =COUNTIF(O4:O91,"×")+COUNTIF(O4:O91,"NG") -> 0 | P93: =COUNTIF(P4:P91,"×")+COUNTIF(P4:P91,"NG") -> 0
B94: 全ﾃｽﾄ項目数： | D94: =SUM(H95:P95) -> 204 | G94: 消化項目数： | H94: =H92+H93 -> 0 | I94: =I92+I93 -> 0 | J94: =J92+J93 -> 0 | K94: =K92+K93 -> 0 | L94: =L92+L93 -> 0 | M94: =M92+M93 -> 0 | N94: =N92+N93 -> 0 | O94: =O92+O93 -> 0 | P94: =P92+P93 -> 0 | Q94: =COUNTA(Q4:Q91) -> 0 | R94: =COUNTA(R4:R91) -> 0 | S94: =COUNTA(S4:S91) -> 0
G95: 全項目数： | H95: =COUNTBLANK(H4:H91)+H94+COUNTIF(H4:H91,"□") -> 63 | I95: =COUNTBLANK(I4:I91)+I94+COUNTIF(I4:I91,"□") -> 0 | J95: =COUNTBLANK(J4:J91)+J94+COUNTIF(J4:J91,"□") -> 0 | K95: =COUNTBLANK(K4:K91)+K94+COUNTIF(K4:K91,"□") -> 8 | L95: =COUNTBLANK(L4:L91)+L94+COUNTIF(L4:L91,"□") -> 58 | M95: =COUNTBLANK(M4:M91)+M94+COUNTIF(M4:M91,"□") -> 58 | N95: =COUNTBLANK(N4:N91)+N94+COUNTIF(N4:N91,"□") -> 0 | O95: =COUNTBLANK(O4:O91)+O94+COUNTIF(O4:O91,"□") -> 17 | P95: =COUNTBLANK(P4:P91)+P94+COUNTIF(P4:P91,"□") -> 0

Sheet Win10対応_SS
B1: いなげや様 Win10対応（POS/SS/PS/CS） リグレッションテスト仕様書
B2: 大分類 | C2: 中分類 | D2: 小分類 | E2: テスト項目 | H2: SS | Q2: チェック日付 | T2: 担当 | U2: 備考
E3: No | F3: POS操作 | G3: 結果 | H3: 動作 | I3: DB | J3: ｶｽﾀﾏ | K3: 画面 | L3: ﾚｼｰﾄ | M3: ｼﾞｬｰﾅﾙ | N3: 音声 | O3: ﾛｸﾞ | P3: 小型 LCD | Q3: OK | R3: NG | S3: 修正 OK
B4: 決済端末 | C4: 開局 | E4: =ROW()-3 -> 1 | F4: 開局処理 | G4: 正常に開局されること。決済端末が待機画面になること。 | H4: ー | I4: ー | J4: ー | K4: ー | L4: ー | M4: ー | N4: ー | O4: ー | P4: ー | U4: 決済端末接続なし
B5: （通常操作） | C5: 会員番号登録 | D5: Vカード | E5: =ROW()-3 -> 2 | F5: Vカードで会員登録 | G5: 正常に会員登録できること | H5: ー | I5: ー | J5: ー | K5: ー | L5: ー | M5: ー | N5: ー | O5: ー | P5: ー
C6: 支払い操作 | D6: 会員宣言：なし Vカード支払い（IC） | E6: =ROW()-3 -> 3 | F6: VカードをICで読み込み | G6: 正常に支払いが完了し売上登録できること | H6: ー | I6: ー | J6: ー | K6: ー | L6: ー | M6: ー | N6: ー | O6: ー | P6: ー | U6: 会員宣言ない場合Vカード支払不可
D7: 会員宣言：なし 他クレ支払い（IC） | E7: =ROW()-3 -> 4 | F7: 他クレカードをICで読み込み | G7: 正常に支払いが完了し売上登録できること | H7: ー | I7: ー | J7: ー | K7: ー | L7: ー | M7: ー | N7: ー | O7: ー | P7: ー
D8: 会員宣言：ingカード（ﾀｯﾁｽｷｬﾅ） 他クレ支払い（MSR） | E8: =ROW()-3 -> 5 | F8: 他クレカードをMSRで読み込み | G8: 正常に支払いが完了し売上登録できること | H8: ー | I8: ー | J8: ー | K8: ー | L8: ー | M8: ー | N8: ー | O8: ー | P8: ー
D9: 会員宣言：Vカード Vカード支払い（IC） | E9: =ROW()-3 -> 6 | F9: VカードをICで読み込み | G9: 正常に支払いが完了し売上登録できること | H9: ー | I9: ー | J9: ー | K9: ー | L9: ー | M9: ー | N9: ー | O9: ー | P9: ー
D10: 会員宣言：Vカード 他クレ支払い（MSR） | E10: =ROW()-3 -> 7 | F10: 他クレカードをMSRで読み込み | G10: 正常に支払いが完了し売上登録できること | H10: ー | I10: ー | J10: ー | K10: ー | L10: ー | M10: ー | N10: ー | O10: ー | P10: ー
C11: 通番取消 | D11: 会員宣言：なし Vカード支払い（IC） | E11: =ROW()-3 -> 8 | F11: 元取引と同じVカードをICで読み込み | G11: 正常に取消処理が完了すること | H11: ー | I11: ー | J11: ー | K11: ー | L11: ー | M11: ー | N11: ー | O11: ー | P11: ー | U11: 会員宣言ない場合Vカード支払不可
D12: 会員宣言：なし 他クレ支払い（IC） | E12: =ROW()-3 -> 9 | F12: 元取引と同じ他クレカードをICで読み込み | G12: 正常に取消処理が完了すること | H12: ー | I12: ー | J12: ー | K12: ー | L12: ー | M12: ー | N12: ー | O12: ー | P12: ー
D13: 会員宣言：ingカード（ﾀｯﾁｽｷｬﾅ） 他クレ支払い（MSR） | E13: =ROW()-3 -> 10 | F13: 元取引と同じ他クレカードをMSRで読み込み | G13: 正常に取消処理が完了すること | H13: ー | I13: ー | J13: ー | K13: ー | L13: ー | M13: ー | N13: ー | O13: ー | P13: ー
D14: 会員宣言：Vカード Vカード支払い（IC） | E14: =ROW()-3 -> 11 | F14: 元取引と同じVカードをICで読み込み | G14: 正常に取消処理が完了すること | H14: ー | I14: ー | J14: ー | K14: ー | L14: ー | M14: ー | N14: ー | O14: ー | P14: ー
D15: 会員宣言：Vカード 他クレ支払い（MSR） | E15: =ROW()-3 -> 12 | F15: 元取引と同じ他クレカードをMSRで読み込み | G15: 正常に取消処理が完了すること | H15: ー | I15: ー | J15: ー | K15: ー | L15: ー | M15: ー | N15: ー | O15: ー | P15: ー
C16: 通番修正 | D16: 元取引がVカード支払い | E16: =ROW()-3 -> 13 | F16: 元取引と同じVカードで通番取消、同じVカードで支払い | G16: 元取引の取消処理と修正後の取引が正常に完了すること | H16: ー | I16: ー | J16: ー | K16: ー | L16: ー | M16: ー | N16: ー | O16: ー | P16: ー
E17: =ROW()-3 -> 14 | F17: 元取引と同じVカードで通番取消、他クレカードで支払い | G17: 元取引の取消処理と修正後の取引が正常に完了すること | H17: ー | I17: ー | J17: ー | K17: ー | L17: ー | M17: ー | N17: ー | O17: ー | P17: ー
E18: =ROW()-3 -> 15 | F18: 元取引と同じVカードで通番取消、現金で支払い | G18: 元取引の取消処理と修正後の取引が正常に完了すること | H18: ー | I18: ー | J18: ー | K18: ー | L18: ー | M18: ー | N18: ー | O18: ー | P18: ー | U18: SS現金支払不可
D19: 元取引が他クレ支払い | E19: =ROW()-3 -> 16 | F19: 元取引と同じ他クレで通番取消、同じカードで支払い | G19: 元取引の取消処理と修正後の取引が正常に完了すること | H19: ー | I19: ー | J19: ー | K19: ー | L19: ー | M19: ー | N19: ー | O19: ー | P19: ー
E20: =ROW()-3 -> 17 | F20: 元取引と同じ他クレで通番取消、Vカードで支払い | G20: 元取引の取消処理と修正後の取引が正常に完了すること | H20: ー | I20: ー | J20: ー | K20: ー | L20: ー | M20: ー | N20: ー | O20: ー | P20: ー
E21: =ROW()-3 -> 18 | F21: 元取引と同じ他クレで通番取消、現金で支払い | G21: 元取引の取消処理と修正後の取引が正常に完了すること | H21: ー | I21: ー | J21: ー | K21: ー | L21: ー | M21: ー | N21: ー | O21: ー | P21: ー | U21: SS現金支払不可
B22: 練習モード | C22: 会員番号登録 | D22: Vカード | E22: =ROW()-3 -> 19 | F22: Vカードで会員登録 | G22: 正常に会員登録できること | H22: ー | I22: ー | J22: ー | K22: ー | L22: ー | M22: ー | N22: ー | O22: ー | P22: ー
C23: 支払い操作 | D23: 会員宣言：なし Vカード支払い（IC） | E23: =ROW()-3 -> 20 | F23: VカードをICで読み込み | G23: 練習：正常に支払いが完了し売上登録できること | H23: ー | I23: ー | J23: ー | K23: ー | L23: ー | M23: ー | N23: ー | O23: ー | P23: ー | U23: 会員宣言ない場合Vカード支払不可
D24: 会員宣言：ingカード（ﾀｯﾁｽｷｬﾅ） Vカード支払い（IC） | E24: =ROW()-3 -> 21 | F24: VカードをICで読み込み | G24: 練習：正常に支払いが完了し売上登録できること | H24: ー | I24: ー | J24: ー | K24: ー | L24: ー | M24: ー | N24: ー | O24: ー | P24: ー
D25: 会員宣言：ingカード（ﾀｯﾁｽｷｬﾅ） 他クレ支払い（MSR） | E25: =ROW()-3 -> 22 | F25: 他クレカードをMSRで読み込み | G25: 練習：正常に支払いが完了し売上登録できること | H25: ー | I25: ー | J25: ー | K25: ー | L25: ー | M25: ー | N25: ー | O25: ー | P25: ー
D26: 会員宣言：Vカード Vカード支払い（IC） | E26: =ROW()-3 -> 23 | F26: VカードをICで読み込み | G26: 練習：正常に支払いが完了し売上登録できること | H26: ー | I26: ー | J26: ー | K26: ー | L26: ー | M26: ー | N26: ー | O26: ー | P26: ー
D27: 会員宣言：Vカード 他クレ支払い（MSR） | E27: =ROW()-3 -> 24 | F27: 他クレカードをMSRで読み込み | G27: 練習：正常に支払いが完了し売上登録できること | H27: ー | I27: ー | J27: ー | K27: ー | L27: ー | M27: ー | N27: ー | O27: ー | P27: ー
C28: 通番取消 | D28: 元取引：会員宣言なし Vカード支払い | E28: =ROW()-3 -> 25 | F28: 元取引と同じVカードをICで読み込み | G28: 練習：正常に取消処理が完了すること | H28: ー | I28: ー | J28: ー | K28: ー | L28: ー | M28: ー | N28: ー | O28: ー | P28: ー | U28: 会員宣言ない場合Vカード支払不可
D29: 元取引：ingカードで会員宣言 Vカード支払い | E29: =ROW()-3 -> 26 | F29: 元取引と同じVカードをMSRで読み込み | G29: 練習：正常に取消処理が完了すること | H29: ー | I29: ー | J29: ー | K29: ー | L29: ー | M29: ー | N29: ー | O29: ー | P29: ー
D30: 元取引：会員宣言なし 他クレ支払い | E30: =ROW()-3 -> 27 | F30: 元取引と同じ他クレカードをMSRで読み込み | G30: 練習：正常に取消処理が完了すること | H30: ー | I30: ー | J30: ー | K30: ー | L30: ー | M30: ー | N30: ー | O30: ー | P30: ー
D31: 元取引がVカードで会員宣言 他クレ支払い | E31: =ROW()-3 -> 28 | F31: 元取引と同じ他クレカードをMSRで読み込み | G31: 練習：正常に取消処理が完了すること | H31: ー | I31: ー | J31: ー | K31: ー | L31: ー | M31: ー | N31: ー | O31: ー | P31: ー
C32: 通番修正 | D32: 元取引がVカード支払い | E32: =ROW()-3 -> 29 | F32: 元取引と同じVカードで通番取消、同じVカードで支払い | G32: 練習：元取引の取消処理と修正後の取引が正常に完了すること | H32: ー | I32: ー | J32: ー | K32: ー | L32: ー | M32: ー | N32: ー | O32: ー | P32: ー
E33: =ROW()-3 -> 30 | F33: 元取引と同じVカードで通番取消、他クレカードで支払い | G33: 練習：元取引の取消処理と修正後の取引が正常に完了すること | H33: ー | I33: ー | J33: ー | K33: ー | L33: ー | M33: ー | N33: ー | O33: ー | P33: ー
D34: 元取引が他クレ支払い | E34: =ROW()-3 -> 31 | F34: 元取引と同じ他クレで通番取消、Vカードで支払い | G34: 練習：元取引の取消処理と修正後の取引が正常に完了すること | H34: ー | I34: ー | J34: ー | K34: ー | L34: ー | M34: ー | N34: ー | O34: ー | P34: ー | U34: 元取引もしくは修正後支払のどちらかで会員宣言が必要
E35: =ROW()-3 -> 32 | F35: 元取引と同じ他クレで通番取消、現金で支払い | G35: 練習：元取引の取消処理と修正後の取引が正常に完了すること | H35: ー | I35: ー | J35: ー | K35: ー | L35: ー | M35: ー | N35: ー | O35: ー | P35: ー | U35: SS現金支払不可
B36: Satisfa | C36: 開局 | E36: =ROW()-3 -> 33 | F36: 開局処理 | G36: POS開局時にエラーが発生しないこと | H36: □ | I36: ー | J36: ー | K36: □ | L36: □ | M36: □ | N36: ー | O36: □ | P36: ー
C37: 会員番号登録 | D37: Vカード | E37: =ROW()-3 -> 34 | F37: Vカードで会員登録 | G37: 正常に会員登録できること。現在ポイントが正しく表示されること | H37: ー | I37: ー | J37: ー | K37: ー | L37: ー | M37: ー | N37: ー | O37: ー | P37: ー
D38: ingfanカード | E38: =ROW()-3 -> 35 | F38: ingfan会員バーコードで会員登録 | G38: 正常に会員登録できること。現在ポイントが正しく表示されること | H38: □ | I38: ー | J38: ー | K38: ー | L38: □ | M38: □ | N38: ー | O38: □ | P38: ー
D39: 手入力 | E39: =ROW()-3 -> 36 | F39: 手入力で会員登録 | G39: 正常に会員登録できること。現在ポイントが正しく表示されること | H39: □ | I39: ー | J39: ー | K39: ー | L39: □ | M39: □ | N39: ー | O39: □ | P39: ー
C40: ポイント付与 | D40: Vカード | E40: =ROW()-3 -> 37 | F40: Vカードで会員登録 | G40: 正常に取引が完了すること。今回ポイントが正しく付与されること | H40: ー | I40: ー | J40: ー | K40: ー | L40: ー | M40: ー | N40: ー | O40: ー | P40: ー
D41: ingfanカード | E41: =ROW()-3 -> 38 | F41: ingfan会員バーコードで会員登録 | G41: 正常に取引が完了すること。今回ポイントが正しく付与されること | H41: □ | I41: ー | J41: ー | K41: ー | L41: □ | M41: □ | N41: ー | O41: □ | P41: ー
D42: 手入力 | E42: =ROW()-3 -> 39 | F42: 手入力で会員登録 | G42: 正常に取引が完了すること。今回ポイントが正しく付与されること | H42: □ | I42: ー | J42: ー | K42: ー | L42: □ | M42: □ | N42: ー | O42: □ | P42: ー
C43: ポイント利用 | D43: Vカード | E43: =ROW()-3 -> 40 | F43: Vカードで会員登録 | G43: 正常に取引が完了すること。ポイント利用分が正しく反映されること | H43: ー | I43: ー | J43: ー | K43: ー | L43: ー | M43: ー | N43: ー | O43: ー | P43: ー
D44: ingfanカード | E44: =ROW()-3 -> 41 | F44: ingfan会員バーコードで会員登録 | G44: 正常に取引が完了すること。ポイント利用分が正しく反映されること | H44: □ | I44: ー | J44: ー | K44: ー | L44: □ | M44: □ | N44: ー | O44: □ | P44: ー
D45: 手入力 | E45: =ROW()-3 -> 42 | F45: 手入力で会員登録 | G45: 正常に取引が完了すること。ポイント利用分が正しく反映されること | H45: □ | I45: ー | J45: ー | K45: ー | L45: □ | M45: □ | N45: ー | O45: □ | P45: ー
C46: ポイント修正 | D46: Vカード | E46: =ROW()-3 -> 43 | F46: Vカードで会員登録 | G46: 正常に取引が完了すること。ポイント利用分が正しく反映されること | H46: ー | I46: ー | J46: ー | K46: ー | L46: ー | M46: ー | N46: ー | O46: ー | P46: ー | U46: SSポイント修正ボタンなし
D47: ingfanカード | E47: =ROW()-3 -> 44 | F47: ingfan会員バーコードで会員登録 | G47: 正常に処理が完了すること。ポイント修正結果が正しく反映されること | H47: ー | I47: ー | J47: ー | K47: ー | L47: ー | M47: ー | N47: ー | O47: ー | P47: ー | U47: 〃
D48: 手入力 | E48: =ROW()-3 -> 45 | F48: 手入力で会員登録 | G48: 正常に処理が完了すること。ポイント修正結果が正しく反映されること | H48: ー | I48: ー | J48: ー | K48: ー | L48: ー | M48: ー | N48: ー | O48: ー | P48: ー | U48: 〃
C49: レジマイナス | D49: 会員宣言なし | E49: =ROW()-3 -> 46 | F49: 会員宣言しない | G49: 正常にマイナス処理が完了すること | H49: □ | I49: ー | J49: ー | K49: □ | L49: □ | M49: □ | N49: ー | O49: □ | P49: ー | U49: Vカードを手入力、200円で1ポイント減産を確認
D50: ingカードで会員宣言 | E50: =ROW()-3 -> 47 | F50: ingfan会員バーコードで会員宣言 | G50: 正常にマイナス処理が完了すること（現在ポイントが減算されること） | H50: □ | I50: ー | J50: ー | K50: □ | L50: □ | M50: □ | N50: ー | O50: □ | P50: ー
D51: Vカードで会員宣言 | E51: =ROW()-3 -> 48 | F51: Vカードで会員宣言 | G51: 正常にマイナス処理が完了すること （現在ポイントが200円1ポイントで減算されること） | H51: ー | I51: ー | J51: ー | K51: ー | L51: ー | M51: ー | N51: ー | O51: ー | P51: ー
C52: さんにち割 | D52: 開局 | E52: =ROW()-3 -> 49 | F52: 開局レシートを確認 | G52: 「さんにち割引」が表示されていること 対象日付が表示されていること | H52: ー | I52: ー | J52: ー | K52: ー | L52: ー | M52: ー | N52: ー | O52: ー | P52: ー | U52: パッケージ系にて実施
D53: 小計自動値引 | E53: =ROW()-3 -> 50 | F53: ingfan会員バーコードで会員登録 | G53: 自動小計値引が反映されないこと | H53: □ | I53: ー | J53: ー | K53: □ | L53: □ | M53: □ | N53: ー | O53: ー | P53: ー
E54: =ROW()-3 -> 51 | F54: Vカードで会員登録 | G54: 自動小計値引（5%）が反映されること | H54: □ | I54: ー | J54: ー | K54: □ | L54: □ | M54: □ | N54: ー | O54: ー | P54: ー | U54: 手入力で確認
B55: 自動釣銭釣札機 | C55: POS連携 | D55: 預り金処理 | E55: =ROW()-3 -> 52 | F55: 預り金を投入 | G55: 正常に処理が完了すること。お釣りが正しく出金されること | H55: ー | I55: ー | J55: ー | K55: ー | L55: ー | M55: ー | N55: ー | O55: ー | P55: ー
B56: （POS / RT-300） | D56: 入金処理（Xモード） | E56: =ROW()-3 -> 53 | F56: 入金処理（Xモード） | G56: 正常に処理が完了すること。 | H56: ー | I56: ー | J56: ー | K56: ー | L56: ー | M56: ー | N56: ー | O56: ー | P56: ー
D57: 在高点検 | E57: =ROW()-3 -> 54 | F57: 在高点検（Xモード） | G57: 正常に処理が完了すること。 | H57: ー | I57: ー | J57: ー | K57: ー | L57: ー | M57: ー | N57: ー | O57: ー | P57: ー
D58: 全回収 | E58: =ROW()-3 -> 55 | F58: 全回収（Zモード） | G58: 正常に処理が完了すること。 | H58: ー | I58: ー | J58: ー | K58: ー | L58: ー | M58: ー | N58: ー | O58: ー | P58: ー
D59: 紙幣途中回収（移動） | E59: =ROW()-3 -> 56 | F59: 紙幣途中回収（移動）（Zモード） | G59: 正常に処理が完了すること。 | H59: ー | I59: ー | J59: ー | K59: ー | L59: ー | M59: ー | N59: ー | O59: ー | P59: ー
D60: 硬貨途中回収 | E60: =ROW()-3 -> 57 | F60: 硬貨途中回収（Zモード） | G60: 正常に処理が完了すること。 | H60: ー | I60: ー | J60: ー | K60: ー | L60: ー | M60: ー | N60: ー | O60: ー | P60: ー
D61: ボックス回収 | E61: =ROW()-3 -> 58 | F61: ボックス回収（Zモード） | G61: 正常に処理が完了すること。 | H61: ー | I61: ー | J61: ー | K61: ー | L61: ー | M61: ー | N61: ー | O61: ー | P61: ー
D62: 出金処理 | E62: =ROW()-3 -> 59 | F62: 出金処理（Zモード） | G62: 正常に処理が完了すること。 | H62: ー | I62: ー | J62: ー | K62: ー | L62: ー | M62: ー | N62: ー | O62: ー | P62: ー
D63: あふれ金収納庫移動 | E63: =ROW()-3 -> 60 | F63: あふれ金収納庫移動（Zモード） | G63: 正常に処理が完了すること。 | H63: ー | I63: ー | J63: ー | K63: ー | L63: ー | M63: ー | N63: ー | O63: ー | P63: ー
B64: 自動釣銭釣札機 | C64: POS連携 | D64: 預り金処理 | E64: =ROW()-3 -> 61 | F64: 預り金を投入 | G64: 正常に処理が完了すること。お釣りが正しく出金されること | H64: ー | I64: ー | J64: ー | K64: ー | L64: ー | M64: ー | N64: ー | O64: ー | P64: ー
B65: （PS / RT-380） | D65: 入金処理（Xモード） | E65: =ROW()-3 -> 62 | F65: 入金処理（Xモード） | G65: 正常に処理が完了すること。 | H65: ー | I65: ー | J65: ー | K65: ー | L65: ー | M65: ー | N65: ー | O65: ー | P65: ー
D66: 在高点検 | E66: =ROW()-3 -> 63 | F66: 在高点検（Xモード） | G66: 正常に処理が完了すること。 | H66: ー | I66: ー | J66: ー | K66: ー | L66: ー | M66: ー | N66: ー | O66: ー | P66: ー
D67: 全回収 | E67: =ROW()-3 -> 64 | F67: 全回収（Zモード） | G67: 正常に処理が完了すること。 | H67: ー | I67: ー | J67: ー | K67: ー | L67: ー | M67: ー | N67: ー | O67: ー | P67: ー
D68: 紙幣途中回収（移動） | E68: =ROW()-3 -> 65 | F68: 紙幣途中回収（移動）（Zモード） | G68: 正常に処理が完了すること。 | H68: ー | I68: ー | J68: ー | K68: ー | L68: ー | M68: ー | N68: ー | O68: ー | P68: ー
D69: 硬貨途中回収 | E69: =ROW()-3 -> 66 | F69: 硬貨途中回収（Zモード） | G69: 正常に処理が完了すること。 | H69: ー | I69: ー | J69: ー | K69: ー | L69: ー | M69: ー | N69: ー | O69: ー | P69: ー
D70: ボックス回収 | E70: =ROW()-3 -> 67 | F70: ボックス回収（Zモード） | G70: 正常に処理が完了すること。 | H70: ー | I70: ー | J70: ー | K70: ー | L70: ー | M70: ー | N70: ー | O70: ー | P70: ー
D71: 出金処理 | E71: =ROW()-3 -> 68 | F71: 出金処理（Zモード） | G71: 正常に処理が完了すること。 | H71: ー | I71: ー | J71: ー | K71: ー | L71: ー | M71: ー | N71: ー | O71: ー | P71: ー
D72: あふれ金収納庫移動 | E72: =ROW()-3 -> 69 | F72: あふれ金収納庫移動（Zモード） | G72: 正常に処理が完了すること。 | H72: ー | I72: ー | J72: ー | K72: ー | L72: ー | M72: ー | N72: ー | O72: ー | P72: ー
H73: ー | I73: ー | J73: ー | K73: ー | L73: ー | M73: ー | N73: ー | O73: ー | P73: ー
B74: 消化ﾃｽﾄ項目数： | D74: =SUM(H76:P76) -> 0 | G74: OK数： | H74: =COUNTIF(H4:H73,"●")+COUNTIF(H4:H73,"■")+COUNTIF(H4:H73,"OK") -> 0 | I74: =COUNTIF(I4:I73,"●")+COUNTIF(I4:I73,"■")+COUNTIF(I4:I73,"OK") -> 0 | J74: =COUNTIF(J4:J73,"●")+COUNTIF(J4:J73,"■")+COUNTIF(J4:J73,"OK") -> 0 | K74: =COUNTIF(K4:K73,"●")+COUNTIF(K4:K73,"■")+COUNTIF(K4:K73,"OK") -> 0 | L74: =COUNTIF(L4:L73,"●")+COUNTIF(L4:L73,"■")+COUNTIF(L4:L73,"OK") -> 0 | M74: =COUNTIF(M4:M73,"●")+COUNTIF(M4:M73,"■")+COUNTIF(M4:M73,"OK") -> 0 | N74: =COUNTIF(N4:N73,"●")+COUNTIF(N4:N73,"■")+COUNTIF(N4:N73,"OK") -> 0 | O74: =COUNTIF(O4:O73,"●")+COUNTIF(O4:O73,"■")+COUNTIF(O4:O73,"OK") -> 0 | P74: =COUNTIF(P4:P73,"●")+COUNTIF(P4:P73,"■")+COUNTIF(P4:P73,"OK") -> 0 | Q74: 合計
G75: NG数： | H75: =COUNTIF(H4:H73,"×")+COUNTIF(H4:H73,"NG") -> 0 | I75: =COUNTIF(I4:I73,"×")+COUNTIF(I4:I73,"NG") -> 0 | J75: =COUNTIF(J4:J73,"×")+COUNTIF(J4:J73,"NG") -> 0 | K75: =COUNTIF(K4:K73,"×")+COUNTIF(K4:K73,"NG") -> 0 | L75: =COUNTIF(L4:L73,"×")+COUNTIF(L4:L73,"NG") -> 0 | M75: =COUNTIF(M4:M73,"×")+COUNTIF(M4:M73,"NG") -> 0 | N75: =COUNTIF(N4:N73,"×")+COUNTIF(N4:N73,"NG") -> 0 | O75: =COUNTIF(O4:O73,"×")+COUNTIF(O4:O73,"NG") -> 0 | P75: =COUNTIF(P4:P73,"×")+COUNTIF(P4:P73,"NG") -> 0
B76: 全ﾃｽﾄ項目数： | D76: =SUM(H77:P77) -> 47 | G76: 消化項目数： | H76: =H74+H75 -> 0 | I76: =I74+I75 -> 0 | J76: =J74+J75 -> 0 | K76: =K74+K75 -> 0 | L76: =L74+L75 -> 0 | M76: =M74+M75 -> 0 | N76: =N74+N75 -> 0 | O76: =O74+O75 -> 0 | P76: =P74+P75 -> 0 | Q76: =COUNTA(Q4:Q73) -> 0 | R76: =COUNTA(R4:R73) -> 0 | S76: =COUNTA(S55:S73) -> 0
G77: 全項目数： | H77: =COUNTBLANK(H4:H73)+H76+COUNTIF(H4:H73,"□") -> 11 | I77: =COUNTBLANK(I4:I73)+I76+COUNTIF(I4:I73,"□") -> 0 | J77: =COUNTBLANK(J4:J73)+J76+COUNTIF(J4:J73,"□") -> 0 | K77: =COUNTBLANK(K4:K73)+K76+COUNTIF(K4:K73,"□") -> 5 | L77: =COUNTBLANK(L4:L73)+L76+COUNTIF(L4:L73,"□") -> 11 | M77: =COUNTBLANK(M4:M73)+M76+COUNTIF(M4:M73,"□") -> 11 | N77: =COUNTBLANK(N4:N73)+N76+COUNTIF(N4:N73,"□") -> 0 | O77: =COUNTBLANK(O4:O73)+O76+COUNTIF(O4:O73,"□") -> 9 | P77: =COUNTBLANK(P4:P73)+P76+COUNTIF(P4:P73,"□") -> 0

Sheet Win10対応_PS
B1: いなげや様 Win10対応（POS/SS/PS/CS） リグレッションテスト仕様書
B2: 大分類 | C2: 中分類 | D2: 小分類 | E2: テスト項目 | H2: PS | Q2: チェック日付 | T2: 担当 | U2: 備考
E3: No | F3: POS操作 | G3: 結果 | H3: 動作 | I3: DB | J3: ｶｽﾀﾏ | K3: 画面 | L3: ﾚｼｰﾄ | M3: ｼﾞｬｰﾅﾙ | N3: 音声 | O3: ﾛｸﾞ | P3: 小型 LCD | Q3: OK | R3: NG | S3: 修正 OK
B4: 決済端末 | C4: 開局 | E4: =ROW()-3 -> 1 | F4: 開局処理 | G4: 正常に開局されること。決済端末が待機画面になること。 | H4: ー | I4: ー | J4: ー | K4: ー | L4: ー | M4: ー | N4: ー | O4: ー | P4: ー | U4: パッケージ系(PS)で実施
B5: （通常操作） | C5: 会員番号登録 | D5: Vカード | E5: =ROW()-3 -> 2 | F5: Vカードで会員登録 | G5: 正常に会員登録できること | H5: □ | I5: ー | J5: ー | K5: □ | L5: □ | M5: □ | N5: ー | O5: ー | P5: ー
C6: 支払い操作 | D6: 会員宣言：なし Vカード支払い（IC） | E6: =ROW()-3 -> 3 | F6: VカードをICで読み込み | G6: 正常に支払いが完了し売上登録できること | H6: ー | I6: ー | J6: ー | K6: ー | L6: ー | M6: ー | N6: ー | O6: ー | P6: ー | U6: 会員宣言ない場合Vカード支払不可
D7: 会員宣言：なし 他クレ支払い（IC） | E7: =ROW()-3 -> 4 | F7: 他クレカードをICで読み込み | G7: 正常に支払いが完了し売上登録できること | H7: □ | I7: ー | J7: ー | K7: ー | L7: □ | M7: □ | N7: ー | O7: ー | P7: ー
D8: 会員宣言：ingカード（固定ｶﾒﾗｽｷｬﾅ） 他クレ支払い（MSR） | E8: =ROW()-3 -> 5 | F8: 他クレカードをMSRで読み込み | G8: 正常に支払いが完了し売上登録できること | H8: □ | I8: ー | J8: ー | K8: ー | L8: □ | M8: □ | N8: ー | O8: ー | P8: ー
D9: 会員宣言：Vカード Vカード支払い（IC） | E9: =ROW()-3 -> 6 | F9: VカードをICで読み込み | G9: 正常に支払いが完了し売上登録できること | H9: □ | I9: ー | J9: ー | K9: ー | L9: □ | M9: □ | N9: ー | O9: ー | P9: ー | U9: 蒲田環境VカードIC支払不可、VカードMS支払
D10: 会員宣言：Vカード 他クレ支払い（MSR） | E10: =ROW()-3 -> 7 | F10: 他クレカードをMSRで読み込み | G10: 正常に支払いが完了し売上登録できること | H10: □ | I10: ー | J10: ー | K10: ー | L10: □ | M10: □ | N10: ー | O10: ー | P10: ー
C11: 通番取消 | D11: 会員宣言：なし Vカード支払い（IC） | E11: =ROW()-3 -> 8 | F11: 元取引と同じVカードをICで読み込み | G11: 正常に取消処理が完了すること | H11: ー | I11: ー | J11: ー | K11: ー | L11: ー | M11: ー | N11: ー | O11: ー | P11: ー | U11: 会員宣言ない場合Vカード支払不可
D12: 会員宣言：なし 他クレ支払い（IC） | E12: =ROW()-3 -> 9 | F12: 元取引と同じ他クレカードをICで読み込み | G12: 正常に取消処理が完了すること | H12: □ | I12: ー | J12: ー | K12: ー | L12: □ | M12: □ | N12: ー | O12: ー | P12: ー
D13: 会員宣言：ingカード（固定ｶﾒﾗｽｷｬﾅ） 他クレ支払い（MSR） | E13: =ROW()-3 -> 10 | F13: 元取引と同じ他クレカードをMSRで読み込み | G13: 正常に取消処理が完了すること | H13: □ | I13: ー | J13: ー | K13: ー | L13: □ | M13: □ | N13: ー | O13: ー | P13: ー
D14: 会員宣言：Vカード Vカード支払い（IC） | E14: =ROW()-3 -> 11 | F14: 元取引と同じVカードをICで読み込み | G14: 正常に取消処理が完了すること | H14: □ | I14: ー | J14: ー | K14: ー | L14: □ | M14: □ | N14: ー | O14: ー | P14: ー
D15: 会員宣言：Vカード 他クレ支払い（MSR） | E15: =ROW()-3 -> 12 | F15: 元取引と同じ他クレカードをMSRで読み込み | G15: 正常に取消処理が完了すること | H15: □ | I15: ー | J15: ー | K15: ー | L15: □ | M15: □ | N15: ー | O15: ー | P15: ー
C16: 通番修正 | D16: 元取引がVカード支払い | E16: =ROW()-3 -> 13 | F16: 元取引と同じVカードで通番取消、同じVカードで支払い | G16: 元取引の取消処理と修正後の取引が正常に完了すること | H16: □ | I16: ー | J16: ー | K16: ー | L16: □ | M16: □ | N16: ー | O16: ー | P16: ー
E17: =ROW()-3 -> 14 | F17: 元取引と同じVカードで通番取消、他クレカードで支払い | G17: 元取引の取消処理と修正後の取引が正常に完了すること | H17: □ | I17: ー | J17: ー | K17: ー | L17: □ | M17: □ | N17: ー | O17: ー | P17: ー
E18: =ROW()-3 -> 15 | F18: 元取引と同じVカードで通番取消、現金で支払い | G18: 元取引の取消処理と修正後の取引が正常に完了すること | H18: □ | I18: ー | J18: ー | K18: ー | L18: □ | M18: □ | N18: ー | O18: ー | P18: ー
D19: 元取引が他クレ支払い | E19: =ROW()-3 -> 16 | F19: 元取引と同じ他クレで通番取消、同じカードで支払い | G19: 元取引の取消処理と修正後の取引が正常に完了すること | H19: □ | I19: ー | J19: ー | K19: ー | L19: □ | M19: □ | N19: ー | O19: ー | P19: ー
E20: =ROW()-3 -> 17 | F20: 元取引と同じ他クレで通番取消、Vカードで支払い | G20: 元取引の取消処理と修正後の取引が正常に完了すること | H20: □ | I20: ー | J20: ー | K20: ー | L20: □ | M20: □ | N20: ー | O20: ー | P20: ー
E21: =ROW()-3 -> 18 | F21: 元取引と同じ他クレで通番取消、現金で支払い | G21: 元取引の取消処理と修正後の取引が正常に完了すること | H21: □ | I21: ー | J21: ー | K21: ー | L21: □ | M21: □ | N21: ー | O21: ー | P21: ー
B22: 練習モード | C22: 会員番号登録 | D22: Vカード | E22: =ROW()-3 -> 19 | F22: Vカードで会員登録 | G22: 正常に会員登録できること | H22: □ | I22: ー | J22: ー | K22: ー | L22: □ | M22: □ | N22: ー | O22: ー | P22: ー
C23: 支払い操作 | D23: 会員宣言：なし Vカード支払い（IC） | E23: =ROW()-3 -> 20 | F23: VカードをICで読み込み | G23: 練習：正常に支払いが完了し売上登録できること | H23: ー | I23: ー | J23: ー | K23: ー | L23: ー | M23: ー | N23: ー | O23: ー | P23: ー | U23: 会員宣言ない場合Vカード支払不可
D24: 会員宣言：ingカード（ﾀｯﾁｽｷｬﾅ） Vカード支払い（IC） | E24: =ROW()-3 -> 21 | F24: VカードをICで読み込み | G24: 練習：正常に支払いが完了し売上登録できること | H24: ー | I24: ー | J24: ー | K24: ー | L24: ー | M24: ー | N24: ー | O24: ー | P24: ー | U24: ペイメントモードではfanカード宣言Ｖカード支払不可
D25: 会員宣言：ingカード（ﾀｯﾁｽｷｬﾅ） 他クレ支払い（MSR） | E25: =ROW()-3 -> 22 | F25: 他クレカードをMSRで読み込み | G25: 練習：正常に支払いが完了し売上登録できること | H25: □ | I25: ー | J25: ー | K25: ー | L25: □ | M25: □ | N25: ー | O25: ー | P25: ー
D26: 会員宣言：Vカード Vカード支払い（IC） | E26: =ROW()-3 -> 23 | F26: VカードをICで読み込み | G26: 練習：正常に支払いが完了し売上登録できること | H26: □ | I26: ー | J26: ー | K26: ー | L26: □ | M26: □ | N26: ー | O26: ー | P26: ー
D27: 会員宣言：Vカード 他クレ支払い（MSR） | E27: =ROW()-3 -> 24 | F27: 他クレカードをMSRで読み込み | G27: 練習：正常に支払いが完了し売上登録できること | H27: □ | I27: ー | J27: ー | K27: ー | L27: □ | M27: □ | N27: ー | O27: ー | P27: ー
C28: 通番取消 | D28: 元取引：会員宣言なし Vカード支払い | E28: =ROW()-3 -> 25 | F28: 元取引と同じVカードをICで読み込み | G28: 練習：正常に取消処理が完了すること | H28: ー | I28: ー | J28: ー | K28: ー | L28: ー | M28: ー | N28: ー | O28: ー | P28: ー | U28: 会員宣言ない場合Vカード支払不可
D29: 元取引：ingカードで会員宣言 Vカード支払い | E29: =ROW()-3 -> 26 | F29: 元取引と同じVカードをMSRで読み込み | G29: 練習：正常に取消処理が完了すること | H29: ー | I29: ー | J29: ー | K29: ー | L29: ー | M29: ー | N29: ー | O29: ー | P29: ー
D30: 元取引：会員宣言なし 他クレ支払い | E30: =ROW()-3 -> 27 | F30: 元取引と同じ他クレカードをMSRで読み込み | G30: 練習：正常に取消処理が完了すること | H30: □ | I30: ー | J30: ー | K30: ー | L30: □ | M30: □ | N30: ー | O30: ー | P30: ー
D31: 元取引がVカードで会員宣言 他クレ支払い | E31: =ROW()-3 -> 28 | F31: 元取引と同じ他クレカードをMSRで読み込み | G31: 練習：正常に取消処理が完了すること | H31: □ | I31: ー | J31: ー | K31: ー | L31: □ | M31: □ | N31: ー | O31: ー | P31: ー
C32: 通番修正 | D32: 元取引がVカード支払い | E32: =ROW()-3 -> 29 | F32: 元取引と同じVカードで通番取消、同じVカードで支払い | G32: 練習：元取引の取消処理と修正後の取引が正常に完了すること | H32: □ | I32: ー | J32: ー | K32: ー | L32: □ | M32: □ | N32: ー | O32: ー | P32: ー
E33: =ROW()-3 -> 30 | F33: 元取引と同じVカードで通番取消、他クレカードで支払い | G33: 練習：元取引の取消処理と修正後の取引が正常に完了すること | H33: □ | I33: ー | J33: ー | K33: ー | L33: □ | M33: □ | N33: ー | O33: ー | P33: ー
D34: 元取引が他クレ支払い | E34: =ROW()-3 -> 31 | F34: 元取引と同じ他クレで通番取消、Vカードで支払い | G34: 練習：元取引の取消処理と修正後の取引が正常に完了すること | H34: □ | I34: ー | J34: ー | K34: ー | L34: □ | M34: □ | N34: ー | O34: ー | P34: ー
E35: =ROW()-3 -> 32 | F35: 元取引と同じ他クレで通番取消、現金で支払い | G35: 練習：元取引の取消処理と修正後の取引が正常に完了すること | H35: □ | I35: ー | J35: ー | K35: ー | L35: □ | M35: □ | N35: ー | O35: ー | P35: ー
B36: Satisfa | C36: 開局 | E36: =ROW()-3 -> 33 | F36: 開局処理 | G36: POS開局時にエラーが発生しないこと | H36: □ | I36: ー | J36: ー | K36: ー | L36: ー | M36: ー | N36: ー | O36: □ | P36: ー
C37: 会員番号登録 | D37: Vカード | E37: =ROW()-3 -> 34 | F37: Vカードで会員登録 | G37: 正常に会員登録できること。現在ポイントが正しく表示されること | H37: □ | I37: ー | J37: ー | K37: ー | L37: □ | M37: □ | N37: ー | O37: □ | P37: ー
D38: ingfanカード | E38: =ROW()-3 -> 35 | F38: ingfan会員バーコードで会員登録 | G38: 正常に会員登録できること。現在ポイントが正しく表示されること | H38: □ | I38: ー | J38: ー | K38: ー | L38: □ | M38: □ | N38: ー | O38: □ | P38: ー
D39: 手入力 | E39: =ROW()-3 -> 36 | F39: 手入力で会員登録 | G39: 正常に会員登録できること。現在ポイントが正しく表示されること | H39: □ | I39: ー | J39: ー | K39: ー | L39: □ | M39: □ | N39: ー | O39: □ | P39: ー | U39: POSモード手入力可
C40: ポイント付与 | D40: Vカード | E40: =ROW()-3 -> 37 | F40: Vカードで会員登録 | G40: 正常に取引が完了すること。今回ポイントが正しく付与されること | H40: □ | I40: ー | J40: ー | K40: ー | L40: □ | M40: □ | N40: ー | O40: □ | P40: ー
D41: ingfanカード | E41: =ROW()-3 -> 38 | F41: ingfan会員バーコードで会員登録 | G41: 正常に取引が完了すること。今回ポイントが正しく付与されること | H41: □ | I41: ー | J41: ー | K41: ー | L41: □ | M41: □ | N41: ー | O41: □ | P41: ー
D42: 手入力 | E42: =ROW()-3 -> 39 | F42: 手入力で会員登録 | G42: 正常に取引が完了すること。今回ポイントが正しく付与されること | H42: □ | I42: ー | J42: ー | K42: ー | L42: □ | M42: □ | N42: ー | O42: □ | P42: ー | U42: POSモード手入力可
C43: ポイント利用 | D43: Vカード | E43: =ROW()-3 -> 40 | F43: Vカードで会員登録 | G43: 正常に取引が完了すること。ポイント利用分が正しく反映されること | H43: □ | I43: ー | J43: ー | K43: ー | L43: □ | M43: □ | N43: ー | O43: □ | P43: ー
D44: ingfanカード | E44: =ROW()-3 -> 41 | F44: ingfan会員バーコードで会員登録 | G44: 正常に取引が完了すること。ポイント利用分が正しく反映されること | H44: □ | I44: ー | J44: ー | K44: ー | L44: □ | M44: □ | N44: ー | O44: □ | P44: ー
D45: 手入力 | E45: =ROW()-3 -> 42 | F45: 手入力で会員登録 | G45: 正常に取引が完了すること。ポイント利用分が正しく反映されること | H45: □ | I45: ー | J45: ー | K45: ー | L45: □ | M45: □ | N45: ー | O45: □ | P45: ー | U45: POSモード手入力可
C46: ポイント修正 | D46: Vカード | E46: =ROW()-3 -> 43 | F46: Vカードで会員登録 | G46: 正常に処理が完了すること。ポイント修正結果が正しく反映されること | H46: □ | I46: ー | J46: ー | K46: ー | L46: □ | M46: □ | N46: ー | O46: □ | P46: ー
D47: ingfanカード | E47: =ROW()-3 -> 44 | F47: ingfan会員バーコードで会員登録 | G47: 正常に処理が完了すること。ポイント修正結果が正しく反映されること | H47: □ | I47: ー | J47: ー | K47: ー | L47: □ | M47: □ | N47: ー | O47: □ | P47: ー
D48: 手入力 | E48: =ROW()-3 -> 45 | F48: 手入力で会員登録 | G48: 正常に処理が完了すること。ポイント修正結果が正しく反映されること | H48: □ | I48: ー | J48: ー | K48: ー | L48: □ | M48: □ | N48: ー | O48: □ | P48: ー | U48: POSモード手入力可
C49: レジマイナス | D49: 会員宣言なし | E49: =ROW()-3 -> 46 | F49: 会員宣言しない | G49: 正常にマイナス処理が完了すること | H49: ー | I49: ー | J49: ー | K49: ー | L49: ー | M49: ー | N49: ー | O49: ー | P49: ー | U49: パッケージ系(PS)で実施
D50: ingカードで会員宣言 | E50: =ROW()-3 -> 47 | F50: ingfan会員バーコードで会員宣言 | G50: 正常にマイナス処理が完了すること（現在ポイントが減算されること） | H50: □ | I50: ー | J50: ー | K50: □ | L50: □ | M50: □ | N50: ー | O50: □ | P50: ー
D51: Vカードで会員宣言 | E51: =ROW()-3 -> 48 | F51: Vカードで会員宣言 | G51: 正常にマイナス処理が完了すること （現在ポイントが200円1ポイントで減算されること） | H51: □ | I51: ー | J51: ー | K51: □ | L51: □ | M51: □ | N51: ー | O51: □ | P51: ー
C52: さんにち割 | D52: 開局 | E52: =ROW()-3 -> 49 | F52: 開局レシートを確認 | G52: 「さんにち割引」が表示されていること 対象日付が表示されていること | H52: ー | I52: ー | J52: ー | K52: ー | L52: ー | M52: ー | N52: ー | O52: ー | P52: ー | U52: パッケージ系(PS)で実施
D53: 小計自動値引 | E53: =ROW()-3 -> 50 | F53: ingfan会員バーコードで会員登録 | G53: 自動小計値引が反映されないこと | H53: □ | I53: ー | J53: ー | K53: □ | L53: □ | M53: □ | N53: ー | O53: □ | P53: ー
E54: =ROW()-3 -> 51 | F54: Vカードで会員登録 | G54: 自動小計値引（5%）が反映されること | H54: □ | I54: ー | J54: ー | K54: □ | L54: □ | M54: □ | N54: ー | O54: □ | P54: ー
B55: 自動釣銭釣札機 | C55: POS連携 | D55: 預り金処理 | E55: =ROW()-3 -> 52 | F55: 預り金を投入 | G55: 正常に処理が完了すること。お釣りが正しく出金されること | H55: ー | I55: ー | J55: ー | K55: ー | L55: ー | M55: ー | N55: ー | O55: ー | P55: ー
B56: （POS / RT-300） | D56: 入金処理（Xモード） | E56: =ROW()-3 -> 53 | F56: 入金処理（Xモード） | G56: 正常に処理が完了すること。 | H56: ー | I56: ー | J56: ー | K56: ー | L56: ー | M56: ー | N56: ー | O56: ー | P56: ー
D57: 在高点検 | E57: =ROW()-3 -> 54 | F57: 在高点検（Xモード） | G57: 正常に処理が完了すること。 | H57: ー | I57: ー | J57: ー | K57: ー | L57: ー | M57: ー | N57: ー | O57: ー | P57: ー
D58: 全回収 | E58: =ROW()-3 -> 55 | F58: 全回収（Zモード） | G58: 正常に処理が完了すること。 | H58: ー | I58: ー | J58: ー | K58: ー | L58: ー | M58: ー | N58: ー | O58: ー | P58: ー
D59: 紙幣途中回収（移動） | E59: =ROW()-3 -> 56 | F59: 紙幣途中回収（移動）（Zモード） | G59: 正常に処理が完了すること。 | H59: ー | I59: ー | J59: ー | K59: ー | L59: ー | M59: ー | N59: ー | O59: ー | P59: ー
D60: 硬貨途中回収 | E60: =ROW()-3 -> 57 | F60: 硬貨途中回収（Zモード） | G60: 正常に処理が完了すること。 | H60: ー | I60: ー | J60: ー | K60: ー | L60: ー | M60: ー | N60: ー | O60: ー | P60: ー
D61: ボックス回収 | E61: =ROW()-3 -> 58 | F61: ボックス回収（Zモード） | G61: 正常に処理が完了すること。 | H61: ー | I61: ー | J61: ー | K61: ー | L61: ー | M61: ー | N61: ー | O61: ー | P61: ー
D62: 出金処理 | E62: =ROW()-3 -> 59 | F62: 出金処理（Zモード） | G62: 正常に処理が完了すること。 | H62: ー | I62: ー | J62: ー | K62: ー | L62: ー | M62: ー | N62: ー | O62: ー | P62: ー
D63: あふれ金収納庫移動 | E63: =ROW()-3 -> 60 | F63: あふれ金収納庫移動（Zモード） | G63: メニューに無いことを確認する。 | H63: ー | I63: ー | J63: ー | K63: ー | L63: ー | M63: ー | N63: ー | O63: ー | P63: ー
B64: 自動釣銭釣札機 | C64: POS連携 | D64: 預り金処理 | E64: =ROW()-3 -> 61 | F64: 預り金を投入 | G64: 正常に処理が完了すること。お釣りが正しく出金されること | H64: □ | I64: ー | J64: ー | K64: ー | L64: □ | M64: □ | N64: ー | O64: ー | P64: ー
B65: （PS / RT-380） | D65: 入金処理（Xモード） | E65: =ROW()-3 -> 62 | F65: 入金処理（Xモード） | G65: 正常に処理が完了すること。 | H65: □ | I65: ー | J65: ー | K65: ー | L65: ー | M65: ー | N65: ー | O65: ー | P65: ー
D66: 在高点検 | E66: =ROW()-3 -> 63 | F66: 在高点検（Xモード） | G66: 正常に処理が完了すること。 | H66: □ | I66: ー | J66: ー | K66: ー | L66: □ | M66: □ | N66: ー | O66: ー | P66: ー
D67: 全回収 | E67: =ROW()-3 -> 64 | F67: 全回収（Zモード） | G67: 正常に処理が完了すること。 | H67: □ | I67: ー | J67: ー | K67: ー | L67: ー | M67: ー | N67: ー | O67: ー | P67: ー
D68: 紙幣途中回収（移動） | E68: =ROW()-3 -> 65 | F68: 紙幣途中回収（移動）（Zモード） | G68: 正常に処理が完了すること。 | H68: □ | I68: ー | J68: ー | K68: ー | L68: ー | M68: ー | N68: ー | O68: ー | P68: ー
D69: 硬貨途中回収 | E69: =ROW()-3 -> 66 | F69: 硬貨途中回収（Zモード） | G69: 正常に処理が完了すること。 | H69: □ | I69: ー | J69: ー | K69: ー | L69: ー | M69: ー | N69: ー | O69: ー | P69: ー
D70: ボックス回収 | E70: =ROW()-3 -> 67 | F70: ボックス回収（Zモード） | G70: 正常に処理が完了すること。 | H70: □ | I70: ー | J70: ー | K70: ー | L70: ー | M70: ー | N70: ー | O70: ー | P70: ー
D71: 出金処理 | E71: =ROW()-3 -> 68 | F71: 出金処理（Zモード） | G71: 正常に処理が完了すること。 | H71: □ | I71: ー | J71: ー | K71: ー | L71: ー | M71: ー | N71: ー | O71: ー | P71: ー
D72: あふれ金収納庫移動 | E72: =ROW()-3 -> 69 | F72: あふれ金収納庫移動（Zモード） | G72: メニューに無いことを確認する。 | H72: ー | I72: ー | J72: ー | K72: □ | L72: ー | M72: ー | N72: ー | O72: ー | P72: ー
H73: ー | I73: ー | J73: ー | K73: ー | L73: ー | M73: ー | N73: ー | O73: ー | P73: ー
B74: 消化ﾃｽﾄ項目数： | D74: =SUM(H76:P76) -> 0 | G74: OK数： | H74: =COUNTIF(H4:H73,"●")+COUNTIF(H4:H73,"■")+COUNTIF(H4:H73,"OK") -> 0 | I74: =COUNTIF(I4:I73,"●")+COUNTIF(I4:I73,"■")+COUNTIF(I4:I73,"OK") -> 0 | J74: =COUNTIF(J4:J73,"●")+COUNTIF(J4:J73,"■")+COUNTIF(J4:J73,"OK") -> 0 | K74: =COUNTIF(K4:K73,"●")+COUNTIF(K4:K73,"■")+COUNTIF(K4:K73,"OK") -> 0 | L74: =COUNTIF(L4:L73,"●")+COUNTIF(L4:L73,"■")+COUNTIF(L4:L73,"OK") -> 0 | M74: =COUNTIF(M4:M73,"●")+COUNTIF(M4:M73,"■")+COUNTIF(M4:M73,"OK") -> 0 | N74: =COUNTIF(N4:N73,"●")+COUNTIF(N4:N73,"■")+COUNTIF(N4:N73,"OK") -> 0 | O74: =COUNTIF(O4:O73,"●")+COUNTIF(O4:O73,"■")+COUNTIF(O4:O73,"OK") -> 0 | P74: =COUNTIF(P4:P73,"●")+COUNTIF(P4:P73,"■")+COUNTIF(P4:P73,"OK") -> 0 | Q74: 合計
G75: NG数： | H75: =COUNTIF(H4:H73,"×")+COUNTIF(H4:H73,"NG") -> 0 | I75: =COUNTIF(I55:I73,"×")+COUNTIF(I55:I73,"NG") -> 0 | J75: =COUNTIF(J55:J73,"×")+COUNTIF(J55:J73,"NG") -> 0 | K75: =COUNTIF(K55:K73,"×")+COUNTIF(K55:K73,"NG") -> 0 | L75: =COUNTIF(L55:L73,"×")+COUNTIF(L55:L73,"NG") -> 0 | M75: =COUNTIF(M55:M73,"×")+COUNTIF(M55:M73,"NG") -> 0 | N75: =COUNTIF(N55:N73,"×")+COUNTIF(N55:N73,"NG") -> 0 | O75: =COUNTIF(O55:O73,"×")+COUNTIF(O55:O73,"NG") -> 0 | P75: =COUNTIF(P55:P73,"×")+COUNTIF(P55:P73,"NG") -> 0
B76: 全ﾃｽﾄ項目数： | D76: =SUM(H77:P77) -> 159 | G76: 消化項目数： | H76: =H74+H75 -> 0 | I76: =I74+I75 -> 0 | J76: =J74+J75 -> 0 | K76: =K74+K75 -> 0 | L76: =L74+L75 -> 0 | M76: =M74+M75 -> 0 | N76: =N74+N75 -> 0 | O76: =O74+O75 -> 0 | P76: =P74+P75 -> 0 | Q76: =COUNTA(Q4:Q73) -> 0 | R76: =COUNTA(R4:R73) -> 0 | S76: =COUNTA(S4:S73) -> 0
G77: 全項目数： | H77: =COUNTBLANK(H4:H73)+H76+COUNTIF(H4:H73,"□") -> 50 | I77: =COUNTBLANK(I4:I73)+I76+COUNTIF(I4:I73,"□") -> 0 | J77: =COUNTBLANK(J4:J73)+J76+COUNTIF(J4:J73,"□") -> 0 | K77: =COUNTBLANK(K4:K73)+K76+COUNTIF(K4:K73,"□") -> 6 | L77: =COUNTBLANK(L4:L73)+L76+COUNTIF(L4:L73,"□") -> 43 | M77: =COUNTBLANK(M4:M73)+M76+COUNTIF(M4:M73,"□") -> 43 | N77: =COUNTBLANK(N4:N73)+N76+COUNTIF(N4:N73,"□") -> 0 | O77: =COUNTBLANK(O4:O73)+O76+COUNTIF(O4:O73,"□") -> 17 | P77: =COUNTBLANK(P4:P73)+P76+COUNTIF(P4:P73,"□") -> 0

Sheet Win10対応_フルセルフ
B1: いなげや様 Win10対応（POS/SS/PS/CS） リグレッションテスト仕様書
B2: 大分類 | C2: 中分類 | D2: 小分類 | E2: テスト項目 | H2: CS | Q2: チェック日付 | T2: 担当 | U2: 備考
E3: No | F3: POS操作 | G3: 結果 | H3: 動作 | I3: DB | J3: ｶｽﾀﾏ | K3: 画面 | L3: ﾚｼｰﾄ | M3: ｼﾞｬｰﾅﾙ | N3: 音声 | O3: ﾛｸﾞ | P3: 小型 LCD | Q3: OK | R3: NG | S3: 修正 OK
B4: フルセルフ | C4: 開局 | E4: =ROW()-3 -> 1 | F4: 開局処理 | G4: 正常に開局されること。決済端末が待機画面になること。 | H4: □ | I4: ー | J4: ー | K4: □ | L4: □ | M4: □ | N4: ー | O4: ー | P4: ー
B5: （通常操作） | C5: 会員番号登録 | D5: Vカード | E5: =ROW()-3 -> 2 | F5: Vカードで会員登録 | G5: 正常に会員登録できること | H5: □ | I5: ー | J5: ー | K5: □ | L5: □ | M5: □ | N5: ー | O5: ー | P5: ー
C6: 支払い操作 | D6: 会員宣言：なし Vカード支払い（IC） | E6: =ROW()-3 -> 3 | F6: VカードをICで読み込み | G6: 正常に支払いが完了し売上登録できること | H6: ー | I6: ー | J6: ー | K6: ー | L6: ー | M6: ー | N6: ー | O6: ー | P6: ー | U6: 会員宣言ない場合Vカード支払不可
D7: 会員宣言：なし 他クレ支払い（IC） | E7: =ROW()-3 -> 4 | F7: 他クレカードをICで読み込み | G7: 正常に支払いが完了し売上登録できること | H7: □ | I7: ー | J7: ー | K7: ー | L7: □ | M7: □ | N7: ー | O7: ー | P7: ー
D8: 会員宣言：ingカード（ﾀｯﾁｽｷｬﾅ） 他クレ支払い（MSR） | E8: =ROW()-3 -> 5 | F8: 他クレカードをMSRで読み込み | G8: 正常に支払いが完了し売上登録できること | H8: □ | I8: ー | J8: ー | K8: ー | L8: □ | M8: □ | N8: ー | O8: ー | P8: ー
D9: 会員宣言：Vカード Vカード支払い（IC） | E9: =ROW()-3 -> 6 | F9: VカードをICで読み込み | G9: 正常に支払いが完了し売上登録できること | H9: □ | I9: ー | J9: ー | K9: ー | L9: □ | M9: □ | N9: ー | O9: ー | P9: ー | U9: 蒲田環境VカードIC支払不可、VカードMS支払
D10: 会員宣言：Vカード 他クレ支払い（MSR） | E10: =ROW()-3 -> 7 | F10: 他クレカードをMSRで読み込み | G10: 正常に支払いが完了し売上登録できること | H10: □ | I10: ー | J10: ー | K10: ー | L10: □ | M10: □ | N10: ー | O10: ー | P10: ー
C11: 通番取消 | D11: 会員宣言：なし Vカード支払い（IC） | E11: =ROW()-3 -> 8 | F11: 元取引と同じVカードをICで読み込み | G11: 正常に取消処理が完了すること | H11: ー | I11: ー | J11: ー | K11: ー | L11: ー | M11: ー | N11: ー | O11: ー | P11: ー | U11: 会員宣言ない場合Vカード支払不可
D12: 会員宣言：なし 他クレ支払い（IC） | E12: =ROW()-3 -> 9 | F12: 元取引と同じ他クレカードをICで読み込み | G12: 正常に取消処理が完了すること | H12: □ | I12: ー | J12: ー | K12: ー | L12: □ | M12: □ | N12: ー | O12: ー | P12: ー
D13: 会員宣言：ingカード（ﾀｯﾁｽｷｬﾅ） 他クレ支払い（MSR） | E13: =ROW()-3 -> 10 | F13: 元取引と同じ他クレカードをMSRで読み込み | G13: 正常に取消処理が完了すること | H13: □ | I13: ー | J13: ー | K13: ー | L13: □ | M13: □ | N13: ー | O13: ー | P13: ー
D14: 会員宣言：Vカード Vカード支払い（IC） | E14: =ROW()-3 -> 11 | F14: 元取引と同じVカードをICで読み込み | G14: 正常に取消処理が完了すること | H14: □ | I14: ー | J14: ー | K14: ー | L14: □ | M14: □ | N14: ー | O14: ー | P14: ー | U14: 蒲田環境のVカードはIC支払はできないがIC取消は可
D15: 会員宣言：Vカード 他クレ支払い（MSR） | E15: =ROW()-3 -> 12 | F15: 元取引と同じ他クレカードをMSRで読み込み | G15: 正常に取消処理が完了すること | H15: □ | I15: ー | J15: ー | K15: ー | L15: □ | M15: □ | N15: ー | O15: ー | P15: ー
C16: 通番修正 | D16: 元取引がVカード支払い | E16: =ROW()-3 -> 13 | F16: 元取引と同じVカードで通番取消、同じVカードで支払い | G16: 元取引の取消処理と修正後の取引が正常に完了すること | H16: □ | I16: ー | J16: ー | K16: ー | L16: □ | M16: □ | N16: ー | O16: ー | P16: ー
E17: =ROW()-3 -> 14 | F17: 元取引と同じVカードで通番取消、他クレカードで支払い | G17: 元取引の取消処理と修正後の取引が正常に完了すること | H17: □ | I17: ー | J17: ー | K17: ー | L17: □ | M17: □ | N17: ー | O17: ー | P17: ー
E18: =ROW()-3 -> 15 | F18: 元取引と同じVカードで通番取消、現金で支払い | G18: 元取引の取消処理と修正後の取引が正常に完了すること | H18: □ | I18: ー | J18: ー | K18: ー | L18: □ | M18: □ | N18: ー | O18: ー | P18: ー
D19: 元取引が他クレ支払い | E19: =ROW()-3 -> 16 | F19: 元取引と同じ他クレで通番取消、同じカードで支払い | G19: 元取引の取消処理と修正後の取引が正常に完了すること | H19: □ | I19: ー | J19: ー | K19: ー | L19: □ | M19: □ | N19: ー | O19: ー | P19: ー
E20: =ROW()-3 -> 17 | F20: 元取引と同じ他クレで通番取消、Vカードで支払い | G20: 元取引の取消処理と修正後の取引が正常に完了すること | H20: □ | I20: ー | J20: ー | K20: ー | L20: □ | M20: □ | N20: ー | O20: ー | P20: ー
E21: =ROW()-3 -> 18 | F21: 元取引と同じ他クレで通番取消、現金で支払い | G21: 元取引の取消処理と修正後の取引が正常に完了すること | H21: □ | I21: ー | J21: ー | K21: ー | L21: □ | M21: □ | N21: ー | O21: ー | P21: ー
B22: 練習モード | C22: 会員番号登録 | D22: Vカード | E22: =ROW()-3 -> 19 | F22: Vカードで会員登録 | G22: 正常に会員登録できること | H22: □ | I22: ー | J22: ー | K22: □ | L22: □ | M22: □ | N22: ー | O22: ー | P22: ー
C23: 支払い操作 | D23: 会員宣言：なし Vカード支払い（IC） | E23: =ROW()-3 -> 20 | F23: VカードをICで読み込み | G23: 練習：正常に支払いが完了し売上登録できること | H23: ー | I23: ー | J23: ー | K23: ー | L23: ー | M23: ー | N23: ー | O23: ー | P23: ー | U23: 会員宣言ない場合Vカード支払不可
D24: 会員宣言：ingカード（ﾀｯﾁｽｷｬﾅ） Vカード支払い（IC） | E24: =ROW()-3 -> 21 | F24: VカードをICで読み込み | G24: 練習：正常に支払いが完了し売上登録できること | H24: ー | I24: ー | J24: ー | K24: ー | L24: ー | M24: ー | N24: ー | O24: ー | P24: ー | U24: (練習)ペイメントモードではfanカード宣言Ｖカード支払不可
D25: 会員宣言：ingカード（ﾀｯﾁｽｷｬﾅ） 他クレ支払い（MSR） | E25: =ROW()-3 -> 22 | F25: 他クレカードをMSRで読み込み | G25: 練習：正常に支払いが完了し売上登録できること | H25: □ | I25: ー | J25: ー | K25: ー | L25: □ | M25: □ | N25: ー | O25: ー | P25: ー
D26: 会員宣言：Vカード Vカード支払い（IC） | E26: =ROW()-3 -> 23 | F26: VカードをICで読み込み | G26: 練習：正常に支払いが完了し売上登録できること | H26: □ | I26: ー | J26: ー | K26: ー | L26: □ | M26: □ | N26: ー | O26: ー | P26: ー
D27: 会員宣言：Vカード 他クレ支払い（MSR） | E27: =ROW()-3 -> 24 | F27: 他クレカードをMSRで読み込み | G27: 練習：正常に支払いが完了し売上登録できること | H27: □ | I27: ー | J27: ー | K27: ー | L27: □ | M27: □ | N27: ー | O27: ー | P27: ー
C28: 通番取消 | D28: 元取引：会員宣言なし Vカード支払い | E28: =ROW()-3 -> 25 | F28: 元取引と同じVカードをICで読み込み | G28: 練習：正常に取消処理が完了すること | H28: ー | I28: ー | J28: ー | K28: ー | L28: ー | M28: ー | N28: ー | O28: ー | P28: ー | U28: 会員宣言ない場合Vカード支払不可
D29: 元取引：ingカードで会員宣言 Vカード支払い | E29: =ROW()-3 -> 26 | F29: 元取引と同じVカードをMSRで読み込み | G29: 練習：正常に取消処理が完了すること | H29: ー | I29: ー | J29: ー | K29: ー | L29: ー | M29: ー | N29: ー | O29: ー | P29: ー | U29: (練習)ペイメントモードではfanカード宣言Ｖカード支払不可
D30: 元取引：会員宣言なし 他クレ支払い | E30: =ROW()-3 -> 27 | F30: 元取引と同じ他クレカードをMSRで読み込み | G30: 練習：正常に取消処理が完了すること | H30: □ | I30: ー | J30: ー | K30: ー | L30: □ | M30: □ | N30: ー | O30: ー | P30: ー
D31: 元取引がVカードで会員宣言 他クレ支払い | E31: =ROW()-3 -> 28 | F31: 元取引と同じ他クレカードをMSRで読み込み | G31: 練習：正常に取消処理が完了すること | H31: □ | I31: ー | J31: ー | K31: ー | L31: □ | M31: □ | N31: ー | O31: ー | P31: ー
C32: 通番修正 | D32: 元取引がVカード支払い | E32: =ROW()-3 -> 29 | F32: 元取引と同じVカードで通番取消、同じVカードで支払い | G32: 練習：元取引の取消処理と修正後の取引が正常に完了すること | H32: □ | I32: ー | J32: ー | K32: ー | L32: □ | M32: □ | N32: ー | O32: ー | P32: ー
E33: =ROW()-3 -> 30 | F33: 元取引と同じVカードで通番取消、他クレカードで支払い | G33: 練習：元取引の取消処理と修正後の取引が正常に完了すること | H33: □ | I33: ー | J33: ー | K33: ー | L33: □ | M33: □ | N33: ー | O33: ー | P33: ー
D34: 元取引が他クレ支払い | E34: =ROW()-3 -> 31 | F34: 元取引と同じ他クレで通番取消、Vカードで支払い | G34: 練習：元取引の取消処理と修正後の取引が正常に完了すること | H34: □ | I34: ー | J34: ー | K34: ー | L34: □ | M34: □ | N34: ー | O34: ー | P34: ー
E35: =ROW()-3 -> 32 | F35: 元取引と同じ他クレで通番取消、現金で支払い | G35: 練習：元取引の取消処理と修正後の取引が正常に完了すること | H35: □ | I35: ー | J35: ー | K35: ー | L35: □ | M35: □ | N35: ー | O35: ー | P35: ー
B36: Satisfa | C36: 開局 | E36: =ROW()-3 -> 33 | F36: 開局処理 | G36: POS開局時にエラーが発生しないこと | H36: □ | I36: ー | J36: ー | K36: ー | L36: ー | M36: ー | N36: ー | O36: □ | P36: ー
C37: 会員番号登録 | D37: Vカード | E37: =ROW()-3 -> 34 | F37: Vカードで会員登録 | G37: 正常に会員登録できること。現在ポイントが正しく表示されること | H37: □ | I37: ー | J37: ー | K37: ー | L37: □ | M37: □ | N37: ー | O37: □ | P37: ー
D38: ingfanカード | E38: =ROW()-3 -> 35 | F38: ingfan会員バーコードで会員登録 | G38: 正常に会員登録できること。現在ポイントが正しく表示されること | H38: □ | I38: ー | J38: ー | K38: ー | L38: □ | M38: □ | N38: ー | O38: □ | P38: ー
D39: 手入力 | E39: =ROW()-3 -> 36 | F39: 手入力で会員登録 | G39: 正常に会員登録できること。現在ポイントが正しく表示されること | H39: □ | I39: ー | J39: ー | K39: ー | L39: □ | M39: □ | N39: ー | O39: □ | P39: ー | U39: POSモードで手入力可能
C40: ポイント付与 | D40: Vカード | E40: =ROW()-3 -> 37 | F40: Vカードで会員登録 | G40: 正常に取引が完了すること。今回ポイントが正しく付与されること | H40: □ | I40: ー | J40: ー | K40: ー | L40: □ | M40: □ | N40: ー | O40: □ | P40: ー
D41: ingfanカード | E41: =ROW()-3 -> 38 | F41: ingfan会員バーコードで会員登録 | G41: 正常に取引が完了すること。今回ポイントが正しく付与されること | H41: □ | I41: ー | J41: ー | K41: ー | L41: □ | M41: □ | N41: ー | O41: □ | P41: ー
D42: 手入力 | E42: =ROW()-3 -> 39 | F42: 手入力で会員登録 | G42: 正常に取引が完了すること。今回ポイントが正しく付与されること | H42: □ | I42: ー | J42: ー | K42: ー | L42: □ | M42: □ | N42: ー | O42: □ | P42: ー | U42: POSモードで手入力可能
C43: ポイント利用 | D43: Vカード | E43: =ROW()-3 -> 40 | F43: Vカードで会員登録 | G43: 正常に取引が完了すること。ポイント利用分が正しく反映されること | H43: □ | I43: ー | J43: ー | K43: ー | L43: □ | M43: □ | N43: ー | O43: □ | P43: ー
D44: ingfanカード | E44: =ROW()-3 -> 41 | F44: ingfan会員バーコードで会員登録 | G44: 正常に取引が完了すること。ポイント利用分が正しく反映されること | H44: □ | I44: ー | J44: ー | K44: ー | L44: □ | M44: □ | N44: ー | O44: □ | P44: ー
D45: 手入力 | E45: =ROW()-3 -> 42 | F45: 手入力で会員登録 | G45: 正常に取引が完了すること。ポイント利用分が正しく反映されること | H45: □ | I45: ー | J45: ー | K45: ー | L45: □ | M45: □ | N45: ー | O45: □ | P45: ー
C46: ポイント修正 | D46: Vカード | E46: =ROW()-3 -> 43 | F46: Vカードで会員登録 | G46: 正常に処理が完了すること。ポイント修正結果が正しく反映されること | H46: □ | I46: ー | J46: ー | K46: ー | L46: □ | M46: □ | N46: ー | O46: □ | P46: ー
D47: ingfanカード | E47: =ROW()-3 -> 44 | F47: ingfan会員バーコードで会員登録 | G47: 正常に処理が完了すること。ポイント修正結果が正しく反映されること | H47: □ | I47: ー | J47: ー | K47: ー | L47: □ | M47: □ | N47: ー | O47: □ | P47: ー
D48: 手入力 | E48: =ROW()-3 -> 45 | F48: 手入力で会員登録 | G48: 正常に処理が完了すること。ポイント修正結果が正しく反映されること | H48: □ | I48: ー | J48: ー | K48: ー | L48: □ | M48: □ | N48: ー | O48: □ | P48: ー
C49: レジマイナス | D49: 会員宣言なし | E49: =ROW()-3 -> 46 | F49: 会員宣言しない | G49: 正常にマイナス処理が完了すること | H49: □ | I49: ー | J49: ー | K49: □ | L49: □ | M49: □ | N49: ー | O49: □ | P49: ー
D50: ingカードで会員宣言 | E50: =ROW()-3 -> 47 | F50: ingfan会員バーコードで会員宣言 | G50: 正常にマイナス処理が完了すること（現在ポイントが減算されること） | H50: □ | I50: ー | J50: ー | K50: □ | L50: □ | M50: □ | N50: ー | O50: □ | P50: ー
D51: Vカードで会員宣言 | E51: =ROW()-3 -> 48 | F51: Vカードで会員宣言 | G51: 正常にマイナス処理が完了すること （現在ポイントが200円1ポイントで減算されること） | H51: □ | I51: ー | J51: ー | K51: □ | L51: □ | M51: □ | N51: ー | O51: □ | P51: ー
C52: さんにち割 | D52: 開局 | E52: =ROW()-3 -> 49 | F52: 開局レシートを確認 | G52: 「さんにち割引」が表示されていること 対象日付が表示されていること | H52: □ | I52: ー | J52: ー | K52: □ | L52: □ | M52: □ | N52: ー | O52: □ | P52: ー
D53: 小計自動値引 | E53: =ROW()-3 -> 50 | F53: ingfan会員バーコードで会員登録 | G53: 自動小計値引が反映されないこと | H53: □ | I53: ー | J53: ー | K53: □ | L53: □ | M53: □ | N53: ー | O53: □ | P53: ー
E54: =ROW()-3 -> 51 | F54: Vカードで会員登録 | G54: 自動小計値引（5%）が反映されること | H54: □ | I54: ー | J54: ー | K54: □ | L54: □ | M54: □ | N54: ー | O54: □ | P54: ー
B55: 自動釣銭釣札機 | C55: POS連携 | D55: 預り金処理 | E55: =ROW()-3 -> 52 | F55: 預り金を投入 | G55: 正常に処理が完了すること。お釣りが正しく出金されること | H55: ー | I55: ー | J55: ー | K55: ー | L55: ー | M55: ー | N55: ー | O55: ー | P55: ー
B56: （POS / RT-300） | D56: 入金処理（Xモード） | E56: =ROW()-3 -> 53 | F56: 入金処理（Xモード） | G56: 正常に処理が完了すること。 | H56: ー | I56: ー | J56: ー | K56: ー | L56: ー | M56: ー | N56: ー | O56: ー | P56: ー
D57: 在高点検 | E57: =ROW()-3 -> 54 | F57: 在高点検（Xモード） | G57: 正常に処理が完了すること。 | H57: ー | I57: ー | J57: ー | K57: ー | L57: ー | M57: ー | N57: ー | O57: ー | P57: ー
D58: 全回収 | E58: =ROW()-3 -> 55 | F58: 全回収（Zモード） | G58: 正常に処理が完了すること。 | H58: ー | I58: ー | J58: ー | K58: ー | L58: ー | M58: ー | N58: ー | O58: ー | P58: ー
D59: 紙幣途中回収（移動） | E59: =ROW()-3 -> 56 | F59: 紙幣途中回収（移動）（Zモード） | G59: 正常に処理が完了すること。 | H59: ー | I59: ー | J59: ー | K59: ー | L59: ー | M59: ー | N59: ー | O59: ー | P59: ー
D60: 硬貨途中回収 | E60: =ROW()-3 -> 57 | F60: 硬貨途中回収（Zモード） | G60: 正常に処理が完了すること。 | H60: ー | I60: ー | J60: ー | K60: ー | L60: ー | M60: ー | N60: ー | O60: ー | P60: ー
D61: ボックス回収 | E61: =ROW()-3 -> 58 | F61: ボックス回収（Zモード） | G61: 正常に処理が完了すること。 | H61: ー | I61: ー | J61: ー | K61: ー | L61: ー | M61: ー | N61: ー | O61: ー | P61: ー
D62: 出金処理 | E62: =ROW()-3 -> 59 | F62: 出金処理（Zモード） | G62: 正常に処理が完了すること。 | H62: ー | I62: ー | J62: ー | K62: ー | L62: ー | M62: ー | N62: ー | O62: ー | P62: ー
D63: あふれ金収納庫移動 | E63: =ROW()-3 -> 60 | F63: あふれ金収納庫移動（Zモード） | G63: メニューに無いことを確認する。 | H63: ー | I63: ー | J63: ー | K63: ー | L63: ー | M63: ー | N63: ー | O63: ー | P63: ー
B64: 自動釣銭釣札機 | C64: POS連携 | D64: 預り金処理 | E64: =ROW()-3 -> 61 | F64: 預り金を投入 | G64: 正常に処理が完了すること。お釣りが正しく出金されること | H64: □ | I64: ー | J64: ー | K64: ー | L64: □ | M64: □ | N64: ー | O64: ー | P64: ー
B65: （PS / RT-380） | D65: 入金処理（Xモード） | E65: =ROW()-3 -> 62 | F65: 入金処理（Xモード） | G65: 正常に処理が完了すること。 | H65: □ | I65: ー | J65: ー | K65: ー | L65: ー | M65: ー | N65: ー | O65: ー | P65: ー
D66: 在高点検 | E66: =ROW()-3 -> 63 | F66: 在高点検（Xモード） | G66: 正常に処理が完了すること。 | H66: □ | I66: ー | J66: ー | K66: ー | L66: □ | M66: □ | N66: ー | O66: ー | P66: ー
D67: 全回収 | E67: =ROW()-3 -> 64 | F67: 全回収（Zモード） | G67: 正常に処理が完了すること。 | H67: □ | I67: ー | J67: ー | K67: ー | L67: □ | M67: □ | N67: ー | O67: ー | P67: ー
D68: 紙幣途中回収（移動） | E68: =ROW()-3 -> 65 | F68: 紙幣途中回収（移動）（Zモード） | G68: 正常に処理が完了すること。 | H68: □ | I68: ー | J68: ー | K68: ー | L68: □ | M68: □ | N68: ー | O68: ー | P68: ー
D69: 硬貨途中回収 | E69: =ROW()-3 -> 66 | F69: 硬貨途中回収（Zモード） | G69: 正常に処理が完了すること。 | H69: □ | I69: ー | J69: ー | K69: ー | L69: □ | M69: □ | N69: ー | O69: ー | P69: ー
D70: ボックス回収 | E70: =ROW()-3 -> 67 | F70: ボックス回収（Zモード） | G70: 正常に処理が完了すること。 | H70: □ | I70: ー | J70: ー | K70: ー | L70: ー | M70: ー | N70: ー | O70: ー | P70: ー
D71: 出金処理 | E71: =ROW()-3 -> 68 | F71: 出金処理（Zモード） | G71: 正常に処理が完了すること。 | H71: □ | I71: ー | J71: ー | K71: ー | L71: □ | M71: □ | N71: ー | O71: ー | P71: ー
D72: あふれ金収納庫移動 | E72: =ROW()-3 -> 69 | F72: あふれ金収納庫移動（Zモード） | G72: メニューに無いことを確認する。 | H72: ー | I72: ー | J72: ー | K72: □ | L72: ー | M72: ー | N72: ー | O72: ー | P72: ー
B73: disk2264 | C73: 定時送信 | F73: 商品一覧画面で定時送信時刻に到達する | G73: 定位送信が実施されないこと | H73: □ | I73: ー | J73: ー | K73: □ | L73: ー | M73: ー | N73: ー | O73: ー | P73: ー
H74: ー | I74: ー | J74: ー | K74: ー | L74: ー | M74: ー | N74: ー | O74: ー | P74: ー
B75: 消化ﾃｽﾄ項目数： | D75: =SUM(H77:P77) -> 0 | G75: OK数： | H75: =COUNTIF(H4:H74,"●")+COUNTIF(H4:H74,"■")+COUNTIF(H4:H74,"OK") -> 0 | I75: =COUNTIF(I4:I74,"●")+COUNTIF(I4:I74,"■")+COUNTIF(I4:I74,"OK") -> 0 | J75: =COUNTIF(J4:J74,"●")+COUNTIF(J4:J74,"■")+COUNTIF(J4:J74,"OK") -> 0 | K75: =COUNTIF(K4:K74,"●")+COUNTIF(K4:K74,"■")+COUNTIF(K4:K74,"OK") -> 0 | L75: =COUNTIF(L4:L74,"●")+COUNTIF(L4:L74,"■")+COUNTIF(L4:L74,"OK") -> 0 | M75: =COUNTIF(M4:M74,"●")+COUNTIF(M4:M74,"■")+COUNTIF(M4:M74,"OK") -> 0 | N75: =COUNTIF(N4:N74,"●")+COUNTIF(N4:N74,"■")+COUNTIF(N4:N74,"OK") -> 0 | O75: =COUNTIF(O4:O74,"●")+COUNTIF(O4:O74,"■")+COUNTIF(O4:O74,"OK") -> 0 | P75: =COUNTIF(P4:P74,"●")+COUNTIF(P4:P74,"■")+COUNTIF(P4:P74,"OK") -> 0 | Q75: 合計
G76: NG数： | H76: =COUNTIF(H4:H74,"×")+COUNTIF(H4:H74,"NG") -> 0 | I76: =COUNTIF(I4:I74,"×")+COUNTIF(I4:I74,"NG") -> 0 | J76: =COUNTIF(J4:J74,"×")+COUNTIF(J4:J74,"NG") -> 0 | K76: =COUNTIF(K4:K74,"×")+COUNTIF(K4:K74,"NG") -> 0 | L76: =COUNTIF(L4:L74,"×")+COUNTIF(L4:L74,"NG") -> 0 | M76: =COUNTIF(M4:M74,"×")+COUNTIF(M4:M74,"NG") -> 0 | N76: =COUNTIF(N4:N74,"×")+COUNTIF(N4:N74,"NG") -> 0 | O76: =COUNTIF(O4:O74,"×")+COUNTIF(O4:O74,"NG") -> 0 | P76: =COUNTIF(P4:P74,"×")+COUNTIF(P4:P74,"NG") -> 0
B77: 全ﾃｽﾄ項目数： | D77: =SUM(H78:P78) -> 184 | G77: 消化項目数： | H77: =H75+H76 -> 0 | I77: =I75+I76 -> 0 | J77: =J75+J76 -> 0 | K77: =K75+K76 -> 0 | L77: =L75+L76 -> 0 | M77: =M75+M76 -> 0 | N77: =N75+N76 -> 0 | O77: =O75+O76 -> 0 | P77: =P75+P76 -> 0 | Q77: =COUNTA(Q4:Q74) -> 0 | R77: =COUNTA(R4:R74) -> 0 | S77: =COUNTA(S4:S74) -> 0
G78: 全項目数： | H78: =COUNTBLANK(H4:H74)+H77+COUNTIF(H4:H74,"□") -> 54 | I78: =COUNTBLANK(I4:I74)+I77+COUNTIF(I4:I74,"□") -> 0 | J78: =COUNTBLANK(J4:J74)+J77+COUNTIF(J4:J74,"□") -> 0 | K78: =COUNTBLANK(K4:K74)+K77+COUNTIF(K4:K74,"□") -> 11 | L78: =COUNTBLANK(L4:L74)+L77+COUNTIF(L4:L74,"□") -> 50 | M78: =COUNTBLANK(M4:M74)+M77+COUNTIF(M4:M74,"□") -> 50 | N78: =COUNTBLANK(N4:N74)+N77+COUNTIF(N4:N74,"□") -> 0 | O78: =COUNTBLANK(O4:O74)+O77+COUNTIF(O4:O74,"□") -> 19 | P78: =COUNTBLANK(P4:P74)+P77+COUNTIF(P4:P74,"□") -> 0

Sheet Win10対応_キャッシュレス
B1: いなげや様 Win10対応（POS/SS/PS/CS） リグレッションテスト仕様書
B2: 大分類 | C2: 中分類 | D2: 小分類 | E2: テスト項目 | H2: CS | Q2: チェック日付 | T2: 担当 | U2: 備考
E3: No | F3: POS操作 | G3: 結果 | H3: 動作 | I3: DB | J3: ｶｽﾀﾏ | K3: 画面 | L3: ﾚｼｰﾄ | M3: ｼﾞｬｰﾅﾙ | N3: 音声 | O3: ﾛｸﾞ | P3: 小型 LCD | Q3: OK | R3: NG | S3: 修正 OK
B4: フルセルフ | C4: 開局 | E4: =ROW()-3 -> 1 | F4: 開局処理 | G4: 正常に開局されること。決済端末が待機画面になること。 | H4: □ | I4: ー | J4: ー | K4: □ | L4: □ | M4: □ | N4: ー | O4: ー | P4: ー
B5: （通常操作） | C5: 会員番号登録 | D5: Vカード | E5: =ROW()-3 -> 2 | F5: Vカードで会員登録 | G5: 正常に会員登録できること | H5: □ | I5: ー | J5: ー | K5: □ | L5: □ | M5: □ | N5: ー | O5: ー | P5: ー
C6: 支払い操作 | D6: 会員宣言：なし Vカード支払い（IC） | E6: =ROW()-3 -> 3 | F6: VカードをICで読み込み | G6: 正常に支払いが完了し売上登録できること | H6: ー | I6: ー | J6: ー | K6: ー | L6: ー | M6: ー | N6: ー | O6: ー | P6: ー | U6: 会員宣言ない場合Vカード支払不可
D7: 会員宣言：なし 他クレ支払い（IC） | E7: =ROW()-3 -> 4 | F7: 他クレカードをICで読み込み | G7: 正常に支払いが完了し売上登録できること | H7: □ | I7: ー | J7: ー | K7: ー | L7: □ | M7: □ | N7: ー | O7: ー | P7: ー
D8: 会員宣言：ingカード（ﾀｯﾁｽｷｬﾅ） 他クレ支払い（MSR） | E8: =ROW()-3 -> 5 | F8: 他クレカードをMSRで読み込み | G8: 正常に支払いが完了し売上登録できること | H8: □ | I8: ー | J8: ー | K8: ー | L8: □ | M8: □ | N8: ー | O8: ー | P8: ー
D9: 会員宣言：Vカード Vカード支払い（IC） | E9: =ROW()-3 -> 6 | F9: VカードをICで読み込み | G9: 正常に支払いが完了し売上登録できること | H9: □ | I9: ー | J9: ー | K9: ー | L9: □ | M9: □ | N9: ー | O9: ー | P9: ー | U9: 蒲田環境VカードIC支払不可、VカードMS支払
D10: 会員宣言：Vカード 他クレ支払い（MSR） | E10: =ROW()-3 -> 7 | F10: 他クレカードをMSRで読み込み | G10: 正常に支払いが完了し売上登録できること | H10: □ | I10: ー | J10: ー | K10: ー | L10: □ | M10: □ | N10: ー | O10: ー | P10: ー
C11: 通番取消 | D11: 会員宣言：なし Vカード支払い（IC） | E11: =ROW()-3 -> 8 | F11: 元取引と同じVカードをICで読み込み | G11: 正常に取消処理が完了すること | H11: ー | I11: ー | J11: ー | K11: ー | L11: ー | M11: ー | N11: ー | O11: ー | P11: ー | U11: 会員宣言ない場合Vカード支払不可
D12: 会員宣言：なし 他クレ支払い（IC） | E12: =ROW()-3 -> 9 | F12: 元取引と同じ他クレカードをICで読み込み | G12: 正常に取消処理が完了すること | H12: □ | I12: ー | J12: ー | K12: ー | L12: □ | M12: □ | N12: ー | O12: ー | P12: ー
D13: 会員宣言：ingカード（ﾀｯﾁｽｷｬﾅ） 他クレ支払い（MSR） | E13: =ROW()-3 -> 10 | F13: 元取引と同じ他クレカードをMSRで読み込み | G13: 正常に取消処理が完了すること | H13: □ | I13: ー | J13: ー | K13: ー | L13: □ | M13: □ | N13: ー | O13: ー | P13: ー
D14: 会員宣言：Vカード Vカード支払い（IC） | E14: =ROW()-3 -> 11 | F14: 元取引と同じVカードをICで読み込み | G14: 正常に取消処理が完了すること | H14: □ | I14: ー | J14: ー | K14: ー | L14: □ | M14: □ | N14: ー | O14: ー | P14: ー | U14: 蒲田環境のVカードはIC支払はできないがIC取消は可
D15: 会員宣言：Vカード 他クレ支払い（MSR） | E15: =ROW()-3 -> 12 | F15: 元取引と同じ他クレカードをMSRで読み込み | G15: 正常に取消処理が完了すること | H15: □ | I15: ー | J15: ー | K15: ー | L15: □ | M15: □ | N15: ー | O15: ー | P15: ー
C16: 通番修正 | D16: 元取引がVカード支払い | E16: =ROW()-3 -> 13 | F16: 元取引と同じVカードで通番取消、同じVカードで支払い | G16: 元取引の取消処理と修正後の取引が正常に完了すること | H16: □ | I16: ー | J16: ー | K16: ー | L16: □ | M16: □ | N16: ー | O16: ー | P16: ー
E17: =ROW()-3 -> 14 | F17: 元取引と同じVカードで通番取消、他クレカードで支払い | G17: 元取引の取消処理と修正後の取引が正常に完了すること | H17: □ | I17: ー | J17: ー | K17: ー | L17: □ | M17: □ | N17: ー | O17: ー | P17: ー
E18: =ROW()-3 -> 15 | F18: 元取引と同じVカードで通番取消、現金で支払い | G18: 元取引の取消処理と修正後の取引が正常に完了すること | H18: □ | I18: ー | J18: ー | K18: ー | L18: □ | M18: □ | N18: ー | O18: ー | P18: ー
D19: 元取引が他クレ支払い | E19: =ROW()-3 -> 16 | F19: 元取引と同じ他クレで通番取消、同じカードで支払い | G19: 元取引の取消処理と修正後の取引が正常に完了すること | H19: □ | I19: ー | J19: ー | K19: ー | L19: □ | M19: □ | N19: ー | O19: ー | P19: ー
E20: =ROW()-3 -> 17 | F20: 元取引と同じ他クレで通番取消、Vカードで支払い | G20: 元取引の取消処理と修正後の取引が正常に完了すること | H20: □ | I20: ー | J20: ー | K20: ー | L20: □ | M20: □ | N20: ー | O20: ー | P20: ー
E21: =ROW()-3 -> 18 | F21: 元取引と同じ他クレで通番取消、現金で支払い | G21: 元取引の取消処理と修正後の取引が正常に完了すること | H21: □ | I21: ー | J21: ー | K21: ー | L21: □ | M21: □ | N21: ー | O21: ー | P21: ー
B22: 練習モード | C22: 会員番号登録 | D22: Vカード | E22: =ROW()-3 -> 19 | F22: Vカードで会員登録 | G22: 正常に会員登録できること | H22: □ | I22: ー | J22: ー | K22: □ | L22: □ | M22: □ | N22: ー | O22: ー | P22: ー
C23: 支払い操作 | D23: 会員宣言：なし Vカード支払い（IC） | E23: =ROW()-3 -> 20 | F23: VカードをICで読み込み | G23: 練習：正常に支払いが完了し売上登録できること | H23: ー | I23: ー | J23: ー | K23: ー | L23: ー | M23: ー | N23: ー | O23: ー | P23: ー | U23: 会員宣言ない場合Vカード支払不可
D24: 会員宣言：ingカード（ﾀｯﾁｽｷｬﾅ） Vカード支払い（IC） | E24: =ROW()-3 -> 21 | F24: VカードをICで読み込み | G24: 練習：正常に支払いが完了し売上登録できること | H24: ー | I24: ー | J24: ー | K24: ー | L24: ー | M24: ー | N24: ー | O24: ー | P24: ー | U24: (練習)ペイメントモードではfanカード宣言Ｖカード支払不可
D25: 会員宣言：ingカード（ﾀｯﾁｽｷｬﾅ） 他クレ支払い（MSR） | E25: =ROW()-3 -> 22 | F25: 他クレカードをMSRで読み込み | G25: 練習：正常に支払いが完了し売上登録できること | H25: □ | I25: ー | J25: ー | K25: ー | L25: □ | M25: □ | N25: ー | O25: ー | P25: ー
D26: 会員宣言：Vカード Vカード支払い（IC） | E26: =ROW()-3 -> 23 | F26: VカードをICで読み込み | G26: 練習：正常に支払いが完了し売上登録できること | H26: □ | I26: ー | J26: ー | K26: ー | L26: □ | M26: □ | N26: ー | O26: ー | P26: ー
D27: 会員宣言：Vカード 他クレ支払い（MSR） | E27: =ROW()-3 -> 24 | F27: 他クレカードをMSRで読み込み | G27: 練習：正常に支払いが完了し売上登録できること | H27: □ | I27: ー | J27: ー | K27: ー | L27: □ | M27: □ | N27: ー | O27: ー | P27: ー
C28: 通番取消 | D28: 元取引：会員宣言なし Vカード支払い | E28: =ROW()-3 -> 25 | F28: 元取引と同じVカードをICで読み込み | G28: 練習：正常に取消処理が完了すること | H28: ー | I28: ー | J28: ー | K28: ー | L28: ー | M28: ー | N28: ー | O28: ー | P28: ー | U28: 会員宣言ない場合Vカード支払不可
D29: 元取引：ingカードで会員宣言 Vカード支払い | E29: =ROW()-3 -> 26 | F29: 元取引と同じVカードをMSRで読み込み | G29: 練習：正常に取消処理が完了すること | H29: ー | I29: ー | J29: ー | K29: ー | L29: ー | M29: ー | N29: ー | O29: ー | P29: ー | U29: (練習)ペイメントモードではfanカード宣言Ｖカード支払不可
D30: 元取引：会員宣言なし 他クレ支払い | E30: =ROW()-3 -> 27 | F30: 元取引と同じ他クレカードをMSRで読み込み | G30: 練習：正常に取消処理が完了すること | H30: □ | I30: ー | J30: ー | K30: ー | L30: □ | M30: □ | N30: ー | O30: ー | P30: ー
D31: 元取引がVカードで会員宣言 他クレ支払い | E31: =ROW()-3 -> 28 | F31: 元取引と同じ他クレカードをMSRで読み込み | G31: 練習：正常に取消処理が完了すること | H31: □ | I31: ー | J31: ー | K31: ー | L31: □ | M31: □ | N31: ー | O31: ー | P31: ー
C32: 通番修正 | D32: 元取引がVカード支払い | E32: =ROW()-3 -> 29 | F32: 元取引と同じVカードで通番取消、同じVカードで支払い | G32: 練習：元取引の取消処理と修正後の取引が正常に完了すること | H32: □ | I32: ー | J32: ー | K32: ー | L32: □ | M32: □ | N32: ー | O32: ー | P32: ー
E33: =ROW()-3 -> 30 | F33: 元取引と同じVカードで通番取消、他クレカードで支払い | G33: 練習：元取引の取消処理と修正後の取引が正常に完了すること | H33: □ | I33: ー | J33: ー | K33: ー | L33: □ | M33: □ | N33: ー | O33: ー | P33: ー
D34: 元取引が他クレ支払い | E34: =ROW()-3 -> 31 | F34: 元取引と同じ他クレで通番取消、Vカードで支払い | G34: 練習：元取引の取消処理と修正後の取引が正常に完了すること | H34: □ | I34: ー | J34: ー | K34: ー | L34: □ | M34: □ | N34: ー | O34: ー | P34: ー
E35: =ROW()-3 -> 32 | F35: 元取引と同じ他クレで通番取消、現金で支払い | G35: 練習：元取引の取消処理と修正後の取引が正常に完了すること | H35: □ | I35: ー | J35: ー | K35: ー | L35: □ | M35: □ | N35: ー | O35: ー | P35: ー
B36: Satisfa | C36: 開局 | E36: =ROW()-3 -> 33 | F36: 開局処理 | G36: POS開局時にエラーが発生しないこと | H36: □ | I36: ー | J36: ー | K36: ー | L36: ー | M36: ー | N36: ー | O36: □ | P36: ー
C37: 会員番号登録 | D37: Vカード | E37: =ROW()-3 -> 34 | F37: Vカードで会員登録 | G37: 正常に会員登録できること。現在ポイントが正しく表示されること | H37: □ | I37: ー | J37: ー | K37: ー | L37: □ | M37: □ | N37: ー | O37: □ | P37: ー
D38: ingfanカード | E38: =ROW()-3 -> 35 | F38: ingfan会員バーコードで会員登録 | G38: 正常に会員登録できること。現在ポイントが正しく表示されること | H38: □ | I38: ー | J38: ー | K38: ー | L38: □ | M38: □ | N38: ー | O38: □ | P38: ー
D39: 手入力 | E39: =ROW()-3 -> 36 | F39: 手入力で会員登録 | G39: 正常に会員登録できること。現在ポイントが正しく表示されること | H39: □ | I39: ー | J39: ー | K39: ー | L39: □ | M39: □ | N39: ー | O39: □ | P39: ー | U39: POSモードで手入力可能
C40: ポイント付与 | D40: Vカード | E40: =ROW()-3 -> 37 | F40: Vカードで会員登録 | G40: 正常に取引が完了すること。今回ポイントが正しく付与されること | H40: □ | I40: ー | J40: ー | K40: ー | L40: □ | M40: □ | N40: ー | O40: □ | P40: ー
D41: ingfanカード | E41: =ROW()-3 -> 38 | F41: ingfan会員バーコードで会員登録 | G41: 正常に取引が完了すること。今回ポイントが正しく付与されること | H41: □ | I41: ー | J41: ー | K41: ー | L41: □ | M41: □ | N41: ー | O41: □ | P41: ー
D42: 手入力 | E42: =ROW()-3 -> 39 | F42: 手入力で会員登録 | G42: 正常に取引が完了すること。今回ポイントが正しく付与されること | H42: □ | I42: ー | J42: ー | K42: ー | L42: □ | M42: □ | N42: ー | O42: □ | P42: ー | U42: POSモードで手入力可能
C43: ポイント利用 | D43: Vカード | E43: =ROW()-3 -> 40 | F43: Vカードで会員登録 | G43: 正常に取引が完了すること。ポイント利用分が正しく反映されること | H43: □ | I43: ー | J43: ー | K43: ー | L43: □ | M43: □ | N43: ー | O43: □ | P43: ー
D44: ingfanカード | E44: =ROW()-3 -> 41 | F44: ingfan会員バーコードで会員登録 | G44: 正常に取引が完了すること。ポイント利用分が正しく反映されること | H44: □ | I44: ー | J44: ー | K44: ー | L44: □ | M44: □ | N44: ー | O44: □ | P44: ー
D45: 手入力 | E45: =ROW()-3 -> 42 | F45: 手入力で会員登録 | G45: 正常に取引が完了すること。ポイント利用分が正しく反映されること | H45: □ | I45: ー | J45: ー | K45: ー | L45: □ | M45: □ | N45: ー | O45: □ | P45: ー
C46: ポイント修正 | D46: Vカード | E46: =ROW()-3 -> 43 | F46: Vカードで会員登録 | G46: 正常に処理が完了すること。ポイント修正結果が正しく反映されること | H46: □ | I46: ー | J46: ー | K46: ー | L46: □ | M46: □ | N46: ー | O46: □ | P46: ー
D47: ingfanカード | E47: =ROW()-3 -> 44 | F47: ingfan会員バーコードで会員登録 | G47: 正常に処理が完了すること。ポイント修正結果が正しく反映されること | H47: □ | I47: ー | J47: ー | K47: ー | L47: □ | M47: □ | N47: ー | O47: □ | P47: ー
D48: 手入力 | E48: =ROW()-3 -> 45 | F48: 手入力で会員登録 | G48: 正常に処理が完了すること。ポイント修正結果が正しく反映されること | H48: □ | I48: ー | J48: ー | K48: ー | L48: □ | M48: □ | N48: ー | O48: □ | P48: ー
C49: レジマイナス | D49: 会員宣言なし | E49: =ROW()-3 -> 46 | F49: 会員宣言しない | G49: 正常にマイナス処理が完了すること | H49: □ | I49: ー | J49: ー | K49: □ | L49: □ | M49: □ | N49: ー | O49: □ | P49: ー
D50: ingカードで会員宣言 | E50: =ROW()-3 -> 47 | F50: ingfan会員バーコードで会員宣言 | G50: 正常にマイナス処理が完了すること（現在ポイントが減算されること） | H50: □ | I50: ー | J50: ー | K50: □ | L50: □ | M50: □ | N50: ー | O50: □ | P50: ー
D51: Vカードで会員宣言 | E51: =ROW()-3 -> 48 | F51: Vカードで会員宣言 | G51: 正常にマイナス処理が完了すること （現在ポイントが200円1ポイントで減算されること） | H51: □ | I51: ー | J51: ー | K51: □ | L51: □ | M51: □ | N51: ー | O51: □ | P51: ー
C52: さんにち割 | D52: 開局 | E52: =ROW()-3 -> 49 | F52: 開局レシートを確認 | G52: 「さんにち割引」が表示されていること 対象日付が表示されていること | H52: □ | I52: ー | J52: ー | K52: □ | L52: □ | M52: □ | N52: ー | O52: □ | P52: ー
D53: 小計自動値引 | E53: =ROW()-3 -> 50 | F53: ingfan会員バーコードで会員登録 | G53: 自動小計値引が反映されないこと | H53: □ | I53: ー | J53: ー | K53: □ | L53: □ | M53: □ | N53: ー | O53: □ | P53: ー
E54: =ROW()-3 -> 51 | F54: Vカードで会員登録 | G54: 自動小計値引（5%）が反映されること | H54: □ | I54: ー | J54: ー | K54: □ | L54: □ | M54: □ | N54: ー | O54: □ | P54: ー
B55: 自動釣銭釣札機 | C55: POS連携 | D55: 預り金処理 | E55: =ROW()-3 -> 52 | F55: 預り金を投入 | G55: 正常に処理が完了すること。お釣りが正しく出金されること | H55: ー | I55: ー | J55: ー | K55: ー | L55: ー | M55: ー | N55: ー | O55: ー | P55: ー
B56: （POS / RT-300） | D56: 入金処理（Xモード） | E56: =ROW()-3 -> 53 | F56: 入金処理（Xモード） | G56: 正常に処理が完了すること。 | H56: ー | I56: ー | J56: ー | K56: ー | L56: ー | M56: ー | N56: ー | O56: ー | P56: ー
D57: 在高点検 | E57: =ROW()-3 -> 54 | F57: 在高点検（Xモード） | G57: 正常に処理が完了すること。 | H57: ー | I57: ー | J57: ー | K57: ー | L57: ー | M57: ー | N57: ー | O57: ー | P57: ー
D58: 全回収 | E58: =ROW()-3 -> 55 | F58: 全回収（Zモード） | G58: 正常に処理が完了すること。 | H58: ー | I58: ー | J58: ー | K58: ー | L58: ー | M58: ー | N58: ー | O58: ー | P58: ー
D59: 紙幣途中回収（移動） | E59: =ROW()-3 -> 56 | F59: 紙幣途中回収（移動）（Zモード） | G59: 正常に処理が完了すること。 | H59: ー | I59: ー | J59: ー | K59: ー | L59: ー | M59: ー | N59: ー | O59: ー | P59: ー
D60: 硬貨途中回収 | E60: =ROW()-3 -> 57 | F60: 硬貨途中回収（Zモード） | G60: 正常に処理が完了すること。 | H60: ー | I60: ー | J60: ー | K60: ー | L60: ー | M60: ー | N60: ー | O60: ー | P60: ー
D61: ボックス回収 | E61: =ROW()-3 -> 58 | F61: ボックス回収（Zモード） | G61: 正常に処理が完了すること。 | H61: ー | I61: ー | J61: ー | K61: ー | L61: ー | M61: ー | N61: ー | O61: ー | P61: ー
D62: 出金処理 | E62: =ROW()-3 -> 59 | F62: 出金処理（Zモード） | G62: 正常に処理が完了すること。 | H62: ー | I62: ー | J62: ー | K62: ー | L62: ー | M62: ー | N62: ー | O62: ー | P62: ー
D63: あふれ金収納庫移動 | E63: =ROW()-3 -> 60 | F63: あふれ金収納庫移動（Zモード） | G63: メニューに無いことを確認する。 | H63: ー | I63: ー | J63: ー | K63: ー | L63: ー | M63: ー | N63: ー | O63: ー | P63: ー
B64: 自動釣銭釣札機 | C64: POS連携 | D64: 預り金処理 | E64: =ROW()-3 -> 61 | F64: 預り金を投入 | G64: 正常に処理が完了すること。お釣りが正しく出金されること | H64: ー | I64: ー | J64: ー | K64: ー | L64: ー | M64: ー | N64: ー | O64: ー | P64: ー
B65: （PS / RT-380） | D65: 入金処理（Xモード） | E65: =ROW()-3 -> 62 | F65: 入金処理（Xモード） | G65: 正常に処理が完了すること。 | H65: ー | I65: ー | J65: ー | K65: ー | L65: ー | M65: ー | N65: ー | O65: ー | P65: ー
D66: 在高点検 | E66: =ROW()-3 -> 63 | F66: 在高点検（Xモード） | G66: 正常に処理が完了すること。 | H66: ー | I66: ー | J66: ー | K66: ー | L66: ー | M66: ー | N66: ー | O66: ー | P66: ー
D67: 全回収 | E67: =ROW()-3 -> 64 | F67: 全回収（Zモード） | G67: 正常に処理が完了すること。 | H67: ー | I67: ー | J67: ー | K67: ー | L67: ー | M67: ー | N67: ー | O67: ー | P67: ー
D68: 紙幣途中回収（移動） | E68: =ROW()-3 -> 65 | F68: 紙幣途中回収（移動）（Zモード） | G68: 正常に処理が完了すること。 | H68: ー | I68: ー | J68: ー | K68: ー | L68: ー | M68: ー | N68: ー | O68: ー | P68: ー
D69: 硬貨途中回収 | E69: =ROW()-3 -> 66 | F69: 硬貨途中回収（Zモード） | G69: 正常に処理が完了すること。 | H69: ー | I69: ー | J69: ー | K69: ー | L69: ー | M69: ー | N69: ー | O69: ー | P69: ー
D70: ボックス回収 | E70: =ROW()-3 -> 67 | F70: ボックス回収（Zモード） | G70: 正常に処理が完了すること。 | H70: ー | I70: ー | J70: ー | K70: ー | L70: ー | M70: ー | N70: ー | O70: ー | P70: ー
D71: 出金処理 | E71: =ROW()-3 -> 68 | F71: 出金処理（Zモード） | G71: 正常に処理が完了すること。 | H71: ー | I71: ー | J71: ー | K71: ー | L71: ー | M71: ー | N71: ー | O71: ー | P71: ー
D72: あふれ金収納庫移動 | E72: =ROW()-3 -> 69 | F72: あふれ金収納庫移動（Zモード） | G72: メニューに無いことを確認する。 | H72: ー | I72: ー | J72: ー | K72: ー | L72: ー | M72: ー | N72: ー | O72: ー | P72: ー
B73: disk2264 | C73: 定時送信 | F73: 商品一覧画面で定時送信時刻に到達する | G73: 定位送信が実施されないこと | H73: □ | I73: ー | J73: ー | K73: □ | L73: ー | M73: ー | N73: ー | O73: ー | P73: ー
H74: ー | I74: ー | J74: ー | K74: ー | L74: ー | M74: ー | N74: ー | O74: ー | P74: ー
B75: 消化ﾃｽﾄ項目数： | D75: =SUM(H77:P77) -> 0 | G75: OK数： | H75: =COUNTIF(H4:H74,"●")+COUNTIF(H4:H74,"■")+COUNTIF(H4:H74,"OK") -> 0 | I75: =COUNTIF(I4:I74,"●")+COUNTIF(I4:I74,"■")+COUNTIF(I4:I74,"OK") -> 0 | J75: =COUNTIF(J4:J74,"●")+COUNTIF(J4:J74,"■")+COUNTIF(J4:J74,"OK") -> 0 | K75: =COUNTIF(K4:K74,"●")+COUNTIF(K4:K74,"■")+COUNTIF(K4:K74,"OK") -> 0 | L75: =COUNTIF(L4:L74,"●")+COUNTIF(L4:L74,"■")+COUNTIF(L4:L74,"OK") -> 0 | M75: =COUNTIF(M4:M74,"●")+COUNTIF(M4:M74,"■")+COUNTIF(M4:M74,"OK") -> 0 | N75: =COUNTIF(N4:N74,"●")+COUNTIF(N4:N74,"■")+COUNTIF(N4:N74,"OK") -> 0 | O75: =COUNTIF(O4:O74,"●")+COUNTIF(O4:O74,"■")+COUNTIF(O4:O74,"OK") -> 0 | P75: =COUNTIF(P4:P74,"●")+COUNTIF(P4:P74,"■")+COUNTIF(P4:P74,"OK") -> 0 | Q75: 合計
G76: NG数： | H76: =COUNTIF(H4:H74,"×")+COUNTIF(H4:H74,"NG") -> 0 | I76: =COUNTIF(I4:I74,"×")+COUNTIF(I4:I74,"NG") -> 0 | J76: =COUNTIF(J4:J74,"×")+COUNTIF(J4:J74,"NG") -> 0 | K76: =COUNTIF(K4:K74,"×")+COUNTIF(K4:K74,"NG") -> 0 | L76: =COUNTIF(L4:L74,"×")+COUNTIF(L4:L74,"NG") -> 0 | M76: =COUNTIF(M4:M74,"×")+COUNTIF(M4:M74,"NG") -> 0 | N76: =COUNTIF(N4:N74,"×")+COUNTIF(N4:N74,"NG") -> 0 | O76: =COUNTIF(O4:O74,"×")+COUNTIF(O4:O74,"NG") -> 0 | P76: =COUNTIF(P4:P74,"×")+COUNTIF(P4:P74,"NG") -> 0
B77: 全ﾃｽﾄ項目数： | D77: =SUM(H78:P78) -> 163 | G77: 消化項目数： | H77: =H75+H76 -> 0 | I77: =I75+I76 -> 0 | J77: =J75+J76 -> 0 | K77: =K75+K76 -> 0 | L77: =L75+L76 -> 0 | M77: =M75+M76 -> 0 | N77: =N75+N76 -> 0 | O77: =O75+O76 -> 0 | P77: =P75+P76 -> 0 | Q77: =COUNTA(Q4:Q74) -> 0 | R77: =COUNTA(R4:R74) -> 0 | S77: =COUNTA(S4:S74) -> 0
G78: 全項目数： | H78: =COUNTBLANK(H4:H74)+H77+COUNTIF(H4:H74,"□") -> 46 | I78: =COUNTBLANK(I4:I74)+I77+COUNTIF(I4:I74,"□") -> 0 | J78: =COUNTBLANK(J4:J74)+J77+COUNTIF(J4:J74,"□") -> 0 | K78: =COUNTBLANK(K4:K74)+K77+COUNTIF(K4:K74,"□") -> 10 | L78: =COUNTBLANK(L4:L74)+L77+COUNTIF(L4:L74,"□") -> 44 | M78: =COUNTBLANK(M4:M74)+M77+COUNTIF(M4:M74,"□") -> 44 | N78: =COUNTBLANK(N4:N74)+N77+COUNTIF(N4:N74,"□") -> 0 | O78: =COUNTBLANK(O4:O74)+O77+COUNTIF(O4:O74,"□") -> 19 | P78: =COUNTBLANK(P4:P74)+P77+COUNTIF(P4:P74,"□") -> 0

Sheet Win10対応_サーバ
B1: いなげや様 Win10対応（POSサーバ） リグレッションテスト仕様書
B2: 大分類 | C2: 中分類 | D2: 小分類 | E2: テスト項目 | H2: サーバ | Q2: チェック日付 | T2: 担当 | U2: 備考
E3: No | F3: サーバ操作 | G3: 結果 | H3: 動作 | I3: DB | J3: 画面 | K3: 帳票 | L3: 電子ｼﾞｬｰﾅﾙ | M3: ログ | N3: ー | O3: ー | P3: ー | Q3: OK | R3: NG | S3: 修正 OK
B4: デバイス設定 | C4: デバイス設定ツール | D4: ツール起動 | E4: =ROW()-3 -> 1 | F4: C:\GSFD\TOOL\デバイス\TP7000M240 GSFDDvcSelect_TP7000M240.exe を実行 | G4: ツールが正常に起動されること | H4: □ | I4: ー | J4: □ | K4: ー | L4: ー | M4: ー | N4: ー | O4: ー | P4: ー
D5: レーンPOS用設定 | E5: =ROW()-3 -> 2 | F5: デバイスグループにレーンPOSのグループを設定 | G5: 正しい装置情報が設定されていること | H5: □ | I5: ー | J5: □ | K5: ー | L5: ー | M5: ー | N5: ー | O5: ー | P5: ー
E6: =ROW()-3 -> 3 | F6: レジ番号選択 | G6: 対象のレジ番号が選択されていること | H6: □ | I6: ー | J6: □ | K6: ー | L6: ー | M6: ー | N6: ー | O6: ー | P6: ー
E7: =ROW()-3 -> 4 | F7: 反映 | G7: 対象のレジにデバイス情報が反映されること | H7: □ | I7: ー | J7: □ | K7: ー | L7: ー | M7: ー | N7: ー | O7: ー | P7: ー
D8: SS用設定 | E8: =ROW()-3 -> 5 | F8: デバイスグループにSSのグループを設定 | G8: 正しい装置情報が設定されていること | H8: □ | I8: ー | J8: □ | K8: ー | L8: ー | M8: ー | N8: ー | O8: ー | P8: ー
E9: =ROW()-3 -> 6 | F9: レジ番号選択 | G9: 対象のレジ番号が選択されていること | H9: □ | I9: ー | J9: □ | K9: ー | L9: ー | M9: ー | N9: ー | O9: ー | P9: ー
E10: =ROW()-3 -> 7 | F10: 反映 | G10: 対象のレジにデバイス情報が反映されること | H10: □ | I10: ー | J10: □ | K10: ー | L10: ー | M10: ー | N10: ー | O10: ー | P10: ー
D11: PS用設定 | E11: =ROW()-3 -> 8 | F11: デバイスグループにPSのグループを設定 | G11: 正しい装置情報が設定されていること | H11: □ | I11: ー | J11: □ | K11: ー | L11: ー | M11: ー | N11: ー | O11: ー | P11: ー
E12: =ROW()-3 -> 9 | F12: レジ番号選択 | G12: 対象のレジ番号が選択されていること | H12: □ | I12: ー | J12: □ | K12: ー | L12: ー | M12: ー | N12: ー | O12: ー | P12: ー
E13: =ROW()-3 -> 10 | F13: 反映 | G13: 対象のレジにデバイス情報が反映されること | H13: □ | I13: ー | J13: □ | K13: ー | L13: ー | M13: ー | N13: ー | O13: ー | P13: ー
D14: CS用設定（釣銭機あり） | E14: =ROW()-3 -> 11 | F14: デバイスグループにCSのグループを設定 | G14: 正しい装置情報が設定されていること | H14: □ | I14: ー | J14: □ | K14: ー | L14: ー | M14: ー | N14: ー | O14: ー | P14: ー
E15: =ROW()-3 -> 12 | F15: レジ番号選択 | G15: 対象のレジ番号が選択されていること | H15: □ | I15: ー | J15: □ | K15: ー | L15: ー | M15: ー | N15: ー | O15: ー | P15: ー
E16: =ROW()-3 -> 13 | F16: 反映 | G16: 対象のレジにデバイス情報が反映されること | H16: □ | I16: ー | J16: □ | K16: ー | L16: ー | M16: ー | N16: ー | O16: ー | P16: ー
D17: CS用設定（キャッシュレス） | E17: =ROW()-3 -> 14 | F17: デバイスグループにCSのグループを設定 | G17: 正しい装置情報が設定されていること | H17: □ | I17: ー | J17: □ | K17: ー | L17: ー | M17: ー | N17: ー | O17: ー | P17: ー
E18: =ROW()-3 -> 15 | F18: レジ番号選択 | G18: 対象のレジ番号が選択されていること | H18: □ | I18: ー | J18: □ | K18: ー | L18: ー | M18: ー | N18: ー | O18: ー | P18: ー
E19: =ROW()-3 -> 16 | F19: 反映 | G19: 対象のレジにデバイス情報が反映されること | H19: □ | I19: ー | J19: □ | K19: ー | L19: ー | M19: ー | N19: ー | O19: ー | P19: ー
H20: ー | I20: ー | J20: ー | K20: ー | L20: ー | M20: ー | N20: ー | O20: ー | P20: ー
H21: ー | I21: ー | J21: ー | K21: ー | L21: ー | M21: ー | N21: ー | O21: ー | P21: ー
H22: ー | I22: ー | J22: ー | K22: ー | L22: ー | M22: ー | N22: ー | O22: ー | P22: ー
B23: 消化ﾃｽﾄ項目数： | D23: =SUM(H25:P25) -> 0 | G23: OK数： | H23: =COUNTIF(H4:H22,"●")+COUNTIF(H4:H22,"■")+COUNTIF(H4:H22,"OK") -> 0 | I23: =COUNTIF(I4:I22,"●")+COUNTIF(I4:I22,"■")+COUNTIF(I4:I22,"OK") -> 0 | J23: =COUNTIF(J4:J22,"●")+COUNTIF(J4:J22,"■")+COUNTIF(J4:J22,"OK") -> 0 | K23: =COUNTIF(K4:K22,"●")+COUNTIF(K4:K22,"■")+COUNTIF(K4:K22,"OK") -> 0 | L23: =COUNTIF(L4:L22,"●")+COUNTIF(L4:L22,"■")+COUNTIF(L4:L22,"OK") -> 0 | M23: =COUNTIF(M4:M22,"●")+COUNTIF(M4:M22,"■")+COUNTIF(M4:M22,"OK") -> 0 | N23: =COUNTIF(N4:N22,"●")+COUNTIF(N4:N22,"■")+COUNTIF(N4:N22,"OK") -> 0 | O23: =COUNTIF(O4:O22,"●")+COUNTIF(O4:O22,"■")+COUNTIF(O4:O22,"OK") -> 0 | P23: =COUNTIF(P4:P22,"●")+COUNTIF(P4:P22,"■")+COUNTIF(P4:P22,"OK") -> 0 | Q23: 合計
G24: NG数： | H24: =COUNTIF(H4:H22,"×")+COUNTIF(H4:H22,"NG") -> 0 | I24: =COUNTIF(I4:I22,"×")+COUNTIF(I4:I22,"NG") -> 0 | J24: =COUNTIF(J4:J22,"×")+COUNTIF(J4:J22,"NG") -> 0 | K24: =COUNTIF(K4:K22,"×")+COUNTIF(K4:K22,"NG") -> 0 | L24: =COUNTIF(L4:L22,"×")+COUNTIF(L4:L22,"NG") -> 0 | M24: =COUNTIF(M4:M22,"×")+COUNTIF(M4:M22,"NG") -> 0 | N24: =COUNTIF(N4:N22,"×")+COUNTIF(N4:N22,"NG") -> 0 | O24: =COUNTIF(O4:O22,"×")+COUNTIF(O4:O22,"NG") -> 0 | P24: =COUNTIF(P4:P22,"×")+COUNTIF(P4:P22,"NG") -> 0
B25: 全ﾃｽﾄ項目数： | D25: =SUM(H26:P26) -> 32 | G25: 消化項目数： | H25: =H23+H24 -> 0 | I25: =I23+I24 -> 0 | J25: =J23+J24 -> 0 | K25: =K23+K24 -> 0 | L25: =L23+L24 -> 0 | M25: =M23+M24 -> 0 | N25: =N23+N24 -> 0 | O25: =O23+O24 -> 0 | P25: =P23+P24 -> 0 | Q25: =COUNTA(Q4:Q22) -> 0 | R25: =COUNTA(R4:R22) -> 0 | S25: =COUNTA(S4:S22) -> 0
G26: 全項目数： | H26: =COUNTBLANK(H4:H22)+H25+COUNTIF(H4:H22,"□") -> 16 | I26: =COUNTBLANK(I4:I22)+I25+COUNTIF(I4:I22,"□") -> 0 | J26: =COUNTBLANK(J4:J22)+J25+COUNTIF(J4:J22,"□") -> 16 | K26: =COUNTBLANK(K4:K22)+K25+COUNTIF(K4:K22,"□") -> 0 | L26: =COUNTBLANK(L4:L22)+L25+COUNTIF(L4:L22,"□") -> 0 | M26: =COUNTBLANK(M4:M22)+M25+COUNTIF(M4:M22,"□") -> 0 | N26: =COUNTBLANK(N4:N22)+N25+COUNTIF(N4:N22,"□") -> 0 | O26: =COUNTBLANK(O4:O22)+O25+COUNTIF(O4:O22,"□") -> 0 | P26: =COUNTBLANK(P4:P22)+P25+COUNTIF(P4:P22,"□") -> 0

Sheet バーコード作成用
B1: ing会員（チェックデジット誤） | I1: ing会員（読取不可）
B2: 2899999999994 | I2: 2818208658799
B17: 担当者マスタ登録

Sheet SPS系
B1: いなげや様 セルフペイメント リグレッションテスト仕様書
B2: 大分類 | C2: 中分類 | D2: 小分類 | E2: テスト項目 | K2: SPS | T2: チェック日付 | W2: 担当 | X2: 備考
E3: No | F3: SS操作 | H3: PS操作 | J3: 結果 | K3: 動作 | L3: DB | M3: ｶｽﾀﾏ | N3: 画面 | O3: ﾚｼｰﾄ | P3: ｼﾞｬｰﾅﾙ | Q3: 音声 | R3: ﾛｸﾞ | S3: 小型 LCD | T3: OK | U3: NG | V3: 修正 OK
B4: 【SS操作】 会員宣言なし | C4: 【SS操作】 商品券ー無し | D4: 【PS操作】 支払ー現金 | E4: =ROW()-3 -> 1 | F4: 商品登録 →小計 →ingfanカード 確認ポップアップ →「PSへ」を選択 | G4: 預合計 →PS指定（ボタンタッチ） | H4: PS画面の確認 | J4: 【PS】 以下画面が表示されていること。 タイトルー「ポイントカードはお持ちですか？」 文言ー「残りお支払金額」 音声ー「ポイントカードはお持ちですか？」 | K4: □ | L4: ー | M4: ー | N4: □ | O4: ー | P4: ー | Q4: □ | R4: ー | S4: ー
E5: =ROW()-3 -> 2 | H5: ボタン選択 | I5: 【係員呼出】をタッチ。 | J5: 【PS】 以下画面が表示されていること。 タイトルー「しばらくお待ちください」 文言ー「まもなく、係員がまいります」 音声ー「まもなく係員がまいります。しばらくお待ちください」 | K5: □ | L5: ー | M5: ー | N5: □ | O5: ー | P5: ー | Q5: □ | R5: ー | S5: ー
E6: =ROW()-3 -> 3 | H6: ボタン選択 | I6: 【呼出取消】をタッチ。 | J6: 【PS】 以下画面が表示されていること。 タイトルー「ポイントカードはお持ちですか？」 文言ー「残りお支払金額」 「はい」「いいえ」 音声ー「ポイントカードはお持ちですか？」 | K6: □ | L6: ー | M6: ー | N6: □ | O6: ー | P6: ー | Q6: □ | R6: ー | S6: ー
E7: =ROW()-3 -> 4 | H7: PS画面の確認 | I7: 「ポイントカードはお持ちですか？」画面で【いいえ】選択 ⇒「お支払方法を選んでください」画面で【現金】を選択。 | J7: 【PS】 タイトルー「現金を入れてください」 音声ー「現金を入れてください」 | K7: □ | L7: ー | M7: ー | N7: □ | O7: ー | P7: ー | Q7: □ | R7: ー | S7: ー
E8: =ROW()-3 -> 5 | H8: PS画面の確認 | I8: 現金を投入。 | J8: 【PS】 以下画面に表示変更されること。 タイトルー「お支払い額がよろしければ「レシート」 または「領収証」を押してください」 音声ー「お支払額がよろしければ「レシート」または 「領収証」を押してください」 | K8: □ | L8: ー | M8: ー | N8: □ | O8: ー | P8: ー | Q8: □ | R8: ー | S8: ー
E9: =ROW()-3 -> 6 | H9: ボタン選択 | I9: タイトルー「お支払額がよろしければ「レシート」または「領収証」を押してください」画面で、 【レシート】をタッチ 支払額一致：お釣りなし | J9: 【PS】 「お買上げありがとうございます」画面に遷移し、 レシートが排出されること。 音声ー「ありがとうございます。レシートをお取りください」 | K9: □ | L9: ー | M9: ー | N9: □ | O9: □ | P9: □ | Q9: □ | R9: ー | S9: ー
E10: =ROW()-3 -> 7 | H10: ボタン選択 | I10: タイトルー「お支払額がよろしければ「レシート」または「領収証」を押してください」画面で、 【レシート】をタッチ 支払額超過：お釣りあり | J10: 【PS】 「お買上げありがとうございます」画面に遷移し、 レシート・お釣りが排出されること。 音声ー「おつりがあります。お取り忘れにご注意ください」 | K10: □ | L10: ー | M10: ー | N10: □ | O10: □ | P10: □ | Q10: □ | R10: ー | S10: ー
E11: =ROW()-3 -> 8 | H11: PS画面の確認 | I11: タイトルー「お買上げありがとうございます」の画面で、 排出されたお釣りを受取る | J11: 【PS】 「お買上げありがとうございます」画面に遷移すること。 音声ー「ありがとうございます。レシートをお取りください」 | K11: □ | L11: ー | M11: ー | N11: □ | O11: ー | P11: ー | Q11: □ | R11: ー | S11: ー
E12: =ROW()-3 -> 9 | F12: 商品登録 →小計 →ingfanカード 確認ポップアップ →「PSへ」を選択 | G12: 預合計 →【精算券】タッチ | H12: PS画面の確認 | J12: 【PS】 以下画面が表示されていること。 タイトルー「精算機」 文言ー「待機中」 | K12: □ | L12: ー | M12: ー | N12: □ | O12: ー | P12: ー | Q12: ー | R12: ー | S12: ー
E13: =ROW()-3 -> 10 | H13: ボタン選択 | I13: 【係員呼出】をタッチ。 | J13: 【PS】 以下画面が表示されていること。 タイトルー「しばらくお待ちください」 文言ー「まもなく、係員がまいります」 音声ー「まもなく係員がまいります。しばらくお待ちください」 | K13: □ | L13: ー | M13: ー | N13: □ | O13: ー | P13: ー | Q13: □ | R13: ー | S13: ー
E14: =ROW()-3 -> 11 | H14: ボタン選択 | I14: 【呼出取消】をタッチ。 | J14: 【PS】 以下画面が表示されていること。 タイトルー「精算機」 文言ー「待機中」 | K14: □ | L14: ー | M14: ー | N14: □ | O14: ー | P14: ー | Q14: ー | R14: ー | S14: ー
E15: =ROW()-3 -> 12 | H15: ボタン選択 | I15: 【言語切替】⇒【English】をタッチ。 | J15: 【PS】 以下画面が表示されていること。 タイトルー「Payment machine」 文言ー「Waiting」 その後、【Language】⇒【日本語】をタッチ。 | K15: □ | L15: ー | M15: ー | N15: □ | O15: ー | P15: ー | Q15: ー | R15: ー | S15: ー
E16: =ROW()-3 -> 13 | H16: PS画面の確認 | I16: タイトルー「精算機」の画面で、 ご精算券のQRコードをスキャン。 | J16: 【PS】 以下画面が表示されていること。 タイトルー「ポイントカードはお持ちですか？」 文言ー「残りお支払金額」 「はい」「いいえ」 音声ー「ポイントカードはお持ちですか？」 | K16: □ | L16: ー | M16: ー | N16: □ | O16: ー | P16: ー | Q16: □ | R16: ー | S16: ー
E17: =ROW()-3 -> 14 | H17: ボタン選択 | I17: タイトルー「お支払方法を選んでください」の画面で、 【係員呼出】をタッチ | J17: 【PS】 以下画面が表示されていること。 タイトルー「しばらくお待ちください」 文言ー「まもなく、係員がまいります」 音声ー「まもなく係員がまいります。しばらくお待ちください」 | K17: □ | L17: ー | M17: ー | N17: □ | O17: ー | P17: ー | Q17: □ | R17: ー | S17: ー
E18: =ROW()-3 -> 15 | H18: ボタン選択 | I18: 【呼出取消】をタッチ。 | J18: 【PS】 以下画面が表示されていること。 タイトルー「ポイントカードはお持ちですか？」 文言ー「残りお支払金額」 「はい」「いいえ」 音声ー「ポイントカードはお持ちですか？」 | K18: □ | L18: ー | M18: ー | N18: □ | O18: ー | P18: ー | Q18: □ | R18: ー | S18: ー
E19: =ROW()-3 -> 16 | H19: PS画面の確認 | I19: 「ポイントカードはお持ちですか？」画面で【いいえ】選択 ⇒「お支払方法を選んでください」画面で【現金】を選択。 | J19: 【PS】 タイトルー「現金を入れてください」 音声ー「現金を入れてください」 | K19: □ | L19: ー | M19: ー | N19: □ | O19: ー | P19: ー | Q19: □ | R19: ー | S19: ー
E20: =ROW()-3 -> 17 | H20: PS画面の確認 | I20: 現金を投入。 | J20: 【PS】 以下画面に表示変更されること。 タイトルー「お支払額がよろしければ「レシート」 または「領収証」を押してください」 音声ー「お支払額がよろしければ「レシート」または 「領収証」を押してください」 | K20: □ | L20: ー | M20: ー | N20: □ | O20: ー | P20: ー | Q20: □ | R20: ー | S20: ー
E21: =ROW()-3 -> 18 | H21: ボタン選択 | I21: タイトルー「お支払額がよろしければ「レシート」または「領収証」を押してください」画面で、 【レシート】をタッチ 支払額一致：お釣りなし | J21: 【PS】 「お買上げありがとうございます」画面に遷移し、 レシートが排出されること。 音声ー「ありがとうございます。レシートをお取りください」 | K21: □ | L21: ー | M21: ー | N21: □ | O21: □ | P21: □ | Q21: □ | R21: ー | S21: ー
E22: =ROW()-3 -> 19 | H22: ボタン選択 | I22: タイトルー「お支払額がよろしければ「レシート」または「領収証」を押してください」画面で、 【レシート】をタッチ 支払額超過：お釣りあり | J22: 【PS】 「お買上げありがとうございます」画面に遷移し、 レシート・お釣りが排出されること。 音声ー「おつりがあります。お取り忘れにご注意ください」 | K22: □ | L22: ー | M22: ー | N22: □ | O22: □ | P22: □ | Q22: □ | R22: ー | S22: ー
E23: =ROW()-3 -> 20 | H23: PS画面の確認 | I23: タイトルー「お買上げありがとうございます」の画面で、 排出されたお釣りを受取る | J23: 【PS】 「お買上げありがとうございます」画面に遷移すること。 音声ー「ありがとうございます。レシートをお取りください」 | K23: □ | L23: ー | M23: ー | N23: □ | O23: ー | P23: ー | Q23: □ | R23: ー | S23: ー
D24: 【PS操作】 支払ークレジット | E24: =ROW()-3 -> 21 | F24: 商品登録 →小計 →ingfanカード 確認ポップアップ →「PSへ」を選択 | G24: 預合計 →PS指定（ボタンタッチ） | H24: PS画面の確認 | J24: 【PS】 以下画面が表示されていること。 タイトルー「ポイントカードはお持ちですか？」 文言ー「残りお支払金額」 「はい」「いいえ」 音声ー「ポイントカードはお持ちですか？」 | K24: □ | L24: ー | M24: ー | N24: □ | O24: ー | P24: ー | Q24: □ | R24: ー | S24: ー
E25: =ROW()-3 -> 22 | H25: ボタン選択 | I25: 【係員呼出】をタッチ。 | J25: 【PS】 以下画面が表示されていること。 タイトルー「しばらくお待ちください」 文言ー「まもなく、係員がまいります」 音声ー「まもなく係員がまいります。しばらくお待ちください」 | K25: □ | L25: ー | M25: ー | N25: □ | O25: ー | P25: ー | Q25: □ | R25: ー | S25: ー
E26: =ROW()-3 -> 23 | H26: ボタン選択 | I26: 【呼出取消】をタッチ。 | J26: 【PS】 以下画面が表示されていること。 タイトルー「ポイントカードはお持ちですか？」 文言ー「残りお支払金額」 「はい」「いいえ」 音声ー「ポイントカードはお持ちですか？」 | K26: □ | L26: ー | M26: ー | N26: □ | O26: ー | P26: ー | Q26: □ | R26: ー | S26: ー
E27: =ROW()-3 -> 24 | H27: PS画面の確認 | I27: 「ポイントカードはお持ちですか？」画面で【いいえ】選択 ⇒「お支払方法を選んでください」画面で【クレジット】を選択。 | J27: 【PS】 タイトルー「決済端末で操作してください」 音声ー「決済端末で操作してください」 | K27: □ | L27: ー | M27: ー | N27: □ | O27: ー | P27: ー | Q27: □ | R27: ー | S27: ー
E28: =ROW()-3 -> 25 | H28: エラーの確認 | I28: クレジットカードを挿入後、すぐにカード抜き取り。 | J28: 【PS】 以下画面に表示変更されること。 タイトルー「しばらくお待ちください」 文言ー「まもなく、係員がまいります」 | K28: □ | L28: ー | M28: ー | N28: □ | O28: ー | P28: ー | Q28: □ | R28: ー | S28: ー
E29: =ROW()-3 -> 26 | H29: エラーの確認 | I29: アテンダントコードスキャン。 | J29: 【PS】 以下画面が表示されていること。 ポップアップー「ICカード読み取りエラーが発生しました。」 | K29: □ | L29: ー | M29: ー | N29: □ | O29: ー | P29: ー | Q29: ー | R29: ー | S29: ー
E30: =ROW()-3 -> 27 | H30: エラーの確認 | I30: 【OK】をタッチ。 | J30: 【PS】 以下画面が表示されていること。 タイトルー「お支払方法を選んでください」 文言ー「残りお支払金額」 音声ー「お支払方法を選んでください」 | K30: □ | L30: ー | M30: ー | N30: □ | O30: ー | P30: ー | Q30: □ | R30: ー | S30: ー
E31: =ROW()-3 -> 28 | H31: PS画面の確認 | I31: 「お支払方法を選んでください」画面で【クレジット】を選択。 | J31: 【PS】 タイトルー「決済端末で操作してください」 音声ー「決済端末で操作してください」 | K31: □ | L31: ー | M31: ー | N31: □ | O31: ー | P31: ー | Q31: □ | R31: ー | S31: ー
E32: =ROW()-3 -> 29 | H32: PS画面の確認 | I32: クレジットカードを挿入後、 決済端末で「カードをお取りください」表示後にカードを抜き取り。 | J32: 【PS】 以下画面に表示変更されること。 タイトルー「お支払額がよろしければ「レシート」 または「領収証」を押してください」 音声ー「お支払額がよろしければ「レシート」または 「領収証」を押してください」 | K32: □ | L32: ー | M32: ー | N32: □ | O32: ー | P32: ー | Q32: □ | R32: ー | S32: ー
E33: =ROW()-3 -> 30 | H33: ボタン選択 | I33: タイトルー「お支払額がよろしければ「レシート」または「領収証」を押してください」画面で、 【レシート】をタッチ | J33: 【PS】 「お買上げありがとうございます」画面に遷移し、 レシートが排出されること。 音声ー「ありがとうございます。レシートをお取りください」 | K33: □ | L33: ー | M33: ー | N33: □ | O33: ー | P33: ー | Q33: □ | R33: ー | S33: ー
C34: 【SS操作】 商品券ーあり | D34: 【PS操作】 支払ー現金 | E34: =ROW()-3 -> 31 | F34: 商品登録 →小計 →ingfanカード 確認ポップアップ →「PSへ」を選択 | G34: 預合計 →商品券登録 ★ →PS指定（ボタンタッチ） | H34: PS画面の確認 | J34: 【PS】 以下画面が表示されていること。 タイトルー「ポイントカードはお持ちですか？」 文言ー「残りお支払金額」 「はい」「いいえ」 音声ー「ポイントカードはお持ちですか？」 | K34: □ | L34: ー | M34: ー | N34: □ | O34: ー | P34: ー | Q34: □ | R34: ー | S34: ー
E35: =ROW()-3 -> 32 | H35: ボタン選択 | I35: 【係員呼出】をタッチ。 | J35: 【PS】 以下画面が表示されていること。 タイトルー「しばらくお待ちください」 文言ー「まもなく、係員がまいります」 音声ー「まもなく係員がまいります。しばらくお待ちください」 | K35: □ | L35: ー | M35: ー | N35: □ | O35: ー | P35: ー | Q35: □ | R35: ー | S35: ー
E36: =ROW()-3 -> 33 | H36: ボタン選択 | I36: 【呼出取消】をタッチ。 | J36: 【PS】 以下画面が表示されていること。 タイトルー「ポイントカードはお持ちですか？」 文言ー「残りお支払金額」 「はい」「いいえ」 音声ー「ポイントカードはお持ちですか？」 | K36: □ | L36: ー | M36: ー | N36: □ | O36: ー | P36: ー | Q36: □ | R36: ー | S36: ー
E37: =ROW()-3 -> 34 | H37: PS画面の確認 | I37: 「ポイントカードはお持ちですか？」画面で【いいえ】選択 ⇒「お支払方法を選んでください」画面で【現金】を選択。 | J37: 【PS】 タイトルー「現金を入れてください」 音声ー「現金を入れてください」 | K37: □ | L37: ー | M37: ー | N37: □ | O37: ー | P37: ー | Q37: □ | R37: ー | S37: ー
E38: =ROW()-3 -> 35 | H38: PS画面の確認 | J38: 【PS】 タイトルー「現金を入れてください」 項目ー「商品券等の支払金額」にSSで登録した商品券の額が表示されていること。 | K38: □ | L38: ー | M38: ー | N38: □ | O38: ー | P38: ー | Q38: ー | R38: ー | S38: ー
E39: =ROW()-3 -> 36 | H39: PS画面の確認 | I39: 現金を投入。 | J39: 【PS】 以下画面に表示変更されること。 タイトルー「お支払額がよろしければ「レシート」 または「領収証」を押してください」 音声ー「お支払額がよろしければ「レシート」または 「領収証」を押してください」 | K39: □ | L39: ー | M39: ー | N39: □ | O39: ー | P39: ー | Q39: □ | R39: ー | S39: ー
E40: =ROW()-3 -> 37 | H40: ボタン選択 | I40: タイトルー「お支払額がよろしければ「レシート」または「領収証」を押してください」画面で、 【レシート】をタッチ 支払額一致：お釣りなし | J40: 【PS】 「お買上げありがとうございます」画面に遷移し、 レシートが排出されること。 音声ー「ありがとうございます。レシートをお取りください」 | K40: □ | L40: ー | M40: ー | N40: □ | O40: □ | P40: □ | Q40: □ | R40: ー | S40: ー
E41: =ROW()-3 -> 38 | H41: ボタン選択 | I41: タイトルー「お支払額がよろしければ「レシート」または「領収証」を押してください」画面で、 【レシート】をタッチ 支払額超過：お釣りあり | J41: 【PS】 「お買上げありがとうございます」画面に遷移し、 レシート・お釣りが排出されること。 音声ー「おつりがあります。お取り忘れにご注意ください」 | K41: □ | L41: ー | M41: ー | N41: □ | O41: □ | P41: □ | Q41: □ | R41: ー | S41: ー
E42: =ROW()-3 -> 39 | H42: PS画面の確認 | I42: タイトルー「お買上げありがとうございます」の画面で、 排出されたお釣りを受取る | J42: 【PS】 「お買上げありがとうございます」画面に遷移すること。 音声ー「ありがとうございます。レシートをお取りください」 | K42: □ | L42: ー | M42: ー | N42: □ | O42: ー | P42: ー | Q42: □ | R42: ー | S42: ー
E43: =ROW()-3 -> 40 | F43: 商品登録 →小計 →ingfanカード 確認ポップアップ →「PSへ」を選択 | G43: 預合計 →商品券登録 ★ →【ご精算券】タッチ | H43: PS画面の確認 | J43: 【PS】 以下画面が表示されていること。 タイトルー「ポイントカードはお持ちですか？」 文言ー「残りお支払金額」 「はい」「いいえ」 音声ー「ポイントカードはお持ちですか？」 | K43: □ | L43: ー | M43: ー | N43: □ | O43: ー | P43: ー | Q43: ー | R43: ー | S43: ー
E44: =ROW()-3 -> 41 | H44: ボタン選択 | I44: 【係員呼出】をタッチ。 | J44: 【PS】 以下画面が表示されていること。 タイトルー「しばらくお待ちください」 文言ー「まもなく、係員がまいります」 音声ー「まもなく係員がまいります。しばらくお待ちください」 | K44: □ | L44: ー | M44: ー | N44: □ | O44: ー | P44: ー | Q44: □ | R44: ー | S44: ー
E45: =ROW()-3 -> 42 | H45: ボタン選択 | I45: 【呼出取消】をタッチ。 | J45: 【PS】 以下画面が表示されていること。 タイトルー「ポイントカードはお持ちですか？」 文言ー「残りお支払金額」 「はい」「いいえ」 音声ー「ポイントカードはお持ちですか？」 | K45: □ | L45: ー | M45: ー | N45: □ | O45: ー | P45: ー | Q45: □ | R45: ー | S45: ー
E46: =ROW()-3 -> 43 | H46: ボタン選択 | I46: 【言語切替】⇒【English】をタッチ。 | J46: 【PS】 以下画面が表示されていること。 タイトルー「Payment machine」 文言ー「Waiting」 その後、【日本語】をタッチ。 | K46: □ | L46: ー | M46: ー | N46: □ | O46: ー | P46: ー | Q46: ー | R46: ー | S46: ー
E47: =ROW()-3 -> 44 | H47: PS画面の確認 | I47: タイトルー「お支払い」の画面で、 ご精算券のQRコードをスキャン。 | J47: 【PS】 以下画面が表示されていること。 タイトルー「ポイントカードはお持ちですか？」 文言ー「残りお支払金額」 「はい」「いいえ」 音声ー「ポイントカードはお持ちですか？」 | K47: □ | L47: ー | M47: ー | N47: □ | O47: ー | P47: ー | Q47: □ | R47: ー | S47: ー
E48: =ROW()-3 -> 45 | H48: ボタン選択 | I48: タイトルー「お支払方法を選んでください」の画面で、 【係員呼出】をタッチ | J48: 【PS】 以下画面が表示されていること。 タイトルー「しばらくお待ちください」 文言ー「まもなく、係員がまいります」 音声ー「まもなく係員がまいります。しばらくお待ちください」 | K48: □ | L48: ー | M48: ー | N48: □ | O48: ー | P48: ー | Q48: □ | R48: ー | S48: ー
E49: =ROW()-3 -> 46 | H49: ボタン選択 | I49: 【呼出取消】をタッチ。 | J49: 【PS】 以下画面が表示されていること。 タイトルー「ポイントカードはお持ちですか？」 文言ー「残りお支払金額」 「はい」「いいえ」 音声ー「ポイントカードはお持ちですか？」 | K49: □ | L49: ー | M49: ー | N49: □ | O49: ー | P49: ー | Q49: □ | R49: ー | S49: ー
E50: =ROW()-3 -> 47 | H50: PS画面の確認 | I50: 「ポイントカードはお持ちですか？」画面で【いいえ】選択 ⇒「お支払方法を選んでください」画面で【現金】を選択。 | J50: 【PS】 タイトルー「現金を入れてください」 音声ー「現金を入れてください」 | K50: □ | L50: ー | M50: ー | N50: □ | O50: ー | P50: ー | Q50: □ | R50: ー | S50: ー
E51: =ROW()-3 -> 48 | H51: PS画面の確認 | J51: 【PS】 タイトルー「現金を入れてください」 項目ー「商品券等の支払金額」にSSで登録した商品券の額が表示されていること。 | K51: □ | L51: ー | M51: ー | N51: □ | O51: ー | P51: ー | Q51: ー | R51: ー | S51: ー
E52: =ROW()-3 -> 49 | H52: PS画面の確認 | I52: 現金を投入。 | J52: 【PS】 以下画面に表示変更されること。 タイトルー「お支払額がよろしければ「レシート」 または「領収証」を押してください」 音声ー「お支払額がよろしければ「レシート」または 「領収証」を押してください」 | K52: □ | L52: ー | M52: ー | N52: □ | O52: ー | P52: ー | Q52: □ | R52: ー | S52: ー
E53: =ROW()-3 -> 50 | H53: ボタン選択 | I53: タイトルー「お支払額がよろしければ「レシート」または「領収証」を押してください」画面で、 【レシート】をタッチ 支払額一致：お釣りなし | J53: 【PS】 「お買上げありがとうございます」画面に遷移し、 レシートが排出されること。 音声ー「ありがとうございます。レシートをお取りください」 | K53: □ | L53: ー | M53: ー | N53: □ | O53: □ | P53: □ | Q53: □ | R53: ー | S53: ー
E54: =ROW()-3 -> 51 | H54: ボタン選択 | I54: タイトルー「お支払額がよろしければ確認を選んでください」画面で、 【レシート】をタッチ 支払額超過：お釣りあり | J54: 【PS】 「お買上げありがとうございます」画面に遷移し、 レシート・お釣りが排出されること。 音声ー「おつりがあります。お取り忘れにご注意ください」 | K54: □ | L54: ー | M54: ー | N54: □ | O54: □ | P54: □ | Q54: □ | R54: ー | S54: ー
E55: =ROW()-3 -> 52 | H55: PS画面の確認 | I55: タイトルー「お買上げありがとうございます」の画面で、 排出されたお釣りを受取る | J55: 【PS】 「お買上げありがとうございます」画面に遷移すること。 音声ー「ありがとうございます。レシートをお取りください」 | K55: □ | L55: ー | M55: ー | N55: □ | O55: ー | P55: ー | Q55: □ | R55: ー | S55: ー
D56: 【PS操作】 支払ークレジット | E56: =ROW()-3 -> 53 | F56: 商品登録 →小計 →ingfanカード 確認ポップアップ →「PSへ」を選択 | G56: 預合計 →商品券登録 ★ →PS指定（ボタンタッチ） | H56: PS画面の確認 | J56: 【PS】 以下画面が表示されていること。 タイトルー「ポイントカードはお持ちですか？」 文言ー「残りお支払金額」 「はい」「いいえ」 音声ー「ポイントカードはお持ちですか？」 | K56: □ | L56: ー | M56: ー | N56: □ | O56: ー | P56: ー | Q56: □ | R56: ー | S56: ー
E57: =ROW()-3 -> 54 | H57: ボタン選択 | I57: 【係員呼出】をタッチ。 | J57: 【PS】 以下画面が表示されていること。 タイトルー「しばらくお待ちください」 文言ー「まもなく、係員がまいります」 音声ー「まもなく係員がまいります。しばらくお待ちください」 | K57: □ | L57: ー | M57: ー | N57: □ | O57: ー | P57: ー | Q57: □ | R57: ー | S57: ー
E58: =ROW()-3 -> 55 | H58: ボタン選択 | I58: 【呼出取消】をタッチ。 | J58: 【PS】 以下画面が表示されていること。 タイトルー「ポイントカードはお持ちですか？」 文言ー「残りお支払金額」 「はい」「いいえ」 音声ー「ポイントカードはお持ちですか？」 | K58: □ | L58: ー | M58: ー | N58: □ | O58: ー | P58: ー | Q58: □ | R58: ー | S58: ー
E59: =ROW()-3 -> 56 | H59: PS画面の確認 | I59: 「ポイントカードはお持ちですか？」画面で【いいえ】選択 ⇒「お支払方法を選んでください」画面で【クレジット】を選択。 | J59: 【PS】 タイトルー「決済端末で操作してください」 音声ー「決済端末で操作してください」 | K59: □ | L59: ー | M59: ー | N59: □ | O59: ー | P59: ー | Q59: □ | R59: ー | S59: ー
E60: =ROW()-3 -> 57 | H60: PS画面の確認 | J60: 【PS】 タイトルー「決済端末で操作してください」 項目ー「商品券等の支払金額」にSSで登録した商品券の額が表示されていること。 | K60: □ | L60: ー | M60: ー | N60: □ | O60: ー | P60: ー | Q60: □ | R60: ー | S60: ー
E61: =ROW()-3 -> 58 | H61: PS画面の確認 | I61: クレジットカードを挿入後、 決済端末で「ICカードをお取りください」表示後にカードを抜き取り。 | J61: 【PS】 以下画面に表示変更されること。 タイトルー「お支払額がよろしければ「レシート」 または「領収証」を押してください」 音声ー「お支払額がよろしければ「レシート」または 「領収証」を押してください」 | K61: □ | L61: ー | M61: ー | N61: □ | O61: ー | P61: ー | Q61: □ | R61: ー | S61: ー
E62: =ROW()-3 -> 59 | H62: ボタン選択 | I62: タイトルー「お支払額がよろしければ「レシート」または「領収証」を押してください」画面で、 【レシート】をタッチ | J62: 【PS】 「お買上げありがとうございます」画面に遷移し、 レシートが排出されること。 音声ー「ありがとうございます。レシートをお取りください」 | K62: □ | L62: ー | M62: ー | N62: □ | O62: □ | P62: □ | Q62: □ | R62: ー | S62: ー
B63: 【SS操作】 会員宣言ー有り （クラブカード) | C63: 【SS操作】 商品券ー無し | D63: 【PS操作】 支払ー現金 | E63: =ROW()-3 -> 60 | F63: 商品登録 →小計 →ingfanカード 確認ポップアップ →ingfanカードスキャン | G63: 預合計 →PS指定（ボタンタッチ） | H63: PS画面の確認 | J63: 【PS】 以下画面が表示されていること。 タイトルー「お支払方法を選んでください」 文言ー「残りお支払金額」 音声ー「お支払方法を選んでください」 | K63: □ | L63: ー | M63: ー | N63: □ | O63: ー | P63: ー | Q63: □ | R63: ー | S63: ー
E64: =ROW()-3 -> 61 | H64: ボタン選択 | I64: 【係員呼出】をタッチ。 | J64: 【PS】 以下画面が表示されていること。 タイトルー「しばらくお待ちください」 文言ー「まもなく、係員がまいります」 音声ー「まもなく係員がまいります。しばらくお待ちください」 | K64: □ | L64: ー | M64: ー | N64: □ | O64: ー | P64: ー | Q64: □ | R64: ー | S64: ー
E65: =ROW()-3 -> 62 | H65: ボタン選択 | I65: 【呼出取消】をタッチ。 | J65: 【PS】 以下画面が表示されていること。 タイトルー「お支払方法を選んでください」 文言ー「残りお支払金額」 音声ー「お支払方法を選んでください」 | K65: □ | L65: ー | M65: ー | N65: □ | O65: ー | P65: ー | Q65: □ | R65: ー | S65: ー
E66: =ROW()-3 -> 63 | H66: PS画面の確認 | I66: 「お支払方法を選んでください」画面で【現金】を選択。 | J66: 【PS】 タイトルー「現金を入れてください」 音声ー「現金を入れてください」 | K66: □ | L66: ー | M66: ー | N66: □ | O66: ー | P66: ー | Q66: □ | R66: ー | S66: ー
E67: =ROW()-3 -> 64 | H67: PS画面の確認 | I67: 現金を投入。 | J67: 【PS】 以下画面に表示変更されること。 タイトルー「お支払額がよろしければ「レシート」 または「領収証」を押してください」 音声ー「お支払額がよろしければ「レシート」または 「領収証」を押してください」 | K67: □ | L67: ー | M67: ー | N67: □ | O67: ー | P67: ー | Q67: □ | R67: ー | S67: ー
E68: =ROW()-3 -> 65 | H68: ボタン選択 | I68: タイトルー「お支払額がよろしければ「レシート」または「領収証」を押してください」画面で、 【レシート】をタッチ 支払額一致：お釣りなし | J68: 【PS】 「お買上げありがとうございます」画面に遷移し、 レシートが排出されること。 音声ー「ありがとうございます。レシートをお取りください」 | K68: □ | L68: ー | M68: ー | N68: □ | O68: □ | P68: □ | Q68: □ | R68: ー | S68: ー
E69: =ROW()-3 -> 66 | H69: ボタン選択 | I69: タイトルー「お支払額がよろしければ「レシート」または「領収証」を押してください」画面で、 【レシート】をタッチ 支払額超過：お釣りあり | J69: 【PS】 「お買上げありがとうございます」画面に遷移し、 レシート・お釣りが排出されること。 音声ー「おつりがあります。お取り忘れにご注意ください」 | K69: □ | L69: ー | M69: ー | N69: □ | O69: □ | P69: □ | Q69: □ | R69: ー | S69: ー
E70: =ROW()-3 -> 67 | H70: PS画面の確認 | I70: タイトルー「お買上げありがとうございます」の画面で、 排出されたお釣りを受取る | J70: 【PS】 「お買上げありがとうございます」画面に遷移すること。 音声ー「ありがとうございます。レシートをお取りください」 | K70: □ | L70: ー | M70: ー | N70: □ | O70: ー | P70: ー | Q70: □ | R70: ー | S70: ー
D71: 【PS操作】 支払ークレジット | E71: =ROW()-3 -> 68 | F71: 商品登録 →小計 →ingfanカード 確認ポップアップ →ingfanカードスキャン | G71: 預合計 →PS指定（ボタンタッチ） | H71: PS画面の確認 | J71: 【PS】 以下画面が表示されていること。 タイトルー「お支払方法を選んでください」 文言ー「残りお支払金額」 音声ー「お支払方法を選んでください」 | K71: □ | L71: ー | M71: ー | N71: □ | O71: ー | P71: ー | Q71: □ | R71: ー | S71: ー
E72: =ROW()-3 -> 69 | H72: ボタン選択 | I72: 【係員呼出】をタッチ。 | J72: 【PS】 以下画面が表示されていること。 タイトルー「しばらくお待ちください」 文言ー「まもなく、係員がまいります」 音声ー「まもなく係員がまいります。しばらくお待ちください」 | K72: □ | L72: ー | M72: ー | N72: □ | O72: ー | P72: ー | Q72: □ | R72: ー | S72: ー
E73: =ROW()-3 -> 70 | H73: ボタン選択 | I73: 【呼出取消】をタッチ。 | J73: 【PS】 以下画面が表示されていること。 タイトルー「お支払方法を選んでください」 文言ー「残りお支払金額」 音声ー「お支払方法を選んでください」 | K73: □ | L73: ー | M73: ー | N73: □ | O73: ー | P73: ー | Q73: □ | R73: ー | S73: ー
E74: =ROW()-3 -> 71 | H74: PS画面の確認 | I74: 「お支払方法を選んでください」画面で【クレジット】を選択。 | J74: 【PS】 タイトルー「決済端末で操作してください」 音声ー「決済端末で操作してください」 | K74: □ | L74: ー | M74: ー | N74: □ | O74: ー | P74: ー | Q74: □ | R74: ー | S74: ー
E75: =ROW()-3 -> 72 | H75: PS画面の確認 | I75: クレジットカードを挿入後、 決済端末で「ICカードをお取りください」表示後にカードを抜き取り。 | J75: 【PS】 以下画面に表示変更されること。 タイトルー「お支払額がよろしければ「レシート」 または「領収証」を押してください」 音声ー「お支払額がよろしければ「レシート」または 「領収証」を押してください」 | K75: □ | L75: ー | M75: ー | N75: □ | O75: ー | P75: ー | Q75: □ | R75: ー | S75: ー
E76: =ROW()-3 -> 73 | H76: ボタン選択 | I76: タイトルー「お支払額がよろしければ「レシート」または「領収証」を押してください」画面で、 【レシート】をタッチ | J76: 【PS】 「お買上げありがとうございます」画面に遷移し、 レシートが排出されること。 音声ー「ありがとうございます。レシートをお取りください」 | K76: □ | L76: ー | M76: ー | N76: □ | O76: □ | P76: □ | Q76: □ | R76: ー | S76: ー
C77: 【SS操作】 商品券ーあり | D77: 【PS操作】 支払ー現金 | E77: =ROW()-3 -> 74 | F77: 商品登録 →小計 →ingfanカード 確認ポップアップ →ingfanカードスキャン | G77: 預合計 →商品券登録 ★ →PS指定（ボタンタッチ） | H77: PS画面の確認 | J77: 【PS】 以下画面が表示されていること。 タイトルー「お支払方法を選んでください」 文言ー「残りお支払金額」 音声ー「お支払方法を選んでください」 | K77: □ | L77: ー | M77: ー | N77: □ | O77: ー | P77: ー | Q77: □ | R77: ー | S77: ー
E78: =ROW()-3 -> 75 | H78: ボタン選択 | I78: 【係員呼出】をタッチ。 | J78: 【PS】 以下画面が表示されていること。 タイトルー「しばらくお待ちください」 文言ー「まもなく、係員がまいります」 音声ー「まもなく係員がまいります。しばらくお待ちください」 | K78: □ | L78: ー | M78: ー | N78: □ | O78: ー | P78: ー | Q78: □ | R78: ー | S78: ー
E79: =ROW()-3 -> 76 | H79: ボタン選択 | I79: 【呼出取消】をタッチ。 | J79: 【PS】 以下画面が表示されていること。 タイトルー「お支払方法を選んでください」 文言ー「残りお支払金額」 音声ー「お支払方法を選んでください」 | K79: □ | L79: ー | M79: ー | N79: □ | O79: ー | P79: ー | Q79: □ | R79: ー | S79: ー
E80: =ROW()-3 -> 77 | H80: PS画面の確認 | I80: 「お支払方法を選んでください」画面で【現金】を選択。 | J80: 【PS】 タイトルー「現金を入れてください」 音声ー「現金を入れてください」 | K80: □ | L80: ー | M80: ー | N80: □ | O80: ー | P80: ー | Q80: □ | R80: ー | S80: ー
E81: =ROW()-3 -> 78 | H81: PS画面の確認 | J81: 【PS】 タイトルー「現金を入れてください」 項目ー「商品券等の支払金額」にSSで登録した商品券の額が表示されていること。 | K81: □ | L81: ー | M81: ー | N81: □ | O81: ー | P81: ー | Q81: □ | R81: ー | S81: ー
E82: =ROW()-3 -> 79 | H82: PS画面の確認 | I82: 現金を投入。 | J82: 【PS】 以下画面に表示変更されること。 タイトルー「お支払額がよろしければ「レシート」 または「領収証」を押してください」 音声ー「お支払額がよろしければ「レシート」または 「領収証」を押してください」 | K82: □ | L82: ー | M82: ー | N82: □ | O82: ー | P82: ー | Q82: □ | R82: ー | S82: ー
E83: =ROW()-3 -> 80 | H83: ボタン選択 | I83: タイトルー「お支払額がよろしければ「レシート」または「領収証」を押してください」画面で、 【レシート】をタッチ 支払額一致：お釣りなし | J83: 【PS】 「お買上げありがとうございます」画面に遷移し、 レシートが排出されること。 音声ー「ありがとうございます。レシートをお取りください」 | K83: □ | L83: ー | M83: ー | N83: □ | O83: □ | P83: □ | Q83: □ | R83: ー | S83: ー
E84: =ROW()-3 -> 81 | H84: ボタン選択 | I84: タイトルー「お支払額がよろしければ「レシート」または「領収証」を押してください」画面で、 【レシート】をタッチ 支払額超過：お釣りあり | J84: 【PS】 「お買上げありがとうございます」画面に遷移し、 レシート・お釣りが排出されること。 音声ー「おつりがあります。お取り忘れにご注意ください」 | K84: □ | L84: ー | M84: ー | N84: □ | O84: □ | P84: □ | Q84: □ | R84: ー | S84: ー
E85: =ROW()-3 -> 82 | H85: PS画面の確認 | I85: タイトルー「お買上げありがとうございます」の画面で、 排出されたお釣りを受取る | J85: 【PS】 「お買上げありがとうございます」画面に遷移すること。 音声ー「ありがとうございます。レシートをお取りください」 | K85: □ | L85: ー | M85: ー | N85: □ | O85: ー | P85: ー | Q85: □ | R85: ー | S85: ー
D86: 【PS操作】 支払ークレジット | E86: =ROW()-3 -> 83 | F86: 商品登録 →小計 →ingfanカード 確認ポップアップ →ingfanカードスキャン | G86: 預合計 →商品券登録 ★ →PS指定（ボタンタッチ） | H86: PS画面の確認 | J86: 【PS】 以下画面が表示されていること。 タイトルー「お支払方法を選んでください」 文言ー「残りお支払金額」 音声ー「お支払方法を選んでください」 | K86: □ | L86: ー | M86: ー | N86: □ | O86: ー | P86: ー | Q86: □ | R86: ー | S86: ー
E87: =ROW()-3 -> 84 | H87: ボタン選択 | I87: 【係員呼出】をタッチ。 | J87: 【PS】 以下画面が表示されていること。 タイトルー「しばらくお待ちください」 文言ー「まもなく、係員がまいります」 音声ー「まもなく係員がまいります。しばらくお待ちください」 | K87: □ | L87: ー | M87: ー | N87: □ | O87: ー | P87: ー | Q87: □ | R87: ー | S87: ー
E88: =ROW()-3 -> 85 | H88: ボタン選択 | I88: 【呼出取消】をタッチ。 | J88: 【PS】 以下画面が表示されていること。 タイトルー「お支払方法を選んでください」 文言ー「残りお支払金額」 音声ー「お支払方法を選んでください」 | K88: □ | L88: ー | M88: ー | N88: □ | O88: ー | P88: ー | Q88: □ | R88: ー | S88: ー
E89: =ROW()-3 -> 86 | H89: PS画面の確認 | I89: 「お支払方法を選んでください」画面で【クレジット】を選択。 | J89: 【PS】 タイトルー「決済端末で操作してください」 音声ー「決済端末で操作してください」 | K89: □ | L89: ー | M89: ー | N89: □ | O89: ー | P89: ー | Q89: □ | R89: ー | S89: ー
E90: =ROW()-3 -> 87 | H90: PS画面の確認 | J90: 【PS】 タイトルー「決済端末で操作してください」 項目ー「商品券等の支払金額」にSSで登録した商品券の額が表示されていること。 | K90: □ | L90: ー | M90: ー | N90: □ | O90: ー | P90: ー | Q90: □ | R90: ー | S90: ー
E91: =ROW()-3 -> 88 | H91: PS画面の確認 | I91: クレジットカードを挿入後、 決済端末で「ICカードをお取りください」表示後にカードを抜き取り。 | J91: 【PS】 以下画面に表示変更されること。 タイトルー「お支払額がよろしければ「レシート」 または「領収証」を押してください」 音声ー「お支払額がよろしければ「レシート」または 「領収証」を押してください」 | K91: □ | L91: ー | M91: ー | N91: □ | O91: ー | P91: ー | Q91: □ | R91: ー | S91: ー
E92: =ROW()-3 -> 89 | H92: ボタン選択 | I92: タイトルー「お支払額がよろしければ「レシート」または「領収証」を押してください」画面で、 【レシート】をタッチ | J92: 【PS】 「お買上げありがとうございます」画面に遷移し、 レシートが排出されること。 音声ー「ありがとうございます。レシートをお取りください」 | K92: □ | L92: ー | M92: ー | N92: □ | O92: □ | P92: □ | Q92: □ | R92: ー | S92: ー
B93: 【SS操作】 会員宣言ー有り （Vカード） | C93: 【SS操作】 商品券ー無し | D93: 【PS操作】 支払ー現金 | E93: =ROW()-3 -> 90 | F93: 商品登録 →小計 →ingfanカード 確認ポップアップ →Vカード挿入 | G93: 預合計 →PS指定（ボタンタッチ） | H93: PS画面の確認 | J93: 【PS】 以下画面が表示されていること。 タイトルー「お支払方法を選んでください」 文言ー「残りお支払金額」 音声ー「お支払方法を選んでください」 | K93: □ | L93: ー | M93: ー | N93: □ | O93: ー | P93: ー | Q93: □ | R93: ー | S93: ー
E94: =ROW()-3 -> 91 | H94: ボタン選択 | I94: 【係員呼出】をタッチ。 | J94: 【PS】 以下画面が表示されていること。 タイトルー「しばらくお待ちください」 文言ー「まもなく、係員がまいります」 音声ー「まもなく係員がまいります。しばらくお待ちください」 | K94: □ | L94: ー | M94: ー | N94: □ | O94: ー | P94: ー | Q94: □ | R94: ー | S94: ー
E95: =ROW()-3 -> 92 | H95: ボタン選択 | I95: 【呼出取消】をタッチ。 | J95: 【PS】 以下画面が表示されていること。 タイトルー「お支払方法を選んでください」 文言ー「残りお支払金額」 音声ー「お支払方法を選んでください」 | K95: □ | L95: ー | M95: ー | N95: □ | O95: ー | P95: ー | Q95: □ | R95: ー | S95: ー
E96: =ROW()-3 -> 93 | H96: PS画面の確認 | I96: 「お支払方法を選んでください」画面で【現金】を選択。 | J96: 【PS】 タイトルー「現金を入れてください」 音声ー「現金を入れてください」 | K96: □ | L96: ー | M96: ー | N96: □ | O96: ー | P96: ー | Q96: □ | R96: ー | S96: ー
E97: =ROW()-3 -> 94 | H97: PS画面の確認 | I97: 現金を投入。 | J97: 【PS】 以下画面に表示変更されること。 タイトルー「お支払額がよろしければ「レシート」 または「領収証」を押してください」 音声ー「お支払額がよろしければ「レシート」または 「領収証」を押してください」 | K97: □ | L97: ー | M97: ー | N97: □ | O97: ー | P97: ー | Q97: □ | R97: ー | S97: ー
E98: =ROW()-3 -> 95 | H98: ボタン選択 | I98: タイトルー「お支払額がよろしければ「レシート」または「領収証」を押してください」画面で、 【レシート】をタッチ 支払額一致：お釣りなし | J98: 【PS】 「お買上げありがとうございます」画面に遷移し、 レシートが排出されること。 音声ー「ありがとうございます。レシートをお取りください」 | K98: □ | L98: ー | M98: ー | N98: □ | O98: □ | P98: □ | Q98: □ | R98: ー | S98: ー
E99: =ROW()-3 -> 96 | H99: ボタン選択 | I99: タイトルー「お支払額がよろしければ「レシート」または「領収証」を押してください」画面で、 【レシート】をタッチ 支払額超過：お釣りあり | J99: 【PS】 「お買上げありがとうございます」画面に遷移し、 レシート・お釣りが排出されること。 音声ー「おつりがあります。お取り忘れにご注意ください」 | K99: □ | L99: ー | M99: ー | N99: □ | O99: □ | P99: □ | Q99: □ | R99: ー | S99: ー
E100: =ROW()-3 -> 97 | H100: PS画面の確認 | I100: タイトルー「お買上げありがとうございます」の画面で、 排出されたお釣りを受取る | J100: 【PS】 「お買上げありがとうございます」画面に遷移すること。 音声ー「ありがとうございます。レシートをお取りください」 | K100: □ | L100: ー | M100: ー | N100: □ | O100: ー | P100: ー | Q100: □ | R100: ー | S100: ー
...
